Workbook

Sheet Main
A1: Tech | I1: Capital Structure = relative proportions of debt, equity, and other securities that a firm has outstanding
B2: BBAI | E2: AAPL | H2: AMZN | K2: IBM | N2: ALRM | Q2: T | U2: AFRM
B4: P | C4: 7.29 | E4: P | F4: 273.94 | G4: 46058 | H4: P | I4: 246.21 | K4: P | L4: 287 | N4: P | O4: 52.3 | Q4: P | R4: 27.06 | U4: P | V4: 78.18 | W4: Q3FY25
B5: S/O | C5: 252.3414 | E5: S/O | F5: =AAPL!O18 -> 14748.158 | G5: Q126 | H5: S/O | I5: =AMZN!M32 -> 10674 | J5: Q225 | K5: S/O | L5: 927.26 | M5: Q125 | N5: S/O | O5: 49.646 | P5: Q125 | Q5: S/O | R5: 7178.183 | S5: Q125 | U5: S/O | V5: 324.05397
B6: MC | C6: =C5*C4 -> 1839.5688 | E6: MC | F6: =F5*F4 -> 4040110.4 | H6: MC | I6: =I5*I4 -> 2628045.5 | K6: MC | L6: =L5*L4 -> 266123.62 | N6: MC | O6: =O5*O4 -> 2596.4858 | Q6: MC | R6: =R5*R4 -> 194241.63 | U6: MC | V6: 25292.412
B7: Cash | C7: 107.61 | E7: Cash | F7: =+AAPL!O68 -> 144795 | G7: Q126 | H7: Cash | I7: =AMZN!M50+AMZN!M51 -> 94197 | J7: Q225 | K7: Cash | L7: =13947+644 -> 14591 | M7: Q125 | N7: Cash | O7: 1220.701 | P7: Q125 | Q7: Cash | R7: =3298+295 -> 3593 | S7: Q125 | U7: Cash | V7: 2131.318 | W7: Q3FY25
B8: Debt | C8: =0.818+100.588 -> 101.406 | E8: Debt | F8: =+AAPL!O79 -> 90509 | G8: Q126 | H8: Debt | I8: =AMZN!M63 -> 50742 | J8: Q225 | K8: Debt (+Lease) | L8: =49884+5089+2655+768 -> 58396 | M8: Q125 | N8: Debt (+Lease) | O8: =983.477+65.534+7.7 -> 1056.711 | P8: Q125 | Q8: Debt (+Lease) | R8: =5089+118443+17391 -> 140923 | S8: Q125 | U8: Debt | V8: 7322.642 | W8: Q3FY25
B10: EV | C10: =C6-C7+C8 -> 1833.3648 | E10: EV | F10: =F6-F7+F8 -> 3985824.4 | H10: EV | I10: =I6-I7+I8 -> 2584590.5 | K10: EV | L10: =L6-L7+L8 -> 309928.62 | N10: EV | O10: =O6-O7+O8 -> 2432.4958 | Q10: EV | R10: =R6-R7+R8 -> 331571.63 | U10: EV | V10: 30483.736
E11: EV/P | F11: =F10/AAPL!V17 -> 35.584541 | H11: EV/P | I11: =I10/AMZN!AA31 -> 34.288394
B13: MSFT | E13: META | H13: GOOGL | K13: BIDU | N13: GTLB | Q13: BABA
B15: P | C15: 525.99 | E15: P | F15: 667.1 | G15: 46058 | H15: P | I15: 331.71 | J15: 46058 | K15: P | L15: 141.31 | N15: P | O15: 46.95 | Q15: P | R15: 190.08
B16: S/O | C16: =+MSFT!AQ42 -> 7434 | D16: Q126 | E16: S/O | F16: =+META!N20 -> 2525 | G16: Q126 | H16: S/O | I16: =+GOOGL!N15 -> 12073 | J16: Q425 | K16: S/O | L16: 344 | N16: S/O | O16: =144.6+19.4 -> 164 | Q16: S/O | R16: 2311 | S16: Q425
B17: MC | C17: =C16*C15 -> 3910209.7 | E17: MC | F17: =F16*F15 -> 1684427.5 | H17: MC | I17: =I16*I15 -> 4004734.8 | K17: MC | L17: =L16*L15 -> 48610.64 | N17: MC | O17: =O16*O15 -> 7699.8 | Q17: MC | R17: =R16*R15 -> 439274.88
B18: Cash | C18: =+MSFT!AQ64 -> 113477 | D18: Q126 | E18: Cash | F18: =+META!N34 -> 109116 | G18: Q126 | H18: Cash | I18: =+GOOGL!N35 -> 195530 | J18: Q425 | K18: Cash | L18: =BIDU!K38 -> 36674 | N18: Cash | O18: =764.728+264.565 -> 1029.293 | Q18: Cash | R18: 51582 | S18: Q425
B19: Debt | C19: =+MSFT!AQ75 -> 43208 | D19: Q126 | E19: Debt | F19: =+META!N45 -> 58744 | G19: Q126 | H19: Debt | I19: =+GOOGL!N49 -> 46547 | J19: Q425 | K19: Debt | L19: =BIDU!K50+BIDU!K53+BIDU!K54 -> 10868 | N19: Debt | O19: 0 | Q19: Debt | R19: 31792 | S19: Q425
B21: EV | C21: =C17-C18+C19 -> 3839940.7 | E21: EV | F21: =F17-F18+F19 -> 1634055.5 | H21: EV | I21: =I17-I18+I19 -> 3855751.8 | K21: EV | L21: =L17-L18+L19 -> 22804.64 | N21: EV | O21: =O17-O18+O19 -> 6670.507 | Q21: EV | R21: =R17-R18+R19 -> 419484.88
B22: EV/P | C22: =C21/MSFT!BE41 -> 37.708585 | E22: EV/P | F22: =F21/META!W19 -> 27.023922 | H22: EV/P | I22: =I21/GOOGL!AA14 -> 29.17267 | L22: 3600 | Q22: EV/P | R22: =+R21/15234 -> 27.536096
L23: =L21/L22 -> 6.3346222
B25: Discount rate = Risk free rate (Estimated Inflation / US Government Bond) + Risk Premium (Opportunity Cost / Risk)
B26: A Company is worth the discounted sum of its cash flows from today until eternity.
C29: Buy/Price | D29: Sell/Price | E29: Years | F29: Cash return | G29: IRR - Internal rate of return.
B30: Short-Term | C30: 10 | D30: 12 | E30: 0.04 | F30: =D30/C30-1 -> 0.2 | G30: =RATE(E30,0,-C30,D30) -> 94.396217 | H30: =_xlfn.FORMULATEXT(G30) -> =RATE(E30,0,-C30,D30)
B31: Long-Term | C31: 10 | D31: 20 | E31: 2 | F31: =D31/C31-1 -> 1 | G31: =RATE(E31,0,-C31,D31) -> 0.41421356
B35: Discounting fast growing company. 1:40:00 - Facebook
B36: https://www.youtube.com/watch?v=gsrEfnsUXOE
D40: Warren Buffet's Financial Statements Rules of Thumb
D41: METRIC | F41: EQUATION | H41: THRESHOLD
B42: INCOME STATEMENT | D42: Gross Margin | F42: Gross Profit Revenue | H42: >40%
D44: SG&A Margin | F44: SG&A Gross Profit | H44: <30%
D46: R&D Margin | F46: R&D Gross Profit | H46: <30%
D48: Depreciation Margin | F48: Depreciation Gross Profit | H48: <10%
D50: Interest Margin | F50: Interest Operating Income | H50: <15%
D52: Tax Margin | F52: Taxes Pre-Tax Income | H52: Corporate Tax Rate
D54: Net Income Margin | F54: Net Income Revenue | H54: >20%
D56: EPS Growth | F56: Year 2 EPS Year 1 EPS | H56: Positive & Growing
B58: BALANCE SHEET | D58: Cash & Debt | F58: Cash > Debt | H58: Cash>Debt
D59: Adjusted Debt to Equity | F59: Total Liabilities Shareholder Equity + Treasury Stock | H59: Below 0.80
D62: Preferred Stock | F62: NONE | H62: NONE
D63: Retained Earnings | F63: Yr 2 Retained Earnings Yr 1 Retained Earnings | H63: Consistent Growth
D65: Treasury Stock | F65: Treasury Stock > 1 | H65: Exists
B66: CASH FLOW STATEMENT | D66: Capex Margin | F66: Capex Net Income | H66: <25%

Sheet GOOGL
A1: Main
C2: Q123 | D2: Q223 | E2: Q323 | F2: Q423 | G2: Q124 | H2: Q224 | I2: Q324 | J2: Q424 | K2: Q125 | L2: Q225 | M2: Q325 | N2: Q425 | O2: Q126 | P2: Q226 | Q2: Q326 | R2: Q426 | S2: Q127 | T2: Q227 | U2: Q327 | V2: Q427 | X2: 2022 | Y2: 2023 | Z2: 2024 | AA2: 2025 | AB2: 2026 | AC2: 2027 | AD2: 2028 | AE2: 2029 | AF2: 2030 | AG2: 2031 | AH2: 2032 | AI2: 2033 | AJ2: 2034 | AK2: 2035 | AL2: 2036 | AM2: 2037 | AN2: 2038 | AO2: 2039 | AP2: 2040 | AQ2: 2041 | AR2: 2042 | AS2: 2043 | AT2: 2044 | AU2: 2045 | AV2: =+AU2+1 -> 2046 | AW2: =+AV2+1 -> 2047 | AX2: =+AW2+1 -> 2048 | AY2: =+AX2+1 -> 2049 | AZ2: =+AY2+1 -> 2050 | BA2: =+AZ2+1 -> 2051 | BB2: =+BA2+1 -> 2052 | BC2: =+BB2+1 -> 2053 | ... YT2: =+YS2+1 -> 2668
B3: Revenue | C3: 69787 | D3: 74604 | E3: 76693 | F3: 86310 | G3: 80539 | H3: 84742 | I3: 88268 | J3: 96469 | K3: 90234 | L3: 96428 | M3: 102346 | N3: 113828 | O3: 100950 | P3: 107080 | Q3: 110600 | R3: 120480 | S3: 105010 | T3: 109580 | U3: =Q3*(1+0.1) -> 121660 | V3: =R3*(1+0.1) -> 132528 | X3: 282836 | Y3: 307394 | Z3: 350018 | AA3: =SUM(K3:N3) -> 402836 | AB3: =SUM(O3:R3) -> 439110 | AC3: =SUM(S3:V3) -> 468778 | AD3: =AC3*(1+AD188) -> 496136.27 | AE3: =AD3*(1+AE188) -> 530102.06 | AF3: =AE3*(1+AF188) -> 572389.21 | AG3: =AF3*(1+AG188) -> 599462.55 | AH3: =AG3*(1+AH188) -> 629634.62 | AI3: =AH3*(1+AI188) -> 663285.68 | AJ3: =AI3*(1+AJ188) -> 724766.26 | AK3: =AJ3*(1+AK188) -> 766755.24 | AL3: =AK3*1.02 -> 782090.34 | AM3: =AL3*1.02 -> 797732.15 | AN3: =AM3*1.02 -> 813686.79 | AO3: =AN3*1.02 -> 829960.53 | AP3: =AO3*1.02 -> 846559.74 | AQ3: =AP3*1.02 -> 863490.93 | AR3: =AQ3*1.02 -> 880760.75 | AS3: =AR3*1.02 -> 898375.97 | ... AU3: =AT3*1.02 -> 934670.36
B4: COGS | C4: 30612 | D4: 31916 | E4: 33229 | F4: 37575 | G4: 33712 | H4: 35507 | I4: 36474 | J4: 40613 | K4: 36361 | L4: 39039 | M4: 41369 | N4: 45766 | O4: =O3-O5 -> 40588.236 | P4: =P3-P5 -> 43052.88 | Q4: =Q3-Q5 -> 44468.141 | R4: =R3-R5 -> 48440.521 | S4: =S3-S5 -> 42220.611 | T4: =T3-T5 -> 44058.037 | U4: =U3-U5 -> 48914.956 | V4: =V3-V5 -> 53284.574 | X4: 126203 | Y4: 133332 | Z4: 146306 | AA4: =SUM(K4:N4) -> 162535 | AB4: =SUM(O4:R4) -> 176549.78 | AC4: =SUM(S4:V4) -> 188478.18
B5: Gross Profit | C5: =C3-C4 -> 39175 | D5: =D3-D4 -> 42688 | E5: =E3-E4 -> 43464 | F5: =F3-F4 -> 48735 | G5: =G3-G4 -> 46827 | H5: =H3-H4 -> 49235 | I5: =I3-I4 -> 51794 | J5: =J3-J4 -> 55856 | ... N5: =N3-N4 -> 68062 | O5: =O3*N20 -> 60361.764 | P5: =P3*O20 -> 64027.12 | Q5: =Q3*P20 -> 66131.859 | R5: =R3*Q20 -> 72039.479 | S5: =S3*R20 -> 62789.389 | T5: =T3*S20 -> 65521.963 | U5: =U3*T20 -> 72745.044 | V5: =V3*U20 -> 79243.426 | X5: =X3-X4 -> 156633 | Y5: =Y3-Y4 -> 174062 | Z5: =Z3-Z4 -> 203712 | AA5: =AA3-AA4 -> 240301 | AB5: =AB3-AB4 -> 262560.22 | AC5: =SUM(S5:V5) -> 280299.82
B6: R&D | C6: 11468 | D6: 10588 | E6: 11258 | F6: 12113 | G6: 11903 | H6: 11860 | I6: 12447 | J6: 13116 | K6: 13556 | L6: 13808 | M6: 15151 | N6: 18572 | O6: =O5*N25 -> 16470.845 | P6: =P5*O25 -> 17471.007 | Q6: =Q5*P25 -> 18045.325 | R6: =R5*Q25 -> 19657.33 | S6: =S5*R25 -> 17133.269 | T6: =T5*S25 -> 17878.903 | U6: =U5*T25 -> 19849.857 | V6: =V5*U25 -> 21623.063 | X6: 39500 | Y6: 45427 | Z6: 49326 | AA6: =SUM(K6:N6) -> 61087 | AB6: =SUM(O6:R6) -> 71644.507 | AC6: =SUM(S6:V6) -> 76485.092
B7: S&M | C7: 6533 | D7: 6781 | E7: 6884 | F7: 7719 | G7: 6426 | H7: 6792 | I7: 7227 | J7: 7363 | K7: 6172 | L7: 7101 | M7: 7205 | N7: 8215 | O7: =O5*N26 -> 7285.591 | P7: =P5*O26 -> 7727.9949 | Q7: =Q5*P26 -> 7982.0343 | R7: =R5*Q26 -> 8695.0768 | S7: =S5*R26 -> 7578.6024 | T7: =T5*S26 -> 7908.4206 | U7: =U5*T26 -> 8780.2377 | V7: =V5*U26 -> 9564.5845 | X7: 26567 | Y7: 27917 | Z7: 27808 | AA7: =SUM(K7:N7) -> 28693 | AB7: =SUM(O7:R7) -> 31690.697 | AC7: =SUM(S7:V7) -> 33831.845
B8: G&A | C8: 3759 | D8: 3481 | E8: 3979 | F8: 5206 | G8: 3026 | H8: 3158 | I8: 3599 | J8: 4405 | K8: 3539 | L8: 5209 | M8: 7393 | N8: 5341 | O8: =O5*N27 -> 4736.7427 | P8: =P5*O27 -> 5024.3726 | Q8: =Q5*P27 -> 5189.5368 | R8: =R5*Q27 -> 5653.123 | S8: =S5*R27 -> 4927.2447 | T8: =T5*S27 -> 5141.6767 | U8: =U5*T27 -> 5708.4905 | V8: =V5*U27 -> 6218.4353 | X8: 15724 | Y8: 16425 | Z8: 14188 | AA8: =SUM(K8:N8) -> 21482 | AB8: =SUM(O8:R8) -> 20603.775 | AC8: =SUM(S8:V8) -> 21995.847
B9: Operating expenses | C9: =SUM(C6:C8) -> 21760 | D9: =SUM(D6:D8) -> 20850 | E9: =SUM(E6:E8) -> 22121 | F9: =SUM(F6:F8) -> 25038 | G9: =SUM(G6:G8) -> 21355 | H9: =SUM(H6:H8) -> 21810 | I9: =SUM(I6:I8) -> 23273 | J9: =SUM(J6:J8) -> 24884 | ... V9: =SUM(V6:V8) -> 37406.083 | X9: =SUM(X6:X8) -> 81791 | Y9: =SUM(Y6:Y8) -> 89769 | Z9: =SUM(Z6:Z8) -> 91322 | AA9: =SUM(AA6:AA8) -> 111262 | AB9: =SUM(AB6:AB8) -> 123938.98 | AC9: =SUM(S9:V9) -> 132312.78
B10: Operating Income | C10: =C5-C9 -> 17415 | D10: =D5-D9 -> 21838 | E10: =E5-E9 -> 21343 | F10: =F5-F9 -> 23697 | G10: =G5-G9 -> 25472 | H10: =H5-H9 -> 27425 | I10: =I5-I9 -> 28521 | J10: =J5-J9 -> 30972 | ... V10: =V5-V9 -> 41837.344 | X10: =X5-X9 -> 74842 | Y10: =Y5-Y9 -> 84293 | Z10: =Z5-Z9 -> 112390 | AA10: =AA5-AA9 -> 129039 | AB10: =AB5-AB9 -> 138621.24 | AC10: =SUM(S10:V10) -> 147987.04
B11: Interest income | C11: 790 | D11: 65 | E11: -146 | F11: 715 | G11: 2843 | H11: 126 | I11: 3185 | J11: 1271 | K11: 11183 | L11: 2662 | M11: 12759 | N11: 3183 | O11: =O12-O10 -> 3444.668 | P11: =P12-P10 -> 3642.0378 | Q11: =Q12-Q10 -> 3326.0009 | R11: =R12-R10 -> 3664.8464 | S11: =S12-S10 -> 6042.4975 | T11: =T12-T10 -> 6804.628 | U11: =U12-U10 -> 3658.601 | V11: =V12-V10 -> 4031.3311 | X11: -3514 | Y11: 1424 | Z11: 7425 | AA11: =SUM(K11:N11) -> 29787 | AB11: =SUM(O11:R11) -> 14077.553 | AC11: =SUM(S11:V11) -> 20537.058
B12: Pre Tax Income | C12: =C10+C11 -> 18205 | D12: =D10+D11 -> 21903 | E12: =E10+E11 -> 21197 | F12: =F10+F11 -> 24412 | G12: =G10+G11 -> 28315 | H12: =H10+H11 -> 27551 | I12: =I10+I11 -> 31706 | J12: =J10+J11 -> 32243 | ... N12: =N10+N11 -> 39117 | O12: =O14/0.83 -> 35313.253 | P12: =P14/0.83 -> 37445.783 | Q12: =Q14/0.83 -> 38240.964 | R12: =R14/0.83 -> 41698.795 | S12: =S14/0.83 -> 39192.771 | T12: =T14/0.83 -> 41397.59 | U12: =U14/0.83 -> 42065.06 | V12: =V14/0.83 -> 45868.675 | X12: =X10+X11 -> 71328 | Y12: =Y10+Y11 -> 85717 | Z12: =Z10+Z11 -> 119815 | AA12: =AA10+AA11 -> 158826 | AB12: =AB10+AB11 -> 152698.8 | AC12: =SUM(S12:V12) -> 168524.1
B13: Taxes | C13: 3154 | D13: 3535 | E13: 1508 | F13: 3725 | G13: 4653 | H13: 3932 | I13: 5405 | J13: 5707 | K13: 7249 | L13: 5737 | M13: 9008 | N13: 4662 | O13: =O12*0.17 -> 6003.253 | P13: =P12*0.17 -> 6365.7831 | Q13: =Q12*0.17 -> 6500.9639 | R13: =R12*0.17 -> 7088.7952 | S13: =S12*0.17 -> 6662.7711 | T13: =T12*0.17 -> 7037.5904 | U13: =U12*0.17 -> 7151.0602 | V13: =V12*0.17 -> 7797.6747 | X13: 11356 | Y13: 11922 | Z13: 19697 | AA13: =SUM(K13:N13) -> 26656 | AB13: =SUM(O13:R13) -> 25958.795 | AC13: =SUM(S13:V13) -> 28649.096
B14: Net Income | C14: =C12-C13 -> 15051 | D14: =D12-D13 -> 18368 | E14: =E12-E13 -> 19689 | F14: =F12-F13 -> 20687 | G14: =G12-G13 -> 23662 | H14: =H12-H13 -> 23619 | I14: =I12-I13 -> 26301 | J14: =J12-J13 -> 26536 | ... N14: =N12-N13 -> 34455 | O14: 29310 | P14: 31080 | Q14: 31740 | R14: 34610 | S14: 32530 | T14: 34360 | U14: =Q14*1.1 -> 34914 | V14: =R14*1.1 -> 38071 | X14: =X12-X13 -> 59972 | Y14: =Y12-Y13 -> 73795 | Z14: =Z12-Z13 -> 100118 | AA14: =AA12-AA13 -> 132170 | AB14: =AB12-AB13 -> 126740 | AC14: =SUM(S14:V14) -> 139875 | AD14: =AD3*AC22 -> 148038.22 | AE14: =AE3*AD22 -> 158173.01 | AF14: =AF3*AE22 -> 170790.74 | AG14: =AG3*AF22 -> 178868.94 | AH14: =AH3*AG22 -> 187871.75 | AI14: =AI3*AH22 -> 197912.62 | AJ14: =AJ3*AI22 -> 216257.34 | AK14: =AK3*AJ22 -> 228786.1 | ... AU14: =AU3*AT22 -> 278888.98 | AV14: =AU14*(1+$AX$22) -> 276100.09 | AW14: =AV14*(1+$AX$22) -> 273339.08 | AX14: =AW14*(1+$AX$22) -> 270605.69 | AY14: =AX14*(1+$AX$22) -> 267899.64 | AZ14: =AY14*(1+$AX$22) -> 265220.64 | BA14: =AZ14*(1+$AX$22) -> 262568.43 | BB14: =BA14*(1+$AX$22) -> 259942.75 | BC14: =BB14*(1+$AX$22) -> 257343.32 | ... YT14: =YS14*(1+$AX$22) -> 532.30137
B15: SE | C15: 12781 | D15: 12668 | E15: 12541 | F15: 12488 | G15: 12415 | H15: 12343 | I15: 12264 | J15: 12228 | K15: =5820+856+5459 -> 12135 | L15: =5817+847+5430 -> 12094 | M15: =5818+5407+842 -> 12067 | N15: 12073 | X15: 12849 | Y15: 12460 | Z15: 12211 | AA15: =Z15*0.98 -> 11966.78 | AB15: =AA15*0.98 -> 11727.444 | AC15: =AB15*0.98 -> 11492.896 | AD15: =AC15*0.98 -> 11263.038 | AE15: =AD15*0.98 -> 11037.777 | AF15: =AE15*0.98 -> 10817.021 | AG15: =AF15*0.98 -> 10600.681 | AH15: =AG15*0.98 -> 10388.667 | ... AU15: =AT15*0.98 -> 7989.1177
B16: EPS | C16: =C14/C15 -> 1.1776074 | D16: =D14/D15 -> 1.4499526 | E16: =E14/E15 -> 1.5699705 | F16: =F14/F15 -> 1.6565503 | G16: =G14/G15 -> 1.9059203 | H16: =H14/H15 -> 1.9135542 | I16: =I14/I15 -> 2.1445695 | J16: =J14/J15 -> 2.1701014 | ... N16: =N14/N15 -> 2.8538888 | X16: =X14/X15 -> 4.6674449 | Y16: =Y14/Y15 -> 5.9225522 | Z16: =Z14/Z15 -> 8.1990009 | AA16: =AA14/AA15 -> 11.044742 | AB16: =AB14/AB15 -> 10.807129 | AC16: =AC14/AC15 -> 12.170562 | AD16: =AD14/AD15 -> 13.143721 | AE16: =AE14/AE15 -> 14.330151 | ... AU16: =AU14/AU15 -> 34.908608
B20: Gross Margin | C20: =C5/C3 -> 0.56135097 | D20: =D5/D3 -> 0.57219452 | E20: =E5/E3 -> 0.56672708 | F20: =F5/F3 -> 0.56465068 | G20: =G5/G3 -> 0.58142018 | H20: =H5/H3 -> 0.5809988 | I20: =I5/I3 -> 0.58678117 | J20: =J5/J3 -> 0.57900465 | ... V20: =V5/V3 -> 0.59793724 | X20: =X5/X3 -> 0.55379443 | Y20: =Y5/Y3 -> 0.56625048 | Z20: =Z5/Z3 -> 0.58200435 | AA20: =AA5/AA3 -> 0.59652315 | AB20: =AB5/AB3 -> 0.59793724 | AC20: =AC5/AC3 -> 0.59793724
B21: Operating Margin | C21: =C10/C3 -> 0.24954504 | D21: =D10/D3 -> 0.29271889 | E21: =E10/E3 -> 0.27829137 | F21: =F10/F3 -> 0.27455683 | G21: =G10/G3 -> 0.31626914 | H21: =H10/H3 -> 0.32362937 | I21: =I10/I3 -> 0.32311823 | J21: =J10/J3 -> 0.32105651 | ... V21: =V10/V3 -> 0.31568683 | X21: =X10/X3 -> 0.26461271 | Y21: =Y10/Y3 -> 0.2742181 | Z21: =Z10/Z3 -> 0.32109777 | AA21: =AA10/AA3 -> 0.32032639 | AB21: =AB10/AB3 -> 0.31568683 | AC21: =AC10/AC3 -> 0.31568683
B22: Net Margin | C22: =C14/C3 -> 0.21567054 | D22: =D14/D3 -> 0.24620664 | E22: =E14/E3 -> 0.25672486 | F22: =F14/F3 -> 0.23968254 | G22: =G14/G3 -> 0.29379555 | H22: =H14/H3 -> 0.27871658 | I22: =I14/I3 -> 0.29796755 | J22: =J14/J3 -> 0.27507282 | ... N22: =N14/N3 -> 0.30269354 | X22: =X14/X3 -> 0.21203807 | Y22: =Y14/Y3 -> 0.24006649 | Z22: =Z14/Z3 -> 0.28603672 | AA22: =AA14/AA3 -> 0.32809878 | AB22: =AB14/AB3 -> 0.28862927 | AC22: =AC14/AC3 -> 0.29838218 | AD22: =AD14/AD3 -> 0.29838218 | AE22: =AE14/AE3 -> 0.29838218 | ... AU22: =AU14/AU3 -> 0.29838218 | AW22: Maturity | AX22: -0.01
AW23: Discount | AX23: 0.06
B24: Tax Margin | C24: =C13/C12 -> 0.17324911 | D24: =D13/D12 -> 0.16139342 | E24: =E13/E12 -> 0.071142143 | F24: =F13/F12 -> 0.15258889 | G24: =G13/G12 -> 0.16432986 | H24: =H13/H12 -> 0.14271714 | I24: =I13/I12 -> 0.17047247 | J24: =J13/J12 -> 0.17699966 | ... V24: =V13/V12 -> 0.17 | X24: =X13/X12 -> 0.15920817 | Y24: =Y13/Y12 -> 0.1390856 | Z24: =Z13/Z12 -> 0.16439511 | AA24: =AA13/AA12 -> 0.16783146 | AB24: =AB13/AB12 -> 0.17 | AC24: =AC13/AC12 -> 0.17 | AW24: NPV | AX24: =NPV(AX23,AB14:YT14)+AA14+L34 -> 3778612.7
B25: R&D Margin | G25: =G6/G5 -> 0.25419096 | H25: =H6/H5 -> 0.24088555 | I25: =I6/I5 -> 0.24031741 | J25: =J6/J5 -> 0.2348181 | K25: =K6/K5 -> 0.25162883 | L25: =L6/L5 -> 0.2406036 | M25: =M6/M5 -> 0.24847073 | N25: =N6/N5 -> 0.27286885 | ... V25: =V6/V5 -> 0.27286885 | X25: =X6/X5 -> 0.25218185 | Y25: =Y6/Y5 -> 0.26098172 | Z25: =Z6/Z5 -> 0.24213596 | AA25: =AA6/AA5 -> 0.25421034 | AB25: =AB6/AB5 -> 0.27286885 | AC25: =AC6/AC5 -> 0.27286885 | AW25: Share | AX25: =AX24/Main!I16 -> 312.98042
B26: S&M Margin | G26: =G7/G5 -> 0.13722852 | H26: =H7/H5 -> 0.13795064 | I26: =I7/I5 -> 0.13953354 | J26: =J7/J5 -> 0.13182111 | K26: =K7/K5 -> 0.11456574 | L26: =L7/L5 -> 0.12373451 | M26: =M7/M5 -> 0.11815931 | N26: =N7/N5 -> 0.12069877 | ... V26: =V7/V5 -> 0.12069877 | AW26: Current | AX26: =Main!I15 -> 331.71
B27: G&A Margin | G27: =(G8)/G5 -> 0.064620838 | H27: =(H8)/H5 -> 0.064141363 | I27: =(I8)/I5 -> 0.069486813 | J27: =(J8)/J5 -> 0.078863506 | K27: =(K8)/K5 -> 0.065691534 | L27: =(L8)/L5 -> 0.090766523 | M27: =(M8)/M5 -> 0.12124244 | N27: =(N8)/N5 -> 0.078472569 | ... V27: =(V8)/V5 -> 0.078472569 | X27: =(X8)/X5 -> 0.10038753 | Y27: =(Y8)/Y5 -> 0.094362928 | Z27: =(Z8)/Z5 -> 0.069647345 | AA27: =(AA8)/AA5 -> 0.089396216 | AB27: =(AB8)/AB5 -> 0.078472569 | AC27: =(AC8)/AC5 -> 0.078472569 | AW27: Return | AX27: =AX25/AX26-1 -> -0.056463705
B28: Interest Margin | G28: =G11/G10 -> 0.11161275 | H28: =H11/H10 -> 0.0045943482 | I28: =I11/I10 -> 0.1116721 | J28: =J11/J10 -> 0.041037066 | K28: =K11/K10 -> 0.36538587 | L28: =L11/L10 -> 0.085126795 | M28: =M11/M10 -> 0.40857564 | N28: =N11/N10 -> 0.088579062 | ... V28: =V11/V10 -> 0.096357242 | X28: =X11/X10 -> -0.046952246 | Y28: =Y11/Y10 -> 0.016893455 | Z28: =Z11/Z10 -> 0.066064596 | AA28: =AA11/AA10 -> 0.23083719 | AB28: =AB11/AB10 -> 0.10155408 | AC28: =AC11/AC10 -> 0.13877606
B30: Revenue y/y | G30: =G3/C3-1 -> 0.15406881 | H30: =H3/D3-1 -> 0.13589084 | I30: =I3/E3-1 -> 0.15092642 | J30: =J3/F3-1 -> 0.11770363 | K30: =K3/G3-1 -> 0.12037646 | L30: =L3/H3-1 -> 0.13790092 | M30: =M3/I3-1 -> 0.15949155 | N30: =N3/J3-1 -> 0.17994382 | ... V30: =V3/R3-1 -> 0.1 | Y30: =Y3/X3-1 -> 0.086827702 | Z30: =Z3/Y3-1 -> 0.13866243 | AA30: =AA3/Z3-1 -> 0.15090081 | AB30: =AB3/AA3-1 -> 0.09004657 | AC30: =AC3/AB3-1 -> 0.067563936
B31: EPS y/y | Y31: =Y16/X16-1 -> 0.2689067 | Z31: =Z16/Y16-1 -> 0.38436955 | AA31: =AA16/Z16-1 -> 0.34708391 | AB31: =AB16/AA16-1 -> -0.021513728 | AC31: =AC16/AB16-1 -> 0.12616058 | AD31: =AD16/AC16-1 -> 0.079960018 | AE31: =AE16/AD16-1 -> 0.090265937 | AF31: =AF16/AE16-1 -> 0.10180786 | ... AK31: =AK16/AJ16-1 -> 0.079525004
B32: S/O | Y32: =Y15/X15-1 -> -0.03027473 | Z32: =Z15/Y15-1 -> -0.019983949 | AA32: =AA15/Z15-1 -> -0.02 | AB32: =AB15/AA15-1 -> -0.02 | AC32: =AC15/AB15-1 -> -0.02
B34: Net Cash | C34: =C35-C49 -> 0 | D34: =D35-D49 -> 0 | E34: =E35-E49 -> 0 | F34: =F35-F49 -> 130054 | G34: =G35-G49 -> 128856 | H34: =H35-H49 -> 121659 | I34: =I35-I49 -> 117110 | J34: =J35-J49 -> 122756 | ... O34: =O35-O49 -> 0 | Y34: =Y35-Y49 -> 130054 | Z34: =Z35-Z49 -> 122756 | AA34: =AA35-AA49 -> 148983
B35: Cash | F35: =24048+86868+31008 -> 141924 | G35: =24493+83597+33994 -> 142084 | H35: =27225+73500+34172 -> 134897 | I35: =19959+73271+36177 -> 129407 | J35: =23466+72191+37982 -> 133639 | K35: =23264+72064+51029 -> 146357 | L35: =21036+74112+52574 -> 147722 | M35: =23090+75406+63800 -> 162296 | N35: =126843+68687 -> 195530 | Y35: =24048+86868+31008 -> 141924 | Z35: =23466+72191+37982 -> 133639 | AA35: =126843+68687 -> 195530
B36: A/R | F36: 47964 | G36: 44552 | H36: 47087 | I36: 49104 | J36: 52340 | K36: 51000 | L36: 55048 | M36: 57148 | N36: 62886 | Y36: 47964 | Z36: 52340 | AA36: 62886
B37: OCA | F37: 12650 | G37: 12829 | H37: 14183 | I37: 15207 | J37: 15714 | K37: 15724 | L37: 16020 | M37: 18303 | N37: 13309 | Y37: 12650 | Z37: 15714 | AA37: 13309
B38: D/R taxes | F38: 12169 | G38: 11687 | H38: 14958 | I38: 15915 | J38: 17180 | K38: 18386 | L38: 19289 | M38: 10331 | N38: 9113 | Y38: 12169 | Z38: 17180 | AA38: 9113
B39: PP&A | F39: 134345 | G39: 143182 | H39: 151155 | I39: 161270 | J39: 171036 | K39: 185062 | L39: 203231 | M39: 223787 | N39: 246597 | Y39: 134345 | Z39: 171036 | AA39: 246597
B40: Lease ROU | F40: 14091 | G40: 13768 | H40: 13606 | I40: 13561 | J40: 13588 | K40: 13722 | L40: 14255 | M40: 14524 | N40: 15221 | Y40: 14091 | Z40: 13588 | AA40: 15221
B41: Goodwill | F41: 29198 | G41: 29183 | H41: 29185 | I41: 31935 | J41: 31885 | K41: 32173 | L41: 32335 | M41: 33269 | N41: 33380 | Y41: 29198 | Z41: 31885 | AA41: 33380
B42: ONCA | F42: 10051 | G42: 10065 | H42: 9699 | I42: 13867 | J42: 14874 | K42: 12950 | L42: 14153 | M42: 16811 | N42: 16245 | Y42: 10051 | Z42: 14874 | AA42: 16245
B43: Total Assets | C43: =SUM(C35:C42) -> 0 | D43: =SUM(D35:D42) -> 0 | E43: =SUM(E35:E42) -> 0 | F43: =SUM(F35:F42) -> 402392 | G43: =SUM(G35:G42) -> 407350 | H43: =SUM(H35:H42) -> 414770 | I43: =SUM(I35:I42) -> 430266 | J43: =SUM(J35:J42) -> 450256 | ... O43: =SUM(O35:O42) -> 0 | Y43: =SUM(Y35:Y42) -> 402392 | Z43: =SUM(Z35:Z42) -> 450256 | AA43: =SUM(AA35:AA42) -> 592281
B44: A/P | F44: 7493 | G44: 6198 | H44: 6092 | I44: 7049 | J44: 7987 | K44: 8497 | L44: 8347 | M44: 10546 | N44: 12200 | Y44: 7493 | Z44: 7987 | AA44: 12200
B45: Wages | F45: 15140 | G45: 9703 | H45: 11373 | I45: 12908 | J45: 15069 | K45: 9984 | L45: 12168 | M45: 13944 | N45: 17546 | Y45: 15140 | Z45: 15069 | AA45: 17546
B46: Accrued Expenses | F46: 46168 | G46: 48603 | H46: 47298 | I46: 46585 | J46: 51228 | K46: 58300 | L46: 52039 | M46: 59437 | N46: 55557 | Y46: 46168 | Z46: 51228 | AA46: 55557
B47: Accrued revenue share | F47: 8876 | G47: 8520 | H47: 8899 | I47: 9365 | J47: 9802 | K47: 9965 | L47: 9787 | M47: 10081 | N47: 10864 | Y47: 8876 | Z47: 9802 | AA47: 10864
B48: D/R | F48: 4137 | G48: =3973+921 -> 4894 | H48: =4251+985 -> 5236 | I48: =4896+1015 -> 5911 | J48: 5036 | K48: 4908 | L48: 4969 | M48: 5542 | N48: 6578 | Y48: 4137 | Z48: 5036 | AA48: 6578
B49: Debt | F49: 11870 | G49: 13228 | H49: 13238 | I49: 12297 | J49: 10883 | K49: 10886 | L49: 23607 | M49: 21607 | N49: 46547 | Y49: 11870 | Z49: 10883 | AA49: 46547
B50: Taxes | F50: 8474 | G50: =9234+486 -> 9720 | H50: =7703+717 -> 8420 | I50: =8219+706 -> 8925 | J50: 8782 | K50: 9773 | L50: 10027 | M50: 10072 | N50: 9531 | Y50: 8474 | Z50: 8782 | AA50: 9531
B51: Lease | F51: 12460 | G51: 11957 | H51: 11708 | I51: 11654 | J51: 11691 | K51: 11678 | L51: 11952 | M51: 12106 | N51: 12744 | Y51: 12460 | Z51: 11691 | AA51: 12744
B52: ONCL | F52: 4395 | G52: 1683 | H52: 1753 | I52: 1453 | J52: 4694 | K52: 6116 | L52: 6241 | M52: 6267 | N52: 8449 | Y52: 4395 | Z52: 4694 | AA52: 8449
B53: Total Liabilities | C53: =SUM(C44:C52) -> 0 | D53: =SUM(D44:D52) -> 0 | E53: =SUM(E44:E52) -> 0 | F53: =SUM(F44:F52) -> 119013 | G53: =SUM(G44:G52) -> 114506 | H53: =SUM(H44:H52) -> 114017 | I53: =SUM(I44:I52) -> 116147 | J53: =SUM(J44:J52) -> 125172 | ... O53: =SUM(O44:O52) -> 0 | Y53: =SUM(Y44:Y52) -> 119013 | Z53: =SUM(Z44:Z52) -> 125172 | AA53: =SUM(AA44:AA52) -> 180016
B54: SE | F54: 283379 | G54: 292844 | H54: 300753 | I54: 314119 | J54: 325084 | K54: 345267 | L54: 362916 | M54: 386867 | N54: 415265 | Y54: 283379 | Z54: 325084 | AA54: 415265
B55: L+SE | C55: =C53+C54 -> 0 | D55: =D53+D54 -> 0 | E55: =E53+E54 -> 0 | F55: =F53+F54 -> 402392 | G55: =G53+G54 -> 407350 | H55: =H53+H54 -> 414770 | I55: =I53+I54 -> 430266 | J55: =J53+J54 -> 450256 | ... O55: =O53+O54 -> 0 | Y55: =Y53+Y54 -> 402392 | Z55: =Z53+Z54 -> 450256 | AA55: =AA53+AA54 -> 595281
B57: Debt to Equity | F57: =F53/F54 -> 0.41997819 | G57: =G53/G54 -> 0.39101365 | H57: =H53/H54 -> 0.37910511 | I57: =I53/I54 -> 0.36975477 | J57: =J53/J54 -> 0.3850451 | K57: =K53/K54 -> 0.37683011 | L57: =L53/L54 -> 0.38338624 | M57: =M53/M54 -> 0.38670137 | ... O57: =O53/O54 -> #DIV/0! | Y57: =Y53/Y54 -> 0.41997819 | Z57: =Z53/Z54 -> 0.3850451 | AA57: =AA53/AA54 -> 0.43349668
B58: PP&A seq growth | G58: =G39/F39-1 -> 0.065778406 | H58: =H39/G39-1 -> 0.055684374 | I58: =I39/H39-1 -> 0.066918064 | J58: =J39/I39-1 -> 0.06055683 | K58: =K39/J39-1 -> 0.082006127 | L58: =L39/K39-1 -> 0.098177908 | M58: =M39/L39-1 -> 0.10114599 | N58: =N39/M39-1 -> 0.10192728 | Z58: =Z39/Y39-1 -> 0.27311028 | AA58: =AA39/Z39-1 -> 0.44178419
B61: Model NI | C61: =C14 -> 15051 | D61: =D14 -> 18368 | E61: =E14 -> 19689 | F61: =F14 -> 20687 | G61: =G14 -> 23662 | H61: =H14 -> 23619 | I61: =I14 -> 26301 | J61: =J14 -> 26536 | ... Q61: =Q14 -> 31740 | X61: =X14 -> 59972 | Y61: =Y14 -> 73795 | Z61: =Z14 -> 100118 | AA61: =AA14 -> 132170 | AB61: =AB14 -> 126740
B62: GAAP NI | C62: 15051 | D62: 18368 | E62: 19689 | F62: 20687 | G62: 23662 | H62: 23619 | I62: 26301 | J62: 26536 | K62: 34540 | L62: 28196 | M62: 34979 | N62: 34455 | Y62: =+SUM(C62:F62) -> 73795 | Z62: =+SUM(G62:J62) -> 100118 | AA62: =SUM(K62:N62) -> 132170
B63: D&A | C63: 2635 | D63: 2824 | E63: 3171 | F63: 3316 | G63: 3413 | H63: 3708 | I63: 3985 | J63: 4205 | K63: 4487 | L63: 4998 | M63: 5611 | N63: 6040 | Y63: =+SUM(C63:F63) -> 11946 | Z63: =+SUM(G63:J63) -> 15311 | AA63: =SUM(K63:N63) -> 21136
B64: Stock compensation | C64: 5284 | D64: 5774 | E64: 5743 | F64: 5659 | G64: 5264 | H64: 5865 | I64: 5846 | J64: 5810 | K64: 5516 | L64: 5998 | M64: 6368 | N64: 7071 | Y64: =+SUM(C64:F64) -> 22460 | Z64: =+SUM(G64:J64) -> 22785 | AA64: =SUM(K64:N64) -> 24953
B65: Deferred income taxes | C65: -1854 | D65: -2415 | E65: -1824 | F65: -1670 | G65: 419 | H65: -3157 | I65: -1071 | J65: -1448 | K65: -1152 | L65: -444 | M65: 8726 | N65: 1218 | Y65: =+SUM(C65:F65) -> -7763 | Z65: =+SUM(G65:J65) -> -5257 | AA65: =SUM(K65:N65) -> 8348
B66: Debt & equity Securities | C66: -84 | D66: 509 | E66: 869 | F66: -471 | G66: -1781 | H66: 1024 | I66: -1981 | J66: 67 | K66: -9960 | L66: -1451 | M66: -10855 | N66: -2354 | Y66: =+SUM(C66:F66) -> 823 | Z66: =+SUM(G66:J66) -> -2671 | AA66: =SUM(K66:N66) -> -24620
B67: Other | C67: 1104 | D67: 670 | E67: 891 | F67: 1665 | G67: 334 | H67: 851 | I67: 1407 | J67: 827 | K67: 481 | L67: 560 | M67: -198 | N67: 1265 | Y67: =+SUM(C67:F67) -> 4330 | Z67: =+SUM(G67:J67) -> 3419 | AA67: =SUM(K67:N67) -> 2108
B68: A/R | C68: 4454 | D68: -2948 | E68: -2821 | F68: -6518 | G68: 3167 | H68: -3057 | I68: -1431 | J68: -4570 | K68: 1638 | L68: -2839 | M68: -2381 | N68: -4943 | Y68: =+SUM(C68:F68) -> -7833 | Z68: =+SUM(G68:J68) -> -5891 | AA68: =SUM(K68:N68) -> -8525
B69: Income taxes | C69: 4069 | D69: 4451 | E69: 1872 | F69: -9869 | G69: 3011 | H69: -3900 | I69: -1908 | J69: 379 | K69: 7197 | L69: -9631 | M69: -858 | N69: 66 | Y69: =+SUM(C69:F69) -> 523 | Z69: =+SUM(G69:J69) -> -2418 | AA69: =SUM(K69:N69) -> -3226
B70: Other Assets | C70: -746 | D70: -513 | E70: -1624 | F70: 740 | G70: -1000 | H70: -532 | I70: -802 | J70: 937 | K70: -1288 | L70: -1479 | M70: -1293 | N70: -482 | Y70: =+SUM(C70:F70) -> -2143 | Z70: =+SUM(G70:J70) -> -1397 | AA70: =SUM(K70:N70) -> -4542
B71: A/P | C71: -1105 | D71: 1119 | E71: 223 | F71: 427 | G71: -2124 | H71: 1561 | I71: 521 | J71: 401 | K71: -880 | L71: 553 | M71: -444 | N71: 227 | Y71: =+SUM(C71:F71) -> 664 | Z71: =+SUM(G71:J71) -> 359 | AA71: =SUM(K71:N71) -> -544
B72: Expenses | C72: -4496 | D72: 459 | E72: 3657 | F72: 4317 | G72: -5054 | H72: -122 | I72: -1190 | J72: 5205 | K72: -5045 | L72: 3485 | M72: 7759 | N72: 7937 | Y72: =+SUM(C72:F72) -> 3937 | Z72: =+SUM(G72:J72) -> -1161 | AA72: =SUM(K72:N72) -> 14136
B73: Accrued revenue share | C73: -602 | D73: 184 | E73: 103 | F73: 797 | G73: -322 | H73: 419 | I73: 381 | J73: 581 | K73: 116 | L73: -335 | M73: 319 | N73: 799 | Y73: =+SUM(C73:F73) -> 482 | Z73: =+SUM(G73:J73) -> 1059 | AA73: =SUM(K73:N73) -> 899
B74: D/R | C74: -201 | D74: 184 | E74: 707 | F74: -165 | G74: -141 | H74: 361 | I74: 640 | J74: 183 | K74: 500 | L74: 136 | M74: 681 | N74: 1103 | Y74: =+SUM(C74:F74) -> 525 | Z74: =+SUM(G74:J74) -> 1043 | AA74: =SUM(K74:N74) -> 2420
B75: CFFO | C75: =SUM(C62:C74) -> 23509 | D75: =SUM(D62:D74) -> 28666 | E75: =SUM(E62:E74) -> 30656 | F75: =SUM(F62:F74) -> 18915 | G75: =SUM(G62:G74) -> 28848 | H75: =SUM(H62:H74) -> 26640 | I75: =SUM(I62:I74) -> 30698 | J75: =SUM(J62:J74) -> 39113 | ... Q75: =SUM(Q62:Q74) -> 0 | X75: =SUM(X62:X74) -> 0 | Y75: =SUM(Y62:Y74) -> 101746 | Z75: =SUM(Z62:Z74) -> 125299 | AA75: =SUM(AA62:AA74) -> 164713 | AB75: =SUM(AB62:AB74) -> 0
B76: Capex | C76: -6289 | D76: -6888 | E76: -8055 | F76: -11019 | G76: -12012 | H76: -13186 | I76: -13061 | J76: -14276 | K76: -17197 | L76: -22446 | M76: -23953 | N76: -27851 | Y76: =+SUM(C76:F76) -> -32251 | Z76: =+SUM(G76:J76) -> -52535 | AA76: =SUM(K76:N76) -> -91447 | AB76: Cons: 175-185
B77: Marketable Securuties | C77: =-14227+18327 -> 4100 | D77: =-21362+18722 -> -2640 | E77: =-13833+15593 -> 1760 | F77: =-28436+34030 -> 5594 | G77: =-20684+24985 -> 4301 | H77: =-22327+33592 -> 11265 | I77: =-22023+23202 -> 1179 | J77: =-21645+21649 -> 4 | K77: =-18453+20345 -> 1892 | L77: =-21417+20585 -> -832 | M77: -593 | N77: =-42939+21939 -> -21000 | Y77: =+SUM(C77:F77) -> 8814 | Z77: =+SUM(G77:J77) -> 16749 | AA77: =SUM(K77:N77) -> -20533
B78: Non-marketable securities | C78: =-626+36 -> -590 | D78: =-887+145 -> -742 | E78: =-663+562 -> -101 | F78: =-851+204 -> -647 | G78: =-1206+313 -> -893 | H78: =-993+292 -> -701 | I78: =-1035+127 -> -908 | J78: =-1800+150 -> -1650 | K78: =-958+259 -> -699 | L78: =-1354+614 -> -740 | M78: -677 | N78: =-2404+171 -> -2233 | Y78: =+SUM(C78:F78) -> -2080 | Z78: =+SUM(G78:J78) -> -4152 | AA78: =SUM(K78:N78) -> -4349
B79: Acquisitions | C79: -42 | D79: -298 | E79: -126 | F79: -29 | G79: -61 | H79: -26 | I79: -2753 | J79: -91 | K79: -340 | L79: -13 | M79: -1072 | N79: -167 | Y79: =+SUM(C79:F79) -> -495 | Z79: =+SUM(G79:J79) -> -2931 | AA79: =SUM(K79:N79) -> -1592
B80: Other | C80: -125 | D80: -232 | E80: -628 | F80: -66 | G80: 101 | H80: -133 | I80: -2468 | J80: -167 | K80: 150 | L80: -513 | M80: -1482 | N80: -525 | Y80: =+SUM(C80:F80) -> -1051 | Z80: =+SUM(G80:J80) -> -2667 | AA80: =SUM(K80:N80) -> -2370
B81: CFFI | C81: =SUM(C76:C80) -> -2946 | D81: =SUM(D76:D80) -> -10800 | E81: =SUM(E76:E80) -> -7150 | F81: =SUM(F76:F80) -> -6167 | G81: =SUM(G76:G80) -> -8564 | H81: =SUM(H76:H80) -> -2781 | I81: =SUM(I76:I80) -> -18011 | J81: =SUM(J76:J80) -> -16180 | ... Q81: =SUM(Q76:Q80) -> 0 | X81: =SUM(X76:X80) -> 0 | Y81: =SUM(Y76:Y80) -> -27063 | Z81: =SUM(Z76:Z80) -> -45536 | AA81: =SUM(AA76:AA80) -> -120291 | AB81: =SUM(AB76:AB80) -> 0
B82: Stock-based awards | C82: -1989 | D82: -2736 | E82: -2432 | F82: -2680 | G82: -2929 | H82: -3209 | I82: -3003 | J82: -3049 | K82: -3110 | L82: -2621 | M82: -3270 | N82: -5166 | Y82: =+SUM(C82:F82) -> -9837 | Z82: =+SUM(G82:J82) -> -12190 | AA82: =SUM(K82:N82) -> -14167
B83: Buybacks | C83: -14557 | D83: -14969 | E83: -15787 | F83: -16191 | G83: -15696 | H83: -15684 | I83: -15291 | J83: -15551 | K83: -15068 | L83: -13638 | M83: -11504 | N83: -5499 | Y83: =+SUM(C83:F83) -> -61504 | Z83: =+SUM(G83:J83) -> -62222 | AA83: =SUM(K83:N83) -> -45709
B84: Dividends | E84: 1248 | H84: -2466 | I84: -2455 | J84: -2442 | K84: -2434 | L84: -2543 | M84: -2536 | N84: -2536 | Y84: =+SUM(C84:F84) -> 1248 | Z84: =+SUM(G84:J84) -> -7363 | AA84: =SUM(K84:N84) -> -10049
B85: Debt | C85: =6927-6952 -> -25 | D85: =1123-1255 -> -132 | E85: -1414 | F85: =1492-1929 -> -437 | G85: =-3079+1982 -> -1097 | H85: =2893-2423 -> 470 | I85: =3819-3449 -> 370 | J85: =4895-3750 -> 1145 | K85: =4532-4521 -> 11 | L85: =26846-13876 -> 12970 | M85: -1073 | N85: =26562-6333 -> 20229 | Y85: =+SUM(C85:F85) -> -2008 | Z85: =+SUM(G85:J85) -> 888 | AA85: =SUM(K85:N85) -> 32137
B86: Sale of entities | C86: 3 | D86: 2 | E86: 3 | G86: 8 | I86: 285 | J86: 861 | K86: 400 | L86: 0 | M86: 0 | N86: 0 | Y86: =+SUM(C86:F86) -> 8 | Z86: =+SUM(G86:J86) -> 1154 | AA86: =SUM(K86:N86) -> 400
B87: CFFF | C87: =SUM(C82:C86) -> -16568 | D87: =SUM(D82:D86) -> -17835 | E87: =SUM(E82:E86) -> -18382 | F87: =SUM(F82:F86) -> -19308 | G87: =SUM(G82:G86) -> -19714 | H87: =SUM(H82:H86) -> -20889 | I87: =SUM(I82:I86) -> -20094 | J87: =SUM(J82:J86) -> -19036 | ... Q87: =SUM(Q82:Q86) -> 0 | X87: =SUM(X82:X86) -> 0 | Y87: =SUM(Y82:Y86) -> -72093 | Z87: =SUM(Z82:Z86) -> -79733 | AA87: =SUM(AA82:AA86) -> -37388 | AB87: =SUM(AB82:AB86) -> 0
B88: Currency adj | C88: 50 | D88: -26 | E88: -351 | F88: -94 | G88: -125 | H88: -238 | I88: 141 | J88: -390 | K88: 43 | L88: 401 | M88: -200 | N88: -36 | Y88: =+SUM(C88:F88) -> -421 | Z88: =+SUM(G88:J88) -> -612 | AA88: =SUM(K88:N88) -> 208
B89: CF | C89: =C87+C88+C81+C75 -> 4045 | D89: =D87+D88+D81+D75 -> 5 | E89: =E87+E88+E81+E75 -> 4773 | F89: =F87+F88+F81+F75 -> -6654 | G89: =G87+G88+G81+G75 -> 445 | H89: =H87+H88+H81+H75 -> 2732 | I89: =I87+I88+I81+I75 -> -7266 | J89: =J87+J88+J81+J75 -> 3507 | ... Q89: =Q87+Q88+Q81+Q75 -> 0 | X89: =X87+X88+X81+X75 -> 0 | Y89: =Y87+Y88+Y81+Y75 -> 2169 | Z89: =Z87+Z88+Z81+Z75 -> -582 | AA89: =AA87+AA88+AA81+AA75 -> 7242 | AB89: =AB87+AB88+AB81+AB75 -> 0
B92: FCF | C92: =C75+C76 -> 17220 | D92: =D75+D76 -> 21778 | E92: =E75+E76 -> 22601 | F92: =F75+F76 -> 7896 | G92: =G75+G76 -> 16836 | H92: =H75+H76 -> 13454 | I92: =I75+I76 -> 17637 | J92: =J75+J76 -> 24837 | ... Q92: =Q75+Q76 -> 0 | X92: =X75+X76 -> 0 | Y92: =Y75+Y76 -> 69495 | Z92: =Z75+Z76 -> 72764 | AA92: =AA75+AA76 -> 73266 | AB92: =AB75+AB76 -> #VALUE!
B93: Capex Margin | C93: =-C76/C61 -> 0.41784599 | D93: =-D76/D61 -> 0.375 | E93: =-E76/E61 -> 0.40911169 | F93: =-F76/F61 -> 0.53265336 | G93: =-G76/G61 -> 0.5076494 | H93: =-H76/H61 -> 0.55827935 | I93: =-I76/I61 -> 0.49659709 | J93: =-J76/J61 -> 0.53798613 | ... Q93: =-Q76/Q61 -> 0 | X93: =-X76/X61 -> 0 | Y93: =-Y76/Y61 -> 0.43703503 | Z93: =-Z76/Z61 -> 0.52473082 | AA93: =-AA76/AA61 -> 0.69188923 | AB93: =-AB76/AB61 -> #VALUE!
B98: Revenues
B99: Google Search & Other | G99: 46156 | H99: 48509 | I99: 49385 | J99: 54034 | K99: 50702 | L99: 54190 | M99: 56567 | N99: 63073
B100: Youtube ads | G100: 8090 | H100: 8663 | I100: 8921 | J100: 10473 | K100: 8927 | L100: 9796 | M100: 10261 | N100: 11383
B101: Google Network | G101: 7413 | H101: 7444 | I101: 7548 | J101: 7954 | K101: 7256 | L101: 7354 | M101: 7354 | N101: 7828
B102: Advertising | G102: =SUM(G99:G101) -> 61659 | H102: =SUM(H99:H101) -> 64616 | I102: =SUM(I99:I101) -> 65854 | J102: =SUM(J99:J101) -> 72461 | K102: =SUM(K99:K101) -> 66885 | L102: =SUM(L99:L101) -> 71340 | M102: =SUM(M99:M101) -> 74182 | N102: =SUM(N99:N101) -> 82284 | O102: =SUM(O99:O101) -> 0
B103: Google subs, platforms & devices | G103: 8739 | H103: 9312 | I103: 10656 | J103: 11633 | K103: 10379 | L103: 11203 | M103: 12870 | N103: 13578
B104: Services total | G104: =SUM(G102:G103) -> 70398 | H104: =SUM(H102:H103) -> 73928 | I104: =SUM(I102:I103) -> 76510 | J104: =SUM(J102:J103) -> 84094 | K104: =SUM(K102:K103) -> 77264 | L104: =SUM(L102:L103) -> 82543 | M104: =SUM(M102:M103) -> 87052 | N104: =SUM(N102:N103) -> 95862 | O104: =SUM(O102:O103) -> 0
B105: Google Cloud | G105: 9574 | H105: 10347 | I105: 11353 | J105: 11955 | K105: 12260 | L105: 13624 | M105: 15157 | N105: 17664
B106: Other Bets | G106: 495 | H106: 365 | I106: 388 | J106: 400 | K106: 450 | L106: 373 | M106: 344 | N106: 370
B107: Hedging gains (losses) | G107: 72 | H107: 102 | I107: 17 | J107: 20 | K107: 260 | L107: -112 | M107: -207 | N107: -68
B108: Total Revenues | G108: =SUM(G104:G107) -> 80539 | H108: =SUM(H104:H107) -> 84742 | I108: =SUM(I104:I107) -> 88268 | J108: =SUM(J104:J107) -> 96469 | K108: =SUM(K104:K107) -> 90234 | L108: =SUM(L104:L107) -> 96428 | M108: =SUM(M104:M107) -> 102346 | N108: =SUM(N104:N107) -> 113828 | O108: =SUM(O104:O107) -> 0
B110: Y/Y
B111: Google Search & Other | K111: =K99/G99-1 -> 0.09849207 | L111: =L99/H99-1 -> 0.11711229 | M111: =M99/I99-1 -> 0.14542877 | N111: =N99/J99-1 -> 0.16728356 | O111: =O99/K99-1 -> -1
B112: Youtube ads | K112: =K100/G100-1 -> 0.10346106 | L112: =L100/H100-1 -> 0.1307861 | M112: =M100/I100-1 -> 0.15020738 | N112: =N100/J100-1 -> 0.086890098 | O112: =O100/K100-1 -> -1
B113: Google Network | K113: =K101/G101-1 -> -0.02117901 | L113: =L101/H101-1 -> -0.012090274 | M113: =M101/I101-1 -> -0.025702173 | N113: =N101/J101-1 -> -0.015841086 | O113: =O101/K101-1 -> -1
B114: Google subs, platforms & devices | K114: =K103/G103-1 -> 0.18766449 | L114: =L103/H103-1 -> 0.20307131 | M114: =M103/I103-1 -> 0.20777027 | N114: =N103/J103-1 -> 0.16719677 | O114: =O103/K103-1 -> -1
B115: Google Cloud | K115: =K105/G105-1 -> 0.28055149 | L115: =L105/H105-1 -> 0.31671016 | M115: =M105/I105-1 -> 0.33506562 | N115: =N105/J105-1 -> 0.47754078 | O115: =O105/K105-1 -> -1
...

Sheet META
A1: Main
C2: Q123 | D2: Q223 | E2: Q323 | F2: Q423 | G2: Q124 | H2: Q224 | I2: Q324 | J2: Q424 | K2: Q125 | L2: Q225 | M2: Q325 | N2: Q425 | O2: Q126 | P2: Q226 | Q2: Q326 | R2: Q426 | T2: 2022 | U2: 2023 | V2: 2024 | W2: 2025 | X2: 2026 | Y2: 2027 | Z2: 2028 | AA2: 2029 | AB2: 2030 | AC2: 2031 | AD2: 2032 | AE2: 2033 | AF2: 2034 | AG2: 2035 | AH2: 2036 | AI2: 2037 | AJ2: 2038 | AK2: 2039 | AL2: 2040 | AM2: 2041 | AN2: 2042 | AO2: 2043 | AP2: 2044 | AQ2: 2045 | AR2: 2046 | AS2: 2047 | AT2: 2048 | AU2: 2049 | AV2: 2050 | AW2: 2051 | AX2: 2052 | AY2: 2053 | AZ2: 2054 | BA2: 2055 | BB2: 2056 | BC2: 2057 | BD2: 2058 | BE2: 2059 | BF2: 2060 | BG2: 2061 | BH2: 2062 | BI2: 2063 | BJ2: 2064 | BK2: 2065 | BL2: 2066 | BM2: 2067 | BN2: 2068 | BO2: 2069 | BP2: 2070 | BQ2: 2071 | BR2: 2072 | BS2: 2073 | BT2: 2074 | BU2: 2075 | BV2: 2076 | BW2: 2077 | BX2: 2078 | BY2: 2079 | BZ2: 2080 | CA2: 2081 | CB2: 2082 | CC2: 2083 | CD2: 2084 | CE2: 2085 | CF2: 2086 | CG2: 2087 | CH2: 2088 | CI2: 2089 | CJ2: 2090 | CK2: 2091 | CL2: 2092 | CM2: 2093 | CN2: 2094 | CO2: 2095 | CP2: 2096 | CQ2: 2097 | CR2: 2098 | CS2: 2099 | CT2: 2100 | CU2: 2101 | CV2: 2102 | CW2: 2103 | CX2: 2104 | CY2: 2105 | CZ2: 2106 | DA2: 2107 | DB2: 2108 | DC2: 2109 | DD2: 2110 | DE2: 2111 | DF2: 2112 | DG2: 2113 | DH2: 2114 | DI2: 2115 | DJ2: 2116 | DK2: 2117 | DL2: 2118 | DM2: 2119 | DN2: 2120 | DO2: 2121 | DP2: 2122 | DQ2: 2123 | DR2: 2124 | DS2: 2125 | DT2: 2126 | DU2: 2127 | DV2: 2128 | DW2: 2129 | DX2: 2130 | DY2: 2131 | DZ2: 2132 | EA2: 2133 | EB2: 2134 | EC2: 2135 | ED2: 2136 | EE2: 2137 | EF2: 2138 | EG2: 2139 | EH2: 2140 | EI2: 2141 | EJ2: 2142 | EK2: 2143 | EL2: 2144 | EM2: 2145 | EN2: 2146 | EO2: 2147 | EP2: 2148 | EQ2: 2149 | ER2: 2150 | ES2: 2151 | ET2: 2152 | EU2: 2153 | EV2: 2154 | EW2: 2155 | EX2: 2156 | EY2: 2157 | EZ2: 2158 | FA2: 2159 | FB2: 2160 | FC2: 2161 | FD2: 2162 | FE2: 2163 | FF2: 2164 | FG2: 2165 | FH2: 2166 | FI2: 2167 | FJ2: 2168 | FK2: 2169 | FL2: 2170 | FM2: 2171 | FN2: 2172 | FO2: 2173 | FP2: 2174 | FQ2: 2175 | FR2: 2176 | FS2: 2177 | FT2: 2178 | FU2: 2179 | FV2: 2180 | FW2: 2181 | FX2: 2182 | FY2: 2183 | FZ2: 2184 | GA2: 2185 | GB2: 2186 | GC2: 2187 | GD2: 2188 | GE2: 2189 | GF2: 2190
B3: DAP | C3: 3020 | D3: 3070 | E3: 3140 | F3: 3190 | G3: 3240 | H3: 3270 | I3: 3290 | J3: 3350 | N3: 3580 | U3: 3190 | V3: 3350 | W3: =V3*1.015 -> 3400.25 | X3: =W3*1.015 -> 3451.2537 | Y3: =X3*1.015 -> 3503.0226 | Z3: =Y3*1.015 -> 3555.5679 | AA3: =Z3*1.015 -> 3608.9014 | AB3: =AA3*1.015 -> 3663.0349 | AC3: =AB3*1.015 -> 3717.9805 | AD3: =AC3*1.015 -> 3773.7502
B4: Avg rev per user | C4: =C8/C3 -> 9.4850993 | D4: =D8/D3 -> 10.423127 | E4: =E8/E3 -> 10.874522 | F4: =F8/F3 -> 12.573981 | G4: =G8/G3 -> 11.251543 | H4: =H8/H3 -> 11.948318 | I4: =I8/I3 -> 12.337082 | J4: =J8/J3 -> 14.443284 | N4: =N8/N3 -> 16.729888 | O4: =O8/O3 -> #DIV/0! | P4: =P8/P3 -> #DIV/0! | Q4: =Q8/Q3 -> #DIV/0! | R4: =R8/R3 -> #DIV/0! | U4: =U8/I3 -> 41.003343 | V4: =V8/J3 -> 49.104478 | W4: =V4*1.2 -> 58.925373 | X4: =W4*1.2 -> 70.710448 | Y4: =X4*1.2 -> 84.852537 | Z4: =Y4*1.2 -> 101.82304 | AA4: =Z4*1.1 -> 112.00535 | AB4: =AA4*1.1 -> 123.20588 | AC4: =AB4*1.1 -> 135.52647 | AD4: =AC4*1.1 -> 149.07912
B5: DAP growth | G5: =G3/C3-1 -> 0.072847682 | H5: =H3/D3-1 -> 0.06514658 | I5: =I3/E3-1 -> 0.047770701 | J5: =J3/F3-1 -> 0.05015674 | N5: =N3/J3-1 -> 0.068656716 | O5: =O3/K3-1 -> #DIV/0! | P5: =P3/L3-1 -> #DIV/0! | Q5: =Q3/M3-1 -> #DIV/0! | R5: =R3/N3-1 -> -1 | V5: =V3/U3-1 -> 0.05015674
B6: ARPU growth | G6: =G4/C4-1 -> 0.18623357 | H6: =H4/D4-1 -> 0.14632758 | I6: =I4/E4-1 -> 0.13449416 | J6: =J4/F4-1 -> 0.14866432 | N6: =N4/J4-1 -> 0.15831612 | O6: =O4/K4-1 -> #DIV/0! | P6: =P4/L4-1 -> #DIV/0! | Q6: =Q4/M4-1 -> #DIV/0! | R6: =R4/N4-1 -> #DIV/0! | V6: =V4/U4-1 -> 0.19757253
B8: Revenue | C8: 28645 | D8: 31999 | E8: 34146 | F8: 40111 | G8: 36455 | H8: 39071 | I8: 40589 | J8: 48385 | K8: 42314 | L8: 47516 | M8: 51242 | N8: 59893 | T8: 116609 | U8: =SUM(C8:F8) -> 134901 | V8: =SUM(G8:J8) -> 164500 | W8: =SUM(K8:N8) -> 200965 | X8: 213430 | Y8: =Y4*Y3 -> 297240.35 | Z8: =Z4*Z3 -> 362038.75 | AA8: =AA4*AA3 -> 404216.26 | AB8: =AB4*AB3 -> 451307.46 | AC8: =AC4*AC3 -> 503884.78 | AD8: =AD4*AD3 -> 562587.35
B9: COGS | C9: 6108 | D9: 5945 | E9: 6210 | F9: 7695 | G9: 6640 | H9: 7308 | I9: 7375 | J9: 8839 | K9: 7572 | L9: 8491 | M9: 9206 | N9: 10905 | T9: 25249 | U9: =SUM(C9:F9) -> 25958 | V9: =SUM(G9:J9) -> 30162 | W9: =SUM(K9:N9) -> 36174
B10: Gross Profit | C10: =C8-C9 -> 22537 | D10: =D8-D9 -> 26054 | E10: =E8-E9 -> 27936 | F10: =F8-F9 -> 32416 | G10: =G8-G9 -> 29815 | H10: =H8-H9 -> 31763 | I10: =I8-I9 -> 33214 | J10: =J8-J9 -> 39546 | ... R10: =R8-R9 -> 0 | T10: =T8-T9 -> 91360 | U10: =U8-U9 -> 108943 | V10: =V8-V9 -> 134338 | W10: =W8-W9 -> 164791 | X10: =X8-X9 -> 213430
B11: R&D | C11: 9381 | D11: 9344 | E11: 9241 | F11: 10517 | G11: 9978 | H11: 10537 | I11: 11177 | J11: 12180 | K11: 12150 | L11: 12942 | M11: 15144 | N11: 17136 | T11: 35338 | U11: =SUM(C11:F11) -> 38483 | V11: =SUM(G11:J11) -> 43872 | W11: =SUM(K11:N11) -> 57372
B12: M&S | C12: 3044 | D12: 3154 | E12: 2877 | F12: 3226 | G12: 2564 | H12: 2721 | I12: 2822 | J12: 3240 | K12: 2757 | L12: 2979 | M12: 2845 | N12: 3410 | T12: 15262 | U12: =SUM(C12:F12) -> 12301 | V12: =SUM(G12:J12) -> 11347 | W12: =SUM(K12:N12) -> 11991
B13: G&A | C13: 2885 | D13: 4164 | E13: 2070 | F13: 2289 | G13: 3455 | H13: 3658 | I13: 1865 | J13: 761 | K13: 2280 | L13: 2663 | M13: 3512 | N13: 3697 | T13: 11816 | U13: =SUM(C13:F13) -> 11408 | V13: =SUM(G13:J13) -> 9739 | W13: =SUM(K13:N13) -> 12152
B14: Operating Expenses | C14: =SUM(C11:C13) -> 15310 | D14: =SUM(D11:D13) -> 16662 | E14: =SUM(E11:E13) -> 14188 | F14: =SUM(F11:F13) -> 16032 | G14: =SUM(G11:G13) -> 15997 | H14: =SUM(H11:H13) -> 16916 | I14: =SUM(I11:I13) -> 15864 | J14: =SUM(J11:J13) -> 16181 | ... R14: =SUM(R11:R13) -> 0 | T14: =SUM(T11:T13) -> 62416 | U14: =SUM(U11:U13) -> 62192 | V14: =SUM(V11:V13) -> 64958 | W14: =SUM(W11:W13) -> 81515 | X14: =SUM(X11:X13) -> 0
B15: Operating Income | C15: =C10-C14 -> 7227 | D15: =D10-D14 -> 9392 | E15: =E10-E14 -> 13748 | F15: =F10-F14 -> 16384 | G15: =G10-G14 -> 13818 | H15: =H10-H14 -> 14847 | I15: =I10-I14 -> 17350 | J15: =J10-J14 -> 23365 | ... R15: =R10-R14 -> 0 | T15: =T10-T14 -> 28944 | U15: =U10-U14 -> 46751 | V15: =V10-V14 -> 69380 | W15: =W10-W14 -> 83276 | X15: =X10-X14 -> 213430
B16: Interest income | C16: 80 | D16: -99 | E16: 272 | F16: 424 | G16: 365 | H16: 259 | I16: 472 | J16: 188 | K16: 827 | L16: 93 | M16: 1128 | N16: 609 | T16: -125 | U16: =SUM(C16:F16) -> 677 | V16: =SUM(G16:J16) -> 1284 | W16: =SUM(K16:N16) -> 2657
B17: Pre-Tax Income | C17: =C15+C16 -> 7307 | D17: =D15+D16 -> 9293 | E17: =E15+E16 -> 14020 | F17: =F15+F16 -> 16808 | G17: =G15+G16 -> 14183 | H17: =H15+H16 -> 15106 | I17: =I15+I16 -> 17822 | J17: =J15+J16 -> 23553 | ... R17: =R15+R16 -> 0 | T17: =T15+T16 -> 28819 | U17: =U15+U16 -> 47428 | V17: =V15+V16 -> 70664 | W17: =W15+W16 -> 85933 | X17: =X15+X16 -> 213430
B18: Taxes | C18: 1598 | D18: 1505 | E18: 2437 | F18: 2791 | G18: 1814 | H18: 1641 | I18: 2134 | J18: 2715 | K18: 1738 | L18: 2197 | M18: 18945 | N18: 2586 | T18: 5619 | U18: =SUM(C18:F18) -> 8331 | V18: =SUM(G18:J18) -> 8304 | W18: =SUM(K18:N18) -> 25466
B19: Net Income | C19: =C17-C18 -> 5709 | D19: =D17-D18 -> 7788 | E19: =E17-E18 -> 11583 | F19: =F17-F18 -> 14017 | G19: =G17-G18 -> 12369 | H19: =H17-H18 -> 13465 | I19: =I17-I18 -> 15688 | J19: =J17-J18 -> 20838 | ... R19: =R17-R18 -> 0 | T19: =T17-T18 -> 23200 | U19: =U17-U18 -> 39097 | V19: =V17-V18 -> 62360 | W19: =W17-W18 -> 60467 | X19: =X17-X18 -> 213430 | Y19: =Y8*0.4 -> 118896.14 | Z19: =Z8*0.4 -> 144815.5 | AA19: =AA8*0.35 -> 141475.69 | AB19: =AB8*0.35 -> 157957.61 | AC19: =AC8*0.35 -> 176359.67 | AD19: =AD8*0.35 -> 196905.57 | AE19: =AD19*(1-$AG$30) -> 189029.35 | AF19: =AE19*(1-$AG$30) -> 181468.18 | AG19: =AF19*(1-$AG$30) -> 174209.45 | AH19: =AG19*(1-$AG$30) -> 167241.07 | AI19: =AH19*(1-$AG$30) -> 160551.43 | AJ19: =AI19*(1-$AG$30) -> 154129.37 | AK19: =AJ19*(1-$AG$30) -> 147964.2 | AL19: =AK19*(1-$AG$30) -> 142045.63 | ... GF19: =GE19*(1-$AG$30) -> 311.25249
B20: S/O | C20: 2587 | D20: 2568 | E20: 2576 | F20: 2566 | G20: 2545 | H20: 2534 | I20: 2529 | J20: 2529 | K20: 2527 | L20: 2518 | M20: 2517 | N20: 2525 | T20: 2687 | U20: 2574 | V20: 2534 | W20: =+N20 -> 2525
B21: EPS | C21: =C19/C20 -> 2.2068032 | D21: =D19/D20 -> 3.0327103 | E21: =E19/E20 -> 4.4965062 | F21: =F19/F20 -> 5.4625877 | G21: =G19/G20 -> 4.8601179 | H21: =H19/H20 -> 5.3137332 | I21: =I19/I20 -> 6.2032424 | J21: =J19/J20 -> 8.2396204 | ... R21: =R19/R20 -> #DIV/0! | T21: =T19/T20 -> 8.6341645 | U21: =U19/U20 -> 15.1892 | V21: =V19/V20 -> 24.609313 | W21: =W19/W20 -> 23.947327 | X21: =X19/X20 -> #DIV/0!
B23: Gross Margin | C23: =C10/C8 -> 0.78676907 | D23: =D10/D8 -> 0.81421294 | E23: =E10/E8 -> 0.8181339 | F23: =F10/F8 -> 0.80815736 | G23: =G10/G8 -> 0.81785763 | H23: =H10/H8 -> 0.8129559 | I23: =I10/I8 -> 0.81830052 | J23: =J10/J8 -> 0.81731942 | ... R23: =R10/R8 -> #DIV/0! | T23: =T10/T8 -> 0.78347297 | U23: =U10/U8 -> 0.80757741 | V23: =V10/V8 -> 0.81664438 | W23: =W10/W8 -> 0.81999851 | X23: =X10/X8 -> 1
B24: Operating Margin | C24: =C15/C8 -> 0.25229534 | D24: =D15/D8 -> 0.29350917 | E24: =E15/E8 -> 0.40262403 | F24: =F15/F8 -> 0.40846651 | G24: =G15/G8 -> 0.37904266 | H24: =H15/H8 -> 0.38000051 | I24: =I15/I8 -> 0.42745571 | J24: =J15/J8 -> 0.48289759 | ... R24: =R15/R8 -> #DIV/0! | T24: =T15/T8 -> 0.24821412 | U24: =U15/U8 -> 0.34655785 | V24: =V15/V8 -> 0.42176292 | W24: =W15/W8 -> 0.41438061 | X24: =X15/X8 -> 1
B25: Net Margin | C25: =C19/C8 -> 0.1993018 | D25: =D19/D8 -> 0.24338261 | E25: =E19/E8 -> 0.33921982 | F25: =F19/F8 -> 0.34945526 | G25: =G19/G8 -> 0.33929502 | H25: =H19/H8 -> 0.34462901 | I25: =I19/I8 -> 0.38650866 | J25: =J19/J8 -> 0.43067066 | ... R25: =R19/R8 -> #DIV/0! | T25: =T19/T8 -> 0.19895548 | U25: =U19/U8 -> 0.28981994 | V25: =V19/V8 -> 0.37908815 | W25: =W19/W8 -> 0.30088324 | X25: =X19/X8 -> 1
B26: Tax Margin | C26: =C18/C17 -> 0.2186944 | D26: =D18/D17 -> 0.16194985 | E26: =E18/E17 -> 0.17382311 | F26: =F18/F17 -> 0.16605188 | G26: =G18/G17 -> 0.1278996 | H26: =H18/H17 -> 0.10863233 | I26: =I18/I17 -> 0.11973965 | J26: =J18/J17 -> 0.11527194 | ... R26: =R18/R17 -> #DIV/0! | T26: =T18/T17 -> 0.19497554 | U26: =U18/U17 -> 0.17565573 | V26: =V18/V17 -> 0.11751387 | W26: =W18/W17 -> 0.29634715 | X26: =X18/X17 -> 0
B27: SG&A Margin | C27: =(C12+C13)/C10 -> 0.26307849 | D27: =(D12+D13)/D10 -> 0.28087818 | E27: =(E12+E13)/E10 -> 0.17708333 | F27: =(F12+F13)/F10 -> 0.17013203 | G27: =(G12+G13)/G10 -> 0.20187825 | H27: =(H12+H13)/H10 -> 0.20083116 | I27: =(I12+I13)/I10 -> 0.14111519 | J27: =(J12+J13)/J10 -> 0.10117332 | ... R27: =(R12+R13)/R10 -> #DIV/0! | T27: =(T12+T13)/T10 -> 0.29638792 | U27: =(U12+U13)/U10 -> 0.21762757 | V27: =(V12+V13)/V10 -> 0.15696229 | W27: =(W12+W13)/W10 -> 0.14650679 | X27: =(X12+X13)/X10 -> 0 | AF27: Change | AG27: =#REF!/Main!F15-1 -> #REF!
B28: R&D Margin | C28: =C11/C10 -> 0.41624884 | D28: =D11/D10 -> 0.35863975 | E28: =E11/E10 -> 0.33079181 | F28: =F11/F10 -> 0.32443855 | G28: =G11/G10 -> 0.33466376 | H28: =H11/H10 -> 0.33173819 | I28: =I11/I10 -> 0.33651472 | J28: =J11/J10 -> 0.30799575 | ... R28: =R11/R10 -> #DIV/0! | T28: =T11/T10 -> 0.38679947 | U28: =U11/U10 -> 0.35323977 | V28: =V11/V10 -> 0.32657923 | W28: =W11/W10 -> 0.34815008 | X28: =X11/X10 -> 0
B30: Revenue y/y | G30: =G8/C8-1 -> 0.27264793 | H30: =H8/D8-1 -> 0.22100691 | I30: =I8/E8-1 -> 0.18868974 | J30: =J8/F8-1 -> 0.20627758 | K30: =K8/G8-1 -> 0.16071869 | L30: =L8/H8-1 -> 0.21614497 | M30: =M8/I8-1 -> 0.26246027 | N30: =N8/J8-1 -> 0.23784231 | ... R30: =R8/N8-1 -> -1 | U30: =U8/T8-1 -> 0.15686611 | V30: =V8/U8-1 -> 0.21941275 | W30: =W8/V8-1 -> 0.22167173 | X30: =X8/W8-1 -> 0.062025726 | AF30: Maturity | AG30: 0.04
AF31: Discount Rate | AG31: 0.0775
B33: Net Cash | F33: =F34-F45 -> 53159 | G33: =G34-G45 -> 45951 | H33: =H34-H45 -> 45898 | I33: =I34-I45 -> 48148 | J33: =J34-J45 -> 55059 | K33: =K34-K45 -> 47569 | L33: =L34-L45 -> 40227 | M33: =M34-M45 -> 40688 | ... P33: =P34-P45 -> 0 | U33: =U34-U45 -> 53159 | V33: =V34-V45 -> 55059 | W33: =W34-W45 -> 50372 | X33: =X34-X45 -> 0 | Y33: =Y34-Y45 -> 0
B34: Cash | F34: =41862+23541+6141 -> 71544 | G34: =32307+25813+6218 -> 64338 | H34: =32045+26035+6207 -> 64287 | I34: =43852+27048+6071 -> 76971 | J34: =43889+33926+6070 -> 83885 | K34: =28750+41480+6168 -> 76398 | L34: =12005+35066+21988 -> 69059 | M34: =10187+34261+25074 -> 69522 | N34: =35873+45719+27524 -> 109116 | U34: =41862+23541+6141 -> 71544 | V34: =43889+33926+6070 -> 83885 | W34: =35873+45719+27524 -> 109116
B35: A/R | F35: 16169 | G35: 13430 | H35: 14505 | I35: 14700 | J35: 16994 | K35: 14514 | L35: 16561 | M35: 17297 | N35: 19769 | U35: 16169 | V35: 16994 | W35: 19769
B36: Prepaids | F36: 3793 | G36: 3780 | H36: 3846 | I36: 5467 | J36: 5236 | K36: 5483 | L36: 9981 | M36: 11373 | N36: 7361 | U36: 3793 | V36: 5236 | W36: 7361
B37: PP&A | F37: 96587 | G37: 98908 | H37: 102959 | I37: 112162 | J37: 121346 | K37: 133567 | L37: 147039 | M37: 160270 | N37: 176400 | U37: 96587 | V37: 121346 | W37: 176400
B38: Lease ROU | F38: 13294 | G38: 13555 | H38: 14058 | I38: 14812 | J38: 14922 | K38: 15505 | L38: 15662 | M38: 17372 | N38: 20404 | U38: 13294 | V38: 14922 | W38: 20404
B39: Goodwill | F39: 20654 | G39: 20654 | H39: 20654 | I39: 20654 | J39: 20654 | K39: 20654 | L39: 20654 | M39: 21158 | N39: 24534 | U39: 20654 | V39: 20654 | W39: 24534
B40: Other assets | F40: 7582 | G40: 8179 | H40: 9929 | I40: 11642 | J40: 13017 | K40: 14092 | L40: 15788 | M40: 6852 | N40: 8437 | U40: 7582 | V40: 13017 | W40: 8437
B41: Total Assets | F41: =SUM(F34:F40) -> 229623 | G41: =SUM(G34:G40) -> 222844 | H41: =SUM(H34:H40) -> 230238 | I41: =SUM(I34:I40) -> 256408 | J41: =SUM(J34:J40) -> 276054 | K41: =SUM(K34:K40) -> 280213 | L41: =SUM(L34:L40) -> 294744 | M41: =SUM(M34:M40) -> 303844 | ... P41: =SUM(P34:P40) -> 0 | U41: =SUM(U34:U40) -> 229623 | V41: =SUM(V34:V40) -> 276054 | W41: =SUM(W34:W40) -> 366021 | X41: =SUM(X34:X40) -> 0 | Y41: =SUM(Y34:Y40) -> 0
B42: A/P | F42: 4849 | G42: 3785 | H42: 3173 | I42: 7656 | J42: 7687 | K42: 8512 | L42: 10271 | M42: 7798 | N42: 8894 | U42: 4849 | V42: 7687 | W42: 8894
B43: Lease | F43: =1623+17226 -> 18849 | G43: =1676+17570 -> 19246 | H43: =1917+17685 -> 19602 | I43: =2016+18208 -> 20224 | J43: =1942+18292 -> 20234 | K43: =1976+18714 -> 20690 | L43: =1977+18751 -> 20728 | M43: =2113+20113 -> 22226 | N43: =2213+22940 -> 25153 | U43: =1623+17226 -> 18849 | V43: =1942+18292 -> 20234 | W43: =2213+22940 -> 25153
B44: OCL | F44: 25488 | G44: 22640 | H44: 21914 | I44: 23658 | J44: 23967 | K44: 23402 | L44: 25057 | M44: 27047 | N44: 30729 | U44: 25488 | V44: 23967 | W44: 30729
B45: Debt | F45: 18385 | G45: 18387 | H45: 18389 | I45: 28823 | J45: 28826 | K45: 28829 | L45: 28832 | M45: 28834 | N45: 58744 | U45: 18385 | V45: 28826 | W45: 58744
B46: Taxes | F46: 7514 | G46: 7795 | H46: 7897 | I46: 9171 | J46: 9987 | K46: 10991 | L46: 12046 | M46: 11738 | N46: 21005 | U46: 7514 | V46: 9987 | W46: 21005
B47: ONCL | F47: 1370 | G47: 1462 | H47: 2500 | I47: 2347 | J47: 2716 | K47: 2760 | L47: 2740 | M47: 12135 | N47: 4253 | U47: 1370 | V47: 2716 | W47: 4253
B48: Total Liabilities | F48: =SUM(F42:F47) -> 76455 | G48: =SUM(G42:G47) -> 73315 | H48: =SUM(H42:H47) -> 73475 | I48: =SUM(I42:I47) -> 91879 | J48: =SUM(J42:J47) -> 93417 | K48: =SUM(K42:K47) -> 95184 | L48: =SUM(L42:L47) -> 99674 | M48: =SUM(M42:M47) -> 109778 | ... P48: =SUM(P42:P47) -> 0 | U48: =SUM(U42:U47) -> 76455 | V48: =SUM(V42:V47) -> 93417 | W48: =SUM(W42:W47) -> 148778 | X48: =SUM(X42:X47) -> 0 | Y48: =SUM(Y42:Y47) -> 0
B49: SE | F49: 153168 | G49: 149529 | H49: 156763 | I49: 164529 | J49: 182637 | K49: 185029 | L49: 195070 | M49: 194066 | N49: 217243 | U49: 153168 | V49: 182637 | W49: 217243
B50: L+SE | F50: =F48+F49 -> 229623 | G50: =G48+G49 -> 222844 | H50: =H48+H49 -> 230238 | I50: =I48+I49 -> 256408 | J50: =J48+J49 -> 276054 | K50: =K48+K49 -> 280213 | L50: =L48+L49 -> 294744 | M50: =M48+M49 -> 303844 | ... P50: =P48+P49 -> 0 | U50: =U48+U49 -> 229623 | V50: =V48+V49 -> 276054 | W50: =W48+W49 -> 366021 | X50: =X48+X49 -> 0 | Y50: =Y48+Y49 -> 0
B52: PP&A Q/Q | G52: =G37/F37-1 -> 0.024030149 | H52: =H37/G37-1 -> 0.040957253 | I52: =I37/H37-1 -> 0.089385095 | J52: =J37/I37-1 -> 0.081881564 | K52: =K37/J37-1 -> 0.10071201 | L52: =L37/K37-1 -> 0.10086324 | M52: =M37/L37-1 -> 0.08998293 | N52: =N37/M37-1 -> 0.10064267 | ... P52: =P37/O37-1 -> #DIV/0!
B53: Net Working Capital | G53: =(G34+G35+G36)-(G42+G43+G44) -> 35877 | H53: =(H34+H35+H36)-(H42+H43+H44) -> 37949 | I53: =(I34+I35+I36)-(I42+I43+I44) -> 45600 | J53: =(J34+J35+J36)-(J42+J43+J44) -> 54227 | K53: =(K34+K35+K36)-(K42+K43+K44) -> 43791 | L53: =(L34+L35+L36)-(L42+L43+L44) -> 39545 | M53: =(M34+M35+M36)-(M42+M43+M44) -> 41121 | N53: =(N34+N35+N36)-(N42+N43+N44) -> 71470 | ... P53: =(P34+P35+P36)-(P42+P43+P44) -> 0
B55: Model NI | C55: =C19 -> 5709 | D55: =D19 -> 7788 | E55: =E19 -> 11583 | F55: =F19 -> 14017 | G55: =G19 -> 12369 | H55: =H19 -> 13465 | I55: =I19 -> 15688 | J55: =J19 -> 20838 | ... R55: =R19 -> 0 | T55: =T19 -> 23200 | U55: =U19 -> 39097 | V55: =V19 -> 62360 | W55: =W19 -> 60467 | X55: =X19 -> 213430
B56: GAAP NI | C56: 5709 | D56: 7788 | E56: 11583 | F56: 14017 | G56: 12369 | H56: 13465 | I56: 15688 | J56: 20838 | K56: 16644 | L56: 18337 | M56: 2709 | N56: 22768 | T56: 23200 | U56: =SUM(C56:F56) -> 39097 | V56: =SUM(G56:J56) -> 62360 | W56: =SUM(K56:N56) -> 60458
B57: D&A | C57: 2524 | D57: 2623 | E57: 2858 | F57: 3172 | G57: 3374 | H57: 3637 | I57: 4027 | J57: 4460 | K57: 3900 | L57: 4342 | M57: 4963 | N57: 5411 | T57: 8686 | U57: =SUM(C57:F57) -> 11177 | V57: =SUM(G57:J57) -> 15498 | W57: =SUM(K57:N57) -> 18616
B58: Stock compensation | C58: 3051 | D58: 4060 | E58: 3492 | F58: 3424 | G58: 3562 | H58: 4616 | I58: 4250 | J58: 4262 | K58: 4147 | L58: 4834 | M58: 5555 | N58: 5890 | T58: 11992 | U58: =SUM(C58:F58) -> 14027 | V58: =SUM(G58:J58) -> 16690 | W58: =SUM(K58:N58) -> 20426
B59: Deferred income taxes | C59: -620 | D59: -1137 | E59: 3049 | F59: -1161 | G59: -456 | H59: -1643 | I59: -1308 | J59: -1332 | K59: -993 | L59: -1170 | M59: 19868 | N59: 1033 | T59: -3286 | U59: =SUM(C59:F59) -> 131 | V59: =SUM(G59:J59) -> -4739 | W59: =SUM(K59:N59) -> 18738
B60: Impairments | C60: 770 | D60: 232 | E60: 340 | F60: 1091 | G60: 240 | H60: 41 | I60: 8 | J60: 94 | L60: 511 | T60: 2218 | U60: =SUM(C60:F60) -> 2433 | V60: =SUM(G60:J60) -> 383 | W60: =SUM(K60:N60) -> 511
B61: Data Center abandonment | F61: 7 | T61: 1341 | U61: =SUM(C61:F61) -> 7
B62: Other | C62: -7 | D62: 212 | E62: 75 | F62: 124 | G62: -66 | H62: -6 | I62: -11 | J62: 169 | K62: -231 | L62: -336 | M62: =-922-23 -> -945 | N62: =-496-56 -> -552 | T62: 641 | U62: =SUM(C62:F62) -> 404 | V62: =SUM(G62:J62) -> 86 | W62: =SUM(K62:N62) -> -2064
B63: A/R | C63: 2546 | D63: -1424 | E63: -678 | F63: -2843 | G63: 2520 | H63: -1171 | I63: 143 | J63: -2978 | K63: 2804 | L63: -1338 | M63: -807 | N63: -2475 | T63: 231 | U63: =SUM(C63:F63) -> -2399 | V63: =SUM(G63:J63) -> -1486 | W63: =SUM(K63:N63) -> -1816
B64: Prepaids | C64: 821 | D64: -54 | E64: -907 | F64: 700 | G64: 100 | H64: -84 | I64: -184 | J64: -530 | K64: 360 | L64: 326 | M64: -1033 | N64: 259 | T64: 162 | U64: =SUM(C64:F64) -> 560 | V64: =SUM(G64:J64) -> -698 | W64: =SUM(K64:N64) -> -88
B65: Other Assets | C65: 30 | D65: 37 | E65: -36 | F65: -111 | G65: -94 | H65: 54 | I65: -29 | J65: -200 | K65: -52 | L65: -190 | M65: 33 | N65: -272 | T65: -106 | U65: =SUM(C65:F65) -> -80 | V65: =SUM(G65:J65) -> -269 | W65: =SUM(K65:N65) -> -481
B66: A/P | C66: -1104 | D66: -51 | E66: 611 | F66: 595 | G66: -1112 | H66: 250 | I66: 667 | J66: 568 | K66: -1034 | L66: 460 | M66: -63 | N66: 623 | T66: 210 | U66: =SUM(C66:F66) -> 51 | V66: =SUM(G66:J66) -> 373 | W66: =SUM(K66:N66) -> -14
B67: OCL | C67: 94 | D67: 5174 | E67: 87 | F67: -274 | G67: -1274 | H67: -497 | I67: 572 | J67: 1523 | K67: -2231 | L67: -1107 | M67: 455 | N67: 3960 | T67: 4300 | U67: =SUM(C67:F67) -> 5081 | V67: =SUM(G67:J67) -> 324 | W67: =SUM(K67:N67) -> 1077
B68: ONCL | C68: 184 | D68: -151 | E68: -72 | F68: 663 | G68: 83 | H68: 708 | I68: 901 | J68: 1114 | K68: 712 | L68: 892 | M68: -736 | N68: -431 | T68: 886 | U68: =SUM(C68:F68) -> 624 | V68: =SUM(G68:J68) -> 2806 | W68: =SUM(K68:N68) -> 437
B69: CFFO | C69: =SUM(C56:C68) -> 13998 | D69: =SUM(D56:D68) -> 17309 | E69: =SUM(E56:E68) -> 20402 | F69: =SUM(F56:F68) -> 19404 | G69: =SUM(G56:G68) -> 19246 | H69: =SUM(H56:H68) -> 19370 | I69: =SUM(I56:I68) -> 24724 | J69: =SUM(J56:J68) -> 27988 | ... R69: =SUM(R56:R68) -> 0 | T69: =SUM(T56:T68) -> 50475 | U69: =SUM(U56:U68) -> 71113 | V69: =SUM(V56:V68) -> 91328 | W69: =SUM(W56:W68) -> 115800 | X69: =SUM(X56:X68) -> 0
B70: CapEx | C70: -6823 | D70: -6134 | E70: -6496 | F70: -7592 | G70: -6400 | H70: -8173 | I70: -8258 | J70: -14425 | K70: -12941 | L70: -16538 | M70: -18829 | N70: -21383 | T70: -31186 | U70: =SUM(C70:F70) -> -27045 | V70: =SUM(G70:J70) -> -37256 | W70: =SUM(K70:N70) -> -69691
B71: Securities | C71: =-85+534 -> 449 | D71: =-717+1816 -> 1099 | E71: =-1008+1475 -> 467 | F71: =-1171+2359 -> 1188 | G71: =-6887+4625 -> -2262 | H71: =-3289+3233 -> -56 | I71: =-4468+4114 -> -354 | J71: =-10898+3817 -> -7081 | K71: =-11763+4784 -> -6979 | L71: =-7746+14273-15114 -> -8587 | M71: =-2840+4704-3046 -> -1182 | N71: =-14580+3113 -> -11467 | T71: =-9626+13158 -> 3532 | U71: =SUM(C71:F71) -> 3203 | V71: =SUM(G71:J71) -> -9753 | W71: =SUM(K71:N71) -> -28215
B72: Acquisitions | C72: -444 | D72: -83 | E72: -38 | F72: -64 | G72: -72 | H72: -57 | I72: -132 | J72: -9 | L72: -61 | M72: -753 | N72: -3415 | T72: -1312 | U72: =SUM(C72:F72) -> -629 | V72: =SUM(G72:J72) -> -270 | W72: =SUM(K72:N72) -> -4229
B73: Other | C73: 75 | D73: -85 | E73: -10 | F73: -4 | H73: -12 | I73: 124 | J73: 17 | K73: -90 | L73: =-775+3 -> -772 | M73: =-62-1022 -> -1084 | N73: =-635+2554-70+229 -> 2078 | T73: -4 | U73: =SUM(C73:F73) -> -24 | V73: =SUM(G73:J73) -> 129 | W73: =SUM(K73:N73) -> 132
B74: CFFI | C74: =SUM(C70:C73) -> -6743 | D74: =SUM(D70:D73) -> -5203 | E74: =SUM(E70:E73) -> -6077 | F74: =SUM(F70:F73) -> -6472 | G74: =SUM(G70:G73) -> -8734 | H74: =SUM(H70:H73) -> -8298 | I74: =SUM(I70:I73) -> -8620 | J74: =SUM(J70:J73) -> -21498 | ... R74: =SUM(R70:R73) -> 0 | T74: =SUM(T70:T73) -> -28970 | U74: =SUM(U70:U73) -> -24495 | V74: =SUM(V70:V73) -> -47150 | W74: =SUM(W70:W73) -> -102003 | X74: =SUM(X70:X73) -> 0
B75: Taxes paid | C75: -1009 | D75: -1692 | E75: -2087 | F75: -2223 | G75: -3162 | H75: -3208 | I75: -3544 | J75: -3857 | K75: -4883 | L75: -4110 | M75: -5135 | N75: -4272 | T75: -3595 | U75: =SUM(C75:F75) -> -7011 | V75: =SUM(G75:J75) -> -13771 | W75: =SUM(K75:N75) -> -18400
B76: Buybacks | C76: -9365 | D76: -898 | E76: -3570 | F76: -5942 | G76: -15008 | H76: -6299 | I76: -8818 | K76: -12754 | L76: -10167 | M76: -3327 | T76: -27956 | U76: =SUM(C76:F76) -> -19775 | V76: =SUM(G76:J76) -> -30125 | W76: =SUM(K76:N76) -> -26248
B77: Dividends | G77: -1273 | H77: -1266 | I77: -1263 | J77: -1269 | K77: -1329 | L77: -1327 | M77: -1330 | N77: -1338 | V77: =SUM(G77:J77) -> -5071 | W77: =SUM(K77:N77) -> -5324
B78: Debt issuance | D78: 8455 | I78: 10432 | N78: 29906 | T78: 9921 | U78: =SUM(C78:F78) -> 8455 | V78: =SUM(G78:J78) -> 10432 | W78: =SUM(K78:N78) -> 29906
B79: Principal on lease | C79: -264 | D79: -220 | E79: -267 | F79: -307 | G79: -315 | H79: -299 | I79: -944 | J79: -411 | K79: -751 | L79: -474 | M79: -545 | N79: -754 | T79: -850 | U79: =SUM(C79:F79) -> -1058 | V79: =SUM(G79:J79) -> -1969 | W79: =SUM(K79:N79) -> -2524
B80: Other | C80: 122 | D80: -353 | E80: 49 | F80: 71 | G80: -9 | H80: -106 | I80: -234 | J80: 72 | K80: 222 | L80: 101 | M80: 290 | N80: 1607 | T80: 344 | U80: =SUM(C80:F80) -> -111 | V80: =SUM(G80:J80) -> -277 | W80: =SUM(K80:N80) -> 2220
B81: CFFF | C81: =SUM(C75:C80) -> -10516 | D81: =SUM(D75:D80) -> 5292 | E81: =SUM(E75:E80) -> -5875 | F81: =SUM(F75:F80) -> -8401 | G81: =SUM(G75:G80) -> -19767 | H81: =SUM(H75:H80) -> -11178 | I81: =SUM(I75:I80) -> -4371 | J81: =SUM(J75:J80) -> -5465 | ... R81: =SUM(R75:R80) -> 0 | T81: =SUM(T75:T80) -> -22136 | U81: =SUM(U75:U80) -> -19500 | V81: =SUM(V75:V80) -> -40781 | W81: =SUM(W75:W80) -> -20370 | X81: =SUM(X75:X80) -> 0
B82: Currency adj | C82: 85 | D82: -14 | E82: -354 | F82: 396 | G82: -288 | H82: -152 | I82: 368 | J82: -714 | K82: 112 | L82: 131 | M82: 9 | N82: -17 | T82: -638 | U82: =SUM(C82:F82) -> 113 | V82: =SUM(G82:J82) -> -786 | W82: =SUM(K82:N82) -> 235
B83: CF | C83: =C69+C74+C81+C82 -> -3176 | D83: =D69+D74+D81+D82 -> 17384 | E83: =E69+E74+E81+E82 -> 8096 | F83: =F69+F74+F81+F82 -> 4927 | G83: =G69+G74+G81+G82 -> -9543 | H83: =H69+H74+H81+H82 -> -258 | I83: =I69+I74+I81+I82 -> 12101 | J83: =J69+J74+J81+J82 -> 311 | ... R83: =R69+R74+R81+R82 -> 0 | T83: =T69+T74+T81+T82 -> -1269 | U83: =U69+U74+U81+U82 -> 27231 | V83: =V69+V74+V81+V82 -> 2611 | W83: =W69+W74+W81+W82 -> -6338 | X83: =X69+X74+X81+X82 -> 0
B84: BOP Cash | C84: =C85-C83 -> 15596 | D84: =D85-D83 -> 12420 | E84: =E85-E83 -> 29804 | F84: =F85-F83 -> 37900 | G84: =G85-G83 -> 42827 | H84: =H85-H83 -> 33284 | I84: =I85-I83 -> 33026 | J84: =J85-J83 -> 45127 | K84: =K85-K83 -> 45438 | L84: 30071 | M84: 30071 | N84: 30071 | O84: 30071 | P84: 30071 | Q84: 30071 | R84: 30071
B85: EOP Cash | C85: =+D84 -> 12420 | D85: =+E84 -> 29804 | E85: =+F84 -> 37900 | F85: =+G84 -> 42827 | G85: =+H84 -> 33284 | H85: =+I84 -> 33026 | I85: =+J84 -> 45127 | J85: =+K84 -> 45438 | K85: =+L84 -> 30071 | L85: =L83+L84 -> 13828 | M85: =M83+M84 -> 28184 | N85: =N83+N84 -> 57230 | O85: =O83+O84 -> 30071 | P85: =P83+P84 -> 30071 | Q85: =Q83+Q84 -> 30071 | R85: =R83+R84 -> 30071
B88: FCF | C88: =C69+C70 -> 7175 | D88: =D69+D70 -> 11175 | E88: =E69+E70 -> 13906 | F88: =F69+F70 -> 11812 | G88: =G69+G70 -> 12846 | H88: =H69+H70 -> 11197 | I88: =I69+I70 -> 16466 | J88: =J69+J70 -> 13563 | ... R88: =R69+R70 -> 0 | T88: =T69+T70 -> 19289 | U88: =U69+U70 -> 44068 | V88: =V69+V70 -> 54072 | W88: =W69+W70 -> 46109 | X88: =X69+X70 -> 0
B89: Capex Margin | C89: =-C70/C55 -> 1.1951305 | D89: =-D70/D55 -> 0.78762198 | E89: =-E70/E55 -> 0.56082189 | F89: =-F70/F55 -> 0.54162802 | G89: =-G70/G55 -> 0.51742259 | H89: =-H70/H55 -> 0.60698106 | I89: =-I70/I55 -> 0.5263896 | J89: =-J70/J55 -> 0.69224494 | ... R89: =-R70/R55 -> #DIV/0! | T89: =-T70/T55 -> 1.3442241 | U89: =-U70/U55 -> 0.69174105 | V89: =-V70/V55 -> 0.59743425 | W89: =-W70/W55 -> 1.152546 | X89: =-X70/X55 -> 0
B90: FCF Margin | C90: =C88/C8 -> 0.25048001 | D90: =D88/D8 -> 0.34922966 | E90: =E88/E8 -> 0.40725122 | F90: =F88/F8 -> 0.29448281 | G90: =G88/G8 -> 0.35237965 | H90: =H88/H8 -> 0.28658084 | I90: =I88/I8 -> 0.40567641 | J90: =J88/J8 -> 0.28031415 | ... R90: =R88/R8 -> #DIV/0! | T90: =T88/T8 -> 0.16541605 | U90: =U88/U8 -> 0.32666919 | V90: =V88/V8 -> 0.32870517 | W90: =W88/W8 -> 0.22943796 | X90: =X88/X8 -> 0
B92: Headcount | N92: 78865 | T92: 2025 CapEx+Principal on lease guidance | W92: 64-72B | X92: Full‑year 2026 CapEx guidance: $115B–$135B, representing a major step‑up.
X93: Driven primarily by:
B95: Quorter highlights: | M95: 3.5B daily active people across apps. | O95: Reach & Engagement | X95: AI infrastructure expansion
M96: Instagram: 3B MAUs; Video time spent +30% YoY. | X96: Investments to support Meta Superintelligence Labs (MSL)
M97: Threads: 150M daily actives (DAUs), Time spent +10%. | O97: 3.5B daily active people across Meta’s Family of Apps. | X97: Continued support for core business compute needs (ranking, recommendations, ads systems)
M98: Facebook: Time spent +5% in Q3 due to AI recs. | O98: Meta AI: Available in 200+ markets, DAU engagement varies by region; usage driven mainly by WhatsApp in India/Indonesia and Facebook in the U.S.
M99: Meta AI: >1B MAUs;
M100: Reels: Annual run rate (ARR) >$50B.
M101: AI ad tools: ARR >$60B;

Sheet MSFT
A1: Main | AD1: 44742 | AF1: 44926 | AH1: 45107 | AJ1: 45291 | AL1: 45473 | AN1: 45657
C2: Q116 | D2: Q216 | E2: Q316 | F2: Q416 | G2: Q117 | H2: Q217 | I2: Q317 | J2: Q417 | K2: Q118 | L2: Q218 | M2: Q318 | N2: Q418 | O2: Q119 | P2: Q219 | Q2: Q319 | R2: Q419 | S2: Q120 | T2: Q220 | U2: Q320 | V2: Q420 | W2: Q121 | X2: Q221 | Y2: Q321 | Z2: Q421 | AA2: Q122 | AB2: Q222 | AC2: Q322 | AD2: Q422 | AE2: Q123 | AF2: Q223 | AG2: Q323 | AH2: Q423 | AI2: Q124 | AJ2: Q224 | AK2: Q324 | AL2: Q424 | AM2: Q125 | AN2: Q225 | AO2: Q325 | AP2: Q425 | AQ2: Q126 | AR2: Q226 | AS2: Q326 | AV2: FY16 | AW2: FY17 | AX2: FY18 | AY2: FY19 | AZ2: FY20 | BA2: FY21 | BB2: FY22 | BC2: FY23 | BD2: FY24 | BE2: FY25 | BF2: FY26 | BG2: FY27 | BH2: FY28 | BI2: FY29 | BJ2: FY30 | BK2: FY31 | BL2: FY32 | BM2: FY33 | BN2: FY34 | BO2: FY35 | BP2: FY36 | BQ2: FY37 | BR2: FY38 | BS2: FY39 | BT2: FY40 | BU2: FY41 | BV2: FY42 | BW2: FY43 | BX2: FY44 | BY2: FY45 | BZ2: FY46 | CA2: FY47 | CB2: FY48 | CC2: FY49 | CD2: FY50 | CE2: FY51 | CF2: FY52 | CG2: FY53 | CH2: FY54 | CI2: FY55 | CJ2: FY56 | CK2: FY57 | CL2: FY58 | CM2: FY59 | CN2: FY60 | CO2: FY61 | CP2: FY62 | CQ2: FY63 | CR2: FY64 | CS2: FY65 | CT2: FY66 | CU2: FY67 | CV2: FY68 | CW2: FY69 | CX2: FY70 | CY2: FY71 | CZ2: FY72 | DA2: FY73 | DB2: FY74 | DC2: FY75 | DD2: FY76 | DE2: FY77 | DF2: FY78 | DG2: FY79 | DH2: FY80 | DI2: FY81 | DJ2: FY82 | DK2: FY83 | DL2: FY84 | DM2: FY85 | DN2: FY86 | DO2: FY87 | DP2: FY88 | DQ2: FY89 | DR2: FY90 | DS2: FY91 | DT2: FY92 | DU2: FY93 | DV2: FY94 | DW2: FY95 | DX2: FY96 | DY2: FY97 | DZ2: FY98 | EA2: FY99 | EB2: FY100 | EC2: FY101 | ED2: FY102 | EE2: FY103 | EF2: FY104 | EG2: FY105 | EH2: FY106 | EI2: FY107 | EJ2: FY108 | EK2: FY109 | EL2: FY110 | EM2: FY111 | EN2: FY112 | EO2: FY113 | EP2: FY114 | EQ2: FY115 | ER2: FY116 | ES2: FY117 | ET2: FY118 | EU2: FY119 | EV2: FY120 | EW2: FY121 | EX2: FY122 | EY2: FY123 | EZ2: FY124 | FA2: FY125 | FB2: FY126 | FC2: FY127 | FD2: FY128 | FE2: FY129 | FF2: FY130 | FG2: FY131 | FH2: FY132 | FI2: FY133 | FJ2: FY134 | FK2: FY135 | FL2: FY136 | FM2: FY137 | FN2: FY138 | FO2: FY139 | FP2: FY140 | FQ2: FY141 | FR2: FY142 | FS2: FY143 | FT2: FY144 | FU2: FY145 | FV2: FY146 | FW2: FY147 | FX2: FY148 | FY2: FY149 | FZ2: FY150 | GA2: FY151 | GB2: FY152 | GC2: FY153 | GD2: FY154 | GE2: FY155 | GF2: FY156 | GG2: FY157 | GH2: FY158 | GI2: FY159 | GJ2: FY160 | GK2: FY161 | GL2: FY162 | GM2: FY163 | GN2: FY164 | GO2: FY165 | GP2: FY166 | GQ2: FY167 | GR2: FY168 | GS2: FY169 | GT2: FY170 | GU2: FY171 | GV2: FY172 | GW2: FY173 | GX2: FY174 | GY2: FY175 | GZ2: FY176 | HA2: FY177 | HB2: FY178 | HC2: FY179 | HD2: FY180 | HE2: FY181 | HF2: FY182 | HG2: FY183 | HH2: FY184 | HI2: FY185 | HJ2: FY186 | HK2: FY187 | HL2: FY188 | HM2: FY189 | HN2: FY190 | HO2: FY191 | HP2: FY192 | HQ2: FY193 | HR2: FY194 | HS2: FY195 | HT2: FY196 | HU2: FY197 | HV2: FY198 | HW2: FY199 | HX2: FY200 | HY2: FY201 | HZ2: FY202 | IA2: FY203 | IB2: FY204 | IC2: FY205 | ID2: FY206 | IE2: FY207 | IF2: FY208 | IG2: FY209 | IH2: FY210 | II2: FY211 | IJ2: FY212 | IK2: FY213 | IL2: FY214 | IM2: FY215 | IN2: FY216 | IO2: FY217 | IP2: FY218 | IQ2: FY219 | IR2: FY220 | IS2: FY221 | IT2: FY222 | IU2: FY223 | IV2: FY224 | IW2: FY225 | IX2: FY226 | IY2: FY227 | IZ2: FY228 | JA2: FY229 | JB2: FY230 | JC2: FY231 | JD2: FY232 | JE2: FY233 | JF2: FY234 | JG2: FY235 | JH2: FY236 | JI2: FY237 | JJ2: FY238 | JK2: FY239 | JL2: FY240 | JM2: FY241 | JN2: FY242 | JO2: FY243 | JP2: FY244 | JQ2: FY245 | JR2: FY246 | JS2: FY247 | JT2: FY248 | JU2: FY249 | JV2: FY250 | JW2: FY251 | JX2: FY252 | JY2: FY253 | JZ2: FY254 | KA2: FY255 | KB2: FY256 | KC2: FY257 | KD2: FY258 | KE2: FY259 | KF2: FY260 | KG2: FY261 | KH2: FY262 | KI2: FY263 | KJ2: FY264 | KK2: FY265 | KL2: FY266 | KM2: FY267 | KN2: FY268 | KO2: FY269 | KP2: FY270 | KQ2: FY271 | KR2: FY272 | KS2: FY273 | KT2: FY274 | KU2: FY275 | KV2: FY276 | KW2: FY277 | KX2: FY278 | KY2: FY279 | KZ2: FY280 | LA2: FY281 | LB2: FY282 | LC2: FY283 | LD2: FY284 | LE2: FY285 | LF2: FY286 | LG2: FY287 | LH2: FY288 | LI2: FY289 | LJ2: FY290 | LK2: FY291 | LL2: FY292 | LM2: FY293 | LN2: FY294 | LO2: FY295 | LP2: FY296 | LQ2: FY297 | LR2: FY298 | LS2: FY299 | LT2: FY300 | LU2: FY301 | LV2: FY302 | LW2: FY303 | LX2: FY304 | LY2: FY305 | LZ2: FY306 | MA2: FY307 | MB2: FY308 | MC2: FY309 | MD2: FY310 | ME2: FY311 | MF2: FY312 | MG2: FY313 | MH2: FY314 | MI2: FY315 | MJ2: FY316 | MK2: FY317 | ML2: FY318 | MM2: FY319 | MN2: FY320 | MO2: FY321 | MP2: FY322 | MQ2: FY323 | MR2: FY324 | MS2: FY325 | MT2: FY326 | MU2: FY327 | MV2: FY328 | MW2: FY329 | MX2: FY330 | MY2: FY331 | MZ2: FY332 | NA2: FY333 | NB2: FY334 | NC2: FY335 | ND2: FY336 | NE2: FY337 | NF2: FY338 | NG2: FY339 | NH2: FY340 | NI2: FY341 | NJ2: FY342 | NK2: FY343 | NL2: FY344 | NM2: FY345 | NN2: FY346 | NO2: FY347 | NP2: FY348 | NQ2: FY349 | NR2: FY350 | NS2: FY351 | NT2: FY352 | NU2: FY353 | NV2: FY354 | NW2: FY355 | NX2: FY356 | NY2: FY357 | NZ2: FY358 | OA2: FY359 | OB2: FY360 | OC2: FY361 | OD2: FY362 | OE2: FY363 | OF2: FY364 | OG2: FY365 | OH2: FY366 | OI2: FY367 | OJ2: FY368 | OK2: FY369 | OL2: FY370 | OM2: FY371 | ON2: FY372 | OO2: FY373 | OP2: FY374 | OQ2: FY375 | OR2: FY376 | OS2: FY377 | OT2: FY378 | OU2: FY379 | OV2: FY380 | OW2: FY381 | OX2: FY382 | OY2: FY383 | OZ2: FY384 | PA2: FY385 | PB2: FY386 | PC2: FY387 | PD2: FY388 | PE2: FY389 | PF2: FY390 | PG2: FY391 | PH2: FY392 | PI2: FY393 | PJ2: FY394 | PK2: FY395 | PL2: FY396 | PM2: FY397 | PN2: FY398 | PO2: FY399 | PP2: FY400 | PQ2: FY401 | PR2: FY402 | PS2: FY403 | PT2: FY404 | PU2: FY405 | PV2: FY406 | PW2: FY407 | PX2: FY408 | PY2: FY409 | PZ2: FY410 | QA2: FY411 | QB2: FY412 | QC2: FY413 | QD2: FY414 | QE2: FY415 | QF2: FY416 | QG2: FY417 | QH2: FY418 | QI2: FY419 | QJ2: FY420 | QK2: FY421 | QL2: FY422 | QM2: FY423 | QN2: FY424 | QO2: FY425 | QP2: FY426 | QQ2: FY427 | QR2: FY428 | QS2: FY429 | QT2: FY430 | QU2: FY431 | QV2: FY432 | QW2: FY433 | QX2: FY434 | QY2: FY435 | QZ2: FY436 | RA2: FY437 | RB2: FY438 | RC2: FY439 | RD2: FY440 | RE2: FY441 | RF2: FY442 | RG2: FY443 | RH2: FY444 | RI2: FY445 | RJ2: FY446 | RK2: FY447 | RL2: FY448 | RM2: FY449 | RN2: FY450 | RO2: FY451 | RP2: FY452 | RQ2: FY453 | RR2: FY454 | RS2: FY455 | RT2: FY456 | RU2: FY457 | RV2: FY458 | RW2: FY459 | RX2: FY460 | RY2: FY461 | RZ2: FY462 | SA2: FY463 | SB2: FY464 | SC2: FY465 | SD2: FY466 | SE2: FY467 | SF2: FY468 | SG2: FY469 | SH2: FY470 | SI2: FY471 | SJ2: FY472 | SK2: FY473 | SL2: FY474 | SM2: FY475 | SN2: FY476 | SO2: FY477 | SP2: FY478 | SQ2: FY479 | SR2: FY480 | SS2: FY481 | ST2: FY482 | SU2: FY483 | SV2: FY484 | SW2: FY485 | SX2: FY486 | SY2: FY487 | SZ2: FY488 | TA2: FY489
B3: Server and cloud | AE3: 14948 | AF3: 16012 | AG3: 16187 | AH3: 17860 | AI3: 18062 | AJ3: 19597 | AK3: 20266 | AL3: 21903 | AM3: 22155 | AN3: 23641 | AO3: 24761 | AP3: 27878 | AQ3: 28872 | AR3: 30865 | BC3: 65007 | BD3: 79828 | BE3: =SUM(AM3:AP3) -> 98435
B4: MS 365 Commercial and cloud | AE4: 15502 | AF4: 15774 | AG4: 17195 | AH4: 18478 | AI4: 18044 | AJ4: 18321 | AK4: 19712 | AL4: 20892 | AM4: 20449 | AN4: 21117 | AO4: 21883 | AP4: 24318 | AQ4: 23966 | AR4: 24524 | BC4: 66949 | BD4: 76969 | BE4: =SUM(AM4:AP4) -> 87767
B5: Gaming | AE5: 3610 | AF5: 4758 | AG5: 3607 | AH5: 3491 | AI5: 3919 | AJ5: 7111 | AK5: 5451 | AL5: 5022 | AM5: 5621 | AN5: 6581 | AO5: 5721 | AP5: 5532 | AQ5: 5508 | AR5: 5958 | BB5: 16230 | BC5: 15466 | BD5: 21503 | BE5: =SUM(AM5:AP5) -> 23455
B6: LinkedIn | AE6: 3628 | AF6: 3833 | AG6: 3659 | AH6: 3869 | AI6: 3913 | AJ6: 4195 | AK6: 4013 | AL6: 4251 | AM6: 4292 | AN6: 4587 | AO6: 4311 | AP6: 4622 | AQ6: 4714 | AR6: 5082 | BB6: 13631 | BC6: 14989 | BD6: 16372 | BE6: =SUM(AM6:AP6) -> 17812
B7: Windows and Devices | AE7: 4593 | AF7: 4219 | AG7: 4040 | AH7: 4295 | AI7: 4340 | AJ7: 4363 | AK7: 4098 | AL7: 4225 | AM7: 4329 | AN7: 4512 | AO7: 4144 | AP7: 4329 | AQ7: 4551 | AR7: 4479 | BB7: =24732+7306 -> 32038 | BC7: 17147 | BD7: 17026 | BE7: =SUM(AM7:AP7) -> 17314
B8: Search and news ads | AE8: 2913 | AF8: 3209 | AG8: 3034 | AH8: 2969 | AI8: 3018 | AJ8: 3168 | AK8: 3055 | AL8: 3065 | AM8: 3225 | AN8: 3558 | AO8: 3504 | AP8: 3591 | AQ8: 3697 | AR8: 3812 | BB8: 11526 | BC8: 12125 | BD8: 12306 | BE8: =SUM(AM8:AP8) -> 13878
B9: Enterprise | AE9: 1929 | AF9: 1907 | AG9: 2047 | AH9: 2017 | AI9: 1944 | AJ9: 1917 | AK9: 1861 | AL9: 1872 | AM9: 1928 | AN9: 1892 | AO9: 1929 | AP9: 2136 | AQ9: 2204 | AR9: 2305 | BB9: 7605 | BC9: 7900 | BD9: 7594 | BE9: =SUM(AM9:AP9) -> 7885
B10: Dynamics and cloud | AE10: 1345 | AF10: 1391 | AG10: 1484 | AH10: 1576 | AI10: 1626 | AJ10: 1659 | AK10: 1740 | AL10: 1806 | AM10: 1849 | AN10: 1913 | AO10: 1946 | AP10: 1994 | AQ10: 2136 | AR10: 2204 | BB10: 4687 | BC10: 5796 | BD10: 6831 | BE10: =SUM(AM10:AP10) -> 7702
B11: MS 365 Consumer and cloud | AE11: 1599 | AF11: 1605 | AG11: 1586 | AH11: 1627 | AI11: 1643 | AJ11: 1679 | AK11: 1648 | AL11: 1678 | AM11: 1727 | AN11: 1821 | AO11: 1821 | AP11: 2035 | AQ11: 2022 | AR11: 2038 | BC11: 6417 | BD11: 6648 | BE11: =SUM(AM11:AP11) -> 7404
B12: Other | AE12: 55 | AF12: 39 | AG12: 18 | AH12: 7 | AI12: 8 | AJ12: 10 | AK12: 14 | AL12: 13 | AM12: 10 | AN12: 10 | AO12: 46 | AP12: 6 | AQ12: 3 | AR12: 6 | BB12: 45 | BC12: 119 | BD12: 45 | BE12: =SUM(AM12:AP12) -> 72
AX13: =SUM(AX3:AX12) -> 0 | AY13: =SUM(AY3:AY12) -> 0 | AZ13: =SUM(AZ3:AZ12) -> 0 | BA13: =SUM(BA3:BA12) -> 0 | BB13: =SUM(BB3:BB12) -> 85762 | BC13: =SUM(BC3:BC12) -> 211915 | BD13: =SUM(BD3:BD12) -> 245122 | BE13: =SUM(BE3:BE12) -> 281724
B14: Y/Y stats
B15: Server and cloud | AI15: =AI3/AE3-1 -> 0.20832218 | AJ15: =AJ3/AF3-1 -> 0.22389458 | AK15: =AK3/AG3-1 -> 0.25199234 | AL15: =AL3/AH3-1 -> 0.22637178 | AM15: =AM3/AI3-1 -> 0.22660835 | AN15: =AN3/AJ3-1 -> 0.20635812 | AO15: =AO3/AK3-1 -> 0.22180006 | AP15: =AP3/AL3-1 -> 0.27279368 | ... AR15: =AR3/AN3-1 -> 0.30557083 | BD15: =BD3/BC3-1 -> 0.22799083 | BE15: =BE3/BD3-1 -> 0.23308864
B16: MS 365 Commercial and cloud | AI16: =AI4/AE4-1 -> 0.16397884 | AJ16: =AJ4/AF4-1 -> 0.16146824 | AK16: =AK4/AG4-1 -> 0.14637976 | AL16: =AL4/AH4-1 -> 0.13064184 | AM16: =AM4/AI4-1 -> 0.1332853 | AN16: =AN4/AJ4-1 -> 0.15261176 | AO16: =AO4/AK4-1 -> 0.11013596 | AP16: =AP4/AL4-1 -> 0.16398621 | ... AR16: =AR4/AN4-1 -> 0.16133921 | BD16: =BD4/BC4-1 -> 0.14966616 | BE16: =BE4/BD4-1 -> 0.14029025
B17: Gaming | AI17: =AI5/AE5-1 -> 0.085595568 | AJ17: =AJ5/AF5-1 -> 0.49453552 | AK17: =AK5/AG5-1 -> 0.51122817 | AL17: =AL5/AH5-1 -> 0.43855629 | AM17: =AM5/AI5-1 -> 0.43429446 | AN17: =AN5/AJ5-1 -> -0.074532415 | AO17: =AO5/AK5-1 -> 0.049532196 | AP17: =AP5/AL5-1 -> 0.10155317 | ... AR17: =AR5/AN5-1 -> -0.094666464 | BD17: =BD5/BC5-1 -> 0.3903401 | BE17: =BE5/BD5-1 -> 0.090778031
B18: LinkedIn | AI18: =AI6/AE6-1 -> 0.078555678 | AJ18: =AJ6/AF6-1 -> 0.094442995 | AK18: =AK6/AG6-1 -> 0.096747745 | AL18: =AL6/AH6-1 -> 0.098733523 | AM18: =AM6/AI6-1 -> 0.096856632 | AN18: =AN6/AJ6-1 -> 0.093444577 | AO18: =AO6/AK6-1 -> 0.074258659 | AP18: =AP6/AL6-1 -> 0.087273583 | ... AR18: =AR6/AN6-1 -> 0.10791367 | BD18: =BD6/BC6-1 -> 0.092267663 | BE18: =BE6/BD6-1 -> 0.087955045
B19: Windows and Devices | AI19: =AI7/AE7-1 -> -0.055083823 | AJ19: =AJ7/AF7-1 -> 0.034131311 | AK19: =AK7/AG7-1 -> 0.014356436 | AL19: =AL7/AH7-1 -> -0.016298021 | AM19: =AM7/AI7-1 -> -0.0025345622 | AN19: =AN7/AJ7-1 -> 0.034150814 | AO19: =AO7/AK7-1 -> 0.011224988 | AP19: =AP7/AL7-1 -> 0.024615385 | ... AR19: =AR7/AN7-1 -> -0.0073138298 | BD19: =BD7/BC7-1 -> -0.007056628 | BE19: =BE7/BD7-1 -> 0.016915306
B20: Search and news ads | AI20: =AI8/AE8-1 -> 0.036045314 | AJ20: =AJ8/AF8-1 -> -0.012776566 | AK20: =AK8/AG8-1 -> 0.0069215557 | AL20: =AL8/AH8-1 -> 0.032334119 | AM20: =AM8/AI8-1 -> 0.068588469 | AN20: =AN8/AJ8-1 -> 0.12310606 | AO20: =AO8/AK8-1 -> 0.14697218 | AP20: =AP8/AL8-1 -> 0.17161501 | ... AR20: =AR8/AN8-1 -> 0.07138842 | BD20: =BD8/BC8-1 -> 0.014927835 | BE20: =BE8/BD8-1 -> 0.12774256
B21: Enterprise | AI21: =AI9/AE9-1 -> 0.0077760498 | AJ21: =AJ9/AF9-1 -> 0.0052438385 | AK21: =AK9/AG9-1 -> -0.09086468 | AL21: =AL9/AH9-1 -> -0.071888944 | AM21: =AM9/AI9-1 -> -0.0082304527 | AN21: =AN9/AJ9-1 -> -0.01304121 | AO21: =AO9/AK9-1 -> 0.036539495 | AP21: =AP9/AL9-1 -> 0.14102564 | ... AR21: =AR9/AN9-1 -> 0.21828753 | BD21: =BD9/BC9-1 -> -0.038734177 | BE21: =BE9/BD9-1 -> 0.038319726
B22: Dynamics and cloud | AI22: =AI10/AE10-1 -> 0.20892193 | AJ22: =AJ10/AF10-1 -> 0.19266715 | AK22: =AK10/AG10-1 -> 0.17250674 | AL22: =AL10/AH10-1 -> 0.14593909 | AM22: =AM10/AI10-1 -> 0.13714637 | AN22: =AN10/AJ10-1 -> 0.15310428 | AO22: =AO10/AK10-1 -> 0.1183908 | AP22: =AP10/AL10-1 -> 0.10409745 | ... AR22: =AR10/AN10-1 -> 0.15211709 | BD22: =BD10/BC10-1 -> 0.17857143 | BE22: =BE10/BD10-1 -> 0.12750695
B23: MS 365 Consumer and cloud | AI23: =AI11/AE11-1 -> 0.027517198 | AJ23: =AJ11/AF11-1 -> 0.046105919 | AK23: =AK11/AG11-1 -> 0.039092055 | AL23: =AL11/AH11-1 -> 0.031346036 | AM23: =AM11/AI11-1 -> 0.051125989 | AN23: =AN11/AJ11-1 -> 0.084574151 | AO23: =AO11/AK11-1 -> 0.10497573 | AP23: =AP11/AL11-1 -> 0.21275328 | ... AR23: =AR11/AN11-1 -> 0.11916529 | BD23: =BD11/BC11-1 -> 0.03599813 | BE23: =BE11/BD11-1 -> 0.11371841
B26: Product | C26: 15750 | D26: 19431 | E26: 15307 | F26: 16848 | G26: 14968 | H26: 18273 | I26: 14513 | J26: 16057 | K26: 14298 | L26: 17926 | M26: 15114 | N26: 17159 | O26: 17299 | P26: 16219 | Q26: 15448 | R26: 17103 | S26: 15768 | T26: 18255 | U26: 15871 | V26: 18147 | W26: 15803 | X26: 19460 | Y26: 16873 | Z26: 18938 | AA26: 16631 | AB26: 20779 | AC26: 17366 | AD26: 17956 | AE26: 15741 | AF26: 16517 | AG26: 15588 | AH26: 16853 | AI26: 15535 | AJ26: 18941 | AK26: 17080 | AL26: 13217 | AM26: 15272 | AN26: 16219 | AO26: 15319 | AP26: 17136 | AQ26: 15922 | AR26: 16451 | AV26: 67336 | AW26: 63811 | AX26: 64497 | AY26: 66069 | AZ26: 68041 | BA26: 71074 | BB26: 72732 | BC26: 64699 | BD26: 64773 | BE26: =AM26+AN26+AO26+AP26 -> 63946
B27: Service and Other | C27: 5160 | D27: 5822 | E27: 6210 | F27: 6626 | G27: 6960 | H27: 7553 | I27: 8699 | J27: 9548 | K27: 10240 | L27: 10992 | M27: 11705 | N27: 12926 | O27: 11785 | P27: 16252 | Q27: 15123 | R27: 16614 | S27: 17287 | T27: 18651 | U27: 19150 | V27: 19886 | W27: 21351 | X27: 23616 | Y27: 24833 | Z27: 27214 | AA27: 28686 | AB27: 30949 | AC27: 31994 | AD27: 33909 | AE27: 34381 | AF27: 36230 | AG27: 37269 | AH27: 39336 | AI27: 40982 | AJ27: 43079 | AK27: 44778 | AL27: 51510 | AM27: 50313 | AN27: 53413 | AO27: 54747 | AP27: 59305 | AQ27: 61751 | AR27: 64822 | AV27: 23818 | AW27: 32760 | AX27: 45863 | AY27: 59774 | AZ27: 74974 | BA27: 97014 | BB27: 125538 | BC27: 147216 | BD27: 180349 | BE27: =AM27+AN27+AO27+AP27 -> 217778
B28: Revenue | C28: =SUM(C26:C27) -> 20910 | D28: =SUM(D26:D27) -> 25253 | E28: =SUM(E26:E27) -> 21517 | F28: =SUM(F26:F27) -> 23474 | G28: =SUM(G26:G27) -> 21928 | H28: =SUM(H26:H27) -> 25826 | I28: =SUM(I26:I27) -> 23212 | J28: =SUM(J26:J27) -> 25605 | ... AR28: =SUM(AR26:AR27) -> 81273 | AV28: =SUM(AV26:AV27) -> 91154 | AW28: =SUM(AW26:AW27) -> 96571 | AX28: =SUM(AX26:AX27) -> 110360 | AY28: =SUM(AY26:AY27) -> 125843 | AZ28: =SUM(AZ26:AZ27) -> 143015 | BA28: =SUM(BA26:BA27) -> 168088 | BB28: =SUM(BB26:BB27) -> 198270 | BC28: =SUM(BC26:BC27) -> 211915 | BD28: =SUM(BD26:BD27) -> 245122 | BE28: =AM28+AN28+AO28+AP28 -> 281724 | BF28: =BE28*1.13 -> 318348.12 | BG28: =BF28*1.1 -> 350182.93 | BH28: =BG28*1.1 -> 385201.23
B29: Product COGS | C29: 4035 | D29: 6268 | E29: 3801 | F29: 3776 | G29: 3581 | H29: 5378 | I29: 3075 | J29: 3141 | K29: 2980 | L29: 5498 | M29: 3425 | N29: 3517 | O29: 3649 | P29: 5885 | Q29: 3441 | R29: 3298 | S29: 3305 | T29: 4966 | U29: 3376 | V29: 4370 | W29: 3597 | X29: 6058 | Y29: 4277 | Z29: 4287 | AA29: 3792 | AB29: 6331 | AC29: 4584 | AD29: 4357 | AE29: 4302 | AF29: 5690 | AG29: 3941 | AH29: 3871 | AI29: 3531 | AJ29: 5964 | AK29: 4339 | AL29: 1438 | AM29: 3294 | AN29: 3856 | AO29: 3037 | AP29: 3314 | AQ29: 2922 | AR29: 3505 | AV29: 17880 | AW29: 15175 | AX29: 15420 | AY29: 16273 | AZ29: 16017 | BA29: 18219 | BB29: 19064 | BC29: 17804 | BD29: 15272 | BE29: =AM29+AN29+AO29+AP29 -> 13501
B30: Services COGS | C30: 3172 | D30: 3604 | E30: 3921 | F30: 4203 | G30: 4263 | H30: 4523 | I30: 4985 | J30: 5315 | K30: 5298 | L30: 5566 | M30: 5844 | N30: 6225 | O30: 6256 | P30: 6538 | Q30: 6729 | R30: 7114 | S30: 7101 | T30: 7392 | U30: 7599 | V30: 7969 | W30: 7405 | X30: 8136 | Y30: 8768 | Z30: 9704 | AA30: 9854 | AB30: 10629 | AC30: 11031 | AD30: 12072 | AE30: 11150 | AF30: 11798 | AG30: 12187 | AH30: 12924 | AI30: 12771 | AJ30: 13659 | AK30: 14166 | AL30: 18246 | AM30: 16805 | AN30: 17943 | AO30: 18882 | AP30: 20700 | AQ30: 21121 | AR30: 22473 | AV30: 14900 | AW30: 19086 | AX30: 22933 | AY30: 26637 | AZ30: 30061 | BA30: 34013 | BB30: 43586 | BC30: 48059 | BD30: 58842 | BE30: =AM30+AN30+AO30+AP30 -> 74330
B31: COGS | C31: =SUM(C29:C30) -> 7207 | D31: =SUM(D29:D30) -> 9872 | E31: =SUM(E29:E30) -> 7722 | F31: =SUM(F29:F30) -> 7979 | G31: =SUM(G29:G30) -> 7844 | H31: =SUM(H29:H30) -> 9901 | I31: =SUM(I29:I30) -> 8060 | J31: =SUM(J29:J30) -> 8456 | ... AR31: =SUM(AR29:AR30) -> 25978 | AV31: =SUM(AV29:AV30) -> 32780 | AW31: =SUM(AW29:AW30) -> 34261 | AX31: =SUM(AX29:AX30) -> 38353 | AY31: =SUM(AY29:AY30) -> 42910 | AZ31: =SUM(AZ29:AZ30) -> 46078 | BA31: =SUM(BA29:BA30) -> 52232 | BB31: =SUM(BB29:BB30) -> 62650 | BC31: =SUM(BC29:BC30) -> 65863 | ... BE31: =SUM(BE29:BE30) -> 87831
B32: Gross Profit | C32: =C28-C31 -> 13703 | D32: =D28-D31 -> 15381 | E32: =E28-E31 -> 13795 | F32: =F28-F31 -> 15495 | G32: =G28-G31 -> 14084 | H32: =H28-H31 -> 15925 | I32: =I28-I31 -> 15152 | J32: =J28-J31 -> 17149 | ... AR32: =AR28-AR31 -> 55295 | AV32: =AV28-AV31 -> 58374 | AW32: =AW28-AW31 -> 62310 | AX32: =AX28-AX31 -> 72007 | AY32: =AY28-AY31 -> 82933 | AZ32: =AZ28-AZ31 -> 96937 | BA32: =BA28-BA31 -> 115856 | BB32: =BB28-BB31 -> 135620 | BC32: =BC28-BC31 -> 146052 | ... BE32: =BE28-BE31 -> 193893 | BF32: =BF28*0.7 -> 222843.68 | BG32: =BG28*0.7 -> 245128.05 | BH32: =BH28*0.7 -> 269640.86
B33: R&D | C33: 2962 | D33: 2900 | E33: 2980 | F33: 3146 | G33: 3106 | H33: 3062 | I33: 3355 | J33: 3514 | K33: 3574 | L33: 3504 | M33: 3715 | N33: 3933 | O33: 3977 | P33: 4070 | Q33: 4316 | R33: 4513 | S33: 4565 | T33: 4603 | U33: 4887 | V33: 5214 | W33: 4926 | X33: 4899 | Y33: 5204 | Z33: 5687 | AA33: 5599 | AB33: 5758 | AC33: 6306 | AD33: 6849 | AE33: 6628 | AF33: 6844 | AG33: 6984 | AH33: 6739 | AI33: 6659 | AJ33: 7142 | AK33: 7653 | AL33: 805 | AM33: 7544 | AN33: 7917 | AO33: 8198 | AP33: 8829 | AQ33: 8146 | AR33: 8504 | AV33: 11988 | AW33: 13037 | AX33: 14726 | AY33: 16876 | AZ33: 19269 | BA33: 20716 | BB33: 24512 | BC33: 27195 | BD33: 29510 | BE33: =AM33+AN33+AO33+AP33 -> 32488
B34: S&M | C34: 3341 | D34: 3954 | E34: 3398 | F34: 3942 | G34: 3218 | H34: 4079 | I34: 3872 | J34: 4292 | K34: 3812 | L34: 4562 | M34: 4335 | N34: 4760 | O34: 4098 | P34: 4588 | Q34: 4565 | R34: 4962 | S34: 4337 | T34: 4933 | U34: 4911 | V34: 5417 | W34: 4231 | X34: 4947 | Y34: 5082 | Z34: 5857 | AA34: 4547 | AB34: 5379 | AC34: 5595 | AD34: 6304 | AE34: 5126 | AF34: 5679 | AG34: 5750 | AH34: 6204 | AI34: 5187 | AJ34: 6246 | AK34: 6207 | AL34: 6816 | AM34: 5717 | AN34: 6440 | AO34: 6212 | AP34: 7285 | AQ34: 5717 | AR34: 6584 | AV34: 14635 | AW34: 15461 | AX34: 17469 | AY34: 18213 | AZ34: 19598 | BA34: 20117 | BB34: 21825 | BC34: 22759 | BD34: 24456 | BE34: =AM34+AN34+AO34+AP34 -> 25654
B35: G&A | C35: 1084 | D35: 1038 | E35: 1140 | F35: =1301+1110 -> 2411 | G35: 1045 | H35: 879 | I35: 1202 | J35: =1355+306 -> 1661 | K35: 1166 | L35: 1109 | M35: 1208 | N35: 1271 | O35: 1149 | P35: 1132 | Q35: 1179 | R35: 1425 | S35: 1061 | T35: 1121 | U35: 1273 | V35: 1656 | W35: 1119 | X35: 1139 | Y35: 1327 | Z35: 1522 | AA35: 1287 | AB35: 1384 | AC35: 1480 | AD35: 1749 | AE35: 1398 | AF35: 2337 | AG35: 1643 | AH35: 2197 | AI35: 1474 | AJ35: 1977 | AK35: 1912 | AL35: 2246 | AM35: 1673 | AN35: 1823 | AO35: 1737 | AP35: 1990 | AQ35: 1806 | AR35: 1932 | AV35: =4563+1110 -> 5673 | AW35: =4481+306 -> 4787 | AX35: 4754 | AY35: 4885 | AZ35: 5111 | BA35: 5107 | BB35: 5900 | BC35: 7575 | BD35: 7609 | BE35: =AM35+AN35+AO35+AP35 -> 7223
B36: Operating Expenses | C36: =SUM(C33:C35) -> 7387 | D36: =SUM(D33:D35) -> 7892 | E36: =SUM(E33:E35) -> 7518 | F36: =SUM(F33:F35) -> 9499 | G36: =SUM(G33:G35) -> 7369 | H36: =SUM(H33:H35) -> 8020 | I36: =SUM(I33:I35) -> 8429 | J36: =SUM(J33:J35) -> 9467 | ... AR36: =SUM(AR33:AR35) -> 17020 | AV36: =SUM(AV33:AV35) -> 32296 | AW36: =SUM(AW33:AW35) -> 33285 | AX36: =SUM(AX33:AX35) -> 36949 | AY36: =SUM(AY33:AY35) -> 39974 | AZ36: =SUM(AZ33:AZ35) -> 43978 | BA36: =SUM(BA33:BA35) -> 45940 | BB36: =SUM(BB33:BB35) -> 52237 | BC36: =SUM(BC33:BC35) -> 57529 | ... BE36: =SUM(BE33:BE35) -> 65365 | BF36: =BE36*1.05 -> 68633.25 | BG36: =BF36*1.05 -> 72064.913 | BH36: =BG36*1.05 -> 75668.158
B37: Operating Income | C37: =C32-C36 -> 6316 | D37: =D32-D36 -> 7489 | E37: =E32-E36 -> 6277 | F37: =F32-F36 -> 5996 | G37: =G32-G36 -> 6715 | H37: =H32-H36 -> 7905 | I37: =I32-I36 -> 6723 | J37: =J32-J36 -> 7682 | ... AR37: =AR32-AR36 -> 38275 | AV37: =AV32-AV36 -> 26078 | AW37: =AW32-AW36 -> 29025 | AX37: =AX32-AX36 -> 35058 | AY37: =AY32-AY36 -> 42959 | AZ37: =AZ32-AZ36 -> 52959 | BA37: =BA32-BA36 -> 69916 | BB37: =BB32-BB36 -> 83383 | BC37: =BC32-BC36 -> 88523 | ... BH37: =BH32-BH36 -> 193972.7
B38: Other expenses | C38: -295 | D38: -176 | E38: -212 | F38: 244 | G38: 112 | H38: 117 | I38: 371 | J38: 276 | K38: 276 | L38: 490 | M38: 349 | N38: 301 | O38: 266 | P38: 127 | Q38: 145 | R38: 191 | S38: 0 | T38: 194 | U38: -132 | V38: 15 | W38: 248 | X38: 440 | Y38: 188 | Z38: 310 | AA38: 286 | AB38: 268 | AC38: -174 | AD38: -47 | AE38: 54 | AF38: -60 | AG38: 321 | AH38: 473 | AI38: 389 | AJ38: -506 | AK38: -854 | AL38: -675 | AM38: -283 | AN38: -2288 | AO38: -623 | AP38: -1707 | AQ38: -3660 | AR38: 9971 | AV38: -439 | AW38: 876 | AX38: 1416 | AY38: 729 | AZ38: 77 | BA38: 1186 | BB38: 333 | BC38: 788 | BD38: -1646 | BE38: =AM38+AN38+AO38+AP38 -> -4901 | BF38: =BE38*(1+$BL$45) -> -4950.01 | BG38: =BF38*(1+$BL$45) -> -4999.5101 | BH38: =BG38*(1+$BL$45) -> -5049.5052
B39: Pre-Tax Income | C39: =C37+C38 -> 6021 | D39: =D37+D38 -> 7313 | E39: =E37+E38 -> 6065 | F39: =F37+F38 -> 6240 | G39: =G37+G38 -> 6827 | H39: =H37+H38 -> 8022 | I39: =I37+I38 -> 7094 | J39: =J37+J38 -> 7958 | ... AR39: =AR37+AR38 -> 48246 | AV39: =AV37+AV38 -> 25639 | AW39: =AW37+AW38 -> 29901 | AX39: =AX37+AX38 -> 36474 | AY39: =AY37+AY38 -> 43688 | AZ39: =AZ37+AZ38 -> 53036 | BA39: =BA37+BA38 -> 71102 | BB39: =BB37+BB38 -> 83716 | BC39: =BC37+BC38 -> 89311 | ... BH39: =BH37+BH38 -> 188923.19
B40: Taxes | C40: 952 | D40: 1375 | E40: 1760 | F40: 1013 | G40: 1160 | H40: 1755 | I40: 1608 | J40: -111 | K40: 1408 | L40: 15471 | M40: 1217 | N40: 1807 | O40: 1397 | P40: 1965 | Q40: 1677 | R40: -591 | S40: 2008 | T40: 2436 | U40: 2091 | V40: 2220 | W40: 2231 | X40: 2874 | Y40: 1779 | Z40: 2947 | AA40: 19 | AB40: 3750 | AC40: 3462 | AD40: 3747 | AE40: 4016 | AF40: 3914 | AG40: 4374 | AH40: 4646 | AI40: 4993 | AJ40: 4656 | AK40: 4788 | AL40: 2514 | AM40: 5602 | AN40: 5257 | AO40: 5553 | AP40: 5383 | AQ40: 6554 | AR40: 9788 | AV40: 5100 | AW40: 4412 | AX40: 19903 | AY40: 4448 | AZ40: 8755 | BA40: 9831 | BB40: 10978 | BC40: 16950 | BD40: 19651 | BE40: =AM40+AN40+AO40+AP40 -> 21795
B41: Net Income | C41: =C39-C40 -> 5069 | D41: =D39-D40 -> 5938 | E41: =E39-E40 -> 4305 | F41: =F39-F40 -> 5227 | G41: =G39-G40 -> 5667 | H41: =H39-H40 -> 6267 | I41: =I39-I40 -> 5486 | J41: =J39-J40 -> 8069 | ... AR41: =AR39-AR40 -> 38458 | AV41: =AV39-AV40 -> 20539 | AW41: =AW39-AW40 -> 25489 | AX41: =AX39-AX40 -> 16571 | AY41: =AY39-AY40 -> 39240 | AZ41: =AZ39-AZ40 -> 44281 | BA41: =BA39-BA40 -> 61271 | BB41: =BB39-BB40 -> 72738 | BC41: =BC39-BC40 -> 72361 | ... BE41: =BE39-BE40 -> 101832 | BF41: 113670 | BG41: 132510 | BH41: =BH39*(1-0.18) -> 154917.02 | BI41: =BH41*1.05 -> 162662.87 | BJ41: =BI41*1.05 -> 170796.01 | BK41: =BJ41*1.05 -> 179335.81 | BL41: =BK41*1.05 -> 188302.61 | BM41: =BL41*1.025 -> 193010.17 | BN41: =BM41*1.025 -> 197835.42 | BO41: =BN41*1.025 -> 202781.31 | BP41: =BO41*1.025 -> 207850.84 | BQ41: =BP41*1 -> 207850.84 | BR41: =BQ41*1 -> 207850.84 | BS41: =BR41*1 -> 207850.84 | BT41: =BS41*1 -> 207850.84 | BU41: =BT41*0.97 -> 201615.32 | BV41: =BU41*0.97 -> 195566.86 | BW41: =BV41*0.97 -> 189699.85 | BX41: =BW41*0.97 -> 184008.86 | BY41: =BX41*(1-$BL$46) -> 182168.77 | BZ41: =BY41*(1-$BL$46) -> 180347.08 | CA41: =BZ41*(1-$BL$46) -> 178543.61 | CB41: =CA41*(1-$BL$46) -> 176758.17 | CC41: =CB41*(1-$BL$46) -> 174990.59 | CD41: =CC41*(1-$BL$46) -> 173240.69 | CE41: =CD41*(1-$BL$46) -> 171508.28 | CF41: =CE41*(1-$BL$46) -> 169793.2 | ... TA41: =SZ41*(1-$BL$46) -> 2101.3593
B42: S/E | AG42: 7441 | AH42: 7434 | AI42: 7429 | AJ42: 7432 | AK42: 7431 | AL42: 7433 | AM42: 7433 | AN42: 7435 | AO42: 7433 | AP42: 7432 | AQ42: 7434 | AR42: 7431 | BC42: 7432 | BD42: 7435 | BE42: =+AP42 -> 7432 | BF42: =BE42*1.001 -> 7439.432 | BG42: =BF42*1.001 -> 7446.8714 | BH42: =BG42*1.001 -> 7454.3183
B43: EPS | C43: 0.63 | D43: 0.75 | E43: 0.55 | F43: 0.67 | G43: 0.73 | H43: 0.81 | I43: 0.71 | J43: 1.05 | K43: 0.85 | L43: -0.82 | M43: 0.96 | N43: 1.15 | O43: 1.15 | P43: 1.09 | Q43: 1.15 | R43: 1.72 | S43: 1.4 | T43: 1.53 | U43: 1.41 | V43: 1.48 | W43: 1.84 | X43: 2.05 | Y43: 2.05 | Z43: 2.19 | AA43: 2.73 | AB43: 2.5 | AC43: 2.23 | AD43: 2.24 | AE43: 2.35 | AF43: 2.2 | AG43: =AG41/AG42 -> 2.4592125 | AH43: =AH41/AH42 -> 2.7012376 | AI43: =AI41/AI42 -> 3.0005384 | AJ43: =AJ41/AJ42 -> 2.9426803 | AK43: =AK41/AK42 -> 2.9523617 | AL43: =AL41/AL42 -> 4.3033768 | AM43: =AM41/AM42 -> 3.3185793 | AN43: =AN41/AN42 -> 3.2425017 | ... AR43: =AR41/AR42 -> 5.1753465 | AV43: 2.59 | AW43: 3.29 | AX43: 2.15 | AY43: 5.11 | AZ43: 5.82 | BA43: 8.12 | BB43: 9.7 | BC43: 9.72 | BD43: 11.86 | BE43: =BE41/BE42 -> 13.70183 | BF43: =BF41/BF42 -> 15.279392 | BG43: =BG41/BG42 -> 17.79405 | BH43: =BH41/BH42 -> 20.782185
B45: Hardware Y/Y | G45: =G26/C26-1 -> -0.049650794 | H45: =H26/D26-1 -> -0.059595492 | I45: =I26/E26-1 -> -0.051871693 | J45: =J26/F26-1 -> -0.046949193 | K45: =K26/G26-1 -> -0.044762159 | L45: =L26/H26-1 -> -0.018989766 | M45: =M26/I26-1 -> 0.041411149 | N45: =N26/J26-1 -> 0.068630504 | ... AR45: =AR26/AN26-1 -> 0.014304211 | AW45: =AW26/AV26-1 -> -0.052349412 | AX45: =AX26/AW26-1 -> 0.010750498 | AY45: =AY26/AX26-1 -> 0.024373227 | AZ45: =AZ26/AY26-1 -> 0.029847584 | BA45: =BA26/AZ26-1 -> 0.044576064 | BB45: =BB26/BA26-1 -> 0.023327799 | BC45: =BC26/BB26-1 -> -0.11044657 | BD45: =BD26/BC26-1 -> 0.001143758 | BE45: =BE26/BD26-1 -> -0.012767666 | BK45: ROIC | BL45: 0.01
B46: Software Y/Y | G46: =G27/C27-1 -> 0.34883721 | H46: =H27/D27-1 -> 0.29732051 | I46: =I27/E27-1 -> 0.40080515 | J46: =J27/F27-1 -> 0.44099004 | K46: =K27/G27-1 -> 0.47126437 | L46: =L27/H27-1 -> 0.45531577 | M46: =M27/I27-1 -> 0.34555696 | N46: =N27/J27-1 -> 0.35379137 | ... AR46: =AR27/AN27-1 -> 0.21359969 | AW46: =AW27/AV27-1 -> 0.37543035 | AX46: =AX27/AW27-1 -> 0.39996947 | AY46: =AY27/AX27-1 -> 0.3033164 | AZ46: =AZ27/AY27-1 -> 0.25429116 | BA46: =BA27/AZ27-1 -> 0.29396858 | BB46: =BB27/BA27-1 -> 0.29401942 | BC46: =BC27/BB27-1 -> 0.17268078 | BD46: =BD27/BC27-1 -> 0.22506385 | BE46: =BE27/BD27-1 -> 0.2075365 | BK46: Maturity | BL46: 0.01
B47: Revenue Y/Y | G47: =G28/C28-1 -> 0.04868484 | H47: =H28/D28-1 -> 0.022690373 | I47: =I28/E28-1 -> 0.078774922 | J47: =J28/F28-1 -> 0.09078129 | K47: =K28/G28-1 -> 0.1190259 | L47: =L28/H28-1 -> 0.11972431 | M47: =M28/I28-1 -> 0.15539376 | N47: =N28/J28-1 -> 0.17496583 | ... AR47: =AR28/AN28-1 -> 0.16717888 | AW47: =AW28/AV28-1 -> 0.059426904 | AX47: =AX28/AW28-1 -> 0.14278614 | AY47: =AY28/AX28-1 -> 0.1402954 | AZ47: =AZ28/AY28-1 -> 0.13645574 | BA47: =BA28/AZ28-1 -> 0.17531727 | BB47: =BB28/BA28-1 -> 0.17956071 | BC47: =BC28/BB28-1 -> 0.068820296 | BD47: =BD28/BC28-1 -> 0.15669962 | ... BH47: =BH28/BG28-1 -> 0.1 | BK47: Discount | BL47: 0.06
B48: R&D Y/Y | AW48: =AW33/AV33-1 -> 0.087504171 | AX48: =AX33/AW33-1 -> 0.12955435 | AY48: =AY33/AX33-1 -> 0.14600027 | AZ48: =AZ33/AY33-1 -> 0.141799 | BA48: =BA33/AZ33-1 -> 0.075094712 | BB48: =BB33/BA33-1 -> 0.18324001 | BC48: =BC33/BB33-1 -> 0.10945659 | BD48: =BD33/BC33-1 -> 0.085125942 | BE48: =BE33/BD33-1 -> 0.10091494 | BK48: NPV | BL48: =NPV(BL47,BE41:TA41) -> 2778234.3
B49: S&M Y/Y | AW49: =AW34/AV34-1 -> 0.056440041 | AX49: =AX34/AW34-1 -> 0.12987517 | AY49: =AY34/AX34-1 -> 0.04258973 | AZ49: =AZ34/AY34-1 -> 0.076044584 | BA49: =BA34/AZ34-1 -> 0.026482294 | BB49: =BB34/BA34-1 -> 0.084903316 | BC49: =BC34/BB34-1 -> 0.04279496 | BD49: =BD34/BC34-1 -> 0.074563909 | BE49: =BE34/BD34-1 -> 0.048985934 | BK49: Net Cash | BL49: =AN63 -> 42166
B50: G&A Y/Y | AW50: =AW35/AV35-1 -> -0.15617839 | AX50: =AX35/AW35-1 -> -0.0068936704 | AY50: =AY35/AX35-1 -> 0.027555743 | AZ50: =AZ35/AY35-1 -> 0.046264074 | BA50: =BA35/AZ35-1 -> -0.00078262571 | BB50: =BB35/BA35-1 -> 0.15527707 | BC50: =BC35/BB35-1 -> 0.28389831 | BD50: =BD35/BC35-1 -> 0.0044884488 | BE50: =BE35/BD35-1 -> -0.050729399 | BK50: Net NPV | BL50: =BL48+BL49 -> 2820400.3
BK51: NPV | BL51: =BL50/BD42 -> 379.341
B52: Gross Margin | C52: =C32/C28 -> 0.65533238 | D52: =D32/D28 -> 0.60907615 | E52: =E32/E28 -> 0.64112097 | F52: =F32/F28 -> 0.66009202 | G52: =G32/G28 -> 0.64228384 | H52: =H32/H28 -> 0.61662666 | I52: =I32/I28 -> 0.65276581 | J52: =J32/J28 -> 0.669752 | ... AR52: =AR32/AR28 -> 0.68036125 | AV52: =AV32/AV28 -> 0.64038879 | AW52: =AW32/AW28 -> 0.64522476 | AX52: =AX32/AX28 -> 0.65247372 | AY52: =AY32/AY28 -> 0.65901957 | AZ52: =AZ32/AZ28 -> 0.67781002 | BA52: =BA32/BA28 -> 0.68925801 | BB52: =BB32/BB28 -> 0.68401674 | BC52: =BC32/BC28 -> 0.68920086 | ... BH52: =BH32/BH28 -> 0.7 | BK52: Change | BL52: =BL51/Main!C15-1 -> -0.27880568
B53: Product Margin | C53: =(C26-C29)/C26 -> 0.74380952 | D53: =(D26-D29)/D26 -> 0.67742268 | E53: =(E26-E29)/E26 -> 0.75168224 | F53: =(F26-F29)/F26 -> 0.77587844 | G53: =(G26-G29)/G26 -> 0.76075628 | H53: =(H26-H29)/H26 -> 0.70568598 | I53: =(I26-I29)/I26 -> 0.78812099 | J53: =(J26-J29)/J26 -> 0.80438438 | ... AR53: =(AR26-AR29)/AR26 -> 0.78694304 | AV53: =(AV26-AV29)/AV26 -> 0.73446596 | AW53: =(AW26-AW29)/AW26 -> 0.76218834 | AX53: =(AX26-AX29)/AX26 -> 0.76091911 | AY53: =(AY26-AY29)/AY26 -> 0.75369689 | AZ53: =(AZ26-AZ29)/AZ26 -> 0.76459782 | BA53: =(BA26-BA29)/BA26 -> 0.74366154 | BB53: =(BB26-BB29)/BB26 -> 0.73788704 | BC53: =(BC26-BC29)/BC26 -> 0.724818 | ... BE53: =(BE26-BE29)/BE26 -> 0.78886873
B54: Service Margin | C54: =(C27-C30)/C27 -> 0.38527132 | D54: =(D27-D30)/D27 -> 0.38096874 | E54: =(E27-E30)/E27 -> 0.36859903 | F54: =(F27-F30)/F27 -> 0.36568065 | G54: =(G27-G30)/G27 -> 0.3875 | H54: =(H27-H30)/H27 -> 0.4011651 | I54: =(I27-I30)/I27 -> 0.42694563 | J54: =(J27-J30)/J27 -> 0.44333892 | ... AR54: =(AR27-AR30)/AR27 -> 0.65331215 | AV54: =(AV27-AV30)/AV27 -> 0.37442271 | AW54: =(AW27-AW30)/AW27 -> 0.41739927 | AX54: =(AX27-AX30)/AX27 -> 0.49996729 | AY54: =(AY27-AY30)/AY27 -> 0.55437147 | AZ54: =(AZ27-AZ30)/AZ27 -> 0.59904767 | BA54: =(BA27-BA30)/BA27 -> 0.64940112 | BB54: =(BB27-BB30)/BB27 -> 0.65280632 | BC54: =(BC27-BC30)/BC27 -> 0.67354771 | ... BE54: =(BE27-BE30)/BE27 -> 0.65868912
B55: Operating Margin | C55: =C37/C28 -> 0.30205643 | D55: =D37/D28 -> 0.29655882 | E55: =E37/E28 -> 0.29172282 | F55: =F37/F28 -> 0.25543154 | G55: =G37/G28 -> 0.30622948 | H55: =H37/H28 -> 0.30608689 | I55: =I37/I28 -> 0.28963467 | J55: =J37/J28 -> 0.30001953 | ... AR55: =AR37/AR28 -> 0.47094361 | AV55: =AV37/AV28 -> 0.28608728 | AW55: =AW37/AW28 -> 0.30055607 | AX55: =AX37/AX28 -> 0.31766945 | AY55: =AY37/AY28 -> 0.3413698 | AZ55: =AZ37/AZ28 -> 0.37030381 | BA55: =BA37/BA28 -> 0.41594879 | BB55: =BB37/BB28 -> 0.42055278 | BC55: =BC37/BC28 -> 0.41772881 | ... BH55: =BH37/BH28 -> 0.503562
B56: Net Margin | C56: =C41/C28 -> 0.24241989 | D56: =D41/D28 -> 0.23514038 | E56: =E41/E28 -> 0.20007436 | F56: =F41/F28 -> 0.22267189 | G56: =G41/G28 -> 0.2584367 | H56: =H41/H28 -> 0.24266243 | I56: =I41/I28 -> 0.23634327 | J56: =J41/J28 -> 0.31513376 | ... AR56: =AR41/AR28 -> 0.47319528 | AV56: =AV41/AV28 -> 0.22532198 | AW56: =AW41/AW28 -> 0.26394052 | AX56: =AX41/AX28 -> 0.15015404 | AY56: =AY41/AY28 -> 0.31181711 | AZ56: =AZ41/AZ28 -> 0.30962486 | BA56: =BA41/BA28 -> 0.3645174 | BB56: =BB41/BB28 -> 0.36686337 | BC56: =BC41/BC28 -> 0.34146238 | ... BH56: =BH41/BH28 -> 0.40217167
B57: Tax rate | C57: =C40/C39 -> 0.15811327 | D57: =D40/D39 -> 0.18802133 | E57: =E40/E39 -> 0.29018961 | F57: =F40/F39 -> 0.16233974 | G57: =G40/G39 -> 0.16991358 | H57: =H40/H39 -> 0.21877337 | I57: =I40/I39 -> 0.22667043 | J57: =J40/J39 -> -0.013948228 | ... AR57: =AR40/AR39 -> 0.20287692 | AV57: =AV40/AV39 -> 0.19891571 | AW57: =AW40/AW39 -> 0.14755359 | AX57: =AX40/AX39 -> 0.54567637 | AY57: =AY40/AY39 -> 0.10181285 | AZ57: =AZ40/AZ39 -> 0.16507655 | BA57: =BA40/BA39 -> 0.13826615 | BB57: =BB40/BB39 -> 0.13113383 | BC57: =BC40/BC39 -> 0.18978625 | ... BE57: =BE40/BE39 -> 0.17629644
B58: SG&A Margin | C58: =(C34+C35)/C32 -> 0.32292199 | D58: =(D34+D35)/D32 -> 0.32455627 | E58: =(E34+E35)/E32 -> 0.32895977 | F58: =(F34+F35)/F32 -> 0.41000323 | G58: =(G34+G35)/G32 -> 0.3026839 | H58: =(H34+H35)/H32 -> 0.31133438 | I58: =(I34+I35)/I32 -> 0.33487328 | J58: =(J34+J35)/J32 -> 0.34713394 | ... AR58: =(AR34+AR35)/AR32 -> 0.15401031 | AV58: =(AV34+AV35)/AV32 -> 0.34789461 | AW58: =(AW34+AW35)/AW32 -> 0.32495587 | AX58: =(AX34+AX35)/AX32 -> 0.30862277 | AY58: =(AY34+AY35)/AY32 -> 0.27851398 | AZ58: =(AZ34+AZ35)/AZ32 -> 0.25489751 | BA58: =(BA34+BA35)/BA32 -> 0.21771855 | BB58: =(BB34+BB35)/BB32 -> 0.2044315 | BC58: =(BC34+BC35)/BC32 -> 0.20769315 | ... BE58: =(BE34+BE35)/BE32 -> 0.16956259
B59: R&D Margin | C59: =C33/C32 -> 0.21615705 | D59: =D33/D32 -> 0.18854431 | E59: =E33/E32 -> 0.2160203 | F59: =F33/F32 -> 0.20303324 | G59: =G33/G32 -> 0.22053394 | H59: =H33/H32 -> 0.1922763 | I59: =I33/I32 -> 0.22142291 | J59: =J33/J32 -> 0.20490991 | ... AR59: =AR33/AR32 -> 0.15379329 | AV59: =AV33/AV32 -> 0.2053654 | AW59: =AW33/AW32 -> 0.20922805 | AX59: =AX33/AX32 -> 0.2045079 | AY59: =AY33/AY32 -> 0.20348956 | AZ59: =AZ33/AZ32 -> 0.19877859 | BA59: =BA33/BA32 -> 0.17880818 | BB59: =BB33/BB32 -> 0.1807403 | BC59: =BC33/BC32 -> 0.18620081 | ... BE59: =BE33/BE32 -> 0.16755633
B60: Interest Margin | C60: =C38/C37 -> -0.046706776 | D60: =D38/D37 -> -0.023501135 | E60: =E38/E37 -> -0.033774096 | F60: =F38/F37 -> 0.040693796 | G60: =G38/G37 -> 0.016679077 | H60: =H38/H37 -> 0.014800759 | I60: =I38/I37 -> 0.055183698 | J60: =J38/J37 -> 0.035928144 | ... AR60: =AR38/AR37 -> 0.26050947 | AV60: =AV38/AV37 -> -0.016834113 | AW60: =AW38/AW37 -> 0.030180879 | AX60: =AX38/AX37 -> 0.040390211 | AY60: =AY38/AY37 -> 0.016969669 | AZ60: =AZ38/AZ37 -> 0.0014539549 | BA60: =BA38/BA37 -> 0.016963213 | BB60: =BB38/BB37 -> 0.0039936198 | BC60: =BC38/BC37 -> 0.0089016414 | ... BE60: =BE38/BE37 -> -0.038131769
B61: EPS Growth | AW61: =AW43/AV43-1 -> 0.27027027 | AX61: =AX43/AW43-1 -> -0.34650456 | AY61: =AY43/AX43-1 -> 1.3767442 | AZ61: =AZ43/AY43-1 -> 0.13894325 | BA61: =BA43/AZ43-1 -> 0.395189 | BB61: =BB43/BA43-1 -> 0.19458128 | BC61: =BC43/BB43-1 -> 0.0020618557 | BD61: =BD43/BC43-1 -> 0.22016461 | BE61: =BE43/BD43-1 -> 0.15529763
B63: Net Cash | AH63: =AH64-AH75 -> 73904 | AK63: =AK64-AK75 -> 29386 | AL63: =AL64-AL75 -> 38513 | AM63: =AM64-AM75 -> 49089 | AN63: =AN64-AN75 -> 42166 | AO63: =AO64-AO75 -> 0 | AP63: =AP64-AP75 -> 66819 | AQ63: =AQ64-AQ75 -> 70269 | AR63: =AR64-AR75 -> 70402 | AS63: =AS64-AS75 -> 0 | BC63: =BC64-BC75 -> 73904 | BD63: =BD64-BD75 -> 38513 | BE63: =BE64-BE75 -> 66819
B64: Cash | AH64: =111262+9879 -> 121141 | AK64: =80021+14807 -> 94828 | AL64: =18315+57228+14600 -> 90143 | AM64: =78428+15778 -> 94206 | AN64: =17482+54073+15581 -> 87136 | AP64: =30242+64323+15405 -> 109970 | AQ64: =28849+73163+11465 -> 113477 | AR64: =24296+65166+21202 -> 110664 | BC64: =111262+9879 -> 121141 | BD64: =18315+57228+14600 -> 90143 | BE64: =30242+64323+15405 -> 109970
B65: A/R | AH65: 48688 | AK65: 44029 | AL65: 56924 | AM65: 44148 | AN65: 48188 | AP65: 69905 | AQ65: 52894 | AR65: 56535 | BC65: 48688 | BD65: 56924 | BE65: 69905
B66: Inventories | AH66: 2500 | AK66: 1304 | AL66: 1246 | AM66: 1626 | AN66: 909 | AP66: 938 | AQ66: 1130 | AR66: 1059 | BC66: 2500 | BD66: 1246 | BE66: 938
B67: OCA | AH67: 21807 | AK67: 21826 | AL67: 26021 | AM67: 25724 | AN67: 26428 | AP67: 25723 | AQ67: 33030 | AR67: 33134 | BC67: 21807 | BD67: 26021 | BE67: 25723
B68: PP&A | AH68: 95641 | AK68: 121375 | AL68: 135591 | AM68: 152863 | AN68: 166902 | AP68: 204966 | AQ68: 230861 | AR68: 261126 | BC68: 95641 | BD68: 135591 | BE68: 204966
B69: Lease ROU | AH69: 14346 | AK69: 17371 | AL69: 18961 | AM69: 20528 | AN69: 22816 | AP69: 24823 | AQ69: 24791 | AR69: 25103 | BC69: 14346 | BD69: 18961 | BE69: 24823
B70: Goodwill | AH70: 67886 | AK70: 119163 | AL70: 119220 | AM70: 119374 | AN70: 119191 | AP70: 119509 | AQ70: 119497 | AR70: 119622 | BC70: 67886 | BD70: 119220 | BE70: 119509
B71: Intangibles | AH71: 9366 | AK71: 28828 | AL71: 27597 | AM71: 26751 | AN71: 25385 | AP71: 22604 | AQ71: 21236 | AR71: 20289 | BC71: 9366 | BD71: 27597 | BE71: 22604
B72: ONCA | AH72: 30601 | AK72: 35551 | AL72: 36460 | AM72: 37793 | AN72: 36943 | AP72: 40565 | AQ72: 39435 | AR72: 37770 | BC72: 30601 | BD72: 36460 | BE72: 40565
B73: Total Assets | AH73: =SUM(AH64:AH72) -> 411976 | AK73: =SUM(AK64:AK72) -> 484275 | AL73: =SUM(AL64:AL72) -> 512163 | AM73: =SUM(AM64:AM72) -> 523013 | AN73: =SUM(AN64:AN72) -> 533898 | AP73: =SUM(AP64:AP72) -> 619003 | AQ73: =SUM(AQ64:AQ72) -> 636351 | AR73: =SUM(AR64:AR72) -> 665302 | AS73: =SUM(AS64:AS72) -> 0 | BC73: =SUM(BC64:BC72) -> 411976 | BD73: =SUM(BD64:BD72) -> 512163 | BE73: =SUM(BE64:BE72) -> 619003
B74: A/P | AH74: 18095 | AK74: 18087 | AL74: 21996 | AM74: 22768 | AN74: 22608 | AP74: 27724 | AQ74: 32580 | AR74: 37328 | BC74: 18095 | BD74: 21996 | BE74: 27724
B75: Debt | AH75: =5247+41990 -> 47237 | AK75: =20535+2249+42658 -> 65442 | AL75: =6693+2249+42688 -> 51630 | AM75: =2249+42868 -> 45117 | AN75: =5248+39722 -> 44970 | AP75: =40152+2999 -> 43151 | AQ75: =7832+35376 -> 43208 | AR75: =4837+35425 -> 40262 | BC75: =5247+41990 -> 47237 | BD75: =6693+2249+42688 -> 51630 | BE75: =40152+2999 -> 43151
B76: Wages | AH76: 11009 | AK76: 10432 | AL76: 12564 | AM76: 8326 | AN76: 9176 | AP76: 13709 | AQ76: 9201 | AR76: 10103 | BC76: 11009 | BD76: 12564 | BE76: 13709
B77: Taxes | AH77: =4152+25560+433 -> 30145 | AK77: =7311+26786+2469 -> 36566 | AL77: =5017+2618+27931 -> 35566 | AM77: =9717+24452+2581 -> 36750 | AN77: =6056+24389+2513 -> 32958 | AP77: =7211+25986+2835 -> 36032 | AQ77: =3655+26569+2852 -> 33076 | AR77: =2050+27256 -> 29306 | BC77: =4152+25560+433 -> 30145 | BD77: =5017+2618+27931 -> 35566 | BE77: =7211+25986+2835 -> 36032
B78: D/R | AH78: =50901+2912 -> 53813 | AK78: =41888+2945 -> 44833 | AL78: =57582+2602 -> 60184 | AM78: =53026+2663 -> 55689 | AN78: =45508+2537 -> 48045 | AP78: =64555+2710 -> 67265 | AQ78: =58987+2546 -> 61533 | AR78: =51376+2668 -> 54044 | BC78: =50901+2912 -> 53813 | BD78: =57582+2602 -> 60184 | BE78: =64555+2710 -> 67265
B79: OCL | AH79: 14745 | AK79: 18023 | AL79: 19185 | AM79: 19114 | AN79: 20286 | AP79: 25020 | AQ79: 22741 | AR79: 24311 | BC79: 14745 | BD79: 19185 | BE79: 25020
B80: Lease | AH80: 12728 | AK80: 14469 | AL80: 15497 | AM80: 16361 | AN80: 17254 | AP80: 17437 | AQ80: 17348 | AR80: 17345 | BC80: 12728 | BD80: 15497 | BE80: 17437
B81: ONCL | AH81: 17981 | AK81: 23271 | AL81: 27064 | AM81: 31165 | AN81: 35906 | AP81: 45186 | AQ81: 53588 | AR81: =58852+2876 -> 61728 | BC81: 17981 | BD81: 27064 | BE81: 45186
B82: Total Liabilities | AH82: =SUM(AH74:AH81) -> 205753 | AK82: =SUM(AK74:AK81) -> 231123 | AL82: =SUM(AL74:AL81) -> 243686 | AM82: =SUM(AM74:AM81) -> 235290 | AN82: =SUM(AN74:AN81) -> 231203 | AP82: =SUM(AP74:AP81) -> 275524 | AQ82: =SUM(AQ74:AQ81) -> 273275 | AR82: =SUM(AR74:AR81) -> 274427 | AS82: =SUM(AS74:AS81) -> 0 | BC82: =SUM(BC74:BC81) -> 205753 | BD82: =SUM(BD74:BD81) -> 243686 | BE82: =SUM(BE74:BE81) -> 275524
B83: SE | AH83: 206223 | AK83: 253152 | AL83: 268477 | AM83: 287723 | AN83: 302695 | AP83: 343479 | AQ83: 363076 | AR83: 390875 | BC83: 206223 | BD83: 268477 | BE83: 343479
B84: L + SE | AH84: =SUM(AH82:AH83) -> 411976 | AK84: =SUM(AK82:AK83) -> 484275 | AL84: =SUM(AL82:AL83) -> 512163 | AM84: =SUM(AM82:AM83) -> 523013 | AN84: =SUM(AN82:AN83) -> 533898 | AP84: =SUM(AP82:AP83) -> 619003 | AQ84: =SUM(AQ82:AQ83) -> 636351 | AR84: =SUM(AR82:AR83) -> 665302 | AS84: =SUM(AS82:AS83) -> 0 | BC84: =SUM(BC82:BC83) -> 411976 | BD84: =SUM(BD82:BD83) -> 512163 | BE84: =SUM(BE82:BE83) -> 619003
B86: Assets Y/Y | BD86: =BD73/BC73-1 -> 0.2431865 | BE86: =BE73/BD73-1 -> 0.20860546
B87: Debt to Equity | BD87: =BD75/BD83 -> 0.19230698 | BE87: =BE75/BE83 -> 0.12562922
B89: Model NI | AG89: =AG41 -> 18299 | AH89: =AH41 -> 20081 | AI89: =AI41 -> 22291 | AJ89: =AJ41 -> 21870 | AK89: =AK41 -> 21939 | AL89: =AL41 -> 31987 | AM89: =AM41 -> 24667 | AN89: =AN41 -> 24108 | ... AQ89: =AQ41 -> 27747 | BD89: =AI89+AJ89+AK89+AL89 -> 98087 | BE89: =BE41 -> 101832
B90: GAAP NI | AG90: 18299 | AH90: 20081 | AI90: 22291 | AJ90: 21870 | AK90: 21939 | AL90: 22036 | AM90: 24667 | AN90: 24108 | AO90: =BE90-AP90-AM90-AN90 -> 25824 | AP90: 27233 | AQ90: 27747 | BD90: =AI90+AJ90+AK90+AL90 -> 88136 | BE90: 101832
B91: D&A | AG91: 3549 | AH91: 3874 | AI91: 3921 | AJ91: 5959 | AK91: 6027 | AL91: 6380 | AM91: 7383 | AN91: 6827 | AO91: =BE91-AP91-AM91-AN91 -> 8740 | AP91: 11203 | AQ91: 13061 | BD91: =AI91+AJ91+AK91+AL91 -> 22287 | BE91: 34153
B92: Compensation expense | AG92: 2465 | AH92: 2416 | AI92: 2507 | AJ92: 2828 | AK92: 2703 | AL92: 2696 | AM92: 2832 | AN92: 3089 | AO92: =BE92-AP92-AM92-AN92 -> 2980 | AP92: 3073 | AQ92: 2983 | BD92: =AI92+AJ92+AK92+AL92 -> 10734 | BE92: 11974
B93: Investments | AG93: -40 | AH93: 44 | AI93: 14 | AJ93: 198 | AK93: 49 | AL93: 44 | AM93: -125 | AN93: 976 | AO93: =BE93-AP93-AM93-AN93 -> -298 | AP93: 56 | AQ93: -1007 | BD93: =AI93+AJ93+AK93+AL93 -> 305 | BE93: 609
B94: Deferred income taxes | AG94: -1675 | AH94: -1888 | AI94: -568 | AJ94: -1702 | AK94: -1323 | AL94: -1145 | AM94: -1433 | AN94: -1158 | AO94: =BE94-AP94-AM94-AN94 -> -2244 | AP94: -2221 | AQ94: 2491 | BD94: =AI94+AJ94+AK94+AL94 -> -4738 | BE94: -7056
B95: A/R | AG95: -1408 | AH95: -11244 | AI95: 11034 | AJ95: -2951 | AK95: -2028 | AL95: -13246 | AM95: 14037 | AN95: -5978 | AO95: =BE95-AP95-AM95-AN95 -> -2461 | AP95: -16179 | AQ95: 16490 | BD95: =AI95+AJ95+AK95+AL95 -> -7191 | BE95: -10581
B96: Inventories | AG96: 106 | AH96: 374 | AI96: -505 | AJ96: 1474 | AK96: 260 | AL96: 55 | AM96: -373 | AN96: 711 | AO96: =BE96-AP96-AM96-AN96 -> 52 | AP96: -81 | AQ96: -192 | BD96: =AI96+AJ96+AK96+AL96 -> 1284 | BE96: 309
B97: OCA | AG97: 1152 | AH97: -2419 | AI97: -796 | AJ97: 725 | AK97: 951 | AL97: -2528 | AM97: -82 | AN97: -353 | AO97: =BE97-AP97-AM97-AN97 -> 1077 | AP97: -3686 | AQ97: -1162 | BD97: =AI97+AJ97+AK97+AL97 -> -1648 | BE97: -3044
B98: ONCA | AG98: -554 | AH98: -1548 | AI98: -2013 | AJ98: -1427 | AK98: -2137 | AL98: -1240 | AM98: -1761 | AN98: -1089 | AO98: =BE98-AP98-AM98-AN98 -> -518 | AP98: 418 | AQ98: -394 | BD98: =AI98+AJ98+AK98+AL98 -> -6817 | BE98: -2950
B99: A/P | AG99: -407 | AH99: 1311 | AI99: 1214 | AJ99: -2521 | AK99: 648 | AL99: 4204 | AM99: -916 | AN99: 958 | AO99: =BE99-AP99-AM99-AN99 -> 1179 | AP99: -652 | AQ99: -614 | BD99: =AI99+AJ99+AK99+AL99 -> 3545 | BE99: 569
B100: D/R | AG100: -181 | AH100: 14224 | AI100: -4126 | AJ100: -5538 | AK100: -645 | AL100: 15657 | AM100: -5553 | AN100: -6338 | AO100: =BE100-AP100-AM100-AN100 -> -1032 | AP100: 18361 | AQ100: -5418 | BD100: =AI100+AJ100+AK100+AL100 -> 5348 | BE100: 5438
B101: Taxes | AG101: 1414 | AH101: 681 | AI101: 1425 | AJ101: -1554 | AK101: 2622 | AL101: -806 | AM101: 1016 | AN101: -3395 | AO101: =BE101-AP101-AM101-AN101 -> 1298 | AP101: 1043 | AQ101: -2944 | BD101: =AI101+AJ101+AK101+AL101 -> 1687 | BE101: -38
... B103: ONCL | AG103: 6 | AH103: 102 | AI103: 291 | AJ103: -26 | AK103: 48 | AL103: 436 | AM103: -33 | AN103: 716 | AO103: =BE103-AP103-AM103-AN103 -> -391 | AP103: -1267 | AQ103: -477 | BD103: =AI103+AJ103+AK103+AL103 -> 749 | BE103: -975
B104: CFFO | AG104: =SUM(AG90:AG103) -> 24441 | AH104: =SUM(AH90:AH103) -> 28770 | AI104: =SUM(AI90:AI103) -> 30583 | AJ104: =SUM(AJ90:AJ103) -> 18853 | AK104: =SUM(AK90:AK103) -> 31917 | AL104: =SUM(AL90:AL103) -> 37195 | AM104: =SUM(AM90:AM103) -> 34180 | AN104: =SUM(AN90:AN103) -> 22291 | ... AQ104: =SUM(AQ90:AQ103) -> 45057 | BD104: =SUM(BD90:BD103) -> 118548 | BE104: =SUM(BE90:BE103) -> 136162
B105: Debt | AH105: -1000 | AI105: =18692+7073-1500 -> 24265 | AJ105: =-8490+10773-2916 -> -633 | AK105: =-3810+6352-11589 -> -9047 | AL105: =-1142+197-13065 -> -14010 | AM105: =-5746-966 -> -6712 | AO105: =BE105-AP105-AM105-AN105 -> -2250 | BD105: =AI105+AJ105+AK105+AL105 -> 575 | BE105: =-5746-3216 -> -8962
B106: Stock | AG106: =536-5509-5059 -> -10032 | AH106: =512-5704-5054 -> -10246 | AI106: =685-4831-5051 -> -9197 | AJ106: =261-4000-5574 -> -9313 | AK106: =522-4213-5572 -> -9263 | AL106: =534-4210-5574 -> -9250 | AM106: =706-4107-5574 -> -8975 | AN106: =256-4986-6170 -> -10900 | AO106: =BE106-AP106-AM106-AN106 -> -10404 | AP106: =548-4546-6169 -> -10167 | AQ106: =689-5650-6169 -> -11130 | BD106: =AI106+AJ106+AK106+AL106 -> -37023 | BE106: =2056-18420-24082 -> -40446
B107: Other | AG107: -258 | AH107: -167 | AI107: -307 | AJ107: -201 | AK107: -498 | AL107: -303 | AM107: -889 | AN107: -343 | AO107: =BE107-AP107-AM107-AN107 -> -382 | AP107: =-677 -> -677 | AQ107: -669 | BD107: =AI107+AJ107+AK107+AL107 -> -1309 | BE107: =-2291 -> -2291
...

Sheet AMZN
A1: Main
B3: INCOME STATEMENT | C3: Q123 | D3: Q223 | E3: Q323 | F3: Q423 | G3: Q124 | H3: Q224 | I3: Q324 | J3: Q424 | K3: Q125 | L3: Q225 | M3: Q325 | N3: Q425 | O3: Q126 | P3: Q226 | Q3: Q326 | R3: Q426 | S3: Q127 | T3: Q227 | U3: Q327 | V3: Q427 | X3: 2022 | Y3: 2023 | Z3: 2024 | AA3: 2025 | AB3: 2026 | AC3: 2027 | AD3: 2028 | AE3: 2029 | AF3: 2030 | AG3: 2031 | AH3: 2032 | AI3: 2033 | AJ3: 2034 | AK3: 2035 | AL3: 2036 | AM3: 2037 | AN3: 2038 | AO3: 2039 | AP3: 2040 | AQ3: 2041 | AR3: 2042 | AS3: 2043 | AT3: 2044 | AU3: 2045 | AV3: 2046 | AW3: 2047
B4: Online stores | G4: 54670 | H4: 55392 | I4: 61411 | J4: 75556 | K4: 57407 | L4: 61485 | M4: 67407 | X4: 220004 | Y4: 231872 | Z4: 247029
B5: Physical stores | G5: 5202 | H5: 5206 | I5: 5228 | J5: 5579 | K5: 5533 | L5: 5595 | M5: 5578 | X5: 18963 | Y5: 20030 | Z5: 21215
B6: Third-party seller services | G6: 34596 | H6: 36201 | I6: 37864 | J6: 47485 | K6: 36512 | L6: 40348 | M6: 42486 | X6: 117716 | Y6: 140053 | Z6: 156146
B7: Ad services | G7: 11824 | H7: 12771 | I7: 14331 | J7: 17288 | K7: 13921 | L7: 15694 | M7: 17703 | X7: 37739 | Y7: 46906 | Z7: 56214
B8: Subscription services | G8: 10722 | H8: 10866 | I8: 11278 | J8: 11508 | K8: 11715 | L8: 12208 | M8: 12574 | X8: 35218 | Y8: 40209 | Z8: 44374
B9: AWS | G9: 25037 | H9: 26281 | I9: 27452 | J9: 28786 | K9: 29267 | L9: 30873 | M9: 33006 | X9: 80096 | Y9: 90757 | Z9: 107556
B10: Other | G10: 1262 | H10: 1260 | I10: 1313 | J10: 1590 | K10: 1312 | L10: 1499 | M10: 1415 | X10: 4247 | Y10: 4958 | Z10: 5425
B11: Total Revenue | C11: =SUM(C4:C10) -> 0 | D11: =SUM(D4:D10) -> 0 | E11: =SUM(E4:E10) -> 0 | F11: =SUM(F4:F10) -> 0 | G11: =SUM(G4:G10) -> 143313 | H11: =SUM(H4:H10) -> 147977 | I11: =SUM(I4:I10) -> 158877 | J11: =SUM(J4:J10) -> 187792 | ... N11: =SUM(N4:N10) -> 0 | X11: =SUM(X4:X10) -> 513983 | Y11: =SUM(Y4:Y10) -> 574785 | Z11: =SUM(Z4:Z10) -> 637959
B13: AWS % in Revenue | G13: =G9/G11 -> 0.17470153 | H13: =H9/H11 -> 0.17760192 | I13: =I9/I11 -> 0.17278775 | J13: =J9/J11 -> 0.15328661 | K13: =K9/K11 -> 0.1880103 | L13: =L9/L11 -> 0.18409441 | M13: =M9/M11 -> 0.18319467 | N13: =N9/N11 -> #DIV/0! | X13: =X9/X11 -> 0.15583395 | Y13: =Y9/Y11 -> 0.1578973 | Z13: =Z9/Z11 -> 0.16859391
B15: Product sales | C15: 56981 | D15: 59032 | E15: 63171 | F15: 76703 | G15: 60915 | H15: 61569 | I15: 67601 | J15: 82226 | K15: 63970 | L15: 68246 | M15: 74058
B16: Service sales | C16: 70377 | D16: 75351 | E16: 79912 | F16: 93258 | G16: 82398 | H16: 86408 | I16: 91276 | J16: 105566 | K16: 91697 | L16: 99456 | M16: 106111
B17: Total Revenue | C17: =SUM(C15:C16) -> 127358 | D17: =SUM(D15:D16) -> 134383 | E17: =SUM(E15:E16) -> 143083 | F17: =SUM(F15:F16) -> 169961 | G17: =SUM(G15:G16) -> 143313 | H17: =SUM(H15:H16) -> 147977 | I17: =SUM(I15:I16) -> 158877 | J17: =SUM(J15:J16) -> 187792 | ... M17: =SUM(M15:M16) -> 180169 | N17: 204740 | O17: 171350 | P17: 177540 | Q17: 189490 | R17: 223600 | S17: 190020 | T17: 195570 | U17: =Q17*1.1 -> 208439 | V17: =R17*1.1 -> 245960 | X17: =242901+271082 -> 513983 | Y17: =255887+318898 -> 574785 | Z17: =272311+365648 -> 637959 | AA17: =SUM(K17:N17) -> 708278 | AB17: =SUM(O17:R17) -> 761980 | AC17: =SUM(S17:V17) -> 839989 | AD17: =AC17*(1+AC41) -> 925984.3 | AE17: =AD17*(1+AD41) -> 1020783.5 | AF17: =AE17*(1+AE41) -> 1125288 | AG17: =AF17*(1+AF41) -> 1240491.2 | AH17: =AG17*(1+AG41) -> 1367488.7 | AI17: =AH17*(1+AH41) -> 1507487.6 | AJ17: =AI17*(1+AI41) -> 1661819.2 | AK17: =AJ17*(1+AJ41) -> 1831950.8
B18: COGS | C18: 67791 | D18: 69373 | E18: 75022 | F18: 92553 | G18: 72633 | H18: 73785 | I18: 80977 | J18: 98893 | K18: 76976 | L18: 80809 | M18: 88670 | X18: 288831 | Y18: 304739 | Z18: 326288
B19: Gross Profit | C19: =C17-C18 -> 59567 | D19: =D17-D18 -> 65010 | E19: =E17-E18 -> 68061 | F19: =F17-F18 -> 77408 | G19: =G17-G18 -> 70680 | H19: =H17-H18 -> 74192 | I19: =I17-I18 -> 77900 | J19: =J17-J18 -> 88899 | ... M19: =M17-M18 -> 91499 | X19: =X17-X18 -> 225152 | Y19: =Y17-Y18 -> 270046 | Z19: =Z17-Z18 -> 311671
B20: Fulfillment | C20: 20905 | D20: 21305 | E20: 22314 | F20: 26095 | G20: 22317 | H20: 23566 | I20: 24660 | J20: 27962 | K20: 24593 | L20: 25976 | M20: 27679 | X20: 84299 | Y20: 90619 | Z20: 98505
B21: T&I | C21: 20450 | D21: 21931 | E21: 21203 | F21: 22038 | G21: 20424 | H21: 22304 | I21: 22245 | J21: 23571 | K21: 22994 | L21: 27166 | M21: 28962 | X21: 73213 | Y21: 85622 | Z21: 88544
B22: S&M | C22: 10172 | D22: 10745 | E22: 10551 | F22: 12902 | G22: 9662 | H22: 10512 | I22: 10609 | J22: 13124 | K22: 9763 | L22: 11416 | M22: 11686 | X22: 42238 | Y22: 44370 | Z22: 43907
B23: G&A | C23: 3043 | D23: 3202 | E23: 2561 | F23: 3010 | G23: 2742 | H23: 3041 | I23: 2713 | J23: 2863 | K23: 2628 | L23: 2965 | M23: 2875 | X23: 11891 | Y23: 11816 | Z23: 11359
B24: OOE | C24: 223 | D24: 146 | E24: 244 | F24: 154 | G24: 228 | H24: 97 | I24: 262 | J24: 176 | K24: 308 | L24: 199 | M24: 2875 | X24: 1263 | Y24: 767 | Z24: 763
B25: Operating Expenses | C25: =SUM(C20:C24) -> 54793 | D25: =SUM(D20:D24) -> 57329 | E25: =SUM(E20:E24) -> 56873 | F25: =SUM(F20:F24) -> 64199 | G25: =SUM(G20:G24) -> 55373 | H25: =SUM(H20:H24) -> 59520 | I25: =SUM(I20:I24) -> 60489 | J25: =SUM(J20:J24) -> 67696 | ... M25: =SUM(M20:M24) -> 74077 | X25: =SUM(X20:X24) -> 212904 | Y25: =SUM(Y20:Y24) -> 233194 | Z25: =SUM(Z20:Z24) -> 243078
B26: Operating Profit | C26: =C19-C25 -> 4774 | D26: =D19-D25 -> 7681 | E26: =E19-E25 -> 11188 | F26: =F19-F25 -> 13209 | G26: =G19-G25 -> 15307 | H26: =H19-H25 -> 14672 | I26: =I19-I25 -> 17411 | J26: =J19-J25 -> 21203 | ... M26: =M19-M25 -> 17422 | X26: =+X19-X25 -> 12248 | Y26: =+Y19-Y25 -> 36852 | Z26: =+Z19-Z25 -> 68593
B27: Interest Income | C27: =611-823-443 -> -655 | D27: =661-840+61 -> -118 | E27: =776-806+1031 -> 1001 | F27: =901-713+289 -> 477 | G27: =993-644-2673 -> -2324 | H27: =1180-589-18 -> 573 | I27: =1256-603-27 -> 626 | J27: =1248-570+468 -> 1146 | K27: =1066-541+2749 -> 3274 | L27: =1085-516+1117 -> 1686 | M27: =1100-538+10186 -> 10748 | X27: =989-2367-16806 -> -18184 | Y27: =2949-3182+938 -> 705 | Z27: =4677-2406-2250 -> 21
B28: Pretax Income | C28: =C26+C27 -> 4119 | D28: =D26+D27 -> 7563 | E28: =E26+E27 -> 12189 | F28: =F26+F27 -> 13686 | G28: =G26+G27 -> 12983 | H28: =H26+H27 -> 15245 | I28: =I26+I27 -> 18037 | J28: =J26+J27 -> 22349 | ... M28: =M26+M27 -> 28170 | X28: =X26+X27 -> -5936 | Y28: =Y26+Y27 -> 37557 | Z28: =Z26+Z27 -> 68614
B29: Taxes | C29: =-948+1 -> -947 | D29: =-804-9 -> -813 | E29: =-2306-4 -> -2310 | F29: -3062 | G29: =-2467-85 -> -2552 | H29: =-1767+7 -> -1760 | I29: =-2706-3 -> -2709 | J29: =-2325-20 -> -2345 | K29: =-4553+1 -> -4552 | L29: =-2678-15 -> -2693 | M29: -6910 | X29: =-3217+3 -> -3214 | Y29: =7120+12 -> 7132 | Z29: =9265+101 -> 9366
B30: Other | C30: 514 | D30: 293 | E30: -1323 | F30: 1963 | G30: -558 | H30: -395 | I30: 2075 | J30: 1884 | K30: -880 | M30: -73
B31: Net Income | C31: =+C28+C29+C30 -> 3686 | D31: =+D28+D29+D30 -> 7043 | E31: =+E28+E29+E30 -> 8556 | F31: =+F28+F29+F30 -> 12587 | G31: =+G28+G29+G30 -> 9873 | H31: =+H28+H29+H30 -> 13090 | I31: =+I28+I29+I30 -> 17403 | J31: =+J28+J29+J30 -> 21888 | ... M31: =+M28+M29+M30 -> 21187 | N31: 19780 | O31: 18380 | P31: 17670 | Q31: 20040 | R31: 23530 | S31: 24520 | T31: 24740 | X31: =X28-X29 -> -2722 | Y31: =Y28-Y29 -> 30425 | Z31: =Z28-Z29 -> 59248 | AA31: =SUM(K31:N31) -> 75378 | AB31: =SUM(O31:R31) -> 79620 | AC31: =AC17*AC38 -> 92811.167 | AD31: =AD17*AD38 -> 107868.77 | AE31: =AE17*AE38 -> 125036.72 | AF31: =AF17*AF38 -> 141213.44 | AG31: =AG17*AG38 -> 159391.88 | AH31: =AH17*AH38 -> 179812.36 | AI31: =AI17*AI38 -> 202743.42 | AJ31: =AJ17*AJ38 -> 228485.08 | AK31: =AK17*AK38 -> 257372.48 | AL31: =+AK31*(1+AO35) -> 254798.75 | AM31: =AL31*1.02 -> 259894.73 | AN31: =AM31*1.02 -> 265092.62 | AO31: =AN31*1.02 -> 270394.47 | AP31: =AO31*1.02 -> 275802.36 | AQ31: =AP31*1.02 -> 281318.41 | AR31: =AQ31*1.02 -> 286944.78 | AS31: =AR31*1.02 -> 292683.67 | AT31: =AS31*1.02 -> 298537.35 | AU31: =AT31*1.02 -> 304508.1 | AV31: =AU31*(1+$AO$35) -> 301463.01 | AW31: =AV31*(1+$AO$35) -> 298448.38 | AX31: =AW31*(1+$AO$35) -> 295463.9 | AY31: =AX31*(1+$AO$35) -> 292509.26 | AZ31: =AY31*(1+$AO$35) -> 289584.17 | BA31: =AZ31*(1+$AO$35) -> 286688.33 | BB31: =BA31*(1+$AO$35) -> 283821.44 | BC31: =BB31*(1+$AO$35) -> 280983.23 | ... ABT31: =ABS31*(1+$AO$35) -> 265.38126
B32: Shares | C32: 10250 | D32: 10285 | E32: 10322 | F32: 10356 | G32: 10393 | H32: 10447 | I32: 10501 | J32: 10552 | K32: 10603 | L32: 10637 | M32: 10674 | X32: 10180 | Y32: 10304 | Z32: 10473 | AA32: =Z32*1.02 -> 10682.46 | AB32: =AA32*1.02 -> 10896.109 | AC32: =AB32*1.02 -> 11114.031 | AD32: =AC32*1.02 -> 11336.312 | AE32: =AD32*1.02 -> 11563.038 | AF32: =AE32*1.02 -> 11794.299 | AG32: =AF32*1.02 -> 12030.185 | AH32: =AG32*1.02 -> 12270.789 | ... AU32: =AT32*1.02 -> 15873.574
B33: EPS | C33: =C31/C32 -> 0.35960976 | D33: =D31/D32 -> 0.68478367 | E33: =E31/E32 -> 0.82890913 | F33: =F31/F32 -> 1.2154307 | G33: =G31/G32 -> 0.94996632 | H33: =H31/H32 -> 1.2529913 | I33: =I31/I32 -> 1.6572707 | J33: =J31/J32 -> 2.0742987 | ... M33: =M31/M32 -> 1.9849166 | X33: =X31/X32 -> -0.26738703 | Y33: =Y31/Y32 -> 2.9527368 | Z33: =Z31/Z32 -> 5.6572138 | AA33: =AA31/AA32 -> 7.0562399 | AB33: =AB31/AB32 -> 7.3071955 | AC33: =AC31/AC32 -> 8.3508102 | AD33: =AD31/AD32 -> 9.5153322 | AE33: =AE31/AE32 -> 10.813484 | ... AU33: =AU31/AU32 -> 19.183336
AN35: Maturity | AO35: -0.01
B36: Gross Margin % | C36: =C19/C17 -> 0.46771306 | D36: =D19/D17 -> 0.48376655 | E36: =E19/E17 -> 0.47567496 | F36: =F19/F17 -> 0.45544566 | G36: =G19/G17 -> 0.49318624 | H36: =H19/H17 -> 0.50137521 | I36: =I19/I17 -> 0.49031641 | J36: =J19/J17 -> 0.47339077 | ... M36: =M19/M17 -> 0.50785096 | X36: =X19/X17 -> 0.4380534 | Y36: =Y19/Y17 -> 0.46982089 | Z36: =Z19/Z17 -> 0.48854393 | AN36: Discount | AO36: 0.06
B37: Operating Margin % | C37: =C25/C17 -> 0.43022818 | D37: =D26/D17 -> 0.057157527 | E37: =E26/E17 -> 0.078192378 | F37: =F26/F17 -> 0.077717829 | G37: =G26/G17 -> 0.10680818 | H37: =H26/H17 -> 0.099150544 | I37: =I26/I17 -> 0.10958792 | J37: =J26/J17 -> 0.11290683 | K37: =K26/K17 -> 0.11823315 | ... M37: =M26/M17 -> 0.0966981 | X37: =X25/X17 -> 0.41422382 | Y37: =Y25/Y17 -> 0.40570648 | Z37: =Z25/Z17 -> 0.38102449 | AN37: NPV | AO37: =NPV(AO36,AB31:ABT31)+AA31+AA49 -> 3606284.8
B38: Net Margin % | C38: =C31/C17 -> 0.028942037 | D38: =D31/D17 -> 0.052409903 | E38: =E31/E17 -> 0.05979746 | F38: =F31/F17 -> 0.074058166 | G38: =G31/G17 -> 0.068891168 | H38: =H31/H17 -> 0.088459693 | I38: =I31/I17 -> 0.10953757 | J38: =J31/J17 -> 0.11655449 | ... M38: =M31/M17 -> 0.11759515 | X38: =X31/X17 -> -0.005295895 | Y38: =Y31/Y17 -> 0.052932836 | Z38: =Z31/Z17 -> 0.092871172 | AA38: =AA31/AA17 -> 0.10642431 | AB38: =AB31/AB17 -> 0.10449093 | AC38: =+AB38+0.006 -> 0.11049093 | AD38: =+AC38+0.006 -> 0.11649093 | AE38: =+AD38+0.006 -> 0.12249093 | AF38: =+AE38+0.003 -> 0.12549093 | AG38: =+AF38+0.003 -> 0.12849093 | AH38: =+AG38+0.003 -> 0.13149093 | AI38: =+AH38+0.003 -> 0.13449093 | AJ38: =+AI38+0.003 -> 0.13749093 | AK38: =+AJ38+0.003 -> 0.14049093 | AN38: Share | AO38: =AO37/Main!I5 -> 337.85692
B39: Tax Rate % | C39: =-C29/C28 -> 0.22991017 | D39: =-D29/D28 -> 0.10749702 | E39: =-E29/E28 -> 0.18951514 | F39: =-F29/F28 -> 0.22373228 | G39: =-G29/G28 -> 0.19656474 | H39: =-H29/H28 -> 0.11544769 | I39: =-I29/I28 -> 0.15019127 | J39: =-J29/J28 -> 0.10492639 | ... M39: =-M29/M28 -> 0.24529641 | X39: =X29/X28 -> 0.54144205 | Y39: =Y29/Y28 -> 0.18989802 | Z39: =Z29/Z28 -> 0.13650275 | AN39: Current | AO39: =+Main!I4 -> 246.21
AN40: Return | AO40: =AO38/AO39-1 -> 0.3722307
B41: Revenue Y/Y | G41: =G17/C17-1 -> 0.12527678 | H41: =H17/D17-1 -> 0.10115863 | I41: =I17/E17-1 -> 0.11038348 | J41: =J17/F17-1 -> 0.1049123 | K41: =K17/G17-1 -> 0.086202926 | L41: =L17/H17-1 -> 0.13329774 | M41: =M17/I17-1 -> 0.13401562 | N41: =N17/J17-1 -> 0.090248786 | ... T41: =T17/P17-1 -> 0.10155458 | Y41: =Y17/X17-1 -> 0.11829574 | Z41: =Z17/Y17-1 -> 0.10990892 | AA41: =AA17/Z17-1 -> 0.11022495 | AB41: =AB17/AA17-1 -> 0.075820511 | AC41: =AC17/AB17-1 -> 0.1023767 | AD41: =AD17/AC17-1 -> 0.1023767 | AE41: =AE17/AD17-1 -> 0.1023767 | AF41: =AF17/AE17-1 -> 0.1023767 | ... AK41: =AK17/AJ17-1 -> 0.1023767
B42: NI Y/Y | G42: =G31/C31-1 -> 1.6785133 | H42: =H31/D31-1 -> 0.85858299 | I42: =I31/E31-1 -> 1.0340112 | J42: =J31/F31-1 -> 0.738937 | K42: =K31/G31-1 -> 0.64559911 | L42: =L31/H31-1 -> 0.38762414 | M42: =M31/I31-1 -> 0.21743378 | N42: =N31/J31-1 -> -0.09630848 | ... T42: =T31/P31-1 -> 0.40011319
B43: Products Y/Y | G43: =G15/C15-1 -> 0.069040557 | H43: =H15/D15-1 -> 0.042976691 | I43: =I15/E15-1 -> 0.070127115 | J43: =J15/F15-1 -> 0.072005006 | K43: =K15/G15-1 -> 0.050151851 | L43: =L15/H15-1 -> 0.10844743 | M43: =M15/I15-1 -> 0.095516339
B44: Services Y/Y | G44: =G16/C16-1 -> 0.17080864 | H44: =H16/D16-1 -> 0.14673992 | I44: =I16/E16-1 -> 0.14220643 | J44: =J16/F16-1 -> 0.13197795 | K44: =K16/G16-1 -> 0.11285468 | L44: =L16/H16-1 -> 0.15100454 | M44: =M16/I16-1 -> 0.16252903
B45: Product % | C45: =C15/C$17 -> 0.44740809 | D45: =D15/D$17 -> 0.43928175 | E45: =E15/E$17 -> 0.44149899 | F45: =F15/F$17 -> 0.45129765 | G45: =G15/G$17 -> 0.42504867 | H45: =H15/H$17 -> 0.41607142 | I45: =I15/I$17 -> 0.42549268 | J45: =J15/J$17 -> 0.43785678 | ... M45: =M15/M$17 -> 0.41104741
B46: Service % | C46: =C16/C$17 -> 0.55259191 | D46: =D16/D$17 -> 0.56071825 | E46: =E16/E$17 -> 0.55850101 | F46: =F16/F$17 -> 0.54870235 | G46: =G16/G$17 -> 0.57495133 | H46: =H16/H$17 -> 0.58392858 | I46: =I16/I$17 -> 0.57450732 | J46: =J16/J$17 -> 0.56214322 | ... M46: =M16/M$17 -> 0.58895259
B48: BALANCE SHEET
B49: Net Cash | F49: =F50+F51-F63-F62 -> -48831 | G49: =G50+G51-G63-G62 -> -49612 | H49: =H50+H51-H63-H62 -> -43881 | I49: =I50+I51-I63-I62 -> -46641 | J49: =J50+J51-J63-J62 -> -29698 | K49: =K50+K51-K63-K62 -> -38680 | L49: =L50+L51-L63-L62 -> -40759 | M49: =M50+M51-M63-M62 -> -41222 | Y49: =Y50+Y51-Y63-Y62 -> -48831 | Z49: =Z50+Z51-Z63-Z62 -> -29698 | AA49: =AA50+AA51-AA63-AA62 -> -38680
B50: Cash & equivalents | F50: 73387 | G50: 72852 | H50: 71178 | I50: 75091 | J50: 78779 | K50: 66207 | L50: 57741 | M50: 66922 | Y50: 73387 | Z50: 78779 | AA50: 66207
B51: Marketable securities | F51: 13393 | G51: 12222 | H51: 17914 | I51: 12960 | J51: 22423 | K51: 28358 | L51: 35439 | M51: 27275 | Y51: 13393 | Z51: 22423 | AA51: 28358
B52: Inventories | F52: 33318 | G52: 31147 | H52: 34109 | I52: 36103 | J52: 34214 | K52: 35864 | L52: 40825 | M52: 41494 | Y52: 33318 | Z52: 34214 | AA52: 35864
B53: A/R | F53: 52253 | G53: 47768 | H53: 50106 | I53: 51638 | J53: 55451 | K53: 54216 | L53: 57415 | M53: 61175 | Y53: 52253 | Z53: 55451 | AA53: 54216
B54: PP&E | F54: 204177 | G54: 209950 | H54: 220717 | I54: 237917 | J54: 252665 | K54: 272781 | L54: 297616 | M54: 324435 | Y54: 204177 | Z54: 252665 | AA54: 272781
B55: Leases | F55: 72513 | G55: 73313 | H55: 74575 | I55: 76527 | J55: 76141 | K55: 78495 | L55: 82125 | M55: 83456 | Y55: 72513 | Z55: 76141 | AA55: 78495
B56: Goodwill | F56: 22789 | G56: 22770 | H56: 22879 | I56: 23081 | J56: 23074 | K56: 23089 | L56: 23155 | M56: 23260 | Y56: 22789 | Z56: 23074 | AA56: 23089
B57: OA | F57: 56024 | G57: 60947 | H57: 63340 | I57: 71309 | J57: 82147 | K57: 84246 | L57: 87854 | M57: 99904 | Y57: 56024 | Z57: 82147 | AA57: 84246
B58: Assets | F58: =SUM(F50:F57) -> 527854 | G58: =SUM(G50:G57) -> 530969 | H58: =SUM(H50:H57) -> 554818 | I58: =SUM(I50:I57) -> 584626 | J58: =SUM(J50:J57) -> 624894 | K58: =SUM(K50:K57) -> 643256 | L58: =SUM(L50:L57) -> 682170 | M58: =SUM(M50:M57) -> 727921 | Y58: =SUM(Y50:Y57) -> 527854 | Z58: =SUM(Z50:Z57) -> 624894 | AA58: =SUM(AA50:AA57) -> 643256
B59: A/P | F59: 84981 | G59: 73068 | H59: 81817 | I59: 84570 | J59: 94363 | K59: 89241 | L59: 98285 | M59: 106032 | Y59: 84981 | Z59: 94363 | AA59: 89241
B60: Accrued Expenses | F60: 64709 | G60: 63970 | H60: 60351 | I60: 60602 | J60: 66965 | K60: 66331 | L60: 66974 | M60: 68051 | Y60: 64709 | Z60: 66965 | AA60: 66331
B61: U/R | F61: 15227 | G61: 15927 | H61: 16004 | I61: 16305 | J61: 18103 | K61: 20599 | L61: 21662 | M61: 21113 | Y61: 15227 | Z61: 18103 | AA61: 20599
B62: LTLL | F62: 77297 | G62: 77052 | H62: 78084 | I62: 79802 | J62: 78277 | K62: 79871 | L62: 83221 | M62: 84677 | Y62: 77297 | Z62: 78277 | AA62: 79871
B63: Debt | F63: 58314 | G63: 57634 | H63: 54889 | I63: 54890 | J63: 52623 | K63: 53374 | L63: 50718 | M63: 50742 | Y63: 58314 | Z63: 52623 | AA63: 53374
B64: OLTL | F64: 25451 | G64: 26657 | H64: 27226 | I64: 29306 | J64: 28593 | K64: 27973 | L64: 27535 | M64: 27675 | Y64: 25451 | Z64: 28593 | AA64: 27973
B65: Liabilities | F65: =SUM(F59:F64) -> 325979 | G65: =SUM(G59:G64) -> 314308 | H65: =SUM(H59:H64) -> 318371 | I65: =SUM(I59:I64) -> 325475 | J65: =SUM(J59:J64) -> 338924 | K65: =SUM(K59:K64) -> 337389 | L65: =SUM(L59:L64) -> 348395 | M65: =SUM(M59:M64) -> 358290 | Y65: =SUM(Y59:Y64) -> 325979 | Z65: =SUM(Z59:Z64) -> 338924 | AA65: =SUM(AA59:AA64) -> 337389
B66: S/E | F66: 201875 | G66: 216661 | H66: 236447 | I66: 259151 | J66: 285970 | K66: 305867 | L66: 333775 | M66: 369631 | Y66: 201875 | Z66: 285970 | AA66: 305867
B67: L+S/E | F67: =F66+F65 -> 527854 | G67: =SUM(G65:G66) -> 530969 | H67: =SUM(H65:H66) -> 554818 | I67: =SUM(I65:I66) -> 584626 | J67: =J66+J65 -> 624894 | K67: =SUM(K65:K66) -> 643256 | L67: =SUM(L65:L66) -> 682170 | M67: =SUM(M65:M66) -> 727921 | Y67: =Y66+Y65 -> 527854 | Z67: =Z66+Z65 -> 624894 | AA67: =SUM(AA65:AA66) -> 643256
B69: PP&E QoQ | G69: =G54/F54-1 -> 0.028274487 | H69: =H54/G54-1 -> 0.051283639 | I69: =I54/H54-1 -> 0.077927844 | J69: =J54/I54-1 -> 0.061988004 | K69: =K54/J54-1 -> 0.079615301 | L69: =L54/K54-1 -> 0.091043731 | M69: =M54/L54-1 -> 0.090112763 | N69: =N54/M54-1 -> -1 | Z69: =Z54/Y54-1 -> 0.23748023 | AA69: =AA54/Z54-1 -> 0.079615301 | AB69: =AB54/AA54-1 -> -1
B71: CASH FLOWS
B72: Model NI | C72: =C31 -> 3686 | D72: =D31 -> 7043 | E72: =E31 -> 8556 | F72: =F31 -> 12587 | G72: =G31 -> 9873 | H72: =H31 -> 13090 | I72: =I31 -> 17403 | J72: =J31 -> 21888 | ... M72: =M31 -> 21187 | X72: =X31 -> -2722 | Y72: =Y31 -> 30425 | Z72: =Z31 -> 59248 | AA72: =AA31 -> 75378
B73: BOP Cash | C73: 54253 | D73: 49734 | E73: 50067 | F73: 50081 | G73: 73890 | H73: 73332 | I73: 71673 | J73: 78677 | K73: 82312 | L73: =K98 -> 69893 | M73: =L98 -> 61453 | Y73: =C73 -> 54253 | Z73: =G73 -> 73890 | AA73: 82312
B74: GAAP NI | C74: 3172 | D74: 6750 | E74: 9879 | F74: 10624 | G74: 10431 | H74: 13485 | I74: 15328 | J74: 20004 | K74: 17127 | L74: 18164 | M74: 21187 | Y74: =SUM(C74:F74) -> 30425 | Z74: =SUM(G74:J74) -> 59248 | AA74: 17127
B75: D&A | C75: 11123 | D75: 11589 | E75: 12131 | F75: 13820 | G75: 11684 | H75: 12038 | I75: 13442 | J75: 15631 | K75: 14262 | L75: 15227 | M75: 16796 | Y75: =SUM(C75:F75) -> 48663 | Z75: =SUM(G75:J75) -> 52795 | AA75: 14262
B76: Stock Compensation | C76: 4748 | D76: 7127 | E76: 5829 | F76: 6319 | G76: 4961 | H76: 6722 | I76: 5333 | J76: 4995 | K76: 3689 | L76: 6534 | M76: 4847 | Y76: =SUM(C76:F76) -> 24023 | Z76: =SUM(G76:J76) -> 22011 | AA76: 3689
B77: Non-operating expense | C77: 534 | D77: 47 | E77: -990 | F77: -339 | G77: 2734 | H77: -95 | I77: -141 | J77: -486 | K77: -2817 | L77: -1258 | M77: -10112 | Y77: =SUM(C77:F77) -> -748 | Z77: =SUM(G77:J77) -> 2012 | AA77: -2817
B78: Deferred income taxes | C78: -472 | D78: -2744 | E78: -1196 | F78: -1464 | G78: -938 | H78: -785 | I78: -1317 | J78: -1608 | K78: 507 | L78: 11 | M78: 10130 | Y78: =SUM(C78:F78) -> -5876 | Z78: =SUM(G78:J78) -> -4648 | AA78: 507
B79: Inventories | C79: 371 | D79: -2373 | E79: 808 | F79: 2643 | G79: 1776 | H79: -3085 | I79: -1509 | J79: 934 | K79: -1222 | L79: -4054 | M79: -827 | Y79: =SUM(C79:F79) -> 1449 | Z79: =SUM(G79:J79) -> -1884 | AA79: -1222
B80: A/R | C80: 4724 | D80: -2041 | E80: -3584 | F80: -7447 | G80: 3684 | H80: -2209 | I80: -701 | J80: -4023 | K80: 1247 | L80: -1125 | M80: -1977 | Y80: =SUM(C80:F80) -> -8348 | Z80: =SUM(G80:J80) -> -3249 | AA80: 1247
B81: OA | C81: -3203 | D81: -3126 | E81: -3134 | F81: -2802 | G81: -2701 | H81: -3055 | I81: -4537 | J81: -4190 | K81: -3402 | L81: -2971 | M81: -4039 | Y81: =SUM(C81:F81) -> -12265 | Z81: =SUM(G81:J81) -> -14483 | AA81: -3402
B82: A/P | C82: -11264 | D82: 3029 | E82: 2820 | F82: 10888 | G82: -11282 | H82: 6005 | I82: -477 | J82: 8726 | K82: -9043 | L82: 7058 | M82: 2151 | Y82: =SUM(C82:F82) -> 5473 | Z82: =SUM(G82:J82) -> 2972 | AA82: -9043
B83: Accrued Expenses | C83: -5763 | D83: -1938 | E83: -1321 | F83: 6594 | G83: -2928 | H83: -4147 | I83: 129 | J83: 4042 | K83: -4061 | L83: -4952 | M83: -1999 | Y83: =SUM(C83:F83) -> -2428 | Z83: =SUM(G83:J83) -> -2904 | AA83: -4061
B84: U/R | C84: 818 | D84: 156 | E84: -25 | F84: 3629 | G84: 1568 | H84: 407 | I84: 421 | J84: 1611 | K84: 728 | L84: -119 | M84: -632 | Y84: =SUM(C84:F84) -> 4578 | Z84: =SUM(G84:J84) -> 4007 | AA84: 728
B85: CFFO | C85: =SUM(C74:C84) -> 4788 | D85: =SUM(D74:D84) -> 16476 | E85: =SUM(E74:E84) -> 21217 | F85: =SUM(F74:F84) -> 42465 | G85: =SUM(G74:G84) -> 18989 | H85: =SUM(H74:H84) -> 25281 | I85: =SUM(I74:I84) -> 25971 | J85: =SUM(J74:J84) -> 45636 | ... M85: =SUM(M74:M84) -> 35525 | Y85: =SUM(Y74:Y84) -> 84946 | Z85: =SUM(Z74:Z84) -> 115877 | AA85: =SUM(AA74:AA84) -> 17015
B86: CapEx | C86: -14207 | D86: -11455 | E86: -12479 | F86: -14588 | G86: -14925 | H86: -17620 | I86: -22620 | J86: -27834 | K86: -25019 | L86: -32183 | M86: -35095 | Y86: =SUM(C86:F86) -> -52729 | Z86: =SUM(G86:J86) -> -82999 | AA86: -25019
B87: PP&E sales | C87: 1137 | D87: 1043 | E87: 1181 | F87: 1235 | G87: 990 | H87: 1227 | I87: 1342 | J87: 1782 | K87: 764 | L87: 815 | M87: 867 | Y87: =SUM(C87:F87) -> 4596 | Z87: =SUM(G87:J87) -> 5341 | AA87: 764
B88: Non-marketable securities | C88: -3513 | D88: -316 | E88: -1629 | F88: -381 | G88: -3354 | H88: -571 | I88: -622 | J88: -2535 | K88: 48 | L88: -1700 | M88: =-786+16367 -> 15581 | Y88: =SUM(C88:F88) -> -5839 | Z88: =SUM(G88:J88) -> -7082 | AA88: 48
B89: Marketable securities | C89: =1115-338 -> 777 | D89: =1551-496 -> 1055 | E89: =1393-219 -> 1174 | F89: =1568-435 -> 1133 | G89: =1392-1965 -> -573 | H89: =3265-8439 -> -5174 | I89: =8069-3068 -> 5001 | J89: =3677-12533 -> -8856 | K89: =7737-13333 -> -5596 | L89: =11441-17797 -> -6356 | M89: -7426 | Y89: =SUM(C89:F89) -> 4139 | Z89: =SUM(G89:J89) -> -9602 | AA89: =7737-13333 -> -5596
B90: CFFI | C90: =SUM(C86:C89) -> -15806 | D90: =SUM(D86:D89) -> -9673 | E90: =SUM(E86:E89) -> -11753 | F90: =SUM(F86:F89) -> -12601 | G90: =SUM(G86:G89) -> -17862 | H90: =SUM(H86:H89) -> -22138 | I90: =SUM(I86:I89) -> -16899 | J90: =SUM(J86:J89) -> -37443 | ... M90: =SUM(M86:M89) -> -26073 | Y90: =SUM(Y86:Y89) -> -49833 | Z90: =SUM(Z86:Z89) -> -94342 | AA90: =SUM(AA86:AA89) -> -29803
B91: Short-term debt | C91: =12780-3603 -> 9177 | D91: =4399-7641 -> -3242 | E91: =216-8095 -> -7879 | F91: =734-6338 -> -5604 | G91: =338-404 -> -66 | H91: =525-229 -> 296 | I91: =1725-1820 -> -95 | J91: =2554-2607 -> -53 | K91: =1815-2082 -> -267 | L91: =2093-1392 -> 701 | M91: =3223-1826 -> 1397 | Y91: =SUM(C91:F91) -> -7548 | Z91: =SUM(G91:J91) -> 82 | AA91: =1815-2082 -> -267
B92: Long-term debt | C92: -1386 | D92: -2000 | F92: -290 | G92: -330 | H92: -4169 | I92: -2183 | J92: -2500 | K92: 746 | L92: -2751 | M92: -1008 | Y92: =SUM(C92:F92) -> -3676 | Z92: =SUM(G92:J92) -> -9182 | AA92: 746
B93: Principal of leases | C93: -1380 | D93: -1220 | E93: -1005 | F93: -779 | G93: -770 | H93: -538 | I93: -402 | J93: -333 | K93: -410 | L93: -411 | M93: -351 | Y93: =SUM(C93:F93) -> -4384 | Z93: =SUM(G93:J93) -> -2043 | AA93: -410
B94: Principal of obligations | C94: -57 | D94: -77 | E94: -64 | F94: -73 | G94: -90 | H94: -79 | I94: -78 | J94: -422 | K94: -116 | L94: -78 | M94: -82 | Y94: =SUM(C94:F94) -> -271 | Z94: =SUM(G94:J94) -> -669 | AA94: -116
B95: CFFF | C95: =SUM(C91:C94) -> 6354 | D95: =SUM(D91:D94) -> -6539 | E95: =SUM(E91:E94) -> -8948 | F95: =SUM(F91:F94) -> -6746 | G95: =SUM(G91:G94) -> -1256 | H95: =SUM(H91:H94) -> -4490 | I95: =SUM(I91:I94) -> -2758 | J95: =SUM(J91:J94) -> -3308 | ... M95: =SUM(M91:M94) -> -44 | Y95: =SUM(Y91:Y94) -> -15879 | Z95: =SUM(Z91:Z94) -> -11812 | AA95: =SUM(AA91:AA94) -> -47
B96: FX adj | C96: 145 | D96: 69 | E96: -502 | F96: 691 | G96: -429 | H96: -312 | I96: 690 | J96: -1250 | K96: 416 | L96: 1008 | M96: -397 | Y96: =SUM(C96:F96) -> 403 | Z96: =SUM(G96:J96) -> -1301 | AA96: 416
B97: CF | C97: =C85+C90+C95+C96 -> -4519 | D97: =D85+D90+D95+D96 -> 333 | E97: =E85+E90+E95+E96 -> 14 | F97: =F85+F90+F95+F96 -> 23809 | G97: =G85+G90+G95+G96 -> -558 | H97: =H85+H90+H95+H96 -> -1659 | I97: =I85+I90+I95+I96 -> 7004 | J97: =J85+J90+J95+J96 -> 3635 | ... M97: =M85+M90+M95+M96 -> 9011 | Y97: =Y85+Y90+Y95+Y96 -> 19637 | Z97: =Z85+Z90+Z95+Z96 -> 8422 | AA97: =AA85+AA90+AA95+AA96 -> -12419
B98: EOP Cash | C98: =C73+C97 -> 49734 | D98: =D73+D97 -> 50067 | E98: =E73+E97 -> 50081 | F98: =F73+F97 -> 73890 | G98: =G73+G97 -> 73332 | H98: =H73+H97 -> 71673 | I98: =I73+I97 -> 78677 | J98: =J73+J97 -> 82312 | ... M98: =M73+M97 -> 70464 | Y98: =SUM(C98:F98) -> 223772 | Z98: =SUM(G98:J98) -> 305994 | AA98: =AA73+AA97 -> 69893
B101: FCF | C101: =+C85+C86 -> -9419 | D101: =+D85+D86 -> 5021 | E101: =+E85+E86 -> 8738 | F101: =+F85+F86 -> 27877 | G101: =+G85+G86 -> 4064 | H101: =+H85+H86 -> 7661 | I101: =+I85+I86 -> 3351 | J101: =+J85+J86 -> 17802 | ... M101: =+M85+M86 -> 430 | Z101: =+Z85+Z86 -> 32878 | AA101: =+AA85+AA86 -> -8004
B102: CapEx Margin | C102: =-C86/C72 -> 3.8543136 | D102: =-D86/D72 -> 1.6264376 | E102: =-E86/E72 -> 1.4585086 | F102: =-F86/F72 -> 1.1589735 | G102: =-G86/G72 -> 1.5116986 | H102: =-H86/H72 -> 1.3460657 | I102: =-I86/I72 -> 1.2997759 | J102: =-J86/J72 -> 1.2716557 | ... M102: =-M86/M72 -> 1.6564403 | Z102: =-Z86/Z72 -> 1.4008743 | AA102: =-AA86/AA72 -> 0.33191382
B104: CapEx YoY | G104: =G86/C86-1 -> 0.050538467 | H104: =H86/D86-1 -> 0.53819293 | I104: =I86/E86-1 -> 0.81264524 | J104: =J86/F86-1 -> 0.90800658 | K104: =K86/G86-1 -> 0.67631491 | L104: =L86/H86-1 -> 0.82650397 | M104: =M86/I86-1 -> 0.55150309

Sheet AAPL
A1: Main | C1: CONFIRMED | L1: FORECAST | W1: FORECAST
B2: INCOME STATEMEMENT | C2: Q123 | D2: Q223 | E2: Q323 | F2: Q423 | G2: Q124 | H2: Q224 | I2: Q324 | J2: Q424 | K2: Q125 | L2: Q225 | M2: Q325 | N2: Q425 | O2: Q126 | P2: Q226 | T2: FY23 | U2: FY24 | V2: FY25 | W2: FY26 | X2: FY27 | Y2: FY28 | Z2: FY29 | AA2: FY30 | AB2: FY31 | AC2: FY32 | AD2: FY33 | AE2: FY34 | AF2: FY35 | AG2: FY36 | AH2: FY37 | AI2: FY38 | AJ2: FY39 | AK2: FY40 | AL2: FY41 | AM2: FY42 | AN2: FY43 | AO2: FY44 | AP2: FY45 | AQ2: FY46 | AR2: FY47 | AS2: FY48 | AT2: FY49 | AU2: FY50 | AV2: FY51 | AW2: FY52 | AX2: FY53 | AY2: FY54 | AZ2: FY55 | BA2: FY56 | BB2: FY57 | BC2: FY58 | BD2: FY59 | BE2: FY60 | BF2: FY61 | BG2: FY62 | BH2: FY63 | BI2: FY64 | BJ2: FY65 | BK2: FY66 | BL2: FY67 | BM2: FY68 | BN2: FY69 | BO2: FY70 | BP2: FY71 | BQ2: FY72 | BR2: FY73 | BS2: FY74 | BT2: FY75 | BU2: FY76 | BV2: FY77 | BW2: FY78 | BX2: FY79 | BY2: FY80 | BZ2: FY81 | CA2: FY82 | CB2: FY83 | CC2: FY84 | CD2: FY85 | CE2: FY86 | CF2: FY87 | CG2: FY88 | CH2: FY89 | CI2: FY90 | CJ2: FY91 | CK2: FY92 | CL2: FY93 | CM2: FY94 | CN2: FY95 | CO2: FY96 | CP2: FY97 | CQ2: FY98 | CR2: FY99 | CS2: FY100 | CT2: FY101 | CU2: FY102 | CV2: FY103 | CW2: FY104 | CX2: FY105 | CY2: FY106 | CZ2: FY107 | DA2: FY108 | DB2: FY109 | DC2: FY110 | DD2: FY111 | DE2: FY112 | DF2: FY113 | DG2: FY114 | DH2: FY115 | DI2: FY116 | DJ2: FY117 | DK2: FY118 | DL2: FY119 | DM2: FY120 | DN2: FY121 | DO2: FY122 | DP2: FY123 | DQ2: FY124 | DR2: FY125 | DS2: FY126 | DT2: FY127 | DU2: FY128 | DV2: FY129 | DW2: FY130 | DX2: FY131 | DY2: FY132 | DZ2: FY133 | EA2: FY134 | EB2: FY135 | EC2: FY136 | ED2: FY137 | EE2: FY138 | EF2: FY139 | EG2: FY140 | EH2: FY141 | EI2: FY142 | EJ2: FY143 | EK2: FY144 | EL2: FY145 | EM2: FY146 | EN2: FY147 | EO2: FY148 | EP2: FY149 | EQ2: FY150 | ER2: FY151 | ES2: FY152 | ET2: FY153 | EU2: FY154 | EV2: FY155 | EW2: FY156 | EX2: FY157 | EY2: FY158 | EZ2: FY159 | FA2: FY160 | FB2: FY161 | FC2: FY162 | FD2: FY163 | FE2: FY164 | FF2: FY165 | FG2: FY166 | FH2: FY167 | FI2: FY168 | FJ2: FY169 | FK2: FY170 | FL2: FY171 | FM2: FY172 | FN2: FY173 | FO2: FY174 | FP2: FY175 | FQ2: FY176 | FR2: FY177 | FS2: FY178 | FT2: FY179 | FU2: FY180 | FV2: FY181 | FW2: FY182 | FX2: FY183 | FY2: FY184 | FZ2: FY185 | GA2: FY186 | GB2: FY187 | GC2: FY188 | GD2: FY189 | GE2: FY190 | GF2: FY191 | GG2: FY192 | GH2: FY193 | GI2: FY194 | GJ2: FY195 | GK2: FY196 | GL2: FY197 | GM2: FY198 | GN2: FY199 | GO2: FY200 | GP2: FY201 | GQ2: FY202 | GR2: FY203 | GS2: FY204 | GT2: FY205 | GU2: FY206 | GV2: FY207 | GW2: FY208 | GX2: FY209 | GY2: FY210 | GZ2: FY211 | HA2: FY212 | HB2: FY213 | HC2: FY214 | HD2: FY215 | HE2: FY216 | HF2: FY217 | HG2: FY218 | HH2: FY219 | HI2: FY220 | HJ2: FY221 | HK2: FY222 | HL2: FY223 | HM2: FY224 | HN2: FY225 | HO2: FY226 | HP2: FY227 | HQ2: FY228 | HR2: FY229 | HS2: FY230 | HT2: FY231 | HU2: FY232 | HV2: FY233 | HW2: FY234 | HX2: FY235 | HY2: FY236 | HZ2: FY237 | IA2: FY238 | IB2: FY239 | IC2: FY240 | ID2: FY241 | IE2: FY242 | IF2: FY243 | IG2: FY244 | IH2: FY245 | II2: FY246 | IJ2: FY247 | IK2: FY248 | IL2: FY249 | IM2: FY250 | IN2: FY251 | IO2: FY252 | IP2: FY253 | IQ2: FY254 | IR2: FY255 | IS2: FY256 | IT2: FY257 | IU2: FY258 | IV2: FY259 | IW2: FY260 | IX2: FY261 | IY2: FY262 | IZ2: FY263 | JA2: FY264 | JB2: FY265 | JC2: FY266 | JD2: FY267 | JE2: FY268 | JF2: FY269 | JG2: FY270 | JH2: FY271 | JI2: FY272 | JJ2: FY273 | JK2: FY274 | JL2: FY275 | JM2: FY276 | JN2: FY277 | JO2: FY278 | JP2: FY279 | JQ2: FY280 | JR2: FY281 | JS2: FY282 | JT2: FY283 | JU2: FY284 | JV2: FY285
B3: Products | G3: 96458 | H3: 66886 | I3: 61564 | J3: 69958 | K3: 97960 | L3: 68714 | M3: 66613 | N3: 73716 | O3: 113743 | U3: 294866 | V3: 307003
B4: Services | G4: 23117 | H4: 23867 | I4: 24213 | J4: 24972 | K4: 26340 | L4: 26645 | M4: 27423 | N4: 28750 | O4: 30013 | U4: 96169 | V4: 109158
B5: Revenue | C5: 117154 | D5: =73929+20907 -> 94836 | E5: 81797 | F5: =383285-SUM(C5:E5) -> 89498 | G5: 119575 | H5: =SUM(H3:H4) -> 90753 | I5: =SUM(I3:I4) -> 85777 | J5: =SUM(J3:J4) -> 94930 | K5: 124300 | L5: =SUM(L3:L4) -> 95359 | M5: =SUM(M3:M4) -> 94036 | N5: =SUM(N3:N4) -> 102466 | O5: =SUM(O3:O4) -> 143756 | P5: =SUM(P3:P4) -> 0 | T5: =SUM(C5:F5) -> 383285 | U5: =SUM(G5:J5) -> 391035 | V5: =SUM(K5:N5) -> 416161 | W5: =V5*1.015 -> 422403.41 | X5: =W5*1.015 -> 428739.47 | Y5: =X5*1.015 -> 435170.56 | Z5: =Y5*1.015 -> 441698.12 | AA5: =Z5*1.015 -> 448323.59 | AB5: =AA5*1.015 -> 455048.44 | AC5: =AB5*1.015 -> 461874.17 | AD5: =AC5*1.015 -> 468802.28 | ... AG5: =AF5*1.015 -> 490216.41
B6: Products | G6: 58440 | H6: 42424 | I6: 39803 | J6: 44566 | K6: 59447 | L6: 44030 | M6: 43620 | N6: 47019 | O6: 67478 | U6: 185233 | V6: 194116
B7: Services | G7: 6280 | H7: 6058 | I7: 6296 | J7: 6485 | K7: 6578 | L7: 6462 | M7: 6698 | N7: 7106 | O7: 7047 | U7: 25119 | V7: 26844
B8: COGS | C8: 66822 | D8: =46795+6065 -> 52860 | E8: 45384 | F8: =214137-SUM(C8:E8) -> 49071 | G8: 64720 | H8: =SUM(H6:H7) -> 48482 | I8: =SUM(I6:I7) -> 46099 | J8: =SUM(J6:J7) -> 51051 | K8: =SUM(K6:K7) -> 66025 | L8: =SUM(L6:L7) -> 50492 | M8: =SUM(M6:M7) -> 50318 | N8: =SUM(N6:N7) -> 54125 | O8: =SUM(O6:O7) -> 74525 | P8: =SUM(P6:P7) -> 0 | T8: =SUM(C8:F8) -> 214137 | U8: =SUM(U6:U7) -> 210352 | V8: =SUM(V6:V7) -> 220960 | W8: =W5-W9 -> 226226.41 | X8: =X5-X9 -> 226677.15 | Y8: =Y5-Y9 -> 227046.37 | Z8: =Z5-Z9 -> 227330.21 | AA8: =AA5-AA9 -> 227524.64 | AB8: =AB5-AB9 -> 227625.53 | AC8: =AC5-AC9 -> 227628.57 | AD8: =AD5-AD9 -> 227529.31 | ... AG8: =AG5-AG9 -> 226570.92
B9: Gross profit | C9: =+C5-C8 -> 50332 | D9: =+D5-D8 -> 41976 | E9: =+E5-E8 -> 36413 | F9: =+F5-F8 -> 40427 | G9: =+G5-G8 -> 54855 | H9: =+H5-H8 -> 42271 | I9: =+I5-I8 -> 39678 | J9: =+J5-J8 -> 43879 | ... P9: =+P5-P8 -> 0 | T9: =T5-T8 -> 169148 | U9: =+U5-U8 -> 180683 | V9: =+V5-V8 -> 195201 | W9: =V9*1.005 -> 196177 | X9: =W9*1.03 -> 202062.32 | Y9: =X9*1.03 -> 208124.18 | Z9: =Y9*1.03 -> 214367.91 | AA9: =Z9*1.03 -> 220798.95 | AB9: =AA9*1.03 -> 227422.92 | AC9: =AB9*1.03 -> 234245.6 | AD9: =AC9*1.03 -> 241272.97 | AE9: =AD9*1.03 -> 248511.16 | ... AG9: =AF9*1.03 -> 263645.49
B10: R&D | C10: 7709 | D10: 7457 | E10: 7442 | F10: =29915-SUM(C10:E10) -> 7307 | G10: 7696 | H10: 7903 | I10: 8006 | J10: =31370-SUM(G10:I10) -> 7765 | K10: 8268 | L10: 8550 | M10: 8866 | N10: 8866 | O10: 10887 | T10: =SUM(C10:F10) -> 29915 | U10: 31370 | V10: 34550 | W10: =V10*1.045 -> 36104.75 | X10: =W10*1.045 -> 37729.464 | Y10: =X10*1.045 -> 39427.29 | Z10: =Y10*1.045 -> 41201.518 | AA10: =Z10*1.045 -> 43055.586 | AB10: =AA10*1.045 -> 44993.087 | AC10: =AB10*1.045 -> 47017.776 | AD10: =AC10*1.045 -> 49133.576 | ... AG10: =AF10*1.045 -> 56069.573
B11: SG&A | C11: 6607 | D11: 6201 | E11: 5973 | F11: =24932-SUM(C11:E11) -> 6151 | G11: 6786 | H11: 6468 | I11: 6320 | J11: =26097-SUM(G11:I11) -> 6523 | K11: 7175 | L11: 6728 | M11: 6650 | N11: 7048 | O11: 7492 | T11: =SUM(C11:F11) -> 24932 | U11: 26097 | V11: 27601 | W11: =V11*1.045 -> 28843.045 | X11: =W11*1.045 -> 30140.982 | Y11: =X11*1.045 -> 31497.326 | Z11: =Y11*1.045 -> 32914.706 | AA11: =Z11*1.045 -> 34395.868 | AB11: =AA11*1.045 -> 35943.682 | AC11: =AB11*1.045 -> 37561.147 | AD11: =AC11*1.045 -> 39251.399 | ... AG11: =AF11*1.045 -> 44792.367
B12: Operating Expenses | C12: =+C10+C11 -> 14316 | D12: =+D10+D11 -> 13658 | E12: =+E10+E11 -> 13415 | F12: =+F10+F11 -> 13458 | G12: =+G10+G11 -> 14482 | H12: =+H10+H11 -> 14371 | I12: =+I10+I11 -> 14326 | J12: =+J10+J11 -> 14288 | K12: =K10+K11 -> 15443 | L12: =+L10+L11 -> 15278 | M12: =+M10+M11 -> 15516 | N12: =+N10+N11 -> 15914 | O12: =+O10+O11 -> 18379 | P12: =+P10+P11 -> 0 | T12: =SUM(T10:T11) -> 54847 | U12: =SUM(U10:U11) -> 57467 | V12: =SUM(V10:V11) -> 62151 | W12: =SUM(W10:W11) -> 64947.795 | X12: =SUM(X10:X11) -> 67870.446 | Y12: =SUM(Y10:Y11) -> 70924.616 | Z12: =SUM(Z10:Z11) -> 74116.224 | AA12: =SUM(AA10:AA11) -> 77451.454 | ... AG12: =SUM(AG10:AG11) -> 100861.94
B13: Operating profit | C13: =+C9-C12 -> 36016 | D13: =+D9-D12 -> 28318 | E13: =+E9-E12 -> 22998 | F13: =+F9-F12 -> 26969 | G13: =+G9-G12 -> 40373 | H13: =+H9-H12 -> 27900 | I13: =+I9-I12 -> 25352 | J13: =+J9-J12 -> 29591 | K13: =K9-K12 -> 42832 | L13: =+L9-L12 -> 29589 | M13: =+M9-M12 -> 28202 | N13: =+N9-N12 -> 32427 | O13: =+O9-O12 -> 50852 | P13: =+P9-P12 -> 0 | T13: =T9-T12 -> 114301 | U13: =U9-U12 -> 123216 | V13: =V9-V12 -> 133050 | W13: =W9-W12 -> 131229.21 | X13: =X9-X12 -> 134191.87 | Y13: =Y9-Y12 -> 137199.57 | Z13: =Z9-Z12 -> 140251.69 | AA13: =AA9-AA12 -> 143347.49 | ... AG13: =AG9-AG12 -> 162783.55
B14: Interest Income | C14: -393 | D14: 64 | E14: -265 | F14: =-565-SUM(C14:E14) -> 29 | G14: -50 | H14: 158 | I14: 142 | J14: =269-SUM(G14:I14) -> 19 | K14: -248 | L14: -279 | M14: -171 | N14: 377 | O14: 150 | T14: =SUM(C14:F14) -> -565 | U14: 269 | V14: -321 | W14: =-AVERAGE(T14:V14)*0.6 -> 123.4 | X14: =W14*0.95 -> 117.23 | Y14: =X14*0.95 -> 111.3685 | Z14: =Y14*0.95 -> 105.80007 | AA14: =Z14*0.95 -> 100.51007 | AB14: =AA14*0.95 -> 95.484568 | AC14: =AB14*0.95 -> 90.710339 | AD14: =AC14*0.95 -> 86.174822 | AE14: =AD14*0.95 -> 81.866081 | ... AG14: =AF14*0.95 -> 73.884138
B15: Pretax Income | C15: =+C13+C14 -> 35623 | D15: =+D13+D14 -> 28382 | E15: =+E13+E14 -> 22733 | F15: =+F13+F14 -> 26998 | G15: =+G13+G14 -> 40323 | H15: =+H13+H14 -> 28058 | I15: =+I13+I14 -> 25494 | J15: =+J13+J14 -> 29610 | K15: =K13+K14 -> 42584 | L15: =+L13+L14 -> 29310 | M15: =+M13+M14 -> 28031 | N15: =+N13+N14 -> 32804 | O15: =+O13+O14 -> 51002 | P15: =+P13+P14 -> 0 | T15: =T13+T14 -> 113736 | U15: =U13+U14 -> 123485 | V15: =V13+V14 -> 132729 | W15: =W13+W14 -> 131352.61 | X15: =X13+X14 -> 134309.1 | Y15: =Y13+Y14 -> 137310.94 | Z15: =Z13+Z14 -> 140357.49 | AA15: =AA13+AA14 -> 143448 | ... AG15: =AG13+AG14 -> 162857.43
B16: Taxes | C16: 5625 | D16: 4222 | E16: 2852 | F16: =16741-SUM(C16:E16) -> 4042 | G16: 6407 | H16: 4422 | I16: 4046 | J16: =29749-SUM(G16:I16) -> 14874 | K16: 6254 | L16: 4530 | M16: 4597 | N16: 5338 | O16: 8905 | T16: =SUM(C16:F16) -> 16741 | U16: 29749 | V16: 20719 | W16: =W15*0.15 -> 19702.891 | X16: =X15*0.15 -> 20146.365 | Y16: =Y15*0.15 -> 20596.641 | Z16: =Z15*0.15 -> 21053.623 | AA16: =AA15*0.15 -> 21517.201 | AB16: =AB15*0.15 -> 21987.245 | AC16: =AC15*0.15 -> 22463.609 | AD16: =AD15*0.15 -> 22946.126 | ... AG16: =AG15*0.15 -> 24428.615
B17: Net Income | C17: =+C15-C16 -> 29998 | D17: =+D15-D16 -> 24160 | E17: =+E15-E16 -> 19881 | F17: =+F15-F16 -> 22956 | G17: =+G15-G16 -> 33916 | H17: =+H15-H16 -> 23636 | I17: =+I15-I16 -> 21448 | J17: =+J15-J16 -> 14736 | ... P17: =+P15-P16 -> 0 | T17: =T15-T16 -> 96995 | U17: =U15-U16 -> 93736 | V17: =V15-V16 -> 112010 | W17: =W15-W16 -> 111649.72 | X17: =X15-X16 -> 114162.73 | Y17: =Y15-Y16 -> 116714.3 | Z17: =Z15-Z16 -> 119303.86 | AA17: =AA15-AA16 -> 121930.8 | ... AG17: =AG15-AG16 -> 138428.82 | AH17: =AG17*(1+$AJ$22) -> 136352.39 | AI17: =AH17*(1+$AJ$22) -> 134307.1 | AJ17: =AI17*(1+$AJ$22) -> 132292.49 | AK17: =AJ17*(1+$AJ$22) -> 130308.11 | AL17: =AK17*(1+$AJ$22) -> 128353.49 | AM17: =AL17*(1+$AJ$22) -> 126428.18 | AN17: =AM17*(1+$AJ$22) -> 124531.76 | AO17: =AN17*(1+$AJ$22) -> 122663.78 | ... JV17: =JU17*(1+$AJ$22) -> 3212.5353
B18: Shares | C18: 15892.72 | D18: 15787.15 | E18: 15697.61 | F18: 15744.231 | G18: 15576.641 | H18: 15405.86 | I18: 15287.52 | J18: 15171.99 | K18: 15150.865 | L18: 14994 | M18: 14903 | N18: 14815.307 | O18: 14748.158 | T18: 15744.231 | U18: 15343.783 | V18: 14948.5 | W18: =V18*0.99 -> 14799.015 | X18: =W18*0.99 -> 14651.025 | Y18: =X18*0.99 -> 14504.515 | Z18: =Y18*0.99 -> 14359.469 | AA18: =Z18*0.99 -> 14215.875 | AB18: =AA18*0.99 -> 14073.716 | AC18: =AB18*0.99 -> 13932.979 | AD18: =AC18*0.99 -> 13793.649 | ... AG18: =AF18*0.99 -> 13383.964
B19: EPS | C19: =+C17/C18 -> 1.8875309 | D19: =+D17/D18 -> 1.5303586 | E19: =+E17/E18 -> 1.2664985 | F19: =+F17/F18 -> 1.4580579 | G19: =+G17/G18 -> 2.1773629 | H19: =+H17/H18 -> 1.5342214 | I19: =+I17/I18 -> 1.4029745 | J19: =+J17/J18 -> 0.97126349 | ... P19: =+P17/P18 -> #DIV/0! | T19: =AVERAGE(C19:F19) -> 1.5356115 | U19: =AVERAGE(G19:J19) -> 1.5214556 | V19: =V17/V18 -> 7.4930595 | W19: =W17/W18 -> 7.544402 | X19: =X17/X18 -> 7.792133 | Y19: =Y17/Y18 -> 8.0467565 | Z19: =Z17/Z18 -> 8.3083755 | AA19: =AA17/AA18 -> 8.5770876 | AB19: =AB17/AB18 -> 8.8529843 | AC19: =AC17/AC18 -> 9.1361498 | ... AG19: =AG17/AG18 -> 10.342887
B22: Gross margin % | C22: =+C9/C5 -> 0.42962255 | D22: =+D9/D5 -> 0.44261673 | E22: =+E9/E5 -> 0.44516303 | F22: =+F9/F5 -> 0.45170842 | G22: =+G9/G5 -> 0.45874974 | H22: =+H9/H5 -> 0.46578075 | I22: =+I9/I5 -> 0.46257155 | J22: =+J9/J5 -> 0.4622248 | ... P22: =+P9/P5 -> #DIV/0! | T22: =T9/T5 -> 0.4413113 | U22: =U9/U5 -> 0.4620635 | V22: =V9/V5 -> 0.46905164 | W22: =W9/W5 -> 0.46443044 | X22: =X9/X5 -> 0.47129395 | Y22: =Y9/Y5 -> 0.47825888 | Z22: =Z9/Z5 -> 0.48532675 | AA22: =AA9/AA5 -> 0.49249906 | ... AG22: =AG9/AG5 -> 0.5378145 | AI22: Maturity Value | AJ22: -0.015
B23: Operating Margin % | C23: =+C13/C5 -> 0.30742442 | D23: =+D13/D5 -> 0.29859969 | E23: =+E13/E5 -> 0.28115946 | F23: =+F13/F5 -> 0.30133634 | G23: =+G13/G5 -> 0.33763747 | H23: =+H13/H5 -> 0.30742785 | I23: =+I13/I5 -> 0.29555708 | J23: =+J13/J5 -> 0.31171389 | ... P23: =+P13/P5 -> #DIV/0! | T23: =T13/T5 -> 0.29821412 | U23: =U13/U5 -> 0.31510223 | V23: =V13/V5 -> 0.319708 | W23: =W13/W5 -> 0.3106727 | X23: =X13/X5 -> 0.31299164 | Y23: =Y13/Y5 -> 0.31527769 | Z23: =Z13/Z5 -> 0.31752838 | AA23: =AA13/AA5 -> 0.31974114 | ... AG23: =AG13/AG5 -> 0.33206467 | AI23: Discount Rate | AJ23: 0.0625
B24: Net Margin % | C24: =+C17/C5 -> 0.25605613 | D24: =+D17/D5 -> 0.25475558 | E24: =+E17/E5 -> 0.24305292 | F24: =+F17/F5 -> 0.25649735 | G24: =+G17/G5 -> 0.28363788 | H24: =+H17/H5 -> 0.26044318 | I24: =+I17/I5 -> 0.25004372 | J24: =+J17/J5 -> 0.15523017 | ... P24: =+P17/P5 -> #DIV/0! | T24: =T17/T5 -> 0.25306234 | U24: =U17/U5 -> 0.23971256 | V24: =V17/V5 -> 0.26915064 | W24: =W16/W5 -> 0.046644726 | X24: =X17/X5 -> 0.26627531 | Y24: =Y17/Y5 -> 0.26820357 | Z24: =Z17/Z5 -> 0.27010272 | AA24: =AA17/AA5 -> 0.27197053 | AB24: =AB17/AB5 -> 0.27380467 | AC24: =AC17/AC5 -> 0.27560273 | AD24: =AD17/AD5 -> 0.27736223 | AE24: =AE17/AE5 -> 0.27908058 | ... AG24: =AG17/AG5 -> 0.28238308 | AI24: NPV | AJ24: =NPV(AJ23,W17:JV17)+V17 -> 1974195.6
B25: Tax Rate % | C25: =+C16/C15 -> 0.1579036 | D25: =+D16/D15 -> 0.14875625 | E25: =+E16/E15 -> 0.12545638 | F25: =+F16/F15 -> 0.14971479 | G25: =+G16/G15 -> 0.15889195 | H25: =+H16/H15 -> 0.15760211 | I25: =+I16/I15 -> 0.15870401 | J25: =+J16/J15 -> 0.50233029 | ... P25: =+P16/P15 -> #DIV/0! | T25: =T16/T15 -> 0.14719174 | U25: =U16/U15 -> 0.24091185 | V25: =V16/V15 -> 0.15610002 | W25: =W16/W15 -> 0.15 | X25: =X16/X15 -> 0.15 | Y25: =Y16/Y15 -> 0.15 | Z25: =Z16/Z15 -> 0.15 | AA25: =AA16/AA15 -> 0.15 | ... AG25: =AG16/AG15 -> 0.15 | AI25: Net Cash | AJ25: =Main!F7-Main!F8 -> 54286
B27: Product margin | H27: =(H3-H6)/H3 -> 0.36572676 | I27: =(I3-I6)/I3 -> 0.35346956 | J27: =(J3-J6)/J3 -> 0.36296063 | K27: =(K3-K6)/K3 -> 0.39315027 | L27: =(L3-L6)/L3 -> 0.3592281 | M27: =(M3-M6)/M3 -> 0.34517286 | N27: =(N3-N6)/N3 -> 0.36216018 | O27: =(O3-O6)/O3 -> 0.40675031 | P27: =(P3-P6)/P3 -> #DIV/0!
B28: Service margin | H28: =(H4-H7)/H4 -> 0.74617673 | I28: =(I4-I7)/I4 -> 0.73997439 | J28: =(J4-J7)/J4 -> 0.74030915 | K28: =(K4-K7)/K4 -> 0.75026576 | L28: =(L4-L7)/L4 -> 0.75747795 | M28: =(M4-M7)/M4 -> 0.75575247 | N28: =(N4-N7)/N4 -> 0.75283478 | O28: =(O4-O7)/O4 -> 0.76520175 | P28: =(P4-P7)/P4 -> #DIV/0!
AI29: Total Value | AJ29: =AJ24+AJ25 -> 2028481.6
B30: Revenue Y/Y | G30: =G5/C5-1 -> 0.020665107 | H30: =H5/D5-1 -> -0.043053271 | I30: =I5/E5-1 -> 0.048657041 | J30: =J5/F5-1 -> 0.060694094 | K30: =K5/G5-1 -> 0.039514949 | L30: =L5/H5-1 -> 0.050753143 | M30: =M5/I5-1 -> 0.096284552 | N30: =N5/J5-1 -> 0.07938481 | ... P30: =P5/L5-1 -> -1 | U30: =U5/T5-1 -> 0.020219941 | V30: =V5/U5-1 -> 0.064255118 | W30: =W5/V5-1 -> 0.015 | X30: =X5/W5-1 -> 0.015 | Y30: =Y5/X5-1 -> 0.015 | Z30: =Z5/Y5-1 -> 0.015 | AA30: =AA5/Z5-1 -> 0.015 | AB30: =AB5/AA5-1 -> 0.015 | ... AG30: =AG5/AF5-1 -> 0.015 | AI30: Per Share | AJ30: =AJ29/Main!F5 -> 137.54135
B31: Product R Y/Y | K31: =K3/G3-1 -> 0.015571544 | L31: =L3/H3-1 -> 0.027330084 | M31: =M3/I3-1 -> 0.082012215 | N31: =N3/J3-1 -> 0.053717945 | O31: =O3/K3-1 -> 0.16111678 | P31: =P3/L3-1 -> -1
B32: Service R Y/Y | K32: =K4/G4-1 -> 0.13942121 | L32: =L4/H4-1 -> 0.11639502 | M32: =M4/I4-1 -> 0.13257341 | N32: =N4/J4-1 -> 0.15128944 | O32: =O4/K4-1 -> 0.13944571 | P32: =P4/L4-1 -> -1
B34: Revenue to SG&A | C34: =C5/C11 -> 17.7318 | D34: =D5/D11 -> 15.293662 | E34: =E5/E11 -> 13.694458 | F34: =F5/F11 -> 14.550154 | G34: =G5/G11 -> 17.620837 | H34: =H5/H11 -> 14.031076 | I34: =I5/I11 -> 13.57231 | J34: =J5/J11 -> 14.55312 | ... P34: =P5/P11 -> #DIV/0! | AI34: Current Price | AJ34: =Main!F4 -> 273.94
B36: Revenue by region
B37: Americas | G37: 50430 | H37: 37273 | I37: 37678 | J37: 41664 | K37: 52648 | L37: 40315 | M37: 41198 | N37: 44192 | O37: 58529 | U37: 167045 | V37: 178353
B38: Europe | G38: 30397 | H38: 24123 | I38: 21884 | J38: 24924 | K38: 33861 | L38: 24454 | M38: 24014 | N38: 28703 | O38: 38146 | U38: 101328 | V38: 111032
B39: Greater China | G39: 20819 | H39: 16372 | I39: 14728 | J39: 15033 | K39: 18513 | L39: 16002 | M39: 15369 | N39: 14493 | O39: 25526 | U39: 66952 | V39: 64377
B40: Japan | G40: 7767 | H40: 6262 | I40: 5097 | J40: 5926 | K40: 8987 | L40: 7298 | M40: 5782 | N40: 6636 | O40: 9413 | U40: 25052 | V40: 28703
B41: Rest of Asia Pacific | G41: 10162 | H41: 6723 | I41: 6390 | J41: 7383 | K41: 10291 | L41: 7290 | M41: 7673 | N41: 8442 | O41: 12142 | U41: 30658 | V41: 33696
B42: Total | G42: =SUM(G37:G41) -> 119575 | H42: =SUM(H37:H41) -> 90753 | I42: =SUM(I37:I41) -> 85777 | J42: =SUM(J37:J41) -> 94930 | K42: =SUM(K37:K41) -> 124300 | L42: =SUM(L37:L41) -> 95359 | M42: =SUM(M37:M41) -> 94036 | N42: =SUM(N37:N41) -> 102466 | ... P42: =SUM(P37:P41) -> 0 | U42: =SUM(U37:U41) -> 391035 | V42: =SUM(V37:V41) -> 416161 | W42: =SUM(W37:W41) -> 0
B44: YoY Growth
B45: Americas | K45: =K37/G37-1 -> 0.043981757 | L45: =L37/H37-1 -> 0.081614037 | M45: =M37/I37-1 -> 0.093423218 | N45: =N37/J37-1 -> 0.060675883 | O45: =O37/K37-1 -> 0.11170415 | P45: =P37/L37-1 -> -1 | V45: =V37/U37-1 -> 0.067694334 | W45: =W37/V37-1 -> -1
B46: Europe | K46: =K38/G38-1 -> 0.11395861 | L46: =L38/H38-1 -> 0.013721345 | M46: =M38/I38-1 -> 0.097331384 | N46: =N38/J38-1 -> 0.15162093 | O46: =O38/K38-1 -> 0.12654676 | P46: =P38/L38-1 -> -1 | V46: =V38/U38-1 -> 0.095768198 | W46: =W38/V38-1 -> -1
B47: Greater China | K47: =K39/G39-1 -> -0.11076421 | L47: =L39/H39-1 -> -0.02259956 | M47: =M39/I39-1 -> 0.043522542 | N47: =N39/J39-1 -> -0.035920974 | O47: =O39/K39-1 -> 0.37881489 | P47: =P39/L39-1 -> -1 | V47: =V39/U39-1 -> -0.03846039 | W47: =W39/V39-1 -> -1
B48: Japan | K48: =K40/G40-1 -> 0.1570748 | L48: =L40/H40-1 -> 0.16544235 | M48: =M40/I40-1 -> 0.13439278 | N48: =N40/J40-1 -> 0.119811 | O48: =O40/K40-1 -> 0.047401803 | P48: =P40/L40-1 -> -1 | V48: =V40/U40-1 -> 0.14573687 | W48: =W40/V40-1 -> -1
B49: Rest of Asia Pacific | K49: =K41/G41-1 -> 0.012694352 | L49: =L41/H41-1 -> 0.084337349 | M49: =M41/I41-1 -> 0.20078247 | N49: =N41/J41-1 -> 0.14343763 | O49: =O41/K41-1 -> 0.1798659 | P49: =P41/L41-1 -> -1 | V49: =V41/U41-1 -> 0.099093222 | W49: =W41/V41-1 -> -1
B51: Revenue by category
B52: iPhone | G52: 69702 | H52: 45963 | I52: 39296 | J52: 46222 | K52: 69138 | L52: 46841 | M52: 44582 | N52: 49025 | O52: 85269 | U52: 201183 | V52: 209586
B53: Mac | G53: 7780 | H53: 7451 | I53: 7009 | J53: 7744 | K53: 8987 | L53: 7949 | M53: 8046 | N53: 8726 | O53: 8386 | U53: 29984 | V53: 33708
B54: iPad | G54: 7023 | H54: 5559 | I54: 7162 | J54: 6950 | K54: 8088 | L54: 6402 | M54: 6581 | N54: 6952 | O54: 8595 | U54: 26694 | V54: 28023
B55: Wearables | G55: 11953 | H55: 7913 | I55: 8097 | J55: 9042 | K55: 11717 | L55: 7552 | M55: 7404 | N55: 9013 | O55: 11493 | U55: 37005 | V55: 35686
B56: Services | G56: 23117 | H56: 23867 | I56: 24213 | J56: 24972 | K56: 26340 | L56: 26645 | M56: 27423 | N56: 28750 | O56: 30013 | U56: 96169 | V56: 109158
B57: Total | G57: =SUM(G52:G56) -> 119575 | H57: =SUM(H52:H56) -> 90753 | I57: =SUM(I52:I56) -> 85777 | J57: =SUM(J52:J56) -> 94930 | K57: =SUM(K52:K56) -> 124270 | L57: =SUM(L52:L56) -> 95389 | M57: =SUM(M52:M56) -> 94036 | N57: =SUM(N52:N56) -> 102466 | ... P57: =SUM(P52:P56) -> 0 | U57: =SUM(U52:U56) -> 391035 | V57: =SUM(V52:V56) -> 416161 | W57: =SUM(W52:W56) -> 0
B59: YoY Growth
B60: iPhone | K60: =K52/G52-1 -> -0.0080915899 | L60: =L52/H52-1 -> 0.019102321 | M60: =M52/I52-1 -> 0.13451751 | N60: =N52/J52-1 -> 0.060642118 | O60: =O52/K52-1 -> 0.23331598 | P60: =P52/L52-1 -> -1 | V60: =V52/U52-1 -> 0.041767943 | W60: =W52/V52-1 -> -1
B61: Mac | K61: =K53/G53-1 -> 0.15514139 | L61: =L53/H53-1 -> 0.066836666 | M61: =M53/I53-1 -> 0.14795263 | N61: =N53/J53-1 -> 0.12680785 | O61: =O53/K53-1 -> -0.066874374 | P61: =P53/L53-1 -> -1 | V61: =V53/U53-1 -> 0.12419957 | W61: =W53/V53-1 -> -1
B62: iPad | K62: =K54/G54-1 -> 0.1516446 | L62: =L54/H54-1 -> 0.15164598 | M62: =M54/I54-1 -> -0.081122591 | N62: =N54/J54-1 -> 0.00028776978 | O62: =O54/K54-1 -> 0.06268546 | P62: =P54/L54-1 -> -1 | V62: =V54/U54-1 -> 0.049786469 | W62: =W54/V54-1 -> -1
B63: Wearables | K63: =K55/G55-1 -> -0.019743997 | L63: =L55/H55-1 -> -0.04562113 | M63: =M55/I55-1 -> -0.085587255 | N63: =N55/J55-1 -> -0.003207255 | O63: =O55/K55-1 -> -0.019117522 | P63: =P55/L55-1 -> -1 | V63: =V55/U55-1 -> -0.035643832 | W63: =W55/V55-1 -> -1
B64: Services | K64: =K56/G56-1 -> 0.13942121 | L64: =L56/H56-1 -> 0.11639502 | M64: =M56/I56-1 -> 0.13257341 | N64: =N56/J56-1 -> 0.15128944 | O64: =O56/K56-1 -> 0.13944571 | P64: =P56/L56-1 -> -1 | V64: =V56/U56-1 -> 0.13506431 | W64: =W56/V56-1 -> -1
B66: BALANCE SHEET | E66: UNCONFIRMED | G66: CONFIRMED
B67: Net Cash | E67: =E68-E79 -> 51011 | G67: =G68-G79 -> 64535 | H67: =H68-H79 -> 57747 | I67: =I68-I79 -> 51737 | J67: =J68-J79 -> 50021 | K67: =K68-K79 -> 44569 | L67: =L68-L79 -> 34736 | M67: =M68-M79 -> 31288 | N67: =N68-N79 -> 33763 | ... P67: =P68-P79 -> 0
B68: Cash | E68: =29965+31590+100544 -> 162099 | G68: =40760+32340+99475 -> 172575 | H68: =32695+34455+95187 -> 162337 | I68: =25565+36236+91240 -> 153041 | J68: =29943+35228+91479 -> 156650 | K68: =30299+23476+87593 -> 141368 | L68: =28162+20336+84424 -> 132922 | M68: =36269+19103+77614 -> 132986 | N68: =35934+18763+77723 -> 132420 | O68: =45317+21590+77888 -> 144795
B69: A/R | E69: 29508 | G69: 23194 | H69: 21837 | I69: 22795 | J69: 33410 | K69: 29639 | L69: 26136 | M69: 27557 | N69: 39777 | O69: 39921
B70: Inventories | E70: 6331 | G70: 6511 | H70: 6232 | I70: 6165 | J70: 7286 | K70: 6911 | L70: 23662 | M70: 19278 | N70: 5718 | O70: 5875
B71: Vendor NTR | E71: 31477 | G71: 26908 | H71: 19313 | I71: 20377 | J71: 32833 | K71: 29667 | L71: 6269 | M71: 5925 | N71: 33180 | O71: 30399
B72: OCA | E72: 14695 | G72: 13979 | H72: 13884 | I72: 14297 | J72: 14287 | K72: 13248 | L72: 14109 | M72: 14359 | N72: 14585 | O72: 15002 | AV72: =AU72*(1+#REF!) -> #REF! | AW72: =AV72*(1+#REF!) -> #REF! | AX72: =AW72*(1+#REF!) -> #REF! | AY72: =AX72*(1+#REF!) -> #REF! | AZ72: =AY72*(1+#REF!) -> #REF! | BA72: =AZ72*(1+#REF!) -> #REF! | BB72: =BA72*(1+#REF!) -> #REF! | BC72: =BB72*(1+#REF!) -> #REF! | ... ABT72: =ABS72*(1+#REF!) -> #REF!
B73: PP&E | E73: 43715 | G73: 43666 | H73: 43546 | I73: 44502 | J73: 45680 | K73: 46069 | L73: 46876 | M73: 48508 | N73: 49834 | O73: 50159
B74: ONCA | E74: 64758 | G74: 66681 | H74: 70262 | I74: 70435 | J74: 74834 | K74: 77183 | L74: 81259 | M74: 82882 | N74: 83727 | O74: 93146
B75: Assets | E75: =SUM(E68:E74) -> 352583 | G75: =SUM(G68:G74) -> 353514 | H75: =SUM(H68:H74) -> 337411 | I75: =SUM(I68:I74) -> 331612 | J75: =SUM(J68:J74) -> 364980 | K75: =SUM(K68:K74) -> 344085 | L75: =SUM(L68:L74) -> 331233 | M75: =SUM(M68:M74) -> 331495 | N75: =SUM(N68:N74) -> 359241 | ... P75: =SUM(P68:P74) -> 0
B76: A/P | E76: 62611 | G76: 58146 | H76: 45753 | I76: 47574 | J76: 68960 | K76: 61910 | L76: 54126 | M76: 50374 | N76: 69860 | O76: 70587
B77: OCL | E77: 58829 | G77: 54611 | H77: 57298 | I77: 60889 | J77: 78304 | K77: 61151 | L77: 61849 | M77: 62499 | N77: 66387 | O77: 68543 | AO77: =NPV(AO76,AB72:ABT72)+AA72+AA96 -> #REF!
B78: D/R | E78: 8061 | G78: 8264 | H78: 8012 | I78: 8053 | J78: 8249 | K78: 8461 | L78: 8976 | M78: 8979 | N78: 9055 | O78: 9413 | AN78: Share | AO78: =AO77/Main!I5 -> #REF!
B79: Debt | E79: =5985+9822+95281 -> 111088 | G79: =1998+10954+95088 -> 108040 | H79: =1997+10762+91831 -> 104590 | I79: =2994+12114+86196 -> 101304 | J79: =9967+10912+85750 -> 106629 | K79: =10848+1995+83956 -> 96799 | L79: =5982+13638+78566 -> 98186 | M79: =9923+9345+82430 -> 101698 | N79: =7979+12350+78328 -> 98657 | O79: =1997+11827+76685 -> 90509 | AN79: Current
B80: ONCL | E80: 49848 | G80: 50353 | H80: 47564 | I80: 47084 | J80: 45888 | K80: 49006 | L80: 41300 | M80: 42115 | N80: 41549 | O80: 52055
B81: Liabilities | E81: =SUM(E76:E80) -> 290437 | G81: =SUM(G76:G80) -> 279414 | H81: =SUM(H76:H80) -> 263217 | I81: =SUM(I76:I80) -> 264904 | J81: =SUM(J76:J80) -> 308030 | K81: =SUM(K76:K80) -> 277327 | L81: =SUM(L76:L80) -> 264437 | M81: =SUM(M76:M80) -> 265665 | N81: =SUM(N76:N80) -> 285508 | ... P81: =SUM(P76:P80) -> 0
B82: S/E | E82: 62146 | G82: 74100 | H82: 74194 | I82: 66708 | J82: 56950 | K82: 66758 | L82: 66796 | M82: 65830 | N82: 73733 | O82: 88190
B83: L+S/E | E83: =+E81+E82 -> 352583 | G83: =+G81+G82 -> 353514 | H83: =+H81+H82 -> 337411 | I83: =+I81+I82 -> 331612 | J83: =+J81+J82 -> 364980 | K83: =+K81+K82 -> 344085 | L83: =+L81+L82 -> 331233 | M83: =+M81+M82 -> 331495 | N83: =+N81+N82 -> 359241 | ... P83: =+P81+P82 -> 0
B85: Current Ratio | H85: =(H68+H69+H70+H71+H72)/(H76+H77+H78) -> 2.0132988 | I85: =(I68+I69+I70+I71+I72)/(I76+I77+I78) -> 1.8596158 | J85: =(J68+J69+J70+J71+J72)/(J76+J77+J78) -> 1.5719972 | K85: =(K68+K69+K70+K71+K72)/(K76+K77+K78) -> 1.6790575 | L85: =(L68+L69+L70+L71+L72)/(L76+L77+L78) -> 1.6254212 | M85: =(M68+M69+M70+M71+M72)/(M76+M77+M78) -> 1.6421971 | N85: =(N68+N69+N70+N71+N72)/(N76+N77+N78) -> 1.5531789 | O85: =(O68+O69+O70+O71+O72)/(O76+O77+O78) -> 1.5887117 | P85: =(P68+P69+P70+P71+P72)/(P76+P77+P78) -> #DIV/0!
B86: Cash Ratio | H86: =+(H68)/(H76+H77+H78+20000) -> 1.2386181 | I86: =+(I68)/(I76+I77+I78+20000) -> 1.1210481 | J86: =+(J68)/(J76+J77+J78+20000) -> 0.89252648 | K86: =+(K68)/(K76+K77+K78+20000) -> 0.93298663 | L86: =+(L68)/(L76+L77+L78+20000) -> 0.91701334 | M86: =+(M68)/(M76+M77+M78+20000) -> 0.93749824 | N86: =+(N68)/(N76+N77+N78+20000) -> 0.80107924 | O86: =+(O68)/(O76+O77+O78+20000) -> 0.85909827 | P86: =+(P68)/(P76+P77+P78+20000) -> 0
B88: Debt-to-Equity | H88: =H81/H82 -> 3.5476858 | I88: =I81/I82 -> 3.9710979 | J88: =J81/J82 -> 5.4087796 | K88: =K81/K82 -> 4.1542137 | L88: =L81/L82 -> 3.9588748 | M88: =M81/M82 -> 4.0356221 | N88: =N81/N82 -> 3.8721875 | O88: =O81/O82 -> 3.3009071 | P88: =P81/P82 -> #DIV/0!
B92: CASH FLOW
B93: Model NI | G93: =G17 -> 33916 | H93: =H17 -> 23636 | I93: =I17 -> 21448 | J93: =J17 -> 14736 | K93: =K17 -> 36330 | L93: =L17 -> 24780 | M93: =M17 -> 23434 | N93: =N17 -> 27466 | ... P93: =P17 -> 0 | U93: =U17 -> 93736 | V93: =V17 -> 112010 | W93: =W17 -> 111649.72
B94: BOP Cash | G94: 30737 | H94: =G117 -> 41974 | I94: =H117 -> 33921 | J94: =I117 -> 26635 | K94: 29943 | L94: =K117 -> 30299 | M94: =L117 -> 28162 | N94: =M117 -> 36269 | O94: =N117 -> 35934 | P94: =O117 -> 45317 | U94: 30737 | V94: =U117 -> 29943 | W94: =V117 -> 35934
B95: GAAP NI | G95: 33916 | H95: 23636 | I95: 21448 | J95: 14736 | K95: 36330 | L95: 24780 | M95: 23434 | N95: 27466 | O95: 42097 | U95: 93736 | V95: 112010
B96: D&A | G96: 2848 | H96: 2836 | I96: 2850 | J96: 2911 | K96: 3080 | L96: 2661 | M96: 2830 | N96: 3127 | O96: 3214 | U96: 11445 | V96: 11698
B97: Share-based compensation | G97: 2997 | H97: 2964 | I97: 2869 | J97: 2858 | K97: 3286 | L97: 3226 | M97: 3168 | N97: 3183 | O97: 3594 | U97: 11688 | V97: 12863
B98: Other | G98: -989 | H98: -982 | I98: 7 | J98: -302 | K98: -2009 | L98: -208 | M98: 469 | N98: 1659 | O98: -528 | U98: -2266 | V98: -89
B99: A/R | G99: 6555 | H99: 1172 | I99: -1030 | J99: -10485 | K99: 3597 | L99: 3669 | M99: -1581 | N99: -12367 | O99: -153 | U99: -3788 | V99: -6682
B100: Vendro receivables | G100: 4569 | H100: 7595 | I100: -1064 | J100: -12456 | K100: 3166 | L100: 6005 | M100: 4384 | N100: -13902 | O100: 2781 | U100: -1356 | V100: -347
B101: Inv. | G101: -137 | H101: 190 | I101: -12 | J101: -1087 | K101: 215 | L101: 643 | M101: 365 | N101: 177 | O101: -211 | U101: -1046 | V101: 1400
B102: OA | G102: -1457 | H102: -2981 | I102: -1188 | J102: -6105 | K102: 939 | L102: -5310 | M102: -1745 | N102: -3081 | O102: -10250 | U102: -11731 | V102: -9197
B103: A/P | G103: -4542 | H103: -12168 | I103: 1539 | J103: 21191 | K103: -6671 | L103: -7933 | M103: -3875 | N103: 19381 | O103: 848 | U103: 6020 | V103: 902
B104: OL | G104: -3865 | H104: 428 | I104: 3439 | J104: 15550 | K104: -11998 | L104: -3581 | M104: 418 | N104: 4085 | O104: 12533 | U104: 15552 | V104: -11076
B105: CFFO | G105: =SUM(G95:G104) -> 39895 | H105: =SUM(H95:H104) -> 22690 | I105: =SUM(I95:I104) -> 28858 | J105: =SUM(J95:J104) -> 26811 | K105: =SUM(K95:K104) -> 29935 | L105: =SUM(L95:L104) -> 23952 | M105: =SUM(M95:M104) -> 27867 | N105: =SUM(N95:N104) -> 29728 | ... P105: =SUM(P95:P104) -> 0 | U105: =SUM(U95:U104) -> 118254 | V105: =SUM(V95:V104) -> 111482 | W105: =SUM(W95:W104) -> 0
B106: Marketable securities | G106: =-9780+13046+1337 -> 4603 | H106: 2131 | I106: 2412 | J106: 4544 | K106: =-6124+15967+3492 -> 13335 | L106: 6020 | M106: 8875 | N106: 1160 | O106: =-12693+7510 -> -5183 | U106: =-48656+51211+11135 -> 13690 | V106: =-24407+40907+12890 -> 29390
B107: CapEx | G107: -2392 | H107: -1996 | I107: -2151 | J107: -2908 | K107: -2940 | L107: -3071 | M107: -3462 | N107: -3242 | O107: =2824-2373 -> 451 | U107: -9447 | V107: -12715
B108: Other | G108: -284 | H108: -445 | I108: -388 | J108: -191 | K108: -603 | L108: -32 | M108: -340 | N108: -505 | O108: -154 | U108: -1308 | V108: -1480
B109: CFFI | G109: =SUM(G106:G108) -> 1927 | H109: =SUM(H106:H108) -> -310 | I109: =SUM(I106:I108) -> -127 | J109: =SUM(J106:J108) -> 1445 | K109: =SUM(K106:K108) -> 9792 | L109: =SUM(L106:L108) -> 2917 | M109: =SUM(M106:M108) -> 5073 | N109: =SUM(N106:N108) -> -2587 | ... P109: =SUM(P106:P108) -> 0 | U109: =SUM(U106:U108) -> 2935 | V109: =SUM(V106:V108) -> 15195 | W109: =SUM(W106:W108) -> 0
B110: Taxes | G110: -2591 | H110: -284 | I110: -2288 | J110: -278 | K110: -2921 | L110: -284 | M110: -2514 | N110: -241 | O110: -2922 | U110: -5441 | V110: -5960
B111: Dividends | G111: -3825 | H111: -3710 | I111: -3895 | J111: -3804 | K111: -3856 | L111: -3758 | M111: -3945 | N111: -3862 | O111: -3921 | U111: -15234 | V111: -15421
B112: Repurchases of stock | G112: -20139 | H112: -23205 | I112: -26522 | J112: -25083 | K112: -23606 | L112: -25898 | M112: -21075 | N112: -20132 | O112: -24701 | U112: -94949 | V112: -90711
B113: Debt | G113: -3984 | H113: -3148 | I113: -3253 | J113: 4387 | K113: =-1009-7944 -> -8953 | L113: 976 | M113: 2711 | N113: -3217 | O113: =-2164-5910 -> -8074 | U113: =-9958+3960 -> -5998 | V113: =4481-10932-2032 -> -8483
B114: Other | G114: -46 | H114: -86 | I114: -59 | J114: -170 | K114: -35 | L114: -42 | M114: -10 | N114: -24 | O114: -38 | U114: -361 | V114: -111
...

Sheet BIDU
A1: Main
A2: More | C2: Q422 | D2: Q123 | E2: Q223 | F2: Q323 | G2: Q423 | H2: Q124 | I2: Q224 | J2: Q324 | K2: Q424 | N2: 2022 | O2: 2023 | P2: 2024 | Q2: 2025 | R2: 2026 | S2: 2027 | T2: 2028 | U2: 2029 | V2: 2030 | W2: 2031 | X2: 2032 | Y2: 2033 | Z2: 2034 | AA2: 2034 | AB2: 2035 | AC2: 2036 | AD2: 2037 | AE2: 2038 | AF2: 2039 | AG2: 2040 | AH2: 2041 | AI2: 2042 | AJ2: 2043 | AK2: 2044 | AL2: 2045 | AM2: 2046 | AN2: 2047 | AO2: 2048 | AP2: 2049 | AQ2: 2050 | AR2: 2051 | AS2: 2052 | AT2: 2053 | AU2: 2054 | AV2: 2055 | AW2: 2056 | AX2: 2057 | AY2: 2058 | AZ2: 2059 | BA2: 2060 | BB2: 2061 | BC2: 2062 | BD2: 2063 | BE2: 2064 | BF2: 2065 | BG2: 2066 | BH2: 2067 | BI2: 2068 | BJ2: 2069 | BK2: 2070 | BL2: 2071 | BM2: 2072 | BN2: 2073 | BO2: 2074 | BP2: 2075 | BQ2: 2076 | BR2: 2077 | BS2: 2078 | BT2: 2079 | BU2: 2080 | BV2: 2081 | BW2: 2082 | BX2: 2083 | BY2: 2084 | BZ2: 2085 | CA2: 2086 | CB2: 2087 | CC2: 2088 | CD2: 2089 | CE2: 2090 | CF2: 2091 | CG2: 2092 | CH2: 2093 | CI2: 2094 | CJ2: 2095 | CK2: 2096 | CL2: 2097 | CM2: 2098 | CN2: 2099 | CO2: 2100 | CP2: 2101 | CQ2: 2102 | CR2: 2103 | CS2: 2104 | CT2: 2105 | CU2: 2106 | CV2: 2107 | CW2: 2108 | CX2: 2109 | CY2: 2110 | CZ2: 2111 | DA2: 2112 | DB2: 2113 | DC2: 2114 | DD2: 2115 | DE2: 2116 | DF2: 2117 | DG2: 2118 | DH2: 2119 | DI2: 2120 | DJ2: 2121 | DK2: 2122 | DL2: 2123 | DM2: 2124 | DN2: 2125 | DO2: 2126 | DP2: 2127 | DQ2: 2128 | DR2: 2129 | DS2: 2130 | DT2: 2131 | DU2: 2132 | DV2: 2133 | DW2: 2134 | DX2: 2135 | DY2: 2136 | DZ2: 2137 | EA2: 2138 | EB2: 2139 | EC2: 2140 | ED2: 2141 | EE2: 2142 | EF2: 2143 | EG2: 2144 | EH2: 2145 | EI2: 2146 | EJ2: 2147 | EK2: 2148 | EL2: 2149 | EM2: 2150 | EN2: 2151 | EO2: 2152 | EP2: 2153 | EQ2: 2154 | ER2: 2155 | ES2: 2156 | ET2: 2157 | EU2: 2158 | EV2: 2159 | EW2: 2160 | EX2: 2161 | EY2: 2162 | EZ2: 2163 | FA2: 2164 | FB2: 2165 | FC2: 2166 | FD2: 2167 | FE2: 2168 | FF2: 2169 | FG2: 2170 | FH2: 2171 | FI2: 2172 | FJ2: 2173 | FK2: 2174 | FL2: 2175 | FM2: 2176 | FN2: 2177 | FO2: 2178 | FP2: 2179 | FQ2: 2180 | FR2: 2181 | FS2: 2182 | FT2: 2183 | FU2: 2184 | FV2: 2185 | FW2: 2186 | FX2: 2187 | FY2: 2188 | FZ2: 2189 | GA2: 2190 | GB2: 2191 | GC2: 2192 | GD2: 2193 | GE2: 2194 | GF2: 2195 | GG2: 2196 | GH2: 2197 | GI2: 2198 | GJ2: 2199 | GK2: 2200 | GL2: 2201 | GM2: 2202 | GN2: 2203 | GO2: 2204 | GP2: 2205 | GQ2: 2206 | GR2: 2207 | GS2: 2208 | GT2: 2209 | GU2: 2210 | GV2: 2211 | GW2: 2212 | GX2: 2213 | GY2: 2214 | GZ2: 2215 | HA2: 2216 | HB2: 2217 | HC2: 2218 | HD2: 2219 | HE2: 2220 | HF2: 2221 | HG2: 2222 | HH2: 2223 | HI2: 2224 | HJ2: 2225 | HK2: 2226 | HL2: 2227 | HM2: 2228 | HN2: 2229 | HO2: 2230 | HP2: 2231 | HQ2: 2232 | HR2: 2233 | HS2: 2234
B3: Online Marketing | C3: 2838 | D3: 2617 | E3: 2907 | F3: 2926 | G3: 2930 | H3: 2561 | I3: 2838 | J3: 2865 | K3: 2650 | N3: 10832 | O3: =SUM(D3:G3) -> 11380 | P3: 10763
B4: Other | C4: 1958 | D4: 1918 | E4: 1790 | F4: 1795 | G4: 1993 | H4: 1804 | I4: 1831 | J4: 1917 | K4: 2025 | N4: 7099 | O4: =SUM(D4:G4) -> 7496 | P4: 7475
B5: Revenue | C5: =SUM(C3:C4) -> 4796 | D5: =SUM(D3:D4) -> 4535 | E5: 4697 | F5: =SUM(F3:F4) -> 4721 | G5: =SUM(G3:G4) -> 4923 | H5: =SUM(H3:H4) -> 4365 | I5: =SUM(I3:I4) -> 4669 | J5: =SUM(J3:J4) -> 4782 | K5: =SUM(K3:K4) -> 4675 | N5: =SUM(N3:N4) -> 17931 | O5: =SUM(O3:O4) -> 18876 | P5: =SUM(P3:P4) -> 18238 | Q5: =139900*0.14 -> 19586 | R5: =148100*0.14 -> 20734 | S5: =156700*0.14 -> 21938 | T5: =S5*1.06 -> 23254.28 | U5: =T5*1.06 -> 24649.537 | V5: =U5*1.06 -> 26128.509 | W5: =V5*1.06 -> 27696.22 | X5: =W5*1.06 -> 29357.993 | Y5: =X5*1.06 -> 31119.472 | Z5: =Y5*1.06 -> 32986.641 | AA5: =Z5*1.06 -> 34965.839 | AB5: =AA5*1.06 -> 37063.789 | AC5: =AB5*1.05 -> 38916.979 | AD5: =AC5*1.05 -> 40862.828 | AE5: =AD5*1.05 -> 42905.969 | AF5: =AE5*1.05 -> 45051.268 | AG5: =AF5*1.05 -> 47303.831 | AH5: =AG5*1.05 -> 49669.023 | AI5: =AH5*1.05 -> 52152.474 | AJ5: =AI5*1.02 -> 53195.523 | AK5: =AJ5*1.02 -> 54259.434 | AL5: =AK5*1.02 -> 55344.622 | AM5: =AL5*1.02 -> 56451.515 | AN5: =AM5*1.02 -> 57580.545 | AO5: =AN5*1.02 -> 58732.156 | AP5: =AO5*1.02 -> 59906.799 | AQ5: =AP5*1.02 -> 61104.935 | ... AU5: =AT5*1.02 -> 66141.947 | AV5: =AU5*0.98 -> 64819.108 | AW5: =AV5*0.98 -> 63522.726 | AX5: =AW5*0.98 -> 62252.271 | AY5: =AX5*0.98 -> 61007.226 | AZ5: =AY5*0.98 -> 59787.081 | BA5: =AZ5*0.98 -> 58591.34 | BB5: =BA5*0.98 -> 57419.513 | BC5: =BB5*0.98 -> 56271.123 | ... HS5: =HR5*0.98 -> 1742.4912
B6: COGS | C6: 2457 | D6: 2206 | E6: 2230 | F6: 2233 | G6: 2453 | H6: 2118 | I6: 2257 | J6: 2337 | K6: 2467 | N6: 9269 | O6: =SUM(D6:G6) -> 9122 | P6: 9056 | Q6: =Q5-Q7 -> 9793 | R6: =R5-R7 -> 10367 | S6: =S5-S7 -> 10969
B7: Gross Profit | C7: =C5-C6 -> 2339 | D7: =D5-D6 -> 2329 | E7: =E5-E6 -> 2467 | F7: =F5-F6 -> 2488 | G7: =G5-G6 -> 2470 | H7: =H5-H6 -> 2247 | I7: =I5-I6 -> 2412 | J7: =J5-J6 -> 2445 | K7: =K5-K6 -> 2208 | N7: =N5-N6 -> 8662 | O7: =O5-O6 -> 9754 | P7: =P5-P6 -> 9182 | Q7: =Q5*Q27 -> 9793 | R7: =R5*R27 -> 10367 | S7: =S5*S27 -> 10969
B8: SG&A | C8: 853 | D8: 814 | E8: 869 | F8: 792 | G8: 825 | H8: 745 | I8: 784 | J8: 836 | K8: 915 | N8: 2975 | O8: =SUM(D8:G8) -> 3300 | P8: 3236 | Q8: =Q7*Q33 -> 3500.2989 | R8: =R7*R33 -> 3757.298 | S8: =S7*S33 -> 4030.325
B9: R&D | C9: 820 | D9: 790 | E9: 880 | F9: 836 | G9: 886 | H9: 742 | I9: 810 | J9: 765 | K9: 756 | N9: 3380 | O9: =SUM(D9:G9) -> 3392 | P9: 3032 | Q9: =Q7*Q34 -> 3086.8641 | R9: =R7*R34 -> 3112.2904 | S9: =S7*S34 -> 3128.4826
B10: Operating expenses | C10: =C9+C8 -> 1673 | D10: =D9+D8 -> 1604 | E10: =E9+E8 -> 1749 | F10: =F9+F8 -> 1628 | G10: =G9+G8 -> 1711 | H10: =H9+H8 -> 1487 | I10: =I9+I8 -> 1594 | J10: =J9+J8 -> 1601 | K10: =K9+K8 -> 1671 | N10: =N9+N8 -> 6355 | O10: =O9+O8 -> 6692 | P10: =P9+P8 -> 6268 | Q10: =Q9+Q8 -> 6587.163 | R10: =R9+R8 -> 6869.5883 | S10: =S9+S8 -> 7158.8076
B11: Operating income | C11: =C7-C10 -> 666 | D11: =D7-D10 -> 725 | E11: =E7-E10 -> 718 | F11: =F7-F10 -> 860 | G11: =G7-G10 -> 759 | H11: =H7-H10 -> 760 | I11: =I7-I10 -> 818 | J11: =J7-J10 -> 844 | K11: =K7-K10 -> 537 | N11: =N7-N10 -> 2307 | O11: =O7-O10 -> 3062 | P11: =P7-P10 -> 2914 | Q11: =25800*0.14 -> 3612 | R11: =28500*0.14 -> 3990 | S11: =32400*0.14 -> 4536
B12: Interest income | C12: =239-107 -> 132 | D12: =279-117 -> 162 | E12: =269-113 -> 156 | F12: =285-117 -> 168 | G12: =291-109 -> 182 | H12: =290-106 -> 184 | I12: =274-102 -> 172 | J12: =267-96 -> 171 | K12: =274-88 -> 186 | N12: =905-422 -> 483 | O12: =SUM(D12:G12) -> 668 | P12: =1091-387 -> 704
B13: FX gain | C13: -49 | D13: -15 | E13: 162 | F13: -4 | G13: -63 | H13: 56 | I13: 13 | J13: -156 | K13: 230 | N13: -215 | O13: =SUM(D13:G13) -> 80 | P13: 147
B14: Investments | C14: -76 | D14: -7 | E14: -53 | F14: -55 | G14: -418 | H14: -28 | I14: -16 | J14: 5 | K14: -55 | N14: -277 | O14: =SUM(D14:G14) -> -533 | P14: -95
B15: Others | C15: 251 | D15: 238 | E15: -76 | F15: 152 | G15: -57 | H15: -39 | I15: -63 | J15: 361 | K15: 3 | N15: -832 | O15: =SUM(D15:G15) -> 257 | P15: 251
B16: Total income | C16: =SUM(C12:C15) -> 258 | D16: =SUM(D12:D15) -> 378 | E16: =SUM(E12:E15) -> 189 | F16: =SUM(F12:F15) -> 261 | G16: =SUM(G12:G15) -> -356 | H16: =SUM(H12:H15) -> 173 | I16: =SUM(I12:I15) -> 106 | J16: =SUM(J12:J15) -> 381 | K16: =SUM(K12:K15) -> 364 | N16: =SUM(N12:N15) -> -841 | O16: =SUM(O12:O15) -> 472 | P16: =SUM(P12:P15) -> 1007 | Q16: =$K$37*0.03 -> 991.56 | R16: =$K$37*0.03 -> 991.56 | S16: =$K$37*0.03 -> 991.56
B17: Pre Tax income | C17: =C11+C16 -> 924 | D17: =D11+D16 -> 1103 | E17: =E11+E16 -> 907 | F17: =F11+F16 -> 1121 | G17: =G11+G16 -> 403 | H17: =H11+H16 -> 933 | I17: =I11+I16 -> 924 | J17: =J11+J16 -> 1225 | K17: =K11+K16 -> 901 | N17: =N11+N16 -> 1466 | O17: =O11+O16 -> 3534 | P17: =P11+P16 -> 3921 | Q17: =Q11+Q16 -> 4603.56 | R17: =R11+R16 -> 4981.56 | S17: =S11+S16 -> 5527.56
B18: Taxes | C18: =181+25 -> 206 | D18: =174+81 -> 255 | E18: =175+14 -> 189 | F18: =175+30 -> 205 | G18: =-14+51 -> 37 | H18: =122+56 -> 178 | I18: =156+13 -> 169 | J18: =116+21 -> 137 | K18: =222-32 -> 190 | N18: =374-4 -> 370 | O18: =SUM(D18:G18) -> 686 | P18: =609+57 -> 666 | Q18: =Q17*0.17 -> 782.6052 | R18: =R17*0.17 -> 846.8652 | S18: =S17*0.17 -> 939.6852
B19: Net Income | C19: =C17-C18 -> 718 | D19: =D17-D18 -> 848 | E19: =E17-E18 -> 718 | F19: =F17-F18 -> 916 | G19: =G17-G18 -> 366 | H19: =H17-H18 -> 755 | I19: =I17-I18 -> 755 | J19: =J17-J18 -> 1088 | K19: =K17-K18 -> 711 | N19: =N17-N18 -> 1096 | O19: =O17-O18 -> 2848 | P19: =P17-P18 -> 3255 | Q19: =25800*0.14 -> 3612 | R19: =27900*0.14 -> 3906 | S19: =32800*0.14 -> 4592 | T19: =T5*0.25 -> 5813.57 | U19: =U5*0.25 -> 6162.3842 | V19: =V5*0.25 -> 6532.1273 | W19: =W5*0.25 -> 6924.0549 | X19: =X5*0.25 -> 7339.4982 | Y19: =Y5*0.25 -> 7779.8681 | Z19: =Z5*0.25 -> 8246.6602 | AA19: =AA5*0.25 -> 8741.4598 | ... HS19: =HS5*0.25 -> 435.62281
B20: S/O | C20: 2758 | D20: 2798 | E20: 2804 | F20: 2814 | G20: 2812 | H20: 2804 | I20: 2796 | J20: 2785 | K20: 2775 | N20: 2782 | O20: =G20 -> 2812 | P20: 2790
B21: EPS | C21: =C19/C20 -> 0.26033358 | D21: =D19/D20 -> 0.30307362 | E21: =E19/E20 -> 0.25606277 | F21: =F19/F20 -> 0.32551528 | G21: =G19/G20 -> 0.13015647 | H21: =H19/H20 -> 0.2692582 | I21: =I19/I20 -> 0.27002861 | J21: =J19/J20 -> 0.39066427 | K21: =K19/K20 -> 0.25621622 | N21: =N19/N20 -> 0.39396118 | O21: =O19/O20 -> 1.0128023 | P21: =P19/P20 -> 1.1666667
B23: Operating Income y/y | O23: =O11/N11-1 -> 0.32726485 | P23: =P11/O11-1 -> -0.048334422 | R23: =R11/Q11-1 -> 0.10465116 | S23: =S11/R11-1 -> 0.13684211
B24: Revenue y/y | G24: =G5/C5-1 -> 0.0264804 | H24: =H5/D5-1 -> -0.037486218 | I24: =I5/E5-1 -> -0.0059612519 | J24: =J5/F5-1 -> 0.012920991 | K24: =K5/G5-1 -> -0.050375787 | O24: =O5/N5-1 -> 0.052702024 | P24: =P5/O5-1 -> -0.033799534 | Q24: =Q5/P5-1 -> 0.073911613 | R24: =R5/Q5-1 -> 0.058613295 | S24: =S5/R5-1 -> 0.058068872 | W24: Maturity | X24: 0.02
B25: NI y/y | O25: =O19/N19-1 -> 1.5985401 | P25: =P19/O19-1 -> 0.1429073 | Q25: =Q19/P19-1 -> 0.10967742 | R25: =R19/Q19-1 -> 0.081395349 | S25: =S19/R19-1 -> 0.17562724 | W25: Discount rate | X25: 0.0729
W26: NPV | X26: =NPV(X25,Q19:HS19) -> 123442.74
B27: Gross Margin | C27: =C7/C5 -> 0.48769808 | D27: =D7/D5 -> 0.51356119 | E27: =E7/E5 -> 0.52522887 | F27: =F7/F5 -> 0.52700699 | G27: =G7/G5 -> 0.50172659 | H27: =H7/H5 -> 0.51477663 | I27: =I7/I5 -> 0.51659884 | J27: =J7/J5 -> 0.51129235 | K27: =K7/K5 -> 0.47229947 | N27: =N7/N5 -> 0.48307401 | O27: =O7/O5 -> 0.51674083 | P27: =P7/P5 -> 0.50345433 | Q27: 0.5 | R27: 0.5 | S27: 0.5 | W27: net NPV | X27: =X26+K37 -> 156494.74
B28: Operating Margin | C28: =C11/C5 -> 0.13886572 | D28: =D11/D5 -> 0.1598677 | E28: =E11/E5 -> 0.15286353 | F28: =F11/F5 -> 0.1821648 | G28: =G11/G5 -> 0.15417428 | H28: =H11/H5 -> 0.17411226 | I28: =I11/I5 -> 0.17519812 | J28: =J11/J5 -> 0.17649519 | K28: =K11/K5 -> 0.11486631 | N28: =N11/N5 -> 0.12865986 | O28: =O11/O5 -> 0.16221657 | P28: =P11/P5 -> 0.15977629 | Q28: =Q11/Q5 -> 0.18441744 | R28: =R11/R5 -> 0.19243754 | S28: =S11/S5 -> 0.20676452 | W28: NPV | X28: =X27/P20 -> 56.091304
B29: Net Margin | C29: =C16/C19 -> 0.35933148 | D29: =D16/D19 -> 0.44575472 | E29: =E16/E19 -> 0.2632312 | F29: =F16/F19 -> 0.2849345 | G29: =G16/G19 -> -0.9726776 | H29: =H16/H19 -> 0.22913907 | I29: =I16/I19 -> 0.14039735 | J29: =J16/J19 -> 0.35018382 | K29: =K16/K19 -> 0.51195499 | N29: =N16/N19 -> -0.76733577 | O29: =O16/O19 -> 0.16573034 | P29: =P16/P19 -> 0.3093702 | Q29: =Q16/Q19 -> 0.27451827 | R29: =R16/R19 -> 0.25385561 | S29: =S16/S19 -> 0.21593206
B30: Interest Margin | C30: =C16/C11 -> 0.38738739 | D30: =D16/D11 -> 0.52137931 | E30: =E16/E11 -> 0.2632312 | F30: =F16/F11 -> 0.30348837 | G30: =G16/G11 -> -0.46903821 | H30: =H16/H11 -> 0.22763158 | I30: =I16/I11 -> 0.12958435 | J30: =J16/J11 -> 0.4514218 | K30: =K16/K11 -> 0.67783985 | N30: =N16/N11 -> -0.3645427 | O30: =O16/O11 -> 0.15414762 | P30: =P16/P11 -> 0.3455731 | Q30: =Q16/Q11 -> 0.27451827 | R30: =R16/R11 -> 0.24851128 | S30: =S16/S11 -> 0.21859788
AV31: =AU31*(1+$AO$35) -> 0 | AW31: =AV31*(1+$AO$35) -> 0 | AX31: =AW31*(1+$AO$35) -> 0 | AY31: =AX31*(1+$AO$35) -> 0 | AZ31: =AY31*(1+$AO$35) -> 0 | BA31: =AZ31*(1+$AO$35) -> 0 | BB31: =BA31*(1+$AO$35) -> 0 | BC31: =BB31*(1+$AO$35) -> 0 | ... ABT31: =ABS31*(1+$AO$35) -> 0
B32: Tax Margin | C32: =C18/C17 -> 0.22294372 | D32: =D18/D17 -> 0.23118767 | E32: =E18/E17 -> 0.20837927 | F32: =F18/F17 -> 0.18287244 | G32: =G18/G17 -> 0.091811414 | H32: =H18/H17 -> 0.19078242 | I32: =I18/I17 -> 0.18290043 | J32: =J18/J17 -> 0.11183673 | K32: =K18/K17 -> 0.2108768 | N32: =N18/N17 -> 0.25238745 | O32: =O18/O17 -> 0.19411432 | P32: =P18/P17 -> 0.16985463 | Q32: =Q18/Q17 -> 0.17 | R32: =R18/R17 -> 0.17 | S32: =S18/S17 -> 0.17
B33: SG&A Margin | C33: =C8/C7 -> 0.36468576 | D33: =D8/D7 -> 0.34950623 | E33: =E8/E7 -> 0.3522497 | F33: =F8/F7 -> 0.31832797 | G33: =G8/G7 -> 0.3340081 | H33: =H8/H7 -> 0.33155318 | I33: =I8/I7 -> 0.32504146 | J33: =J8/J7 -> 0.34192229 | K33: =K8/K7 -> 0.41440217 | N33: =N8/N7 -> 0.34345417 | O33: =O8/O7 -> 0.33832274 | P33: =P8/P7 -> 0.35242866 | Q33: =P33+0.005 -> 0.35742866 | R33: =Q33+0.005 -> 0.36242866 | S33: =R33+0.005 -> 0.36742866
B34: R&D Margin | C34: =C9/C7 -> 0.35057717 | D34: =D9/D7 -> 0.33920137 | E34: =E9/E7 -> 0.35670855 | F34: =F9/F7 -> 0.33601286 | G34: =G9/G7 -> 0.35870445 | H34: =H9/H7 -> 0.33021807 | I34: =I9/I7 -> 0.3358209 | J34: =J9/J7 -> 0.31288344 | K34: =K9/K7 -> 0.3423913 | N34: =N9/N7 -> 0.39021011 | O34: =O9/O7 -> 0.34775477 | P34: =P9/P7 -> 0.33021128 | Q34: =+P34-0.015 -> 0.31521128 | R34: =+Q34-0.015 -> 0.30021128 | S34: =+R34-0.015 -> 0.28521128
B37: Net Cash | C37: =C38-C50 -> 33905 | D37: =D38-D50 -> 34421 | E37: =E38-E50 -> 0 | F37: =F38-F50 -> 0 | G37: =G38-G50 -> 34092 | H37: =H38-H50 -> 33808 | I37: =I38-I50 -> 33250 | J37: =J38-J50 -> 34129 | K37: =K38-K50 -> 33052 | N37: =N38-N50 -> 33905 | O37: =O38-O50 -> 34092 | P37: =P38-P50 -> 33052 | AO37: =NPV(AO36,AB31:ABT31)+AA31+AA49 -> 0
B38: Cash and equivalents | C38: =7707+17520+3426+8017 -> 36670 | D38: =3442+23171+2719+8076 -> 37408 | G38: =3554+23757+6755+3474 -> 37540 | H38: =4213+20744+6502+6289 -> 37748 | I38: =5990+14699+6356+9976 -> 37021 | J38: =4087+14838+12618+6361 -> 37904 | K38: =3402+14057+5716+13499 -> 36674 | N38: =7707+17520+3426+8017 -> 36670 | O38: =3554+23757+6755+3474 -> 37540 | P38: =3402+14057+5716+13499 -> 36674 | AN38: Share | AO38: =AO37/Main!I5 -> 0
B39: Restricted cash | C39: 1643 | D39: 1638 | G39: 1620 | H39: 1605 | I39: 1603 | J39: 1662 | K39: 1602 | N39: 1643 | O39: 1620 | P39: 1602 | AN39: Current
B40: A/R | C40: =1701+788+9 -> 2498 | D40: =1572+759+14 -> 2345 | G40: =1528+201+27 -> 1756 | H40: =1514+162+40 -> 1716 | I40: =1529+192+29 -> 1750 | J40: =1403+197+17 -> 1617 | K40: =1384+108+19 -> 1511 | N40: =1701+788+9 -> 2498 | O40: =1528+201+27 -> 1756 | P40: =1384+108+19 -> 1511
B41: OCA | C41: 1501 | D41: 2793 | G41: 1772 | H41: 1882 | I41: 1756 | J41: 2339 | K41: 2580 | N41: 1501 | O41: 1772 | P41: 2580
B42: Fixed assets | C42: 3476 | D42: 3345 | G42: 3938 | H42: 3900 | I42: 4012 | J42: 4232 | K42: 4124 | N42: 3476 | O42: 3938 | P42: 4124
B43: Intangibles | C43: =992+1885+182 -> 3059 | D43: =1835+976+172 -> 2983 | G43: =981+1884+124 -> 2989 | H43: =958+1885+121 -> 2964 | I43: =951+1970+112 -> 3033 | J43: =978+2040+107 -> 3125 | K43: =949+2013+106 -> 3068 | N43: =992+1885+182 -> 3059 | O43: =981+1884+124 -> 2989 | P43: =949+2013+106 -> 3068
B44: Goodwill | C44: 3259 | D44: 3289 | G44: 3181 | H44: 3128 | I44: 3108 | J44: 3218 | K44: 3094 | N44: 3259 | O44: 3181 | P44: 3094
B45: Deferred tax | C45: 309 | D45: 304 | G45: 296 | H45: 312 | I45: 322 | J45: 406 | K45: 300 | N45: 309 | O45: 296 | P45: 300
B46: Lease ROU | C46: 1503 | D46: 1483 | G46: 1528 | H46: 1481 | I46: 1503 | J46: 1524 | K46: 1493 | N46: 1503 | O46: 1528 | P46: 1493
B47: Prepaymetns | K47: 1856 | P47: 1856
B48: ONCA | C48: 2768 | D48: 2798 | G48: 2671 | H48: 2699 | I48: 3071 | J48: 3440 | K48: 2304 | N48: 2768 | O48: 2671 | P48: 2304
B49: Total Asets | C49: =SUM(C38:C48) -> 56686 | D49: =SUM(D38:D48) -> 58386 | G49: =SUM(G38:G48) -> 57291 | H49: =SUM(H38:H48) -> 57435 | I49: =SUM(I38:I48) -> 57179 | J49: =SUM(J38:J48) -> 59467 | K49: =SUM(K38:K48) -> 58606 | N49: =SUM(N38:N48) -> 56686 | O49: =SUM(O38:O48) -> 57291 | P49: =SUM(P38:P48) -> 58606
B50: Debt | C50: =775+1990 -> 2765 | D50: =995+1992 -> 2987 | G50: =1445+2003 -> 3448 | H50: =1900+3+2037 -> 3940 | I50: =1722+4+2045 -> 3771 | J50: =1706+2064+5 -> 3775 | K50: =1462+2137+23 -> 3622 | N50: =775+1990 -> 2765 | O50: =1445+2003 -> 3448 | P50: =1462+2137+23 -> 3622
B51: A/P | C51: =5512+735+14 -> 6261 | D51: =4957+759+14 -> 5730 | G51: =5312+226+11 -> 5549 | H51: =5089+204+10 -> 5303 | I51: =5227+252+9 -> 5488 | J51: =5557+279+9 -> 5845 | K51: =5677+246+8 -> 5931 | N51: =5512+735+14 -> 6261 | O51: =5312+226+11 -> 5549 | P51: =5677+246+8 -> 5931
B52: D/R | C52: =1902+10+23+48 -> 1983 | D52: =2026+21+17+55 -> 2119 | G52: =2060+43+28+68 -> 2199 | H52: =1889+32+27+70 -> 2018 | I52: =40+1932+39+72 -> 2083 | J52: =2039+43+38+76 -> 2196 | K52: =2003+94+32+80 -> 2209 | N52: =1902+10+23+48 -> 1983 | O52: =2060+43+28+68 -> 2199 | P52: =2003+94+32+80 -> 2209
B53: Notes | C53: =1204+1001+5784+1387 -> 9376 | D53: =1203+1000+5776+1699 -> 9678 | G53: =395+849+1147+4928 -> 7319 | H53: =395+850+4931+1157 -> 7333 | I53: =1099+398+3834+1157 -> 6488 | J53: =2+1099+1167+3835 -> 6103 | K53: =33+1100+3835+1144 -> 6112 | N53: =1204+1001+5784+1387 -> 9376 | O53: =395+849+1147+4928 -> 7319 | P53: =33+1100+3835+1144 -> 6112
B54: Lease | C54: =407+697 -> 1104 | D54: =407+677 -> 1084 | G54: =438+710 -> 1148 | H54: =431+677 -> 1108 | I54: =440+696 -> 1136 | J54: =445+700 -> 1145 | K54: =453+681 -> 1134 | N54: =407+697 -> 1104 | O54: =438+710 -> 1148 | P54: =453+681 -> 1134
B55: Deferred tax | C55: 420 | D55: 439 | G55: 384 | H55: 390 | I55: 405 | J55: 411 | K55: 530 | N55: 420 | O55: 384 | P55: 530
B56: ONCL | C56: 299 | D56: 300 | G56: 257 | H56: 258 | I56: 250 | J56: 208 | K56: 213 | N56: 299 | O56: 257 | P56: 213
B57: Total Liabilities | C57: =SUM(C50:C56) -> 22208 | D57: =SUM(D50:D56) -> 22337 | G57: =SUM(G50:G56) -> 20304 | H57: =SUM(H50:H56) -> 20350 | I57: =SUM(I50:I56) -> 19621 | J57: =SUM(J50:J56) -> 19683 | K57: =SUM(K50:K56) -> 19751 | N57: =SUM(N50:N56) -> 22208 | O57: =SUM(O50:O56) -> 20304 | P57: =SUM(P50:P56) -> 19751
B58: SE | C58: =1217+33261 -> 34478 | D58: =1268+34781 -> 36049 | G58: =1333+35654 -> 36987 | H58: =1372+35713 -> 37085 | I58: =1391+36167 -> 37558 | J58: =1327+38457 -> 39784 | K58: =37503+1352 -> 38855 | N58: =1217+33261 -> 34478 | O58: =1333+35654 -> 36987 | P58: =37503+1352 -> 38855
B59: L+SE | C59: =C57+C58 -> 56686 | D59: =D57+D58 -> 58386 | G59: =G57+G58 -> 57291 | H59: =H57+H58 -> 57435 | I59: =I57+I58 -> 57179 | J59: =J57+J58 -> 59467 | K59: =K57+K58 -> 58606 | N59: =N57+N58 -> 56686 | O59: =O57+O58 -> 57291 | P59: =P57+P58 -> 58606
B61: Model NI | C61: =C19 -> 718 | D61: =D19 -> 848 | E61: =E19 -> 718 | F61: =F19 -> 916 | G61: =G19 -> 366 | H61: =H19 -> 755 | I61: =I19 -> 755 | J61: =J19 -> 1088 | K61: =K19 -> 711
B62: CFFO | C62: 1139 | D62: 850 | E62: 1466 | F62: 1306 | G62: 1496 | H62: 861 | I62: 1153 | J62: 610 | K62: 323 | N62: 3794 | O62: =SUM(D62:G62) -> 5118 | P62: =SUM(H62:K62) -> 2947
B63: CFFI | C63: -772 | D63: -4754 | E63: 950 | F63: -1563 | G63: -1864 | H63: -432 | I63: 1946 | J63: -1990 | K63: -772 | N63: -572 | O63: =SUM(D63:G63) -> -7231 | P63: =SUM(H63:K63) -> -1248
B64: CFFF | C64: -328 | D64: -335 | E64: 101 | F64: -683 | G64: -1072 | H64: 331 | I64: -1249 | J64: -769 | K64: -229 | N64: -926 | O64: =SUM(D64:G64) -> -1989 | P64: =SUM(H64:K64) -> -1916
B65: CF | C65: =C62+C63+C64 -> 39 | D65: =D62+D63+D64 -> -4239 | E65: =E62+E63+E64 -> 2517 | F65: =F62+F63+F64 -> -940 | G65: =G62+G63+G64 -> -1440 | H65: =H62+H63+H64 -> 760 | I65: =I62+I63+I64 -> 1850 | J65: =J62+J63+J64 -> -2149 | K65: =K62+K63+K64 -> -678 | N65: =N62+N63+N64 -> 2296 | O65: =O62+O63+O64 -> -4102 | P65: =P62+P63+P64 -> -217
B67: Capex | C67: -280 | D67: -189 | E67: -373 | F67: -484 | G67: -516 | H67: -282 | I67: -291 | J67: -234 | K67: -320 | N67: -1201 | O67: =SUM(D67:G67) -> -1562 | P67: =SUM(H67:K67) -> -1127
B69: FCF | C69: =C62+C67 -> 859 | D69: =D62+D67 -> 661 | E69: =E62+E67 -> 1093 | F69: =F62+F67 -> 822 | G69: =G62+G67 -> 980 | H69: =H62+H67 -> 579 | I69: =I62+I67 -> 862 | J69: =J62+J67 -> 376 | K69: =K62+K67 -> 3 | N69: =N62+N67 -> 2593 | O69: =O62+O67 -> 3556 | P69: =P62+P67 -> 1820
B70: FCF y/y | O70: =O69/N69-1 -> 0.3713845 | P70: =P69/O69-1 -> -0.48818898

Sheet IBM FA
A1: IBM
G2: Incorporated: 1911
B5: Name | E5: FY24 | F5: FY23 | K5: Name | O5: Q124 | P5: Q224 | Q5: Q324 | R5: Q424
B6: Revenue | C6: ($ in millions) | K6: Revenue | L6: ($ in millions) | O6: Revenue y/y | P6: Revenue y/y | Q6: Revenue y/y | R6: Revenue y/y
B7: Software | E7: 27085 | F7: 25011 | K7: Software | O7: 0.055 | P7: 0.071 | Q7: 0.097 | R7: 0.104
B8: Hybrid Platform & Solutions | K8: Hybrid Platform & Solutions | O8: 0.07 | P8: 0.05 | Q8: 0.1 | R8: 0.11
B9: Transaction Processing | L9: Red Hat | O9: 0.09 | P9: 0.07 | Q9: 0.14 | R9: 0.16
B10: % of revenue | E10: =E7/E31 -> 0.43161283 | F10: =F7/F31 -> 0.40430966 | L10: Automation | O10: 0.13 | P10: 0.15 | Q10: 0.13 | R10: 0.15
B11: Gross margin | E11: 0.837 | F11: 0.829 | L11: Data & AU | O11: 0.01 | P11: 0.03 | Q11: 0.05 | R11: 0.04
B12: Consulting | E12: 20692 | F12: 20884 | L12: Security | O12: -0.03 | P12: 0.02 | Q12: 0.01 | R12: 0.04
B13: Business Transformation | K13: Transaction Processing | O13: 0.03 | P13: 0.11 | Q13: 0.09 | R13: 0.1 | U13: Name | X13: Description | Y13: % of Revenue | Z13: Notes | AA13: Competition
B14: Technology consulting | K14: % of revenue | U14: Software | X14: Hybrid cloud and AI platforms allow clients to realize their digital and AI transformations across the applications, data, and environments in which they operate. | Y14: 0.43161283 | AA14: Alphabet, Amazon, BMC, Broadcom, Informatica, Microsoft, Oracle, Salesforce, SAP and Splunk.
B15: Application Operations | K15: Gross margin | U15: Hybrid Platform & Solutions
B16: % of revenue | E16: =E12/E31 -> 0.32973722 | F16: =F12/F31 -> 0.33759558 | K16: Consulting | O16: -0.002 | P16: -0.009 | Q16: -0.005 | R16: -0.02 | U16: Transaction Processing
B17: Gross margin | E17: 0.27 | F17: 0.268 | K17: Business Transformation | O17: 0.01 | P17: 0.03 | Q17: 0.02 | R17: 0.01 | U17: Consulting | X17: Consulting includes consulting, systems integration, application development, application management and business process outsourcing services | Y17: 0.32973722 | AA17: Accenture, Capgemini, India-based service providers, management consulting firms, the consulting practices of public accounting firms, engineering service providers, and companies that focus on local/niche markets.
B18: Infrastructure | E18: 14020 | F18: 14593 | K18: Technology consulting | O18: 0.01 | P18: -0.03 | Q18: -0.04 | R18: -0.07 | U18: Business Transformation
B19: Hybrid Infrastructure | K19: Application Operations | O19: -0.03 | P19: -0.04 | Q19: -0.01 | R19: -0.04 | U19: Technology consulting
B20: Infrastructure Support | K20: % of revenue | U20: Application Operations
B21: % of revenue | E21: =E18/E31 -> 0.22341561 | F21: =F18/F31 -> 0.23589984 | K21: Gross margin | U21: Infrastructure | X21: IBM provides on-premises and cloud-based server and storage solutions. Also, they offer a portfolio of life-cycle services for hybrid cloud infrastructure deployment. | Y21: 0.22341561 | AA21: Dell Technologies, Hewlett-Packard Enterprise (HPE), Intel, NetApp and Pure Storage as well as original device manufacturers (ODMs).
B22: Gross margin | E22: 0.558 | F22: 0.561 | K22: Infrastructure | O22: -0.007 | P22: 0.007 | Q22: -0.07 | R22: -0.076 | U22: Hybrid Infrastructure
B23: Financing | E23: 713 | F23: 741 | K23: Hybrid Infrastructure | O23: 0.05 | P23: 0.04 | Q23: -0.09 | R23: -0.1 | U23: Infrastructure Support
B24: Client Financing | L24: IBM Z | O24: 0.04 | P24: 0.06 | Q24: -0.19 | R24: -0.21 | U24: Financing | X24: Financing provides client and commercial financing, facilitating IBM clients’ acquisition of hardware, software and services. | Y24: 0.011362007 | Z24: In client and commercial financing, Financing primarily competes with non-captive financing entities and financial institutions. | AA24: Interest rates charged, IT product experience, client service, contract flexibility, ease of doing business, global capabilities and residual values.
B25: Commercial Financing | L25: Distributed Infrastructure flat | O25: 0.06 | P25: 0.03 | Q25: -0.03 | R25: 0.02 | U25: Client Financing
B26: % of revenue | E26: =E23/E31 -> 0.011362007 | F26: =F23/F31 -> 0.011978468 | K26: Infrastructure Support | O26: -0.08 | P26: -0.05 | Q26: -0.04 | R26: -0.02 | U26: Commercial Financing
B27: Gross margin | E27: 0.479 | F27: 0.481 | K27: % of revenue
B28: Other | E28: 243 | F28: 632 | K28: Gross margin
B29: % of revenue | E29: =E28/E31 -> 0.0038723248 | F29: =F28/F31 -> 0.010216453 | K29: Financing | O29: -0.016 | P29: -0.083 | Q29: -0.025 | R29: -0.025
B30: Gross margin | E30: -3.528 | F30: -0.874 | K30: Client Financing
B31: Total revenue | E31: =E28+E23+E18+E12+E7 -> 62753 | F31: =F28+F23+F18+F12+F7 -> 61861 | K31: Commercial Financing
B32: Total gross profit | E32: =35551 -> 35551 | F32: 34300 | K32: % of revenue
B33: Total gross margin | E33: =E32/E31 -> 0.56652272 | F33: =F32/F31 -> 0.55446889 | K33: Gross margin

Sheet IBM
A1: Main | B1: Fundamental Analysis | W1: FORECAST
C2: Q123 | D2: Q223 | E2: Q323 | F2: Q423 | G2: Q124 | H2: Q224 | I2: Q324 | J2: Q424 | K2: Q125 | L2: Q225 | M2: Q325 | N2: Q425 | Q2: FY19 | R2: FY20 | S2: FY21 | T2: FY22 | U2: FY23 | V2: FY24 | W2: FY25 | X2: FY26 | Y2: FY27 | Z2: FY28 | AA2: FY29 | AB2: FY30 | AC2: FY31 | AD2: FY32 | AE2: FY33 | AF2: FY34 | AG2: FY35 | AH2: FY36 | AI2: FY37 | AJ2: FY38
B3: Services | C3: 7524 | D3: 7553 | E3: 7541 | F3: =30378-SUM(C3:E3) -> 7760 | G3: 7470 | H3: 7405 | I3: 7453 | J3: =29813-SUM(G3:I3) -> 7485 | U3: =SUM(C3:F3) -> 30378 | V3: =SUM(G3:J3) -> 29813 | W3: =+W6*0.48 -> 31326.298
B4: Sales | C4: 6532 | D4: 7739 | E4: 7025 | F4: =30745-SUM(C4:E4) -> 9449 | G4: 6799 | H4: 8195 | I4: 7334 | J4: =32231-SUM(G4:I4) -> 9903 | U4: =SUM(C4:F4) -> 30745 | V4: =SUM(G4:J4) -> 32231
B5: Financing | C5: 196 | D5: 183 | E5: 186 | F5: =737-SUM(C5:E5) -> 172 | G5: 192 | H5: 169 | I5: 180 | J5: =709-SUM(G5:I5) -> 168 | U5: =SUM(C5:F5) -> 737 | V5: =SUM(G5:J5) -> 709
B6: Revenue | C6: =SUM(C3:C5) -> 14252 | D6: =SUM(D3:D5) -> 15475 | E6: =SUM(E3:E5) -> 14752 | F6: =SUM(F3:F5) -> 17381 | G6: =SUM(G3:G5) -> 14461 | H6: =SUM(H3:H5) -> 15769 | I6: =SUM(I3:I5) -> 14967 | J6: =SUM(J3:J5) -> 17556 | Q6: 57714 | R6: 55179 | S6: 57350 | T6: 60530 | U6: =SUM(U3:U5) -> 61860 | V6: =SUM(V3:V5) -> 62753 | W6: =V6*1.04 -> 65263.12 | X6: =W6*1.04 -> 67873.645 | Y6: =X6*1.04 -> 70588.591 | Z6: =Y6*1.04 -> 73412.134 | AA6: =Z6*1.04 -> 76348.62 | AB6: =AA6*1.04 -> 79402.564 | AC6: =AB6*1.04 -> 82578.667 | AD6: =AC6*1.04 -> 85881.814 | ... AJ6: =AI6*1.04 -> 108667.89
B7: Services Cost | C7: 5310 | D7: 5294 | E7: 5217 | F7: =21051-SUM(C7:E7) -> 5230 | G7: 5239 | H7: 5126 | I7: 5048 | J7: =20529-SUM(G7:I7) -> 5116 | U7: =SUM(C7:F7) -> 21051 | V7: =SUM(G7:J7) -> 20529
B8: Sales Cost | C8: 1322 | D8: 1587 | E8: 1419 | F8: =6127-SUM(C8:E8) -> 1799 | G8: 1381 | H8: 1607 | I8: 1404 | J8: =6303-SUM(G8:I8) -> 1911 | U8: =SUM(C8:F8) -> 6127 | V8: =SUM(G8:J8) -> 6303
B9: Financing Cost | C9: 110 | D9: 93 | E9: 94 | F9: =382-SUM(C9:E9) -> 85 | G9: 99 | H9: 86 | I9: 95 | J9: =369-SUM(G9:I9) -> 89 | U9: =SUM(C9:F9) -> 382 | V9: =SUM(G9:J9) -> 369
B10: COGS | C10: =SUM(C7:C9) -> 6742 | D10: =SUM(D7:D9) -> 6974 | E10: =SUM(E7:E9) -> 6730 | F10: =SUM(F7:F9) -> 7114 | G10: =SUM(G7:G9) -> 6719 | H10: =SUM(H7:H9) -> 6819 | I10: =SUM(I7:I9) -> 6547 | J10: =SUM(J7:J9) -> 7116 | Q10: 26181 | R10: 24314 | S10: 25865 | T10: 27842 | U10: =SUM(U7:U9) -> 27560 | V10: =SUM(V7:V9) -> 27201
B11: Gross Profit | C11: =C6-C10 -> 7510 | D11: =D6-D10 -> 8501 | E11: =E6-E10 -> 8022 | F11: =F6-F10 -> 10267 | G11: =G6-G10 -> 7742 | H11: =H6-H10 -> 8950 | I11: =I6-I10 -> 8420 | J11: =J6-J10 -> 10440 | Q11: =Q6-Q10 -> 31533 | R11: =R6-R10 -> 30865 | S11: =S6-S10 -> 31485 | T11: =T6-T10 -> 32688 | U11: =U6-U10 -> 34300 | V11: =V6-V10 -> 35552 | W11: =W6*0.58 -> 37852.61 | X11: =X6*0.58 -> 39366.714 | Y11: =Y6*0.58 -> 40941.383 | Z11: =Z6*0.58 -> 42579.038 | AA11: =AA6*0.58 -> 44282.199 | AB11: =AB6*0.6 -> 47641.539 | AC11: =AC6*0.6 -> 49547.2 | AD11: =AD6*0.6 -> 51529.088 | AE11: =AE6*0.6 -> 53590.252 | AF11: =AF6*0.6 -> 55733.862 | AG11: =AG6*0.6 -> 57963.216 | AH11: =AH6*0.6 -> 60281.745 | AI11: =AI6*0.6 -> 62693.015 | AJ11: =AJ6*0.6 -> 65200.735
B12: Servides GP | C12: =C3-C7 -> 2214 | D12: =D3-D7 -> 2259 | E12: =E3-E7 -> 2324 | F12: =F3-F7 -> 2530 | G12: =G3-G7 -> 2231 | H12: =H3-H7 -> 2279 | I12: =I3-I7 -> 2405 | J12: =J3-J7 -> 2369 | U12: =U3-U7 -> 9327 | V12: =V3-V7 -> 9284
B13: Sales GP | C13: =C4-C8 -> 5210 | D13: =D4-D8 -> 6152 | E13: =E4-E8 -> 5606 | F13: =F4-F8 -> 7650 | G13: =G4-G8 -> 5418 | H13: =H4-H8 -> 6588 | I13: =I4-I8 -> 5930 | J13: =J4-J8 -> 7992 | U13: =U4-U8 -> 24618 | V13: =V4-V8 -> 25928
B14: Financing GP | C14: =C5-C9 -> 86 | D14: =D5-D9 -> 90 | E14: =E5-E9 -> 92 | F14: =F5-F9 -> 87 | G14: =G5-G9 -> 93 | H14: =H5-H9 -> 83 | I14: =I5-I9 -> 85 | J14: =J5-J9 -> 79 | U14: =U5-U9 -> 355 | V14: =V5-V9 -> 340
B15: SG&A | C15: 4853 | D15: 4900 | E15: 4458 | F15: =19003-SUM(C15:E15) -> 4792 | G15: 4974 | H15: 4938 | I15: 4911 | J15: =19688-SUM(G15:I15) -> 4865 | Q15: 18724 | R15: 20561 | S15: 18745 | T15: 18609 | U15: =SUM(C15:F15) -> 19003 | V15: =SUM(G15:J15) -> 19688
B16: R&D | C16: 1655 | D16: 1687 | E16: 1685 | F16: =6775-SUM(C16:E16) -> 1748 | G16: 1796 | H16: 1840 | I16: 1876 | J16: =7479-SUM(G16:I16) -> 1967 | Q16: 5910 | R16: 6262 | S16: 6488 | T16: 6567 | U16: =SUM(C16:F16) -> 6775 | V16: =SUM(G16:J16) -> 7479
B17: Operating Expenses | C17: =+C15+C16 -> 6508 | D17: =+D15+D16 -> 6587 | E17: =+E15+E16 -> 6143 | F17: =+F15+F16 -> 6540 | G17: =+G15+G16 -> 6770 | H17: =+H15+H16 -> 6778 | I17: =+I15+I16 -> 6787 | J17: =+J15+J16 -> 6832 | Q17: =+Q15+Q16 -> 24634 | R17: =+R15+R16 -> 26823 | S17: =+S15+S16 -> 25233 | T17: =+T15+T16 -> 25176 | U17: =+U15+U16 -> 25778 | V17: =+V15+V16 -> 27167 | W17: =V17*1.01 -> 27438.67 | X17: =W17*1.01 -> 27713.057 | Y17: =X17*1.01 -> 27990.187 | Z17: =Y17*1.01 -> 28270.089 | AA17: =Z17*1.01 -> 28552.79 | AB17: =AA17*1.01 -> 28838.318 | AC17: =AB17*1.01 -> 29126.701 | AD17: =AC17*1.01 -> 29417.968 | ... AJ17: =AI17*1.01 -> 31227.766
B18: Operating Income | C18: =C11-C17 -> 1002 | D18: =D11-D17 -> 1914 | E18: =E11-E17 -> 1879 | F18: =F11-F17 -> 3727 | G18: =G11-G17 -> 972 | H18: =H11-H17 -> 2172 | I18: =I11-I17 -> 1633 | J18: =J11-J17 -> 3608 | Q18: =Q11-Q17 -> 6899 | R18: =R11-R17 -> 4042 | S18: =S11-S17 -> 6252 | T18: =T11-T17 -> 7512 | U18: =U11-U17 -> 8522 | V18: =V11-V17 -> 8385 | W18: =W11-W17 -> 10413.94 | X18: =X11-X17 -> 11653.657 | ... AJ18: =AJ11-AJ17 -> 33972.969
B19: Other Expense | C19: =-180-245+367 -> -58 | D19: =-248-261+423 -> -86 | E19: =-190-215+412 -> 7 | F19: =-860-914+1607-SUM(C19:E19) -> -30 | G19: =-216-317+432 -> -101 | H19: =-241-233+427 -> -47 | I19: =-238+2244+429 -> 2435 | J19: =-996+1871+1712-SUM(G19:I19) -> 300 | Q19: =-639-1012+1344 -> -307 | R19: =-620+802+1288 -> 1470 | S19: =-612+873+1155 -> 1416 | T19: =-665+5803+1216 -> 6354 | U19: =SUM(C19:F19) -> -167 | V19: =SUM(G19:J19) -> 2587 | W19: 760 | X19: =W19*(1+$AM$25) -> 782.8 | Y19: =X19*(1+$AM$25) -> 806.284 | Z19: =Y19*(1+$AM$25) -> 830.47252 | AA19: =Z19*(1+$AM$25) -> 855.3867 | AB19: =AA19*(1+$AM$25) -> 881.0483 | AC19: =AB19*(1+$AM$25) -> 907.47975 | AD19: =AC19*(1+$AM$25) -> 934.70414 | AE19: =AD19*(1+$AM$25) -> 962.74526 | ... AJ19: =AI19*(1+$AM$25) -> 1116.0856
