Workbook

Sheet Model
B2: FY | C2: 39813 | D2: 40178 | E2: 40543 | F2: 40908 | G2: 41274 | H2: 41639 | I2: 42004 | J2: 42369 | K2: 42735 | L2: 43100 | M2: 43465 | N2: 43830 | O2: 44196 | P2: 44561 | Q2: 44926 | R2: 45291 | S2: 45657 | T2: 46022
B3: Revenue | C3: 60420 | D3: 58437 | E3: 62484 | F3: 69943 | G3: 73723 | H3: 77849 | I3: 86833 | J3: 93580 | K3: 91154 | L3: 96571 | M3: 110360 | N3: 125843 | O3: 143015 | P3: 168088 | Q3: 198270 | R3: 211915 | S3: 245122 | T3: 281724
B4: COGS | C4: 11598 | D4: 12155 | E4: 12395 | F4: 15577 | G4: 17530 | H4: 20385 | I4: 27078 | J4: 33038 | K4: 32780 | L4: 34261 | M4: 38353 | N4: 42910 | O4: 46078 | P4: 52232 | Q4: 62650 | R4: 65863 | S4: 74114 | T4: 87831
B5: Gross Profit | C5: =+C3-C4 -> 48822 | D5: =+D3-D4 -> 46282 | E5: =+E3-E4 -> 50089 | F5: =+F3-F4 -> 54366 | G5: =+G3-G4 -> 56193 | H5: =+H3-H4 -> 57464 | I5: =+I3-I4 -> 59755 | J5: =+J3-J4 -> 60542 | ... T5: =+T3-T4 -> 193893
B6: R&D Expense | C6: 8164 | D6: 9010 | E6: 8714 | F6: 9043 | G6: 9811 | H6: 10411 | I6: 11381 | J6: 12046 | K6: 11988 | L6: 13037 | M6: 14726 | N6: 16876 | O6: 19269 | P6: 20716 | Q6: 24512 | R6: 27195 | S6: 29510 | T6: 32488
B7: S&M Expense | C7: 13260 | D7: 12879 | E7: 13214 | F7: 13940 | G7: 20050 | H7: 15276 | I7: 15811 | J7: 25724 | K7: 15745 | L7: 15767 | M7: 17469 | N7: 18213 | O7: 19598 | P7: 20117 | Q7: 21825 | R7: 22759 | S7: 24456 | T7: 25654
B8: G&A Expense | C8: 5127 | D8: 4030 | E8: 4063 | F8: 4222 | G8: 4569 | H8: 5013 | I8: 4677 | J8: 4611 | K8: 4563 | L8: 4481 | M8: 4754 | N8: 4885 | O8: 5111 | P8: 5107 | Q8: 5900 | R8: 7575 | S8: 7609 | T8: 7223
B9: Operating Expenses | C9: =SUM(C6:C8) -> 26551 | D9: =SUM(D6:D8) -> 25919 | E9: =SUM(E6:E8) -> 25991 | F9: =SUM(F6:F8) -> 27205 | G9: =SUM(G6:G8) -> 34430 | H9: =SUM(H6:H8) -> 30700 | I9: =SUM(I6:I8) -> 31869 | J9: =SUM(J6:J8) -> 42381 | ... T9: =SUM(T6:T8) -> 65365
B10: Operating Income | C10: =C5-C9 -> 22271 | D10: =D5-D9 -> 20363 | E10: =E5-E9 -> 24098 | F10: =F5-F9 -> 27161 | G10: =G5-G9 -> 21763 | H10: =H5-H9 -> 26764 | I10: =I5-I9 -> 27886 | J10: =J5-J9 -> 18161 | ... T10: =T5-T9 -> 128528
B11: Other Income | C11: 1543 | D11: -542 | E11: 915 | F11: 910 | G11: 504 | H11: 288 | I11: 61 | J11: 346 | K11: -439 | L11: 876 | M11: 1416 | N11: 729 | O11: 77 | P11: 1186 | Q11: 333 | R11: 788 | S11: -1646 | T11: -4901
B12: Pretax Income | C12: =C10+C11 -> 23814 | D12: =D10+D11 -> 19821 | E12: =E10+E11 -> 25013 | F12: =F10+F11 -> 28071 | G12: =G10+G11 -> 22267 | H12: =H10+H11 -> 27052 | I12: =I10+I11 -> 27947 | J12: =J10+J11 -> 18507 | ... T12: =T10+T11 -> 123627
B13: Income Taxes | C13: 6133 | D13: 5252 | E13: 6253 | F13: 4921 | G13: 5289 | H13: 5189 | I13: 5746 | J13: 6314 | K13: 5100 | L13: 4412 | M13: 19903 | N13: 4448 | O13: 8755 | P13: 9831 | Q13: 10978 | R13: 16950 | S13: 19651 | T13: 21795
B14: Net Income | C14: =C12-C13 -> 17681 | D14: =D12-D13 -> 14569 | E14: =E12-E13 -> 18760 | F14: =F12-F13 -> 23150 | G14: =G12-G13 -> 16978 | H14: =H12-H13 -> 21863 | I14: =I12-I13 -> 22201 | J14: =J12-J13 -> 12193 | ... T14: =T12-T13 -> 101832
B15: S/O Basic | C15: 9328 | D15: 8945 | E15: 8813 | F15: 8490 | G15: 8396 | H15: 8375 | I15: 8299 | J15: 8177 | K15: 7925 | L15: 7746 | M15: 7700 | N15: 7673 | O15: 7610 | P15: 7547 | Q15: 7496 | R15: 7446 | S15: 7435 | T15: 7432
B16: EPS | C16: =C14/C15 -> 1.895476 | D16: =D14/D15 -> 1.6287311 | E16: =E14/E15 -> 2.1286736 | F16: =F14/F15 -> 2.7267373 | G16: =G14/G15 -> 2.0221534 | H16: =H14/H15 -> 2.6105075 | I16: =I14/I15 -> 2.6751416 | J16: =J14/J15 -> 1.4911337 | ... T16: =T14/T15 -> 13.70183
B18: Effective tax rate | C18: =C13/C12 -> 0.25753758 | D18: =D13/D12 -> 0.26497149 | E18: =E13/E12 -> 0.24999001 | F18: =F13/F12 -> 0.17530548 | G18: =G13/G12 -> 0.23752638 | H18: =H13/H12 -> 0.19181576 | I18: =I13/I12 -> 0.20560346 | J18: =J13/J12 -> 0.34116821 | ... T18: =T13/T12 -> 0.17629644
B20: % Growth | D20: =D3/C3-1 -> -0.032820258 | E20: =E3/D3-1 -> 0.069254068 | F20: =F3/E3-1 -> 0.11937456 | G20: =G3/F3-1 -> 0.054044007 | H20: =H3/G3-1 -> 0.055966252 | I20: =I3/H3-1 -> 0.1154029 | J20: =J3/I3-1 -> 0.077700874 | K20: =K3/J3-1 -> -0.025924343 | ... T20: =T3/S3-1 -> 0.14932156
B24: Net Cash | C24: =C25+C26-C39-C45 -> 23661.999 | D24: =D25+D26-D39-D45 -> 24017 | E24: =E25+E26-E39-E45 -> 30849 | F24: =F25+F26-F39-F45 -> 40851 | G24: =G25+G26-G39-G45 -> 51096 | H24: =H25+H26-H39-H45 -> 61422 | I24: =I25+I26-I39-I45 -> 63064 | J24: =J25+J26-J39-J45 -> 61234 | ... T24: =T25+T26-T39-T45 -> 51414
B25: Cash & Equivalents | C25: 10339 | D25: 6076 | E25: 5505 | F25: 9610 | G25: 6938 | H25: 3804 | I25: 8669 | J25: 5595 | K25: 6510 | L25: 7663 | M25: 11946 | N25: 11356 | O25: 13576 | P25: 14224 | Q25: 13931 | R25: 34704 | S25: 18315 | T25: 30242
B26: Short Term Investments | C26: 13323 | D26: 25371 | E26: 31283 | F26: 43162 | G26: 56102 | H26: 73218 | I26: 77040 | J26: 90931 | K26: 106730 | L26: 125318 | M26: 121822 | N26: 122463 | O26: 122951 | P26: 116110 | Q26: 90826 | R26: 76558 | S26: 57228 | T26: 64323
B27: Accounts Receivable | C27: 13589 | D27: 11192 | E27: 13014 | F27: 14987 | G27: 15780 | H27: 17486 | I27: 19544 | J27: 17908 | K27: 18277 | L27: 22431 | M27: 26481 | N27: 29524 | O27: 32011 | P27: 38043 | Q27: 44261 | R27: 48688 | S27: 56924 | T27: 69905
B28: Inventory | C28: 985 | D28: 717 | E28: 740 | F28: 1372 | G28: 1137 | H28: 1938 | I28: 2660 | J28: 2902 | K28: 2251 | L28: 2181 | M28: 2662 | N28: 2063 | O28: 1895 | P28: 2636 | Q28: 3742 | R28: 2500 | S28: 1246 | T28: 938
B29: Other Current Assets | C29: 5006 | D29: 5924 | E29: 5134 | F29: 5787 | G29: 5127 | H29: 5020 | I29: 6333 | J29: 5461 | K29: 5892 | L29: 5103 | M29: 6751 | N29: 10146 | O29: 11482 | P29: 13393 | Q29: 16924 | R29: 21807 | S29: 26021 | T29: 25723
B30: Current Assets | C30: =SUM(C25:C29) -> 43242 | D30: =SUM(D25:D29) -> 49280 | E30: =SUM(E25:E29) -> 55676 | F30: =SUM(F25:F29) -> 74918 | G30: =SUM(G25:G29) -> 85084 | H30: =SUM(H25:H29) -> 101466 | I30: =SUM(I25:I29) -> 114246 | J30: =SUM(J25:J29) -> 122797 | ... T30: =SUM(T25:T29) -> 191131
B31: PP&E | C31: 6242 | D31: 7535 | E31: 7630 | F31: 8162 | G31: 8269 | H31: 9991 | I31: 13011 | J31: 14731 | K31: 18356 | L31: 23734 | M31: 29460 | N31: 36477 | O31: 44151 | P31: 59715 | Q31: 74398 | R31: 95641 | S31: 135591 | T31: 204966
B32: Long Term Investments | C32: 6588 | D32: 4933 | E32: 7754 | F32: 10865 | G32: 9776 | H32: 10844 | I32: 14597 | J32: 12053 | K32: 10431 | L32: 6023 | M32: 1862 | N32: 2649 | O32: 2965 | P32: 5984 | Q32: 6891 | R32: 9879 | S32: 14600 | T32: 15405
B33: Goodwill | C33: 12108 | D33: 12503 | E33: 12394 | F33: 12581 | G33: 13452 | H33: 14655 | I33: 20127 | J33: 16939 | K33: 17872 | L33: 35122 | M33: 35683 | N33: 42026 | O33: 43351 | P33: 49711 | Q33: 67524 | R33: 67886 | S33: 119220 | T33: 119509
B34: Intangible assets | C34: 1973 | D34: 1759 | E34: 1158 | F34: 744 | G34: 3170 | H34: 3083 | I34: 6981 | J34: 4835 | K34: 3733 | L34: 10106 | M34: 8053 | N34: 7750 | O34: 7038 | P34: 7800 | Q34: 11298 | R34: 9366 | S34: 27597 | T34: 22604
B35: Other Noncurrent Assets | C35: 2640 | D35: 1878 | E35: 1501 | F35: 1434 | G35: 1520 | H35: 2392 | I35: 3422 | J35: 3117 | K35: 3416 | L35: 12631 | M35: 14128 | N35: 22102 | O35: 21891 | P35: 26163 | Q35: 35045 | R35: 44947 | S35: 55421 | T35: 65388
B36: Noncurrent Assets | C36: =SUM(C31:C35) -> 29551 | D36: =SUM(D31:D35) -> 28608 | E36: =SUM(E31:E35) -> 30437 | F36: =SUM(F31:F35) -> 33786 | G36: =SUM(G31:G35) -> 36187 | H36: =SUM(H31:H35) -> 40965 | I36: =SUM(I31:I35) -> 58138 | J36: =SUM(J31:J35) -> 51675 | ... T36: =SUM(T31:T35) -> 427872
B37: Total Assets | C37: =C30+C36 -> 72793 | D37: =D30+D36 -> 77888 | E37: =E30+E36 -> 86113 | F37: =F30+F36 -> 108704 | G37: =G30+G36 -> 121271 | H37: =H30+H36 -> 142431 | I37: =I30+I36 -> 172384 | J37: =J30+J36 -> 174472 | ... T37: =T30+T36 -> 619003
B38: Accounts Payable | C38: 4034 | D38: 3324 | E38: 4025 | F38: 4197 | G38: 4175 | H38: 4828 | I38: 7432 | J38: 6591 | K38: 6898 | L38: 7390 | M38: 8617 | N38: 9382 | O38: 12530 | P38: 15163 | Q38: 19000 | R38: 18095 | S38: 21996 | T38: 27724
B39: Short Term Debt | C39: 0 | D39: 3684 | E39: 1000 | F39: 0 | G39: 1231 | H39: 2999 | I39: 2000 | J39: 7484 | K39: 12904 | L39: 10121 | M39: 3998 | N39: 5516 | O39: 3749 | P39: 8072 | Q39: 2749 | R39: 5247 | S39: 8942 | T39: 2999
B40: Accrued compensation | C40: 2934 | D40: 3156 | E40: 3283 | F40: 3575 | G40: 3875 | H40: 4117 | I40: 4797 | J40: 5096 | K40: 5264 | L40: 5819 | M40: 6103 | N40: 6830 | O40: 7874 | P40: 10057 | Q40: 10661 | R40: 11009 | S40: 12564 | T40: 13709
B41: Income taxes | C41: 3248 | D41: 725 | E41: 1074 | F41: 580 | G41: 789 | H41: 592 | I41: 782 | J41: 606 | K41: 580 | L41: 718 | M41: 2121 | N41: 5665 | O41: 2130 | P41: 2174 | Q41: 4067 | R41: 4152 | S41: 5017 | T41: 7211
B42: Current Deferred Revenue | C42: 13397 | D42: 13003 | E42: 13652 | F42: 15722 | G42: 18653 | H42: 20639 | I42: 23150 | J42: 23223 | K42: 27468 | L42: 24013 | M42: 28905 | N42: 32676 | O42: 36000 | P42: 41525 | Q42: 45538 | R42: 50901 | S42: 57582 | T42: 64555
B43: Other Current Liabilities | C43: 6273 | D43: 3142 | E43: 3113 | F43: 4700 | G43: 3965 | H43: 4242 | I43: 7464 | J43: 6647 | K43: 6243 | L43: 7684 | M43: 8744 | N43: 9351 | O43: 10027 | P43: 11666 | Q43: 13067 | R43: 14745 | S43: 19185 | T43: 25020
B44: Current Liabilities | C44: =SUM(C38:C43) -> 29886 | D44: =SUM(D38:D43) -> 27034 | E44: =SUM(E38:E43) -> 26147 | F44: =SUM(F38:F43) -> 28774 | G44: =SUM(G38:G43) -> 32688 | H44: =SUM(H38:H43) -> 37417 | I44: =SUM(I38:I43) -> 45625 | J44: =SUM(J38:J43) -> 49647 | ... T44: =SUM(T38:T43) -> 141218
B45: Long Term Debt | C45: 0.001 | D45: 3746 | E45: 4939 | F45: 11921 | G45: 10713 | H45: 12601 | I45: 20645 | J45: 27808 | K45: 40557 | L45: 76073 | M45: 72242 | N45: 66662 | O45: 59578 | P45: 50074 | Q45: 47032 | R45: 41990 | S45: 42688 | T45: 40152
B46: Long Term Deferred Revenue | C46: 1900 | D46: 1281 | E46: 1178 | F46: 1398 | G46: 1406 | H46: 1760 | I46: 2008 | J46: 2095 | K46: 6441 | L46: 10377 | M46: 3815 | N46: 4530 | O46: 3180 | P46: 2616 | Q46: 2870 | R46: 2912 | S46: 2602 | T46: 2710
B47: Other Noncurrent Liabilities | C47: 6544 | D47: 6269 | E47: 7674 | F47: 9528 | G47: 10101 | H47: 11709 | I47: 14322 | J47: 14839 | K47: 15116 | L47: 20406 | M47: 41585 | N47: 43614 | O47: 47939 | P47: 50444 | Q47: 53314 | R47: 56702 | S47: 73110 | T47: 91444
B48: Noncurrent Liabilities | C48: =SUM(C45:C47) -> 8444.001 | D48: =SUM(D45:D47) -> 11296 | E48: =SUM(E45:E47) -> 13791 | F48: =SUM(F45:F47) -> 22847 | G48: =SUM(G45:G47) -> 22220 | H48: =SUM(H45:H47) -> 26070 | I48: =SUM(I45:I47) -> 36975 | J48: =SUM(J45:J47) -> 44742 | ... T48: =SUM(T45:T47) -> 134306
B49: Total Liabilities | C49: =C44+C48 -> 38330.001 | D49: =D44+D48 -> 38330 | E49: =E44+E48 -> 39938 | F49: =F44+F48 -> 51621 | G49: =G44+G48 -> 54908 | H49: =H44+H48 -> 63487 | I49: =I44+I48 -> 82600 | J49: =J44+J48 -> 94389 | ... T49: =T44+T48 -> 275524
B50: Total stockholders' equity | C50: 39558 | D50: 39558 | E50: 46175 | F50: 57083 | G50: 66363 | H50: 78944 | I50: 89784 | J50: 80083 | K50: 71997 | L50: 87711 | M50: 82718 | N50: 102330 | O50: 118304 | P50: 141988 | Q50: 166542 | R50: 206223 | S50: 268477 | T50: 343479
B51: Total liabilities and stockholders’ equity | C51: =+C50+C49 -> 77888.001 | D51: =+D50+D49 -> 77888 | E51: =+E50+E49 -> 86113 | F51: =+F50+F49 -> 108704 | G51: =+G50+G49 -> 121271 | H51: =+H50+H49 -> 142431 | I51: =+I50+I49 -> 172384 | J51: =+J50+J49 -> 174472 | ... T51: =+T50+T49 -> 619003
B54: Total Debt-to-Equity ratio | C54: =(C39+C45)/C50 -> 2.5279337e-08 | D54: =(D39+D45)/D50 -> 0.18782547 | E54: =(E39+E45)/E50 -> 0.12861938 | F54: =(F39+F45)/F50 -> 0.20883626 | G54: =(G39+G45)/G50 -> 0.17997981 | H54: =(H39+H45)/H50 -> 0.19760843 | I54: =(I39+I45)/I50 -> 0.25221643 | J54: =(J39+J45)/J50 -> 0.44069278 | ... T54: =(T39+T45)/T50 -> 0.12562922
B59: NOPAT | C59: =C10*(1-$T$65) -> 18068.09 | D59: =D10*(1-$T$65) -> 16520.162 | E59: =E10*(1-$T$65) -> 19550.305 | F59: =F10*(1-$T$65) -> 22035.265 | G59: =G10*(1-$T$65) -> 17655.958 | H59: =H10*(1-$T$65) -> 21713.186 | I59: =I10*(1-$T$65) -> 22623.446 | J59: =J10*(1-$T$65) -> 14733.716 | ... T59: =T10*(1-$T$65) -> 104272.62
B60: Invested capital | C60: =C39+C45+C50 -> 39558.001 | D60: =D39+D45+D50 -> 46988 | E60: =E39+E45+E50 -> 52114 | F60: =F39+F45+F50 -> 69004 | G60: =G39+G45+G50 -> 78307 | H60: =H39+H45+H50 -> 94544 | I60: =I39+I45+I50 -> 112429 | J60: =J39+J45+J50 -> 115375 | ... T60: =T39+T45+T50 -> 386630
B61: EVA | C61: =C59-(C60*WACC!D16) -> 14838.989 | D61: =D59-(D60*WACC!E16) -> 16520.162 | E61: =E59-(E60*WACC!F16) -> 19550.305 | F61: =F59-(F60*WACC!G16) -> 22035.265 | G61: =G59-(G60*WACC!H16) -> 17655.958 | H61: =H59-(H60*WACC!I16) -> 21713.186 | I61: =I59-(I60*WACC!J16) -> 22623.446 | J61: =J59-(J60*WACC!K16) -> 14733.716 | ... T61: =T59-(T60*WACC!U16) -> 104272.62
B62: % Growth | D62: =D61/C61-1 -> 0.11329427 | E62: =E61/D61-1 -> 0.18342091 | F62: =F61/E61-1 -> 0.12710598 | G62: =G61/F61-1 -> -0.19874084 | H62: =H61/G61-1 -> 0.22979369 | I62: =I61/H61-1 -> 0.041921985 | J62: =J61/I61-1 -> -0.3487413 | K62: =K61/J61-1 -> 0.43593414 | ... T62: =T61/S61-1 -> 0.17449033
B63: ROIC | C63: =C59/C60 -> 0.45674932 | D63: =D59/D60 -> 0.35158256 | E63: =E59/E60 -> 0.37514496 | F63: =F59/F60 -> 0.31933316 | G63: =G59/G60 -> 0.22547101 | H63: =H59/H60 -> 0.22966223 | I63: =I59/I60 -> 0.20122429 | J63: =J59/J60 -> 0.12770284 | ... T63: =T59/T60 -> 0.26969614
B64: WACC | C64: 0.081629526 | D64: 0.081629526 | E64: 0.081629526 | F64: 0.081629526 | G64: 0.081629526 | H64: 0.081629526 | I64: 0.081629526 | J64: 0.081629526 | K64: 0.081629526 | L64: 0.081629526 | M64: 0.081629526 | N64: 0.081629526 | O64: 0.081629526 | P64: 0.081629526 | Q64: 0.081629526 | R64: 0.081629526 | S64: 0.081629526 | T64: 0.081629526
B65: Selected tax rate | T65: =HARMEAN(C18:T18) -> 0.18871672
B67: Industry (Software (System & Application)
B68: ROIC | T68: =T74*T75 -> 0.51020288
B70: NOPAT Margin | C70: =C59/C3 -> 0.29904154 | D70: =D59/D3 -> 0.28270037 | E70: =E59/E3 -> 0.31288497 | F70: =F59/F3 -> 0.31504604 | G70: =G59/G3 -> 0.2394905 | H70: =H59/H3 -> 0.27891413 | I70: =I59/I3 -> 0.26053972 | J70: =J59/J3 -> 0.15744513 | ... T70: =T59/T3 -> 0.3701233
B71: Capital Turnover | C71: =C3/C60 -> 1.5273775 | D71: =D3/D60 -> 1.243658 | E71: =E3/E60 -> 1.1989868 | F71: =F3/F60 -> 1.0136079 | G71: =G3/G60 -> 0.94146117 | H71: =H3/H60 -> 0.82341555 | I71: =I3/I60 -> 0.77233632 | J71: =J3/J60 -> 0.81109426 | ... T71: =T3/T60 -> 0.72866565
B73: Industry (Software (System & Application)
B74: NOPAT Margin | T74: =(T83-T84-T85)/T86 -> 0.33188697
B75: Capital Turnover | T75: =1/(T93+T94+T95) -> 1.537279
B77: Gross Margin | C77: =C5/C3 -> 0.80804369 | D77: =D5/D3 -> 0.79199822 | E77: =E5/E3 -> 0.80162922 | F77: =F5/F3 -> 0.77729008 | G77: =G5/G3 -> 0.76221803 | H77: =H5/H3 -> 0.73814693 | I77: =I5/I3 -> 0.68816003 | J77: =J5/J3 -> 0.64695448 | ... T77: =T5/T3 -> 0.68823742
B78: SG&A Margin | C78: =(C7+C8)/C3 -> 0.30431976 | D78: =(D7+D8)/D3 -> 0.28935435 | E78: =(E7+E8)/E3 -> 0.27650278 | F78: =(F7+F8)/F3 -> 0.25966859 | G78: =(G7+G8)/G3 -> 0.3339392 | H78: =(H7+H8)/H3 -> 0.26061992 | I78: =(I7+I8)/I3 -> 0.23594716 | J78: =(J7+J8)/J3 -> 0.32416115 | ... T78: =(T7+T8)/T3 -> 0.11669932
B79: R&D Margin | C79: =C6/C3 -> 0.13512082 | D79: =D6/D3 -> 0.15418314 | E79: =E6/E3 -> 0.1394597 | F79: =F6/F3 -> 0.12929099 | G79: =G6/G3 -> 0.13307923 | H79: =H6/H3 -> 0.13373325 | I79: =I6/I3 -> 0.13106768 | J79: =J6/J3 -> 0.12872409 | ... T79: =T6/T3 -> 0.11531854
B80: (1-Tax rate) | C80: =1-$T$65 -> 0.81128328 | D80: =1-$T$65 -> 0.81128328 | E80: =1-$T$65 -> 0.81128328 | F80: =1-$T$65 -> 0.81128328 | G80: =1-$T$65 -> 0.81128328 | H80: =1-$T$65 -> 0.81128328 | I80: =1-$T$65 -> 0.81128328 | J80: =1-$T$65 -> 0.81128328 | ... T80: =1-$T$65 -> 0.81128328
B82: Industry (Software (System & Application)
B83: Gross Margin | T83: 0.7172
B84: SG&A Margin | T84: 0.1598
B85: R&D Margin | T85: 0.2438
B86: (1-Tax rate) | T86: =+(1-0.0551) -> 0.9449
B88: Fixed Asset Turnover Ratio | C88: =(C31+C34)/C3 -> 0.13596491 | D88: =(D31+D34)/D3 -> 0.15904307 | E88: =(E31+E34)/E3 -> 0.140644 | F88: =(F31+F34)/F3 -> 0.12733226 | G88: =(G31+G34)/G3 -> 0.15516189 | H88: =(H31+H34)/H3 -> 0.1679405 | I88: =(I31+I34)/I3 -> 0.23023505 | J88: =(J31+J34)/J3 -> 0.20908314 | ... T88: =(T31+T34)/T3 -> 0.80777641
B89: Working Capital Ratio | C89: =(C28+C27-C38)/C3 -> 0.17444555 | D89: =(D28+D27-D38)/D3 -> 0.14691035 | E89: =(E28+E27-E38)/E3 -> 0.15570386 | F89: =(F28+F27-F38)/F3 -> 0.17388445 | G89: =(G28+G27-G38)/G3 -> 0.17283616 | H89: =(H28+H27-H38)/H3 -> 0.18749117 | I89: =(I28+I27-I38)/I3 -> 0.17011965 | J89: =(J28+J27-J38)/J3 -> 0.15194486 | ... T89: =(T28+T27-T38)/T3 -> 0.15305405
B90: Net Other Assets Ratio | C90: =(C29+C35+C33)/C3 -> 0.32694472 | D90: =(D29+D35+D33)/D3 -> 0.34746821 | E90: =(E29+E35+E33)/E3 -> 0.30454196 | F90: =(F29+F35+F33)/F3 -> 0.28311625 | G90: =(G29+G35+G33)/G3 -> 0.27262862 | H90: =(H29+H35+H33)/H3 -> 0.283459 | I90: =(I29+I35+I33)/I3 -> 0.34413184 | J90: =(J29+J35+J33)/J3 -> 0.27267579 | ... T90: =(T29+T35+T33)/T3 -> 0.74761114
B92: Industry (Software (System & Application))
B93: Fixed Asset Turnover Ratio | T93: 0.14
B94: Working Capital Ratio | T94: 0.1005
B95: Net Other Assets Ratio | T95: 0.41
B98: Year-end close price | C98: 19.44 | D98: 30.48 | E98: 27.91 | F98: 25.96 | G98: 26.71 | H98: 37.41 | I98: 46.45 | J98: 55.48 | K98: 62.14 | L98: 85.54 | M98: 101.57 | N98: 157.7 | O98: 222.42 | P98: 336.32 | Q98: 239.82 | R98: 376.04 | S98: 421.5 | T98: 483.62
B99: Market Cap | C99: =C98*C15 -> 181336.32 | D99: =D98*D15 -> 272643.6 | E99: =E98*E15 -> 245970.83 | F99: =F98*F15 -> 220400.4 | G99: =G98*G15 -> 224257.16 | H99: =H98*H15 -> 313308.75 | I99: =I98*I15 -> 385488.55 | J99: =J98*J15 -> 453659.96 | ... T99: =T98*T15 -> 3594263.8
B102: Hypothetical Amortization Expense | C102: =+D6/5 -> 1802 | D102: =(SUM(C6:D6)/5) -> 3434.8 | E102: =SUM(C6:E6)/5 -> 5177.6 | F102: =SUM(C6:F6)/5 -> 6986.2 | G102: =SUM(C6:G6)/5 -> 8948.4 | H102: =SUM(D6:H6)/5 -> 9397.8 | I102: =SUM(E6:I6)/5 -> 9872 | J102: =SUM(F6:J6)/5 -> 10538.4 | K102: =SUM(G6:K6)/5 -> 11127.4 | L102: =SUM(H6:L6)/5 -> 11772.6 | M102: =SUM(I6:M6)/5 -> 12635.6 | N102: =SUM(J6:N6)/5 -> 13734.6 | ... T102: =SUM(P6:T6)/5 -> 26884.2
B103: Capitalized R&D | C103: =C6-C102 -> 6362 | D103: =C103+D6-D102 -> 11937.2 | E103: =D103+E6-E102 -> 15473.6 | F103: =E103+F6-F102 -> 17530.4 | G103: =F103+G6-G102 -> 18393 | H103: =G103+H6-H102 -> 19406.2 | I103: =H103+I6-I102 -> 20915.2 | J103: =I103+J6-J102 -> 22422.8 | K103: =J103+K6-K102 -> 23283.4 | ... T103: =S103+T6-T102 -> 59307.6
B104: Adjusted Invested Capital | C104: =C60 -> 39558.001 | D104: =D60+D103 -> 58925.2 | E104: =E60+E103 -> 67587.6 | F104: =F60+F103 -> 86534.4 | G104: =G60+G103 -> 96700 | H104: =H60+H103 -> 113950.2 | I104: =I60+I103 -> 133344.2 | J104: =J60+J103 -> 137797.8 | K104: =K60+K103 -> 148741.4 | ... T104: =T60+T103 -> 445937.6
B105: Adjusted NOPAT | C105: =(C5-C7-C8-C102+C114)*(1-$T$65) -> 25967.555 | D105: =(D5-D7-D8-D102+D114)*(1-$T$65) -> 22115.745 | E105: =(E5-E7-E8-E102+E114)*(1-$T$65) -> 24203.339 | F105: =(F5-F7-F8-F102+F114)*(1-$T$65) -> 27013.137 | G105: =(G5-G7-G8-G102+G114)*(1-$T$65) -> 27199.57 | H105: =(H5-H7-H8-H102+H114)*(1-$T$65) -> 26274.383 | I105: =(I5-I7-I8-I102+I114)*(1-$T$65) -> 27621.762 | J105: =(J5-J7-J8-J102+J114)*(1-$T$65) -> 23414.934 | ... T105: =(T5-T7-T8-T102+T114)*(1-$T$65) -> 119027.26
B107: Adjusted EVA | C107: =+C105-(C104*WACC!$D$16) -> 22738.454 | D107: =+D105-(D104*WACC!$D$16) -> 17305.708 | E107: =+E105-(E104*WACC!$D$16) -> 18686.195 | F107: =+F105-(F104*WACC!$D$16) -> 19949.375 | G107: =+G105-(G104*WACC!$D$16) -> 19305.995 | H107: =+H105-(H104*WACC!$D$16) -> 16972.682 | I107: =+I105-(I104*WACC!$D$16) -> 16736.938 | J107: =+J105-(J104*WACC!$D$16) -> 12166.564 | ... T107: =+T105-(T104*WACC!$D$16) -> 82625.59
B108: Adjusted ROIC | C108: =C105/C104 -> 0.65644256 | D108: =D105/D104 -> 0.37531896 | E108: =E105/E104 -> 0.35810324 | F108: =F105/F104 -> 0.31216646 | G108: =G105/G104 -> 0.28127787 | H108: =H105/H104 -> 0.23057777 | I108: =I105/I104 -> 0.20714633 | J108: =J105/J104 -> 0.16992241 | ... T108: =T105/T104 -> 0.26691462
B109: Normal % Diff. | C109: =C107/C61-1 -> 0.53234525 | D109: =D107/D61-1 -> 0.0475508 | E109: =E107/E61-1 -> -0.044199292 | F109: =F107/F61-1 -> -0.094661448 | G109: =G107/G61-1 -> 0.093454959 | H109: =H107/H61-1 -> -0.21832374 | I109: =I107/I61-1 -> -0.26019501 | J109: =J107/J61-1 -> -0.17423651 | ... T109: =T107/T61-1 -> -0.20760031
B111: Net Income | C111: 17681 | D111: 14569 | E111: 18760 | F111: 23150 | G111: 16978 | H111: 21863 | I111: 22074 | J111: 12193 | K111: 20539 | L111: 25489 | M111: 16571 | N111: 39240 | O111: 44281 | P111: 61271 | Q111: 72738 | R111: 72361 | S111: 88136 | T111: 101832
B112: D&A | C112: 2056 | D112: 2562 | E112: 2673 | F112: 2766 | G112: 2967 | H112: 3755 | I112: 5212 | J112: 5957 | K112: 6622 | L112: 8778 | M112: 10261 | N112: 11682 | O112: 12796 | P112: 11686 | Q112: 14460 | R112: 13861 | S112: 22287 | T112: 34153
B113: Deferred Taxes | C113: 935 | D113: 762 | E113: -220 | F113: 2 | G113: 954 | H113: -19 | I113: -331 | J113: 224 | K113: 2479 | L113: -829 | M113: -5143 | N113: -6463 | O113: 11 | P113: -150 | Q113: -5702 | R113: -6059 | S113: -4738 | T113: -7056
B114: Non-Cash Items | C114: 3375 | D114: 1322 | E114: 2199 | F114: 4079 | G114: 10901 | H114: 4609 | I114: 4652 | J114: 9193 | K114: 3075 | L114: 1193 | M114: 1728 | N114: 3860 | O114: 5070 | P114: 4869 | Q114: 7093 | R114: 9807 | S114: 11039 | T114: 12583
B115: Cash Taxes Paid | C115: 5400 | D115: 6600 | E115: 4100 | F115: 5300 | G115: 3500 | H115: 3900 | I115: 5500 | J115: 4400 | K115: 3900 | L115: 1600 | M115: 5500 | N115: 8400 | O115: 12500 | P115: 13400 | Q115: 16000 | R115: 23100 | S115: 23400 | T115: 28700
B116: Cash Interest Paid | C116: - | D116: - | E116: 145 | F116: 197 | G116: 344 | H116: 371 | I116: 509 | J116: 620 | K116: 1100 | L116: 1600 | M116: 2400 | N116: 2400 | O116: 2400 | P116: 2000 | Q116: 1900 | R116: 1700 | S116: 1700 | T116: 1600
B117: Changes in Working Capital | C117: -2435 | D117: -178 | E117: 661 | F117: -3003 | G117: -174 | H117: -1375 | I117: 624 | J117: 1513 | K117: 610 | L117: 4876 | M117: 20467 | N117: 3866 | O117: -1483 | P117: -936 | Q117: 446 | R117: -2388 | S117: 1824 | T117: -5350
B118: Cash from Operating Activities | C118: 21612 | D118: 19037 | E118: 24073 | F118: 26994 | G118: 31626 | H118: 28833 | I118: 32231 | J118: 29080 | K118: 33325 | L118: 39507 | M118: 43884 | N118: 52185 | O118: 60675 | P118: 76740 | Q118: 89035 | R118: 87582 | S118: 118548 | T118: 136162
B120: Capital Expenditures | C120: -3182 | D120: -3119 | E120: -1977 | F120: -2355 | G120: -2305 | H120: -4257 | I120: -5485 | J120: -5944 | K120: -8343 | L120: -8129 | M120: -11632 | N120: -13925 | O120: -15441 | P120: -20622 | Q120: -23886 | R120: -28107 | S120: -44477 | T120: -64551
B121: Other Investing Cash Flow Items | C121: -1405 | D121: -12651 | E121: -9337 | F121: -12261 | G121: -22481 | H121: -19554 | I121: -13348 | J121: -17057 | K121: -15607 | L121: -38652 | M121: 5571 | N121: -1848 | O121: 3218 | P121: -6955 | Q121: -6425 | R121: 5427 | S121: -52493 | T121: -8048
B122: Cash from Investing Activities | C122: -4587 | D122: -15770 | E122: -11314 | F122: -14616 | G122: -24786 | H122: -23811 | I122: -18833 | J122: -23001 | K122: -23950 | L122: -46781 | M122: -6061 | N122: -15773 | O122: -12223 | P122: -27577 | Q122: -30311 | R122: -22680 | S122: -96970 | T122: -72599
B124: Financing Cash Flow Items | C124: 120 | D124: 33 | E124: 55 | F124: -23 | G124: 93 | H124: 199 | I124: 232 | J124: 950 | K124: -369 | L124: -190 | M124: -971 | N124: -675 | O124: -3751 | P124: -2523 | Q124: -863 | R124: -1006 | S124: -1309 | T124: -2291
B125: Total Cash Dividends Paid | C125: -4015 | D125: -4468 | E125: -4578 | F125: -5180 | G125: -6385 | H125: -7455 | I125: -8879 | J125: -9882 | K125: -11006 | L125: -11845 | M125: -12699 | N125: -13811 | O125: -15137 | P125: -16521 | Q125: -18135 | R125: -19800 | S125: -21771 | T125: -24082
B126: Issuance (Retirement) of Stock | C126: -9039 | D126: -8774 | E126: -8958 | F126: -9133 | G126: -3116 | H126: -4429 | I126: -6709 | J126: -13809 | K126: -15301 | L126: -11016 | M126: -9719 | N126: -18401 | O126: -21625 | P126: -25692 | Q126: -30855 | R126: -20379 | S126: -15252 | T126: -16364
B127: Issuance (Retirement) of Debt | C127: - | D127: 5746 | E127: 190 | F127: 5960 | G127: - | H127: 3537 | I127: 6962 | J127: 13661 | K127: 18283 | L127: 31459 | M127: -10201 | N127: -4000 | O127: -5518 | P127: -3750 | Q127: -9023 | R127: -2750 | S127: 575 | T127: -8962
...

Sheet Segments
B2: FY | C2: 42735 | D2: 43100 | E2: 43465 | F2: 43830 | G2: 44196 | H2: 44561 | I2: 44926 | J2: 45291 | K2: 45657 | L2: 2025
A3: Server & Cloud (Pre-FY25) | B3: Server Products and Cloud Services Revenue (Pre-FY2025) | C3: 19062 | D3: 21649 | E3: 26129 | F3: 32622 | G3: 41379 | H3: 52589 | I3: 67350 | J3: 79970 | K3: 97726 | L3: 114163.69
A4: Office | B4: Office Products and Cloud Services | C4: 23868 | D4: 25573 | E4: 28316 | F4: 31769 | G4: 35316 | H4: 39872 | I4: 44970 | J4: 48848 | K4: 54875 | L4: 64105.073
A5: Windows | B5: Windows | C5: 17548 | D5: 18593 | E5: 19518 | F5: 20395 | G5: 21510 | H5: 22488 | I5: 24732 | J5: 21507 | K5: 23244 | L5: 27153.682
A6: Gaming | B6: Gaming | C6: 9202 | D6: 9051 | E6: 10353 | F6: 11386 | G6: 11575 | H6: 15370 | I6: 16230 | J6: 15466 | K6: 21503 | L6: 23455
A7: Search & Ads | B7: Search and News Advertising | C7: 5428 | D7: 6219 | E7: 7012 | F7: 7628 | G7: 8524 | H7: 9267 | I7: 11526 | J7: 12125 | K7: 12306 | L7: 13878
A8: Enterprise Services | B8: Enterprise and Partner Services | C8: 5659 | D8: 5542 | E8: 5846 | F8: 6124 | G8: 6409 | H8: 6943 | I8: 7605 | J8: 7900 | K8: 7594 | L8: 7885
A9: Devices | B9: Devices | C9: 7888 | D9: 5062 | E9: 5134 | F9: 6095 | G9: 6457 | H9: 7143 | I9: 7306 | J9: 5521 | K9: 4706 | L9: 5497.5576
A10: Other Products (Pre-FY23) | B10: Other Product Revenue (Pre-FY2023) | C10: 2499 | D10: 2611 | E10: 2793 | F10: 3070 | G10: 3768 | H10: 4479 | I10: 5291 | J10: 0 | K10: 0 | L10: 0
A11: LinkedIn | B11: LinkedIn | C11: 0 | D11: 2271 | E11: 5259 | F11: 6754 | G11: 8077 | H11: 10289 | I11: 13631 | J11: 14989 | K11: 16372 | L11: 17812
A12: Dynamics | B12: Dynamics Products and Cloud Services | C12: 0 | D12: 0 | E12: 0 | F12: 0 | G12: 0 | H12: 3754 | I12: 4687 | J12: 5796 | K12: 6831 | L12: 7702
A13: Other Products (Post-FY22) | B13: Other Product Revenue (Post-FY2022) | C13: 0 | D13: 0 | E13: 0 | F13: 0 | G13: 0 | H13: 373 | I13: 233 | J13: 119 | K13: 45 | L13: 72
A14: Other | B14: Other | C14: 0 | D14: 0 | E14: 0 | F14: 0 | G14: 0 | H14: -4479 | I14: -5291 | J14: -155846 | K14: -180551 | L14: =-SUM(L15:L18) -> -210920
A15: Server & Cloud (Post-FY24) | B15: Server Products and Cloud Services Revenue (Post-FY2024) | C15: 0 | D15: 0 | E15: 0 | F15: 0 | G15: 0 | H15: 0 | I15: 0 | J15: 65007 | K15: 79828 | L15: 98435
A16: M365 Commercial | B16: Microsoft 365 Commercial Products and Cloud Services | C16: 0 | D16: 0 | E16: 0 | F16: 0 | G16: 0 | H16: 0 | I16: 0 | J16: 66949 | K16: 76969 | L16: 87767
A17: Windows & Devices | B17: Windows and Devices | C17: 0 | D17: 0 | E17: 0 | F17: 0 | G17: 0 | H17: 0 | I17: 0 | J17: 17147 | K17: 17026 | L17: 17314
A18: M365 Consumer | B18: Microsoft 365 Consumer Products and Cloud Services | C18: 0 | D18: 0 | E18: 0 | F18: 0 | G18: 0 | H18: 0 | I18: 0 | J18: 6417 | K18: 6648 | L18: 7404
B19: Total Revenue by Product | C19: =SUM(C3:C18) -> 91154 | D19: =SUM(D3:D18) -> 96571 | E19: =SUM(E3:E18) -> 110360 | F19: =SUM(F3:F18) -> 125843 | G19: =SUM(G3:G18) -> 143015 | H19: =SUM(H3:H18) -> 168088 | I19: =SUM(I3:I18) -> 198270 | J19: =SUM(J3:J18) -> 211915 | ... L19: =SUM(L3:L18) -> 281724 | N19: =L19/C19 -> 3.0906378
A21: Other | C21: =C10+C13 -> 2499 | D21: =D10+D13 -> 2611 | E21: =E10+E13 -> 2793 | F21: =F10+F13 -> 3070 | G21: =G10+G13 -> 3768 | H21: =H10+H13 -> 4852 | I21: =I10+I13 -> 5524 | J21: =J10+J13 -> 119 | ... L21: =L10+L13 -> 72
B23: Growth Y/Y | N23: CAGR
B24: Server & Cloud (Pre-FY25) | D24: =D3/C3-1 -> 0.13571504 | E24: =E3/D3-1 -> 0.20693796 | F24: =F3/E3-1 -> 0.24849784 | G24: =G3/F3-1 -> 0.26843848 | H24: =H3/G3-1 -> 0.27091037 | I24: =I3/H3-1 -> 0.28068608 | J24: =J3/I3-1 -> 0.18737936 | K24: =K3/J3-1 -> 0.22203326 | L24: =L3/K3-1 -> 0.16820178 | N24: =(L3/C3)^(1/10)-1 -> 0.19601314
B25: Office | D25: =D4/C4-1 -> 0.071434557 | E25: =E4/D4-1 -> 0.10726156 | F25: =F4/E4-1 -> 0.12194519 | G25: =G4/F4-1 -> 0.11164972 | H25: =H4/G4-1 -> 0.12900668 | I25: =I4/H4-1 -> 0.12785915 | J25: =J4/I4-1 -> 0.086235268 | K25: =K4/J4-1 -> 0.12338274 | L25: =L4/K4-1 -> 0.16820178 | N25: =(L4/C4)^(1/10)-1 -> 0.10384384
B26: Windows | D26: =D5/C5-1 -> 0.059550946 | E26: =E5/D5-1 -> 0.049749906 | F26: =F5/E5-1 -> 0.044932882 | G26: =G5/F5-1 -> 0.054670262 | H26: =H5/G5-1 -> 0.045467225 | I26: =I5/H5-1 -> 0.099786553 | J26: =J5/I5-1 -> -0.13039787 | K26: =K5/J5-1 -> 0.080764402 | L26: =L5/K5-1 -> 0.16820178 | N26: =(L5/C5)^(1/10)-1 -> 0.044624267
B27: Gaming | D27: =D6/C6-1 -> -0.016409476 | E27: =E6/D6-1 -> 0.14385151 | F27: =F6/E6-1 -> 0.099777842 | G27: =G6/F6-1 -> 0.016599333 | H27: =H6/G6-1 -> 0.32786177 | I27: =I6/H6-1 -> 0.055953155 | J27: =J6/I6-1 -> -0.047073321 | K27: =K6/J6-1 -> 0.3903401 | L27: =L6/K6-1 -> 0.090778031 | N27: =(L6/C6)^(1/10)-1 -> 0.098083386
B28: Search & Ads | D28: =D7/C7-1 -> 0.14572587 | E28: =E7/D7-1 -> 0.12751246 | F28: =F7/E7-1 -> 0.087849401 | G28: =G7/F7-1 -> 0.11746198 | H28: =H7/G7-1 -> 0.08716565 | I28: =I7/H7-1 -> 0.24376821 | J28: =J7/I7-1 -> 0.05196946 | K28: =K7/J7-1 -> 0.014927835 | L28: =L7/K7-1 -> 0.12774256 | N28: =(L7/C7)^(1/10)-1 -> 0.098420689
B29: Enterprise Services | D29: =D8/C8-1 -> -0.020675031 | E29: =E8/D8-1 -> 0.054853843 | F29: =F8/E8-1 -> 0.047553883 | G29: =G8/F8-1 -> 0.04653821 | H29: =H8/G8-1 -> 0.083320331 | I29: =I8/H8-1 -> 0.095347832 | J29: =J8/I8-1 -> 0.03879027 | K29: =K8/J8-1 -> -0.038734177 | L29: =L8/K8-1 -> 0.038319726 | N29: =(L8/C8)^(1/10)-1 -> 0.033727811
B30: Devices | D30: =D9/C9-1 -> -0.35826572 | E30: =E9/D9-1 -> 0.014223627 | F30: =F9/E9-1 -> 0.18718348 | G30: =G9/F9-1 -> 0.059392945 | H30: =H9/G9-1 -> 0.10624129 | I30: =I9/H9-1 -> 0.022819544 | J30: =J9/I9-1 -> -0.24431974 | K30: =K9/J9-1 -> -0.14761819 | L30: =L9/K9-1 -> 0.16820178 | N30: =(L9/C9)^(1/10)-1 -> -0.035459898
B31: LinkedIn | D31: =D11/C11-1 -> #DIV/0! | E31: =E11/D11-1 -> 1.3157199 | F31: =F11/E11-1 -> 0.28427458 | G31: =G11/F11-1 -> 0.19588392 | H31: =H11/G11-1 -> 0.27386406 | I31: =I11/H11-1 -> 0.32481291 | J31: =J11/I11-1 -> 0.099625853 | K31: =K11/J11-1 -> 0.092267663 | L31: =L11/K11-1 -> 0.087955045 | N31: =(L11/C11)^(1/10)-1 -> #DIV/0!
B32: Dynamics | D32: =D12/C12-1 -> #DIV/0! | E32: =E12/D12-1 -> #DIV/0! | F32: =F12/E12-1 -> #DIV/0! | G32: =G12/F12-1 -> #DIV/0! | H32: =H12/G12-1 -> #DIV/0! | I32: =I12/H12-1 -> 0.2485349 | J32: =J12/I12-1 -> 0.23661191 | K32: =K12/J12-1 -> 0.17857143 | L32: =L12/K12-1 -> 0.12750695 | N32: =(L12/C12)^(1/10)-1 -> #DIV/0!
B33: Total Revenue | D33: =D19/C19-1 -> 0.059426904 | E33: =E19/D19-1 -> 0.14278614 | F33: =F19/E19-1 -> 0.1402954 | G33: =G19/F19-1 -> 0.13645574 | H33: =H19/G19-1 -> 0.17531727 | I33: =I19/H19-1 -> 0.17956071 | J33: =J19/I19-1 -> 0.068820296 | K33: =K19/J19-1 -> 0.15669962 | L33: =L19/K19-1 -> 0.14932156 | N33: =(L19/C19)^(1/10)-1 -> 0.11945029
B36: % of total Revenue
B37: Server & Cloud | C37: =C3/C$19 -> 0.20911863 | D37: =D3/D$19 -> 0.22417703 | E37: =E3/E$19 -> 0.23676151 | F37: =F3/F$19 -> 0.25922777 | G37: =G3/G$19 -> 0.28933329 | H37: =H3/H$19 -> 0.31286588 | I37: =I3/I$19 -> 0.3396883 | J37: =J3/J$19 -> 0.37736828 | ... L37: =L3/L$19 -> 0.40523238
B38: Office | C38: =C4/C$19 -> 0.2618426 | D38: =D4/D$19 -> 0.26481035 | E38: =E4/E$19 -> 0.25657847 | F38: =F4/F$19 -> 0.25244948 | G38: =G4/G$19 -> 0.24693913 | H38: =H4/H$19 -> 0.23720908 | I38: =I4/I$19 -> 0.22681192 | J38: =J4/J$19 -> 0.23050751 | ... L38: =L4/L$19 -> 0.22754566
B39: Windows | C39: =C5/C$19 -> 0.19250938 | D39: =D5/D$19 -> 0.19253192 | E39: =E5/E$19 -> 0.17685756 | F39: =F5/F$19 -> 0.16206702 | G39: =G5/G$19 -> 0.1504038 | H39: =H5/H$19 -> 0.13378706 | I39: =I5/I$19 -> 0.12473899 | J39: =J5/J$19 -> 0.1014888 | ... L39: =L5/L$19 -> 0.096383987
B40: Gaming | C40: =C6/C$19 -> 0.10095004 | D40: =D6/D$19 -> 0.093723789 | E40: =E6/E$19 -> 0.093811163 | F40: =F6/F$19 -> 0.090477818 | G40: =G6/G$19 -> 0.080935566 | H40: =H6/H$19 -> 0.091440198 | I40: =I6/I$19 -> 0.081858072 | J40: =J6/J$19 -> 0.072982092 | ... L40: =L6/L$19 -> 0.083255243
B41: Search & Ads | C41: =C7/C$19 -> 0.059547579 | D41: =D7/D$19 -> 0.064398215 | E41: =E7/E$19 -> 0.063537514 | F41: =F7/F$19 -> 0.060615211 | G41: =G7/G$19 -> 0.05960214 | H41: =H7/H$19 -> 0.055131836 | I41: =I7/I$19 -> 0.058132849 | J41: =J7/J$19 -> 0.057216337 | ... L41: =L7/L$19 -> 0.049260979
B42: Enterprise Services | C42: =C8/C$19 -> 0.062081752 | D42: =D8/D$19 -> 0.057387829 | E42: =E8/E$19 -> 0.052972091 | F42: =F8/F$19 -> 0.048663811 | G42: =G8/G$19 -> 0.044813481 | H42: =H8/H$19 -> 0.041305745 | I42: =I8/I$19 -> 0.038356786 | J42: =J8/J$19 -> 0.037279098 | ... L42: =L8/L$19 -> 0.027988386
B43: Devices | C43: =C9/C$19 -> 0.086534875 | D43: =D9/D$19 -> 0.052417392 | E43: =E9/E$19 -> 0.046520478 | F43: =F9/F$19 -> 0.048433365 | G43: =G9/G$19 -> 0.04514911 | H43: =H9/H$19 -> 0.042495598 | I43: =I9/I$19 -> 0.036848742 | J43: =J9/J$19 -> 0.026052899 | ... L43: =L9/L$19 -> 0.019513984
B44: LinkedIn | C44: =C11/C$19 -> 0 | D44: =D11/D$19 -> 0.023516377 | E44: =E11/E$19 -> 0.047653135 | F44: =F11/F$19 -> 0.053670049 | G44: =G11/G$19 -> 0.056476593 | H44: =H11/H$19 -> 0.061211984 | I44: =I11/I$19 -> 0.068749685 | J44: =J11/J$19 -> 0.070731189 | ... L44: =L11/L$19 -> 0.063225
B45: Dynamics | C45: =C12/C$19 -> 0 | D45: =D12/D$19 -> 0 | E45: =E12/E$19 -> 0 | F45: =F12/F$19 -> 0 | G45: =G12/G$19 -> 0 | H45: =H12/H$19 -> 0.02233354 | I45: =I12/I$19 -> 0.023639482 | J45: =J12/J$19 -> 0.027350589 | ... L45: =L12/L$19 -> 0.027338814
B46: Other | C46: =C21/C$19 -> 0.027415144 | D46: =D21/D$19 -> 0.027037102 | E46: =E21/E$19 -> 0.025308083 | F46: =F21/F$19 -> 0.024395477 | G46: =G21/G$19 -> 0.026346887 | H46: =H21/H$19 -> 0.028865832 | I46: =I21/I$19 -> 0.027860998 | J46: =J21/J$19 -> 0.0005615459 | ... L46: =L21/L$19 -> 0.00025556928
T63: Linear Scaling | W63: 1 | X63: =1+W63 -> 2 | Y63: =1+X63 -> 3 | Z63: =1+Y63 -> 4 | AA63: =1+Z63 -> 5 | AB63: =1+AA63 -> 6 | AC63: =1+AB63 -> 7 | AD63: =1+AC63 -> 8 | AE63: =1+AD63 -> 9 | ... DR63: =1+DQ63 -> 100
V64: Server & Cloud | W64: =10746*W63-3837.8 -> 6908.2 | X64: =10746*X63-3837.8 -> 17654.2 | Y64: =10746*Y63-3837.8 -> 28400.2 | Z64: =10746*Z63-3837.8 -> 39146.2 | AA64: =10746*AA63-3837.8 -> 49892.2 | AB64: =10746*AB63-3837.8 -> 60638.2 | AC64: =10746*AC63-3837.8 -> 71384.2 | AD64: =10746*AD63-3837.8 -> 82130.2 | ... DR64: =10746*DR63-3837.8 -> 1070762.2
V65: Office | W65: =4327.7*W63 + 15949 -> 20276.7 | X65: =4327.7*X63 + 15949 -> 24604.4 | Y65: =4327.7*Y63 + 15949 -> 28932.1 | Z65: =4327.7*Z63 + 15949 -> 33259.8 | AA65: =4327.7*AA63 + 15949 -> 37587.5 | AB65: =4327.7*AB63 + 15949 -> 41915.2 | AC65: =4327.7*AC63 + 15949 -> 46242.9 | AD65: =4327.7*AD63 + 15949 -> 50570.6 | ... DR65: =4327.7*DR63 + 15949 -> 448719
V66: Windows | W66: =866.32*W63 + 16904 -> 17770.32 | X66: =866.32*X63 + 16904 -> 18636.64 | Y66: =866.32*Y63 + 16904 -> 19502.96 | Z66: =866.32*Z63 + 16904 -> 20369.28 | AA66: =866.32*AA63 + 16904 -> 21235.6 | AB66: =866.32*AB63 + 16904 -> 22101.92 | AC66: =866.32*AC63 + 16904 -> 22968.24 | AD66: =866.32*AD63 + 16904 -> 23834.56 | ... DR66: =866.32*DR63 + 16904 -> 103536
V67: Gaming | W67: =1571.7*W63 + 5714.7 -> 7286.4 | X67: =1571.7*X63 + 5714.7 -> 8858.1 | Y67: =1571.7*Y63 + 5714.7 -> 10429.8 | Z67: =1571.7*Z63 + 5714.7 -> 12001.5 | AA67: =1571.7*AA63 + 5714.7 -> 13573.2 | AB67: =1571.7*AB63 + 5714.7 -> 15144.9 | AC67: =1571.7*AC63 + 5714.7 -> 16716.6 | AD67: =1571.7*AD63 + 5714.7 -> 18288.3 | ... DR67: =1571.7*DR63 + 5714.7 -> 162884.7
V68: Search & Ads | W68: =949.46*W63 + 4169.3 -> 5118.76 | X68: =949.46*X63 + 4169.3 -> 6068.22 | Y68: =949.46*Y63 + 4169.3 -> 7017.68 | Z68: =949.46*Z63 + 4169.3 -> 7967.14 | AA68: =949.46*AA63 + 4169.3 -> 8916.6 | AB68: =949.46*AB63 + 4169.3 -> 9866.06 | AC68: =949.46*AC63 + 4169.3 -> 10815.52 | AD68: =949.46*AD63 + 4169.3 -> 11764.98 | ... DR68: =949.46*DR63 + 4169.3 -> 99115.3
V69: Enterprise Services | W69: =300.88*W63 + 5095.9 -> 5396.78 | X69: =300.88*X63 + 5095.9 -> 5697.66 | Y69: =300.88*Y63 + 5095.9 -> 5998.54 | Z69: =300.88*Z63 + 5095.9 -> 6299.42 | AA69: =300.88*AA63 + 5095.9 -> 6600.3 | AB69: =300.88*AB63 + 5095.9 -> 6901.18 | AC69: =300.88*AC63 + 5095.9 -> 7202.06 | AD69: =300.88*AD63 + 5095.9 -> 7502.94 | ... DR69: =300.88*DR63 + 5095.9 -> 35183.9
V70: Devices | W70: =107.59*W63 + 6672.7 -> 6780.29 | X70: =107.59*X63 + 6672.7 -> 6887.88 | Y70: =107.59*Y63 + 6672.7 -> 6995.47 | Z70: =107.59*Z63 + 6672.7 -> 7103.06 | AA70: =107.59*AA63 + 6672.7 -> 7210.65 | AB70: =107.59*AB63 + 6672.7 -> 7318.24 | AC70: =107.59*AC63 + 6672.7 -> 7425.83 | AD70: =107.59*AD63 + 6672.7 -> 7533.42 | ... DR70: =107.59*DR63 + 6672.7 -> 17431.7
V71: LinkedIn | W71: =2003.1*W63 - 1471.5 -> 531.6 | X71: =2003.1*X63 - 1471.5 -> 2534.7 | Y71: =2003.1*Y63 - 1471.5 -> 4537.8 | Z71: =2003.1*Z63 - 1471.5 -> 6540.9 | AA71: =2003.1*AA63 - 1471.5 -> 8544 | AB71: =2003.1*AB63 - 1471.5 -> 10547.1 | AC71: =2003.1*AC63 - 1471.5 -> 12550.2 | AD71: =2003.1*AD63 - 1471.5 -> 14553.3 | ... DR71: =2003.1*DR63 - 1471.5 -> 198838.5
V72: Dynamics | W72: =993.52*W63 - 2587.3 -> -1593.78 | X72: =993.52*X63 - 2587.3 -> -600.26 | Y72: =993.52*Y63 - 2587.3 -> 393.26 | Z72: =993.52*Z63 - 2587.3 -> 1386.78 | AA72: =993.52*AA63 - 2587.3 -> 2380.3 | AB72: =993.52*AB63 - 2587.3 -> 3373.82 | AC72: =993.52*AC63 - 2587.3 -> 4367.34 | AD72: =993.52*AD63 - 2587.3 -> 5360.86 | ... DR72: =993.52*DR63 - 2587.3 -> 96764.7
V73: Other
V75: Growth rates
V76: Server & Cloud | AG76: =AG64/AF64-1 -> 0.10370365 | AH76: =AH64/AG64-1 -> 0.093959685 | AI76: =AI64/AH64-1 -> 0.085889531 | AJ76: =AJ64/AI64-1 -> 0.079096012 | AK76: =AK64/AJ64-1 -> 0.073298401 | AL76: =AL64/AK64-1 -> 0.068292658 | AM76: =AM64/AL64-1 -> 0.063926919 | AN76: =AN64/AM64-1 -> 0.060085818 | ... DR76: =DR64/DQ64-1 -> 0.010137581
V77: Office | AG77: =AG65/AF65-1 -> 0.073070949 | AH77: =AH65/AG65-1 -> 0.06809517 | AI77: =AI65/AH65-1 -> 0.063753841 | AJ77: =AJ65/AI65-1 -> 0.059932889 | AK77: =AK65/AJ65-1 -> 0.056544042 | AL77: =AL65/AK65-1 -> 0.053517922 | AM77: =AM65/AL65-1 -> 0.050799252 | AN77: =AN65/AM65-1 -> 0.048343441 | ... DR77: =DR65/DQ65-1 -> 0.0097384895
V78: Windows | AG78: =AG66/AF66-1 -> 0.033884039 | AH78: =AH66/AG66-1 -> 0.032773539 | AI78: =AI66/AH66-1 -> 0.031733519 | AJ78: =AJ66/AI66-1 -> 0.030757476 | AK78: =AK66/AJ66-1 -> 0.029839683 | AL78: =AL66/AK66-1 -> 0.028975076 | AM78: =AM66/AL66-1 -> 0.028159162 | AN78: =AN66/AM66-1 -> 0.027387941 | ... DR78: =DR66/DQ66-1 -> 0.0084379342
V79: Gaming | AG79: =AG67/AF67-1 -> 0.073335293 | AH79: =AH67/AG67-1 -> 0.068324682 | AI79: =AI67/AH67-1 -> 0.063954979 | AJ79: =AJ67/AI67-1 -> 0.060110606 | AK79: =AK67/AJ67-1 -> 0.056702203 | AL79: =AL67/AK67-1 -> 0.053659586 | AM79: =AM67/AL67-1 -> 0.050926871 | AN79: =AN67/AM67-1 -> 0.048459005 | ... DR79: =DR67/DQ67-1 -> 0.0097431701
V80: Search & Ads | AG80: =AG68/AF68-1 -> 0.06948675 | AH80: =AH68/AG68-1 -> 0.064972053 | AI80: =AI68/AH68-1 -> 0.061008223 | AJ80: =AJ68/AI68-1 -> 0.057500236 | AK80: =AK68/AJ68-1 -> 0.054373734 | AL80: =AL68/AK68-1 -> 0.051569697 | AM80: =AM68/AL68-1 -> 0.049040684 | AN80: =AN68/AM68-1 -> 0.046748124 | ... DR80: =DR68/DQ68-1 -> 0.009672
V81: Enterprise Services | AG81: =AG69/AF69-1 -> 0.037124138 | AH81: =AH69/AG69-1 -> 0.035795269 | AI81: =AI69/AH69-1 -> 0.034558248 | AJ81: =AJ69/AI69-1 -> 0.033403868 | AK81: =AK69/AJ69-1 -> 0.032324118 | AL81: =AL69/AK69-1 -> 0.031311986 | AM81: =AM69/AL69-1 -> 0.030361313 | AN81: =AN69/AM69-1 -> 0.029466666 | ... DR81: =DR69/DQ69-1 -> 0.0086254
V82: Devices | AG82: =AG70/AF70-1 -> 0.013885089 | AH82: =AH70/AG70-1 -> 0.013694934 | AI82: =AI70/AH70-1 -> 0.013509916 | AJ82: =AJ70/AI70-1 -> 0.013329831 | AK82: =AK70/AJ70-1 -> 0.013154484 | AL82: =AL70/AK70-1 -> 0.01298369 | AM82: =AM70/AL70-1 -> 0.012817275 | AN82: =AN70/AM70-1 -> 0.012655071 | ... DR82: =DR70/DQ70-1 -> 0.00621042
AG83: 0 | AH83: 0 | AI83: 0 | AJ83: 0 | AK83: 0 | AL83: 0 | AM83: 0 | AN83: 0 | AO83: 0 | AP83: 0 | AQ83: 0 | AR83: 0 | AS83: 0 | AT83: 0 | AU83: 0 | AV83: 0 | AW83: 0 | AX83: 0 | AY83: 0 | AZ83: 0 | BA83: 0 | BB83: 0 | BC83: 0 | BD83: 0 | BE83: 0 | BF83: 0 | BG83: 0 | BH83: 0 | BI83: 0 | BJ83: 0 | BK83: 0 | BL83: 0 | BM83: 0 | BN83: 0 | BO83: 0 | BP83: 0 | BQ83: 0 | BR83: 0 | BS83: 0 | BT83: 0 | BU83: 0 | BV83: 0 | BW83: 0 | BX83: 0 | BY83: 0 | BZ83: 0 | CA83: 0 | CB83: 0 | CC83: 0 | CD83: 0 | CE83: 0 | CF83: 0 | CG83: 0 | CH83: 0 | CI83: 0 | CJ83: 0 | CK83: 0 | CL83: 0 | CM83: 0 | CN83: 0 | CO83: 0 | CP83: 0 | CQ83: 0 | CR83: 0 | CS83: 0 | CT83: 0 | CU83: 0 | CV83: 0 | CW83: 0 | CX83: 0 | CY83: 0 | CZ83: 0 | DA83: 0 | DB83: 0 | DC83: 0 | DD83: 0 | DE83: 0 | DF83: 0 | DG83: 0 | DH83: 0 | DI83: 0 | DJ83: 0 | DK83: 0 | DL83: 0 | DM83: 0 | DN83: 0 | DO83: 0 | DP83: 0 | DQ83: 0 | DR83: 0
V84: LinkedIn | AG84: =AG71/AF71-1 -> 0.10792855 | AH84: =AH71/AG71-1 -> 0.097414724 | AI84: =AI71/AH71-1 -> 0.088767466 | AJ84: =AJ71/AI71-1 -> 0.081530233 | AK84: =AK71/AJ71-1 -> 0.075384146 | AL84: =AL71/AK71-1 -> 0.070099738 | AM84: =AM71/AL71-1 -> 0.065507667 | AN84: =AN71/AM71-1 -> 0.06148024 | ... DR84: =DR71/DQ71-1 -> 0.010176523
V85: Dynamics | AG85: =AG72/AF72-1 -> 0.13521142 | AH85: =AH72/AG72-1 -> 0.11910682 | AI85: =AI72/AH72-1 -> 0.10643025 | AJ85: =AJ72/AI72-1 -> 0.096192462 | AK85: =AK72/AJ72-1 -> 0.087751436 | AL85: =AL72/AK72-1 -> 0.080672323 | AM85: =AM72/AL72-1 -> 0.074650125 | AN85: =AN72/AM72-1 -> 0.069464585 | ... DR85: =DR72/DQ72-1 -> 0.010373893
AG86: 0 | AH86: 0 | AI86: 0 | AJ86: 0 | AK86: 0 | AL86: 0 | AM86: 0 | AN86: 0 | AO86: 0 | AP86: 0 | AQ86: 0 | AR86: 0 | AS86: 0 | AT86: 0 | AU86: 0 | AV86: 0 | AW86: 0 | AX86: 0 | AY86: 0 | AZ86: 0 | BA86: 0 | BB86: 0 | BC86: 0 | BD86: 0 | BE86: 0 | BF86: 0 | BG86: 0 | BH86: 0 | BI86: 0 | BJ86: 0 | BK86: 0 | BL86: 0 | BM86: 0 | BN86: 0 | BO86: 0 | BP86: 0 | BQ86: 0 | BR86: 0 | BS86: 0 | BT86: 0 | BU86: 0 | BV86: 0 | BW86: 0 | BX86: 0 | BY86: 0 | BZ86: 0 | CA86: 0 | CB86: 0 | CC86: 0 | CD86: 0 | CE86: 0 | CF86: 0 | CG86: 0 | CH86: 0 | CI86: 0 | CJ86: 0 | CK86: 0 | CL86: 0 | CM86: 0 | CN86: 0 | CO86: 0 | CP86: 0 | CQ86: 0 | CR86: 0 | CS86: 0 | CT86: 0 | CU86: 0 | CV86: 0 | CW86: 0 | CX86: 0 | CY86: 0 | CZ86: 0 | DA86: 0 | DB86: 0 | DC86: 0 | DD86: 0 | DE86: 0 | DF86: 0 | DG86: 0 | DH86: 0 | DI86: 0 | DJ86: 0 | DK86: 0 | DL86: 0 | DM86: 0 | DN86: 0 | DO86: 0 | DP86: 0 | DQ86: 0 | DR86: 0

Sheet Forecast
A1: Timeline | B1: Total Revenue | C1: Forecast(Total Revenue) | D1: Lower Confidence Bound(Total Revenue) | E1: Upper Confidence Bound(Total Revenue) | F1: Shade base | G1: Column1 | H1: shade gap
A2: 42735 | B2: 91154
A3: 43100 | B3: 96571 | I3: 386708.12 | J3: 412754.55 | K3: 438800.99 | L3: 464847.42 | M3: 490893.86 | N3: 516940.29 | O3: 542986.73 | P3: 569033.16 | Q3: 595079.6 | R3: 621126.03 | S3: 647172.47 | T3: 673218.9 | U3: 699265.34 | V3: 725311.77 | W3: 751358.21 | X3: 777404.64 | Y3: 803451.08 | Z3: 829497.51 | AA3: 855543.94 | AB3: 881590.38 | AC3: 907636.81 | AD3: 933683.25 | AE3: 959729.68
A4: 43465 | B4: 110360 | I4: 407158.26 | J4: 454562.15 | K4: 505996.05 | L4: 561400.47 | M4: 620586.12 | N4: 683218.09 | O4: 748804.5 | P4: 816691.05 | Q4: 886062.83 | R4: 926205.34 | S4: 966347.84 | T4: 1006490.3 | U4: 1046632.9 | V4: 1086775.4 | W4: 1126917.9 | X4: 1167060.4 | Y4: 1207202.9 | Z4: 1247345.4 | AA4: 1287487.9 | AB4: 1327630.4 | AC4: 1367772.9 | AD4: 1407915.4 | AE4: 1448057.9
A5: 43830 | B5: 125843 | I5: 363386.9 | J5: 387727.29 | K5: 411399.15 | L5: 434119.27 | M5: 455610.31 | N5: 474441.81 | O5: 491555.66 | P5: 511709.77 | Q5: 531667.98 | R5: 551432.98 | S5: 571007.47 | T5: 590394.13 | U5: 609595.63 | V5: 628614.63 | W5: 647453.78 | X5: 666115.7 | Y5: 684602.99 | Z5: 702918.24 | AA5: 721064 | AB5: 739042.81 | AC5: 756857.19 | AD5: 774509.61 | AE5: 792002.54
A6: 44196 | B6: 143015
A7: 44561 | B7: 172567
A8: 44926 | B8: 203561
A9: 45291 | B9: 212241
A10: 45657 | B10: 245202
A11: 46022 | B11: 281724
A12: 46387 | B12: 321869.75 | C12: 321869.75 | D12: 306730.09 | E12: 321446.93 | F12: =MIN(Table1[[#This Row],[Lower Confidence Bound(Total Revenue)]:[Upper Confidence Bound(Total Revenue)]])-Table1[[#This Row],[Column1]] -> 291590.43 | G12: 15139.663 | H12: =MAX(Table1[[#This Row],[Upper Confidence Bound(Total Revenue)]],Table1[[#This Row],[Lower Confidence Bound(Total Revenue)]])-Table1[[#This Row],[Shade base]]-Table1[[#This Row],[Column1]] -> 14716.841
A13: 46752 | C13: 360661.68 | D13: 335779.11 | E13: 363732.74 | F13: =MIN(Table1[[#This Row],[Lower Confidence Bound(Total Revenue)]:[Upper Confidence Bound(Total Revenue)]]) -> 335779.11 | G13: 24882.57 | H13: =MAX(Table1[[#This Row],[Upper Confidence Bound(Total Revenue)]],Table1[[#This Row],[Lower Confidence Bound(Total Revenue)]])-Table1[[#This Row],[Shade base]]-Table1[[#This Row],[Column1]] -> 3071.0542
A14: 47118 | C14: 386708.12 | D14: 363386.9 | E14: 407158.26 | F14: =MIN(Table1[[#This Row],[Lower Confidence Bound(Total Revenue)]:[Upper Confidence Bound(Total Revenue)]]) -> 363386.9 | G14: 23321.222 | H14: =MAX(Table1[[#This Row],[Upper Confidence Bound(Total Revenue)]],Table1[[#This Row],[Lower Confidence Bound(Total Revenue)]])-Table1[[#This Row],[Shade base]]-Table1[[#This Row],[Column1]] -> 20450.14
A15: 47483 | C15: 412754.55 | D15: 387727.29 | E15: 454562.15 | F15: =MIN(Table1[[#This Row],[Lower Confidence Bound(Total Revenue)]:[Upper Confidence Bound(Total Revenue)]]) -> 387727.29 | G15: 25027.262 | H15: =MAX(Table1[[#This Row],[Upper Confidence Bound(Total Revenue)]],Table1[[#This Row],[Lower Confidence Bound(Total Revenue)]])-Table1[[#This Row],[Shade base]]-Table1[[#This Row],[Column1]] -> 41807.602
A16: 47848 | C16: 438800.99 | D16: 411399.15 | E16: 505996.05 | F16: =MIN(Table1[[#This Row],[Lower Confidence Bound(Total Revenue)]:[Upper Confidence Bound(Total Revenue)]]) -> 411399.15 | G16: 27401.835 | H16: =MAX(Table1[[#This Row],[Upper Confidence Bound(Total Revenue)]],Table1[[#This Row],[Lower Confidence Bound(Total Revenue)]])-Table1[[#This Row],[Shade base]]-Table1[[#This Row],[Column1]] -> 67195.06
A17: 48213 | C17: 464847.42 | D17: 434119.27 | E17: 561400.47 | F17: =MIN(Table1[[#This Row],[Lower Confidence Bound(Total Revenue)]:[Upper Confidence Bound(Total Revenue)]]) -> 434119.27 | G17: 30728.156 | H17: =MAX(Table1[[#This Row],[Upper Confidence Bound(Total Revenue)]],Table1[[#This Row],[Lower Confidence Bound(Total Revenue)]])-Table1[[#This Row],[Shade base]]-Table1[[#This Row],[Column1]] -> 96553.043
A18: 48579 | C18: 490893.86 | D18: 455610.31 | E18: 620586.12 | F18: =MIN(Table1[[#This Row],[Lower Confidence Bound(Total Revenue)]:[Upper Confidence Bound(Total Revenue)]]) -> 455610.31 | G18: 35283.545 | H18: =MAX(Table1[[#This Row],[Upper Confidence Bound(Total Revenue)]],Table1[[#This Row],[Lower Confidence Bound(Total Revenue)]])-Table1[[#This Row],[Shade base]]-Table1[[#This Row],[Column1]] -> 129692.26
A19: 48944 | C19: 516940.29 | D19: 474441.81 | E19: 683218.09 | F19: =MIN(Table1[[#This Row],[Lower Confidence Bound(Total Revenue)]:[Upper Confidence Bound(Total Revenue)]]) -> 474441.81 | G19: 42498.482 | H19: =MAX(Table1[[#This Row],[Upper Confidence Bound(Total Revenue)]],Table1[[#This Row],[Lower Confidence Bound(Total Revenue)]])-Table1[[#This Row],[Shade base]]-Table1[[#This Row],[Column1]] -> 166277.8
A20: 49309 | C20: 542986.73 | D20: 491555.66 | E20: 748804.5 | F20: =MIN(Table1[[#This Row],[Lower Confidence Bound(Total Revenue)]:[Upper Confidence Bound(Total Revenue)]]) -> 491555.66 | G20: 51431.067 | H20: =MAX(Table1[[#This Row],[Upper Confidence Bound(Total Revenue)]],Table1[[#This Row],[Lower Confidence Bound(Total Revenue)]])-Table1[[#This Row],[Shade base]]-Table1[[#This Row],[Column1]] -> 205817.77
A21: 49674 | C21: 569033.16 | D21: 511709.77 | E21: 816691.05 | F21: =MIN(Table1[[#This Row],[Lower Confidence Bound(Total Revenue)]:[Upper Confidence Bound(Total Revenue)]]) -> 511709.77 | G21: 57323.391 | H21: =MAX(Table1[[#This Row],[Upper Confidence Bound(Total Revenue)]],Table1[[#This Row],[Lower Confidence Bound(Total Revenue)]])-Table1[[#This Row],[Shade base]]-Table1[[#This Row],[Column1]] -> 247657.89
A22: 50040 | C22: 595079.6 | D22: 531667.98 | E22: 886062.83 | F22: =MIN(Table1[[#This Row],[Lower Confidence Bound(Total Revenue)]:[Upper Confidence Bound(Total Revenue)]]) -> 531667.98 | G22: 63411.617 | H22: =MAX(Table1[[#This Row],[Upper Confidence Bound(Total Revenue)]],Table1[[#This Row],[Lower Confidence Bound(Total Revenue)]])-Table1[[#This Row],[Shade base]]-Table1[[#This Row],[Column1]] -> 290983.24
A23: 50405 | C23: 621126.03 | D23: 551432.98 | E23: 926205.34 | F23: =MIN(Table1[[#This Row],[Lower Confidence Bound(Total Revenue)]:[Upper Confidence Bound(Total Revenue)]]) -> 551432.98 | G23: 69693.051 | H23: =MAX(Table1[[#This Row],[Upper Confidence Bound(Total Revenue)]],Table1[[#This Row],[Lower Confidence Bound(Total Revenue)]])-Table1[[#This Row],[Shade base]]-Table1[[#This Row],[Column1]] -> 305079.31
A24: 50770 | C24: 647172.47 | D24: 571007.47 | E24: 966347.84 | F24: =MIN(Table1[[#This Row],[Lower Confidence Bound(Total Revenue)]:[Upper Confidence Bound(Total Revenue)]]) -> 571007.47 | G24: 76164.998 | H24: =MAX(Table1[[#This Row],[Upper Confidence Bound(Total Revenue)]],Table1[[#This Row],[Lower Confidence Bound(Total Revenue)]])-Table1[[#This Row],[Shade base]]-Table1[[#This Row],[Column1]] -> 319175.38
... A36: 55153 | C36: 959729.68 | D36: 792002.54 | E36: 1448057.9 | F36: =MIN(Table1[[#This Row],[Lower Confidence Bound(Total Revenue)]:[Upper Confidence Bound(Total Revenue)]]) -> 792002.54 | G36: 167727.14 | H36: =MAX(Table1[[#This Row],[Upper Confidence Bound(Total Revenue)]],Table1[[#This Row],[Lower Confidence Bound(Total Revenue)]])-Table1[[#This Row],[Shade base]]-Table1[[#This Row],[Column1]] -> 488328.22

Sheet DCF
B2: FY | C2: 42735 | D2: 43100 | E2: 43465 | F2: 43830 | G2: 44196 | H2: 44561 | I2: 44926 | J2: 45291 | K2: 45657 | L2: 46022 | M2: 46387 | N2: 46752 | O2: 47118 | P2: 47483 | Q2: 47848 | R2: 48213 | S2: 48579 | T2: 48944 | U2: 49309 | V2: 49674 | W2: 50040 | X2: 50405 | Y2: 50770 | Z2: 51135 | AA2: 51501 | AB2: 51866 | AC2: 52231 | AD2: 52596 | AE2: 52962 | AF2: 53327 | AG2: 53692 | AH2: 54057 | AI2: 54423 | AJ2: 54788 | AK2: 55153 | AL2: 55518 | AM2: 55884 | AN2: 56249 | AO2: 56614 | AP2: 56979 | AQ2: 57345 | AR2: 57710 | AS2: 58075 | AT2: 58440 | AU2: 58806 | AV2: 59171 | AW2: 59536 | AX2: 59901 | AY2: 60267 | AZ2: 60632 | BA2: 60997 | BB2: 61362 | BC2: 61728 | BD2: 62093 | BE2: 62458 | BF2: 62823 | BG2: 63189 | BH2: 63554 | BI2: 63919 | BJ2: 64284 | BK2: 64650 | BL2: 65015 | BM2: 65380 | BN2: 65745 | BO2: 66111 | BP2: 66476 | BQ2: 66841 | BR2: 67206 | BS2: 67572 | BT2: 67937 | BU2: 68302 | BV2: 68667 | BW2: 69033 | BX2: 69398 | BY2: 69763 | BZ2: 70128 | CA2: 70494 | CB2: 70859 | CC2: 71224 | CD2: 71589 | CE2: 71955 | CF2: 72320 | CG2: 72685 | CH2: 73050 | CI2: 73415
B3: BASE CASE (Linear growth)
A4: Server & Cloud | B4: Server Products and Cloud Services Revenue (Pre-FY2025) | C4: 19062 | D4: 21649 | E4: 26129 | F4: 32622 | G4: 41379 | H4: 52589 | I4: 67350 | J4: 79970 | K4: 97726 | L4: 114163.69 | M4: =L4*(1+Segments!AG76+0.1) -> 137419.25 | N4: =M4*(1+Segments!AH76+0.08) -> 161324.66 | O4: =N4*(1+Segments!AI76) -> 175180.75 | P4: =O4*(1+Segments!AJ76) -> 189036.85 | Q4: =P4*(1+Segments!AK76) -> 202892.95 | R4: =Q4*(1+Segments!AL76) -> 216749.05 | S4: =R4*(1+Segments!AM76) -> 230605.15 | T4: =S4*(1+Segments!AN76) -> 244461.25 | U4: =T4*(1+Segments!AO76) -> 258317.35 | V4: =U4*(1+Segments!AP76) -> 272173.45 | ... CI4: =CH4*(1+Segments!DC76) -> 1172819.9
A5: Office | B5: Office Products and Cloud Services | C5: 23868 | D5: 25573 | E5: 28316 | F5: 31769 | G5: 35316 | H5: 39872 | I5: 44970 | J5: 48848 | K5: 54875 | L5: 64105.073 | M5: =L5*(1+Segments!AG77+0.05) -> 71994.545 | N5: =M5*(1+Segments!AH77+0.04) -> 79776.807 | O5: =N5*(1+Segments!AI77) -> 84862.885 | P5: =O5*(1+Segments!AJ77) -> 89948.963 | Q5: =P5*(1+Segments!AK77) -> 95035.041 | R5: =Q5*(1+Segments!AL77) -> 100121.12 | S5: =R5*(1+Segments!AM77) -> 105207.2 | T5: =S5*(1+Segments!AN77) -> 110293.28 | U5: =T5*(1+Segments!AO77) -> 115379.35 | V5: =U5*(1+Segments!AP77) -> 120465.43 | ... CI5: =CH5*(1+Segments!DC77) -> 451060.5
A6: Windows | B6: Windows | C6: 17548 | D6: 18593 | E6: 19518 | F6: 20395 | G6: 21510 | H6: 22488 | I6: 24732 | J6: 21507 | K6: 23244 | L6: 27153.682 | M6: =L6*(1+Segments!AG78) -> 28073.759 | N6: =M6*(1+Segments!AH78) -> 28993.835 | O6: =N6*(1+Segments!AI78) -> 29913.912 | P6: =O6*(1+Segments!AJ78) -> 30833.988 | Q6: =P6*(1+Segments!AK78) -> 31754.064 | R6: =Q6*(1+Segments!AL78) -> 32674.141 | S6: =R6*(1+Segments!AM78) -> 33594.217 | T6: =S6*(1+Segments!AN78) -> 34514.294 | ... CI6: =CH6*(1+Segments!DC78) -> 96159.414
A7: Gaming | B7: Gaming | C7: 9202 | D7: 9051 | E7: 10353 | F7: 11386 | G7: 11575 | H7: 15370 | I7: 16230 | J7: 15466 | K7: 21503 | L7: 23455 | M7: =L7*(1+Segments!AG79+0.05) -> 26347.829 | N7: =M7*(1+Segments!AH79) -> 28148.036 | O7: =N7*(1+Segments!AI79) -> 29948.243 | P7: =O7*(1+Segments!AJ79) -> 31748.451 | Q7: =P7*(1+Segments!AK79) -> 33548.658 | R7: =Q7*(1+Segments!AL79) -> 35348.865 | S7: =R7*(1+Segments!AM79) -> 37149.072 | T7: =S7*(1+Segments!AN79) -> 38949.279 | U7: =T7*(1+Segments!AO79) -> 40749.486 | ... CI7: =CH7*(1+Segments!DC79) -> 159563.15
A8: Search & Ads | B8: Search and News Advertising | C8: 5428 | D8: 6219 | E8: 7012 | F8: 7628 | G8: 8524 | H8: 9267 | I8: 11526 | J8: 12125 | K8: 12306 | L8: 13878 | M8: =L8*(1+Segments!AG80) -> 14842.337 | N8: =M8*(1+Segments!AH80) -> 15806.674 | O8: =N8*(1+Segments!AI80) -> 16771.011 | P8: =O8*(1+Segments!AJ80) -> 17735.348 | Q8: =P8*(1+Segments!AK80) -> 18699.686 | R8: =Q8*(1+Segments!AL80) -> 19664.023 | S8: =R8*(1+Segments!AM80) -> 20628.36 | T8: =S8*(1+Segments!AN80) -> 21592.697 | ... CI8: =CH8*(1+Segments!DC80) -> 86203.283
A9: Enterprise Services | B9: Enterprise and Partner Services | C9: 5659 | D9: 5542 | E9: 5846 | F9: 6124 | G9: 6409 | H9: 6943 | I9: 7605 | J9: 7900 | K9: 7594 | L9: 7885 | M9: =L9*(1+Segments!AG81) -> 8177.7238 | N9: =M9*(1+Segments!AH81) -> 8470.4477 | O9: =N9*(1+Segments!AI81) -> 8763.1715 | P9: =O9*(1+Segments!AJ81) -> 9055.8953 | Q9: =P9*(1+Segments!AK81) -> 9348.6191 | R9: =Q9*(1+Segments!AL81) -> 9641.343 | S9: =R9*(1+Segments!AM81) -> 9934.0668 | T9: =S9*(1+Segments!AN81) -> 10226.791 | ... CI9: =CH9*(1+Segments!DC81) -> 29839.287
A10: Devices | B10: Devices | C10: 7888 | D10: 5062 | E10: 5134 | F10: 6095 | G10: 6457 | H10: 7143 | I10: 7306 | J10: 5521 | K10: 4706 | L10: 5497.5576 | M10: =L10*(1+Segments!AG82) -> 5573.8917 | N10: =M10*(1+Segments!AH82) -> 5650.2257 | O10: =N10*(1+Segments!AI82) -> 5726.5598 | P10: =O10*(1+Segments!AJ82) -> 5802.8939 | Q10: =P10*(1+Segments!AK82) -> 5879.228 | R10: =Q10*(1+Segments!AL82) -> 5955.562 | S10: =R10*(1+Segments!AM82) -> 6031.8961 | T10: =S10*(1+Segments!AN82) -> 6108.2302 | ... CI10: =CH10*(1+Segments!DC82) -> 11222.613
B11: Other Product Revenue (Pre-FY2023) | C11: 2499 | D11: 2611 | E11: 2793 | F11: 3070 | G11: 3768 | H11: 4479 | I11: 5291 | J11: 0 | K11: 0 | L11: 0 | M11: =L11*(1+Segments!AG83) -> 0 | N11: =M11*(1+Segments!AH83) -> 0 | O11: =N11*(1+Segments!AI83) -> 0 | P11: =O11*(1+Segments!AJ83) -> 0 | Q11: =P11*(1+Segments!AK83) -> 0 | R11: =Q11*(1+Segments!AL83) -> 0 | S11: =R11*(1+Segments!AM83) -> 0 | T11: =S11*(1+Segments!AN83) -> 0 | ... CI11: =CH11*(1+Segments!DC83) -> 0
A12: LinkedIn | B12: LinkedIn | C12: 0 | D12: 2271 | E12: 5259 | F12: 6754 | G12: 8077 | H12: 10289 | I12: 13631 | J12: 14989 | K12: 16372 | L12: 17812 | M12: =L12*(1+Segments!AG84+0.05) -> 20625.023 | N12: =M12*(1+Segments!AH84) -> 22634.204 | O12: =N12*(1+Segments!AI84) -> 24643.385 | P12: =O12*(1+Segments!AJ84) -> 26652.566 | Q12: =P12*(1+Segments!AK84) -> 28661.747 | R12: =Q12*(1+Segments!AL84) -> 30670.928 | S12: =R12*(1+Segments!AM84) -> 32680.109 | T12: =S12*(1+Segments!AN84) -> 34689.29 | U12: =T12*(1+Segments!AO84) -> 36698.471 | ... CI12: =CH12*(1+Segments!DC84) -> 169304.41
A13: Dynamics | B13: Dynamics Products and Cloud Services | C13: 0 | D13: 0 | E13: 0 | F13: 0 | G13: 0 | H13: 3754 | I13: 4687 | J13: 5796 | K13: 6831 | L13: 7702 | M13: =L13*(1+Segments!AG85) -> 8743.3984 | N13: =M13*(1+Segments!AH85) -> 9784.7967 | O13: =N13*(1+Segments!AI85) -> 10826.195 | P13: =O13*(1+Segments!AJ85) -> 11867.593 | Q13: =P13*(1+Segments!AK85) -> 12908.992 | R13: =Q13*(1+Segments!AL85) -> 13950.39 | S13: =R13*(1+Segments!AM85) -> 14991.789 | T13: =S13*(1+Segments!AN85) -> 16033.187 | ... CI13: =CH13*(1+Segments!DC85) -> 85806.877
B14: Other Product Revenue (Post-FY2022) | C14: 0 | D14: 0 | E14: 0 | F14: 0 | G14: 0 | H14: 373 | I14: 233 | J14: 119 | K14: 45 | L14: 72 | M14: =L14*(1+Segments!AG86) -> 72 | N14: =M14*(1+Segments!AH86) -> 72 | O14: =N14*(1+Segments!AI86) -> 72 | P14: =O14*(1+Segments!AJ86) -> 72 | Q14: =P14*(1+Segments!AK86) -> 72 | R14: =Q14*(1+Segments!AL86) -> 72 | S14: =R14*(1+Segments!AM86) -> 72 | T14: =S14*(1+Segments!AN86) -> 72 | ... CI14: =CH14*(1+Segments!DC86) -> 72
B15: Total Revenue | C15: =SUM(C4:C14) -> 91154 | D15: =SUM(D4:D14) -> 96571 | E15: =SUM(E4:E14) -> 110360 | F15: =SUM(F4:F14) -> 125843 | G15: =SUM(G4:G14) -> 143015 | H15: =SUM(H4:H14) -> 172567 | I15: =SUM(I4:I14) -> 203561 | J15: =SUM(J4:J14) -> 212241 | ... CI15: =SUM(CI4:CI14) -> 2262051.4
B16: % Growth | D16: =D15/C15-1 -> 0.059426904 | E16: =E15/D15-1 -> 0.14278614 | F16: =F15/E15-1 -> 0.1402954 | G16: =G15/F15-1 -> 0.13645574 | H16: =H15/G15-1 -> 0.20663567 | I16: =I15/H15-1 -> 0.1796056 | J16: =J15/I15-1 -> 0.042640781 | K16: =K15/J15-1 -> 0.15529987 | ... CI16: =CI15/CH15-1 -> 0.011648648
B17: COGS | C17: 32780 | D17: 34261 | E17: 38353 | F17: 42910 | G17: 46078 | H17: 52232 | I17: 62650 | J17: 65863 | K17: 74114 | L17: 87831 | M17: =M15*(L18-0.001) -> 100025.07 | N17: =N15*(M18-0.001) -> 111719.49 | O17: =O15*(N18-0.001) -> 119400.99 | P17: =P15*(O18-0.001) -> 127030.4 | Q17: =Q15*(P18-0.001) -> 134607.72 | R17: =R15*(Q18-0.001) -> 142132.95 | S17: =S15*(R18-0.001) -> 149606.08 | T17: =T15*(S18-0.001) -> 157027.11 | ... CI17: =CI15*(CH18-0.001) -> 535569.12
B18: % of Revenue | C18: =C17/C$15 -> 0.35961121 | D18: =D17/D$15 -> 0.35477524 | E18: =E17/E$15 -> 0.34752628 | F18: =F17/F$15 -> 0.34098043 | G18: =G17/G$15 -> 0.32218998 | H18: =H17/H$15 -> 0.30267664 | I18: =I17/I$15 -> 0.30777015 | J18: =J17/J$15 -> 0.31032176 | ... CI18: =CI17/CI$15 -> 0.23676258
B19: Operating expenses | C19: 32296 | D19: 33285 | E19: 36949 | F19: 39974 | G19: 43978 | H19: 45940 | I19: 52237 | J19: 57529 | K19: 61575 | L19: 65365 | M19: =M15*L20 -> 74679.532 | N19: =N15*M20 -> 83679.952 | O19: =O15*N20 -> 89723.191 | P19: =P15*O20 -> 95766.429 | Q19: =Q15*P20 -> 101809.67 | R19: =R15*Q20 -> 107852.9 | S19: =S15*R20 -> 113896.14 | T19: =T15*S20 -> 119939.38 | ... CI19: =CI15*CH20 -> 524836.33
B20: % of Revenue | C20: =C19/C$15 -> 0.35430151 | D20: =D19/D$15 -> 0.34466869 | E20: =E19/E$15 -> 0.33480428 | F20: =F19/F$15 -> 0.31764977 | G20: =G19/G$15 -> 0.30750621 | H20: =H19/H$15 -> 0.26621544 | I20: =I19/I$15 -> 0.25661595 | J20: =J19/J$15 -> 0.27105507 | ... CI20: =CI19/CI$15 -> 0.23201786
B21: Net interest & other expenses | C21: -439 | D21: 876 | E21: 1416 | F21: 729 | G21: 77 | H21: 1186 | I21: 333 | J21: 788 | K21: -1646 | L21: -4901 | M21: =M15*$L$22 -> -5599.394 | N21: =N15*$L$22 -> -6274.2362 | O21: =O15*$L$22 -> -6727.3519 | P21: =P15*$L$22 -> -7180.4676 | Q21: =Q15*$L$22 -> -7633.5834 | R21: =R15*$L$22 -> -8086.6991 | S21: =S15*$L$22 -> -8539.8148 | T21: =T15*$L$22 -> -8992.9306 | ... CI21: =CI15*$L$22 -> -39351.685
B22: % of Revenue | C22: =C21/C$15 -> -0.0048160256 | D22: =D21/D$15 -> 0.0090710462 | E22: =E21/E$15 -> 0.012830736 | F22: =F21/F$15 -> 0.0057929325 | G22: =G21/G$15 -> 0.00053840506 | H22: =H21/H$15 -> 0.0068726929 | I22: =I21/I$15 -> 0.0016358733 | J22: =J21/J$15 -> 0.0037127605 | ... CI22: =CI21/CI$15 -> -0.017396459
B23: Taxes | C23: 5100 | D23: 4412 | E23: 19903 | F23: 4448 | G23: 8755 | H23: 9831 | I23: 10978 | J23: 16950 | K23: 19651 | L23: 21795 | M23: =+(M15-M17-M19+M21)*M24 -> 24957.538 | N23: =+(N15-N17-N19+N21)*N24 -> 28029.019 | O23: =+(O15-O17-O19+O21)*O24 -> 30121.407 | P23: =+(P15-P17-P19+P21)*P24 -> 32222.979 | Q23: =+(Q15-Q17-Q19+Q21)*Q24 -> 34333.735 | R23: =+(R15-R17-R19+R21)*R24 -> 36453.674 | S23: =+(S15-S17-S19+S21)*S24 -> 38582.797 | T23: =+(T15-T17-T19+T21)*T24 -> 40721.104 | ... CI23: =+(CI15-CI17-CI19+CI21)*CI24 -> 204908.34
B24: Tax rate | C24: =C23/(C15-C17-C19+C21) -> 0.19891571 | D24: =D23/(D15-D17-D19+D21) -> 0.14755359 | E24: =E23/(E15-E17-E19+E21) -> 0.54567637 | F24: =F23/(F15-F17-F19+F21) -> 0.10181285 | G24: =G23/(G15-G17-G19+G21) -> 0.16507655 | H24: =H23/(H15-H17-H19+H21) -> 0.13007237 | I24: =I23/(I15-I17-I19+I21) -> 0.12333861 | J24: =J23/(J15-J17-J19+J21) -> 0.18909602 | ... L24: =L23/(L15-L17-L19+L21) -> 0.17629644 | M24: 0.17629644 | N24: 0.17629644 | O24: 0.17629644 | P24: 0.17629644 | Q24: 0.17629644 | R24: 0.17629644 | S24: 0.17629644 | T24: 0.17629644 | U24: 0.17629644 | V24: 0.17629644 | W24: 0.17629644 | X24: 0.17629644 | Y24: 0.17629644 | Z24: 0.17629644 | AA24: 0.17629644 | AB24: 0.17629644 | AC24: 0.17629644 | AD24: 0.17629644 | AE24: 0.17629644 | AF24: 0.17629644 | AG24: 0.17629644 | AH24: 0.17629644 | AI24: 0.17629644 | AJ24: 0.17629644 | AK24: 0.17629644 | AL24: 0.17629644 | AM24: 0.17629644 | AN24: 0.17629644 | AO24: 0.17629644 | AP24: 0.17629644 | AQ24: 0.17629644 | AR24: 0.17629644 | AS24: 0.17629644 | AT24: 0.17629644 | AU24: 0.17629644 | AV24: 0.17629644 | AW24: 0.17629644 | AX24: 0.17629644 | AY24: 0.17629644 | AZ24: 0.17629644 | BA24: 0.17629644 | BB24: 0.17629644 | BC24: 0.17629644 | BD24: 0.17629644 | BE24: 0.17629644 | BF24: 0.17629644 | BG24: 0.17629644 | BH24: 0.17629644 | BI24: 0.17629644 | BJ24: 0.17629644 | BK24: 0.17629644 | BL24: 0.17629644 | BM24: 0.17629644 | BN24: 0.17629644 | BO24: 0.17629644 | BP24: 0.17629644 | BQ24: 0.17629644 | BR24: 0.17629644 | BS24: 0.17629644 | BT24: 0.17629644 | BU24: 0.17629644 | BV24: 0.17629644 | BW24: 0.17629644 | BX24: 0.17629644 | BY24: 0.17629644 | BZ24: 0.17629644 | CA24: 0.17629644 | CB24: 0.17629644 | CC24: 0.17629644 | CD24: 0.17629644 | CE24: 0.17629644 | CF24: 0.17629644 | CG24: 0.17629644 | CH24: 0.17629644 | CI24: 0.17629644
B25: Net Income | C25: 20539 | D25: 25489 | E25: 16571 | F25: 39240 | G25: 44281 | H25: 61271 | I25: 72738 | J25: 72361 | K25: 88136 | L25: 101832 | M25: =+(M15-M17-M19+M21-M23) -> 116608.22 | N25: =+(N15-N17-N19+N21-N23) -> 130958.98 | O25: =+(O15-O17-O19+O21-O23) -> 140735.17 | P25: =+(P15-P17-P19+P21-P23) -> 150554.27 | Q25: =+(Q15-Q17-Q19+Q21-Q23) -> 160416.28 | R25: =+(R15-R17-R19+R21-R23) -> 170321.2 | S25: =+(S15-S17-S19+S21-S23) -> 180269.03 | T25: =+(T15-T17-T19+T21-T23) -> 190259.76 | ... CI25: =+(CI15-CI17-CI19+CI21-CI23) -> 957385.94
B26: % Margin | C26: =C25/C15 -> 0.22532198 | D26: =D25/D15 -> 0.26394052 | E26: =E25/E15 -> 0.15015404 | F26: =F25/F15 -> 0.31181711 | G26: =G25/G15 -> 0.30962486 | H26: =H25/H15 -> 0.3550563 | I26: =I25/I15 -> 0.35732778 | J26: =J25/J15 -> 0.3409379 | ... CI26: =CI25/CI15 -> 0.42323792
F28: 2026-2035 CAGR
E29: Base Case | N29: Discount | O29: =+WACC!D16 -> 0.081629526
E30: Revenue | F30: =(V15/M15)^(1/10)-1 -> 0.058633763 | N30: NPV | O30: =NPV(O29,M25:CI25) -> 2981729.3
E31: Cloud | F31: =(V4/M4)^(1/10)-1 -> 0.070729626 | N31: Net cash | O31: =Model!$T$24 -> 51414
E32: Office | F32: =(V5/M5)^(1/10)-1 -> 0.052825232
E33: Windows | F33: =(V6/M6)^(1/10)-1 -> 0.026185083
E34: Gaming | F34: =(V7/M7)^(1/10)-1 -> 0.049095825
E35: Best Case | N35: Fair value | O35: =O30+O31 -> 3033143.3
E36: Revenue | F36: =(V60/M60)^(1/10)-1 -> 0.097728276 | N36: S/O | O36: =Model!$T$15 -> 7432
E37: Cloud | F37: =(V49/M49)^(1/10)-1 -> 0.14265552 | N37: Fair price | O37: =O35/O36 -> 408.11939
E38: Office | F38: =(V50/M50)^(1/10)-1 -> 0.052825232
E39: Windows | F39: =(V51/M51)^(1/10)-1 -> 0.026185083
E40: Gaming | F40: =(V52/M52)^(1/10)-1 -> 0.049095825
E41: Worst Case | N41: Stock price | O41: 418.79
E42: Revenue | F42: =(V98/M98)^(1/10)-1 -> 0.052511216 | N42: Downside | O42: =O37/O41-1 -> -0.02547962
E43: Cloud | F43: =(V87/M87)^(1/10)-1 -> 0.055976635
E44: Office | F44: =(V88/M88)^(1/10)-1 -> 0.057628233
E45: Windows | F45: =(V89/M89)^(1/10)-1 -> 0.026185083
E46: Gaming | F46: =(V90/M90)^(1/10)-1 -> 0.053883386
B48: BEST CASE (Cloud acceleration)
A49: Server & Cloud | B49: Server Products and Cloud Services Revenue (Pre-FY2025) | C49: 19062 | D49: 21649 | E49: 26129 | F49: 32622 | G49: 41379 | H49: 52589 | I49: 67350 | J49: 79970 | K49: 97726 | L49: 114163.69 | M49: =+L49*1.2 -> 136996.42 | N49: =+M49*1.2 -> 164395.71 | O49: =+N49*1.19 -> 195630.89 | P49: =+O49*1.18 -> 230844.46 | Q49: =+P49*1.17 -> 270088.01 | R49: =+Q49*1.16 -> 313302.1 | S49: =+R49*1.15 -> 360297.41 | T49: =+S49*1.14 -> 410739.05 | U49: =+T49*1.13 -> 464135.12 | V49: =+U49*1.12 -> 519831.34 | W49: =+V49*1.11 -> 577012.79 | X49: =+W49*(1+Segments!AR76) -> 604964.95 | Y49: =+X49*(1+Segments!AS76) -> 632917.12 | Z49: =+Y49*(1+Segments!AT76) -> 660869.29 | AA49: =+Z49*(1+Segments!AU76) -> 688821.46 | AB49: =+AA49*(1+Segments!AV76) -> 716773.63 | AC49: =+AB49*(1+Segments!AW76) -> 744725.8 | AD49: =+AC49*(1+Segments!AX76) -> 772677.97 | AE49: =+AD49*(1+Segments!AY76) -> 800630.14 | ... CI49: =+CH49*(1+Segments!DC76) -> 2365951.6
A50: Office | B50: Office Products and Cloud Services | C50: 23868 | D50: 25573 | E50: 28316 | F50: 31769 | G50: 35316 | H50: 39872 | I50: 44970 | J50: 48848 | K50: 54875 | L50: 64105.073 | M50: 71994.545 | N50: 79776.807 | O50: 84862.885 | P50: 89948.963 | Q50: 95035.041 | R50: 100121.12 | S50: 105207.2 | T50: 110293.28 | U50: 115379.35 | V50: 120465.43 | W50: 125551.51 | X50: 130637.59 | Y50: 135723.66 | Z50: 140809.74 | AA50: 145895.82 | AB50: 150981.9 | AC50: 156067.98 | AD50: 161154.05 | AE50: 166240.13 | AF50: 171326.21 | AG50: 176412.29 | AH50: 181498.37 | AI50: 186584.44 | AJ50: 191670.52 | AK50: 196756.6 | AL50: 201842.68 | AM50: 206928.76 | AN50: 212014.83 | AO50: 217100.91 | AP50: 222186.99 | AQ50: 227273.07 | AR50: 232359.15 | AS50: 237445.22 | AT50: 242531.3 | AU50: 247617.38 | AV50: 252703.46 | AW50: 257789.53 | AX50: 262875.61 | AY50: 267961.69 | AZ50: 273047.77 | BA50: 278133.85 | BB50: 283219.92 | BC50: 288306 | BD50: 293392.08 | BE50: 298478.16 | BF50: 303564.24 | BG50: 308650.31 | BH50: 313736.39 | BI50: 318822.47 | BJ50: 323908.55 | BK50: 328994.63 | BL50: 334080.7 | BM50: 339166.78 | BN50: 344252.86 | BO50: 349338.94 | BP50: 354425.02 | BQ50: 359511.09 | BR50: 364597.17 | BS50: 369683.25 | BT50: 374769.33 | BU50: 379855.4 | BV50: 384941.48 | BW50: 390027.56 | BX50: 395113.64 | BY50: 400199.72 | BZ50: 405285.79 | CA50: 410371.87 | CB50: 415457.95 | CC50: 420544.03 | CD50: 425630.11 | CE50: 430716.18 | CF50: 435802.26 | CG50: 440888.34 | CH50: 445974.42 | CI50: 451060.5
A51: Windows | B51: Windows | C51: 17548 | D51: 18593 | E51: 19518 | F51: 20395 | G51: 21510 | H51: 22488 | I51: 24732 | J51: 21507 | K51: 23244 | L51: 27153.682 | M51: 28073.759 | N51: 28993.835 | O51: 29913.912 | P51: 30833.988 | Q51: 31754.064 | R51: 32674.141 | S51: 33594.217 | T51: 34514.294 | U51: 35434.37 | V51: 36354.446 | W51: 37274.523 | X51: 38194.599 | Y51: 39114.676 | Z51: 40034.752 | AA51: 40954.829 | AB51: 41874.905 | AC51: 42794.981 | AD51: 43715.058 | AE51: 44635.134 | AF51: 45555.211 | AG51: 46475.287 | AH51: 47395.364 | AI51: 48315.44 | AJ51: 49235.516 | AK51: 50155.593 | AL51: 51075.669 | AM51: 51995.746 | AN51: 52915.822 | AO51: 53835.899 | AP51: 54755.975 | AQ51: 55676.051 | AR51: 56596.128 | AS51: 57516.204 | AT51: 58436.281 | AU51: 59356.357 | AV51: 60276.434 | AW51: 61196.51 | AX51: 62116.586 | AY51: 63036.663 | AZ51: 63956.739 | BA51: 64876.816 | BB51: 65796.892 | BC51: 66716.969 | BD51: 67637.045 | BE51: 68557.121 | BF51: 69477.198 | BG51: 70397.274 | BH51: 71317.351 | BI51: 72237.427 | BJ51: 73157.504 | BK51: 74077.58 | BL51: 74997.656 | BM51: 75917.733 | BN51: 76837.809 | BO51: 77757.886 | BP51: 78677.962 | BQ51: 79598.038 | BR51: 80518.115 | BS51: 81438.191 | BT51: 82358.268 | BU51: 83278.344 | BV51: 84198.421 | BW51: 85118.497 | BX51: 86038.573 | BY51: 86958.65 | BZ51: 87878.726 | CA51: 88798.803 | CB51: 89718.879 | CC51: 90638.956 | CD51: 91559.032 | CE51: 92479.108 | CF51: 93399.185 | CG51: 94319.261 | CH51: 95239.338 | CI51: 96159.414
A52: Gaming | B52: Gaming | C52: 9202 | D52: 9051 | E52: 10353 | F52: 11386 | G52: 11575 | H52: 15370 | I52: 16230 | J52: 15466 | K52: 21503 | L52: 23455 | M52: 26347.829 | N52: 28148.036 | O52: 29948.243 | P52: 31748.451 | Q52: 33548.658 | R52: 35348.865 | S52: 37149.072 | T52: 38949.279 | U52: 40749.486 | V52: 42549.693 | W52: 44349.9 | X52: 46150.107 | Y52: 47950.314 | Z52: 49750.521 | AA52: 51550.728 | AB52: 53350.935 | AC52: 55151.142 | AD52: 56951.349 | AE52: 58751.557 | AF52: 60551.764 | AG52: 62351.971 | AH52: 64152.178 | AI52: 65952.385 | AJ52: 67752.592 | AK52: 69552.799 | AL52: 71353.006 | AM52: 73153.213 | AN52: 74953.42 | AO52: 76753.627 | AP52: 78553.834 | AQ52: 80354.041 | AR52: 82154.248 | AS52: 83954.456 | AT52: 85754.663 | AU52: 87554.87 | AV52: 89355.077 | AW52: 91155.284 | AX52: 92955.491 | AY52: 94755.698 | AZ52: 96555.905 | BA52: 98356.112 | BB52: 100156.32 | BC52: 101956.53 | BD52: 103756.73 | BE52: 105556.94 | BF52: 107357.15 | BG52: 109157.35 | BH52: 110957.56 | BI52: 112757.77 | BJ52: 114557.98 | BK52: 116358.18 | BL52: 118158.39 | BM52: 119958.6 | BN52: 121758.8 | BO52: 123559.01 | BP52: 125359.22 | BQ52: 127159.43 | BR52: 128959.63 | BS52: 130759.84 | BT52: 132560.05 | BU52: 134360.25 | BV52: 136160.46 | BW52: 137960.67 | BX52: 139760.87 | BY52: 141561.08 | BZ52: 143361.29 | CA52: 145161.5 | CB52: 146961.7 | CC52: 148761.91 | CD52: 150562.12 | CE52: 152362.32 | CF52: 154162.53 | CG52: 155962.74 | CH52: 157762.95 | CI52: 159563.15
A53: Search & Ads | B53: Search and News Advertising | C53: 5428 | D53: 6219 | E53: 7012 | F53: 7628 | G53: 8524 | H53: 9267 | I53: 11526 | J53: 12125 | K53: 12306 | L53: 13878 | M53: 14842.337 | N53: 15806.674 | O53: 16771.011 | P53: 17735.348 | Q53: 18699.686 | R53: 19664.023 | S53: 20628.36 | T53: 21592.697 | U53: 22557.034 | V53: 23521.371 | W53: 24485.708 | X53: 25450.045 | Y53: 26414.382 | Z53: 27378.72 | AA53: 28343.057 | AB53: 29307.394 | AC53: 30271.731 | AD53: 31236.068 | AE53: 32200.405 | AF53: 33164.742 | AG53: 34129.079 | AH53: 35093.416 | AI53: 36057.754 | AJ53: 37022.091 | AK53: 37986.428 | AL53: 38950.765 | AM53: 39915.102 | AN53: 40879.439 | AO53: 41843.776 | AP53: 42808.113 | AQ53: 43772.451 | AR53: 44736.788 | AS53: 45701.125 | AT53: 46665.462 | AU53: 47629.799 | AV53: 48594.136 | AW53: 49558.473 | AX53: 50522.81 | AY53: 51487.147 | AZ53: 52451.485 | BA53: 53415.822 | BB53: 54380.159 | BC53: 55344.496 | BD53: 56308.833 | BE53: 57273.17 | BF53: 58237.507 | BG53: 59201.844 | BH53: 60166.181 | BI53: 61130.519 | BJ53: 62094.856 | BK53: 63059.193 | BL53: 64023.53 | BM53: 64987.867 | BN53: 65952.204 | BO53: 66916.541 | BP53: 67880.878 | BQ53: 68845.215 | BR53: 69809.553 | BS53: 70773.89 | BT53: 71738.227 | BU53: 72702.564 | BV53: 73666.901 | BW53: 74631.238 | BX53: 75595.575 | BY53: 76559.912 | BZ53: 77524.249 | CA53: 78488.587 | CB53: 79452.924 | CC53: 80417.261 | CD53: 81381.598 | CE53: 82345.935 | CF53: 83310.272 | CG53: 84274.609 | CH53: 85238.946 | CI53: 86203.283
A54: Enterprise Services | B54: Enterprise and Partner Services | C54: 5659 | D54: 5542 | E54: 5846 | F54: 6124 | G54: 6409 | H54: 6943 | I54: 7605 | J54: 7900 | K54: 7594 | L54: 7885 | M54: 8177.7238 | N54: 8470.4477 | O54: 8763.1715 | P54: 9055.8953 | Q54: 9348.6191 | R54: 9641.343 | S54: 9934.0668 | T54: 10226.791 | U54: 10519.514 | V54: 10812.238 | W54: 11104.962 | X54: 11397.686 | Y54: 11690.41 | Z54: 11983.134 | AA54: 12275.857 | AB54: 12568.581 | AC54: 12861.305 | AD54: 13154.029 | AE54: 13446.753 | AF54: 13739.477 | AG54: 14032.2 | AH54: 14324.924 | AI54: 14617.648 | AJ54: 14910.372 | AK54: 15203.096 | AL54: 15495.819 | AM54: 15788.543 | AN54: 16081.267 | AO54: 16373.991 | AP54: 16666.715 | AQ54: 16959.439 | AR54: 17252.162 | AS54: 17544.886 | AT54: 17837.61 | AU54: 18130.334 | AV54: 18423.058 | AW54: 18715.782 | AX54: 19008.505 | AY54: 19301.229 | AZ54: 19593.953 | BA54: 19886.677 | BB54: 20179.401 | BC54: 20472.125 | BD54: 20764.848 | BE54: 21057.572 | BF54: 21350.296 | BG54: 21643.02 | BH54: 21935.744 | BI54: 22228.468 | BJ54: 22521.191 | BK54: 22813.915 | BL54: 23106.639 | BM54: 23399.363 | BN54: 23692.087 | BO54: 23984.81 | BP54: 24277.534 | BQ54: 24570.258 | BR54: 24862.982 | BS54: 25155.706 | BT54: 25448.43 | BU54: 25741.153 | BV54: 26033.877 | BW54: 26326.601 | BX54: 26619.325 | BY54: 26912.049 | BZ54: 27204.773 | CA54: 27497.496 | CB54: 27790.22 | CC54: 28082.944 | CD54: 28375.668 | CE54: 28668.392 | CF54: 28961.116 | CG54: 29253.839 | CH54: 29546.563 | CI54: 29839.287
A55: Devices | B55: Devices | C55: 7888 | D55: 5062 | E55: 5134 | F55: 6095 | G55: 6457 | H55: 7143 | I55: 7306 | J55: 5521 | K55: 4706 | L55: 5497.5576 | M55: 5573.8917 | N55: 5650.2257 | O55: 5726.5598 | P55: 5802.8939 | Q55: 5879.228 | R55: 5955.562 | S55: 6031.8961 | T55: 6108.2302 | U55: 6184.5643 | V55: 6260.8983 | W55: 6337.2324 | X55: 6413.5665 | Y55: 6489.9006 | Z55: 6566.2347 | AA55: 6642.5687 | AB55: 6718.9028 | AC55: 6795.2369 | AD55: 6871.571 | AE55: 6947.905 | AF55: 7024.2391 | AG55: 7100.5732 | AH55: 7176.9073 | AI55: 7253.2413 | AJ55: 7329.5754 | AK55: 7405.9095 | AL55: 7482.2436 | AM55: 7558.5776 | AN55: 7634.9117 | AO55: 7711.2458 | AP55: 7787.5799 | AQ55: 7863.9139 | AR55: 7940.248 | AS55: 8016.5821 | AT55: 8092.9162 | AU55: 8169.2502 | AV55: 8245.5843 | AW55: 8321.9184 | AX55: 8398.2525 | AY55: 8474.5865 | AZ55: 8550.9206 | BA55: 8627.2547 | BB55: 8703.5888 | BC55: 8779.9229 | BD55: 8856.2569 | BE55: 8932.591 | BF55: 9008.9251 | BG55: 9085.2592 | BH55: 9161.5932 | BI55: 9237.9273 | BJ55: 9314.2614 | BK55: 9390.5955 | BL55: 9466.9295 | BM55: 9543.2636 | BN55: 9619.5977 | BO55: 9695.9318 | BP55: 9772.2658 | BQ55: 9848.5999 | BR55: 9924.934 | BS55: 10001.268 | BT55: 10077.602 | BU55: 10153.936 | BV55: 10230.27 | BW55: 10306.604 | BX55: 10382.938 | BY55: 10459.273 | BZ55: 10535.607 | CA55: 10611.941 | CB55: 10688.275 | CC55: 10764.609 | CD55: 10840.943 | CE55: 10917.277 | CF55: 10993.611 | CG55: 11069.945 | CH55: 11146.279 | CI55: 11222.613
B56: Other Product Revenue (Pre-FY2023) | C56: 2499 | D56: 2611 | E56: 2793 | F56: 3070 | G56: 3768 | H56: 4479 | I56: 5291 | J56: 0 | K56: 0 | L56: 0 | M56: 0 | N56: 0 | O56: 0 | P56: 0 | Q56: 0 | R56: 0 | S56: 0 | T56: 0 | U56: 0 | V56: 0 | W56: 0 | X56: 0 | Y56: 0 | Z56: 0 | AA56: 0 | AB56: 0 | AC56: 0 | AD56: 0 | AE56: 0 | AF56: 0 | AG56: 0 | AH56: 0 | AI56: 0 | AJ56: 0 | AK56: 0 | AL56: 0 | AM56: 0 | AN56: 0 | AO56: 0 | AP56: 0 | AQ56: 0 | AR56: 0 | AS56: 0 | AT56: 0 | AU56: 0 | AV56: 0 | AW56: 0 | AX56: 0 | AY56: 0 | AZ56: 0 | BA56: 0 | BB56: 0 | BC56: 0 | BD56: 0 | BE56: 0 | BF56: 0 | BG56: 0 | BH56: 0 | BI56: 0 | BJ56: 0 | BK56: 0 | BL56: 0 | BM56: 0 | BN56: 0 | BO56: 0 | BP56: 0 | BQ56: 0 | BR56: 0 | BS56: 0 | BT56: 0 | BU56: 0 | BV56: 0 | BW56: 0 | BX56: 0 | BY56: 0 | BZ56: 0 | CA56: 0 | CB56: 0 | CC56: 0 | CD56: 0 | CE56: 0 | CF56: 0 | CG56: 0 | CH56: 0 | CI56: 0
A57: LinkedIn | B57: LinkedIn | C57: 0 | D57: 2271 | E57: 5259 | F57: 6754 | G57: 8077 | H57: 10289 | I57: 13631 | J57: 14989 | K57: 16372 | L57: 17812 | M57: 20625.023 | N57: 22634.204 | O57: 24643.385 | P57: 26652.566 | Q57: 28661.747 | R57: 30670.928 | S57: 32680.109 | T57: 34689.29 | U57: 36698.471 | V57: 38707.652 | W57: 40716.833 | X57: 42726.014 | Y57: 44735.195 | Z57: 46744.376 | AA57: 48753.557 | AB57: 50762.738 | AC57: 52771.919 | AD57: 54781.1 | AE57: 56790.281 | AF57: 58799.462 | AG57: 60808.643 | AH57: 62817.824 | AI57: 64827.005 | AJ57: 66836.185 | AK57: 68845.366 | AL57: 70854.547 | AM57: 72863.728 | AN57: 74872.909 | AO57: 76882.09 | AP57: 78891.271 | AQ57: 80900.452 | AR57: 82909.633 | AS57: 84918.814 | AT57: 86927.995 | AU57: 88937.176 | AV57: 90946.357 | AW57: 92955.538 | AX57: 94964.719 | AY57: 96973.9 | AZ57: 98983.081 | BA57: 100992.26 | BB57: 103001.44 | BC57: 105010.62 | BD57: 107019.8 | BE57: 109028.99 | BF57: 111038.17 | BG57: 113047.35 | BH57: 115056.53 | BI57: 117065.71 | BJ57: 119074.89 | BK57: 121084.07 | BL57: 123093.25 | BM57: 125102.43 | BN57: 127111.61 | BO57: 129120.8 | BP57: 131129.98 | BQ57: 133139.16 | BR57: 135148.34 | BS57: 137157.52 | BT57: 139166.7 | BU57: 141175.88 | BV57: 143185.06 | BW57: 145194.24 | BX57: 147203.42 | BY57: 149212.6 | BZ57: 151221.79 | CA57: 153230.97 | CB57: 155240.15 | CC57: 157249.33 | CD57: 159258.51 | CE57: 161267.69 | CF57: 163276.87 | CG57: 165286.05 | CH57: 167295.23 | CI57: 169304.41
A58: Dynamics | B58: Dynamics Products and Cloud Services | C58: 0 | D58: 0 | E58: 0 | F58: 0 | G58: 0 | H58: 3754 | I58: 4687 | J58: 5796 | K58: 6831 | L58: 7702 | M58: 8743.3984 | N58: 9784.7967 | O58: 10826.195 | P58: 11867.593 | Q58: 12908.992 | R58: 13950.39 | S58: 14991.789 | T58: 16033.187 | U58: 17074.585 | V58: 18115.984 | W58: 19157.382 | X58: 20198.78 | Y58: 21240.179 | Z58: 22281.577 | AA58: 23322.975 | AB58: 24364.374 | AC58: 25405.772 | AD58: 26447.171 | AE58: 27488.569 | AF58: 28529.967 | AG58: 29571.366 | AH58: 30612.764 | AI58: 31654.162 | AJ58: 32695.561 | AK58: 33736.959 | AL58: 34778.357 | AM58: 35819.756 | AN58: 36861.154 | AO58: 37902.553 | AP58: 38943.951 | AQ58: 39985.349 | AR58: 41026.748 | AS58: 42068.146 | AT58: 43109.544 | AU58: 44150.943 | AV58: 45192.341 | AW58: 46233.739 | AX58: 47275.138 | AY58: 48316.536 | AZ58: 49357.935 | BA58: 50399.333 | BB58: 51440.731 | BC58: 52482.13 | BD58: 53523.528 | BE58: 54564.926 | BF58: 55606.325 | BG58: 56647.723 | BH58: 57689.121 | BI58: 58730.52 | BJ58: 59771.918 | BK58: 60813.317 | BL58: 61854.715 | BM58: 62896.113 | BN58: 63937.512 | BO58: 64978.91 | BP58: 66020.308 | BQ58: 67061.707 | BR58: 68103.105 | BS58: 69144.503 | BT58: 70185.902 | BU58: 71227.3 | BV58: 72268.699 | BW58: 73310.097 | BX58: 74351.495 | BY58: 75392.894 | BZ58: 76434.292 | CA58: 77475.69 | CB58: 78517.089 | CC58: 79558.487 | CD58: 80599.885 | CE58: 81641.284 | CF58: 82682.682 | CG58: 83724.081 | CH58: 84765.479 | CI58: 85806.877
B59: Other Product Revenue (Post-FY2022) | C59: 0 | D59: 0 | E59: 0 | F59: 0 | G59: 0 | H59: 373 | I59: 233 | J59: 119 | K59: 45 | L59: 72 | M59: 72 | N59: 72 | O59: 72 | P59: 72 | Q59: 72 | R59: 72 | S59: 72 | T59: 72 | U59: 72 | V59: 72 | W59: 72 | X59: 72 | Y59: 72 | Z59: 72 | AA59: 72 | AB59: 72 | AC59: 72 | AD59: 72 | AE59: 72 | AF59: 72 | AG59: 72 | AH59: 72 | AI59: 72 | AJ59: 72 | AK59: 72 | AL59: 72 | AM59: 72 | AN59: 72 | AO59: 72 | AP59: 72 | AQ59: 72 | AR59: 72 | AS59: 72 | AT59: 72 | AU59: 72 | AV59: 72 | AW59: 72 | AX59: 72 | AY59: 72 | AZ59: 72 | BA59: 72 | BB59: 72 | BC59: 72 | BD59: 72 | BE59: 72 | BF59: 72 | BG59: 72 | BH59: 72 | BI59: 72 | BJ59: 72 | BK59: 72 | BL59: 72 | BM59: 72 | BN59: 72 | BO59: 72 | BP59: 72 | BQ59: 72 | BR59: 72 | BS59: 72 | BT59: 72 | BU59: 72 | BV59: 72 | BW59: 72 | BX59: 72 | BY59: 72 | BZ59: 72 | CA59: 72 | CB59: 72 | CC59: 72 | CD59: 72 | CE59: 72 | CF59: 72 | CG59: 72 | CH59: 72 | CI59: 72
B60: Total Revenue | C60: =SUM(C49:C59) -> 91154 | D60: =SUM(D49:D59) -> 96571 | E60: =SUM(E49:E59) -> 110360 | F60: =SUM(F49:F59) -> 125843 | G60: =SUM(G49:G59) -> 143015 | H60: =SUM(H49:H59) -> 172567 | I60: =SUM(I49:I59) -> 203561 | J60: =SUM(J49:J59) -> 212241 | ... CI60: =SUM(CI49:CI59) -> 3455183.2
B61: % Growth | D61: =D60/C60-1 -> 0.059426904 | E61: =E60/D60-1 -> 0.14278614 | F61: =F60/E60-1 -> 0.1402954 | G61: =G60/F60-1 -> 0.13645574 | H61: =H60/G60-1 -> 0.20663567 | I61: =I60/H60-1 -> 0.1796056 | J61: =J60/I60-1 -> 0.042640781 | K61: =K60/J60-1 -> 0.15529987 | ... CI61: =CI60/CH60-1 -> 0.01175462
B62: COGS | C62: 32780 | D62: 34261 | E62: 38353 | F62: 42910 | G62: 46078 | H62: 52232 | I62: 62650 | J62: 65863 | K62: 74114 | L62: 87831 | M62: =M60*(L63) -> 100215.12 | N62: =N60*(0.315) -> 114575.81 | O62: =O60*(0.3) -> 122147.48 | P62: =P60*(0.3) -> 136368.65 | Q62: =Q60*(0.3) -> 151798.81 | R62: =R60*(0.3) -> 168420.14 | S62: =S60*(0.3) -> 186175.83 | T62: =T60*(0.3) -> 204965.43 | U62: =U60*(0.3) -> 224641.35 | V62: =V60*(0.3) -> 245007.32 | ... CI62: =CI60*(0.3) -> 1036554.9
B63: % of Revenue | C63: =C62/C$15 -> 0.35961121 | D63: =D62/D$15 -> 0.35477524 | E63: =E62/E$15 -> 0.34752628 | F63: =F62/F$15 -> 0.34098043 | G63: =G62/G$15 -> 0.32218998 | H63: =H62/H$15 -> 0.30267664 | I63: =I62/I$15 -> 0.30777015 | J63: =J62/J$15 -> 0.31032176 | ... L63: =L62/L$15 -> 0.31176258 | M63: =M62/M60 -> 0.31176258 | N63: =N62/N60 -> 0.315 | O63: =O62/O60 -> 0.3 | P63: =P62/P60 -> 0.3 | Q63: =Q62/Q60 -> 0.3 | R63: =R62/R60 -> 0.3 | S63: =S62/S60 -> 0.3 | T63: =T62/T60 -> 0.3 | ... CI63: =CI62/CI60 -> 0.3
B64: Operating expenses | C64: 32296 | D64: 33285 | E64: 36949 | F64: 39974 | G64: 43978 | H64: 45940 | I64: 52237 | J64: 57529 | K64: 61575 | L64: 65365 | M64: =M60*L65 -> 74581.43 | N64: =N60*M65 -> 84392.492 | O64: =O60*N65 -> 94467.988 | P64: =P60*O65 -> 105466.54 | Q64: =Q60*P65 -> 117400.12 | R64: =R60*Q65 -> 130254.94 | S64: =S60*R65 -> 143987.06 | T64: =T60*S65 -> 158518.8 | ... CI64: =CI60*CH65 -> 801664.21
B65: % of Revenue | C65: =C64/C$15 -> 0.35430151 | D65: =D64/D$15 -> 0.34466869 | E65: =E64/E$15 -> 0.33480428 | F65: =F64/F$15 -> 0.31764977 | G65: =G64/G$15 -> 0.30750621 | H65: =H64/H$15 -> 0.26621544 | I65: =I64/I$15 -> 0.25661595 | J65: =J64/J$15 -> 0.27105507 | ... L65: =L64/L$15 -> 0.23201786 | M65: =M64/M60 -> 0.23201786 | N65: =N64/N60 -> 0.23201786 | O65: =O64/O60 -> 0.23201786 | P65: =P64/P60 -> 0.23201786 | Q65: =Q64/Q60 -> 0.23201786 | R65: =R64/R60 -> 0.23201786 | S65: =S64/S60 -> 0.23201786 | T65: =T64/T60 -> 0.23201786 | ... CI65: =CI64/CI60 -> 0.23201786
B66: Net interest & other expenses | C66: -439 | D66: 876 | E66: 1416 | F66: 729 | G66: 77 | H66: 1186 | I66: 333 | J66: 788 | K66: -1646 | L66: -4901 | M66: =M60*(L67) -> -5592.0384 | N66: =N60*(M67) -> -6327.6616 | O66: =O60*(N67) -> -7083.1119 | P66: =P60*(O67) -> -7907.7719 | Q66: =Q60*(P67) -> -8802.5395 | R66: =R60*(Q67) -> -9766.3802 | S66: =S60*(R67) -> -10796.001 | T66: =T60*(S67) -> -11885.575 | ... CI66: =CI60*(CH67) -> -60107.952
B67: % of Revenue | C67: =C66/C$15 -> -0.0048160256 | D67: =D66/D$15 -> 0.0090710462 | E67: =E66/E$15 -> 0.012830736 | F67: =F66/F$15 -> 0.0057929325 | G67: =G66/G$15 -> 0.00053840506 | H67: =H66/H$15 -> 0.0068726929 | I67: =I66/I$15 -> 0.0016358733 | J67: =J66/J$15 -> 0.0037127605 | ... L67: =L66/L$15 -> -0.017396459 | M67: =M66/M60 -> -0.017396459 | N67: =N66/N60 -> -0.017396459 | O67: =O66/O60 -> -0.017396459 | P67: =P66/P60 -> -0.017396459 | Q67: =Q66/Q60 -> -0.017396459 | R67: =R66/R60 -> -0.017396459 | S67: =S66/S60 -> -0.017396459 | T67: =T66/T60 -> -0.017396459 | ... CI67: =CI66/CI60 -> -0.017396459
B68: Taxes | C68: 5100 | D68: 4412 | E68: 19903 | F68: 4448 | G68: 8755 | H68: 9831 | I68: 10978 | J68: 16950 | K68: 19651 | L68: 21795 | M68: =+(M60-M62-M64+M66)*M69 -> 24868.083 | N68: =+(N60-N62-N64+N66)*N69 -> 27931.839 | O68: =+(O60-O62-O64+O66)*O69 -> 32343.289 | P68: =+(P60-P62-P64+P66)*P69 -> 36108.895 | Q68: =+(Q60-Q62-Q64+Q66)*Q69 -> 40194.632 | R68: =+(R60-R62-R64+R66)*R69 -> 44595.773 | S68: =+(S60-S62-S64+S66)*S69 -> 49297.283 | T68: =+(T60-T62-T64+T66)*T69 -> 54272.557 | ... CI68: =+(CI60-CI62-CI64+CI66)*CI69 -> 274468.18
B69: Tax rate | C69: =C68/(C60-C62-C64+C66) -> 0.19891571 | D69: =D68/(D60-D62-D64+D66) -> 0.14755359 | E69: =E68/(E60-E62-E64+E66) -> 0.54567637 | F69: =F68/(F60-F62-F64+F66) -> 0.10181285 | G69: =G68/(G60-G62-G64+G66) -> 0.16507655 | H69: =H68/(H60-H62-H64+H66) -> 0.13007237 | I69: =I68/(I60-I62-I64+I66) -> 0.12333861 | J69: =J68/(J60-J62-J64+J66) -> 0.18909602 | ... L69: =L68/(L60-L62-L64+L66) -> 0.17629644 | M69: 0.17629644 | N69: 0.17629644 | O69: 0.17629644 | P69: 0.17629644 | Q69: 0.17629644 | R69: 0.17629644 | S69: 0.17629644 | T69: 0.17629644 | U69: 0.17629644 | V69: 0.17629644 | W69: 0.17629644 | X69: 0.17629644 | Y69: 0.17629644 | Z69: 0.17629644 | AA69: 0.17629644 | AB69: 0.17629644 | AC69: 0.17629644 | AD69: 0.17629644 | AE69: 0.17629644 | AF69: 0.17629644 | AG69: 0.17629644 | AH69: 0.17629644 | AI69: 0.17629644 | AJ69: 0.17629644 | AK69: 0.17629644 | AL69: 0.17629644 | AM69: 0.17629644 | AN69: 0.17629644 | AO69: 0.17629644 | AP69: 0.17629644 | AQ69: 0.17629644 | AR69: 0.17629644 | AS69: 0.17629644 | AT69: 0.17629644 | AU69: 0.17629644 | AV69: 0.17629644 | AW69: 0.17629644 | AX69: 0.17629644 | AY69: 0.17629644 | AZ69: 0.17629644 | BA69: 0.17629644 | BB69: 0.17629644 | BC69: 0.17629644 | BD69: 0.17629644 | BE69: 0.17629644 | BF69: 0.17629644 | BG69: 0.17629644 | BH69: 0.17629644 | BI69: 0.17629644 | BJ69: 0.17629644 | BK69: 0.17629644 | BL69: 0.17629644 | BM69: 0.17629644 | BN69: 0.17629644 | BO69: 0.17629644 | BP69: 0.17629644 | BQ69: 0.17629644 | BR69: 0.17629644 | BS69: 0.17629644 | BT69: 0.17629644 | BU69: 0.17629644 | BV69: 0.17629644 | BW69: 0.17629644 | BX69: 0.17629644 | BY69: 0.17629644 | BZ69: 0.17629644 | CA69: 0.17629644 | CB69: 0.17629644 | CC69: 0.17629644 | CD69: 0.17629644 | CE69: 0.17629644 | CF69: 0.17629644 | CG69: 0.17629644 | CH69: 0.17629644 | CI69: 0.17629644
B70: Net Income | C70: 20539 | D70: 25489 | E70: 16571 | F70: 39240 | G70: 44281 | H70: 61271 | I70: 72738 | J70: 72361 | K70: 88136 | L70: 101832 | M70: =+(M60-M62-M64+M66-M68) -> 116190.26 | N70: =+(N60-N62-N64+N66-N68) -> 130504.93 | O70: =+(O60-O62-O64+O66-O68) -> 151116.39 | P70: =+(P60-P62-P64+P66-P68) -> 168710.3 | Q70: =+(Q60-Q62-Q64+Q66-Q68) -> 187799.94 | R70: =+(R60-R62-R64+R66-R68) -> 208363.24 | S70: =+(S60-S62-S64+S66-S68) -> 230329.93 | T70: =+(T60-T62-T64+T66-T68) -> 253575.73 | ... CI70: =+(CI60-CI62-CI64+CI66-CI68) -> 1282387.9
B71: % Margin | C71: =C70/C60 -> 0.22532198 | D71: =D70/D60 -> 0.26394052 | E71: =E70/E60 -> 0.15015404 | F71: =F70/F60 -> 0.31181711 | G71: =G70/G60 -> 0.30962486 | H71: =H70/H60 -> 0.3550563 | I71: =I70/I60 -> 0.35732778 | J71: =J70/J60 -> 0.3409379 | ... CI71: =CI70/CI60 -> 0.37114903
N74: Discount | O74: =+WACC!$D$16 -> 0.081629526
N75: NPV | O75: =NPV(O74,M70:CI70) -> 4070336.7
N76: Net cash | O76: =Model!$T$24 -> 51414
N77: Fair value | O77: =O75+O76 -> 4121750.7
N78: S/O | O78: =Model!$T$15 -> 7432
N79: Fair price | O79: =O77/O78 -> 554.59509
N80: Stock price | O80: 418.79
N81: Upside | O81: =O79/O80-1 -> 0.32427968
B86: WORST CASE (AI bubble)
A87: Server & Cloud | B87: Server Products and Cloud Services Revenue (Pre-FY2025) | C87: 19062 | D87: 21649 | E87: 26129 | F87: 32622 | G87: 41379 | H87: 52589 | I87: 67350 | J87: 79970 | K87: 97726 | L87: 114163.69 | M87: =+L87*1.11 -> 126721.69 | N87: =+M87*1.1 -> 139393.86 | O87: =+N87*1.09 -> 151939.31 | P87: =+O87*1.08 -> 164094.45 | Q87: =+P87*1.07 -> 175581.07 | R87: =+Q87*1.06 -> 186115.93 | S87: =+R87*1.05 -> 195421.73 | T87: =+S87*1.04 -> 203238.6 | U87: =+T87*1.03 -> 209335.75 | V87: =+U87*(1+Segments!AP76-0.01) -> 218471.13 | W87: =+V87*(1+Segments!AQ76-0.01) -> 227408.58 | X87: =+W87*(1+Segments!AR76-0.01) -> 236150.83 | Y87: =+X87*(1+Segments!AS76-0.01) -> 244700.58 | Z87: =+Y87*(1+Segments!AT76-0.01) -> 253060.53 | AA87: =+Z87*(1+Segments!AU76-0.01) -> 261233.39 | AB87: =+AA87*(1+Segments!AV76-0.01) -> 269221.83 | AC87: =+AB87*(1+Segments!AW76-0.01) -> 277028.51 | ... CI87: =+CH87*(1+Segments!DC76-0.01) -> 497037.91
A88: Office | B88: Office Products and Cloud Services | C88: 23868 | D88: 25573 | E88: 28316 | F88: 31769 | G88: 35316 | H88: 39872 | I88: 44970 | J88: 48848 | K88: 54875 | L88: 64105.073 | M88: =L5*(1+Segments!AG77-0.001) -> 68725.186 | N88: =M5*(1+Segments!AH77-0.001) -> 76825.031 | O88: =N5*(1+Segments!AI77-0.001) -> 84783.109 | P88: =O5*(1+Segments!AJ77-0.001) -> 89864.1 | Q88: =P5*(1+Segments!AK77-0.001) -> 94945.092 | R88: =Q5*(1+Segments!AL77-0.001) -> 100026.08 | S88: =R5*(1+Segments!AM77-0.001) -> 105107.08 | T88: =S5*(1+Segments!AN77-0.001) -> 110188.07 | ... CI88: =CH5*(1+Segments!DC77-0.001) -> 450614.52
A89: Windows | B89: Windows | C89: 17548 | D89: 18593 | E89: 19518 | F89: 20395 | G89: 21510 | H89: 22488 | I89: 24732 | J89: 21507 | K89: 23244 | L89: 27153.682 | M89: 28073.759 | N89: 28993.835 | O89: 29913.912 | P89: 30833.988 | Q89: 31754.064 | R89: 32674.141 | S89: 33594.217 | T89: 34514.294 | U89: 35434.37 | V89: 36354.446 | W89: 37274.523 | X89: 38194.599 | Y89: 39114.676 | Z89: 40034.752 | AA89: 40954.829 | AB89: 41874.905 | AC89: 42794.981 | AD89: 43715.058 | AE89: 44635.134 | AF89: 45555.211 | AG89: 46475.287 | AH89: 47395.364 | AI89: 48315.44 | AJ89: 49235.516 | AK89: 50155.593 | AL89: 51075.669 | AM89: 51995.746 | AN89: 52915.822 | AO89: 53835.899 | AP89: 54755.975 | AQ89: 55676.051 | AR89: 56596.128 | AS89: 57516.204 | AT89: 58436.281 | AU89: 59356.357 | AV89: 60276.434 | AW89: 61196.51 | AX89: 62116.586 | AY89: 63036.663 | AZ89: 63956.739 | BA89: 64876.816 | BB89: 65796.892 | BC89: 66716.969 | BD89: 67637.045 | BE89: 68557.121 | BF89: 69477.198 | BG89: 70397.274 | BH89: 71317.351 | BI89: 72237.427 | BJ89: 73157.504 | BK89: 74077.58 | BL89: 74997.656 | BM89: 75917.733 | BN89: 76837.809 | BO89: 77757.886 | BP89: 78677.962 | BQ89: 79598.038 | BR89: 80518.115 | BS89: 81438.191 | BT89: 82358.268 | BU89: 83278.344 | BV89: 84198.421 | BW89: 85118.497 | BX89: 86038.573 | BY89: 86958.65 | BZ89: 87878.726 | CA89: 88798.803 | CB89: 89718.879 | CC89: 90638.956 | CD89: 91559.032 | CE89: 92479.108 | CF89: 93399.185 | CG89: 94319.261 | CH89: 95239.338 | CI89: 96159.414
A90: Gaming | B90: Gaming | C90: 9202 | D90: 9051 | E90: 10353 | F90: 11386 | G90: 11575 | H90: 15370 | I90: 16230 | J90: 15466 | K90: 21503 | L90: 23455 | M90: =L7*(1+Segments!AG79) -> 25175.079 | N90: =M7*(1+Segments!AH79) -> 28148.036 | O90: =N7*(1+Segments!AI79) -> 29948.243 | P90: =O7*(1+Segments!AJ79) -> 31748.451 | Q90: =P7*(1+Segments!AK79) -> 33548.658 | R90: =Q7*(1+Segments!AL79) -> 35348.865 | S90: =R7*(1+Segments!AM79) -> 37149.072 | T90: =S7*(1+Segments!AN79) -> 38949.279 | ... CI90: =CH7*(1+Segments!DC79) -> 159563.15
A91: Search & Ads | B91: Search and News Advertising | C91: 5428 | D91: 6219 | E91: 7012 | F91: 7628 | G91: 8524 | H91: 9267 | I91: 11526 | J91: 12125 | K91: 12306 | L91: 13878 | M91: 14842.337 | N91: 15806.674 | O91: 16771.011 | P91: 17735.348 | Q91: 18699.686 | R91: 19664.023 | S91: 20628.36 | T91: =S91*0.99 -> 20422.076 | U91: =T91*0.99 -> 20217.855 | V91: =U91*0.99 -> 20015.677 | W91: =V91*0.99 -> 19815.52 | X91: =W91*0.99 -> 19617.365 | Y91: =X91*0.99 -> 19421.191 | Z91: =Y91*0.99 -> 19226.979 | AA91: =Z91*0.99 -> 19034.71 | ... CI91: =CH91*0.99 -> 10414.968
A92: Enterprise Services | B92: Enterprise and Partner Services | C92: 5659 | D92: 5542 | E92: 5846 | F92: 6124 | G92: 6409 | H92: 6943 | I92: 7605 | J92: 7900 | K92: 7594 | L92: 7885 | M92: 8177.7238 | N92: 8470.4477 | O92: 8763.1715 | P92: 9055.8953 | Q92: 9348.6191 | R92: 9641.343 | S92: 9934.0668 | T92: 10226.791 | U92: 10519.514 | V92: 10812.238 | W92: 11104.962 | X92: 11397.686 | Y92: 11690.41 | Z92: 11983.134 | AA92: 12275.857 | AB92: 12568.581 | AC92: 12861.305 | AD92: 13154.029 | AE92: 13446.753 | AF92: 13739.477 | AG92: 14032.2 | AH92: 14324.924 | AI92: 14617.648 | AJ92: 14910.372 | AK92: 15203.096 | AL92: 15495.819 | AM92: 15788.543 | AN92: 16081.267 | AO92: 16373.991 | AP92: 16666.715 | AQ92: 16959.439 | AR92: 17252.162 | AS92: 17544.886 | AT92: 17837.61 | AU92: 18130.334 | AV92: 18423.058 | AW92: 18715.782 | AX92: 19008.505 | AY92: 19301.229 | AZ92: 19593.953 | BA92: 19886.677 | BB92: 20179.401 | BC92: 20472.125 | BD92: 20764.848 | BE92: 21057.572 | BF92: 21350.296 | BG92: 21643.02 | BH92: 21935.744 | BI92: 22228.468 | BJ92: 22521.191 | BK92: 22813.915 | BL92: 23106.639 | BM92: 23399.363 | BN92: 23692.087 | BO92: 23984.81 | BP92: 24277.534 | BQ92: 24570.258 | BR92: 24862.982 | BS92: 25155.706 | BT92: 25448.43 | BU92: 25741.153 | BV92: 26033.877 | BW92: 26326.601 | BX92: 26619.325 | BY92: 26912.049 | BZ92: 27204.773 | CA92: 27497.496 | CB92: 27790.22 | CC92: 28082.944 | CD92: 28375.668 | CE92: 28668.392 | CF92: 28961.116 | CG92: 29253.839 | CH92: 29546.563 | CI92: 29839.287
A93: Devices | B93: Devices | C93: 7888 | D93: 5062 | E93: 5134 | F93: 6095 | G93: 6457 | H93: 7143 | I93: 7306 | J93: 5521 | K93: 4706 | L93: 5497.5576 | M93: 5573.8917 | N93: 5650.2257 | O93: 5726.5598 | P93: 5802.8939 | Q93: 5879.228 | R93: 5955.562 | S93: 6031.8961 | T93: 6108.2302 | U93: 6184.5643 | V93: 6260.8983 | W93: 6337.2324 | X93: 6413.5665 | Y93: 6489.9006 | Z93: 6566.2347 | AA93: 6642.5687 | AB93: 6718.9028 | AC93: 6795.2369 | AD93: 6871.571 | AE93: 6947.905 | AF93: 7024.2391 | AG93: 7100.5732 | AH93: 7176.9073 | AI93: 7253.2413 | AJ93: 7329.5754 | AK93: 7405.9095 | AL93: 7482.2436 | AM93: 7558.5776 | AN93: 7634.9117 | AO93: 7711.2458 | AP93: 7787.5799 | AQ93: 7863.9139 | AR93: 7940.248 | AS93: 8016.5821 | AT93: 8092.9162 | AU93: 8169.2502 | AV93: 8245.5843 | AW93: 8321.9184 | AX93: 8398.2525 | AY93: 8474.5865 | AZ93: 8550.9206 | BA93: 8627.2547 | BB93: 8703.5888 | BC93: 8779.9229 | BD93: 8856.2569 | BE93: 8932.591 | BF93: 9008.9251 | BG93: 9085.2592 | BH93: 9161.5932 | BI93: 9237.9273 | BJ93: 9314.2614 | BK93: 9390.5955 | BL93: 9466.9295 | BM93: 9543.2636 | BN93: 9619.5977 | BO93: 9695.9318 | BP93: 9772.2658 | BQ93: 9848.5999 | BR93: 9924.934 | BS93: 10001.268 | BT93: 10077.602 | BU93: 10153.936 | BV93: 10230.27 | BW93: 10306.604 | BX93: 10382.938 | BY93: 10459.273 | BZ93: 10535.607 | CA93: 10611.941 | CB93: 10688.275 | CC93: 10764.609 | CD93: 10840.943 | CE93: 10917.277 | CF93: 10993.611 | CG93: 11069.945 | CH93: 11146.279 | CI93: 11222.613
B94: Other Product Revenue (Pre-FY2023) | C94: 2499 | D94: 2611 | E94: 2793 | F94: 3070 | G94: 3768 | H94: 4479 | I94: 5291 | J94: 0 | K94: 0 | L94: 0 | M94: 0 | N94: 0 | O94: 0 | P94: 0 | Q94: 0 | R94: 0 | S94: 0 | T94: 0 | U94: 0 | V94: 0 | W94: 0 | X94: 0 | Y94: 0 | Z94: 0 | AA94: 0 | AB94: 0 | AC94: 0 | AD94: 0 | AE94: 0 | AF94: 0 | AG94: 0 | AH94: 0 | AI94: 0 | AJ94: 0 | AK94: 0 | AL94: 0 | AM94: 0 | AN94: 0 | AO94: 0 | AP94: 0 | AQ94: 0 | AR94: 0 | AS94: 0 | AT94: 0 | AU94: 0 | AV94: 0 | AW94: 0 | AX94: 0 | AY94: 0 | AZ94: 0 | BA94: 0 | BB94: 0 | BC94: 0 | BD94: 0 | BE94: 0 | BF94: 0 | BG94: 0 | BH94: 0 | BI94: 0 | BJ94: 0 | BK94: 0 | BL94: 0 | BM94: 0 | BN94: 0 | BO94: 0 | BP94: 0 | BQ94: 0 | BR94: 0 | BS94: 0 | BT94: 0 | BU94: 0 | BV94: 0 | BW94: 0 | BX94: 0 | BY94: 0 | BZ94: 0 | CA94: 0 | CB94: 0 | CC94: 0 | CD94: 0 | CE94: 0 | CF94: 0 | CG94: 0 | CH94: 0 | CI94: 0
A95: LinkedIn | B95: LinkedIn | C95: 0 | D95: 2271 | E95: 5259 | F95: 6754 | G95: 8077 | H95: 10289 | I95: 13631 | J95: 14989 | K95: 16372 | L95: 17812 | M95: 20625.023 | N95: 22634.204 | O95: 24643.385 | P95: 26652.566 | Q95: 28661.747 | R95: 30670.928 | S95: 32680.109 | T95: 34689.29 | U95: 36698.471 | V95: 38707.652 | W95: 40716.833 | X95: 42726.014 | Y95: 44735.195 | Z95: 46744.376 | AA95: 48753.557 | AB95: 50762.738 | AC95: 52771.919 | AD95: 54781.1 | AE95: 56790.281 | AF95: 58799.462 | AG95: 60808.643 | AH95: 62817.824 | AI95: 64827.005 | AJ95: 66836.185 | AK95: 68845.366 | AL95: 70854.547 | AM95: 72863.728 | AN95: 74872.909 | AO95: 76882.09 | AP95: 78891.271 | AQ95: 80900.452 | AR95: 82909.633 | AS95: 84918.814 | AT95: 86927.995 | AU95: 88937.176 | AV95: 90946.357 | AW95: 92955.538 | AX95: 94964.719 | AY95: 96973.9 | AZ95: 98983.081 | BA95: 100992.26 | BB95: 103001.44 | BC95: 105010.62 | BD95: 107019.8 | BE95: 109028.99 | BF95: 111038.17 | BG95: 113047.35 | BH95: 115056.53 | BI95: 117065.71 | BJ95: 119074.89 | BK95: 121084.07 | BL95: 123093.25 | BM95: 125102.43 | BN95: 127111.61 | BO95: 129120.8 | BP95: 131129.98 | BQ95: 133139.16 | BR95: 135148.34 | BS95: 137157.52 | BT95: 139166.7 | BU95: 141175.88 | BV95: 143185.06 | BW95: 145194.24 | BX95: 147203.42 | BY95: 149212.6 | BZ95: 151221.79 | CA95: 153230.97 | CB95: 155240.15 | CC95: 157249.33 | CD95: 159258.51 | CE95: 161267.69 | CF95: 163276.87 | CG95: 165286.05 | CH95: 167295.23 | CI95: 169304.41
A96: Dynamics | B96: Dynamics Products and Cloud Services | C96: 0 | D96: 0 | E96: 0 | F96: 0 | G96: 0 | H96: 3754 | I96: 4687 | J96: 5796 | K96: 6831 | L96: 7702 | M96: 8743.3984 | N96: 9784.7967 | O96: 10826.195 | P96: 11867.593 | Q96: 12908.992 | R96: 13950.39 | S96: 14991.789 | T96: 16033.187 | U96: 17074.585 | V96: 18115.984 | W96: 19157.382 | X96: 20198.78 | Y96: 21240.179 | Z96: 22281.577 | AA96: 23322.975 | AB96: 24364.374 | AC96: 25405.772 | AD96: 26447.171 | AE96: 27488.569 | AF96: 28529.967 | AG96: 29571.366 | AH96: 30612.764 | AI96: 31654.162 | AJ96: 32695.561 | AK96: 33736.959 | AL96: 34778.357 | AM96: 35819.756 | AN96: 36861.154 | AO96: 37902.553 | AP96: 38943.951 | AQ96: 39985.349 | AR96: 41026.748 | AS96: 42068.146 | AT96: 43109.544 | AU96: 44150.943 | AV96: 45192.341 | AW96: 46233.739 | AX96: 47275.138 | AY96: 48316.536 | AZ96: 49357.935 | BA96: 50399.333 | BB96: 51440.731 | BC96: 52482.13 | BD96: 53523.528 | BE96: 54564.926 | BF96: 55606.325 | BG96: 56647.723 | BH96: 57689.121 | BI96: 58730.52 | BJ96: 59771.918 | BK96: 60813.317 | BL96: 61854.715 | BM96: 62896.113 | BN96: 63937.512 | BO96: 64978.91 | BP96: 66020.308 | BQ96: 67061.707 | BR96: 68103.105 | BS96: 69144.503 | BT96: 70185.902 | BU96: 71227.3 | BV96: 72268.699 | BW96: 73310.097 | BX96: 74351.495 | BY96: 75392.894 | BZ96: 76434.292 | CA96: 77475.69 | CB96: 78517.089 | CC96: 79558.487 | CD96: 80599.885 | CE96: 81641.284 | CF96: 82682.682 | CG96: 83724.081 | CH96: 84765.479 | CI96: 85806.877
B97: Other Product Revenue (Post-FY2022) | C97: 0 | D97: 0 | E97: 0 | F97: 0 | G97: 0 | H97: 373 | I97: 233 | J97: 119 | K97: 45 | L97: 72 | M97: 72 | N97: 72 | O97: 72 | P97: 72 | Q97: 72 | R97: 72 | S97: 72 | T97: 72 | U97: 72 | V97: 72 | W97: 72 | X97: 72 | Y97: 72 | Z97: 72 | AA97: 72 | AB97: 72 | AC97: 72 | AD97: 72 | AE97: 72 | AF97: 72 | AG97: 72 | AH97: 72 | AI97: 72 | AJ97: 72 | AK97: 72 | AL97: 72 | AM97: 72 | AN97: 72 | AO97: 72 | AP97: 72 | AQ97: 72 | AR97: 72 | AS97: 72 | AT97: 72 | AU97: 72 | AV97: 72 | AW97: 72 | AX97: 72 | AY97: 72 | AZ97: 72 | BA97: 72 | BB97: 72 | BC97: 72 | BD97: 72 | BE97: 72 | BF97: 72 | BG97: 72 | BH97: 72 | BI97: 72 | BJ97: 72 | BK97: 72 | BL97: 72 | BM97: 72 | BN97: 72 | BO97: 72 | BP97: 72 | BQ97: 72 | BR97: 72 | BS97: 72 | BT97: 72 | BU97: 72 | BV97: 72 | BW97: 72 | BX97: 72 | BY97: 72 | BZ97: 72 | CA97: 72 | CB97: 72 | CC97: 72 | CD97: 72 | CE97: 72 | CF97: 72 | CG97: 72 | CH97: 72 | CI97: 72
B98: Total Revenue | C98: =SUM(C87:C97) -> 91154 | D98: =SUM(D87:D97) -> 96571 | E98: =SUM(E87:E97) -> 110360 | F98: =SUM(F87:F97) -> 125843 | G98: =SUM(G87:G97) -> 143015 | H98: =SUM(H87:H97) -> 172567 | I98: =SUM(I87:I97) -> 203561 | J98: =SUM(J87:J97) -> 212241 | ... CI98: =SUM(CI87:CI97) -> 1510035.2
B99: % Growth | D99: =D98/C98-1 -> 0.059426904 | E99: =E98/D98-1 -> 0.14278614 | F99: =F98/E98-1 -> 0.1402954 | G99: =G98/F98-1 -> 0.13645574 | H99: =H98/G98-1 -> 0.20663567 | I99: =I98/H98-1 -> 0.1796056 | J99: =J98/I98-1 -> 0.042640781 | K99: =K98/J98-1 -> 0.15529987 | ... CI99: =CI98/CH98-1 -> 0.0080682418
B100: COGS | C100: 32780 | D100: 34261 | E100: 38353 | F100: 42910 | G100: 46078 | H100: 52232 | I100: 62650 | J100: 65863 | K100: 74114 | L100: 87831 | M100: =M98*(L101-0.001) -> 95320.233 | N100: =N98*(0.315) -> 105770.42 | O100: =O98*(0.315) -> 114466.87 | P100: =P98*(0.315) -> 122134.1 | Q100: =Q98*(0.315) -> 129590.73 | R100: =R98*(0.315) -> 136747.57 | S100: =S98*(0.315) -> 143517.25 | T100: =T98*(0.315) -> 149449.17 | U100: =U98*(0.315) -> 154840.03 | ... CI100: =CI98*(0.315) -> 475661.07
B101: % of Revenue | C101: =C100/C$15 -> 0.35961121 | D101: =D100/D$15 -> 0.35477524 | E101: =E100/E$15 -> 0.34752628 | F101: =F100/F$15 -> 0.34098043 | G101: =G100/G$15 -> 0.32218998 | H101: =H100/H$15 -> 0.30267664 | I101: =I100/I$15 -> 0.30777015 | J101: =J100/J$15 -> 0.31032176 | ... L101: =L100/L$15 -> 0.31176258 | M101: =M100/M98 -> 0.31076258 | N101: =N100/N98 -> 0.315 | O101: =O100/O98 -> 0.315 | P101: =P100/P98 -> 0.315 | Q101: =Q100/Q98 -> 0.315 | R101: =R100/R98 -> 0.315 | S101: =S100/S98 -> 0.315 | T101: =T100/T98 -> 0.315 | ... CI101: =CI100/CI98 -> 0.315
B102: Operating expenses | C102: 32296 | D102: 33285 | E102: 36949 | F102: 39974 | G102: 43978 | H102: 45940 | I102: 52237 | J102: 57529 | K102: 61575 | L102: 65365 | M102: =M98*L103 -> 71166.86 | N102: =N98*M103 -> 77906.752 | O102: =O98*N103 -> 84312.251 | P102: =P98*O103 -> 89959.657 | Q102: =Q98*P103 -> 95451.952 | R102: =R98*Q103 -> 100723.42 | S102: =S98*R103 -> 105709.73 | T102: =T98*S103 -> 110078.97 | ... CI102: =CI98*CH103 -> 350355.13
B103: % of Revenue | C103: =C102/C$15 -> 0.35430151 | D103: =D102/D$15 -> 0.34466869 | E103: =E102/E$15 -> 0.33480428 | F103: =F102/F$15 -> 0.31764977 | G103: =G102/G$15 -> 0.30750621 | H103: =H102/H$15 -> 0.26621544 | I103: =I102/I$15 -> 0.25661595 | J103: =J102/J$15 -> 0.27105507 | ... L103: =L102/L$15 -> 0.23201786 | M103: =M102/M98 -> 0.23201786 | N103: =N102/N98 -> 0.23201786 | O103: =O102/O98 -> 0.23201786 | P103: =P102/P98 -> 0.23201786 | Q103: =Q102/Q98 -> 0.23201786 | R103: =R102/R98 -> 0.23201786 | S103: =S102/S98 -> 0.23201786 | T103: =T102/T98 -> 0.23201786 | ... CI103: =CI102/CI98 -> 0.23201786
B104: Net interest & other expenses | C104: -439 | D104: 876 | E104: 1416 | F104: 729 | G104: 77 | H104: 1186 | I104: 333 | J104: 788 | K104: -1646 | L104: -4901 | M104: =M98*(L105) -> -5336.0174 | N104: =N98*(M105) -> -8058.6987 | O104: =O98*(N105) -> -8721.2855 | P104: =P98*(O105) -> -9305.455 | Q104: =Q98*(P105) -> -9873.5797 | R104: =R98*(Q105) -> -10418.862 | S104: =S98*(R105) -> -10934.647 | T104: =T98*(S105) -> -11386.603 | ... CI104: =CI98*(CH105) -> -36240.844
B105: % of Revenue | C105: =C104/C$15 -> -0.0048160256 | D105: =D104/D$15 -> 0.0090710462 | E105: =E104/E$15 -> 0.012830736 | F105: =F104/F$15 -> 0.0057929325 | G105: =G104/G$15 -> 0.00053840506 | H105: =H104/H$15 -> 0.0068726929 | I105: =I104/I$15 -> 0.0016358733 | J105: =J104/J$15 -> 0.0037127605 | ... L105: =L104/L$15 -> -0.017396459 | M105: -0.024 | N105: -0.024 | O105: -0.024 | P105: -0.024 | Q105: -0.024 | R105: -0.024 | S105: -0.024 | T105: -0.024 | U105: -0.024 | V105: -0.024 | W105: -0.024 | X105: -0.024 | Y105: -0.024 | Z105: -0.024 | AA105: -0.024 | AB105: -0.024 | AC105: -0.024 | AD105: -0.024 | AE105: -0.024 | AF105: -0.024 | AG105: -0.024 | AH105: -0.024 | AI105: -0.024 | AJ105: -0.024 | AK105: -0.024 | AL105: -0.024 | AM105: -0.024 | AN105: -0.024 | AO105: -0.024 | AP105: -0.024 | AQ105: -0.024 | AR105: -0.024 | AS105: -0.024 | AT105: -0.024 | AU105: -0.024 | AV105: -0.024 | AW105: -0.024 | AX105: -0.024 | AY105: -0.024 | AZ105: -0.024 | BA105: -0.024 | BB105: -0.024 | BC105: -0.024 | BD105: -0.024 | BE105: -0.024 | BF105: -0.024 | BG105: -0.024 | BH105: -0.024 | BI105: -0.024 | BJ105: -0.024 | BK105: -0.024 | BL105: -0.024 | BM105: -0.024 | BN105: -0.024 | BO105: -0.024 | BP105: -0.024 | BQ105: -0.024 | BR105: -0.024 | BS105: -0.024 | BT105: -0.024 | BU105: -0.024 | BV105: -0.024 | BW105: -0.024 | BX105: -0.024 | BY105: -0.024 | BZ105: -0.024 | CA105: -0.024 | CB105: -0.024 | CC105: -0.024 | CD105: -0.024 | CE105: -0.024 | CF105: -0.024 | CG105: -0.024 | CH105: -0.024 | CI105: -0.024
B106: Taxes | C106: 5100 | D106: 4412 | E106: 19903 | F106: 4448 | G106: 8755 | H106: 9831 | I106: 10978 | J106: 16950 | K106: 19651 | L106: 21795 | M106: =+(M98-M100-M102+M104)*M107 -> 25510.373 | N106: =+(N98-N100-N102+N104)*N107 -> 27238.004 | O106: =+(O98-O100-O102+O104)*O107 -> 29477.515 | P106: =+(P98-P100-P102+P104)*P107 -> 31451.979 | Q106: =+(Q98-Q100-Q102+Q104)*Q107 -> 33372.212 | R106: =+(R98-R100-R102+R104)*R107 -> 35215.241 | S106: =+(S98-S100-S102+S104)*S107 -> 36958.569 | T106: =+(T98-T100-T102+T104)*T107 -> 38486.158 | ... CI106: =+(CI98-CI100-CI102+CI104)*CI107 -> 122492.26
B107: Tax rate | C107: =C106/(C98-C100-C102+C104) -> 0.19891571 | D107: =D106/(D98-D100-D102+D104) -> 0.14755359 | E107: =E106/(E98-E100-E102+E104) -> 0.54567637 | F107: =F106/(F98-F100-F102+F104) -> 0.10181285 | G107: =G106/(G98-G100-G102+G104) -> 0.16507655 | H107: =H106/(H98-H100-H102+H104) -> 0.13007237 | I107: =I106/(I98-I100-I102+I104) -> 0.12333861 | J107: =J106/(J98-J100-J102+J104) -> 0.18909602 | ... L107: =L106/(L98-L100-L102+L104) -> 0.17629644 | M107: =$J$107 -> 0.18909602 | N107: =$J$107 -> 0.18909602 | O107: =$J$107 -> 0.18909602 | P107: =$J$107 -> 0.18909602 | Q107: =$J$107 -> 0.18909602 | R107: =$J$107 -> 0.18909602 | S107: =$J$107 -> 0.18909602 | T107: =$J$107 -> 0.18909602 | ... CI107: =$J$107 -> 0.18909602
B108: Net Income | C108: 20539 | D108: 25489 | E108: 16571 | F108: 39240 | G108: 44281 | H108: 61271 | I108: 72738 | J108: 72361 | K108: 88136 | L108: 101832 | M108: =+(M98-M100-M102+M104-M106) -> 109396.61 | N108: =+(N98-N100-N102+N104-N106) -> 116805.24 | O108: =+(O98-O100-O102+O104-O106) -> 126408.97 | P108: =+(P98-P100-P102+P104-P106) -> 134876.1 | Q108: =+(Q98-Q100-Q102+Q104-Q106) -> 143110.68 | R108: =+(R98-R100-R102+R104-R106) -> 151014.17 | S108: =+(S98-S100-S102+S104-S106) -> 158490.12 | T108: =+(T98-T100-T102+T104-T106) -> 165040.9 | ... CI108: =+(CI98-CI100-CI102+CI104-CI106) -> 525285.85
B109: % Margin | C109: =C108/C98 -> 0.22532198 | D109: =D108/D98 -> 0.26394052 | E109: =E108/E98 -> 0.15015404 | F109: =F108/F98 -> 0.31181711 | G109: =G108/G98 -> 0.30962486 | H109: =H108/H98 -> 0.3550563 | I109: =I108/I98 -> 0.35732778 | J109: =J108/J98 -> 0.3409379 | ... CI109: =CI108/CI98 -> 0.34786332
...

Sheet Model2
A1: Main | AD1: 44742 | AF1: 44926 | AH1: 45107 | AJ1: 45291 | AL1: 45473 | AN1: 45657
C2: Q116 | D2: Q216 | E2: Q316 | F2: Q416 | G2: Q117 | H2: Q217 | I2: Q317 | J2: Q417 | K2: Q118 | L2: Q218 | M2: Q318 | N2: Q418 | O2: Q119 | P2: Q219 | Q2: Q319 | R2: Q419 | S2: Q120 | T2: Q220 | U2: Q320 | V2: Q420 | W2: Q121 | X2: Q221 | Y2: Q321 | Z2: Q421 | AA2: Q122 | AB2: Q222 | AC2: Q322 | AD2: Q422 | AE2: Q123 | AF2: Q223 | AG2: Q323 | AH2: Q423 | AI2: Q124 | AJ2: Q224 | AK2: Q324 | AL2: Q424 | AM2: Q125 | AN2: Q225 | AO2: Q325 | AP2: Q425 | AQ2: Q126 | AR2: Q226 | AS2: Q326 | AV2: FY16 | AW2: FY17 | AX2: FY18 | AY2: FY19 | AZ2: FY20 | BA2: FY21 | BB2: FY22 | BC2: FY23 | BD2: FY24 | BE2: FY25 | BF2: FY26 | BG2: FY27 | BH2: FY28 | BI2: FY29 | BJ2: FY30 | BK2: FY31 | BL2: FY32 | BM2: FY33 | BN2: FY34 | BO2: FY35 | BP2: FY36 | BQ2: FY37 | BR2: FY38 | BS2: FY39 | BT2: FY40 | BU2: FY41 | BV2: FY42 | BW2: FY43 | BX2: FY44 | BY2: FY45 | BZ2: FY46 | CA2: FY47 | CB2: FY48 | CC2: FY49 | CD2: FY50 | CE2: FY51 | CF2: FY52 | CG2: FY53 | CH2: FY54 | CI2: FY55 | CJ2: FY56 | CK2: FY57 | CL2: FY58 | CM2: FY59 | CN2: FY60 | CO2: FY61 | CP2: FY62 | CQ2: FY63 | CR2: FY64 | CS2: FY65 | CT2: FY66 | CU2: FY67 | CV2: FY68 | CW2: FY69 | CX2: FY70 | CY2: FY71 | CZ2: FY72 | DA2: FY73 | DB2: FY74 | DC2: FY75 | DD2: FY76 | DE2: FY77 | DF2: FY78 | DG2: FY79 | DH2: FY80 | DI2: FY81 | DJ2: FY82 | DK2: FY83 | DL2: FY84 | DM2: FY85 | DN2: FY86 | DO2: FY87 | DP2: FY88 | DQ2: FY89 | DR2: FY90 | DS2: FY91 | DT2: FY92 | DU2: FY93 | DV2: FY94 | DW2: FY95 | DX2: FY96 | DY2: FY97 | DZ2: FY98 | EA2: FY99 | EB2: FY100 | EC2: FY101 | ED2: FY102 | EE2: FY103 | EF2: FY104 | EG2: FY105 | EH2: FY106 | EI2: FY107 | EJ2: FY108 | EK2: FY109 | EL2: FY110 | EM2: FY111 | EN2: FY112 | EO2: FY113 | EP2: FY114 | EQ2: FY115 | ER2: FY116 | ES2: FY117 | ET2: FY118 | EU2: FY119 | EV2: FY120 | EW2: FY121 | EX2: FY122 | EY2: FY123 | EZ2: FY124 | FA2: FY125 | FB2: FY126 | FC2: FY127 | FD2: FY128 | FE2: FY129 | FF2: FY130 | FG2: FY131 | FH2: FY132 | FI2: FY133 | FJ2: FY134 | FK2: FY135 | FL2: FY136 | FM2: FY137 | FN2: FY138 | FO2: FY139 | FP2: FY140 | FQ2: FY141 | FR2: FY142 | FS2: FY143 | FT2: FY144 | FU2: FY145 | FV2: FY146 | FW2: FY147 | FX2: FY148 | FY2: FY149 | FZ2: FY150 | GA2: FY151 | GB2: FY152 | GC2: FY153 | GD2: FY154 | GE2: FY155 | GF2: FY156 | GG2: FY157 | GH2: FY158 | GI2: FY159 | GJ2: FY160 | GK2: FY161 | GL2: FY162 | GM2: FY163 | GN2: FY164 | GO2: FY165 | GP2: FY166 | GQ2: FY167 | GR2: FY168 | GS2: FY169 | GT2: FY170 | GU2: FY171 | GV2: FY172 | GW2: FY173 | GX2: FY174 | GY2: FY175 | GZ2: FY176 | HA2: FY177 | HB2: FY178 | HC2: FY179 | HD2: FY180 | HE2: FY181 | HF2: FY182 | HG2: FY183 | HH2: FY184 | HI2: FY185 | HJ2: FY186 | HK2: FY187 | HL2: FY188 | HM2: FY189 | HN2: FY190 | HO2: FY191 | HP2: FY192 | HQ2: FY193 | HR2: FY194 | HS2: FY195 | HT2: FY196 | HU2: FY197 | HV2: FY198 | HW2: FY199 | HX2: FY200 | HY2: FY201 | HZ2: FY202 | IA2: FY203 | IB2: FY204 | IC2: FY205 | ID2: FY206 | IE2: FY207 | IF2: FY208 | IG2: FY209 | IH2: FY210 | II2: FY211 | IJ2: FY212 | IK2: FY213 | IL2: FY214 | IM2: FY215 | IN2: FY216 | IO2: FY217 | IP2: FY218 | IQ2: FY219 | IR2: FY220 | IS2: FY221 | IT2: FY222 | IU2: FY223 | IV2: FY224 | IW2: FY225 | IX2: FY226 | IY2: FY227 | IZ2: FY228 | JA2: FY229 | JB2: FY230 | JC2: FY231 | JD2: FY232 | JE2: FY233 | JF2: FY234 | JG2: FY235 | JH2: FY236 | JI2: FY237 | JJ2: FY238 | JK2: FY239 | JL2: FY240 | JM2: FY241 | JN2: FY242 | JO2: FY243 | JP2: FY244 | JQ2: FY245 | JR2: FY246 | JS2: FY247 | JT2: FY248 | JU2: FY249 | JV2: FY250 | JW2: FY251 | JX2: FY252 | JY2: FY253 | JZ2: FY254 | KA2: FY255 | KB2: FY256 | KC2: FY257 | KD2: FY258 | KE2: FY259 | KF2: FY260 | KG2: FY261 | KH2: FY262 | KI2: FY263 | KJ2: FY264 | KK2: FY265 | KL2: FY266 | KM2: FY267 | KN2: FY268 | KO2: FY269 | KP2: FY270 | KQ2: FY271 | KR2: FY272 | KS2: FY273 | KT2: FY274 | KU2: FY275 | KV2: FY276 | KW2: FY277 | KX2: FY278 | KY2: FY279 | KZ2: FY280 | LA2: FY281 | LB2: FY282 | LC2: FY283 | LD2: FY284 | LE2: FY285 | LF2: FY286 | LG2: FY287 | LH2: FY288 | LI2: FY289 | LJ2: FY290 | LK2: FY291 | LL2: FY292 | LM2: FY293 | LN2: FY294 | LO2: FY295 | LP2: FY296 | LQ2: FY297 | LR2: FY298 | LS2: FY299 | LT2: FY300 | LU2: FY301 | LV2: FY302 | LW2: FY303 | LX2: FY304 | LY2: FY305 | LZ2: FY306 | MA2: FY307 | MB2: FY308 | MC2: FY309 | MD2: FY310 | ME2: FY311 | MF2: FY312 | MG2: FY313 | MH2: FY314 | MI2: FY315 | MJ2: FY316 | MK2: FY317 | ML2: FY318 | MM2: FY319 | MN2: FY320 | MO2: FY321 | MP2: FY322 | MQ2: FY323 | MR2: FY324 | MS2: FY325 | MT2: FY326 | MU2: FY327 | MV2: FY328 | MW2: FY329 | MX2: FY330 | MY2: FY331 | MZ2: FY332 | NA2: FY333 | NB2: FY334 | NC2: FY335 | ND2: FY336 | NE2: FY337 | NF2: FY338 | NG2: FY339 | NH2: FY340 | NI2: FY341 | NJ2: FY342 | NK2: FY343 | NL2: FY344 | NM2: FY345 | NN2: FY346 | NO2: FY347 | NP2: FY348 | NQ2: FY349 | NR2: FY350 | NS2: FY351 | NT2: FY352 | NU2: FY353 | NV2: FY354 | NW2: FY355 | NX2: FY356 | NY2: FY357 | NZ2: FY358 | OA2: FY359 | OB2: FY360 | OC2: FY361 | OD2: FY362 | OE2: FY363 | OF2: FY364 | OG2: FY365 | OH2: FY366 | OI2: FY367 | OJ2: FY368 | OK2: FY369 | OL2: FY370 | OM2: FY371 | ON2: FY372 | OO2: FY373 | OP2: FY374 | OQ2: FY375 | OR2: FY376 | OS2: FY377 | OT2: FY378 | OU2: FY379 | OV2: FY380 | OW2: FY381 | OX2: FY382 | OY2: FY383 | OZ2: FY384 | PA2: FY385 | PB2: FY386 | PC2: FY387 | PD2: FY388 | PE2: FY389 | PF2: FY390 | PG2: FY391 | PH2: FY392 | PI2: FY393 | PJ2: FY394 | PK2: FY395 | PL2: FY396 | PM2: FY397 | PN2: FY398 | PO2: FY399 | PP2: FY400 | PQ2: FY401 | PR2: FY402 | PS2: FY403 | PT2: FY404 | PU2: FY405 | PV2: FY406 | PW2: FY407 | PX2: FY408 | PY2: FY409 | PZ2: FY410 | QA2: FY411 | QB2: FY412 | QC2: FY413 | QD2: FY414 | QE2: FY415 | QF2: FY416 | QG2: FY417 | QH2: FY418 | QI2: FY419 | QJ2: FY420 | QK2: FY421 | QL2: FY422 | QM2: FY423 | QN2: FY424 | QO2: FY425 | QP2: FY426 | QQ2: FY427 | QR2: FY428 | QS2: FY429 | QT2: FY430 | QU2: FY431 | QV2: FY432 | QW2: FY433 | QX2: FY434 | QY2: FY435 | QZ2: FY436 | RA2: FY437 | RB2: FY438 | RC2: FY439 | RD2: FY440 | RE2: FY441 | RF2: FY442 | RG2: FY443 | RH2: FY444 | RI2: FY445 | RJ2: FY446 | RK2: FY447 | RL2: FY448 | RM2: FY449 | RN2: FY450 | RO2: FY451 | RP2: FY452 | RQ2: FY453 | RR2: FY454 | RS2: FY455 | RT2: FY456 | RU2: FY457 | RV2: FY458 | RW2: FY459 | RX2: FY460 | RY2: FY461 | RZ2: FY462 | SA2: FY463 | SB2: FY464 | SC2: FY465 | SD2: FY466 | SE2: FY467 | SF2: FY468 | SG2: FY469 | SH2: FY470 | SI2: FY471 | SJ2: FY472 | SK2: FY473 | SL2: FY474 | SM2: FY475 | SN2: FY476 | SO2: FY477 | SP2: FY478 | SQ2: FY479 | SR2: FY480 | SS2: FY481 | ST2: FY482 | SU2: FY483 | SV2: FY484 | SW2: FY485 | SX2: FY486 | SY2: FY487 | SZ2: FY488 | TA2: FY489
B3: Server and cloud | AE3: 14948 | AF3: 16012 | AG3: 16187 | AH3: 17860 | AI3: 18062 | AJ3: 19597 | AK3: 20266 | AL3: 21903 | AM3: 22155 | AN3: 23641 | AO3: 24761 | AP3: 27878 | AQ3: 28872 | AR3: 30865 | BC3: 65007 | BD3: 79828 | BE3: =SUM(AM3:AP3) -> 98435
B4: MS 365 Commercial and cloud | AE4: 15502 | AF4: 15774 | AG4: 17195 | AH4: 18478 | AI4: 18044 | AJ4: 18321 | AK4: 19712 | AL4: 20892 | AM4: 20449 | AN4: 21117 | AO4: 21883 | AP4: 24318 | AQ4: 23966 | AR4: 24524 | BC4: 66949 | BD4: 76969 | BE4: =SUM(AM4:AP4) -> 87767
B5: Gaming | AE5: 3610 | AF5: 4758 | AG5: 3607 | AH5: 3491 | AI5: 3919 | AJ5: 7111 | AK5: 5451 | AL5: 5022 | AM5: 5621 | AN5: 6581 | AO5: 5721 | AP5: 5532 | AQ5: 5508 | AR5: 5958 | BB5: 16230 | BC5: 15466 | BD5: 21503 | BE5: =SUM(AM5:AP5) -> 23455
B6: LinkedIn | AE6: 3628 | AF6: 3833 | AG6: 3659 | AH6: 3869 | AI6: 3913 | AJ6: 4195 | AK6: 4013 | AL6: 4251 | AM6: 4292 | AN6: 4587 | AO6: 4311 | AP6: 4622 | AQ6: 4714 | AR6: 5082 | BB6: 13631 | BC6: 14989 | BD6: 16372 | BE6: =SUM(AM6:AP6) -> 17812
B7: Windows and Devices | AE7: 4593 | AF7: 4219 | AG7: 4040 | AH7: 4295 | AI7: 4340 | AJ7: 4363 | AK7: 4098 | AL7: 4225 | AM7: 4329 | AN7: 4512 | AO7: 4144 | AP7: 4329 | AQ7: 4551 | AR7: 4479 | BB7: =24732+7306 -> 32038 | BC7: 17147 | BD7: 17026 | BE7: =SUM(AM7:AP7) -> 17314
B8: Search and news ads | AE8: 2913 | AF8: 3209 | AG8: 3034 | AH8: 2969 | AI8: 3018 | AJ8: 3168 | AK8: 3055 | AL8: 3065 | AM8: 3225 | AN8: 3558 | AO8: 3504 | AP8: 3591 | AQ8: 3697 | AR8: 3812 | BB8: 11526 | BC8: 12125 | BD8: 12306 | BE8: =SUM(AM8:AP8) -> 13878
B9: Enterprise | AE9: 1929 | AF9: 1907 | AG9: 2047 | AH9: 2017 | AI9: 1944 | AJ9: 1917 | AK9: 1861 | AL9: 1872 | AM9: 1928 | AN9: 1892 | AO9: 1929 | AP9: 2136 | AQ9: 2204 | AR9: 2305 | BB9: 7605 | BC9: 7900 | BD9: 7594 | BE9: =SUM(AM9:AP9) -> 7885
B10: Dynamics and cloud | AE10: 1345 | AF10: 1391 | AG10: 1484 | AH10: 1576 | AI10: 1626 | AJ10: 1659 | AK10: 1740 | AL10: 1806 | AM10: 1849 | AN10: 1913 | AO10: 1946 | AP10: 1994 | AQ10: 2136 | AR10: 2204 | BB10: 4687 | BC10: 5796 | BD10: 6831 | BE10: =SUM(AM10:AP10) -> 7702
B11: MS 365 Consumer and cloud | AE11: 1599 | AF11: 1605 | AG11: 1586 | AH11: 1627 | AI11: 1643 | AJ11: 1679 | AK11: 1648 | AL11: 1678 | AM11: 1727 | AN11: 1821 | AO11: 1821 | AP11: 2035 | AQ11: 2022 | AR11: 2038 | BC11: 6417 | BD11: 6648 | BE11: =SUM(AM11:AP11) -> 7404
B12: Other | AE12: 55 | AF12: 39 | AG12: 18 | AH12: 7 | AI12: 8 | AJ12: 10 | AK12: 14 | AL12: 13 | AM12: 10 | AN12: 10 | AO12: 46 | AP12: 6 | AQ12: 3 | AR12: 6 | BB12: 45 | BC12: 119 | BD12: 45 | BE12: =SUM(AM12:AP12) -> 72
AX13: =SUM(AX3:AX12) -> 0 | AY13: =SUM(AY3:AY12) -> 0 | AZ13: =SUM(AZ3:AZ12) -> 0 | BA13: =SUM(BA3:BA12) -> 0 | BB13: =SUM(BB3:BB12) -> 85762 | BC13: =SUM(BC3:BC12) -> 211915 | BD13: =SUM(BD3:BD12) -> 245122 | BE13: =SUM(BE3:BE12) -> 281724
B14: Y/Y stats
B15: Server and cloud | AI15: =AI3/AE3-1 -> 0.20832218 | AJ15: =AJ3/AF3-1 -> 0.22389458 | AK15: =AK3/AG3-1 -> 0.25199234 | AL15: =AL3/AH3-1 -> 0.22637178 | AM15: =AM3/AI3-1 -> 0.22660835 | AN15: =AN3/AJ3-1 -> 0.20635812 | AO15: =AO3/AK3-1 -> 0.22180006 | AP15: =AP3/AL3-1 -> 0.27279368 | ... AR15: =AR3/AN3-1 -> 0.30557083 | BD15: =BD3/BC3-1 -> 0.22799083 | BE15: =BE3/BD3-1 -> 0.23308864
B16: MS 365 Commercial and cloud | AI16: =AI4/AE4-1 -> 0.16397884 | AJ16: =AJ4/AF4-1 -> 0.16146824 | AK16: =AK4/AG4-1 -> 0.14637976 | AL16: =AL4/AH4-1 -> 0.13064184 | AM16: =AM4/AI4-1 -> 0.1332853 | AN16: =AN4/AJ4-1 -> 0.15261176 | AO16: =AO4/AK4-1 -> 0.11013596 | AP16: =AP4/AL4-1 -> 0.16398621 | ... AR16: =AR4/AN4-1 -> 0.16133921 | BD16: =BD4/BC4-1 -> 0.14966616 | BE16: =BE4/BD4-1 -> 0.14029025
B17: Gaming | AI17: =AI5/AE5-1 -> 0.085595568 | AJ17: =AJ5/AF5-1 -> 0.49453552 | AK17: =AK5/AG5-1 -> 0.51122817 | AL17: =AL5/AH5-1 -> 0.43855629 | AM17: =AM5/AI5-1 -> 0.43429446 | AN17: =AN5/AJ5-1 -> -0.074532415 | AO17: =AO5/AK5-1 -> 0.049532196 | AP17: =AP5/AL5-1 -> 0.10155317 | ... AR17: =AR5/AN5-1 -> -0.094666464 | BD17: =BD5/BC5-1 -> 0.3903401 | BE17: =BE5/BD5-1 -> 0.090778031
B18: LinkedIn | AI18: =AI6/AE6-1 -> 0.078555678 | AJ18: =AJ6/AF6-1 -> 0.094442995 | AK18: =AK6/AG6-1 -> 0.096747745 | AL18: =AL6/AH6-1 -> 0.098733523 | AM18: =AM6/AI6-1 -> 0.096856632 | AN18: =AN6/AJ6-1 -> 0.093444577 | AO18: =AO6/AK6-1 -> 0.074258659 | AP18: =AP6/AL6-1 -> 0.087273583 | ... AR18: =AR6/AN6-1 -> 0.10791367 | BD18: =BD6/BC6-1 -> 0.092267663 | BE18: =BE6/BD6-1 -> 0.087955045
B19: Windows and Devices | AI19: =AI7/AE7-1 -> -0.055083823 | AJ19: =AJ7/AF7-1 -> 0.034131311 | AK19: =AK7/AG7-1 -> 0.014356436 | AL19: =AL7/AH7-1 -> -0.016298021 | AM19: =AM7/AI7-1 -> -0.0025345622 | AN19: =AN7/AJ7-1 -> 0.034150814 | AO19: =AO7/AK7-1 -> 0.011224988 | AP19: =AP7/AL7-1 -> 0.024615385 | ... AR19: =AR7/AN7-1 -> -0.0073138298 | BD19: =BD7/BC7-1 -> -0.007056628 | BE19: =BE7/BD7-1 -> 0.016915306
B20: Search and news ads | AI20: =AI8/AE8-1 -> 0.036045314 | AJ20: =AJ8/AF8-1 -> -0.012776566 | AK20: =AK8/AG8-1 -> 0.0069215557 | AL20: =AL8/AH8-1 -> 0.032334119 | AM20: =AM8/AI8-1 -> 0.068588469 | AN20: =AN8/AJ8-1 -> 0.12310606 | AO20: =AO8/AK8-1 -> 0.14697218 | AP20: =AP8/AL8-1 -> 0.17161501 | ... AR20: =AR8/AN8-1 -> 0.07138842 | BD20: =BD8/BC8-1 -> 0.014927835 | BE20: =BE8/BD8-1 -> 0.12774256
B21: Enterprise | AI21: =AI9/AE9-1 -> 0.0077760498 | AJ21: =AJ9/AF9-1 -> 0.0052438385 | AK21: =AK9/AG9-1 -> -0.09086468 | AL21: =AL9/AH9-1 -> -0.071888944 | AM21: =AM9/AI9-1 -> -0.0082304527 | AN21: =AN9/AJ9-1 -> -0.01304121 | AO21: =AO9/AK9-1 -> 0.036539495 | AP21: =AP9/AL9-1 -> 0.14102564 | ... AR21: =AR9/AN9-1 -> 0.21828753 | BD21: =BD9/BC9-1 -> -0.038734177 | BE21: =BE9/BD9-1 -> 0.038319726
B22: Dynamics and cloud | AI22: =AI10/AE10-1 -> 0.20892193 | AJ22: =AJ10/AF10-1 -> 0.19266715 | AK22: =AK10/AG10-1 -> 0.17250674 | AL22: =AL10/AH10-1 -> 0.14593909 | AM22: =AM10/AI10-1 -> 0.13714637 | AN22: =AN10/AJ10-1 -> 0.15310428 | AO22: =AO10/AK10-1 -> 0.1183908 | AP22: =AP10/AL10-1 -> 0.10409745 | ... AR22: =AR10/AN10-1 -> 0.15211709 | BD22: =BD10/BC10-1 -> 0.17857143 | BE22: =BE10/BD10-1 -> 0.12750695
B23: MS 365 Consumer and cloud | AI23: =AI11/AE11-1 -> 0.027517198 | AJ23: =AJ11/AF11-1 -> 0.046105919 | AK23: =AK11/AG11-1 -> 0.039092055 | AL23: =AL11/AH11-1 -> 0.031346036 | AM23: =AM11/AI11-1 -> 0.051125989 | AN23: =AN11/AJ11-1 -> 0.084574151 | AO23: =AO11/AK11-1 -> 0.10497573 | AP23: =AP11/AL11-1 -> 0.21275328 | ... AR23: =AR11/AN11-1 -> 0.11916529 | BD23: =BD11/BC11-1 -> 0.03599813 | BE23: =BE11/BD11-1 -> 0.11371841
B26: Product | C26: 15750 | D26: 19431 | E26: 15307 | F26: 16848 | G26: 14968 | H26: 18273 | I26: 14513 | J26: 16057 | K26: 14298 | L26: 17926 | M26: 15114 | N26: 17159 | O26: 17299 | P26: 16219 | Q26: 15448 | R26: 17103 | S26: 15768 | T26: 18255 | U26: 15871 | V26: 18147 | W26: 15803 | X26: 19460 | Y26: 16873 | Z26: 18938 | AA26: 16631 | AB26: 20779 | AC26: 17366 | AD26: 17956 | AE26: 15741 | AF26: 16517 | AG26: 15588 | AH26: 16853 | AI26: 15535 | AJ26: 18941 | AK26: 17080 | AL26: 13217 | AM26: 15272 | AN26: 16219 | AO26: 15319 | AP26: 17136 | AQ26: 15922 | AR26: 16451 | AV26: 67336 | AW26: 63811 | AX26: 64497 | AY26: 66069 | AZ26: 68041 | BA26: 71074 | BB26: 72732 | BC26: 64699 | BD26: 64773 | BE26: =AM26+AN26+AO26+AP26 -> 63946
B27: Service and Other | C27: 5160 | D27: 5822 | E27: 6210 | F27: 6626 | G27: 6960 | H27: 7553 | I27: 8699 | J27: 9548 | K27: 10240 | L27: 10992 | M27: 11705 | N27: 12926 | O27: 11785 | P27: 16252 | Q27: 15123 | R27: 16614 | S27: 17287 | T27: 18651 | U27: 19150 | V27: 19886 | W27: 21351 | X27: 23616 | Y27: 24833 | Z27: 27214 | AA27: 28686 | AB27: 30949 | AC27: 31994 | AD27: 33909 | AE27: 34381 | AF27: 36230 | AG27: 37269 | AH27: 39336 | AI27: 40982 | AJ27: 43079 | AK27: 44778 | AL27: 51510 | AM27: 50313 | AN27: 53413 | AO27: 54747 | AP27: 59305 | AQ27: 61751 | AR27: 64822 | AV27: 23818 | AW27: 32760 | AX27: 45863 | AY27: 59774 | AZ27: 74974 | BA27: 97014 | BB27: 125538 | BC27: 147216 | BD27: 180349 | BE27: =AM27+AN27+AO27+AP27 -> 217778
B28: Revenue | C28: =SUM(C26:C27) -> 20910 | D28: =SUM(D26:D27) -> 25253 | E28: =SUM(E26:E27) -> 21517 | F28: =SUM(F26:F27) -> 23474 | G28: =SUM(G26:G27) -> 21928 | H28: =SUM(H26:H27) -> 25826 | I28: =SUM(I26:I27) -> 23212 | J28: =SUM(J26:J27) -> 25605 | ... AR28: =SUM(AR26:AR27) -> 81273 | AV28: =SUM(AV26:AV27) -> 91154 | AW28: =SUM(AW26:AW27) -> 96571 | AX28: =SUM(AX26:AX27) -> 110360 | AY28: =SUM(AY26:AY27) -> 125843 | AZ28: =SUM(AZ26:AZ27) -> 143015 | BA28: =SUM(BA26:BA27) -> 168088 | BB28: =SUM(BB26:BB27) -> 198270 | BC28: =SUM(BC26:BC27) -> 211915 | BD28: =SUM(BD26:BD27) -> 245122 | BE28: =AM28+AN28+AO28+AP28 -> 281724 | BF28: =BE28*1.13 -> 318348.12 | BG28: =BF28*1.1 -> 350182.93 | BH28: =BG28*1.1 -> 385201.23
B29: Product COGS | C29: 4035 | D29: 6268 | E29: 3801 | F29: 3776 | G29: 3581 | H29: 5378 | I29: 3075 | J29: 3141 | K29: 2980 | L29: 5498 | M29: 3425 | N29: 3517 | O29: 3649 | P29: 5885 | Q29: 3441 | R29: 3298 | S29: 3305 | T29: 4966 | U29: 3376 | V29: 4370 | W29: 3597 | X29: 6058 | Y29: 4277 | Z29: 4287 | AA29: 3792 | AB29: 6331 | AC29: 4584 | AD29: 4357 | AE29: 4302 | AF29: 5690 | AG29: 3941 | AH29: 3871 | AI29: 3531 | AJ29: 5964 | AK29: 4339 | AL29: 1438 | AM29: 3294 | AN29: 3856 | AO29: 3037 | AP29: 3314 | AQ29: 2922 | AR29: 3505 | AV29: 17880 | AW29: 15175 | AX29: 15420 | AY29: 16273 | AZ29: 16017 | BA29: 18219 | BB29: 19064 | BC29: 17804 | BD29: 15272 | BE29: =AM29+AN29+AO29+AP29 -> 13501
B30: Services COGS | C30: 3172 | D30: 3604 | E30: 3921 | F30: 4203 | G30: 4263 | H30: 4523 | I30: 4985 | J30: 5315 | K30: 5298 | L30: 5566 | M30: 5844 | N30: 6225 | O30: 6256 | P30: 6538 | Q30: 6729 | R30: 7114 | S30: 7101 | T30: 7392 | U30: 7599 | V30: 7969 | W30: 7405 | X30: 8136 | Y30: 8768 | Z30: 9704 | AA30: 9854 | AB30: 10629 | AC30: 11031 | AD30: 12072 | AE30: 11150 | AF30: 11798 | AG30: 12187 | AH30: 12924 | AI30: 12771 | AJ30: 13659 | AK30: 14166 | AL30: 18246 | AM30: 16805 | AN30: 17943 | AO30: 18882 | AP30: 20700 | AQ30: 21121 | AR30: 22473 | AV30: 14900 | AW30: 19086 | AX30: 22933 | AY30: 26637 | AZ30: 30061 | BA30: 34013 | BB30: 43586 | BC30: 48059 | BD30: 58842 | BE30: =AM30+AN30+AO30+AP30 -> 74330
B31: COGS | C31: =SUM(C29:C30) -> 7207 | D31: =SUM(D29:D30) -> 9872 | E31: =SUM(E29:E30) -> 7722 | F31: =SUM(F29:F30) -> 7979 | G31: =SUM(G29:G30) -> 7844 | H31: =SUM(H29:H30) -> 9901 | I31: =SUM(I29:I30) -> 8060 | J31: =SUM(J29:J30) -> 8456 | ... AR31: =SUM(AR29:AR30) -> 25978 | AV31: =SUM(AV29:AV30) -> 32780 | AW31: =SUM(AW29:AW30) -> 34261 | AX31: =SUM(AX29:AX30) -> 38353 | AY31: =SUM(AY29:AY30) -> 42910 | AZ31: =SUM(AZ29:AZ30) -> 46078 | BA31: =SUM(BA29:BA30) -> 52232 | BB31: =SUM(BB29:BB30) -> 62650 | BC31: =SUM(BC29:BC30) -> 65863 | ... BE31: =SUM(BE29:BE30) -> 87831
B32: Gross Profit | C32: =C28-C31 -> 13703 | D32: =D28-D31 -> 15381 | E32: =E28-E31 -> 13795 | F32: =F28-F31 -> 15495 | G32: =G28-G31 -> 14084 | H32: =H28-H31 -> 15925 | I32: =I28-I31 -> 15152 | J32: =J28-J31 -> 17149 | ... AR32: =AR28-AR31 -> 55295 | AV32: =AV28-AV31 -> 58374 | AW32: =AW28-AW31 -> 62310 | AX32: =AX28-AX31 -> 72007 | AY32: =AY28-AY31 -> 82933 | AZ32: =AZ28-AZ31 -> 96937 | BA32: =BA28-BA31 -> 115856 | BB32: =BB28-BB31 -> 135620 | BC32: =BC28-BC31 -> 146052 | ... BE32: =BE28-BE31 -> 193893 | BF32: =BF28*0.7 -> 222843.68 | BG32: =BG28*0.7 -> 245128.05 | BH32: =BH28*0.7 -> 269640.86
B33: R&D | C33: 2962 | D33: 2900 | E33: 2980 | F33: 3146 | G33: 3106 | H33: 3062 | I33: 3355 | J33: 3514 | K33: 3574 | L33: 3504 | M33: 3715 | N33: 3933 | O33: 3977 | P33: 4070 | Q33: 4316 | R33: 4513 | S33: 4565 | T33: 4603 | U33: 4887 | V33: 5214 | W33: 4926 | X33: 4899 | Y33: 5204 | Z33: 5687 | AA33: 5599 | AB33: 5758 | AC33: 6306 | AD33: 6849 | AE33: 6628 | AF33: 6844 | AG33: 6984 | AH33: 6739 | AI33: 6659 | AJ33: 7142 | AK33: 7653 | AL33: 805 | AM33: 7544 | AN33: 7917 | AO33: 8198 | AP33: 8829 | AQ33: 8146 | AR33: 8504 | AV33: 11988 | AW33: 13037 | AX33: 14726 | AY33: 16876 | AZ33: 19269 | BA33: 20716 | BB33: 24512 | BC33: 27195 | BD33: 29510 | BE33: =AM33+AN33+AO33+AP33 -> 32488
B34: S&M | C34: 3341 | D34: 3954 | E34: 3398 | F34: 3942 | G34: 3218 | H34: 4079 | I34: 3872 | J34: 4292 | K34: 3812 | L34: 4562 | M34: 4335 | N34: 4760 | O34: 4098 | P34: 4588 | Q34: 4565 | R34: 4962 | S34: 4337 | T34: 4933 | U34: 4911 | V34: 5417 | W34: 4231 | X34: 4947 | Y34: 5082 | Z34: 5857 | AA34: 4547 | AB34: 5379 | AC34: 5595 | AD34: 6304 | AE34: 5126 | AF34: 5679 | AG34: 5750 | AH34: 6204 | AI34: 5187 | AJ34: 6246 | AK34: 6207 | AL34: 6816 | AM34: 5717 | AN34: 6440 | AO34: 6212 | AP34: 7285 | AQ34: 5717 | AR34: 6584 | AV34: 14635 | AW34: 15461 | AX34: 17469 | AY34: 18213 | AZ34: 19598 | BA34: 20117 | BB34: 21825 | BC34: 22759 | BD34: 24456 | BE34: =AM34+AN34+AO34+AP34 -> 25654
B35: G&A | C35: 1084 | D35: 1038 | E35: 1140 | F35: =1301+1110 -> 2411 | G35: 1045 | H35: 879 | I35: 1202 | J35: =1355+306 -> 1661 | K35: 1166 | L35: 1109 | M35: 1208 | N35: 1271 | O35: 1149 | P35: 1132 | Q35: 1179 | R35: 1425 | S35: 1061 | T35: 1121 | U35: 1273 | V35: 1656 | W35: 1119 | X35: 1139 | Y35: 1327 | Z35: 1522 | AA35: 1287 | AB35: 1384 | AC35: 1480 | AD35: 1749 | AE35: 1398 | AF35: 2337 | AG35: 1643 | AH35: 2197 | AI35: 1474 | AJ35: 1977 | AK35: 1912 | AL35: 2246 | AM35: 1673 | AN35: 1823 | AO35: 1737 | AP35: 1990 | AQ35: 1806 | AR35: 1932 | AV35: =4563+1110 -> 5673 | AW35: =4481+306 -> 4787 | AX35: 4754 | AY35: 4885 | AZ35: 5111 | BA35: 5107 | BB35: 5900 | BC35: 7575 | BD35: 7609 | BE35: =AM35+AN35+AO35+AP35 -> 7223
B36: Operating Expenses | C36: =SUM(C33:C35) -> 7387 | D36: =SUM(D33:D35) -> 7892 | E36: =SUM(E33:E35) -> 7518 | F36: =SUM(F33:F35) -> 9499 | G36: =SUM(G33:G35) -> 7369 | H36: =SUM(H33:H35) -> 8020 | I36: =SUM(I33:I35) -> 8429 | J36: =SUM(J33:J35) -> 9467 | ... AR36: =SUM(AR33:AR35) -> 17020 | AV36: =SUM(AV33:AV35) -> 32296 | AW36: =SUM(AW33:AW35) -> 33285 | AX36: =SUM(AX33:AX35) -> 36949 | AY36: =SUM(AY33:AY35) -> 39974 | AZ36: =SUM(AZ33:AZ35) -> 43978 | BA36: =SUM(BA33:BA35) -> 45940 | BB36: =SUM(BB33:BB35) -> 52237 | BC36: =SUM(BC33:BC35) -> 57529 | ... BE36: =SUM(BE33:BE35) -> 65365 | BF36: =BE36*1.05 -> 68633.25 | BG36: =BF36*1.05 -> 72064.913 | BH36: =BG36*1.05 -> 75668.158
B37: Operating Income | C37: =C32-C36 -> 6316 | D37: =D32-D36 -> 7489 | E37: =E32-E36 -> 6277 | F37: =F32-F36 -> 5996 | G37: =G32-G36 -> 6715 | H37: =H32-H36 -> 7905 | I37: =I32-I36 -> 6723 | J37: =J32-J36 -> 7682 | ... AR37: =AR32-AR36 -> 38275 | AV37: =AV32-AV36 -> 26078 | AW37: =AW32-AW36 -> 29025 | AX37: =AX32-AX36 -> 35058 | AY37: =AY32-AY36 -> 42959 | AZ37: =AZ32-AZ36 -> 52959 | BA37: =BA32-BA36 -> 69916 | BB37: =BB32-BB36 -> 83383 | BC37: =BC32-BC36 -> 88523 | ... BH37: =BH32-BH36 -> 193972.7
B38: Other expenses | C38: -295 | D38: -176 | E38: -212 | F38: 244 | G38: 112 | H38: 117 | I38: 371 | J38: 276 | K38: 276 | L38: 490 | M38: 349 | N38: 301 | O38: 266 | P38: 127 | Q38: 145 | R38: 191 | S38: 0 | T38: 194 | U38: -132 | V38: 15 | W38: 248 | X38: 440 | Y38: 188 | Z38: 310 | AA38: 286 | AB38: 268 | AC38: -174 | AD38: -47 | AE38: 54 | AF38: -60 | AG38: 321 | AH38: 473 | AI38: 389 | AJ38: -506 | AK38: -854 | AL38: -675 | AM38: -283 | AN38: -2288 | AO38: -623 | AP38: -1707 | AQ38: -3660 | AR38: 9971 | AV38: -439 | AW38: 876 | AX38: 1416 | AY38: 729 | AZ38: 77 | BA38: 1186 | BB38: 333 | BC38: 788 | BD38: -1646 | BE38: =AM38+AN38+AO38+AP38 -> -4901 | BF38: =BE38*(1+$BL$45) -> -4950.01 | BG38: =BF38*(1+$BL$45) -> -4999.5101 | BH38: =BG38*(1+$BL$45) -> -5049.5052
B39: Pre-Tax Income | C39: =C37+C38 -> 6021 | D39: =D37+D38 -> 7313 | E39: =E37+E38 -> 6065 | F39: =F37+F38 -> 6240 | G39: =G37+G38 -> 6827 | H39: =H37+H38 -> 8022 | I39: =I37+I38 -> 7094 | J39: =J37+J38 -> 7958 | ... AR39: =AR37+AR38 -> 48246 | AV39: =AV37+AV38 -> 25639 | AW39: =AW37+AW38 -> 29901 | AX39: =AX37+AX38 -> 36474 | AY39: =AY37+AY38 -> 43688 | AZ39: =AZ37+AZ38 -> 53036 | BA39: =BA37+BA38 -> 71102 | BB39: =BB37+BB38 -> 83716 | BC39: =BC37+BC38 -> 89311 | ... BH39: =BH37+BH38 -> 188923.19
B40: Taxes | C40: 952 | D40: 1375 | E40: 1760 | F40: 1013 | G40: 1160 | H40: 1755 | I40: 1608 | J40: -111 | K40: 1408 | L40: 15471 | M40: 1217 | N40: 1807 | O40: 1397 | P40: 1965 | Q40: 1677 | R40: -591 | S40: 2008 | T40: 2436 | U40: 2091 | V40: 2220 | W40: 2231 | X40: 2874 | Y40: 1779 | Z40: 2947 | AA40: 19 | AB40: 3750 | AC40: 3462 | AD40: 3747 | AE40: 4016 | AF40: 3914 | AG40: 4374 | AH40: 4646 | AI40: 4993 | AJ40: 4656 | AK40: 4788 | AL40: 2514 | AM40: 5602 | AN40: 5257 | AO40: 5553 | AP40: 5383 | AQ40: 6554 | AR40: 9788 | AV40: 5100 | AW40: 4412 | AX40: 19903 | AY40: 4448 | AZ40: 8755 | BA40: 9831 | BB40: 10978 | BC40: 16950 | BD40: 19651 | BE40: =AM40+AN40+AO40+AP40 -> 21795
B41: Net Income | C41: =C39-C40 -> 5069 | D41: =D39-D40 -> 5938 | E41: =E39-E40 -> 4305 | F41: =F39-F40 -> 5227 | G41: =G39-G40 -> 5667 | H41: =H39-H40 -> 6267 | I41: =I39-I40 -> 5486 | J41: =J39-J40 -> 8069 | ... AR41: =AR39-AR40 -> 38458 | AV41: =AV39-AV40 -> 20539 | AW41: =AW39-AW40 -> 25489 | AX41: =AX39-AX40 -> 16571 | AY41: =AY39-AY40 -> 39240 | AZ41: =AZ39-AZ40 -> 44281 | BA41: =BA39-BA40 -> 61271 | BB41: =BB39-BB40 -> 72738 | BC41: =BC39-BC40 -> 72361 | ... BE41: =BE39-BE40 -> 101832 | BF41: 113670 | BG41: 132510 | BH41: =BH39*(1-0.18) -> 154917.02 | BI41: =BH41*1.05 -> 162662.87 | BJ41: =BI41*1.05 -> 170796.01 | BK41: =BJ41*1.05 -> 179335.81 | BL41: =BK41*1.05 -> 188302.61 | BM41: =BL41*1.025 -> 193010.17 | BN41: =BM41*1.025 -> 197835.42 | BO41: =BN41*1.025 -> 202781.31 | BP41: =BO41*1.025 -> 207850.84 | BQ41: =BP41*1 -> 207850.84 | BR41: =BQ41*1 -> 207850.84 | BS41: =BR41*1 -> 207850.84 | BT41: =BS41*1 -> 207850.84 | BU41: =BT41*0.97 -> 201615.32 | BV41: =BU41*0.97 -> 195566.86 | BW41: =BV41*0.97 -> 189699.85 | BX41: =BW41*0.97 -> 184008.86 | BY41: =BX41*(1-$BL$46) -> 182168.77 | BZ41: =BY41*(1-$BL$46) -> 180347.08 | CA41: =BZ41*(1-$BL$46) -> 178543.61 | CB41: =CA41*(1-$BL$46) -> 176758.17 | CC41: =CB41*(1-$BL$46) -> 174990.59 | CD41: =CC41*(1-$BL$46) -> 173240.69 | CE41: =CD41*(1-$BL$46) -> 171508.28 | CF41: =CE41*(1-$BL$46) -> 169793.2 | ... TA41: =SZ41*(1-$BL$46) -> 2101.3593
B42: S/E | AG42: 7441 | AH42: 7434 | AI42: 7429 | AJ42: 7432 | AK42: 7431 | AL42: 7433 | AM42: 7433 | AN42: 7435 | AO42: 7433 | AP42: 7432 | AQ42: 7434 | AR42: 7431 | BC42: 7432 | BD42: 7435 | BE42: =+AP42 -> 7432 | BF42: =BE42*1.001 -> 7439.432 | BG42: =BF42*1.001 -> 7446.8714 | BH42: =BG42*1.001 -> 7454.3183
B43: EPS | C43: 0.63 | D43: 0.75 | E43: 0.55 | F43: 0.67 | G43: 0.73 | H43: 0.81 | I43: 0.71 | J43: 1.05 | K43: 0.85 | L43: -0.82 | M43: 0.96 | N43: 1.15 | O43: 1.15 | P43: 1.09 | Q43: 1.15 | R43: 1.72 | S43: 1.4 | T43: 1.53 | U43: 1.41 | V43: 1.48 | W43: 1.84 | X43: 2.05 | Y43: 2.05 | Z43: 2.19 | AA43: 2.73 | AB43: 2.5 | AC43: 2.23 | AD43: 2.24 | AE43: 2.35 | AF43: 2.2 | AG43: =AG41/AG42 -> 2.4592125 | AH43: =AH41/AH42 -> 2.7012376 | AI43: =AI41/AI42 -> 3.0005384 | AJ43: =AJ41/AJ42 -> 2.9426803 | AK43: =AK41/AK42 -> 2.9523617 | AL43: =AL41/AL42 -> 4.3033768 | AM43: =AM41/AM42 -> 3.3185793 | AN43: =AN41/AN42 -> 3.2425017 | ... AR43: =AR41/AR42 -> 5.1753465 | AV43: 2.59 | AW43: 3.29 | AX43: 2.15 | AY43: 5.11 | AZ43: 5.82 | BA43: 8.12 | BB43: 9.7 | BC43: 9.72 | BD43: 11.86 | BE43: =BE41/BE42 -> 13.70183 | BF43: =BF41/BF42 -> 15.279392 | BG43: =BG41/BG42 -> 17.79405 | BH43: =BH41/BH42 -> 20.782185
B45: Hardware Y/Y | G45: =G26/C26-1 -> -0.049650794 | H45: =H26/D26-1 -> -0.059595492 | I45: =I26/E26-1 -> -0.051871693 | J45: =J26/F26-1 -> -0.046949193 | K45: =K26/G26-1 -> -0.044762159 | L45: =L26/H26-1 -> -0.018989766 | M45: =M26/I26-1 -> 0.041411149 | N45: =N26/J26-1 -> 0.068630504 | ... AR45: =AR26/AN26-1 -> 0.014304211 | AW45: =AW26/AV26-1 -> -0.052349412 | AX45: =AX26/AW26-1 -> 0.010750498 | AY45: =AY26/AX26-1 -> 0.024373227 | AZ45: =AZ26/AY26-1 -> 0.029847584 | BA45: =BA26/AZ26-1 -> 0.044576064 | BB45: =BB26/BA26-1 -> 0.023327799 | BC45: =BC26/BB26-1 -> -0.11044657 | BD45: =BD26/BC26-1 -> 0.001143758 | BE45: =BE26/BD26-1 -> -0.012767666 | BK45: ROIC | BL45: 0.01
B46: Software Y/Y | G46: =G27/C27-1 -> 0.34883721 | H46: =H27/D27-1 -> 0.29732051 | I46: =I27/E27-1 -> 0.40080515 | J46: =J27/F27-1 -> 0.44099004 | K46: =K27/G27-1 -> 0.47126437 | L46: =L27/H27-1 -> 0.45531577 | M46: =M27/I27-1 -> 0.34555696 | N46: =N27/J27-1 -> 0.35379137 | ... AR46: =AR27/AN27-1 -> 0.21359969 | AW46: =AW27/AV27-1 -> 0.37543035 | AX46: =AX27/AW27-1 -> 0.39996947 | AY46: =AY27/AX27-1 -> 0.3033164 | AZ46: =AZ27/AY27-1 -> 0.25429116 | BA46: =BA27/AZ27-1 -> 0.29396858 | BB46: =BB27/BA27-1 -> 0.29401942 | BC46: =BC27/BB27-1 -> 0.17268078 | BD46: =BD27/BC27-1 -> 0.22506385 | BE46: =BE27/BD27-1 -> 0.2075365 | BK46: Maturity | BL46: 0.01
B47: Revenue Y/Y | G47: =G28/C28-1 -> 0.04868484 | H47: =H28/D28-1 -> 0.022690373 | I47: =I28/E28-1 -> 0.078774922 | J47: =J28/F28-1 -> 0.09078129 | K47: =K28/G28-1 -> 0.1190259 | L47: =L28/H28-1 -> 0.11972431 | M47: =M28/I28-1 -> 0.15539376 | N47: =N28/J28-1 -> 0.17496583 | ... AR47: =AR28/AN28-1 -> 0.16717888 | AW47: =AW28/AV28-1 -> 0.059426904 | AX47: =AX28/AW28-1 -> 0.14278614 | AY47: =AY28/AX28-1 -> 0.1402954 | AZ47: =AZ28/AY28-1 -> 0.13645574 | BA47: =BA28/AZ28-1 -> 0.17531727 | BB47: =BB28/BA28-1 -> 0.17956071 | BC47: =BC28/BB28-1 -> 0.068820296 | BD47: =BD28/BC28-1 -> 0.15669962 | ... BH47: =BH28/BG28-1 -> 0.1 | BK47: Discount | BL47: 0.06
B48: R&D Y/Y | AW48: =AW33/AV33-1 -> 0.087504171 | AX48: =AX33/AW33-1 -> 0.12955435 | AY48: =AY33/AX33-1 -> 0.14600027 | AZ48: =AZ33/AY33-1 -> 0.141799 | BA48: =BA33/AZ33-1 -> 0.075094712 | BB48: =BB33/BA33-1 -> 0.18324001 | BC48: =BC33/BB33-1 -> 0.10945659 | BD48: =BD33/BC33-1 -> 0.085125942 | BE48: =BE33/BD33-1 -> 0.10091494 | BK48: NPV | BL48: =NPV(BL47,BE41:TA41) -> 2778234.3
B49: S&M Y/Y | AW49: =AW34/AV34-1 -> 0.056440041 | AX49: =AX34/AW34-1 -> 0.12987517 | AY49: =AY34/AX34-1 -> 0.04258973 | AZ49: =AZ34/AY34-1 -> 0.076044584 | BA49: =BA34/AZ34-1 -> 0.026482294 | BB49: =BB34/BA34-1 -> 0.084903316 | BC49: =BC34/BB34-1 -> 0.04279496 | BD49: =BD34/BC34-1 -> 0.074563909 | BE49: =BE34/BD34-1 -> 0.048985934 | BK49: Net Cash | BL49: =AN63 -> 42166
B50: G&A Y/Y | AW50: =AW35/AV35-1 -> -0.15617839 | AX50: =AX35/AW35-1 -> -0.0068936704 | AY50: =AY35/AX35-1 -> 0.027555743 | AZ50: =AZ35/AY35-1 -> 0.046264074 | BA50: =BA35/AZ35-1 -> -0.00078262571 | BB50: =BB35/BA35-1 -> 0.15527707 | BC50: =BC35/BB35-1 -> 0.28389831 | BD50: =BD35/BC35-1 -> 0.0044884488 | BE50: =BE35/BD35-1 -> -0.050729399 | BK50: Net NPV | BL50: =BL48+BL49 -> 2820400.3
BK51: NPV | BL51: =BL50/BD42 -> 379.341
B52: Gross Margin | C52: =C32/C28 -> 0.65533238 | D52: =D32/D28 -> 0.60907615 | E52: =E32/E28 -> 0.64112097 | F52: =F32/F28 -> 0.66009202 | G52: =G32/G28 -> 0.64228384 | H52: =H32/H28 -> 0.61662666 | I52: =I32/I28 -> 0.65276581 | J52: =J32/J28 -> 0.669752 | ... AR52: =AR32/AR28 -> 0.68036125 | AV52: =AV32/AV28 -> 0.64038879 | AW52: =AW32/AW28 -> 0.64522476 | AX52: =AX32/AX28 -> 0.65247372 | AY52: =AY32/AY28 -> 0.65901957 | AZ52: =AZ32/AZ28 -> 0.67781002 | BA52: =BA32/BA28 -> 0.68925801 | BB52: =BB32/BB28 -> 0.68401674 | BC52: =BC32/BC28 -> 0.68920086 | ... BH52: =BH32/BH28 -> 0.7 | BK52: Change | BL52: =BL51/[1]Main!C15-1 -> -0.27880568
B53: Product Margin | C53: =(C26-C29)/C26 -> 0.74380952 | D53: =(D26-D29)/D26 -> 0.67742268 | E53: =(E26-E29)/E26 -> 0.75168224 | F53: =(F26-F29)/F26 -> 0.77587844 | G53: =(G26-G29)/G26 -> 0.76075628 | H53: =(H26-H29)/H26 -> 0.70568598 | I53: =(I26-I29)/I26 -> 0.78812099 | J53: =(J26-J29)/J26 -> 0.80438438 | ... AR53: =(AR26-AR29)/AR26 -> 0.78694304 | AV53: =(AV26-AV29)/AV26 -> 0.73446596 | AW53: =(AW26-AW29)/AW26 -> 0.76218834 | AX53: =(AX26-AX29)/AX26 -> 0.76091911 | AY53: =(AY26-AY29)/AY26 -> 0.75369689 | AZ53: =(AZ26-AZ29)/AZ26 -> 0.76459782 | BA53: =(BA26-BA29)/BA26 -> 0.74366154 | BB53: =(BB26-BB29)/BB26 -> 0.73788704 | BC53: =(BC26-BC29)/BC26 -> 0.724818 | ... BE53: =(BE26-BE29)/BE26 -> 0.78886873
B54: Service Margin | C54: =(C27-C30)/C27 -> 0.38527132 | D54: =(D27-D30)/D27 -> 0.38096874 | E54: =(E27-E30)/E27 -> 0.36859903 | F54: =(F27-F30)/F27 -> 0.36568065 | G54: =(G27-G30)/G27 -> 0.3875 | H54: =(H27-H30)/H27 -> 0.4011651 | I54: =(I27-I30)/I27 -> 0.42694563 | J54: =(J27-J30)/J27 -> 0.44333892 | ... AR54: =(AR27-AR30)/AR27 -> 0.65331215 | AV54: =(AV27-AV30)/AV27 -> 0.37442271 | AW54: =(AW27-AW30)/AW27 -> 0.41739927 | AX54: =(AX27-AX30)/AX27 -> 0.49996729 | AY54: =(AY27-AY30)/AY27 -> 0.55437147 | AZ54: =(AZ27-AZ30)/AZ27 -> 0.59904767 | BA54: =(BA27-BA30)/BA27 -> 0.64940112 | BB54: =(BB27-BB30)/BB27 -> 0.65280632 | BC54: =(BC27-BC30)/BC27 -> 0.67354771 | ... BE54: =(BE27-BE30)/BE27 -> 0.65868912
B55: Operating Margin | C55: =C37/C28 -> 0.30205643 | D55: =D37/D28 -> 0.29655882 | E55: =E37/E28 -> 0.29172282 | F55: =F37/F28 -> 0.25543154 | G55: =G37/G28 -> 0.30622948 | H55: =H37/H28 -> 0.30608689 | I55: =I37/I28 -> 0.28963467 | J55: =J37/J28 -> 0.30001953 | ... AR55: =AR37/AR28 -> 0.47094361 | AV55: =AV37/AV28 -> 0.28608728 | AW55: =AW37/AW28 -> 0.30055607 | AX55: =AX37/AX28 -> 0.31766945 | AY55: =AY37/AY28 -> 0.3413698 | AZ55: =AZ37/AZ28 -> 0.37030381 | BA55: =BA37/BA28 -> 0.41594879 | BB55: =BB37/BB28 -> 0.42055278 | BC55: =BC37/BC28 -> 0.41772881 | ... BH55: =BH37/BH28 -> 0.503562
B56: Net Margin | C56: =C41/C28 -> 0.24241989 | D56: =D41/D28 -> 0.23514038 | E56: =E41/E28 -> 0.20007436 | F56: =F41/F28 -> 0.22267189 | G56: =G41/G28 -> 0.2584367 | H56: =H41/H28 -> 0.24266243 | I56: =I41/I28 -> 0.23634327 | J56: =J41/J28 -> 0.31513376 | ... AR56: =AR41/AR28 -> 0.47319528 | AV56: =AV41/AV28 -> 0.22532198 | AW56: =AW41/AW28 -> 0.26394052 | AX56: =AX41/AX28 -> 0.15015404 | AY56: =AY41/AY28 -> 0.31181711 | AZ56: =AZ41/AZ28 -> 0.30962486 | BA56: =BA41/BA28 -> 0.3645174 | BB56: =BB41/BB28 -> 0.36686337 | BC56: =BC41/BC28 -> 0.34146238 | ... BH56: =BH41/BH28 -> 0.40217167
B57: Tax rate | C57: =C40/C39 -> 0.15811327 | D57: =D40/D39 -> 0.18802133 | E57: =E40/E39 -> 0.29018961 | F57: =F40/F39 -> 0.16233974 | G57: =G40/G39 -> 0.16991358 | H57: =H40/H39 -> 0.21877337 | I57: =I40/I39 -> 0.22667043 | J57: =J40/J39 -> -0.013948228 | ... AR57: =AR40/AR39 -> 0.20287692 | AV57: =AV40/AV39 -> 0.19891571 | AW57: =AW40/AW39 -> 0.14755359 | AX57: =AX40/AX39 -> 0.54567637 | AY57: =AY40/AY39 -> 0.10181285 | AZ57: =AZ40/AZ39 -> 0.16507655 | BA57: =BA40/BA39 -> 0.13826615 | BB57: =BB40/BB39 -> 0.13113383 | BC57: =BC40/BC39 -> 0.18978625 | ... BE57: =BE40/BE39 -> 0.17629644
B58: SG&A Margin | C58: =(C34+C35)/C32 -> 0.32292199 | D58: =(D34+D35)/D32 -> 0.32455627 | E58: =(E34+E35)/E32 -> 0.32895977 | F58: =(F34+F35)/F32 -> 0.41000323 | G58: =(G34+G35)/G32 -> 0.3026839 | H58: =(H34+H35)/H32 -> 0.31133438 | I58: =(I34+I35)/I32 -> 0.33487328 | J58: =(J34+J35)/J32 -> 0.34713394 | ... AR58: =(AR34+AR35)/AR32 -> 0.15401031 | AV58: =(AV34+AV35)/AV32 -> 0.34789461 | AW58: =(AW34+AW35)/AW32 -> 0.32495587 | AX58: =(AX34+AX35)/AX32 -> 0.30862277 | AY58: =(AY34+AY35)/AY32 -> 0.27851398 | AZ58: =(AZ34+AZ35)/AZ32 -> 0.25489751 | BA58: =(BA34+BA35)/BA32 -> 0.21771855 | BB58: =(BB34+BB35)/BB32 -> 0.2044315 | BC58: =(BC34+BC35)/BC32 -> 0.20769315 | ... BE58: =(BE34+BE35)/BE32 -> 0.16956259
B59: R&D Margin | C59: =C33/C32 -> 0.21615705 | D59: =D33/D32 -> 0.18854431 | E59: =E33/E32 -> 0.2160203 | F59: =F33/F32 -> 0.20303324 | G59: =G33/G32 -> 0.22053394 | H59: =H33/H32 -> 0.1922763 | I59: =I33/I32 -> 0.22142291 | J59: =J33/J32 -> 0.20490991 | ... AR59: =AR33/AR32 -> 0.15379329 | AV59: =AV33/AV32 -> 0.2053654 | AW59: =AW33/AW32 -> 0.20922805 | AX59: =AX33/AX32 -> 0.2045079 | AY59: =AY33/AY32 -> 0.20348956 | AZ59: =AZ33/AZ32 -> 0.19877859 | BA59: =BA33/BA32 -> 0.17880818 | BB59: =BB33/BB32 -> 0.1807403 | BC59: =BC33/BC32 -> 0.18620081 | ... BE59: =BE33/BE32 -> 0.16755633
B60: Interest Margin | C60: =C38/C37 -> -0.046706776 | D60: =D38/D37 -> -0.023501135 | E60: =E38/E37 -> -0.033774096 | F60: =F38/F37 -> 0.040693796 | G60: =G38/G37 -> 0.016679077 | H60: =H38/H37 -> 0.014800759 | I60: =I38/I37 -> 0.055183698 | J60: =J38/J37 -> 0.035928144 | ... AR60: =AR38/AR37 -> 0.26050947 | AV60: =AV38/AV37 -> -0.016834113 | AW60: =AW38/AW37 -> 0.030180879 | AX60: =AX38/AX37 -> 0.040390211 | AY60: =AY38/AY37 -> 0.016969669 | AZ60: =AZ38/AZ37 -> 0.0014539549 | BA60: =BA38/BA37 -> 0.016963213 | BB60: =BB38/BB37 -> 0.0039936198 | BC60: =BC38/BC37 -> 0.0089016414 | ... BE60: =BE38/BE37 -> -0.038131769
B61: EPS Growth | AW61: =AW43/AV43-1 -> 0.27027027 | AX61: =AX43/AW43-1 -> -0.34650456 | AY61: =AY43/AX43-1 -> 1.3767442 | AZ61: =AZ43/AY43-1 -> 0.13894325 | BA61: =BA43/AZ43-1 -> 0.395189 | BB61: =BB43/BA43-1 -> 0.19458128 | BC61: =BC43/BB43-1 -> 0.0020618557 | BD61: =BD43/BC43-1 -> 0.22016461 | BE61: =BE43/BD43-1 -> 0.15529763
B63: Net Cash | AH63: =AH64-AH75 -> 73904 | AK63: =AK64-AK75 -> 29386 | AL63: =AL64-AL75 -> 38513 | AM63: =AM64-AM75 -> 49089 | AN63: =AN64-AN75 -> 42166 | AO63: =AO64-AO75 -> 0 | AP63: =AP64-AP75 -> 66819 | AQ63: =AQ64-AQ75 -> 70269 | AR63: =AR64-AR75 -> 70402 | AS63: =AS64-AS75 -> 0 | BC63: =BC64-BC75 -> 73904 | BD63: =BD64-BD75 -> 38513 | BE63: =BE64-BE75 -> 66819
B64: Cash | AH64: =111262+9879 -> 121141 | AK64: =80021+14807 -> 94828 | AL64: =18315+57228+14600 -> 90143 | AM64: =78428+15778 -> 94206 | AN64: =17482+54073+15581 -> 87136 | AP64: =30242+64323+15405 -> 109970 | AQ64: =28849+73163+11465 -> 113477 | AR64: =24296+65166+21202 -> 110664 | BC64: =111262+9879 -> 121141 | BD64: =18315+57228+14600 -> 90143 | BE64: =30242+64323+15405 -> 109970
B65: A/R | AH65: 48688 | AK65: 44029 | AL65: 56924 | AM65: 44148 | AN65: 48188 | AP65: 69905 | AQ65: 52894 | AR65: 56535 | BC65: 48688 | BD65: 56924 | BE65: 69905
B66: Inventories | AH66: 2500 | AK66: 1304 | AL66: 1246 | AM66: 1626 | AN66: 909 | AP66: 938 | AQ66: 1130 | AR66: 1059 | BC66: 2500 | BD66: 1246 | BE66: 938
B67: OCA | AH67: 21807 | AK67: 21826 | AL67: 26021 | AM67: 25724 | AN67: 26428 | AP67: 25723 | AQ67: 33030 | AR67: 33134 | BC67: 21807 | BD67: 26021 | BE67: 25723
B68: PP&A | AH68: 95641 | AK68: 121375 | AL68: 135591 | AM68: 152863 | AN68: 166902 | AP68: 204966 | AQ68: 230861 | AR68: 261126 | BC68: 95641 | BD68: 135591 | BE68: 204966
B69: Lease ROU | AH69: 14346 | AK69: 17371 | AL69: 18961 | AM69: 20528 | AN69: 22816 | AP69: 24823 | AQ69: 24791 | AR69: 25103 | BC69: 14346 | BD69: 18961 | BE69: 24823
B70: Goodwill | AH70: 67886 | AK70: 119163 | AL70: 119220 | AM70: 119374 | AN70: 119191 | AP70: 119509 | AQ70: 119497 | AR70: 119622 | BC70: 67886 | BD70: 119220 | BE70: 119509
B71: Intangibles | AH71: 9366 | AK71: 28828 | AL71: 27597 | AM71: 26751 | AN71: 25385 | AP71: 22604 | AQ71: 21236 | AR71: 20289 | BC71: 9366 | BD71: 27597 | BE71: 22604
B72: ONCA | AH72: 30601 | AK72: 35551 | AL72: 36460 | AM72: 37793 | AN72: 36943 | AP72: 40565 | AQ72: 39435 | AR72: 37770 | BC72: 30601 | BD72: 36460 | BE72: 40565
B73: Total Assets | AH73: =SUM(AH64:AH72) -> 411976 | AK73: =SUM(AK64:AK72) -> 484275 | AL73: =SUM(AL64:AL72) -> 512163 | AM73: =SUM(AM64:AM72) -> 523013 | AN73: =SUM(AN64:AN72) -> 533898 | AP73: =SUM(AP64:AP72) -> 619003 | AQ73: =SUM(AQ64:AQ72) -> 636351 | AR73: =SUM(AR64:AR72) -> 665302 | AS73: =SUM(AS64:AS72) -> 0 | BC73: =SUM(BC64:BC72) -> 411976 | BD73: =SUM(BD64:BD72) -> 512163 | BE73: =SUM(BE64:BE72) -> 619003
B74: A/P | AH74: 18095 | AK74: 18087 | AL74: 21996 | AM74: 22768 | AN74: 22608 | AP74: 27724 | AQ74: 32580 | AR74: 37328 | BC74: 18095 | BD74: 21996 | BE74: 27724
B75: Debt | AH75: =5247+41990 -> 47237 | AK75: =20535+2249+42658 -> 65442 | AL75: =6693+2249+42688 -> 51630 | AM75: =2249+42868 -> 45117 | AN75: =5248+39722 -> 44970 | AP75: =40152+2999 -> 43151 | AQ75: =7832+35376 -> 43208 | AR75: =4837+35425 -> 40262 | BC75: =5247+41990 -> 47237 | BD75: =6693+2249+42688 -> 51630 | BE75: =40152+2999 -> 43151
B76: Wages | AH76: 11009 | AK76: 10432 | AL76: 12564 | AM76: 8326 | AN76: 9176 | AP76: 13709 | AQ76: 9201 | AR76: 10103 | BC76: 11009 | BD76: 12564 | BE76: 13709
B77: Taxes | AH77: =4152+25560+433 -> 30145 | AK77: =7311+26786+2469 -> 36566 | AL77: =5017+2618+27931 -> 35566 | AM77: =9717+24452+2581 -> 36750 | AN77: =6056+24389+2513 -> 32958 | AP77: =7211+25986+2835 -> 36032 | AQ77: =3655+26569+2852 -> 33076 | AR77: =2050+27256 -> 29306 | BC77: =4152+25560+433 -> 30145 | BD77: =5017+2618+27931 -> 35566 | BE77: =7211+25986+2835 -> 36032
B78: D/R | AH78: =50901+2912 -> 53813 | AK78: =41888+2945 -> 44833 | AL78: =57582+2602 -> 60184 | AM78: =53026+2663 -> 55689 | AN78: =45508+2537 -> 48045 | AP78: =64555+2710 -> 67265 | AQ78: =58987+2546 -> 61533 | AR78: =51376+2668 -> 54044 | BC78: =50901+2912 -> 53813 | BD78: =57582+2602 -> 60184 | BE78: =64555+2710 -> 67265
B79: OCL | AH79: 14745 | AK79: 18023 | AL79: 19185 | AM79: 19114 | AN79: 20286 | AP79: 25020 | AQ79: 22741 | AR79: 24311 | BC79: 14745 | BD79: 19185 | BE79: 25020
B80: Lease | AH80: 12728 | AK80: 14469 | AL80: 15497 | AM80: 16361 | AN80: 17254 | AP80: 17437 | AQ80: 17348 | AR80: 17345 | BC80: 12728 | BD80: 15497 | BE80: 17437
B81: ONCL | AH81: 17981 | AK81: 23271 | AL81: 27064 | AM81: 31165 | AN81: 35906 | AP81: 45186 | AQ81: 53588 | AR81: =58852+2876 -> 61728 | BC81: 17981 | BD81: 27064 | BE81: 45186
B82: Total Liabilities | AH82: =SUM(AH74:AH81) -> 205753 | AK82: =SUM(AK74:AK81) -> 231123 | AL82: =SUM(AL74:AL81) -> 243686 | AM82: =SUM(AM74:AM81) -> 235290 | AN82: =SUM(AN74:AN81) -> 231203 | AP82: =SUM(AP74:AP81) -> 275524 | AQ82: =SUM(AQ74:AQ81) -> 273275 | AR82: =SUM(AR74:AR81) -> 274427 | AS82: =SUM(AS74:AS81) -> 0 | BC82: =SUM(BC74:BC81) -> 205753 | BD82: =SUM(BD74:BD81) -> 243686 | BE82: =SUM(BE74:BE81) -> 275524
B83: SE | AH83: 206223 | AK83: 253152 | AL83: 268477 | AM83: 287723 | AN83: 302695 | AP83: 343479 | AQ83: 363076 | AR83: 390875 | BC83: 206223 | BD83: 268477 | BE83: 343479
B84: L + SE | AH84: =SUM(AH82:AH83) -> 411976 | AK84: =SUM(AK82:AK83) -> 484275 | AL84: =SUM(AL82:AL83) -> 512163 | AM84: =SUM(AM82:AM83) -> 523013 | AN84: =SUM(AN82:AN83) -> 533898 | AP84: =SUM(AP82:AP83) -> 619003 | AQ84: =SUM(AQ82:AQ83) -> 636351 | AR84: =SUM(AR82:AR83) -> 665302 | AS84: =SUM(AS82:AS83) -> 0 | BC84: =SUM(BC82:BC83) -> 411976 | BD84: =SUM(BD82:BD83) -> 512163 | BE84: =SUM(BE82:BE83) -> 619003
B86: Assets Y/Y | BD86: =BD73/BC73-1 -> 0.2431865 | BE86: =BE73/BD73-1 -> 0.20860546
B87: Debt to Equity | BD87: =BD75/BD83 -> 0.19230698 | BE87: =BE75/BE83 -> 0.12562922
B89: Model NI | AG89: =AG41 -> 18299 | AH89: =AH41 -> 20081 | AI89: =AI41 -> 22291 | AJ89: =AJ41 -> 21870 | AK89: =AK41 -> 21939 | AL89: =AL41 -> 31987 | AM89: =AM41 -> 24667 | AN89: =AN41 -> 24108 | ... AQ89: =AQ41 -> 27747 | BD89: =AI89+AJ89+AK89+AL89 -> 98087 | BE89: =BE41 -> 101832
B90: GAAP NI | AG90: 18299 | AH90: 20081 | AI90: 22291 | AJ90: 21870 | AK90: 21939 | AL90: 22036 | AM90: 24667 | AN90: 24108 | AO90: =BE90-AP90-AM90-AN90 -> 25824 | AP90: 27233 | AQ90: 27747 | BD90: =AI90+AJ90+AK90+AL90 -> 88136 | BE90: 101832
B91: D&A | AG91: 3549 | AH91: 3874 | AI91: 3921 | AJ91: 5959 | AK91: 6027 | AL91: 6380 | AM91: 7383 | AN91: 6827 | AO91: =BE91-AP91-AM91-AN91 -> 8740 | AP91: 11203 | AQ91: 13061 | BD91: =AI91+AJ91+AK91+AL91 -> 22287 | BE91: 34153
B92: Compensation expense | AG92: 2465 | AH92: 2416 | AI92: 2507 | AJ92: 2828 | AK92: 2703 | AL92: 2696 | AM92: 2832 | AN92: 3089 | AO92: =BE92-AP92-AM92-AN92 -> 2980 | AP92: 3073 | AQ92: 2983 | BD92: =AI92+AJ92+AK92+AL92 -> 10734 | BE92: 11974
B93: Investments | AG93: -40 | AH93: 44 | AI93: 14 | AJ93: 198 | AK93: 49 | AL93: 44 | AM93: -125 | AN93: 976 | AO93: =BE93-AP93-AM93-AN93 -> -298 | AP93: 56 | AQ93: -1007 | BD93: =AI93+AJ93+AK93+AL93 -> 305 | BE93: 609
B94: Deferred income taxes | AG94: -1675 | AH94: -1888 | AI94: -568 | AJ94: -1702 | AK94: -1323 | AL94: -1145 | AM94: -1433 | AN94: -1158 | AO94: =BE94-AP94-AM94-AN94 -> -2244 | AP94: -2221 | AQ94: 2491 | BD94: =AI94+AJ94+AK94+AL94 -> -4738 | BE94: -7056
B95: A/R | AG95: -1408 | AH95: -11244 | AI95: 11034 | AJ95: -2951 | AK95: -2028 | AL95: -13246 | AM95: 14037 | AN95: -5978 | AO95: =BE95-AP95-AM95-AN95 -> -2461 | AP95: -16179 | AQ95: 16490 | BD95: =AI95+AJ95+AK95+AL95 -> -7191 | BE95: -10581
B96: Inventories | AG96: 106 | AH96: 374 | AI96: -505 | AJ96: 1474 | AK96: 260 | AL96: 55 | AM96: -373 | AN96: 711 | AO96: =BE96-AP96-AM96-AN96 -> 52 | AP96: -81 | AQ96: -192 | BD96: =AI96+AJ96+AK96+AL96 -> 1284 | BE96: 309
B97: OCA | AG97: 1152 | AH97: -2419 | AI97: -796 | AJ97: 725 | AK97: 951 | AL97: -2528 | AM97: -82 | AN97: -353 | AO97: =BE97-AP97-AM97-AN97 -> 1077 | AP97: -3686 | AQ97: -1162 | BD97: =AI97+AJ97+AK97+AL97 -> -1648 | BE97: -3044
B98: ONCA | AG98: -554 | AH98: -1548 | AI98: -2013 | AJ98: -1427 | AK98: -2137 | AL98: -1240 | AM98: -1761 | AN98: -1089 | AO98: =BE98-AP98-AM98-AN98 -> -518 | AP98: 418 | AQ98: -394 | BD98: =AI98+AJ98+AK98+AL98 -> -6817 | BE98: -2950
B99: A/P | AG99: -407 | AH99: 1311 | AI99: 1214 | AJ99: -2521 | AK99: 648 | AL99: 4204 | AM99: -916 | AN99: 958 | AO99: =BE99-AP99-AM99-AN99 -> 1179 | AP99: -652 | AQ99: -614 | BD99: =AI99+AJ99+AK99+AL99 -> 3545 | BE99: 569
B100: D/R | AG100: -181 | AH100: 14224 | AI100: -4126 | AJ100: -5538 | AK100: -645 | AL100: 15657 | AM100: -5553 | AN100: -6338 | AO100: =BE100-AP100-AM100-AN100 -> -1032 | AP100: 18361 | AQ100: -5418 | BD100: =AI100+AJ100+AK100+AL100 -> 5348 | BE100: 5438
B101: Taxes | AG101: 1414 | AH101: 681 | AI101: 1425 | AJ101: -1554 | AK101: 2622 | AL101: -806 | AM101: 1016 | AN101: -3395 | AO101: =BE101-AP101-AM101-AN101 -> 1298 | AP101: 1043 | AQ101: -2944 | BD101: =AI101+AJ101+AK101+AL101 -> 1687 | BE101: -38
... B103: ONCL | AG103: 6 | AH103: 102 | AI103: 291 | AJ103: -26 | AK103: 48 | AL103: 436 | AM103: -33 | AN103: 716 | AO103: =BE103-AP103-AM103-AN103 -> -391 | AP103: -1267 | AQ103: -477 | BD103: =AI103+AJ103+AK103+AL103 -> 749 | BE103: -975
B104: CFFO | AG104: =SUM(AG90:AG103) -> 24441 | AH104: =SUM(AH90:AH103) -> 28770 | AI104: =SUM(AI90:AI103) -> 30583 | AJ104: =SUM(AJ90:AJ103) -> 18853 | AK104: =SUM(AK90:AK103) -> 31917 | AL104: =SUM(AL90:AL103) -> 37195 | AM104: =SUM(AM90:AM103) -> 34180 | AN104: =SUM(AN90:AN103) -> 22291 | ... AQ104: =SUM(AQ90:AQ103) -> 45057 | BD104: =SUM(BD90:BD103) -> 118548 | BE104: =SUM(BE90:BE103) -> 136162
B105: Debt | AH105: -1000 | AI105: =18692+7073-1500 -> 24265 | AJ105: =-8490+10773-2916 -> -633 | AK105: =-3810+6352-11589 -> -9047 | AL105: =-1142+197-13065 -> -14010 | AM105: =-5746-966 -> -6712 | AO105: =BE105-AP105-AM105-AN105 -> -2250 | BD105: =AI105+AJ105+AK105+AL105 -> 575 | BE105: =-5746-3216 -> -8962
B106: Stock | AG106: =536-5509-5059 -> -10032 | AH106: =512-5704-5054 -> -10246 | AI106: =685-4831-5051 -> -9197 | AJ106: =261-4000-5574 -> -9313 | AK106: =522-4213-5572 -> -9263 | AL106: =534-4210-5574 -> -9250 | AM106: =706-4107-5574 -> -8975 | AN106: =256-4986-6170 -> -10900 | AO106: =BE106-AP106-AM106-AN106 -> -10404 | AP106: =548-4546-6169 -> -10167 | AQ106: =689-5650-6169 -> -11130 | BD106: =AI106+AJ106+AK106+AL106 -> -37023 | BE106: =2056-18420-24082 -> -40446
B107: Other | AG107: -258 | AH107: -167 | AI107: -307 | AJ107: -201 | AK107: -498 | AL107: -303 | AM107: -889 | AN107: -343 | AO107: =BE107-AP107-AM107-AN107 -> -382 | AP107: =-677 -> -677 | AQ107: -669 | BD107: =AI107+AJ107+AK107+AL107 -> -1309 | BE107: =-2291 -> -2291
...

Sheet WACC
C2: Category | D2: Low | E2: High
C4: Long-term bond rate | D4: 0.039 | E4: 0.044
C5: Equity market risk premium | D5: 0.046 | E5: 0.056
C6: Beta | D6: 0.77 | E6: 1.06
C7: Cost of equity (CAPM) | D7: =D4+D6*D5 -> 0.07442 | E7: =E4+E6*E5 -> 0.10336
C9: Tax rate | D9: 0.176 | E9: 0.1887
C10: Debt-to-Equity ratio (Book) | D10: 0.13 | E10: 0.13
C11: Cost of debt | D11: 0.04 | E11: 0.045
C13: After-tax WACC | D13: =(D10/(1+D10))*D11*(1-D9)+(1/(1+D10))*D7 -> 0.069650265 | E13: =(E10/(1+E10))*E11*(1-E9)+(1/(1+E10))*E7 -> 0.095669119
C16: Selected WACC | D16: =GEOMEAN(D13:E13) -> 0.081629526

Sheet META
B2: FY | C2: 40543 | D2: 40908 | E2: 41274 | F2: 41639 | G2: 42004 | H2: 42369 | I2: 42735 | J2: 43100 | K2: 43465 | L2: 43830 | M2: 44196 | N2: 44561 | O2: 44926 | P2: 45291 | Q2: 45657 | R2: 46022
B3: Revenue | C3: 1974 | D3: 3711 | E3: 5089 | F3: 7872 | G3: 12466 | H3: 17928 | I3: 27638 | J3: 40653 | K3: 55838 | L3: 70697 | M3: 85965 | N3: 117929 | O3: 116609 | P3: 134902 | Q3: 164501 | R3: 200966
B4: COGS | C4: 493 | D4: 860 | E4: 1364 | F4: 1875 | G4: 2153 | H4: 2867 | I4: 3789 | J4: 5454 | K4: 9355 | L4: 12770 | M4: 16692 | N4: 22649 | O4: 25249 | P4: 25959 | Q4: 30161 | R4: 36175
B5: Gross Profit | C5: 1481 | D5: 2851 | E5: 3725 | F5: 5997 | G5: 10313 | H5: 15061 | I5: 23849 | J5: 35199 | K5: 46483 | L5: 57927 | M5: 69273 | N5: 95280 | O5: 91360 | P5: 108943 | Q5: 134340 | R5: 164791
B6: SG&A Expense | C6: 138 | D6: 314 | E6: 892 | F6: 781 | G6: 973 | H6: 1295 | I6: 1731 | J6: 2517 | K6: 3451 | L6: 10465 | M6: 6564 | N6: 9829 | O6: 11816 | P6: 11408 | Q6: 9740 | R6: 12152
B7: R&D Expense | C7: 144 | D7: 388 | E7: 1399 | F7: 1415 | G7: 2666 | H7: 4816 | I7: 5919 | J7: 7754 | K7: 10273 | L7: 13600 | M7: 18447 | N7: 24655 | O7: 35338 | P7: 38483 | Q7: 43873 | R7: 57372
B8: Operating Expenses | C8: 449 | D8: 1095 | E8: 3187 | F8: 3193 | G8: 5319 | H8: 8836 | I8: 11422 | J8: 14996 | K8: 21570 | L8: 33941 | M8: 36602 | N8: 48527 | O8: 62416 | P8: 62192 | Q8: 64960 | R8: 81515
B9: Operating Income | C9: 1032 | D9: 1756 | E9: 538 | F9: 2804 | G9: 4994 | H9: 6225 | I9: 12427 | J9: 20203 | K9: 24913 | L9: 23986 | M9: 32671 | N9: 46753 | O9: 28944 | P9: 46751 | Q9: 69380 | R9: 83276
B10: Other Income | C10: -24 | D10: -61 | E10: -44 | F10: -50 | G10: -84 | H10: -31 | I10: 91 | J10: 391 | K10: 448 | L10: 826 | M10: 509 | N10: 531 | O10: -125 | P10: 677 | Q10: 1283 | R10: 2656
B11: Pretax Income | C11: 1008 | D11: 1695 | E11: 494 | F11: 2754 | G11: 4910 | H11: 6194 | I11: 12518 | J11: 20594 | K11: 25361 | L11: 24812 | M11: 33180 | N11: 47284 | O11: 28819 | P11: 47428 | Q11: 70663 | R11: 85932
B12: Income Taxes | C12: 402 | D12: 695 | E12: 441 | F12: 1254 | G12: 1970 | H12: 2506 | I12: 2301 | J12: 4660 | K12: 3249 | L12: 6327 | M12: 4034 | N12: 7914 | O12: 5619 | P12: 8330 | Q12: 8303 | R12: 25474
B13: Net Income | C13: 606 | D13: 1000 | E13: 53 | F13: 1500 | G13: 2940 | H13: 3688 | I13: 10217 | J13: 15934 | K13: 22112 | L13: 18485 | M13: 29146 | N13: 39370 | O13: 23200 | P13: 39098 | Q13: 62360 | R13: 60458
B16: Effective tax rate | C16: =C12/C11 -> 0.39880952 | D16: =D12/D11 -> 0.4100295 | E16: =E12/E11 -> 0.89271255 | F16: =F12/F11 -> 0.45533769 | G16: =G12/G11 -> 0.401222 | H16: =H12/H11 -> 0.40458508 | I16: =I12/I11 -> 0.18381531 | J16: =J12/J11 -> 0.2262795 | ... R16: =R12/R11 -> 0.2964437
B19: Cash & Equivalents | D19: 1512 | E19: 2384 | F19: 3323 | G19: 4315 | H19: 4907 | I19: 8903 | J19: 8079 | K19: 10019 | L19: 19079 | M19: 17576 | N19: 16601 | O19: 14681 | P19: 41862 | Q19: 43889 | R19: 35873
B20: Short Term Investments | D20: 2396 | E20: 7242 | F20: 8126 | G20: 6884 | H20: 13527 | I20: 20546 | J20: 33632 | K20: 31095 | L20: 35776 | M20: 44378 | N20: 31397 | O20: 26057 | P20: 23541 | Q20: 33926 | R20: 45719
B21: Accounts Receivable | D21: 547 | E21: 719 | F21: 1109 | G21: 1678 | H21: 2559 | I21: 3993 | J21: 5832 | K21: 7587 | L21: 9518 | M21: 11335 | N21: 14039 | O21: 13466 | P21: 16169 | Q21: 16994 | R21: 19769
B22: Inventory | D22: 0 | E22: 0 | F22: 0 | G22: 0 | H22: 0 | I22: 0 | J22: 0 | K22: 0 | L22: 0 | M22: 0 | N22: 0 | O22: 0 | P22: 0 | Q22: 0 | R22: 0
B23: Other Current Assets | D23: 0 | E23: 0 | F23: 0 | G23: 0 | H23: 0 | I23: 0 | J23: 0 | K23: 0 | L23: 0 | M23: 0 | N23: 0 | O23: 0 | P23: 0 | Q23: 0 | R23: 0
B24: Current Assets | D24: 4604 | E24: 11267 | F24: 13070 | G24: 13390 | H24: 21652 | I24: 34401 | J24: 48563 | K24: 50480 | L24: 66225 | M24: 75670 | N24: 66666 | O24: 59549 | P24: 85365 | Q24: 100045 | R24: 108722
B25: PP&E | D25: 1475 | E25: 2391 | F25: 2882 | G25: 3967 | H25: 5687 | I25: 8591 | J25: 13721 | K25: 24683 | L25: 35323 | M25: 45633 | N25: 57809 | O25: 79518 | P25: 96587 | Q25: 121346 | R25: 176400
B26: Long Term Investments | D26: 0 | E26: 0 | F26: 0 | G26: 0 | H26: 0 | I26: 0 | J26: 0 | K26: 0 | L26: 86 | M26: 6234 | N26: 6775 | O26: 6201 | P26: 6141 | Q26: 6070 | R26: 27524
B27: Other Noncrnt Assets | D27: 90 | E27: 57 | F27: 221 | G27: 699 | H27: 796 | I27: 1312 | J27: 2135 | K27: 2576 | L27: 12133 | M27: 12106 | N27: 14906 | O27: 19256 | P27: 20088 | Q27: 27939 | R27: 28841
B28: Noncurrent Assets | D28: 252 | E28: 1445 | F28: 1943 | G28: 22609 | H28: 22068 | I28: 21969 | J28: 22240 | K28: 22171 | L28: 31828 | M28: 38013 | N28: 41512 | O28: 46660 | P28: 47671 | Q28: 54663 | R28: 80899
B29: Assets | D29: 6331 | E29: 15103 | F29: 17895 | G29: 39966 | H29: 49407 | I29: 64961 | J29: 84524 | K29: 97334 | L29: 133376 | M29: 159316 | N29: 165987 | O29: 185727 | P29: 229623 | Q29: 276054 | R29: 366021
B30: Short Term Debt | D30: 279 | E30: 365 | F30: 239 | G30: 114 | H30: 7 | I30: 0 | J30: 0 | K30: 0 | L30: 800 | M30: 1023 | N30: 1127 | O30: 1367 | P30: 0 | Q30: 1942 | R30: 2213
... B38: Total stockholders' equity | D38: 4899 | E38: 11755 | F38: 15470 | G38: 36096 | H38: 44218 | I38: 59194 | J38: 74347 | K38: 84127 | L38: 101054 | M38: 128290 | N38: 124879 | O38: 125713 | P38: 153168 | Q38: 182637 | R38: 217243
B39: Total liabilities and stockholders’ equity | D39: =SUM(D38+D37) -> 6331 | E39: =SUM(E38+E37) -> 15103 | F39: =SUM(F38+F37) -> 17895 | G39: =SUM(G38+G37) -> 39966 | H39: =SUM(H38+H37) -> 49407 | I39: =SUM(I38+I37) -> 64961 | J39: =SUM(J38+J37) -> 84524 | K39: =SUM(K38+K37) -> 97334 | ... R39: =SUM(R38+R37) -> 366021
B42: WACC | R42: 0.087
B43: Selected tax rate | R43: =HARMEAN(C16:R16) -> 0.22309032
B44: NOPAT | D44: =D9*(1-$R$43) -> 1364.2534 | E44: =E9*(1-$R$43) -> 417.97741 | F44: =F9*(1-$R$43) -> 2178.4547 | G44: =G9*(1-$R$43) -> 3879.8869 | H44: =H9*(1-$R$43) -> 4836.2627 | I44: =I9*(1-$R$43) -> 9654.6565 | J44: =J9*(1-$R$43) -> 15695.906 | K44: =K9*(1-$R$43) -> 19355.151 | ... R44: =R9*(1-$R$43) -> 64697.93
B45: Invested Capital | D45: =D30+D35+D38 -> 5178 | E45: =E30+E35+E38 -> 13620 | F45: =F30+F35+F38 -> 15709 | G45: =G30+G35+G38 -> 36210 | H45: =H30+H35+H38 -> 44225 | I45: =I30+I35+I38 -> 59194 | J45: =J30+J35+J38 -> 74347 | K45: =K30+K35+K38 -> 84127 | ... R45: =R30+R35+R38 -> 278200
B46: EVA | D46: =D44-D45*$R$42 -> 913.76739 | E46: =E44-E45*$R$42 -> -766.96259 | F46: =F44-F45*$R$42 -> 811.77173 | G46: =G44-G45*$R$42 -> 729.61692 | H46: =H44-H45*$R$42 -> 988.68773 | I46: =I44-I45*$R$42 -> 4504.7785 | J46: =J44-J45*$R$42 -> 9227.7172 | K46: =K44-K45*$R$42 -> 12036.102 | ... R46: =R44-R45*$R$42 -> 40494.53
B48: ROIC | D48: =D44/D45 -> 0.26347111 | E48: =E44/E45 -> 0.030688503 | F48: =F44/F45 -> 0.13867558 | G48: =G44/G45 -> 0.1071496 | H48: =H44/H45 -> 0.10935586 | I48: =I44/I45 -> 0.16310195 | J48: =J44/J45 -> 0.21111687 | K48: =K44/K45 -> 0.23007062 | ... R48: =R44/R45 -> 0.23255906

Sheet CRM
B2: FY | C2: 39813 | D2: 40178 | E2: 40543 | F2: 40908 | G2: 41274 | H2: 41639 | I2: 42004 | J2: 42369 | K2: 42735 | L2: 43100 | M2: 43465 | N2: 43830 | O2: 44196 | P2: 44561 | Q2: 44926 | R2: 45291 | S2: 45657 | T2: 46022
B3: Revenue | C3: 748.7 | D3: 1076.8 | E3: 1305.6 | F3: 1657.1 | G3: 2266.5 | H3: 3231.6 | I3: 4071 | J3: 5373.6 | K3: 6667.2 | L3: 8437 | M3: 10540 | N3: 13282 | O3: 17098 | P3: 21252 | Q3: 26492 | R3: 31352 | S3: 34857 | T3: 41525
B4: COGS | C4: 171.6 | D4: 220.5 | E4: 257.9 | F4: 323.8 | G4: 488.9 | H4: 873 | I4: 968.4 | J4: 1289.3 | K4: 1654.5 | L4: 2234 | M4: 2773 | N4: 3451 | O4: 4235 | P4: 5438 | Q4: 7026 | R4: 8360 | S4: 8541 | T4: 9270
B5: Gross Profit | C5: 577.1 | D5: 856.3 | E5: 1047.7 | F5: 1333.3 | G5: 1777.7 | H5: 2366.6 | I5: 3102.6 | J5: 4084.3 | K5: 5012.7 | L5: 6203 | M5: 7767 | N5: 9831 | O5: 12863 | P5: 15814 | Q5: 19466 | R5: 22992 | S5: 26316 | T5: 32255
B6: SG&A Expense | C6: 116.5 | D6: 158.6 | E6: 195.3 | F6: 255.9 | G6: 347.8 | H6: 433.8 | I6: 596.7 | J6: 679.9 | K6: 748.2 | L6: 966 | M6: 1089 | N6: 1346 | O6: 1704 | P6: 2087 | Q6: 2598 | R6: 2553 | S6: 2534 | T6: 3000
B7: R&D Expense | C7: 63.8 | D7: 99.5 | E7: 131.9 | F7: 187.9 | G7: 295.3 | H7: 429.5 | I7: 623.8 | J7: 792.9 | K7: 946.3 | L7: 1208 | M7: 1553 | N7: 1886 | O7: 2766 | P7: 3598 | Q7: 4465 | R7: 5055 | S7: 4906 | T7: 5993
B8: Operating Expenses | C8: 556.8 | D8: 792.6 | E8: 932.4 | F8: 1235.8 | G8: 1812.7 | H8: 2477.3 | I8: 3388.6 | J8: 4229.9 | K8: 4897.7 | L8: 5985 | M8: 7313 | N8: 9296 | O8: 12566 | P8: 15359 | Q8: 18918 | R8: 21962 | S8: 21305 | T8: 23924
B9: Operating Income | C9: 20.3 | D9: 63.7 | E9: 115.3 | F9: 97.5 | G9: -35.1 | H9: -110.7 | I9: -286.1 | J9: -145.6 | K9: 114.9 | L9: 218 | M9: 454 | N9: 535 | O9: 297 | P9: 455 | Q9: 548 | R9: 1030 | S9: 5011 | T9: 8331
B10: Other Income | C10: 25.9 | D10: 21.8 | E10: 27.1 | F10: 6.8 | G10: 1.8 | H10: -17.1 | I10: -71.9 | J10: -67.5 | K10: -50.6 | L10: -39 | M10: -34 | N10: 448 | O10: 409 | P10: 2106 | Q10: 984 | R10: -370 | S10: -61 | T10: 1189
B11: Pretax Income | C11: 46.2 | D11: 85.6 | E11: 142.4 | F11: 104.3 | G11: -33.3 | H11: -127.8 | I11: -357.9 | J11: -213.1 | K11: 64.3 | L11: 179 | M11: 420 | N11: 983 | O11: 706 | P11: 2561 | Q11: 1532 | R11: 660 | S11: 4950 | T11: 9520
B12: Income Taxes | C12: 23.4 | D12: 37.6 | E12: 57.7 | F12: 34.6 | G12: -21.7 | H12: 142.7 | I12: -125.8 | J12: 49.6 | K12: 111.7 | L12: -144 | M12: 60 | N12: -127 | O12: 580 | P12: -1511 | Q12: 88 | R12: 452 | S12: 814 | T12: 2063
B13: Net Income | C13: 22.8 | D13: 48 | E13: 84.7 | F13: 69.7 | G13: -11.6 | H13: -270.4 | I13: -232.2 | J13: -262.7 | K13: -47.4 | L13: 323 | M13: 360 | N13: 1110 | O13: 126 | P13: 4072 | Q13: 1444 | R13: 208 | S13: 4136 | T13: 7457
B15: Effective tax rate | C15: =C12/C11 -> 0.50649351 | D15: =D12/D11 -> 0.43925234 | E15: =E12/E11 -> 0.40519663 | F15: =F12/F11 -> 0.33173538 | G15: =G12/G11 -> 0.65165165 | H15: =H12/H11 -> -1.1165884 | I15: =I12/I11 -> 0.35149483 | J15: =J12/J11 -> -0.23275458 | ... T15: =T12/T11 -> 0.21670168
B18: Cash & Equivalents | D18: 483.8 | E18: 1011.3 | F18: 424.3 | G18: 607.3 | H18: 747.2 | I18: 781.6 | J18: 908.1 | K18: 1158.4 | L18: 1606.5 | M18: 2543 | N18: 2669 | O18: 4145 | P18: 6195 | Q18: 5464 | R18: 7016 | S18: 8472 | T18: 7327
B19: Short Term Investments | D19: 213.8 | E19: 230.7 | F19: 72.7 | G19: 170.6 | H19: 120.4 | I19: 57.1 | J19: 87.3 | K19: 1567 | L19: 602.3 | M19: 1978 | N19: 1673 | O19: 3802 | P19: 5771 | Q19: 5073 | R19: 5492 | S19: 5722 | T19: 2238
B20: Accounts Receivable | D20: 266.6 | E20: 321 | F20: 426.9 | G20: 683.7 | H20: 872.6 | I20: 1360.8 | J20: 1905.5 | K20: 2496.2 | L20: 3196.6 | M20: 3921 | N20: 4924 | O20: 6174 | P20: 7786 | Q20: 9739 | R20: 10755 | S20: 11414 | T20: 14339
B21: Inventory | D21: 0 | E21: 0 | F21: 0 | G21: 0 | H21: 0 | I21: 0 | J21: 0 | K21: 0 | L21: 0 | M21: 0 | N21: 0 | O21: 0 | P21: 0 | Q21: 0 | R21: 0 | S21: 0 | T21: 0
B22: Other Current Assets | D22: 39.4 | E22: 47.4 | F22: 67.8 | G22: 98.5 | H22: 142.3 | I22: 171.5 | J22: 368.6 | K22: 259.2 | L22: 311.8 | M22: 671 | N22: 788 | O22: 926 | P22: 1146 | Q22: 1454 | R22: 1776 | S22: 1905 | T22: 2075
B23: Current Assets | D23: 1068.6 | E23: 1706.2 | F23: 1074.9 | G23: 1672.2 | H23: 2015.9 | I23: 2680.3 | J23: 3514.5 | K23: 5731.3 | L23: 5996.8 | M23: 9584 | N23: 10683 | O23: 15963 | P23: 21889 | Q23: 22850 | R23: 26395 | S23: 29074 | T23: 28222
B24: PP&E | D24: 77 | E24: 89.7 | F24: 387.2 | G24: 527.9 | H24: 604.7 | I24: 1240.7 | J24: 1125.9 | K24: 1715.8 | L24: 1787.5 | M24: 1947 | N24: 2051 | O24: 2375 | P24: 2459 | Q24: 2815 | R24: 3702 | S24: 3689 | T24: 3120
B25: Long Term Investments | D25: 185 | E25: 485.1 | F25: 910.6 | G25: 669.3 | H25: 890.7 | I25: 482.2 | J25: 1185.6 | K25: 520.7 | L25: 567 | M25: 677 | N25: 1302 | O25: 1963 | P25: 3909 | Q25: 4784 | R25: 4672 | S25: 4848 | T25: 7591
B26: Other Noncrnt Assets | D26: 47.8 | E26: 67.9 | F26: 153.2 | G26: 233.3 | H26: 281 | I26: 766.9 | J26: 623 | K26: 332 | L26: 714.7 | M26: 1489 | N26: 1927 | O26: 4967 | P26: 7612 | Q26: 7845 | R26: 8387 | S26: 8314 | T26: 8616
B27: Noncurrent Assets | D27: 334.2 | E27: 664.3 | F27: 1629.1 | G27: 1964 | H27: 2908.4 | I27: 5231.9 | J27: 6024.7 | K27: 5315.8 | L27: 9800.6 | M27: 10453 | N27: 18003 | O27: 36788 | P27: 41953 | Q27: 69544 | R27: 68752 | S27: 67060 | T27: 80963
B28: Assets | D28: 1479.8 | E28: 2460.2 | F28: 3091.2 | G28: 4164.2 | H28: 5529 | I28: 9152.9 | J28: 10665.1 | K28: 12762.9 | L28: 17584.9 | M28: 21984 | N28: 30737 | O28: 55126 | P28: 66301 | Q28: 95209 | R28: 98849 | S28: 99823 | T28: 112305
B29: Short Term Debt | D29: 0 | E29: 0 | F29: 0 | G29: 496.1 | H29: 521.3 | I29: 572.2 | J29: 0 | K29: 0 | L29: 0 | M29: 1025 | N29: 0 | O29: 0 | P29: 0 | Q29: 4 | R29: 1182 | S29: 999 | T29: 4000
... B38: Liabilities And Equity | D38: 1479.8 | E38: 2460.2 | F38: 3091.2 | G38: 4164.2 | H38: 5529 | I38: 9152.9 | J38: 10665.1 | K38: 12762.9 | L38: 17584.9 | M38: 21984 | N38: 30737 | O38: 55126 | P38: 66301 | Q38: 95209 | R38: 98849 | S38: 99823 | T38: 112305
B41: Selected tax rate | T41: =AVERAGE(C15:T15) -> 0.20210023
B42: WACC | T42: 0.085
B43: NOPAT | D43: =D9*(1-$T$41) -> 50.826216 | E43: =E9*(1-$T$41) -> 91.997844 | F43: =F9*(1-$T$41) -> 77.795228 | G43: =G9*(1-$T$41) -> -28.006282 | H43: =H9*(1-$T$41) -> -88.327505 | I43: =I9*(1-$T$41) -> -228.27912 | J43: =J9*(1-$T$41) -> -116.17421 | K43: =K9*(1-$T$41) -> 91.678684 | ... T43: =T9*(1-$T$41) -> 6647.303
B44: Invested Capital | D44: =D29+D34+D37 -> 682.5 | E44: =E29+E34+E37 -> 1506.9 | F44: =F29+F34+F37 -> 1749 | G44: =G29+G34+G37 -> 2083.5 | H44: =H29+H34+H37 -> 2838.9 | I44: =I29+I34+I37 -> 4912.6 | J44: =J29+J34+J37 -> 5345.9 | K44: =K29+K34+K37 -> 6289 | ... T44: =T29+T34+T37 -> 73581
B45: EVA | D45: =D43+D44*$T$42 -> 108.83872 | E45: =E43+E44*$T$42 -> 220.08434 | F45: =F43+F44*$T$42 -> 226.46023 | G45: =G43+G44*$T$42 -> 149.09122 | H45: =H43+H44*$T$42 -> 152.979 | I45: =I43+I44*$T$42 -> 189.29188 | J45: =J43+J44*$T$42 -> 338.22729 | K45: =K43+K44*$T$42 -> 626.24368 | ... T45: =T43+T44*$T$42 -> 12901.688
B47: ROIC | D47: =D43/D44 -> 0.074470645 | E47: =E43/E44 -> 0.061051061 | F47: =F43/F44 -> 0.044479833 | G47: =G43/G44 -> -0.01344194 | H47: =H43/H44 -> -0.031113285 | I47: =I43/I44 -> -0.046468087 | J47: =J43/J44 -> -0.021731459 | K47: =K43/K44 -> 0.014577625 | ... T47: =T43/T44 -> 0.090339938

Sheet GOOG
B2: FY | C2: 39447 | D2: 39813 | E2: 40178 | F2: 40543 | G2: 40908 | H2: 41274 | I2: 41639 | J2: 42004 | K2: 42369 | L2: 42735 | M2: 43100 | N2: 43465 | O2: 43830 | P2: 44196 | Q2: 44561 | R2: 44926 | S2: 45291 | T2: 45657 | U2: 46022
B3: Revenue | C3: 16594 | D3: 21796 | E3: 23651 | F3: 29321 | G3: 37905 | H3: 46039 | I3: 55519 | J3: 66001 | K3: 74989 | L3: 90272 | M3: 110855 | N3: 136819 | O3: 161857 | P3: 182527 | Q3: 257637 | R3: 282836 | S3: 307394 | T3: 350018 | U3: 402836
B4: COGS | C4: 6649.1 | D4: 8622 | E4: 8844 | F4: 10417 | G4: 13188 | H4: 17176 | I4: 21993 | J4: 25691 | K4: 28164 | L4: 35138 | M4: 45583 | N4: 59549 | O4: 71896 | P4: 84732 | Q4: 110939 | R4: 126203 | S4: 133332 | T4: 146306 | U4: 162535
B5: Gross Profit | C5: 9944.9 | D5: 13174 | E5: 14807 | F5: 18904 | G5: 24717 | H5: 28863 | I5: 33526 | J5: 40310 | K5: 46825 | L5: 55134 | M5: 65272 | N5: 77270 | O5: 89961 | P5: 97795 | Q5: 146698 | R5: 156633 | S5: 174062 | T5: 203712 | U5: 240301
B6: SG&A Expense | C6: 1279.2 | D6: 1803 | E6: 1668 | F6: 1962 | G6: 2724 | H6: 3481 | I6: 4432 | J6: 5851 | K6: 6136 | L6: 6985 | M6: 6840 | N6: 6923 | O6: 9551 | P6: 11052 | Q6: 13510 | R6: 15724 | S6: 16425 | T6: 14188 | U6: 21482
B7: R&D Expense | C7: 2120 | D7: 2793 | E7: 2843 | F7: 3762 | G7: 5162 | H7: 6083 | I7: 7137 | J7: 9832 | K7: 12282 | L7: 13948 | M7: 16625 | N7: 21419 | O7: 26018 | P7: 27573 | Q7: 31562 | R7: 39500 | S7: 45427 | T7: 49326 | U7: 61087
B8: Operating Expenses | C8: 4860.5 | D8: 6542 | E8: 6495 | F8: 8523 | G8: 12975 | H8: 15029 | I8: 18123 | J8: 23814 | K8: 27465 | L8: 31418 | M8: 39094 | N8: 49746 | O8: 55730 | P8: 56571 | Q8: 67984 | R8: 81791 | S8: 89769 | T8: 91322 | U8: 111262
B9: Operating Income | C9: 5084.4 | D9: 6632 | E9: 8312 | F9: 10381 | G9: 11742 | H9: 13834 | I9: 15403 | J9: 16496 | K9: 19360 | L9: 23716 | M9: 26178 | N9: 27524 | O9: 34231 | P9: 41224 | Q9: 78714 | R9: 74842 | S9: 84293 | T9: 112390 | U9: 129039
B10: Other Income | C10: 589.6 | D10: -779 | E10: 69 | F10: 415 | G10: 584 | H10: 635 | I10: 496 | J10: 763 | K10: 291 | L10: 434 | M10: 1015 | N10: 7389 | O10: 5394 | P10: 6858 | Q10: 12020 | R10: -3514 | S10: 1424 | T10: 7425 | U10: 29787
B11: Pretax Income | C11: 5674 | D11: 5853 | E11: 8381 | F11: 10796 | G11: 12326 | H11: 14469 | I11: 15899 | J11: 17259 | K11: 19651 | L11: 24150 | M11: 27193 | N11: 34913 | O11: 39625 | P11: 48082 | Q11: 90734 | R11: 71328 | S11: 85717 | T11: 119815 | U11: 158826
B12: Income Taxes | C12: 1470.3 | D12: 1626 | E12: 1861 | F12: 2291 | G12: 2589 | H12: 2916 | I12: 2739 | J12: 3639 | K12: 3303 | L12: 4672 | M12: 14531 | N12: 4177 | O12: 5282 | P12: 7813 | Q12: 14701 | R12: 11356 | S12: 11922 | T12: 19697 | U12: 26656
B13: Net Income | C13: 4203.7 | D13: 4227 | E13: 6520 | F13: 8505 | G13: 9737 | H13: 10737 | I13: 12733 | J13: 14136 | K13: 16348 | L13: 19478 | M13: 12662 | N13: 30736 | O13: 34343 | P13: 40269 | Q13: 76033 | R13: 59972 | S13: 73795 | T13: 100118 | U13: 132170
B16: Effective tax rate | C16: =C12/C11 -> 0.25912936 | D16: =D12/D11 -> 0.27780625 | E16: =E12/E11 -> 0.22204987 | F16: =F12/F11 -> 0.21220823 | G16: =G12/G11 -> 0.21004381 | H16: =H12/H11 -> 0.20153431 | I16: =I12/I11 -> 0.17227499 | J16: =J12/J11 -> 0.21084651 | ... U16: =U12/U11 -> 0.16783146
B19: Cash & Equivalents | D19: 8656.7 | E19: 10198 | F19: 13630 | G19: 9983 | H19: 14778 | I19: 18898 | J19: 36694 | K19: 16549 | L19: 12918 | M19: 10715 | N19: 16701 | O19: 18498 | P19: 26465 | Q19: 20945 | R19: 21879 | S19: 24048 | T19: 23466 | U19: 30708
B20: Short Term Investments | D20: 7189.1 | E20: 14287 | F20: 22095 | G20: 35388 | H20: 34010 | I20: 39919 | J20: 93846 | K20: 56967 | L20: 73415 | M20: 91156 | N20: 92439 | O20: 101177 | P20: 110229 | Q20: 118704 | R20: 91883 | S20: 86868 | T20: 72191 | U20: 96135
B21: Accounts Receivable | D21: 2642.2 | E21: 3178 | F21: 4252 | G21: 5427 | H21: 7885 | I21: 8882 | J21: 18766 | K21: 11556 | L21: 14137 | M21: 18336 | N21: 20838 | O21: 25326 | P21: 30930 | Q21: 39304 | R21: 40258 | S21: 47964 | T21: 52340 | U21: 62886
B22: Inventory | D22: 0 | E22: 0 | F22: 0 | G22: 35 | H22: 505 | I22: 0 | J22: 0 | K22: 491 | L22: 268 | M22: 749 | N22: 1107 | O22: 999 | P22: 728 | Q22: 1170 | R22: 0 | S22: 0 | T22: 0 | U22: 0
B23: Other Current Assets | D23: 0 | E23: 0 | F23: 0 | G23: 0 | H23: 0 | I23: 0 | J23: 0 | K23: 0 | L23: 4575 | M23: 2983 | N23: 4236 | O23: 4412 | P23: 5490 | Q23: 8020 | R23: 10775 | S23: 12650 | T23: 15714 | U23: 16309
B24: Current Assets | D24: 20178.2 | E24: 29167 | F24: 41562 | G24: 52758 | H24: 60454 | I24: 72886 | J24: 157312 | K24: 90114 | L24: 105408 | M24: 124308 | N24: 135676 | O24: 152578 | P24: 174296 | Q24: 188143 | R24: 164795 | S24: 171530 | T24: 163711 | U24: 206038
B25: PP&E | D25: 5233.8 | E25: 4845 | F25: 7759 | G25: 9603 | H25: 11854 | I25: 16524 | J25: 47766 | K25: 29016 | L25: 34234 | M25: 42383 | N25: 59719 | O25: 73646 | P25: 84749 | Q25: 97599 | R25: 112668 | S25: 134345 | T25: 171036 | U25: 246597
B26: Long Term Investments | D26: 85.2 | E26: 129 | F26: 523 | G26: 790 | H26: 1469 | I26: 1976 | J26: 6158 | K26: 5183 | L26: 5878 | M26: 7813 | N26: 13859 | O26: 13078 | P26: 20703 | Q26: 29549 | R26: 30492 | S26: 31008 | T26: 37982 | U26: 68687
B27: Other Noncrnt Assets | D27: 433.8 | E27: 415 | F27: 442 | G27: 499 | H27: 2011 | I27: 1976 | J27: 6374 | K27: 3181 | L27: 1819 | M27: 2672 | N27: 2693 | O27: 13283 | P27: 16164 | Q27: 18320 | R27: 23088 | S27: 24142 | T27: 28462 | U27: 31466
B28: Noncurrent Assets | D28: 6355.6 | E28: 6485 | F28: 8530 | G28: 10213 | H28: 21490 | I28: 21510 | J28: 53296 | K28: 28331 | L28: 27855 | M28: 30604 | N28: 37397 | O28: 49685 | P28: 60571 | Q28: 73526 | R28: 87801 | S28: 96517 | T28: 115509 | U28: 142646
B29: Assets | D29: 31767.6 | E29: 40497 | F29: 57851 | G29: 72574 | H29: 93798 | I29: 110920 | J29: 258374 | K29: 147461 | L29: 167497 | M29: 197295 | N29: 232792 | O29: 275909 | P29: 319616 | Q29: 359268 | R29: 365264 | S29: 402392 | T29: 450256 | U29: 595281
B30: Short Term Debt | D30: 0 | E30: 0 | F30: 5826 | G30: 3225 | H30: 2549 | I30: 3009 | J30: 4018 | K30: 3225 | L30: 0 | M30: 0 | N30: 0 | O30: 0 | P30: 0 | Q30: 0 | R30: 0 | S30: 0 | T30: 0 | U30: 0
... B38: Total stockholders' equity | D38: 28238.9 | E38: 36004 | F38: 46241 | G38: 58145 | H38: 71715 | I38: 87309 | J38: 207720 | K38: 120331 | L38: 139036 | M38: 152502 | N38: 177628 | O38: 201442 | P38: 222544 | Q38: 251635 | R38: 256144 | S38: 283379 | T38: 325084 | U38: 415265
B39: Liabilities And Equity | D39: =D38+D37 -> 31767.6 | E39: =E38+E37 -> 40497 | F39: =F38+F37 -> 57851 | G39: =G38+G37 -> 72574 | H39: =H38+H37 -> 93798 | I39: =I38+I37 -> 110920 | J39: =J38+J37 -> 258374 | K39: =K38+K37 -> 147461 | ... U39: =U38+U37 -> 595281
B42: Selected tax rate | U42: =HARMEAN(C16:U16) -> 0.18333878
B43: WACC | U43: 0.074
B44: NOPAT | D44: =D9*(1-U42) -> 5416.0972 | E44: =E9*(1-V42) -> 8312 | F44: =F9*(1-W42) -> 10381 | G44: =G9*(1-X42) -> 11742 | H44: =H9*(1-Y42) -> 13834 | I44: =I9*(1-Z42) -> 15403 | J44: =J9*(1-AA42) -> 16496 | K44: =K9*(1-AB42) -> 19360 | ... U44: =U9*(1-AL42) -> 129039
B45: Invested Capital | D45: =D30+D35+D38 -> 28238.9 | E45: =E30+E35+E38 -> 36004 | F45: =F30+F35+F38 -> 52067 | G45: =G30+G35+G38 -> 64356 | H45: =H30+H35+H38 -> 77252 | I45: =I30+I35+I38 -> 92554 | J45: =J30+J35+J38 -> 218194 | K45: =K30+K35+K38 -> 125551 | ... U45: =U30+U35+U38 -> 461812
B46: EVA | D46: =D44-D45*$U$43 -> 3326.4186 | E46: =E44-E45*$U$43 -> 5647.704 | F46: =F44-F45*$U$43 -> 6528.042 | G46: =G44-G45*$U$43 -> 6979.656 | H46: =H44-H45*$U$43 -> 8117.352 | I46: =I44-I45*$U$43 -> 8554.004 | J46: =J44-J45*$U$43 -> 349.644 | K46: =K44-K45*$U$43 -> 10069.226 | ... U46: =U44-U45*$U$43 -> 94864.912
B48: ROIC | D48: =D44/D45 -> 0.19179561 | E48: =E44/E45 -> 0.23086324 | F48: =F44/F45 -> 0.19937772 | G48: =G44/G45 -> 0.18245385 | H48: =H44/H45 -> 0.17907627 | I48: =I44/I45 -> 0.16642176 | J48: =J44/J45 -> 0.075602446 | K48: =K44/K45 -> 0.15420029 | ... U48: =U44/U45 -> 0.2794189
