Workbook

Sheet Main
A1: Main
B5: Segment | C5: Product | D5: % | E5: Employees
B6: Cloud | C6: Oracle Applications, Oracle Database and Oracle Middleware software offerings | D6: =(Model!V3+Model!V4)/Model!V7 -> 0.83956119 | E6: 29000 | J6: Price | K6: 338.36
B7: Hardware | C7: Oracle Engineered Systems, servers, storage and industry-specific products, among others. | D7: =Model!V5/Model!V7 -> 0.057891656 | E7: 3000 | J7: S/O | K7: 2805 | L7: Q126
B8: Software | D8: =+Model!V3/Model!V4 -> 7.7510333 | E8: 37000 | J8: MC | K8: =K6*K7 -> 949099.8
J9: Cash | K9: =+Model!K51+Model!K52 -> 11005 | L9: Q126
B10: R&D | E10: 50000 | J10: Debt | K10: =+Model!K61+Model!K66 -> 91315 | L10: Q126
B11: S&M | E11: 31000
B12: G&A | E12: 12000 | J12: EV | K12: =K8-K9+K10 -> 1029409.8
E13: =SUM(E6:E12) -> 162000
B16: Oracle, Java, MySQL, and NetSuite are registered trademarks of Oracle Corporation. NetSuite was the first cloud company—ushering in the new era of cloud computing.

Sheet Model
A1: Main | J1: 45808
C2: Q124 | D2: Q224 | E2: Q324 | F2: Q424 | G2: Q125 | H2: Q225 | I2: Q325 | J2: Q425 | K2: Q126 | L2: Q226 | M2: Q326 | N2: Q426 | O2: Q127 | P2: Q227 | T2: 2024 | U2: 2025 | V2: FY24 | W2: FY25 | X2: FY26 | Y2: FY27 | Z2: FY28 | AA2: FY29 | AB2: FY30 | AC2: FY31 | AD2: FY32 | AE2: FY33 | AF2: FY34 | AG2: FY35 | AH2: FY36 | AI2: FY37 | AJ2: FY38 | AK2: FY39 | AL2: FY40 | AM2: FY41 | AN2: FY42 | AO2: FY43 | AP2: FY44 | AQ2: FY45
B3: Cloud services and license support | C3: 9547 | D3: 9639 | E3: 9963 | F3: 10234 | G3: 10519 | H3: 10806 | I3: 11007 | J3: 11698 | K3: 7186 | V3: 39383 | W3: 44029
B4: Cloud license and on-premise license | C4: 809 | D4: 1178 | E4: 1256 | F4: 1838 | G4: 870 | H4: 1195 | I4: 1129 | J4: 2007 | K4: 5721 | V4: 5081 | W4: 5201
B5: Hardware | C5: 714 | D5: 756 | E5: 754 | F5: 842 | G5: 655 | H5: 728 | I5: 703 | J5: 850 | K5: 670 | V5: 3066 | W5: 2936
B6: Services | C6: 1383 | D6: 1368 | E6: 1307 | F6: 1373 | G6: 1263 | H6: 1330 | I6: 1291 | J6: 1348 | K6: 1349 | V6: 5431 | W6: 5233
B7: Total revenues | C7: =SUM(C3:C6) -> 12453 | D7: =SUM(D3:D6) -> 12941 | E7: =SUM(E3:E6) -> 13280 | F7: =SUM(F3:F6) -> 14287 | G7: =SUM(G3:G6) -> 13307 | H7: =SUM(H3:H6) -> 14059 | I7: =SUM(I3:I6) -> 14130 | J7: =SUM(J3:J6) -> 15903 | ... O7: =SUM(O3:O6) -> 0 | T7: =SUM(F7:I7) -> 55783 | U7: =+J7+15040+16200+16730 -> 63873 | V7: =SUM(V3:V6) -> 52961 | W7: =SUM(W3:W6) -> 57399 | X7: 66760 | Y7: 80050 | Z7: =(Y112*Y113)/0.86 -> 108882.9 | AA7: =(Z112*Z113)/0.87 -> 133904.77 | AB7: =(AA112*AA113)/0.87 -> 166566.53 | AC7: =(AB112*AB113)/0.87 -> 207164.59 | AD7: =(AC112*AC113)/0.88 -> 228269.99 | AE7: =(AD112*AD113)/0.88 -> 254380.96 | AF7: =(AE112*AE113)/0.89 -> 280255.13 | AG7: =(AF112*AF113)/0.89 -> 312227.93 | AH7: =(AG112*AG113)/0.9 -> 343938.36
B8: Cloud services and license support costs | C8: 2179 | D8: 2274 | E8: 2452 | F8: 2522 | G8: 2597 | H8: 2746 | I8: 2882 | J8: 3343 | K8: 3607 | V8: 9427 | W8: 11569
B9: Hardware | C9: 219 | D9: 213 | E9: 217 | F9: 241 | G9: 162 | H9: 172 | I9: 197 | J9: 252 | K9: 178 | V9: 891 | W9: 782
B10: Services | C10: 1212 | D10: 1253 | E10: 1200 | F10: 1160 | G10: 1147 | H10: 1167 | I10: 1116 | J10: 1145 | K10: 1099 | V10: 4825 | W10: 4576
B11: COGS | C11: =SUM(C8:C10) -> 3610 | D11: =SUM(D8:D10) -> 3740 | E11: =SUM(E8:E10) -> 3869 | F11: =SUM(F8:F10) -> 3923 | G11: =SUM(G8:G10) -> 3906 | H11: =SUM(H8:H10) -> 4085 | I11: =SUM(I8:I10) -> 4195 | J11: =SUM(J8:J10) -> 4740 | ... O11: =SUM(O8:O10) -> 0 | V11: =SUM(V8:V10) -> 15143 | W11: =SUM(W8:W10) -> 16927
B12: Gross Profit | C12: =C7-C11 -> 8843 | D12: =D7-D11 -> 9201 | E12: =E7-E11 -> 9411 | F12: =F7-F11 -> 10364 | G12: =G7-G11 -> 9401 | H12: =H7-H11 -> 9974 | I12: =I7-I11 -> 9935 | J12: =J7-J11 -> 11163 | ... O12: =O7-O11 -> 0 | V12: =V7-V11 -> 37818 | W12: =W7-W11 -> 40472
B13: S&M | C13: 2026 | D13: 2093 | E13: 2042 | F13: 2114 | G13: 2036 | H13: 2190 | I13: 2119 | J13: 2306 | K13: 2063 | V13: 8274 | W13: 8651
B14: R&D | C14: 2216 | D14: 2226 | E14: 2248 | F14: 2226 | G14: 2306 | H14: 2471 | I14: 2429 | J14: 2654 | K14: 2491 | V14: 8915 | W14: 9860
B15: G&A | C15: 393 | D15: 375 | E15: 377 | F15: 402 | G15: 358 | H15: 387 | I15: 390 | J15: 467 | K15: 376 | V15: 1548 | W15: 1602
B16: Amortization | C16: 763 | D16: 755 | E16: 749 | F16: 743 | G16: 624 | H16: 591 | I16: 548 | J16: 544 | K16: 420 | V16: 3010 | W16: 2307
B17: Acquisition related and other | C17: 11 | D17: 47 | E17: 155 | F17: 101 | G17: 13 | H17: 31 | I17: 28 | J17: 4 | K17: 13 | V17: 314 | W17: 75
B18: Restructuring | C18: 138 | D18: 83 | E18: 90 | F18: 92 | G18: 73 | H18: 84 | I18: 63 | J18: 79 | K18: 402 | V18: 404 | W18: 299
B19: Operating expenses | C19: =SUM(C13:C18) -> 5547 | D19: =SUM(D13:D18) -> 5579 | E19: =SUM(E13:E18) -> 5661 | F19: =SUM(F13:F18) -> 5678 | G19: =SUM(G13:G18) -> 5410 | H19: =SUM(H13:H18) -> 5754 | I19: =SUM(I13:I18) -> 5577 | J19: =SUM(J13:J18) -> 6054 | ... O19: =SUM(O13:O18) -> 0 | V19: =SUM(V13:V18) -> 22465 | W19: =SUM(W13:W18) -> 22794
B20: Operating Profit | C20: =C12-C19 -> 3296 | D20: =D12-D19 -> 3622 | E20: =E12-E19 -> 3750 | F20: =F12-F19 -> 4686 | G20: =G12-G19 -> 3991 | H20: =H12-H19 -> 4220 | I20: =I12-I19 -> 4358 | J20: =J12-J19 -> 5109 | ... O20: =O12-O19 -> 0 | V20: =V12-V19 -> 15353 | W20: =W12-W19 -> 17678
B21: Interest income | C21: =-872-49 -> -921 | D21: =-888-14 -> -902 | E21: =-876-9 -> -885 | F21: =-878-26 -> -904 | G21: =-842+20 -> -822 | H21: =-866+36 -> -830 | I21: =-892-18 -> -910 | J21: =-978+20 -> -958 | K21: =-923+73 -> -850 | V21: =-3514-98 -> -3612 | W21: =-3578+60 -> -3518
B22: Pretax Income | C22: =C20+C21 -> 2375 | D22: =D20+D21 -> 2720 | E22: =E20+E21 -> 2865 | F22: =F20+F21 -> 3782 | G22: =G20+G21 -> 3169 | H22: =H20+H21 -> 3390 | I22: =I20+I21 -> 3448 | J22: =J20+J21 -> 4151 | ... O22: =O20+O21 -> 0 | V22: =V20+V21 -> 11741 | W22: =W20+W21 -> 14160
B23: Taxes | C23: -45 | D23: 217 | E23: 464 | F23: 639 | G23: 240 | H23: 239 | I23: 512 | J23: 724 | K23: 500 | V23: 1274 | W23: 1717
B24: Net Income | C24: =C22-C23 -> 2420 | D24: =D22-D23 -> 2503 | E24: =E22-E23 -> 2401 | F24: =F22-F23 -> 3143 | G24: =G22-G23 -> 2929 | H24: =H22-H23 -> 3151 | I24: =I22-I23 -> 2936 | J24: =J22-J23 -> 3427 | ... O24: =O22-O23 -> 0 | V24: =V22-V23 -> 10467 | W24: =W22-W23 -> 12443 | X24: 14730 | Y24: 19260 | Z24: =+Z7*Z37 -> 27245.072 | AA24: =+AA7*AA37 -> 34846.381 | AB24: =+AB7*AB37 -> 45079.875 | AC24: =+AC7*AC37 -> 58310.105 | AD24: =+AD7*AD37 -> 65535.601 | AE24: =+AE7*AE37 -> 74492.621 | AF24: =+AF7*AF37 -> 83710.974 | AG24: =+AG7*AG37 -> 95126.329 | AH24: =+AH7*AH37 -> 106883.28 | AI24: =+AH24*(1.01) -> 107952.11 | AJ24: =+AI24*(1.01) -> 109031.64 | AK24: =+AJ24*(1.01) -> 110121.95 | AL24: =+AK24*(1.01) -> 111223.17 | AM24: =+AL24*(1.01) -> 112335.4 | AN24: =+AM24*(1.01) -> 113458.76 | AO24: =+AN24*(1.01) -> 114593.34 | AP24: =+AO24*(1.01) -> 115739.28 | AQ24: =+AP24*(1.01) -> 116896.67 | AR24: =+AQ24*(1+$AL$26) -> 115727.7 | AS24: =+AR24*(1+$AL$26) -> 114570.43 | AT24: =+AS24*(1+$AL$26) -> 113424.72 | AU24: =+AT24*(1+$AL$26) -> 112290.48 | AV24: =+AU24*(1+$AL$26) -> 111167.57 | AW24: =+AV24*(1+$AL$26) -> 110055.9 | AX24: =+AW24*(1+$AL$26) -> 108955.34 | AY24: =+AX24*(1+$AL$26) -> 107865.78 | ... AKN24: =+AKM24*(1+$AL$26) -> 9.8955219
B25: SO | C25: 2728 | D25: 2746 | E25: 2748 | F25: 2753 | G25: 2761 | H25: 2790 | I25: 2799 | J25: 2805 | K25: 2826 | V25: 2753 | W25: 2805
B26: EPS | C26: =C24/C25 -> 0.88709677 | D26: =D24/D25 -> 0.91150765 | E26: =E24/E25 -> 0.87372635 | F26: =F24/F25 -> 1.1416636 | G26: =G24/G25 -> 1.0608475 | H26: =H24/H25 -> 1.1293907 | I26: =I24/I25 -> 1.0489461 | J26: =J24/J25 -> 1.2217469 | ... O26: =O24/O25 -> #DIV/0! | V26: =V24/V25 -> 3.8020341 | W26: =W24/W25 -> 4.4360071 | AK26: Maturity | AL26: -0.01
AK27: Discount | AL27: 0.08
B28: Non-GAAP NI | C28: 3358 | D28: 3762 | E28: 3982 | F28: 4607 | G28: 3964 | H28: 4207 | I28: 4231 | J28: 4881 | K28: 4283 | V28: 15710 | W28: 17284 | AK28: NPV | AL28: =NPV(AL27,Y24:AKN24)+X24+W50 -> 923580.87
B29: Non-GAAP EPS | C29: =C28/C25 -> 1.2309384 | D29: =D28/D25 -> 1.3699927 | E29: =E28/E25 -> 1.4490539 | F29: =F28/F25 -> 1.6734471 | G29: =G28/G25 -> 1.4357117 | H29: =H28/H25 -> 1.5078853 | I29: =I28/I25 -> 1.5116113 | J29: =J28/J25 -> 1.740107 | ... M29: =M28/M25 -> #DIV/0! | V29: =V28/V25 -> 5.706502 | W29: =W28/W25 -> 6.1618538 | AK29: Share | AL29: =+AL28/W25 -> 329.26234
AK30: Current | AL30: =Main!K6 -> 338.36
B31: Cloud % | C31: =SUM(C3:C4)/C7 -> 0.83160684 | D31: =SUM(D3:D4)/D7 -> 0.83587049 | E31: =SUM(E3:E4)/E7 -> 0.84480422 | F31: =SUM(F3:F4)/F7 -> 0.84496395 | G31: =SUM(G3:G4)/G7 -> 0.85586533 | H31: =SUM(H3:H4)/H7 -> 0.8536169 | I31: =SUM(I3:I4)/I7 -> 0.85888181 | J31: =SUM(J3:J4)/J7 -> 0.86178708 | ... M31: =SUM(M3:M4)/M7 -> #DIV/0! | V31: =SUM(V3:V4)/V7 -> 0.83956119 | W31: =SUM(W3:W4)/W7 -> 0.85768045 | AK31: Return | AL31: =AL29/AL30-1 -> -0.026887509
B32: Cloud Y/Y | G32: =SUM(G3:G4)/SUM(C3:C4)-1 -> 0.099748938 | H32: =SUM(H3:H4)/SUM(D3:D4)-1 -> 0.10945734 | I32: =SUM(I3:I4)/SUM(E3:E4)-1 -> 0.08173634 | J32: =SUM(J3:J4)/SUM(F3:F4)-1 -> 0.1352717 | K32: =SUM(K3:K4)/SUM(G3:G4)-1 -> 0.1332865 | L32: =SUM(L3:L4)/SUM(H3:H4)-1 -> -1 | M32: =SUM(M3:M4)/SUM(I3:I4)-1 -> -1 | W32: =SUM(W3:W4)/SUM(V3:V4)-1 -> 0.10718784
B33: Cloud % Y/Y | G33: =(SUM(G3:G4)/G7)/(SUM(C3:C4)/C7)-1 -> 0.029170626 | H33: =(SUM(H3:H4)/H7)/(SUM(D3:D4)/D7)-1 -> 0.021231053 | I33: =(SUM(I3:I4)/I7)/(SUM(E3:E4)/E7)-1 -> 0.016663737 | J33: =(SUM(J3:J4)/J7)/(SUM(F3:F4)/F7)-1 -> 0.01990988 | K33: =(SUM(K3:K4)/K7)/(SUM(G3:G4)/G7)-1 -> 0.01036068 | L33: =(SUM(L3:L4)/L7)/(SUM(H3:H4)/H7)-1 -> #DIV/0! | M33: =(SUM(M3:M4)/M7)/(SUM(I3:I4)/I7)-1 -> #DIV/0! | W33: =(SUM(W3:W4)/W7)/(SUM(V3:V4)/V7)-1 -> 0.021581823
B35: Gross Margin | C35: =C12/C7 -> 0.71011001 | D35: =D12/D7 -> 0.71099606 | E35: =E12/E7 -> 0.70865964 | F35: =F12/F7 -> 0.72541471 | G35: =G12/G7 -> 0.70647028 | H35: =H12/H7 -> 0.70943879 | I35: =I12/I7 -> 0.70311394 | J35: =J12/J7 -> 0.70194303 | ... M35: =M12/M7 -> #DIV/0! | V35: =V12/V7 -> 0.71407262 | W35: =W12/W7 -> 0.70509939
B36: Operating Margin | C36: =C20/C7 -> 0.26467518 | D36: =D20/D7 -> 0.27988563 | E36: =E20/E7 -> 0.28237952 | F36: =F20/F7 -> 0.32799048 | G36: =G20/G7 -> 0.29991734 | H36: =H20/H7 -> 0.3001636 | I36: =I20/I7 -> 0.3084218 | J36: =J20/J7 -> 0.32126014 | ... M36: =M20/M7 -> #DIV/0! | V36: =V20/V7 -> 0.28989256 | W36: =W20/W7 -> 0.30798446
B37: Net Margin | C37: =C24/C7 -> 0.19433068 | D37: =D24/D7 -> 0.19341627 | E37: =E24/E7 -> 0.18079819 | F37: =F24/F7 -> 0.2199902 | G37: =G24/G7 -> 0.22010972 | H37: =H24/H7 -> 0.22412689 | I37: =I24/I7 -> 0.20778485 | J37: =J24/J7 -> 0.21549393 | ... M37: =M24/M7 -> #DIV/0! | V37: =V24/V7 -> 0.197636 | W37: =W24/W7 -> 0.21678078 | X37: =X24/X7 -> 0.2206411 | Y37: =Y24/Y7 -> 0.24059963 | Z37: =Y37*1.04 -> 0.25022361 | AA37: =Z37*1.04 -> 0.26023255 | AB37: =AA37*1.04 -> 0.27064186 | AC37: =AB37*1.04 -> 0.28146753 | AD37: =AC37*1.02 -> 0.28709688 | AE37: =AD37*1.02 -> 0.29283882 | AF37: =AE37*1.02 -> 0.2986956 | AG37: =AF37*1.02 -> 0.30466951 | AH37: =AG37*1.02 -> 0.3107629
B39: Tax Margin | C39: =C23/C22 -> -0.018947368 | D39: =D23/D22 -> 0.079779412 | E39: =E23/E22 -> 0.16195462 | F39: =F23/F22 -> 0.16895822 | G39: =G23/G22 -> 0.07573367 | H39: =H23/H22 -> 0.070501475 | I39: =I23/I22 -> 0.14849188 | J39: =J23/J22 -> 0.1744158 | ... M39: =M23/M22 -> #DIV/0! | V39: =V23/V22 -> 0.10850864 | W39: =W23/W22 -> 0.12125706
B40: R&D Margin | C40: =C14/C12 -> 0.25059369 | D40: =D14/D12 -> 0.24193022 | E40: =E14/E12 -> 0.23886941 | F40: =F14/F12 -> 0.21478194 | G40: =G14/G12 -> 0.24529305 | H40: =H14/H12 -> 0.24774413 | I40: =I14/I12 -> 0.24448918 | J40: =J14/J12 -> 0.23774971 | ... M40: =M14/M12 -> #DIV/0! | V40: =V14/V12 -> 0.23573431 | W40: =W14/W12 -> 0.24362522
B41: S&M Margin | C41: =C13/C12 -> 0.22910777 | D41: =D13/D12 -> 0.22747527 | E41: =E13/E12 -> 0.21698013 | F41: =F13/F12 -> 0.2039753 | G41: =G13/G12 -> 0.21657271 | H41: =H13/H12 -> 0.21957088 | I41: =I13/I12 -> 0.21328636 | J41: =J13/J12 -> 0.20657529 | ... M41: =M13/M12 -> #DIV/0! | V41: =V13/V12 -> 0.21878471 | W41: =W13/W12 -> 0.21375272
B42: G&A Margin | C42: =C15/C12 -> 0.044441931 | D42: =D15/D12 -> 0.04075644 | E42: =E15/E12 -> 0.040059505 | F42: =F15/F12 -> 0.038788113 | G42: =G15/G12 -> 0.038081055 | H42: =H15/H12 -> 0.038800882 | I42: =I15/I12 -> 0.039255159 | J42: =J15/J12 -> 0.041834632 | ... M42: =M15/M12 -> #DIV/0! | V42: =V15/V12 -> 0.040932889 | W42: =W15/W12 -> 0.039582922
B43: Interest Margin | C43: =C21/C20 -> -0.27942961 | D43: =D21/D20 -> -0.24903368 | E43: =E21/E20 -> -0.236 | F43: =F21/F20 -> -0.19291507 | G43: =G21/G20 -> -0.20596342 | H43: =H21/H20 -> -0.19668246 | I43: =I21/I20 -> -0.20881138 | J43: =J21/J20 -> -0.18751223 | ... M43: =M21/M20 -> #DIV/0! | V43: =V21/V20 -> -0.23526347 | W43: =W21/W20 -> -0.19900441
B45: Revenue y/y | G45: =G7/C7-1 -> 0.068577853 | H45: =H7/D7-1 -> 0.086392087 | I45: =I7/E7-1 -> 0.064006024 | J45: =J7/F7-1 -> 0.11310982 | K45: =K7/G7-1 -> 0.12166529 | L45: =L7/H7-1 -> -1 | M45: =M7/I7-1 -> -1 | W45: =W7/V7-1 -> 0.083797511 | X45: =X7/W7-1 -> 0.16308646 | Y45: =Y7/X7-1 -> 0.1990713 | Z45: =Z7/Y7-1 -> 0.36018614 | AA45: =AA7/Z7-1 -> 0.22980533 | AB45: =AB7/AA7-1 -> 0.24391782 | AC45: =AC7/AB7-1 -> 0.24373479 | AD45: =AD7/AC7-1 -> 0.10187743 | ... AG45: =AG7/AF7-1 -> 0.11408461
B46: EPS y/y | G46: =G26/C26-1 -> 0.19586448 | H46: =H26/D26-1 -> 0.23903588 | I46: =I26/E26-1 -> 0.200543 | J46: =J26/F26-1 -> 0.07014609 | K46: =K26/G26-1 -> -0.023667829 | L46: =L26/H26-1 -> #DIV/0! | M46: =M26/I26-1 -> #DIV/0! | W46: =W29/V29-1 -> 0.079795264
B50: Net Cash | F50: =+F51+F52-F61-F66 -> -76208 | G50: =+G51+G52-G61-G66 -> -73604 | H50: =+H51+H52-H61-H66 -> -77313 | I50: =+I51+I52-I61-I66 -> -78453 | J50: =+J51+J52-J61-J66 -> -81365 | K50: =+K51+K52-K61-K66 -> -80310 | V50: =V51+V52-V61-V66 -> -76208 | W50: =W51+W52-W61-W66 -> -81365
B51: Cash & equivalents | F51: 10454 | G51: 10616 | H51: 10941 | I51: 17406 | J51: 10786 | K51: 10445 | V51: 10454 | W51: 10786
B52: Marketable securities | F52: 207 | G52: 295 | H52: 370 | I52: 417 | J52: 417 | K52: 560 | V52: 207 | W52: 417
B53: A/R | F53: 7874 | G53: 8021 | H53: 8177 | I53: 8051 | J53: 8558 | K53: 8843 | V53: 7874 | W53: 8558
B54: Prepaids | F54: 4019 | G54: 4140 | H54: 4015 | I54: 4242 | J54: 4818 | K54: 4786 | V54: 4019 | W54: 4818
B55: PP&A | F55: 21536 | G55: 23094 | H55: 26432 | I55: 31970 | J55: 43522 | K55: 53194 | V55: 21536 | W55: 43522
B56: Intangibles | F56: 6890 | G56: 6270 | H56: 5679 | I56: 5131 | J56: 4587 | K56: 4167 | V56: 6890 | W56: 4587
B57: Goodwill | F57: 62230 | G57: 62249 | H57: 62204 | I57: 62171 | J57: 62207 | K57: 62211 | V57: 62230 | W57: 62207
B58: Deferred tax | F58: 12273 | G58: 12219 | H58: 11984 | I58: 11799 | J58: 11877 | K58: 11734 | V58: 12273 | W58: 11877
B59: ONCA | F59: 15493 | G59: 17310 | H59: 18681 | I59: 20191 | J59: 21589 | K59: 24509 | V59: 15493 | W59: 21589
B60: Total Assets | F60: =SUM(F51:F59) -> 140976 | G60: =SUM(G51:G59) -> 144214 | H60: =SUM(H51:H59) -> 148483 | I60: =SUM(I51:I59) -> 161378 | J60: =SUM(J51:J59) -> 168361 | K60: =SUM(K51:K59) -> 180449 | V60: =SUM(V51:V59) -> 140976 | W60: =SUM(W51:W59) -> 168361
B61: Current debt | F61: 10605 | G61: 9201 | H61: 8162 | I61: 8167 | J61: 7271 | K61: 9079 | V61: 10605 | W61: 7271
B62: A/P | F62: 2357 | G62: 2207 | H62: 2679 | I62: 2423 | J62: 5113 | K62: 8203 | V62: 2357 | W62: 5113
B63: Accrued compensation | F63: 1916 | G63: 1772 | H63: 1653 | I63: 1839 | J63: 2243 | K63: 1794 | V63: 1916 | W63: 2243
B64: Deferred revenues | F64: 9313 | G64: 11455 | H64: 9430 | I64: 9019 | J64: 9387 | K64: 12098 | V64: 9313 | W64: 9387
B65: OCL | F65: 7353 | G65: 7410 | H65: 7128 | I65: 8175 | J65: 8629 | K65: 8700 | V65: 7353 | W65: 8629
B66: Non-current debt | F66: 76264 | G66: 75314 | H66: 80462 | I66: 88109 | J66: 85297 | K66: 82236 | V66: 76264 | W66: 85297
B67: Income taxes | F67: 10817 | G67: 11038 | H67: 9553 | I67: 9813 | J67: 10269 | K67: 10583 | V67: 10817 | W67: 10269
B68: Operating lease | F68: 6255 | G68: 3442 | H68: 2864 | I68: 2208 | J68: 11536 | K68: 14094 | V68: 6255 | W68: 11536
B69: ONCL | F69: 6857 | G69: 11106 | H69: 12316 | I69: 14364 | J69: 7647 | K69: 8996 | V69: 6857 | W69: 7647
B70: Total Liabilities | F70: =SUM(F61:F69) -> 131737 | G70: =SUM(G61:G69) -> 132945 | H70: =SUM(H61:H69) -> 134247 | I70: =SUM(I61:I69) -> 144117 | J70: =SUM(J61:J69) -> 147392 | K70: =SUM(K61:K69) -> 155783 | V70: =SUM(V61:V69) -> 131737 | W70: =SUM(W61:W69) -> 147392
B71: SE | F71: 9239 | G71: 11269 | H71: 14236 | I71: 17261 | J71: 20969 | K71: 24666 | V71: 9239 | W71: 20969
B72: L+SE | F72: =F70+F71 -> 140976 | G72: =G70+G71 -> 144214 | H72: =H70+H71 -> 148483 | I72: =I70+I71 -> 161378 | J72: =J70+J71 -> 168361 | K72: =K70+K71 -> 180449 | V72: =V70+V71 -> 140976 | W72: =W70+W71 -> 168361
B76: Reported NI | C76: =C24 -> 2420 | D76: =D24 -> 2503 | E76: =E24 -> 2401 | F76: =F24 -> 3143 | G76: =G24 -> 2929 | H76: =H24 -> 3151 | I76: =I24 -> 2936 | J76: =J24 -> 3427 | K76: =K24 -> 2927 | V76: =V24 -> 10467 | W76: =W24 -> 12443
B77: GAAP NI | C77: 2420 | D77: 2503 | E77: 2400 | F77: 3144 | G77: 2929 | H77: =6080-G77 -> 3151 | I77: 2936 | J77: 3427 | K77: 2927 | V77: 10467 | W77: 12443
B78: Depriciation | C78: 712 | D78: 798 | E78: 808 | F78: 811 | G78: 804 | H78: =1712-G78 -> 908 | I78: 1003 | J78: 1152 | K78: 1351 | V78: 3129 | W78: 3867
B79: Amortization | C79: 763 | D79: 755 | E79: 749 | F79: 743 | G79: 624 | H79: =1215-G79 -> 591 | I79: 548 | J79: 544 | K79: 420 | V79: 3010 | W79: 2307
B80: Deferred income taxes | C80: -517 | D80: -532 | E80: -706 | F80: -384 | G80: -151 | H80: =-601-G80 -> -450 | I80: -496 | J80: -540 | K80: 515 | V80: -2139 | W80: -1637
B81: Stock-based compensation | C81: 849 | D81: 1029 | E81: 1049 | F81: 1047 | G81: 1007 | H81: =2176-G81 -> 1169 | I81: 1198 | J81: 1300 | K81: 1124 | V81: 3974 | W81: 4674
B82: Other | C82: 169 | D82: 162 | E82: 300 | F82: 89 | G82: 130 | H82: =298-G82 -> 168 | I82: 124 | J82: 245 | K82: 164 | V82: 720 | W82: 667
B83: A/R | C83: 380 | D83: -235 | E83: -554 | F83: -556 | G83: -81 | H83: =-451-G83 -> -370 | I83: 139 | J83: -341 | K83: -245 | V83: -965 | W83: -653
B84: Prepaids | C84: 269 | D84: 32 | E84: 156 | F84: 85 | G84: 367 | H84: =676-G84 -> 309 | I84: -73 | J84: -337 | K84: 59 | V84: 542 | W84: 266
B85: A/P | C85: -457 | D85: -591 | E85: 366 | F85: 88 | G85: -531 | H85: =-1143-G85 -> -612 | I85: 510 | J85: 25 | K85: -334 | V85: -594 | W85: -608
B86: Income taxes payable | C86: 69 | D86: -1610 | E86: 753 | F86: 661 | G86: 24 | H86: =-1685-G86 -> -1709 | I86: 463 | J86: 563 | K86: -391 | V86: -127 | W86: -659
B87: Deferred revenues | C87: 2317 | D87: -2168 | E87: 154 | F87: 353 | G87: 2305 | H87: =454-G87 -> -1851 | I87: -419 | J87: 119 | K87: 2550 | V87: 656 | W87: 154
B88: CFFO | C88: =SUM(C77:C87) -> 6974 | D88: =SUM(D77:D87) -> 143 | E88: =SUM(E77:E87) -> 5475 | F88: =SUM(F77:F87) -> 6081 | G88: =SUM(G77:G87) -> 7427 | H88: =SUM(H77:H87) -> 1304 | I88: =SUM(I77:I87) -> 5933 | J88: =SUM(J77:J87) -> 6157 | K88: =SUM(K77:K87) -> 8140 | V88: =SUM(V77:V87) -> 18673 | W88: =SUM(W77:W87) -> 20821
B89: Purchase of marketable securities | C89: -333 | D89: -182 | E89: -159 | F89: -329 | G89: -477 | H89: =-636-G89 -> -159 | I89: -202 | J89: -434 | K89: -471 | V89: -1003 | W89: -1272
B90: Proceeds from marketable securities | C90: 85 | D90: 72 | E90: 50 | F90: 365 | G90: 15 | H90: =356-G90 -> 341 | I90: 88 | J90: 332 | K90: 255 | V90: 572 | W90: 776
B91: Acquisitions | D91: -59 | E91: 0 | F91: -4 | I91: 0 | J91: 0 | K91: 0 | V91: -63
B92: CapEx | C92: -1314 | D92: -1080 | E92: -1674 | F92: -2798 | G92: -2303 | H92: =-6273-G92 -> -3970 | I92: -5862 | J92: -9080 | K92: -8502 | V92: -6866 | W92: -21215
B93: CFFI | C93: =SUM(C89:C92) -> -1562 | D93: =SUM(D89:D92) -> -1249 | E93: =SUM(E89:E92) -> -1783 | F93: =SUM(F89:F92) -> -2766 | G93: =SUM(G89:G92) -> -2765 | H93: =SUM(H89:H92) -> -3788 | I93: =SUM(I89:I92) -> -5976 | J93: =SUM(J89:J92) -> -9182 | K93: =SUM(K89:K92) -> -8718 | V93: =SUM(V89:V92) -> -7360 | W93: =SUM(W89:W92) -> -21711
B94: Stock repurchases | C94: -150 | D94: -450 | E94: -450 | F94: -152 | G94: -150 | H94: -150 | I94: -150 | J94: -150 | K94: -95 | V94: -1202 | W94: -600
B95: Stock issuance | C95: 308 | D95: 118 | E95: 28 | F95: 288 | G95: 179 | H95: 128 | I95: 213 | J95: 133 | K95: 1170 | V95: 742 | W95: 653
B96: Shares repurchased for tax witholdings | C96: -1060 | D96: -673 | E96: -132 | F96: -175 | G96: -851 | H96: -47 | I96: -2 | J96: 0 | K96: -17 | V96: -2040 | W96: -900
B97: Dividends | C97: -1091 | D97: -1099 | E97: -1099 | F97: -1102 | G97: -1103 | H97: -1118 | I97: -1119 | J97: -1403 | K97: -1413 | V97: -4391 | W97: -4743
B98: Proceeds from issuance of commerical paper | C98: -562 | D98: 2311 | E98: -813 | F98: -1103 | G98: -396 | H98: 0 | I98: 0 | J98: 2285 | K98: -238 | V98: -167 | W98: 1889
B99: Notes | C99: -1000 | D99: -2500 | E99: 0 | F99: 0 | G99: =5627-7630 -> -2003 | H99: 4140 | I99: 7640 | J99: -6070 | K99: -1052 | V99: -3500 | W99: =19548-15841 -> 3707
B100: Other | C100: 27 | D100: 4 | E100: 3 | F100: -30 | G100: -261 | H100: -15 | I100: -23 | J100: 1391 | K100: 1855 | V100: 4 | W100: 1092
B101: CFFF | C101: =SUM(C94:C100) -> -3528 | D101: =SUM(D94:D100) -> -2289 | E101: =SUM(E94:E100) -> -2463 | F101: =SUM(F94:F100) -> -2274 | G101: =SUM(G94:G100) -> -4585 | H101: =SUM(H94:H100) -> 2938 | I101: =SUM(I94:I100) -> 6559 | J101: =SUM(J94:J100) -> -3814 | K101: =SUM(K94:K100) -> 210 | V101: =SUM(V94:V100) -> -10554 | W101: =SUM(W94:W100) -> 1098
B102: FX adj | C102: -36 | D102: 26 | E102: 8 | F102: -68 | G102: 85 | H102: =-44-G102 -> -129 | I102: -51 | J102: 219 | K102: 27 | V102: -70 | W102: 124
B103: CF | C103: =C88+C93+C101+C102 -> 1848 | D103: =D88+D93+D101+D102 -> -3369 | E103: =E88+E93+E101+E102 -> 1237 | F103: =F88+F93+F101+F102 -> 973 | G103: =G88+G93+G101+G102 -> 162 | H103: =H88+H93+H101+H102 -> 325 | I103: =I88+I93+I101+I102 -> 6465 | J103: =J88+J93+J101+J102 -> -6620 | K103: =K88+K93+K101+K102 -> -341 | V103: =V88+V93+V101+V102 -> 689 | W103: =W88+W93+W101+W102 -> 332
B106: FCF | C106: =C88+C92 -> 5660 | D106: =D88+D92 -> -937 | E106: =E88+E92 -> 3801 | F106: =F88+F92 -> 3283 | G106: =G88+G92 -> 5124 | H106: =H88+H92 -> -2666 | I106: =I88+I92 -> 71 | J106: =J88+J92 -> -2923 | K106: =K88+K92 -> -362 | V106: =V88+V92 -> 11807 | W106: =W88+W92 -> -394
B107: CapEx Margin | C107: =-C92/C77 -> 0.54297521 | D107: =-D92/D77 -> 0.43148222 | E107: =-E92/E77 -> 0.6975 | F107: =-F92/F77 -> 0.88994911 | G107: =-#REF!/G77 -> #REF! | H107: =-H92/H77 -> 1.2599175 | I107: =-I92/I77 -> 1.996594 | J107: =-J92/J77 -> 2.6495477 | K107: =-K92/K77 -> 2.9046806 | V107: =-V92/V77 -> 0.65596637 | W107: =-W92/W77 -> 1.7049747
B112: Global Cloud | V112: 675000 | W112: 723420 | X112: 947300 | Y112: 1164070 | Z112: 1430443.3 | AA112: 1757770.6 | AB112: 2160000 | AC112: 2378902.3 | AD112: 2619989 | AE112: 2885508.3 | AF112: 3177936.3 | AG112: 3500000
B113: ORACLE % | V113: =SUM(W3:W4)/V112 -> 0.072933333 | W113: =X7/W112*0.85 -> 0.078441293 | X113: =+W113+0.001 -> 0.079441293 | Y113: =+X113+0.001 -> 0.080441293 | Z113: =+Y113+0.001 -> 0.081441293 | AA113: =+Z113+0.001 -> 0.082441293 | AB113: =+AA113+0.001 -> 0.083441293 | AC113: =+AB113+0.001 -> 0.084441293 | AD113: =+AC113+0.001 -> 0.085441293 | AE113: =+AD113+0.001 -> 0.086441293 | ... AG113: =+AF113+0.001 -> 0.088441293
X114: =+X112*X113/0.85 -> 88534.984
