Workbook

Sheet Main
K7: Price (€) | L7: 235.85 | M7: 46070 | N7: 147.34
K8: S/O | L8: 786 | M8: Q1 FY26 | N8: =+L8*2 -> 1572
K9: MC | L9: =+L7*L8 -> 185378.1 | N9: =+N7*N8 -> 231618.48
K10: C | L10: =+Model!AA73 -> 15263 | M10: Q1 FY26
K11: D | L11: =+Model!AA93+Model!AA102 -> 56465 | M11: Q1 FY26
K13: EV | L13: =+L9-L10+L11 -> 226580.1

Sheet Model
A1: Main
B2: (in million of €) | C2: Q1 FY20 | D2: Q2 FY20 | E2: Q3 FY20 | F2: Q4 FY20 | G2: Q1 FY21 | H2: Q2 FY21 | I2: Q3 FY21 | J2: Q4 FY21 | K2: Q1 FY22 | L2: Q2 FY22 | M2: Q3 FY22 | N2: Q4 FY22 | O2: Q1 FY23 | P2: Q2 FY23 | Q2: Q3 FY23 | R2: Q4 FY23 | S2: Q1 FY24 | T2: Q2 FY24 | U2: Q3 FY24 | V2: Q4 FY24 | W2: Q1 FY25 | X2: Q2 FY25 | Y2: Q3 FY25 | Z2: Q4 FY25 | AA2: Q1 FY26 | AB2: Q2 FY26 | AC2: Q3 FY26 | AD2: Q4 FY26 | AH2: FY2020 | AI2: FY2021 | AJ2: FY2022 | AK2: FY2023 | AL2: FY2024 | AM2: FY2025 | AN2: FY2026 | AO2: FY2027 | AP2: FY2028 | AQ2: FY2029 | AR2: FY2030
B3: Revenue | C3: 13675 | D3: 13784 | E3: 12979 | F3: 14816 | G3: 14071 | H3: 14665 | I3: 16085 | J3: 17444 | K3: 16497 | L3: 17040 | M3: 17867 | N3: 20573 | O3: 18070 | P3: 19416 | Q3: 18889 | R3: 21393 | S3: 17745 | T3: 18474 | U3: 18900 | V3: 20811 | W3: 18353 | X3: 19757 | Y3: 19377 | Z3: 21427 | AA3: 19139 | AH3: 55254 | AI3: 62265 | AJ3: 71977 | AK3: 74882 | AL3: 75930 | AM3: 78914
B4: Cost of sales | C4: -8688 | D4: -8771 | E4: -8224 | F4: -9683 | G4: -8751 | H4: -9426 | I4: -10213 | J4: -11137 | K4: -10292 | L4: -11300 | M4: -11638 | N4: -12901 | O4: -11104 | P4: -12217 | Q4: -11637 | R4: -13158 | S4: -10707 | T4: -11363 | U4: -11152 | V4: -12885 | W4: -11264 | X4: -12088 | Y4: -11840 | Z4: -13322 | AA4: -11506 | AH4: -35366 | AI4: -39527 | AJ4: -46130 | AK4: -45766 | AL4: -46107 | AM4: -48515
B5: Gross profit | C5: 4987 | D5: 5013 | E5: 4755 | F5: 5133 | G5: 5318 | H5: 5239 | I5: 5872 | J5: 6308 | K5: 6205 | L5: 5741 | M5: 6229 | N5: 7672 | O5: 6967 | P5: 7199 | Q5: 7252 | R5: 8235 | S5: 7038 | T5: 7111 | U5: 7748 | V5: 7926 | W5: 7089 | X5: 7669 | Y5: 7537 | Z5: 8104 | AA5: 7633 | AH5: 19888 | AI5: 22737 | AJ5: 25847 | AK5: 29117 | AL5: 29823 | AM5: 30399
B6: R&D | C6: -1125 | D6: -1159 | E6: -1087 | F6: -1198 | G6: -1064 | H6: -1128 | I6: -1220 | J6: -1447 | K6: -1251 | L6: -1359 | M6: -1400 | N6: -1582 | O6: -1430 | P6: -1528 | Q6: -1542 | R6: -1684 | S6: -1496 | T6: -1567 | U6: -1561 | V6: -1651 | W6: -1545 | X6: -1621 | Y6: -1650 | Z6: -1744 | AA6: -1637 | AH6: -4569 | AI6: -4859 | AJ6: -5591 | AK6: -6113 | AL6: -6276 | AM6: -6559
B7: SG&A | C7: -2840 | D7: -2649 | E7: -2519 | F7: -2674 | G7: -2461 | H7: -2562 | I7: -2940 | J7: -3228 | K7: -2933 | L7: -3081 | M7: -3179 | N7: -3663 | O7: -3349 | P7: -3375 | Q7: -3418 | R7: -3799 | S7: -3373 | T7: -3369 | U7: -3571 | V7: -3671 | W7: -3500 | X7: -3659 | Y7: -3571 | Z7: -4097 | AA7: -3608 | AH7: -10682 | AI7: -11191 | AJ7: -12857 | AK7: -13553 | AL7: -13984 | AM7: -14827
B8: Other operating income | C8: 256 | D8: 74 | E8: 33 | F8: 267 | G8: 122 | H8: 27 | I8: 36 | J8: 51 | K8: 29 | L8: 38 | M8: 833 | N8: 1271 | O8: 172 | P8: 52 | Q8: 126 | R8: 224 | S8: 194 | T8: 74 | U8: 136 | V8: 141 | W8: 105 | X8: 396 | Y8: 362 | Z8: 118 | AA8: 151 | AH8: 630 | AI8: 236 | AJ8: 2171 | AK8: 572 | AL8: 544 | AM8: 981
B9: Other operating expenses | C9: -106 | D9: -57 | E9: -57 | F9: -176 | G9: -181 | H9: -102 | I9: -87 | J9: -61 | K9: -85 | L9: -70 | M9: -52 | N9: -78 | O9: -134 | P9: -126 | Q9: -127 | R9: -68 | S9: -78 | T9: -204 | U9: -139 | V9: -93 | W9: -85 | X9: -118 | Y9: -64 | Z9: -132 | AA9: -45 | AH9: -396 | AI9: -431 | AJ9: -285 | AK9: -447 | AL9: -514 | AM9: -400
B10: Income (loss) from investments accounted for using the equity method, net | C10: 44 | D10: -3 | E10: -84 | F10: -553 | G10: 9 | H10: -29 | I10: -153 | J10: -255 | K10: 239 | L10: 145 | M10: -2814 | N10: 346 | O10: -178 | P10: 1818 | Q10: -533 | R10: -201 | S10: 664 | T10: 72 | U10: 39 | V10: 52 | W10: 90 | X10: 257 | Y10: 36 | Z10: 15 | AA10: 284 | AH10: -596 | AI10: -428 | AJ10: -2085 | AK10: 906 | AL10: 827 | AM10: 397
B11: Interest income | C11: 343 | D11: 488 | E11: 403 | F11: 311 | G11: 317 | H11: 348 | I11: 361 | J11: 415 | K11: 371 | L11: 367 | M11: 419 | N11: 475 | O11: 540 | P11: 578 | Q11: 615 | R11: 673 | S11: 713 | T11: 704 | U11: 703 | V11: 714 | W11: 747 | X11: 706 | Y11: 670 | Z11: 642 | AA11: 686 | AH11: 1545 | AI11: 1441 | AJ11: 1632 | AK11: 2402 | AL11: 2833 | AM11: 2765
B12: Interest expenses | C12: -143 | D12: -312 | E12: -218 | F12: -141 | G12: -165 | H12: -164 | I12: -137 | J12: -178 | K12: -165 | L12: -188 | M12: -160 | N12: -177 | O12: -276 | P12: -348 | Q12: -379 | R12: -370 | S12: -420 | T12: -447 | U12: -447 | V12: -471 | W12: -386 | X12: -370 | Y12: -450 | Z12: -434 | AA12: -435 | AH12: -814 | AI12: -644 | AJ12: -689 | AK12: -1369 | AL12: -1785 | AM12: -1640
B13: Other financial income (expenses), net | C13: 39 | D13: -107 | E13: 122 | F13: 442 | G13: 68 | H13: 355 | I13: -23 | J13: 235 | K13: 37 | L13: 158 | M13: -788 | N13: -394 | O13: -88 | P13: -130 | Q13: -9 | R13: -159 | S13: -24 | T13: -117 | U13: -56 | V13: -44 | W13: -133 | X13: -87 | Y13: 21 | Z13: -88 | AA13: -86 | AH13: 496 | AI13: 635 | AJ13: -987 | AK13: -388 | AL13: -240 | AM13: -287
B14: Income from continuing operations before income taxes | C14: 1457 | D14: 1287 | E14: 1347 | F14: 1411 | G14: 1963 | H14: 1984 | I14: 1708 | J14: 1841 | K14: 2447 | L14: 1750 | M14: -912 | N14: 3869 | O14: 2223 | P14: 4141 | Q14: 1985 | R14: 2851 | S14: 3217 | T14: 2256 | U14: 2852 | V14: 2903 | W14: 2381 | X14: 3173 | Y14: 2890 | Z14: 2385 | AA14: 2944 | AH14: 5502 | AI14: 7496 | AJ14: 7154 | AK14: 11126 | AL14: 11227 | AM14: 10830
... B18: Net income | C18: 1089 | D18: 697 | E18: 535 | F18: 1879 | G18: 1497 | H18: 2390 | I18: 1480 | J18: 1330 | K18: 1796 | L18: 1213 | M18: -1531 | N18: 2913 | O18: 1636 | P18: 3551 | Q18: 1440 | R18: 1902 | S18: 2548 | T18: 2196 | U18: 2133 | V18: 2115 | W18: 3868 | X18: 2439 | Y18: 2243 | Z18: 1837 | AA18: 2222 | AH18: 4200 | AI18: 6697 | AJ18: 4392 | AK18: 8529 | AL18: 8992 | AM18: 10387
B20: Attributable to:
B21: Non-controlling interests | C21: 8 | D21: 44 | E21: -3 | F21: 121 | G21: 121 | H21: 125 | I21: 128 | J21: 163 | K21: 153 | L21: 179 | M21: 125 | N21: 212 | O21: 159 | P21: 74 | Q21: 162 | R21: 184 | S21: 160 | T21: 163 | U21: 154 | V21: 215 | W21: 163 | X21: 189 | Y21: 197 | Z21: 218 | AA21: 192 | AH21: 170 | AI21: 537 | AJ21: 669 | AK21: 579 | AL21: 691 | AM21: 767
B22: Shareholders of Siemens AG | C22: 1081 | D22: 652 | E22: 539 | F22: 1758 | G22: 1377 | H22: 2265 | I22: 1352 | J22: 1167 | K22: 1643 | L22: 1034 | M22: -1655 | N22: 2701 | O22: 1477 | P22: 3477 | Q22: 1278 | R22: 1718 | S22: 2389 | T22: 2033 | U22: 1980 | V22: 1900 | W22: 3705 | X22: 2250 | Y22: 2046 | Z22: 1619 | AA22: 2030 | AH22: 4030 | AI22: 6161 | AJ22: 3723 | AK22: 7949 | AL22: 8301 | AM22: 9620
B24: Basic earnings per share
B25: Income from continuing operations | C25: 1.37 | D25: 1.15 | E25: 1.07 | F25: 1.18 | G25: 1.7 | H25: 1.73 | I25: 1.55 | J25: 1.38 | K25: 2.06 | L25: 1.28 | M25: -2.05 | N25: 3.4 | O25: 1.88 | P25: 4.4 | Q25: 1.57 | R25: 2.18 | S25: 3.05 | T25: 2.33 | U25: 2.54 | V25: 2.49 | W25: 2.08 | X25: 2.86 | Y25: 2.58 | Z25: 2.11 | AA25: 2.61 | AH25: 4.77 | AI25: 6.36 | AJ25: 4.67 | AK25: 10.04 | AL25: 10.42 | AM25: 9.63
B26: Income from discontinued operations | C26: -0.05 | D26: -0.34 | E26: -0.4 | F26: 1.02 | G26: 0.02 | H26: 1.09 | I26: 0.13 | J26: 0.08 | K26: -0.02 | L26: 0.01 | M26: -0.01 | N26: 0 | O26: -0.01 | P26: 0 | Q26: 0.04 | R26: -0.01 | S26: -0.03 | T26: 0.24 | U26: -0.03 | V26: -0.08 | W26: 2.63 | X26: 0 | Y26: 0.03 | Z26: -0.04 | AA26: 0 | AH26: 0.23 | AI26: 1.32 | AJ26: -0.03 | AK26: 0 | AL26: 0.11 | AM26: 2.62
B27: Net income | C27: 1.33 | D27: 0.8 | E27: 0.67 | F27: 2.2 | G27: 1.73 | H27: 2.82 | I27: 1.68 | J27: 1.45 | K27: 2.05 | L27: 1.29 | M27: -2.06 | N27: 3.39 | O27: 1.87 | P27: 4.39 | Q27: 1.61 | R27: 2.17 | S27: 3.03 | T27: 2.57 | U27: 2.51 | V27: 2.42 | W27: 4.71 | X27: 2.86 | Y27: 2.61 | Z27: 2.07 | AA27: 2.6 | AH27: 5 | AI27: 7.68 | AJ27: 4.65 | AK27: 10.04 | AL27: 10.53 | AM27: 12.25
B29: Diluted earnings per share
B30: Income from continuing operations | C30: 1.35 | D30: 1.13 | E30: 1.06 | F30: 1.16 | G30: 1.67 | H30: 1.71 | I30: 1.54 | J30: 1.36 | K30: 2.04 | L30: 1.27 | M30: -2.06 | N30: 3.36 | O30: 1.86 | P30: 4.35 | Q30: 1.55 | R30: 2.15 | S30: 3.01 | T30: 2.3 | U30: 2.51 | V30: 2.46 | W30: 2.06 | X30: 2.83 | Y30: 2.55 | Z30: 2.08 | AA30: 2.58 | AH30: 4.7 | AI30: 6.28 | AJ30: 4.62 | AK30: 9.91 | AL30: 10.27 | AM30: 9.52
B31: Income from discontinued operations | C31: -0.05 | D31: -0.34 | E31: -0.39 | F31: 1.01 | G31: 0.03 | H31: 1.08 | I31: 0.13 | J31: 0.07 | K31: -0.02 | L31: 0.01 | M31: -0.01 | N31: 0 | O31: -0.01 | P31: 0 | Q31: 0.04 | R31: -0.01 | S31: -0.03 | T31: 0.24 | U31: -0.03 | V31: -0.08 | W31: 2.6 | X31: 0 | Y31: 0.03 | Z31: -0.04 | AA31: 0 | AH31: 0.23 | AI31: 1.31 | AJ31: -0.03 | AK31: 0 | AL31: 0.11 | AM31: 2.59
B32: Net income | C32: 1.3 | D32: 0.79 | E32: 0.67 | F32: 2.17 | G32: 1.71 | H32: 2.79 | I32: 1.66 | J32: 1.43 | K32: 2.02 | L32: 1.27 | M32: -2.07 | N32: 3.36 | O32: 1.85 | P32: 4.34 | Q32: 1.59 | R32: 2.14 | S32: 2.99 | T32: 2.54 | U32: 2.48 | V32: 2.38 | W32: 4.66 | X32: 2.83 | Y32: 2.58 | Z32: 2.05 | AA32: 2.58 | AH32: 4.93 | AI32: 7.59 | AJ32: 4.59 | AK32: 9.91 | AL32: 10.38 | AM32: 12.11
B34: Consolidated Statements of Comprehensive Income
B35: Net income | C35: 1089 | D35: 697 | E35: 535 | F35: 1879 | G35: 1497 | H35: 2390 | I35: 1480 | J35: 1330 | K35: 1796 | L35: 1213 | M35: -1531 | N35: 2913 | O35: 1636 | P35: 3551 | Q35: 1440 | R35: 1902 | S35: 2548 | T35: 2196 | U35: 2133 | V35: 2115 | W35: 3868 | X35: 2439 | Y35: 2243 | Z35: 1837 | AA35: 2222 | AH35: 4200 | AI35: 6697 | AJ35: 4392 | AK35: 8529 | AL35: 8992 | AM35: 10387
B37: Remeasurements of defined benefit plans | C37: 322 | D37: 41 | E37: -277 | F37: -347 | G37: 307 | H37: 918 | I37: 679 | J37: 219 | K37: 191 | L37: -27 | M37: 78 | N37: -831 | O37: 305 | P37: 134 | Q37: -542 | R37: -1 | S37: -323 | T37: 529 | U37: 419 | V37: 62 | W37: -83 | X37: 1 | Y37: -33 | Z37: -479 | AA37: 259 | AH37: -261 | AI37: 2123 | AJ37: -589 | AK37: -104 | AL37: 687 | AM37: -594
B38: therein: Income tax effects | C38: -166 | D38: -250 | E38: 319 | F38: 130 | G38: 255 | H38: -311 | I38: -2 | J38: 13 | K38: -93 | L38: -199 | M38: -391 | N38: 123 | O38: -76 | P38: -14 | Q38: 305 | R38: -298 | S38: 290 | T38: -120 | U38: -54 | V38: 296 | W38: 54 | X38: -109 | Y38: -38 | Z38: -525 | AA38: -31 | AH38: 33 | AI38: -45 | AJ38: -560 | AK38: -84 | AL38: 411 | AM38: -618
B39: Remeasurements of equity instruments | C39: 15 | D39: 2 | E39: -12 | F39: 0 | G39: -1 | H39: 18 | I39: -17 | J39: 30 | K39: -4 | L39: -6 | M39: 2 | N39: 9 | O39: -23 | P39: -8 | Q39: 8 | R39: -18 | S39: 122 | T39: 665 | U39: 995 | V39: 1184 | W39: 2352 | X39: 553 | Y39: 1625 | Z39: 2065 | AA39: 959 | AH39: 5 | AI39: 30 | AJ39: 1 | AK39: -41 | AL39: 2966 | AM39: 6595
B40: therein: Income tax effects | C40: -3 | D40: 0 | E40: 0 | F40: 0 | G40: 0 | H40: 0 | I40: 0 | J40: -1 | K40: 0 | L40: -1 | M40: 0 | N40: 0 | O40: 0 | P40: 0 | Q40: 0 | R40: 0 | S40: 0 | T40: 0 | U40: 0 | V40: 0 | W40: -13 | X40: 12 | Y40: 0 | Z40: -61 | AA40: -88 | AH40: -3 | AI40: -1 | AJ40: -1 | AK40: 10 | AL40: 0 | AM40: -61
B41: Income (loss) from investments accounted for using the equity method, net | C41: -3 | D41: -1 | E41: 3 | F41: 18 | G41: 4 | H41: 39 | I41: 7 | J41: 7 | K41: 2 | L41: 40 | M41: 44 | N41: -14 | O41: 1 | P41: -4 | Q41: -3 | R41: 15 | S41: -18 | T41: 0 | U41: 0 | V41: 0 | X41: 0 | Y41: 0 | Z41: 0 | AH41: 17 | AI41: 57 | AJ41: 72 | AK41: 0 | AL41: -18 | AM41: 0
B42: Items that will not be reclassified to profit or loss | C42: 334 | D42: 42 | E42: -287 | F42: -329 | G42: 310 | H42: 975 | I42: 669 | J42: 256 | K42: 188 | L42: 7 | M42: 125 | N42: -835 | O42: 284 | P42: 122 | Q42: -537 | R42: -5 | S42: -218 | T42: 1194 | U42: 1414 | V42: 1246 | W42: 2269 | X42: 554 | Y42: 1592 | Z42: 1586 | AA42: 1218 | AH42: -240 | AI42: 2210 | AJ42: -516 | AK42: -135 | AL42: 3636 | AM42: 6000
B44: Currency translation differences | C44: -846 | D44: -254 | E44: -869 | F44: -836 | G44: -1200 | H44: 1529 | I44: -236 | J44: 1211 | K44: 1110 | L44: 778 | M44: 2567 | N44: 2348 | O44: -4041 | P44: -864 | Q44: -310 | R44: 953 | S44: -1505 | T44: 768 | U44: 439 | V44: -1603 | W44: 2827 | X44: -1775 | Y44: -3506 | Z44: -280 | AA44: -19 | AH44: -2805 | AI44: 1304 | AJ44: 6803 | AK44: -4262 | AL44: -1900 | AM44: -2733
B45: Derivative financial instruments | C45: 27 | D45: -45 | E45: 99 | F45: 67 | G45: -271 | H45: 101 | I45: -29 | J45: -38 | K45: -25 | L45: -69 | M45: 0 | N45: 21 | O45: 223 | P45: 56 | Q45: -112 | R45: -175 | S45: 93 | T45: -10 | U45: -4 | V45: 84 | W45: -228 | X45: 190 | Y45: 129 | Z45: 6 | AA45: -6 | AH45: 148 | AI45: -237 | AJ45: -74 | AK45: -8 | AL45: 163 | AM45: 97
B46: therein: Income tax effects | C46: -19 | D46: 20 | E46: -23 | F46: -16 | G46: 79 | H46: -26 | I46: -37 | J46: 15 | K46: 8 | L46: 33 | M46: 4 | N46: 0 | O46: -98 | P46: -38 | Q46: 52 | R46: 69 | S46: -34 | T46: 14 | U46: -8 | V46: -42 | W46: 93 | X46: -75 | Y46: -46 | Z46: -12 | AA46: 4 | AH46: -38 | AI46: 31 | AJ46: 45 | AK46: -15 | AL46: -69 | AM46: -40
B47: Income (loss) from investments accounted for using the equity method, net | C47: 9 | D47: -42 | E47: -32 | F47: -24 | G47: -9 | H47: 28 | I47: 50 | J47: 19 | K47: 44 | L47: 74 | M47: 166 | N47: 114 | O47: -150 | P47: -22 | Q47: -18 | R47: 29 | S47: -75 | T47: 3 | U47: 6 | V47: -17 | W47: 26 | X47: -3 | Y47: -24 | Z47: -1 | AA47: -5 | AH47: -89 | AI47: 88 | AJ47: 398 | AK47: -161 | AL47: -82 | AM47: -3
B48: Items that may be reclassified subsequently to profit or loss | C48: -812 | D48: -340 | E48: -802 | F48: -792 | G48: -1482 | H48: 1659 | I48: -215 | J48: 1192 | K48: 1128 | L48: 783 | M48: 2733 | N48: 2483 | O48: -3967 | P48: -829 | Q48: -440 | R48: 806 | S48: -1486 | T48: 761 | U48: 442 | V48: -1536 | W48: 2625 | X48: -1588 | Y48: -3401 | Z48: -275 | AA48: -29 | AH48: -2746 | AI48: 1154 | AJ48: 7127 | AK48: -4431 | AL48: -1819 | AM48: -2639
C49: -478 | D49: -298 | E49: -1088 | F49: -1122 | G49: 3364 | H49: 2634 | I49: 453 | J49: 1448 | AH49: -2986
B50: Other comprehensive income, net of income taxes | K50: 1316 | L50: 790 | M50: 2858 | N50: 1648 | O50: -3684 | P50: -707 | Q50: -977 | R50: 801 | S50: -1705 | T50: 1955 | U50: 1855 | V50: -289 | W50: 4894 | X50: -1035 | Y50: -1809 | Z50: 1311 | AA50: 1189 | AI50: 3364 | AJ50: 6611 | AK50: -4566 | AL50: 1817 | AM50: 3361
B51: Total comprehensive income | C51: 611 | D51: 399 | E51: -553 | F51: 757 | G51: 325 | H51: 5024 | I51: 1934 | J51: 2778 | K51: 3112 | L51: 2003 | M51: 1327 | N51: 4561 | O51: -2048 | P51: 2844 | Q51: 463 | R51: 2703 | S51: 843 | T51: 4152 | U51: 3988 | V51: 1826 | W51: 8762 | X51: 1405 | Y51: 434 | Z51: 3148 | AA51: 3411 | AH51: 1214 | AI51: 10061 | AJ51: 11003 | AK51: 3962 | AL51: 10809 | AM51: 13748
B53: Attributable to:
B54: Non-controlling interests | C54: -48 | D54: 58 | E54: -52 | F54: -5 | G54: -111 | H54: 238 | I54: 145 | J54: 351 | K54: 289 | L54: 253 | M54: 418 | N54: 490 | O54: -354 | P54: -20 | Q54: 76 | R54: 289 | S54: 43 | T54: 227 | U54: 197 | V54: 16 | W54: 466 | X54: -3 | Y54: -251 | Z54: 55 | AA54: 123 | AH54: -47 | AI54: 623 | AJ54: 1450 | AK54: -10 | AL54: 483 | AM54: 267
B55: Shareholders of Siemens AG | C55: 658 | D55: 341 | E55: -501 | F55: 763 | G55: 437 | H55: 4786 | I55: 1788 | J55: 2427 | K55: 2823 | L55: 1750 | M55: 909 | N55: 4071 | O55: -1694 | P55: 2864 | Q55: 388 | R55: 2414 | S55: 800 | T55: 3925 | U55: 3791 | V55: 1809 | W55: 8296 | X55: 1407 | Y55: 684 | Z55: 3093 | AA55: 3288 | AH55: 1261 | AI55: 9438 | AJ55: 9553 | AK55: 3972 | AL55: 10326 | AM55: 13481
B58: Gross Margin | C58: =C5/C3 -> 0.36468007 | D58: =D5/D3 -> 0.36368253 | E58: =E5/E3 -> 0.36636104 | F58: =F5/F3 -> 0.34644978 | G58: =G5/G3 -> 0.37794044 | H58: =H5/H3 -> 0.35724514 | I58: =I5/I3 -> 0.36506062 | J58: =J5/J3 -> 0.36161431 | ... AC58: =AC5/AC3 -> #DIV/0! | AH58: =AH5/AH3 -> 0.35993774 | AI58: =AI5/AI3 -> 0.36516502 | AJ58: =AJ5/AJ3 -> 0.35910082 | AK58: =AK5/AK3 -> 0.38883844 | AL58: =AL5/AL3 -> 0.39276966 | AM58: =AM5/AM3 -> 0.38521682 | AN58: =AN5/AN3 -> #DIV/0! | AO58: =AO5/AO3 -> #DIV/0!
B59: Op Margin | C59: =(C5+C6+C7)/C3 -> 0.074734918 | D59: =(D5+D6+D7)/D3 -> 0.087420197 | E59: =(E5+E6+E7)/E3 -> 0.088527622 | F59: =(F5+F6+F7)/F3 -> 0.085110691 | G59: =(G5+G6+G7)/G3 -> 0.1274252 | H59: =(H5+H6+H7)/H3 -> 0.10562564 | I59: =(I5+I6+I7)/I3 -> 0.10643457 | J59: =(J5+J6+J7)/J3 -> 0.09361385 | ... AC59: =(AC5+AC6+AC7)/AC3 -> #DIV/0! | AH59: =(AH5+AH6+AH7)/AH3 -> 0.083921526 | AI59: =(AI5+AI6+AI7)/AI3 -> 0.10739581 | AJ59: =(AJ5+AJ6+AJ7)/AJ3 -> 0.10279673 | AK59: =(AK5+AK6+AK7)/AK3 -> 0.12621191 | AL59: =(AL5+AL6+AL7)/AL3 -> 0.12594495 | AM59: =(AM5+AM6+AM7)/AM3 -> 0.11421294 | AN59: =(AN5+AN6+AN7)/AN3 -> #DIV/0! | AO59: =(AO5+AO6+AO7)/AO3 -> #DIV/0!
B60: Interest Margin | C60: =C14/C3 -> 0.10654479 | D60: =D14/D3 -> 0.093369124 | E60: =E14/E3 -> 0.10378303 | F60: =F14/F3 -> 0.095234881 | G60: =G14/G3 -> 0.13950679 | H60: =H14/H3 -> 0.1352881 | I60: =I14/I3 -> 0.10618589 | J60: =J14/J3 -> 0.10553772 | ... AC60: =AC14/AC3 -> #DIV/0! | AH60: =AH14/AH3 -> 0.099576501 | AI60: =AI14/AI3 -> 0.12038866 | AJ60: =AJ14/AJ3 -> 0.099392862 | AK60: =AK14/AK3 -> 0.14858043 | AL60: =AL14/AL3 -> 0.14785987 | AM60: =AM14/AM3 -> 0.13723801 | AN60: =AN14/AN3 -> #DIV/0! | AO60: =AO14/AO3 -> #DIV/0!
B61: Tax Rate | C61: =-C15/C14 -> 0.18462594 | D61: =-D15/D14 -> 0.22999223 | E61: =-E15/E14 -> 0.30363771 | F61: =-F15/F14 -> 0.26364281 | G61: =-G15/G14 -> 0.24961793 | H61: =-H15/H14 -> 0.2358871 | I61: =-I15/I14 -> 0.19437939 | J61: =-J15/J14 -> 0.31015752 | ... L61: =-L15/L14 -> 0.30914286 | N61: =-N15/N14 -> 0.24631688 | O61: =-O15/O14 -> 0.26045884 | P61: =-P15/P14 -> 0.14199469 | Q61: =-Q15/Q14 -> 0.29017632 | R61: =-R15/R14 -> 0.33111189 | S61: =-S15/S14 -> 0.2014299 | T61: =-T15/T14 -> 0.11170213 | U61: =-U15/U14 -> 0.24333801 | ... AC61: =-AC15/AC14 -> #DIV/0! | AH61: =-AH15/AH14 -> 0.24463831 | AI61: =-AI15/AI14 -> 0.24826574 | AJ61: =-AJ15/AJ14 -> 0.3831423 | AK61: =-AK15/AK14 -> 0.23368686 | AL61: =-AL15/AL14 -> 0.2066447 | AM61: =-AM15/AM14 -> 0.23093259 | AN61: =-AN15/AN14 -> #DIV/0! | AO61: =-AO15/AO14 -> #DIV/0!
B62: Net Margin | C62: =C18/C3 -> 0.079634369 | D62: =D18/D3 -> 0.050565873 | E62: =E18/E3 -> 0.041220433 | F62: =F18/F3 -> 0.12682235 | G62: =G18/G3 -> 0.10638903 | H62: =H18/H3 -> 0.16297307 | I62: =I18/I3 -> 0.092011191 | J62: =J18/J3 -> 0.076243981 | ... AC62: =AC18/AC3 -> #DIV/0! | AH62: =AH18/AH3 -> 0.076012596 | AI62: =AI18/AI3 -> 0.10755641 | AJ62: =AJ18/AJ3 -> 0.061019492 | AK62: =AK18/AK3 -> 0.1138992 | AL62: =AL18/AL3 -> 0.11842487 | AM62: =AM18/AM3 -> 0.1316243 | AN62: =AN18/AN3 -> #DIV/0! | AO62: =AO18/AO3 -> #DIV/0!
B63: Net Margin (Comperhensive) | C63: =C51/C3 -> 0.044680073 | D63: =D51/D3 -> 0.028946605 | E63: =E51/E3 -> -0.042607289 | F63: =F51/F3 -> 0.051093413 | G63: =G51/G3 -> 0.02309715 | H63: =H51/H3 -> 0.34258438 | I63: =I51/I3 -> 0.12023624 | J63: =J51/J3 -> 0.15925247 | ... AC63: =AC51/AC3 -> #DIV/0! | AH63: =AH51/AH3 -> 0.02197126 | AI63: =AI51/AI3 -> 0.16158355 | AJ63: =AJ51/AJ3 -> 0.15286828 | AK63: =AK51/AK3 -> 0.052909912 | AL63: =AL51/AL3 -> 0.1423548 | AM63: =AM51/AM3 -> 0.17421497 | AN63: =AN51/AN3 -> #DIV/0! | AO63: =AO51/AO3 -> #DIV/0!
B65: Revenue y/y | G65: =G3/C3-1 -> 0.028957952 | H65: =H3/D3-1 -> 0.063914684 | I65: =I3/E3-1 -> 0.23930965 | J65: =J3/F3-1 -> 0.17737581 | K65: =K3/G3-1 -> 0.17241134 | L65: =L3/H3-1 -> 0.16195022 | M65: =M3/I3-1 -> 0.11078645 | N65: =N3/J3-1 -> 0.179374 | ... AC65: =AC3/Y3-1 -> -1 | AI65: =AI3/AH3-1 -> 0.12688674 | AJ65: =AJ3/AI3-1 -> 0.15597848 | AK65: =AK3/AJ3-1 -> 0.040360115 | AL65: =AL3/AK3-1 -> 0.013995353 | AM65: =AM3/AL3-1 -> 0.039299355 | AN65: =AN3/AM3-1 -> -1 | AO65: =AO3/AN3-1 -> #DIV/0!
B67: R&D Gross Margin Share | C67: =-C6/C5 -> 0.22558652 | D67: =-D6/D5 -> 0.23119888 | E67: =-E6/E5 -> 0.22860147 | F67: =-F6/F5 -> 0.23339178 | G67: =-G6/G5 -> 0.20007522 | H67: =-H6/H5 -> 0.21530826 | I67: =-I6/I5 -> 0.20776567 | J67: =-J6/J5 -> 0.22939125 | ... AC67: =-AC6/AC5 -> #DIV/0! | AH67: =-AH6/AH5 -> 0.22973652 | AI67: =-AI6/AI5 -> 0.21370453 | AJ67: =-AJ6/AJ5 -> 0.21631137 | AK67: =-AK6/AK5 -> 0.20994608 | AL67: =-AL6/AL5 -> 0.21044161 | AM67: =-AM6/AM5 -> 0.21576368 | AN67: =-AN6/AN5 -> #DIV/0! | AO67: =-AO6/AO5 -> #DIV/0!
B68: SG&A Gross Margin Share | C68: =-C7/C5 -> 0.56948065 | D68: =-D7/D5 -> 0.52842609 | E68: =-E7/E5 -> 0.52975815 | F68: =-F7/F5 -> 0.52094292 | G68: =-G7/G5 -> 0.46276796 | H68: =-H7/H5 -> 0.48902462 | I68: =-I7/I5 -> 0.5006812 | J68: =-J7/J5 -> 0.51173114 | ... AC68: =-AC7/AC5 -> #DIV/0! | AH68: =-AH7/AH5 -> 0.5371078 | AI68: =-AI7/AI5 -> 0.49219334 | AJ68: =-AJ7/AJ5 -> 0.49742717 | AK68: =-AK7/AK5 -> 0.46546691 | AL68: =-AL7/AL5 -> 0.46889984 | AM68: =-AM7/AM5 -> 0.48774631 | AN68: =-AN7/AN5 -> #DIV/0! | AO68: =-AO7/AO5 -> #DIV/0!
B71: Net Cash | F71: =F73-F93-F102 -> -30526 | G71: =G73-G93-G102 -> -29464 | H71: =H73-H93-H102 -> -28459 | I71: =I73-I93-I102 -> -40433 | J71: =J73-J93-J102 -> -39155 | K71: =K73-K93-K102 -> -39268 | L71: =L73-L93-L102 -> -42258 | M71: =M73-M93-M102 -> -41459 | ... AD71: =AD73-AD93-AD102 -> 0 | AH71: =AH73-AH93-AH102 -> -30526 | AI71: =AI73-AI93-AI102 -> -39155 | AJ71: =AJ73-AJ93-AJ102 -> -40171 | AK71: =AK73-AK93-AK102 -> -36512 | AL71: =AL73-AL93-AL102 -> -38763 | AM71: =AM73-AM93-AM102 -> -41520 | AN71: =AN73-AN93-AN102 -> 0 | AO71: =AO73-AO93-AO102 -> 0
B72: Assets
B73: Cash and cash equivalents | F73: 14041 | G73: 14016 | H73: 23639 | I73: 10678 | J73: 9545 | K73: 12199 | L73: 9495 | M73: 10097 | N73: 10465 | O73: 10135 | P73: 9186 | Q73: 9802 | R73: 10084 | S73: 10769 | T73: 7715 | U73: 7758 | V73: 9156 | W73: 13926 | X73: 12686 | Y73: 14641 | Z73: 14495 | AA73: 15263 | AH73: 14041 | AI73: 9545 | AJ73: 10465 | AK73: 10084 | AL73: 9156 | AM73: 14495
B74: Trade and other receivables | F74: 14074 | G74: 13866 | H74: 13951 | I74: 15126 | J74: 15518 | K74: 15916 | L74: 15960 | M74: 16162 | N74: 16701 | O74: 16941 | P74: 16587 | Q74: 16791 | R74: 17405 | S74: 17215 | T74: 17159 | U74: 16865 | V74: 16963 | W74: 17287 | X74: 17418 | Y74: 17043 | Z74: 16628 | AA74: 16881 | AH74: 14074 | AI74: 15518 | AJ74: 16701 | AK74: 17405 | AL74: 16963 | AM74: 16628
B75: Other current financial assets | F75: 8382 | G75: 8410 | H75: 9144 | I75: 7493 | J75: 7985 | K75: 8791 | L75: 8603 | M75: 9642 | N75: 9696 | O75: 9864 | P75: 9697 | Q75: 10039 | R75: 10605 | S75: 10240 | T75: 11161 | U75: 10802 | V75: 10492 | W75: 11782 | X75: 11246 | Y75: 11369 | Z75: 11523 | AA75: 12451 | AH75: 8382 | AI75: 7985 | AJ75: 9696 | AK75: 10605 | AL75: 10492 | AM75: 11523
B76: Contract assets | F76: 5545 | G76: 5475 | H76: 5963 | I76: 6373 | J76: 6645 | K76: 6493 | L76: 6643 | M76: 7046 | N76: 7559 | O76: 6911 | P76: 7033 | Q76: 7066 | R76: 7581 | S76: 7464 | T76: 7825 | U76: 7961 | V76: 7985 | W76: 8142 | X76: 8390 | Y76: 8091 | Z76: 8141 | AA76: 8251 | AH76: 5545 | AI76: 6645 | AJ76: 7559 | AK76: 7581 | AL76: 7985 | AM76: 8141
B77: Inventories | F77: 7795 | G77: 7743 | H77: 7956 | I77: 8956 | J77: 8836 | K77: 9737 | L77: 10114 | M77: 10786 | N77: 10626 | O77: 11241 | P77: 11580 | Q77: 11961 | R77: 11548 | S77: 12184 | T77: 12400 | U77: 12105 | V77: 10923 | W77: 11707 | X77: 11498 | Y77: 11165 | Z77: 10582 | AA77: 11100 | AH77: 7795 | AI77: 8836 | AJ77: 10626 | AK77: 11548 | AL77: 10923 | AM77: 10582
B78: Current income tax assets | F78: 1523 | G78: 1508 | H78: 1601 | I78: 1727 | J78: 1795 | K78: 1502 | L78: 1534 | M78: 1596 | N78: 1432 | O78: 1361 | P78: 1493 | Q78: 1737 | R78: 1363 | S78: 1501 | T78: 1581 | U78: 1995 | V78: 1767 | W78: 1647 | X78: 1804 | Y78: 1786 | Z78: 1536 | AA78: 1673 | AH78: 1523 | AI78: 1795 | AJ78: 1432 | AK78: 1363 | AL78: 1767 | AM78: 1536
B79: Other current assets | F79: 1271 | G79: 1239 | H79: 1299 | I79: 1430 | J79: 1751 | K79: 1326 | L79: 1849 | M79: 1726 | N79: 1935 | O79: 1841 | P79: 1868 | Q79: 2139 | R79: 1955 | S79: 1635 | T79: 1725 | U79: 1561 | V79: 1632 | W79: 1775 | X79: 1795 | Y79: 1676 | Z79: 1768 | AA79: 1985 | AH79: 1271 | AI79: 1751 | AJ79: 1935 | AK79: 1955 | AL79: 1632 | AM79: 1768
B80: Assets classified as held for disposal | F80: 338 | G80: 1862 | H80: 241 | I80: 229 | J80: 223 | K80: 401 | L80: 1452 | M80: 1184 | N80: 413 | O80: 300 | P80: 293 | Q80: 78 | R80: 99 | S80: 189 | T80: 123 | U80: 2424 | V80: 2433 | W80: 2406 | X80: 114 | Y80: 19 | Z80: 36 | AA80: 308 | AH80: 338 | AI80: 223 | AJ80: 413 | AK80: 99 | AL80: 2433 | AM80: 36
B81: Total current assets | F81: 52968 | G81: =SUM(G73:G80) -> 54119 | H81: 63793 | I81: 52012 | J81: 52298 | K81: 56365 | L81: 55650 | M81: 58239 | N81: 58829 | O81: 58592 | P81: 57737 | Q81: 59613 | R81: 60639 | S81: 61198 | T81: 59690 | U81: 61472 | V81: 61353 | W81: 68673 | X81: 64951 | Y81: 65791 | Z81: 64711 | AA81: 67912 | AH81: 52968 | AI81: 52298 | AJ81: 58829 | AK81: 60639 | AL81: 61353 | AM81: 64711
B82: Goodwill | F82: 20449 | G82: 19872 | H82: 20605 | I82: 28376 | J82: 29672 | K82: 30428 | L82: 30760 | M82: 31677 | N82: 33861 | O82: 32116 | P82: 31820 | Q82: 31772 | R82: 32224 | S82: 31807 | T82: 32094 | U82: 32002 | V82: 31384 | W82: 32803 | X82: 39951 | Y82: 38021 | Z82: 40670 | AA82: 40650 | AH82: 20449 | AI82: 29672 | AJ82: 33861 | AK82: 32224 | AL82: 31384 | AM82: 40670
B83: Other intangible assets | F83: 4838 | G83: 4585 | H83: 4664 | I83: 11119 | J83: 10827 | K83: 11150 | L83: 11007 | M83: 11208 | N83: 12196 | O83: 11262 | P83: 10674 | Q83: 10520 | R83: 10641 | S83: 10265 | T83: 10198 | U83: 10038 | V83: 9593 | W83: 10022 | X83: 11323 | Y83: 10472 | Z83: 12199 | AA83: 11927 | AH83: 4838 | AI83: 10827 | AJ83: 12196 | AK83: 10641 | AL83: 9593 | AM83: 12199
B84: Property, plant and equipment | F84: 10250 | G84: 9786 | H84: 10089 | I84: 10621 | J84: 11023 | K84: 11204 | L84: 11157 | M84: 11414 | N84: 11733 | O84: 11400 | P84: 11423 | Q84: 11457 | R84: 11938 | S84: 11871 | T84: 12114 | U84: 12019 | V84: 12242 | W84: 12834 | X84: 12957 | Y84: 12647 | Z84: 13023 | AA84: 13260 | AH84: 10250 | AI84: 11023 | AJ84: 11733 | AK84: 11938 | AL84: 12242 | AM84: 13023
B85: Investments accounted for using the equity method | F85: 7862 | G85: 7829 | H85: 7847 | I85: 7763 | J85: 7539 | K85: 7700 | L85: 7605 | M85: 4900 | N85: 4955 | O85: 3335 | P85: 4882 | Q85: 3212 | R85: 3014 | S85: 1159 | T85: 1182 | U85: 1061 | V85: 980 | W85: 1060 | X85: 1004 | Y85: 926 | Z85: 866 | AA85: 864 | AH85: 7862 | AI85: 7539 | AJ85: 4955 | AK85: 3014 | AL85: 980 | AM85: 866
B86: Other financial assets | F86: 22771 | G86: 20537 | H86: 20175 | I86: 22243 | J86: 22964 | K86: 22395 | L86: 23152 | M86: 24172 | N86: 25903 | O86: 23591 | P86: 22929 | Q86: 23018 | R86: 22855 | S86: 24020 | T86: 24403 | U86: 26174 | V86: 27388 | W86: 27640 | X86: 27926 | Y86: 30166 | Z86: 30670 | AA86: 31430 | AH86: 22771 | AI86: 22964 | AJ86: 25903 | AK86: 22855 | AL86: 27388 | AM86: 30670
B87: Deferred tax assets | F87: 2988 | G87: 3110 | H87: 2828 | I87: 2740 | J87: 2865 | K87: 2728 | L87: 2667 | M87: 2455 | N87: 2459 | O87: 2186 | P87: 1967 | Q87: 2609 | R87: 2235 | S87: 2518 | T87: 2566 | U87: 2576 | V87: 2677 | W87: 2754 | X87: 2354 | Y87: 2349 | Z87: 1944 | AA87: 1528 | AH87: 2988 | AI87: 2865 | AJ87: 2459 | AK87: 2235 | AL87: 2677 | AM87: 1944
B88: Other assets | F88: 1769 | G88: 1597 | H88: 1657 | I88: 1958 | J88: 2183 | K88: 2438 | L88: 1948 | M88: 1924 | N88: 1565 | O88: 1447 | P88: 1565 | Q88: 1482 | R88: 1523 | S88: 1946 | T88: 2505 | U88: 2778 | V88: 2196 | W88: 2069 | X88: 2127 | Y88: 2084 | Z88: 2118 | AA88: 2564 | AH88: 1769 | AI88: 2183 | AJ88: 1565 | AK88: 1523 | AL88: 2196 | AM88: 2118
B89: Total non-current assets | F89: 70928 | G89: =SUM(G82:G88) -> 67316 | H89: 67865 | I89: 84819 | J89: 87074 | K89: 88044 | L89: 88296 | M89: 87750 | N89: 92673 | O89: 85337 | P89: 85260 | Q89: 84071 | R89: 84432 | S89: 83586 | T89: 85061 | U89: 86648 | V89: 86459 | W89: 89182 | X89: 97642 | Y89: 96665 | Z89: 101490 | AA89: 102222 | AH89: 70928 | AI89: 87074 | AJ89: 92673 | AK89: 84432 | AL89: 86459 | AM89: 101490
B90: Total assets | F90: 123897 | G90: =G81+G89 -> 121435 | H90: 131658 | I90: 136831 | J90: 139372 | K90: 144409 | L90: 143946 | M90: 145988 | N90: 151502 | O90: 143929 | P90: 142997 | Q90: 143684 | R90: 145071 | S90: 144784 | T90: 144751 | U90: 148121 | V90: 147812 | W90: 157855 | X90: 162593 | Y90: 162455 | Z90: 166202 | AA90: 170134 | AH90: 123897 | AI90: 139372 | AJ90: 151502 | AK90: 145071 | AL90: 147812 | AM90: 166202
B92: Liabilities and equity
B93: Short-term debt and current maturities of long-term debt | F93: 6562 | G93: 7538 | H93: 8528 | I93: 10778 | J93: 7821 | K93: 9701 | L93: 10499 | M93: 9899 | N93: 6658 | O93: 7106 | P93: 9411 | Q93: 9687 | R93: 7483 | S93: 9711 | T93: 7135 | U93: 7809 | V93: 6598 | W93: 8149 | X93: 18887 | Y93: 10242 | Z93: 11174 | AA93: 13630 | AH93: 6562 | AI93: 7821 | AJ93: 6658 | AK93: 7483 | AL93: 6598 | AM93: 11174
B94: Trade payables | F94: 7873 | G94: 7025 | H94: 7274 | I94: 8034 | J94: 8832 | K94: 8486 | L94: 8932 | M94: 9128 | N94: 10317 | O94: 9443 | P94: 9544 | Q94: 9454 | R94: 10130 | S94: 9204 | T94: 8947 | U94: 8348 | V94: 8843 | W94: 8701 | X94: 8764 | Y94: 8573 | Z94: 9183 | AA94: 8572 | AH94: 7873 | AI94: 8832 | AJ94: 10317 | AK94: 10130 | AL94: 8843 | AM94: 9183
B95: Other current financial liabilities | F95: 1958 | G95: 2314 | H95: 1757 | I95: 1925 | J95: 1731 | K95: 1434 | L95: 1356 | M95: 1801 | N95: 1616 | O95: 1591 | P95: 1389 | Q95: 1542 | R95: 1613 | S95: 2419 | T95: 2132 | U95: 2093 | V95: 2006 | W95: 2327 | X95: 2462 | Y95: 1238 | Z95: 1896 | AA95: 2467 | AH95: 1958 | AI95: 1731 | AJ95: 1616 | AK95: 1613 | AL95: 2006 | AM95: 1896
B96: Contract liabilities | F96: 7524 | G96: 7584 | H96: 7882 | I96: 9007 | J96: 9876 | K96: 10275 | L96: 11208 | M96: 11997 | N96: 12049 | O96: 11904 | P96: 12205 | Q96: 12692 | R96: 12571 | S96: 12780 | T96: 13258 | U96: 12792 | V96: 12855 | W96: 13310 | X96: 13371 | Y96: 12790 | Z96: 12761 | AA96: 12919 | AH96: 7524 | AI96: 9876 | AJ96: 12049 | AK96: 12571 | AL96: 12855 | AM96: 12761
B97: Current provisions | F97: 1674 | G97: 1582 | H97: 1611 | I97: 2035 | J97: 2293 | K97: 2245 | L97: 2234 | M97: 2153 | N97: 2156 | O97: 2119 | P97: 2066 | Q97: 2209 | R97: 2320 | S97: 2502 | T97: 2449 | U97: 2390 | V97: 2730 | W97: 2715 | X97: 2574 | Y97: 2414 | Z97: 2187 | AA97: 2136 | AH97: 1674 | AI97: 2293 | AJ97: 2156 | AK97: 2320 | AL97: 2730 | AM97: 2187
B98: Current income tax liabilities | F98: 2281 | G98: 2232 | H98: 1628 | I98: 1643 | J98: 1809 | K98: 1783 | L98: 1476 | M98: 1849 | N98: 2381 | O98: 2516 | P98: 2131 | Q98: 2237 | R98: 2566 | S98: 2671 | T98: 1753 | U98: 1916 | V98: 1805 | W98: 2174 | X98: 1591 | Y98: 1581 | Z98: 2094 | AA98: 2168 | AH98: 2281 | AI98: 1809 | AJ98: 2381 | AK98: 2566 | AL98: 1805 | AM98: 2094
B99: Other current liabilities | F99: 6209 | G99: 5640 | H99: 5937 | I99: 6776 | J99: 7628 | K99: 6726 | L99: 6258 | M99: 6754 | N99: 7448 | O99: 6571 | P99: 6258 | Q99: 6990 | R99: 8182 | S99: 7050 | T99: 6690 | U99: 7134 | V99: 7833 | W99: 7264 | X99: 6777 | Y99: 7126 | Z99: 7945 | AA99: 7304 | AH99: 6209 | AI99: 7628 | AJ99: 7448 | AK99: 8182 | AL99: 7833 | AM99: 7945
B100: Liabilities associated with assets classified as held for disposal | F100: 35 | G100: 711 | H100: 11 | I100: 10 | J100: 10 | K100: 43 | L100: 719 | M100: 328 | N100: 61 | O100: 33 | P100: 22 | Q100: 6 | R100: 50 | S100: 74 | T100: 38 | U100: 1312 | V100: 1245 | W100: 52 | X100: 8 | Y100: 3 | Z100: 20 | AA100: 152 | AH100: 35 | AI100: 10 | AJ100: 61 | AK100: 50 | AL100: 1245 | AM100: 20
B101: Total current liabilities | F101: 34117 | G101: =SUM(G93:G100) -> 34626 | H101: 34629 | I101: 40209 | J101: 40000 | K101: 40693 | L101: 42684 | M101: 43910 | N101: 42686 | O101: 41284 | P101: 43025 | Q101: 44818 | R101: 44913 | S101: 46413 | T101: 42400 | U101: 43795 | V101: 43913 | W101: 44691 | X101: 54434 | Y101: 43969 | Z101: 47261 | AA101: 49348 | AH101: 34117 | AI101: 40000 | AJ101: 42686 | AK101: 44913 | AL101: 43913 | AM101: 47261
B102: Long-term debt | F102: 38005 | G102: 35942 | H102: 43570 | I102: 40333 | J102: 40879 | K102: 41766 | L102: 41254 | M102: 41657 | N102: 43978 | O102: 42137 | P102: 40619 | Q102: 39203 | R102: 39113 | S102: 39610 | T102: 43316 | U102: 42093 | V102: 41321 | W102: 41735 | X102: 38635 | Y102: 46446 | Z102: 44841 | AA102: 42835 | AH102: 38005 | AI102: 40879 | AJ102: 43978 | AK102: 39113 | AL102: 41321 | AM102: 44841
B103: Provisions for pensions and similar obligations | F103: 6360 | G103: 4968 | H103: 3288 | I103: 2877 | J103: 2839 | K103: 2865 | L103: 2209 | M103: 1892 | N103: 2275 | O103: 1804 | P103: 1776 | Q103: 1692 | R103: 1426 | S103: 1505 | T103: 1383 | U103: 1328 | V103: 912 | W103: 866 | X103: 833 | Y103: 783 | Z103: 732 | AA103: 703 | AH103: 6360 | AI103: 2839 | AJ103: 2275 | AK103: 1426 | AL103: 912 | AM103: 732
B104: Deferred tax liabilities | F104: 664 | G104: 659 | H104: 677 | I104: 2360 | J104: 2337 | K104: 2563 | L104: 2692 | M104: 2535 | N104: 2381 | O104: 2162 | P104: 1889 | Q104: 2154 | R104: 1655 | S104: 1758 | T104: 1854 | U104: 1731 | V104: 1483 | W104: 1633 | X104: 1605 | Y104: 1459 | Z104: 1261 | AA104: 1390 | AH104: 664 | AI104: 2337 | AJ104: 2381 | AK104: 1655 | AL104: 1483 | AM104: 1261
B105: Provisions | F105: 2352 | G105: 2327 | H105: 2329 | I105: 1835 | J105: 1723 | K105: 1724 | L105: 1882 | M105: 1819 | N105: 1857 | O105: 1820 | P105: 1888 | Q105: 1863 | R105: 1463 | S105: 1473 | T105: 1387 | U105: 1368 | V105: 1120 | W105: 1248 | X105: 1229 | Y105: 1183 | Z105: 1198 | AA105: 1200 | AH105: 2352 | AI105: 1723 | AJ105: 1857 | AK105: 1463 | AL105: 1120 | AM105: 1198
B106: Other financial liabilities | F106: 769 | G106: 745 | H106: 738 | I106: 703 | J106: 679 | K106: 805 | L106: 875 | M106: 1298 | N106: 1867 | O106: 1894 | P106: 1802 | Q106: 1796 | R106: 1516 | S106: 1131 | T106: 1108 | U106: 1096 | V106: 864 | W106: 862 | X106: 783 | Y106: 688 | Z106: 482 | AA106: 540 | AH106: 769 | AI106: 679 | AJ106: 1867 | AK106: 1516 | AL106: 864 | AM106: 482
B107: Other liabilities | F107: 1808 | G107: 1756 | H107: 1831 | I107: 1838 | J107: 1925 | K107: 1895 | L107: 1730 | M107: 1673 | N107: 1654 | O107: 1610 | P107: 1604 | Q107: 1679 | R107: 1933 | S107: 2057 | T107: 2077 | U107: 1943 | V107: 1968 | W107: 1984 | X107: 1900 | Y107: 1888 | Z107: 2055 | AA107: 2097 | AH107: 1808 | AI107: 1925 | AJ107: 1654 | AK107: 1933 | AL107: 1968 | AM107: 2055
B108: Total non-current liabilities | F108: 49957 | G108: =SUM(G102:G107) -> 46397 | H108: 52434 | I108: 49946 | J108: 50381 | K108: 51618 | L108: 50641 | M108: 50874 | N108: 54011 | O108: 51426 | P108: 49577 | Q108: 48387 | R108: 47106 | S108: 47536 | T108: 51125 | U108: 49559 | V108: 47667 | W108: 48327 | X108: 44984 | Y108: 52447 | Z108: 50570 | AA108: 48766 | AH108: 49957 | AI108: 50381 | AJ108: 54011 | AK108: 47106 | AL108: 47667 | AM108: 50570
B109: Total liabilities | F109: 84074 | G109: =G101+G108 -> 81023 | H109: 87063 | I109: 90155 | J109: 90381 | K109: 92311 | L109: 93325 | M109: 94784 | N109: 96697 | O109: 92709 | P109: 92602 | Q109: 93205 | R109: 92019 | S109: 93948 | T109: 93525 | U109: 93353 | V109: 91581 | W109: 93018 | X109: 99418 | Y109: 96416 | Z109: 97830 | AA109: 98114 | AH109: 84074 | AI109: 90381 | AJ109: 96697 | AK109: 92019 | AL109: 91581 | AM109: 97830
B110: Equity
B111: Issued capital | F111: 2550 | G111: 2550 | H111: 2550 | I111: 2550 | J111: 2550 | K111: 2550 | L111: 2550 | M111: 2550 | N111: 2550 | O111: 2550 | P111: 2400 | Q111: 2400 | R111: 2400 | S111: 2400 | T111: 2400 | U111: 2400 | V111: 2400 | W111: 2400 | X111: 2400 | Y111: 2400 | Z111: 2400 | AA111: 2400 | AH111: 2550 | AI111: 2550 | AJ111: 2550 | AK111: 2400 | AL111: 2400 | AM111: 2400
B112: Capital reserve | F112: 6840 | G112: 6830 | H112: 6846 | I112: 6912 | J112: 7040 | K112: 6993 | L112: 7029 | M112: 7108 | N112: 7174 | O112: 7071 | P112: 7109 | Q112: 7212 | R112: 7411 | S112: 7336 | T112: 7393 | U112: 7515 | V112: 7757 | W112: 7470 | X112: 7524 | Y112: 7646 | Z112: 7895 | AA112: 7739 | AH112: 6840 | AI112: 7040 | AJ112: 7174 | AK112: 7411 | AL112: 7757 | AM112: 7895
B113: Retained earnings | F113: 33078 | G113: 34653 | H113: 36291 | I113: 38338 | J113: 39607 | K113: 41363 | L113: 39207 | M113: 37308 | N113: 38959 | O113: 39517 | P113: 34570 | Q113: 35064 | R113: 36866 | S113: 36541 | T113: 35323 | U113: 37698 | V113: 39657 | W113: 43112 | X113: 42208 | Y113: 47198 | Z113: 49601 | AA113: 52275 | AH113: 33078 | AI113: 39607 | AJ113: 38959 | AK113: 36866 | AL113: 39657 | AM113: 49601
B114: Other components of equity | F114: -1449 | G114: -2493 | H114: -939 | I114: -1065 | J114: -232 | K114: 764 | L114: 1483 | M114: 3950 | N114: 6159 | O114: 2686 | P114: 1946 | Q114: 1587 | R114: 2282 | S114: 1016 | T114: 2392 | U114: 3786 | V114: 3615 | W114: 8294 | X114: 7439 | Y114: 6112 | Z114: 5868 | AA114: 6844 | AH114: -1449 | AI114: -232 | AJ114: 6159 | AK114: 2282 | AL114: 3615 | AM114: 5868
B115: Treasury shares, at cost | F115: -4629 | G115: -4475 | H115: -4622 | I115: -4659 | J115: -4804 | K115: -4667 | L115: -4733 | M115: -5193 | N115: -5948 | O115: -6115 | P115: -830 | Q115: -901 | R115: -1177 | S115: -1282 | T115: -1308 | U115: -1598 | V115: -2165 | W115: -1872 | X115: -1998 | Y115: -2769 | Z115: -3520 | AA115: -3778 | AH115: -4629 | AI115: -4804 | AJ115: -5948 | AK115: -1177 | AL115: -2165 | AM115: -3520
B116: Total equity attributable to shareholders of Siemens AG | F116: 36390 | G116: =SUM(G111:G115) -> 37065 | H116: 40126 | I116: 42075 | J116: 44160 | K116: 47002 | L116: 45536 | M116: 45723 | N116: 48895 | O116: 45708 | P116: 45195 | Q116: 45362 | R116: 47782 | S116: 46011 | T116: 46199 | U116: 49801 | V116: 51264 | W116: 59403 | X116: 57574 | Y116: 60587 | Z116: 62244 | AA116: 65481 | AH116: 36390 | AI116: 44160 | AJ116: 48895 | AK116: 47782 | AL116: 51264 | AM116: 62244
B117: Non-controlling interests | F117: 3433 | G117: 3344 | H117: 4469 | I117: 4601 | J117: 4831 | K117: 5095 | L117: 5085 | M117: 5481 | N117: 5910 | O117: 5511 | P117: 5199 | Q117: 5117 | R117: 5270 | S117: 4825 | T117: 5026 | U117: 4966 | V117: 4967 | W117: 5433 | X117: 5601 | Y117: 5452 | Z117: 6127 | AA117: 6539 | AH117: 3433 | AI117: 4831 | AJ117: 5910 | AK117: 5270 | AL117: 4967 | AM117: 6127
...

Sheet Valuation
C2: Q1 FY20 | D2: Q2 FY20 | E2: Q3 FY20 | F2: Q4 FY20 | G2: Q1 FY21 | H2: Q2 FY21 | I2: Q3 FY21 | J2: Q4 FY21 | K2: Q1 FY22 | L2: Q2 FY22 | M2: Q3 FY22 | N2: Q4 FY22 | O2: Q1 FY23 | P2: Q2 FY23 | Q2: Q3 FY23 | R2: Q4 FY23 | S2: Q1 FY24 | T2: Q2 FY24 | U2: Q3 FY24 | V2: Q4 FY24 | W2: Q1 FY25 | X2: Q2 FY25 | Y2: Q3 FY25 | Z2: Q4 FY25 | AA2: Q1 FY26 | AB2: Q2 FY26 | AC2: Q3 FY26 | AD2: Q4 FY26 | AH2: FY2020 | AI2: FY2021 | AJ2: FY2022 | AK2: FY2023 | AL2: FY2024 | AM2: FY2025 | AN2: FY2026 | AO2: FY2027 | AP2: FY2028 | AQ2: FY2029 | AR2: FY2030
B3: Revenue | C3: =Model!C3 -> 13675 | D3: =Model!D3 -> 13784 | E3: =Model!E3 -> 12979 | F3: =Model!F3 -> 14816 | G3: =Model!G3 -> 14071 | H3: =Model!H3 -> 14665 | I3: =Model!I3 -> 16085 | J3: =Model!J3 -> 17444 | ... AD3: =Model!AD3 -> 0 | AH3: =Model!AH3 -> 55254 | AI3: =Model!AI3 -> 62265 | AJ3: =Model!AJ3 -> 71977 | AK3: =Model!AK3 -> 74882 | AL3: =Model!AL3 -> 75930 | AM3: =Model!AM3 -> 78914 | AN3: =Model!AN3 -> 0 | AO3: =Model!AO3 -> 0
B4: Gross Profit | C4: =+Model!C5 -> 4987 | D4: =+Model!D5 -> 5013 | E4: =+Model!E5 -> 4755 | F4: =+Model!F5 -> 5133 | G4: =+Model!G5 -> 5318 | H4: =+Model!H5 -> 5239 | I4: =+Model!I5 -> 5872 | J4: =+Model!J5 -> 6308 | ... AD4: =+Model!AD5 -> 0 | AH4: =+Model!AH5 -> 19888 | AI4: =+Model!AI5 -> 22737 | AJ4: =+Model!AJ5 -> 25847 | AK4: =+Model!AK5 -> 29117 | AL4: =+Model!AL5 -> 29823 | AM4: =+Model!AM5 -> 30399 | AN4: =+Model!AN5 -> 0 | AO4: =+Model!AO5 -> 0
B5: EBIT | C5: =+C4+Model!C6+Model!C7 -> 1022 | D5: =+D4+Model!D6+Model!D7 -> 1205 | E5: =+E4+Model!E6+Model!E7 -> 1149 | F5: =+F4+Model!F6+Model!F7 -> 1261 | G5: =+G4+Model!G6+Model!G7 -> 1793 | H5: =+H4+Model!H6+Model!H7 -> 1549 | I5: =+I4+Model!I6+Model!I7 -> 1712 | J5: =+J4+Model!J6+Model!J7 -> 1633 | ... AD5: =+AD4+Model!AD6+Model!AD7 -> 0 | AH5: =+AH4+Model!AH6+Model!AH7 -> 4637 | AI5: =+AI4+Model!AI6+Model!AI7 -> 6687 | AJ5: =+AJ4+Model!AJ6+Model!AJ7 -> 7399 | AK5: =+AK4+Model!AK6+Model!AK7 -> 9451 | AL5: =+AL4+Model!AL6+Model!AL7 -> 9563 | AM5: =+AM4+Model!AM6+Model!AM7 -> 9013 | AN5: =+AN4+Model!AN6+Model!AN7 -> 0 | AO5: =+AO4+Model!AO6+Model!AO7 -> 0
B6: Net Income | C6: =Model!C18 -> 1089 | D6: =Model!D18 -> 697 | E6: =Model!E18 -> 535 | F6: =Model!F18 -> 1879 | G6: =Model!G18 -> 1497 | H6: =Model!H18 -> 2390 | I6: =Model!I18 -> 1480 | J6: =Model!J18 -> 1330 | ... AD6: =Model!AD18 -> 0 | AH6: =Model!AH18 -> 4200 | AI6: =Model!AI18 -> 6697 | AJ6: =Model!AJ18 -> 4392 | AK6: =Model!AK18 -> 8529 | AL6: =Model!AL18 -> 8992 | AM6: =Model!AM18 -> 10387 | AN6: =Model!AN18 -> 0 | AO6: =Model!AO18 -> 0
B8: Cash | F8: =Model!F73 -> 14041 | G8: =Model!G73 -> 14016 | H8: =Model!H73 -> 23639 | I8: =Model!I73 -> 10678 | J8: =Model!J73 -> 9545 | K8: =Model!K73 -> 12199 | L8: =Model!L73 -> 9495 | M8: =Model!M73 -> 10097 | ... AD8: =Model!AD73 -> 0 | AH8: =Model!AH73 -> 14041 | AI8: =Model!AI73 -> 9545 | AJ8: =Model!AJ73 -> 10465 | AK8: =Model!AK73 -> 10084 | AL8: =Model!AL73 -> 9156 | AM8: =Model!AM73 -> 14495 | AN8: =Model!AN73 -> 0 | AO8: =Model!AO73 -> 0
B9: Total Assets | F9: =Model!F90 -> 123897 | G9: =Model!G90 -> 121435 | H9: =Model!H90 -> 131658 | I9: =Model!I90 -> 136831 | J9: =Model!J90 -> 139372 | K9: =Model!K90 -> 144409 | L9: =Model!L90 -> 143946 | M9: =Model!M90 -> 145988 | ... AD9: =Model!AD90 -> 0 | AH9: =Model!AH90 -> 123897 | AI9: =Model!AI90 -> 139372 | AJ9: =Model!AJ90 -> 151502 | AK9: =Model!AK90 -> 145071 | AL9: =Model!AL90 -> 147812 | AM9: =Model!AM90 -> 166202 | AN9: =Model!AN90 -> 0 | AO9: =Model!AO90 -> 0
B10: Total Debt | F10: =Model!F93+Model!F102 -> 44567 | G10: =Model!G93+Model!G102 -> 43480 | H10: =Model!H93+Model!H102 -> 52098 | I10: =Model!I93+Model!I102 -> 51111 | J10: =Model!J93+Model!J102 -> 48700 | K10: =Model!K93+Model!K102 -> 51467 | L10: =Model!L93+Model!L102 -> 51753 | M10: =Model!M93+Model!M102 -> 51556 | ... AD10: =Model!AD93+Model!AD102 -> 0 | AH10: =Model!AH93+Model!AH102 -> 44567 | AI10: =Model!AI93+Model!AI102 -> 48700 | AJ10: =Model!AJ93+Model!AJ102 -> 50636 | AK10: =Model!AK93+Model!AK102 -> 46596 | AL10: =Model!AL93+Model!AL102 -> 47919 | AM10: =Model!AM93+Model!AM102 -> 56015 | AN10: =Model!AN93+Model!AN102 -> 0 | AO10: =Model!AO93+Model!AO102 -> 0
B11: Total Liabilities | F11: =+Model!F109 -> 84074 | G11: =+Model!G109 -> 81023 | H11: =+Model!H109 -> 87063 | I11: =+Model!I109 -> 90155 | J11: =+Model!J109 -> 90381 | K11: =+Model!K109 -> 92311 | L11: =+Model!L109 -> 93325 | M11: =+Model!M109 -> 94784 | ... AD11: =+Model!AD109 -> 0 | AH11: =+Model!AH109 -> 84074 | AI11: =+Model!AI109 -> 90381 | AJ11: =+Model!AJ109 -> 96697 | AK11: =+Model!AK109 -> 92019 | AL11: =+Model!AL109 -> 91581 | AM11: =+Model!AM109 -> 97830 | AN11: =+Model!AN109 -> 0 | AO11: =+Model!AO109 -> 0
B12: Equity | F12: =+Model!F118 -> 39823 | G12: =+Model!G118 -> 40409 | H12: =+Model!H118 -> 44595 | I12: =+Model!I118 -> 46676 | J12: =+Model!J118 -> 48991 | K12: =+Model!K118 -> 52098 | L12: =+Model!L118 -> 50621 | M12: =+Model!M118 -> 51204 | ... AD12: =+Model!AD118 -> 0 | AH12: =+Model!AH118 -> 39823 | AI12: =+Model!AI118 -> 48991 | AJ12: =+Model!AJ118 -> 54805 | AK12: =+Model!AK118 -> 53052 | AL12: =+Model!AL118 -> 56231 | AM12: =+Model!AM118 -> 68371 | AN12: =+Model!AN118 -> 0 | AO12: =+Model!AO118 -> 0
B14: CFFO | C14: =+Model!C166 -> 531 | D14: =+Model!D166 -> 669 | E14: =+Model!E166 -> 3020 | F14: =+Model!F166 -> 4642 | G14: =+Model!G166 -> 1312 | H14: =+Model!H166 -> 1594 | I14: =+Model!I166 -> 2692 | J14: =+Model!J166 -> 4398 | ... AD14: =+Model!AD166 -> 0 | AH14: =+Model!AH166 -> 8862 | AI14: =+Model!AI166 -> 9996 | AJ14: =+Model!AJ166 -> 10241 | AK14: =+Model!AK166 -> 12239 | AL14: =+Model!AL166 -> 11665 | AM14: =+Model!AM166 -> 13257 | AN14: =+Model!AN166 -> 0 | AO14: =+Model!AO166 -> 0
B15: CFFI | C15: =+Model!C177 -> -2196 | D15: =+Model!D177 -> -1407 | E15: =+Model!E177 -> -266 | F15: =+Model!F177 -> -1315 | G15: =+Model!G177 -> -448 | H15: =+Model!H177 -> 1071 | I15: =+Model!I177 -> -14501 | J15: =+Model!J177 -> -1616 | ... AD15: =+Model!AD177 -> 0 | AH15: =+Model!AH177 -> -5184 | AI15: =+Model!AI177 -> -15494 | AJ15: =+Model!AJ177 -> -2490 | AK15: =+Model!AK177 -> -3176 | AL15: =+Model!AL177 -> -3282 | AM15: =+Model!AM177 -> -11314 | AN15: =+Model!AN177 -> 0 | AO15: =+Model!AO177 -> 0
B16: CFFF | C16: =+Model!C189 -> 704 | D16: =+Model!D189 -> -672 | E16: =+Model!E189 -> 1918 | F16: =+Model!F189 -> 1222 | G16: =+Model!G189 -> -619 | H16: =+Model!H189 -> 6573 | I16: =+Model!I189 -> -1101 | J16: =+Model!J189 -> -4068 | ... AD16: =+Model!AD189 -> 0 | AH16: =+Model!AH189 -> 3172 | AI16: =+Model!AI189 -> 785 | AJ16: =+Model!AJ189 -> -7502 | AK16: =+Model!AK189 -> -8731 | AL16: =+Model!AL189 -> -8880 | AM16: =+Model!AM189 -> 3641 | AN16: =+Model!AN189 -> 0 | AO16: =+Model!AO189 -> 0
B17: CF | C17: =+Model!C192 -> -1041 | D17: =+Model!D192 -> -1480 | E17: =+Model!E192 -> 4580 | F17: =+Model!F192 -> -396 | G17: =+Model!G192 -> 28 | H17: =+Model!H192 -> 9556 | I17: =+Model!I192 -> -12961 | J17: =+Model!J192 -> -1132 | ... AD17: =+Model!AD192 -> 0 | AH17: =+Model!AH192 -> 1663 | AI17: =+Model!AI192 -> -4509 | AJ17: =+Model!AJ192 -> 927 | AK17: =+Model!AK192 -> -388 | AL17: =+Model!AL192 -> -717 | AM17: =+Model!AM192 -> 5135 | AN17: =+Model!AN192 -> 0 | AO17: =+Model!AO192 -> 0
B19: CapEx | C19: =Model!C168 -> -338 | D19: =Model!D168 -> -342 | E19: =Model!E168 -> -332 | F19: =Model!F168 -> -486 | G19: =Model!G168 -> -329 | H19: =Model!H168 -> -363 | I19: =Model!I168 -> -418 | J19: =Model!J168 -> -620 | ... AD19: =Model!AD168 -> 0 | AH19: =Model!AH168 -> -1498 | AI19: =Model!AI168 -> -1730 | AJ19: =Model!AJ168 -> -2084 | AK19: =Model!AK168 -> -2146 | AL19: =Model!AL168 -> -2088 | AM19: =Model!AM168 -> -2445 | AN19: =Model!AN168 -> 0 | AO19: =Model!AO168 -> 0
B20: Model FCF | C20: =+Model!C199 -> 201 | D20: =+Model!D199 -> 359 | E20: =+Model!E199 -> 2694 | F20: =+Model!F199 -> 4157 | G20: =+Model!G199 -> 1032 | H20: =+Model!H199 -> 1232 | I20: =+Model!I199 -> 2287 | J20: =+Model!J199 -> 3813 | ... AD20: =+Model!AD199 -> 0 | AH20: =+Model!AH199 -> 7411 | AI20: =+Model!AI199 -> 8364 | AJ20: =+Model!AJ199 -> 8433 | AK20: =+Model!AK199 -> 10329 | AL20: =+Model!AL199 -> 9814 | AM20: =+Model!AM199 -> 10998 | AN20: =+Model!AN199 -> 0 | AO20: =+Model!AO199 -> 0
B22: Reported FCF | C22: =+Model!C325 -> -3 | D22: =+Model!D325 -> 685 | E22: =+Model!E325 -> 1920 | F22: =+Model!F325 -> 3750 | G22: =+Model!G325 -> 906 | H22: =+Model!H325 -> 1326 | I22: =+Model!I325 -> 2285 | J22: =+Model!J325 -> 3862 | ... AD22: =+Model!AD325 -> 0 | AH22: =+Model!AH325 -> 6352 | AI22: =+Model!AI325 -> 8379 | AJ22: =+Model!AJ325 -> 8238 | AK22: =+Model!AK325 -> 10146 | AL22: =+Model!AL325 -> 9726 | AM22: =+Model!AM325 -> 11004 | AN22: =+Model!AN325 -> 0 | AO22: =+Model!AO325 -> 0
B24: EBITDA | C24: =Model!C338 -> 1950 | D24: =Model!D338 -> 1952 | E24: =Model!E338 -> 1798 | F24: =Model!F338 -> 1673 | G24: =Model!G338 -> 2454 | H24: =Model!H338 -> 2141 | I24: =Model!I338 -> 2366 | J24: =Model!J338 -> 2178 | ... AD24: =Model!AD338 -> 0 | AH24: =Model!AH338 -> 7373 | AI24: =Model!AI338 -> 9139 | AJ24: =Model!AJ338 -> 10759 | AK24: =Model!AK338 -> 14026 | AL24: =Model!AL338 -> 13577 | AM24: =Model!AM338 -> 13380 | AN24: =Model!AN338 -> 0 | AO24: =Model!AO338 -> 0
B26: Implied Basic S/O | C26: =C6/Model!C27 -> 818.79699 | D26: =D6/Model!D27 -> 871.25 | E26: =E6/Model!E27 -> 798.50746 | F26: =F6/Model!F27 -> 854.09091 | G26: =G6/Model!G27 -> 865.31792 | H26: =H6/Model!H27 -> 847.51773 | I26: =I6/Model!I27 -> 880.95238 | J26: =J6/Model!J27 -> 917.24138 | ... AD26: =AD6/Model!AD27 -> #DIV/0! | AH26: =AH6/Model!AH27 -> 840 | AI26: =AI6/Model!AI27 -> 872.00521 | AJ26: =AJ6/Model!AJ27 -> 944.51613 | AK26: =AK6/Model!AK27 -> 849.50199 | AL26: =AL6/Model!AL27 -> 853.94112 | AM26: =AM6/Model!AM27 -> 847.91837 | AN26: =AN6/Model!AN27 -> #DIV/0! | AO26: =AO6/Model!AO27 -> #DIV/0!
B27: Implied Diluted S/O | C27: =C6/Model!C32 -> 837.69231 | D27: =D6/Model!D32 -> 882.27848 | E27: =E6/Model!E32 -> 798.50746 | F27: =F6/Model!F32 -> 865.89862 | G27: =G6/Model!G32 -> 875.4386 | H27: =H6/Model!H32 -> 856.63082 | I27: =I6/Model!I32 -> 891.56627 | J27: =J6/Model!J32 -> 930.06993 | ... AD27: =AD6/Model!AD32 -> #DIV/0! | AH27: =AH6/Model!AH32 -> 851.92698 | AI27: =AI6/Model!AI32 -> 882.34519 | AJ27: =AJ6/Model!AJ32 -> 956.86275 | AK27: =AK6/Model!AK32 -> 860.64581 | AL27: =AL6/Model!AL32 -> 866.28131 | AM27: =AM6/Model!AM32 -> 857.72089 | AN27: =AN6/Model!AN32 -> #DIV/0! | AO27: =AO6/Model!AO32 -> #DIV/0!
B30: Price | C30: 62.26 | D30: 47.88 | E30: 67.905 | F30: 72.66 | G30: 81.65 | H30: 87.77 | I30: 83.67 | J30: 86.61 | K30: 82.1 | L30: 58.92 | M30: 56.53 | N30: 67.33 | O30: 79.47 | P30: 83.68 | Q30: 81.86 | R30: 79.72 | S30: 91.775 | T30: 95 | U30: 87.22 | V30: 100.55 | W30: 119.24 | X30: 124.62 | Y30: 135.75 | Z30: 134 | AA30: 140
B31: MC | C31: =C26*C30*2 -> 101956.6 | D31: =D26*D30*2 -> 83430.9 | E31: =E26*E30*2 -> 108445.3 | F31: =F26*F30*2 -> 124116.49 | G31: =G26*G30*2 -> 141306.42 | H31: =H26*H30*2 -> 148773.26 | I31: =I26*I30*2 -> 147418.57 | J31: =J26*J30*2 -> 158884.55 | ... AD31: =AD26*AD30*2 -> #DIV/0!
B33: EV | C33: =C31-C8+C10 -> 101956.6 | D33: =D31-D8+D10 -> 83430.9 | E33: =E31-E8+E10 -> 108445.3 | F33: =F31-F8+F10 -> 154642.49 | G33: =G31-G8+G10 -> 170770.42 | H33: =H31-H8+H10 -> 177232.26 | I33: =I31-I8+I10 -> 187851.57 | J33: =J31-J8+J10 -> 198039.55 | ... AD33: =AD31-AD8+AD10 -> #DIV/0!
B36: Trl P/E | C36: 29.551545 | D36: 29.551545 | E36: 29.551545 | F36: =(F31)/SUM(C6:F6) -> 29.551545 | G36: =(G31)/SUM(D6:G6) -> 30.665455 | H36: =(H31)/SUM(E6:H6) -> 23.611056 | I36: =(I31)/SUM(F6:I6) -> 20.344821 | J36: =(J31)/SUM(G6:J6) -> 23.724735 | K36: =(K31)/SUM(H6:K6) -> 20.562496 | L36: =(L31)/SUM(I6:L6) -> 19.042127 | M36: =(M31)/SUM(J6:M6) -> 29.924014 | ... AD36: =(AD31)/SUM(AA6:AD6) -> #DIV/0!
B37: Trl EV/FCF | C37: 20.866616 | D37: 20.866616 | E37: 20.866616 | F37: =F33/SUM(C20:F20) -> 20.866616 | G37: =G33/SUM(D20:G20) -> 20.719536 | H37: =H33/SUM(E20:H20) -> 19.444022 | I37: =I33/SUM(F20:I20) -> 21.572298 | J37: =J33/SUM(G20:J20) -> 23.677613 | K37: =K33/SUM(H20:K20) -> 21.645771 | L37: =L33/SUM(I20:L20) -> 17.8688 | M37: =M33/SUM(J20:M20) -> 14.62707 | ... AD37: =AD33/SUM(AA20:AD20) -> #DIV/0!
B38: Trl EV/EBITDA | C38: 20.974161 | D38: 20.974161 | E38: 20.974161 | F38: =F33/SUM(C24:F24) -> 20.974161 | G38: =G33/SUM(D24:G24) -> 21.679626 | H38: =H33/SUM(E24:H24) -> 21.972758 | I38: =I33/SUM(F24:I24) -> 21.757189 | J38: =J33/SUM(G24:J24) -> 21.669718 | K38: =K33/SUM(H24:K24) -> 18.85924 | L38: =L33/SUM(I24:L24) -> 15.377149 | M38: =M33/SUM(J24:M24) -> 15.522715 | ... AD38: =AD33/SUM(AA24:AD24) -> #DIV/0!
B43: Inventories | F43: =Model!F77+Model!F85 -> 15657 | G43: =Model!G77+Model!G85 -> 15572 | H43: =Model!H77+Model!H85 -> 15803 | I43: =Model!I77+Model!I85 -> 16719 | J43: =Model!J77+Model!J85 -> 16375 | K43: =Model!K77+Model!K85 -> 17437 | L43: =Model!L77+Model!L85 -> 17719 | M43: =Model!M77+Model!M85 -> 15686 | ... AD43: =Model!AD77+Model!AD85 -> 0 | AH43: =Model!AH77+Model!AH85 -> 15657 | AI43: =Model!AI77+Model!AI85 -> 16375 | AJ43: =Model!AJ77+Model!AJ85 -> 15581 | AK43: =Model!AK77+Model!AK85 -> 14562 | AL43: =Model!AL77+Model!AL85 -> 11903 | AM43: =Model!AM77+Model!AM85 -> 11448 | AN43: =Model!AN77+Model!AN85 -> 0 | AO43: =Model!AO77+Model!AO85 -> 0 | ... AQ43: =Model!AQ77+Model!AQ85 -> 0
B44: A/R | F44: =Model!F74 -> 14074 | G44: =Model!G74 -> 13866 | H44: =Model!H74 -> 13951 | I44: =Model!I74 -> 15126 | J44: =Model!J74 -> 15518 | K44: =Model!K74 -> 15916 | L44: =Model!L74 -> 15960 | M44: =Model!M74 -> 16162 | ... AD44: =Model!AD74 -> 0 | AH44: =Model!AH74 -> 14074 | AI44: =Model!AI74 -> 15518 | AJ44: =Model!AJ74 -> 16701 | AK44: =Model!AK74 -> 17405 | AL44: =Model!AL74 -> 16963 | AM44: =Model!AM74 -> 16628 | AN44: =Model!AN74 -> 0 | AO44: =Model!AO74 -> 0 | ... AQ44: =Model!AQ74 -> 0
B45: A/P | F45: =Model!F94 -> 7873 | G45: =Model!G94 -> 7025 | H45: =Model!H94 -> 7274 | I45: =Model!I94 -> 8034 | J45: =Model!J94 -> 8832 | K45: =Model!K94 -> 8486 | L45: =Model!L94 -> 8932 | M45: =Model!M94 -> 9128 | ... AD45: =Model!AD94 -> 0 | AH45: =Model!AH94 -> 7873 | AI45: =Model!AI94 -> 8832 | AJ45: =Model!AJ94 -> 10317 | AK45: =Model!AK94 -> 10130 | AL45: =Model!AL94 -> 8843 | AM45: =Model!AM94 -> 9183 | AN45: =Model!AN94 -> 0 | AO45: =Model!AO94 -> 0 | ... AQ45: =Model!AQ94 -> 0
B46: Working capital, net | F46: =F43+F44-F45 -> 21858 | G46: =G43+G44-G45 -> 22413 | H46: =H43+H44-H45 -> 22480 | I46: =I43+I44-I45 -> 23811 | J46: =J43+J44-J45 -> 23061 | K46: =K43+K44-K45 -> 24867 | L46: =L43+L44-L45 -> 24747 | M46: =M43+M44-M45 -> 22720 | ... AD46: =AD43+AD44-AD45 -> 0 | AH46: =AH43+AH44-AH45 -> 21858 | AI46: =AI43+AI44-AI45 -> 23061 | AJ46: =AJ43+AJ44-AJ45 -> 21965 | AK46: =AK43+AK44-AK45 -> 21837 | AL46: =AL43+AL44-AL45 -> 20023 | AM46: =AM43+AM44-AM45 -> 18893 | AN46: =AN43+AN44-AN45 -> 0 | AO46: =AO43+AO44-AO45 -> 0 | ... AQ46: =AQ43+AQ44-AQ45 -> 0
B47: % of sales TTM | F47: =F46/SUM(C3:F3) -> 0.39559127 | G47: =G46/SUM(D3:G3) -> 0.40274933 | H47: =H46/SUM(E3:H3) -> 0.39765792 | I47: =I46/SUM(F3:I3) -> 0.39926556 | J47: =J46/SUM(G3:J3) -> 0.37036859 | K47: =K46/SUM(H3:K3) -> 0.38439659 | L47: =L46/SUM(I3:L3) -> 0.36899472 | M47: =M46/SUM(J3:M3) -> 0.33000232 | ... AD47: =AD46/SUM(AA3:AD3) -> 0 | AH47: =AH46/AH3 -> 0.39559127 | AI47: =AI46/AI3 -> 0.37036859 | AJ47: =AJ46/AJ3 -> 0.30516693 | AK47: =AK46/AK3 -> 0.29161881 | AL47: =AL46/AL3 -> 0.26370341 | AM47: =AM46/AM3 -> 0.23941253 | AN47: =AN46/AN3 -> #DIV/0! | AO47: =AO46/AO3 -> #DIV/0! | ... AQ47: =AQ46/AQ3 -> #DIV/0!
B48: Change in working capital | G48: =G46-F46 -> 555 | H48: =H46-G46 -> 67 | I48: =I46-H46 -> 1331 | J48: =J46-I46 -> -750 | K48: =K46-J46 -> 1806 | L48: =L46-K46 -> -120 | M48: =M46-L46 -> -2027 | N48: =N46-M46 -> -755 | ... AD48: =AD46-AC46 -> 0 | AI48: =AI46-AH46 -> 1203 | AJ48: =AJ46-AI46 -> -1096 | AK48: =AK46-AJ46 -> -128 | AL48: =AL46-AK46 -> -1814 | AM48: =AM46-AL46 -> -1130 | AN48: =AN46-AM46 -> -18893 | AO48: =AO46-AN46 -> 0 | AP48: =AP46-AO46 -> 0 | AQ48: =AQ46-AP46 -> 0
B50: Days inventories on hand TTM | F50: =365/((-SUM(Model!C4:G4))/Valuation!F43) -> 129.53748 | G50: =365/((-SUM(Model!D4:H4))/((Valuation!G43+F43)/2)) -> 127.06036 | H50: =365/((-SUM(Model!E4:I4))/((Valuation!H43+G43)/2)) -> 123.67837 | I50: =365/((-SUM(Model!F4:J4))/((Valuation!I43+H43)/2)) -> 120.61095 | J50: =365/((-SUM(Model!G4:K4))/((Valuation!J43+I43)/2)) -> 121.23196 | K50: =365/((-SUM(Model!H4:L4))/((Valuation!K43+J43)/2)) -> 117.83322 | L50: =365/((-SUM(Model!I4:M4))/((Valuation!L43+K43)/2)) -> 117.55167 | M50: =365/((-SUM(Model!J4:N4))/((Valuation!M43+L43)/2)) -> 106.45408 | N50: =365/((-SUM(Model!K4:O4))/((Valuation!N43+M43)/2)) -> 99.698218 | ... AD50: =365/((-SUM(Model!AA4:AE4))/((Valuation!AD43+AC43)/2)) -> #DIV/0! | AH50: =365/(-Model!AH4/Valuation!AH43) -> 161.59037 | AI50: =365/(-Model!AI4/((Valuation!AI43+AH43)/2)) -> 147.89486 | AJ50: =365/(-Model!AJ4/((Valuation!AJ43+AI43)/2)) -> 126.42467 | AK50: =365/(-Model!AK4/((Valuation!AK43+AJ43)/2)) -> 120.20053 | AL50: =365/(-Model!AL4/((Valuation!AL43+AK43)/2)) -> 104.75335 | AM50: =365/(-Model!AM4/((Valuation!AM43+AL43)/2)) -> 87.839998 | AN50: =365/(-Model!AN4/((Valuation!AN43+AM43)/2)) -> #DIV/0! | AO50: =365/(-Model!AO4/((Valuation!AO43+AN43)/2)) -> #DIV/0! | AP50: =365/(-Model!AP4/((Valuation!AP43+AO43)/2)) -> #DIV/0! | AQ50: =365/(-Model!AQ4/((Valuation!AQ43+AP43)/2)) -> #DIV/0!
B51: Days sales outstanding TTM | F51: =365/(SUM(C3:F3)/F44) -> 92.970826 | G51: =365/(SUM(D3:G3)/((G44+F44)/2)) -> 91.627134 | H51: =365/(SUM(E3:H3)/((H44+G44)/2)) -> 89.8021 | I51: =365/(SUM(F3:I3)/((I44+H44)/2)) -> 88.980876 | J51: =365/(SUM(G3:J3)/((J44+I44)/2)) -> 89.818196 | K51: =365/(SUM(H3:K3)/((K44+J44)/2)) -> 88.678564 | L51: =365/(SUM(I3:L3)/((L44+K44)/2)) -> 86.740972 | M51: =365/(SUM(J3:M3)/((M44+L44)/2)) -> 85.147935 | N51: =365/(SUM(K3:N3)/((N44+M44)/2)) -> 83.325194 | ... AD51: =365/(SUM(AA3:AD3)/((AD44+AC44)/2)) -> #DIV/0! | AH51: =365/(AH3/AH44) -> 92.970826 | AI51: =365/(AI3/((AI44+AH44)/2)) -> 86.734763 | AJ51: =365/(AJ3/((AJ44+AI44)/2)) -> 81.692311 | AK51: =365/(AK3/((AK44+AJ44)/2)) -> 83.122045 | AL51: =365/(AL3/((AL44+AK44)/2)) -> 82.604504 | AM51: =365/(AM3/((AM44+AL44)/2)) -> 77.684029 | AN51: =365/(AN3/((AN44+AM44)/2)) -> #DIV/0! | AO51: =365/(AO3/((AO44+AN44)/2)) -> #DIV/0! | AP51: =365/(AP3/((AP44+AO44)/2)) -> #DIV/0! | AQ51: =365/(AQ3/((AQ44+AP44)/2)) -> #DIV/0!
B52: Days payable outstanding TTM | F52: =365/((-SUM(Model!C4:G4))/F45) -> 65.136909 | G52: =365/((-SUM(Model!D4:H4))/((Valuation!G45+F45)/2)) -> 60.614982 | H52: =365/((-SUM(Model!E4:I4))/((Valuation!H45+G45)/2)) -> 56.365801 | I52: =365/((-SUM(Model!F4:J4))/((Valuation!I45+H45)/2)) -> 56.771185 | J52: =365/((-SUM(Model!G4:K4))/((Valuation!J45+I45)/2)) -> 61.78456 | K52: =365/((-SUM(Model!H4:L4))/((Valuation!K45+J45)/2)) -> 60.35241 | L52: =365/((-SUM(Model!I4:M4))/((Valuation!L45+K45)/2)) -> 58.240839 | M52: =365/((-SUM(Model!J4:N4))/((Valuation!M45+L45)/2)) -> 57.553084 | N52: =365/((-SUM(Model!K4:O4))/((Valuation!N45+M45)/2)) -> 62.00249 | ... AD52: =365/((-SUM(Model!AA4:AE4))/((Valuation!AD45+AC45)/2)) -> #DIV/0! | AH52: =365/(-Model!AH4/Valuation!AH45) -> 81.254453 | AI52: =365/(-Model!AI4/((Valuation!AI45+AH45)/2)) -> 77.128608 | AJ52: =365/(-Model!AJ4/((Valuation!AJ45+AI45)/2)) -> 75.757479 | AK52: =365/(-Model!AK4/((Valuation!AK45+AJ45)/2)) -> 81.53602 | AL52: =365/(-Model!AL4/((Valuation!AL45+AK45)/2)) -> 75.098629 | AM52: =365/(-Model!AM4/((Valuation!AM45+AL45)/2)) -> 67.808822 | AN52: =365/(-Model!AN4/((Valuation!AN45+AM45)/2)) -> #DIV/0! | AO52: =365/(-Model!AO4/((Valuation!AO45+AN45)/2)) -> #DIV/0! | AP52: =365/(-Model!AP4/((Valuation!AP45+AO45)/2)) -> #DIV/0! | AQ52: =365/(-Model!AQ4/((Valuation!AQ45+AP45)/2)) -> #DIV/0!
B53: Cash Conversion Cycle | F53: =F50+F51-F52 -> 157.3714 | G53: =G50+G51-G52 -> 158.07251 | H53: =H50+H51-H52 -> 157.11467 | I53: =I50+I51-I52 -> 152.82064 | J53: =J50+J51-J52 -> 149.2656 | K53: =K50+K51-K52 -> 146.15937 | L53: =L50+L51-L52 -> 146.0518 | M53: =M50+M51-M52 -> 134.04894 | ... AD53: =AD50+AD51-AD52 -> #DIV/0! | AH53: =AH50+AH51-AH52 -> 173.30674 | AI53: =AI50+AI51-AI52 -> 157.50101 | AJ53: =AJ50+AJ51-AJ52 -> 132.3595 | AK53: =AK50+AK51-AK52 -> 121.78656 | AL53: =AL50+AL51-AL52 -> 112.25922 | AM53: =AM50+AM51-AM52 -> 97.715205 | AN53: =AN50+AN51-AN52 -> #DIV/0! | AO53: =AO50+AO51-AO52 -> #DIV/0! | ... AQ53: =AQ50+AQ51-AQ52 -> #DIV/0!

Sheet Norge Ownership
E2: Company | F2: Value | G2: Currency | H2: Rate | I2: USD | J2: Ownership % | K2: Country | L2: Sector
E3: Siemens AG | F3: 40757194248 | G3: NOK | H3: 9.6305 | I3: =F3/$H$3 -> 4.2320953e+09 | J3: 0.018 | K3: Germany | L3: Industrials
E4: Siemens Energy AG | F4: 23721468884 | G4: NOK | I4: =F4/$H$3 -> 2.4631607e+09 | J4: 0.0193 | K4: Germany | L4: Energy
E5: Siemens Healthcare AG | F5: 12471723386 | G5: NOK | I5: =F5/$H$3 -> 1.2950235e+09 | J5: 0.0208 | K5: Germany | L5: Healthcare
E6: General Electric Co | F6: 41916805908 | G6: NOK | I6: =F6/$H$3 -> 4.3525057e+09 | J6: 0.0128 | K6: United States | L6: Industrials
E7: GE Vernova Inc | F7: 21824505506 | G7: NOK | I7: =F7/$H$3 -> 2.2661861e+09 | J7: 0.0122 | K7: United States | L7: Industrials
E8: Schneider Electric SE | F8: 36763709310 | G8: NOK | I8: =F8/$H$3 -> 3.8174248e+09 | J8: 0.0229 | K8: France | L8: Industrials
E9: ABB Ltd | F9: 21558767704 | G9: NOK | I9: =F9/$H$3 -> 2.2385928e+09 | J9: 0.0155 | K9: Switzerland | L9: Industrials
E10: Rockwell Automation Inc | F10: 5200185686 | G10: NOK | I10: =F10/$H$3 -> 5.3997048e+08 | J10: 0.0118 | K10: United States | L10: Industrials
E11: Emerson Electric Co | F11: 9454991822 | G11: NOK | I11: =F11/$H$3 -> 9.817758e+08 | J11: 0.0126 | K11: United States | L11: Industrials
E12: Mitsubishi Electric Corp | F12: 10116783439 | G12: NOK | I12: =F12/$H$3 -> 1.0504941e+09 | J12: 0.0162 | K12: Japan | L12: Industrials
E13: Panasonic Holdings Corp | F13: 4921305417 | G13: NOK | I13: =F13/$H$3 -> 5.1101245e+08 | J13: 0.0154 | K13: Japan | L13: Consumer Discretionary
E14: Hitachi Ltd | F14: 23796328080 | G14: NOK | I14: =F14/$H$3 -> 2.4709338e+09 | J14: 0.0165 | K14: Japan | L14: Industrials
E15: Toshiba TEC Corp | F15: 26060746 | G15: NOK | I15: =F15/$H$3 -> 2706063.7 | J15: 0.0026 | K15: Japan | L15: Technology
... E18: thyssenkrupp AG | F18: 934836496 | G18: NOK | I18: =F18/$H$3 -> 97070401 | J18: 0.0137 | K18: Germany | L18: Industrials
