Workbook

Sheet Main
A1: SaaS
Q4: Q1 FY27 Guidance | U4: FY27 Guidance
I5: Price | J5: 19.78 | M5: 1Yβ | N5: 1.544 | P5: Revenue | Q5: 253 | R5: 255 | U5: 1099 | V5: 1118
I6: S/O | J6: =+FS!Q21/1000 -> 167.407 | K6: Q3FY26 | M6: US 1-YR | N6: 3.607 | P6: Non-GAAP EBIT | Q6: 32 | R6: 34 | U6: 129 | V6: 137
I7: MC | J7: =J5*J6 -> 3311.3105 | M7: E[M] | N7: 0.2 | P7: Margin | Q7: =Q6/Q5 -> 0.12648221 | R7: =R6/R5 -> 0.13333333 | U7: =U6/U5 -> 0.11737944 | V7: =V6/V5 -> 0.12254025
I8: Cash | J8: =+FS!Q50/1000 -> 1204.308 | K8: Q3FY26 | M8: E[GTLB] | N8: =N6/100+N5*(N7-N6/100) -> 0.28917792 | P8: Diluted WASO | R8: 173 | V8: 175
I9: Debt | J9: 0 | K9: Q3FY26 | P9: Non-GAAP EPS | Q9: 0.2 | R9: 0.21 | U9: 0.76 | V9: 0.8
P10: Implied Non-GAAP NI | Q10: =+Q9*R8 -> 34.6 | R10: =R9*R8 -> 36.33 | U10: =U9*V8 -> 133 | V10: =+V9*V8 -> 140
I11: EV | J11: =J7-J8+J94 -> 2107.0025 | P11: Net Margin | Q11: =Q10/Q5 -> 0.13675889 | R11: =R10/R5 -> 0.14247059 | U11: =U10/U5 -> 0.12101911 | V11: =V10/V5 -> 0.12522361
J14: =1000/J5 -> 50.556117
J15: =J14/J6 -> 0.30199524

Sheet FS
A1: Main | B1: 45802
B2: INCOME STATEMENT | C2: Q123 | D2: Q223 | E2: Q323 | F2: Q423 | G2: Q124 | H2: Q224 | I2: Q324 | J2: Q424 | K2: Q125 | L2: Q225 | M2: Q325 | N2: Q425 | O2: Q126 | P2: Q226 | Q2: Q326 | R2: Q426 | S2: Q127 | T2: Q227 | U2: Q327 | V2: Q427 | W2: Q128 | X2: Q228 | Y2: Q328 | Z2: Q428 | AC2: 2023 | AD2: 2024 | AE2: 2025 | AF2: 2026 | AG2: 2027 | AH2: 2028 | AI2: 2029 | AJ2: 2030 | AK2: 2031 | AL2: 2032 | AM2: 2033 | AN2: 2034 | AO2: 2035 | AP2: 2036 | AQ2: 2037 | AR2: 2038 | AS2: 2039 | AT2: 2040 | AU2: 2041 | AV2: 2042 | AW2: 2043 | AX2: 2044 | AY2: 2045 | AZ2: 2046 | BA2: 2047 | BB2: 2048 | BC2: 2049 | BD2: 2050 | BE2: 2051 | BF2: 2052 | BG2: 2053 | BH2: 2054 | BI2: 2055 | BJ2: 2056 | BK2: 2057 | BL2: 2058 | BM2: 2059 | BN2: 2060 | BO2: 2061 | BP2: 2062 | BQ2: 2063 | BR2: 2064 | BS2: 2065 | BT2: 2066 | BU2: 2067 | BV2: 2068 | BW2: 2069 | BX2: 2070 | BY2: 2071 | BZ2: 2072 | CA2: 2073 | CB2: 2074 | CC2: 2075 | CD2: 2076 | CE2: 2077 | CF2: 2078 | CG2: 2079 | CH2: 2080 | CI2: 2081 | CJ2: 2082 | CK2: 2083 | CL2: 2084 | CM2: 2085 | CN2: 2086 | CO2: 2087 | CP2: 2088 | CQ2: 2089 | CR2: 2090 | CS2: 2091 | CT2: 2092 | CU2: 2093 | CV2: 2094 | CW2: 2095 | CX2: 2096 | CY2: 2097 | CZ2: 2098 | DA2: 2099 | DB2: 2100 | DC2: 2101 | DD2: 2102 | DE2: 2103 | DF2: 2104 | DG2: 2105 | DH2: 2106 | DI2: 2107 | DJ2: 2108 | DK2: 2109 | DL2: 2110 | DM2: 2111 | DN2: 2112 | DO2: 2113 | DP2: 2114 | DQ2: 2115 | DR2: 2116 | DS2: 2117 | DT2: 2118 | DU2: 2119 | DV2: 2120 | DW2: 2121 | DX2: 2122 | DY2: 2123 | DZ2: 2124 | EA2: 2125 | EB2: 2126 | EC2: 2127 | ED2: 2128 | EE2: 2129 | EF2: 2130 | EG2: 2131 | EH2: 2132 | EI2: 2133 | EJ2: 2134 | EK2: 2135 | EL2: 2136 | EM2: 2137 | EN2: 2138 | EO2: 2139 | EP2: 2140 | EQ2: 2141 | ER2: 2142 | ES2: 2143 | ET2: 2144 | EU2: 2145
B3: Subscription | C3: 76923 | D3: 88936 | E3: 98435 | F3: 105055 | G3: 111191 | H3: 122096 | I3: 130993 | J3: 142026 | K3: 151179 | L3: 163181 | M3: 175257 | N3: 185562 | O3: 194481 | P3: 212684 | Q3: 223262 | R3: 234277 | AC3: 369349 | AD3: 506306 | AE3: 675179
B4: License | C4: 10484 | D4: 12105 | E4: 14546 | F4: 17852 | G4: 15687 | H4: 17485 | I4: 18675 | J4: 21753 | K4: 18008 | L4: 19403 | M4: 20790 | N4: 25869 | O4: 20028 | P4: 23276 | Q4: 21091 | R4: 26125 | AC4: 54987 | AD4: 73600 | AE4: 84070
B5: Revenue | C5: =+C3+C4 -> 87407 | D5: =+D3+D4 -> 101041 | E5: =+E3+E4 -> 112981 | F5: =+F3+F4 -> 122907 | G5: =+G3+G4 -> 126878 | H5: =+H3+H4 -> 139581 | I5: =+I3+I4 -> 149668 | J5: =+J3+J4 -> 163779 | ... R5: =+R3+R4 -> 260402 | S5: 255000 | T5: 277000 | U5: 293000 | V5: 311000 | W5: 323000 | X5: =T5*1.2 -> 332400 | Y5: =U5*1.2 -> 351600 | Z5: =V5*1.2 -> 373200 | AC5: =+AC3+AC4 -> 424336 | AD5: =+AD3+AD4 -> 579906 | AE5: =+AE3+AE4 -> 759249 | AF5: =SUM(O5:R5) -> 955224 | AG5: =SUM(S5:V5) -> 1136000 | AH5: =SUM(W5:Z5) -> 1380200 | AI5: =AH5*1.15 -> 1587230 | AJ5: =AI5*1.15 -> 1825314.5 | AK5: =AJ5*1.1 -> 2007845.9 | AL5: =AK5*1.1 -> 2208630.5 | AM5: =AL5*1.1 -> 2429493.6 | AN5: =AM5*1.1 -> 2672443 | AO5: =AN5*1.1 -> 2939687.3 | AP5: =AO5*1.05 -> 3086671.6 | AQ5: =AP5*1.05 -> 3241005.2 | AR5: =AQ5*1.05 -> 3403055.5 | AS5: =AR5*1.05 -> 3573208.2 | AT5: =AS5*1.05 -> 3751868.6 | AU5: =AT5*1.05 -> 3939462.1 | AV5: =AU5*1.05 -> 4136435.2 | AW5: =AV5*1.05 -> 4343256.9 | ... AY5: =AX5*1.05 -> 4788440.8
B6: Subscription Cost | C6: 7933 | D6: 10671 | E6: 11113 | F6: 11124 | G6: 10891 | H6: 10871 | I6: 11559 | J6: 12165 | K6: 13839 | L6: 16630 | M6: 17170 | N6: 17277 | O6: 19268 | P6: 21753 | Q6: 25184 | R6: 28297 | AC6: 40841 | AD6: 45486 | AE6: 64916
B7: License Cost | C7: 1915 | D7: 2359 | E7: 3451 | F7: 3114 | G7: 3048 | H7: 3825 | I7: 3525 | J7: 3824 | K7: 4937 | L7: 4740 | M7: 4955 | N7: 5592 | O7: 5767 | P7: 6752 | Q7: 7037 | R7: 6685 | AC7: 10839 | AD7: 14222 | AE7: 20224
B8: COGS | C8: =+C6+C7 -> 9848 | D8: =+D6+D7 -> 13030 | E8: =+E6+E7 -> 14564 | F8: =+F6+F7 -> 14238 | G8: =+G6+G7 -> 13939 | H8: =+H6+H7 -> 14696 | I8: =+I6+I7 -> 15084 | J8: =+J6+J7 -> 15989 | ... T8: =+T6+T7 -> 0 | AC8: =+AC6+AC7 -> 51680 | AD8: =+AD6+AD7 -> 59708 | AE8: =+AE6+AE7 -> 85140
B9: Gross Profit | C9: =+C5-C8 -> 77559 | D9: =+D5-D8 -> 88011 | E9: =+E5-E8 -> 98417 | F9: =+F5-F8 -> 108669 | G9: =+G5-G8 -> 112939 | H9: =+H5-H8 -> 124885 | I9: =+I5-I8 -> 134584 | J9: =+J5-J8 -> 147790 | ... T9: =+T5-T8 -> 277000 | AC9: =+AC5-AC8 -> 372656 | AD9: =+AD5-AD8 -> 520198 | AE9: =+AE5-AE8 -> 674109 | AF9: =+AF5*0.89 -> 850149.36 | AG9: =+AG5*0.89 -> 1011040 | AH9: =+AH5*0.89 -> 1228378 | AI9: =+AI5*0.89 -> 1412634.7 | AJ9: =+AJ5*0.89 -> 1624529.9 | AK9: =+AK5*0.89 -> 1786982.9 | AL9: =+AL5*0.89 -> 1965681.2 | AM9: =+AM5*0.89 -> 2162249.3 | ... AY9: =+AY5*0.89 -> 4261712.3
B10: S&M | C10: 66710 | D10: 80689 | E10: 81080 | F10: 81513 | G10: 86537 | H10: 92116 | I10: 86978 | J10: 90762 | K10: 92424 | L10: 97778 | M10: 95340 | N10: 98753 | O10: 107587 | P10: 109583 | Q10: 104974 | R10: 112581 | AC10: 309992 | AD10: 356393 | AE10: 384295 | AF10: =AF9*0.27 -> 229540.33 | AG10: =AG9*0.27 -> 272980.8 | AH10: =+AH9*0.22 -> 270243.16 | AI10: =+AI9*0.2 -> 282526.94 | AJ10: =+AJ9*0.15 -> 243679.49 | AK10: =+AK9*0.15 -> 268047.43 | AL10: =+AL9*0.15 -> 294852.18 | AM10: =+AM9*0.15 -> 324337.4 | AN10: =+AN9*0.15 -> 356771.14 | AO10: =+AO9*0.15 -> 392448.25 | AP10: =+AP9*0.15 -> 412070.66 | AQ10: =+AQ9*0.15 -> 432674.19 | ... AY10: =+AY9*0.15 -> 639256.84
B11: R&D | C11: 31830 | D11: 39520 | E11: 41113 | F11: 43680 | G11: 50387 | H11: 49007 | I11: 49058 | J11: 52388 | K11: 54140 | L11: 61273 | M11: 61354 | N11: 62885 | O11: 65410 | P11: 71488 | Q11: 68715 | R11: 68961 | AC11: 156143 | AD11: 200840 | AE11: 239652 | AF11: =AF9*0.3 -> 255044.81 | AG11: =AG9*0.3 -> 303312 | AH11: =AH9*0.3 -> 368513.4 | AI11: =AI9*0.3 -> 423790.41 | AJ11: =AJ9*0.3 -> 487358.97 | AK11: =AK9*0.3 -> 536094.87 | AL11: =AL9*0.3 -> 589704.36 | AM11: =AM9*0.3 -> 648674.79 | ... AY11: =AY9*0.3 -> 1278513.7
B12: G&A | C12: 21892 | D12: 33104 | E12: 33186 | F12: 29750 | G12: 34248 | H12: 37819 | I12: 38815 | J12: 39523 | K12: 57487 | L12: 43168 | M12: 45960 | N12: 42370 | O12: 51087 | P12: 44735 | Q12: 50799 | R12: 49042 | AC12: 117932 | AD12: 150405 | AE12: 192877 | AF12: =AF9*0.29 -> 246543.31 | AG12: =AG9*0.29 -> 293201.6 | AH12: =AH9*0.22 -> 270243.16 | AI12: =AI9*0.2 -> 282526.94 | AJ12: =AJ9*0.15 -> 243679.49 | AK12: =AK9*0.15 -> 268047.43 | AL12: =AL9*0.15 -> 294852.18 | AM12: =AM9*0.15 -> 324337.4 | AN12: =AN9*0.15 -> 356771.14 | AO12: =AO9*0.15 -> 392448.25 | AP12: =AP9*0.15 -> 412070.66 | AQ12: =AQ9*0.15 -> 432674.19 | ... AY12: =AY9*0.15 -> 639256.84
B13: Operating Expenses | C13: =+C10+C11+C12 -> 120432 | D13: =+D10+D11+D12 -> 153313 | E13: =+E10+E11+E12 -> 155379 | F13: =+F10+F11+F12 -> 154943 | G13: =+G10+G11+G12 -> 171172 | H13: =+H10+H11+H12 -> 178942 | I13: =+I10+I11+I12 -> 174851 | J13: =+J10+J11+J12 -> 182673 | ... T13: =+T10+T11+T12 -> 0 | AC13: =+AC10+AC11+AC12 -> 584067 | AD13: =+AD10+AD11+AD12 -> 707638 | AE13: =+AE10+AE11+AE12 -> 816824 | AF13: =+AF10+AF11+AF12 -> 731128.45 | AG13: =+AG10+AG11+AG12 -> 869494.4 | AH13: =+AH10+AH11+AH12 -> 908999.72 | AI13: =+AI10+AI11+AI12 -> 988844.29 | AJ13: =+AJ10+AJ11+AJ12 -> 974717.94 | ... AY13: =+AY10+AY11+AY12 -> 2557027.4
B14: Operating Profit/Loss | C14: =+C9-C13 -> -42873 | D14: =+D9-D13 -> -65302 | E14: =+E9-E13 -> -56962 | F14: =+F9-F13 -> -46274 | G14: =+G9-G13 -> -58233 | H14: =+H9-H13 -> -54057 | I14: =+I9-I13 -> -40267 | J14: =+J9-J13 -> -34883 | ... T14: =+T9-T13 -> 277000 | AC14: =AC9-AC13 -> -211411 | AD14: =AD9-AD13 -> -187440 | AE14: =AE9-AE13 -> -142715 | AF14: =AF9-AF13 -> 119020.91 | AG14: =AG9-AG13 -> 141545.6 | AH14: =AH9-AH13 -> 319378.28 | AI14: =AI9-AI13 -> 423790.41 | AJ14: =AJ9-AJ13 -> 649811.96 | ... AY14: =AY9-AY13 -> 1704684.9
B15: Interest Income | C15: 526 | D15: 3064 | E15: 4657 | F15: 6249 | G15: 7315 | H15: 9112 | I15: 10874 | J15: 11813 | K15: 12030 | L15: 12827 | M15: 12586 | N15: 10292 | O15: 10862 | P15: 11511 | Q15: 11704 | R15: 11630 | AC15: 14496 | AD15: 39114 | AE15: 47735
B16: Other Income | C16: 18448 | D16: 1500 | E16: 2661 | F16: -1024 | G16: 253 | H16: -1330 | I16: 569 | J16: -11451 | K16: -567 | L16: 1032 | M16: 4992 | N16: 4017 | O16: -9971 | P16: -911 | Q16: -6334 | R16: -6075 | AC16: 21621 | AD16: -12241 | AE16: 9187
B17: Pre Tax Income | C17: =+C14+C15+C16 -> -23899 | D17: =+D14+D15+D16 -> -60738 | E17: =+E14+E15+E16 -> -49644 | F17: =+F14+F15+F16 -> -41049 | G17: =+G14+G15+G16 -> -50665 | H17: =+H14+H15+H16 -> -46275 | I17: =+I14+I15+I16 -> -28824 | J17: =+J14+J15+J16 -> -34521 | ... T17: =+T14+T15+T16 -> 277000 | AC17: =+AC14+AC15+AC16 -> -175294 | AD17: =+AD14+AD15+AD16 -> -160567 | AE17: =+AE14+AE15+AE16 -> -85793 | AF17: =+(O50*0.04)+AF14 -> 163214.19 | AG17: =+($O$50*0.04)+AF14 -> 163214.19 | AH17: =+($O$50*0.04)+AG14 -> 185738.88 | AI17: =+($O$50*0.04)+AH14 -> 363571.56 | AJ17: =+($O$50*0.04)+AI14 -> 467983.69 | AK17: =+($O$50*0.04)+AJ14 -> 694005.24 | AL17: =+($O$50*0.04)+AK14 -> 758986.44 | AM17: =+($O$50*0.04)+AL14 -> 830465.75 | AN17: =+($O$50*0.04)+AM14 -> 909093 | ... AY17: =+($O$50*0.04)+AX14 -> 1667702.7
B18: Stake in Other Businesses | C18: -203 | D18: -816 | E18: -756 | F18: -693 | G18: -748 | H18: -917 | I18: -743 | J18: -1416 | K18: 0 | L18: 0 | M18: 0 | N18: 0 | O18: 0 | P18: 0 | Q18: 0 | R18: 0 | AC18: -2468 | AD18: -3824 | AE18: 0
B19: Taxes | C19: 2511 | D19: -57 | E19: 65 | F19: 379 | G19: 1486 | H19: 4016 | I19: 256788 | J19: 2035 | K19: 12710 | L19: -39420 | M19: -39421 | N19: -11344 | O19: 2539 | P19: 2245 | Q19: 1811 | R19: 3904 | AC19: 4030 | AD19: 265145 | AE19: -76674 | AF19: =+AF17*0.2 -> 32642.838 | AG19: =+AG17*0.2 -> 32642.838 | AH19: =+AH17*0.2 -> 37147.776 | AI19: =+AI17*0.2 -> 72714.312 | AJ19: =+AJ17*0.2 -> 93596.738 | AK19: =+AK17*0.2 -> 138801.05 | AL19: =+AL17*0.2 -> 151797.29 | AM19: =+AM17*0.2 -> 166093.15 | ... AY19: =+AY17*0.2 -> 333540.54
B20: Net Income/Loss | C20: =C17+C18-C19 -> -26613 | D20: =D17+D18-D19 -> -61497 | E20: =E17+E18-E19 -> -50465 | F20: =F17+F18-F19 -> -42121 | G20: =G17+G18-G19 -> -52899 | H20: =H17+H18-H19 -> -51208 | I20: =I17+I18-I19 -> -286355 | J20: =J17+J18-J19 -> -37972 | ... T20: =T17+T18-T19 -> 277000 | U20: -17000 | V20: -10200 | W20: -20440 | AC20: =AC17+AC18-AC19 -> -181792 | AD20: =AD17+AD18-AD19 -> -429536 | AE20: =AE17+AE18-AE19 -> -9119 | AF20: =+AF21*AF22 -> 129375 | AG20: =AG17-AG19 -> 130571.35 | AH20: =AH17-AH19 -> 148591.1 | AI20: =AI17-AI19 -> 290857.25 | AJ20: =AJ17-AJ19 -> 374386.95 | AK20: =AK17-AK19 -> 555204.19 | AL20: =AL17-AL19 -> 607189.15 | AM20: =AM17-AM19 -> 664372.6 | AN20: =AN17-AN19 -> 727274.4 | ... AY20: =AY17-AY19 -> 1334162.2 | AZ20: =AY20*(1+$BA$26) -> 1307478.9 | BA20: =AZ20*(1+$BA$26) -> 1281329.4 | BB20: =BA20*(1+$BA$26) -> 1255702.8 | BC20: =BB20*(1+$BA$26) -> 1230588.7 | BD20: =BC20*(1+$BA$26) -> 1205976.9 | BE20: =BD20*(1+$BA$26) -> 1181857.4 | BF20: =BE20*(1+$BA$26) -> 1158220.3 | BG20: =BF20*(1+$BA$26) -> 1135055.8 | ... WO20: =WN20*(1+$BA$26) -> 15.640951
B21: S/O | C21: 146643 | D21: 147797 | E21: 148883 | F21: 150133 | G21: 151692 | H21: 153644 | I21: 155123 | J21: 156601 | K21: 158157 | L21: 159677 | M21: 161317 | N21: 163055 | O21: 164491 | P21: 165953 | Q21: 167407 | R21: 169231 | AC21: 148407 | AD21: 154283 | AE21: 160580 | AF21: 172500
B22: EPS | C22: =+C20/C21 -> -0.18148156 | D22: =+D20/D21 -> -0.41609099 | E22: =+E20/E21 -> -0.33895744 | F22: =+F20/F21 -> -0.28055791 | G22: =+G20/G21 -> -0.34872637 | H22: =+H20/H21 -> -0.33328994 | I22: =+I20/I21 -> -1.8459867 | J22: =+J20/J21 -> -0.2424761 | ... T22: =+T20/T21 -> #DIV/0! | AC22: =AC20/AC21 -> -1.2249557 | AD22: =AD20/AD21 -> -2.7840786 | AE22: =AE20/AE21 -> -0.056787894 | AF22: 0.75
B23: Non-GAAP Net Income | H23: 1866 | I23: 14446 | J23: 25044 | K23: 4474 | L23: 24522 | M23: 39145 | N23: 56700 | O23: 29350 | P23: 40927 | Q23: 43518 | AD23: 32598 | AE23: 124841 | AF23: =+AF21*0.75 -> 129375
B24: Non-GAAP EPS | H24: =+H23/H21 -> 0.012144958 | I24: =+I23/I21 -> 0.0931261 | J24: =+J23/J21 -> 0.15992235 | K24: =+K23/K21 -> 0.028288346 | L24: =+L23/L21 -> 0.15357252 | M24: =+M23/M21 -> 0.24265886 | N24: =+N23/N21 -> 0.34773543 | O24: =+O23/O21 -> 0.17842921 | ... T24: =+T23/T21 -> #DIV/0! | AD24: =+AD23/AD21 -> 0.21128705 | AE24: =+AE23/AE21 -> 0.77743804
AZ26: Maturity | BA26: -0.02
B27: Gross Margin | C27: =+C9/C5 -> 0.88733168 | D27: =+D9/D5 -> 0.87104245 | E27: =+E9/E5 -> 0.87109337 | F27: =+F9/F5 -> 0.88415631 | G27: =+G9/G5 -> 0.89013856 | H27: =+H9/H5 -> 0.89471346 | I27: =+I9/I5 -> 0.89921693 | J27: =+J9/J5 -> 0.90237454 | ... R27: =+R9/R5 -> 0.86566155 | AC27: =+AC9/AC5 -> 0.87820972 | AD27: =+AD9/AD5 -> 0.89703849 | AE27: =+AE9/AE5 -> 0.88786288 | AZ27: Discount | BA27: 0.09
B28: Operating Margin | C28: =C14/C5 -> -0.49049847 | D28: =D14/D5 -> -0.6462921 | E28: =E14/E5 -> -0.50417327 | F28: =F14/F5 -> -0.37649605 | G28: =G14/G5 -> -0.45896846 | H28: =H14/H5 -> -0.3872805 | I28: =I14/I5 -> -0.26904215 | J28: =J14/J5 -> -0.21298823 | ... R28: =R14/R5 -> -0.019830877 | AC28: =AC14/AC5 -> -0.49821604 | AD28: =AD14/AD5 -> -0.3232248 | AE28: =AE14/AE5 -> -0.18796864 | AZ28: NPV | BA28: =NPV(BA27,AG20:WO20)+AF20+O50 -> 9209270.9
B29: Net Margin | C29: =+C20/C5 -> -0.30447218 | D29: =+D20/D5 -> -0.60863412 | E29: =+E20/E5 -> -0.44666802 | F29: =+F20/F5 -> -0.34270627 | G29: =+G20/G5 -> -0.41692807 | H29: =+H20/H5 -> -0.36686942 | I29: =+I20/I5 -> -1.913268 | J29: =+J20/J5 -> -0.23184902 | ... R29: =+R20/R5 -> -0.01349068 | AC29: =+AC20/AC5 -> -0.42841522 | AD29: =+AD20/AD5 -> -0.74069935 | AE29: =+AE20/AE5 -> -0.012010553 | AZ29: Share | BA29: =BA28/170000 -> 54.172182
B30: Effective Tax Rate | C30: =+C19/(C17+C18) -> -0.10418223 | D30: =+D19/(D17+D18) -> 0.00092601618 | E30: =+E19/(E17+E18) -> -0.0012896825 | F30: =+F19/(F17+F18) -> -0.0090795841 | G30: =+G19/(G17+G18) -> -0.028903196 | H30: =+H19/(H17+H18) -> -0.085099169 | I30: =+I19/(I17+I18) -> -8.6849528 | J30: =+J19/(J17+J18) -> -0.056626875 | ... R30: =+R19/(R17+R18) -> 9.9846547 | AC30: =+AC19/(AC17+AC18) -> -0.022670762 | AD30: =+AD19/(AD17+AD18) -> -1.6128924 | AE30: =+AE19/(AE17+AE18) -> 0.89370928 | AZ30: Current | BA30: 40.6
B31: S&M Margin | C31: =+(C10)/C9 -> 0.86011939 | D31: =+(D10)/D9 -> 0.91680585 | E31: =+(E10)/E9 -> 0.82384141 | F31: =+(F10)/F9 -> 0.75010353 | G31: =+(G10)/G9 -> 0.76622779 | H31: =+(H10)/H9 -> 0.7376066 | I31: =+(I10)/I9 -> 0.64627296 | J31: =+(J10)/J9 -> 0.61412815 | ... R31: =+(R10)/R9 -> 0.49942773 | AC31: =+(AC10)/AC9 -> 0.83184492 | AD31: =+(AD10)/AD9 -> 0.68511028 | AE31: =+(AE10)/AE9 -> 0.57007843 | AZ31: Return | BA31: =BA29/BA30-1 -> 0.33429019
B32: R&D Margin | C32: =+C11/C9 -> 0.41039725 | D32: =+D11/D9 -> 0.44903478 | E32: =+E11/E9 -> 0.41774287 | F32: =+F11/F9 -> 0.40195456 | G32: =+G11/G9 -> 0.44614349 | H32: =+H11/H9 -> 0.39241702 | I32: =+I11/I9 -> 0.36451584 | J32: =+J11/J9 -> 0.35447595 | ... R32: =+R11/R9 -> 0.30592228 | AC32: =+AC11/AC9 -> 0.41900036 | AD32: =+AD11/AD9 -> 0.38608376 | AE32: =+AE11/AE9 -> 0.35550927
B33: G&A Margin | C33: =+(C12)/C9 -> 0.28226254 | D33: =+(D12)/D9 -> 0.3761348 | E33: =+(E12)/E9 -> 0.33719784 | F33: =+(F12)/F9 -> 0.27376713 | G33: =+(G12)/G9 -> 0.30324334 | H33: =+(H12)/H9 -> 0.3028306 | I33: =+(I12)/I9 -> 0.28840724 | J33: =+(J12)/J9 -> 0.26742675 | ... R33: =+(R12)/R9 -> 0.21755834 | AC33: =+(AC12)/AC9 -> 0.31646344 | AD33: =+(AD12)/AD9 -> 0.28913029 | AE33: =+(AE12)/AE9 -> 0.28612138
B34: Interest Margin | C34: =+(C15+C16)/C14 -> -0.44256292 | D34: =+(D15+D16)/D14 -> -0.069890662 | E34: =+(E15+E16)/E14 -> -0.12847161 | F34: =+(F15+F16)/F14 -> -0.11291438 | G34: =+(G15+G16)/G14 -> -0.12996068 | H34: =+(H15+H16)/H14 -> -0.14395915 | I34: =+(I15+I16)/I14 -> -0.28417811 | J34: =+(J15+J16)/J14 -> -0.010377548 | ... R34: =+(R15+R16)/R14 -> -1.0757165 | AC34: =+(AC15+AC16)/AC14 -> -0.17083785 | AD34: =+(AD15+AD16)/AD14 -> -0.14336854 | AE34: =+(AE15+AE16)/AE14 -> -0.39885086
B35: Non-GAAP Net Margin | H35: =H23/H5 -> 0.013368582 | I35: =I23/I5 -> 0.096520298 | J35: =J23/J5 -> 0.15291338 | K35: =K23/K5 -> 0.026444112 | L35: =L23/L5 -> 0.13430531 | M35: =M23/M5 -> 0.19967151 | N35: =N23/N5 -> 0.2681726 | O35: =O23/O5 -> 0.1368241 | ... R35: =R23/R5 -> 0 | AD35: =+AD23/AD5 -> 0.056212559 | AE35: =+AE23/AE5 -> 0.16442695 | AF35: =+AF23/AF5 -> 0.13543944
B37: Revenue to S&M | C37: =C5/C10 -> 1.3102533 | D37: =D5/D10 -> 1.2522277 | E37: =E5/E10 -> 1.3934509 | F37: =F5/F10 -> 1.5078208 | G37: =G5/G10 -> 1.4661705 | H37: =H5/H10 -> 1.5152742 | I37: =I5/I10 -> 1.720757 | J37: =J5/J10 -> 1.8044887 | ... R37: =R5/R10 -> 2.3130191
B39: EV/Revenue | AC39: =[1]Main!$O$21*1000/AC5 -> 15.719871 | AD39: =[1]Main!$O$21*1000/AD5 -> 11.502738 | AE39: =[1]Main!$O$21*1000/AE5 -> 8.7856645
B41: S&M y/y | G41: =G10/C10-1 -> 0.29721181 | H41: =H10/D10-1 -> 0.14161782 | I41: =I10/E10-1 -> 0.07274297 | J41: =J10/F10-1 -> 0.11346656 | K41: =K10/G10-1 -> 0.068028704 | L41: =L10/H10-1 -> 0.061465978 | M41: =M10/I10-1 -> 0.096139254 | N41: =N10/J10-1 -> 0.088043454 | ... R41: =R10/N10-1 -> 0.14002613 | AD41: =AD10/AC10-1 -> 0.14968451 | AE41: =AE10/AD10-1 -> 0.078289978
B42: R&D y/y | G42: =G11/C11-1 -> 0.58300346 | H42: =H11/D11-1 -> 0.24005567 | I42: =I11/E11-1 -> 0.19324788 | J42: =J11/F11-1 -> 0.19935897 | K42: =K11/G11-1 -> 0.074483498 | L42: =L11/H11-1 -> 0.25029077 | M42: =M11/I11-1 -> 0.2506421 | N42: =N11/J11-1 -> 0.20037031 | ... R42: =R11/N11-1 -> 0.096620816 | AD42: =AD11/AC11-1 -> 0.28625683 | AE42: =AE11/AD11-1 -> 0.19324836
B43: G&A y/y | G43: =G12/C12-1 -> 0.56440709 | H43: =H12/D12-1 -> 0.14242992 | I43: =I12/E12-1 -> 0.16961972 | J43: =J12/F12-1 -> 0.3285042 | K43: =K12/G12-1 -> 0.67855057 | L43: =L12/H12-1 -> 0.14143684 | M43: =M12/I12-1 -> 0.18407832 | N43: =N12/J12-1 -> 0.072034006 | ... R43: =R12/N12-1 -> 0.15746991 | AD43: =AD12/AC12-1 -> 0.27535359 | AE43: =AE12/AD12-1 -> 0.28238423
B44: Operating Expenses y/y | G44: =G13/C13-1 -> 0.42131659 | H44: =H13/D13-1 -> 0.16716782 | I44: =I13/E13-1 -> 0.12531938 | J44: =J13/F13-1 -> 0.17896904 | K44: =K13/G13-1 -> 0.19208165 | L44: =L13/H13-1 -> 0.13008126 | M44: =M13/I13-1 -> 0.15900967 | N44: =N13/J13-1 -> 0.1167934 | ... R44: =R13/N13-1 -> 0.1302694
B45: Revenue y/y | G45: =G5/C5-1 -> 0.4515771 | H45: =H5/D5-1 -> 0.38142932 | I45: =I5/E5-1 -> 0.32471832 | J45: =J5/F5-1 -> 0.33254412 | K45: =K5/G5-1 -> 0.33346207 | L45: =L5/H5-1 -> 0.30808634 | M45: =M5/I5-1 -> 0.3098792 | N45: =N5/J5-1 -> 0.29095305 | ... Z45: =Z5/V5-1 -> 0.2 | AD45: =AD5/AC5-1 -> 0.36661985 | AE45: =AE5/AD5-1 -> 0.30926219 | AF45: =AF5/AE5-1 -> 0.2581169 | AG45: =AG5/AF5-1 -> 0.18924985 | AH45: =0.23 -> 0.23 | AI45: =0.23 -> 0.23 | AJ45: =0.22 -> 0.22 | AK45: =+AJ45-0.02 -> 0.2 | AL45: =+AK45-0.015 -> 0.185 | AM45: =+AL45-0.015 -> 0.17 | AN45: =+AM45-0.015 -> 0.155 | AO45: =+AN45-0.015 -> 0.14 | AP45: =+AO45-0.01 -> 0.13 | AQ45: =+AP45-0.01 -> 0.12 | AR45: =+AQ45-0.01 -> 0.11 | AS45: =+AR45-0.01 -> 0.1 | AT45: =+AS45-0.01 -> 0.09 | AU45: =+AT45-0.01 -> 0.08 | AV45: =+AU45-0.01 -> 0.07 | AW45: =+AV45-0.01 -> 0.06 | ... BB45: =+BA45-0.01 -> 0.01 | BC45: =+BB45-0.002 -> 0.008 | BD45: =+BC45-0.002 -> 0.006 | BE45: =+BD45-0.002 -> 0.004 | BF45: =+BE45-0.002 -> 0.002 | BG45: =+BF45-0.002 -> -3.1225023e-17 | BH45: =+BG45-0.002 -> -0.002 | BI45: =+BH45-0.002 -> -0.004 | BJ45: =+BI45-0.002 -> -0.006 | ... EU45: =+ET45-0.002 -> -0.184
B46: Revenue q/q | D46: =D5/C5-1 -> 0.15598293 | E46: =E5/D5-1 -> 0.11816985 | F46: =F5/E5-1 -> 0.08785548 | G46: =G5/F5-1 -> 0.032308982 | H46: =H5/G5-1 -> 0.1001198 | I46: =I5/H5-1 -> 0.072266283 | J46: =J5/I5-1 -> 0.094282011 | K46: =K5/J5-1 -> 0.033020106 | ... R46: =R5/Q5-1 -> 0.06567957
B50: Cash | F50: =295402+641249+12682 -> 949333 | G50: =315933+621706+11735 -> 949374 | H50: =273225+713058+10574 -> 996857 | I50: =285309+704325+9634 -> 999268 | J50: =287996+748289 -> 1036285 | K50: =420322+641173 -> 1061495 | L50: =438616+644488 -> 1083104 | M50: =176632+740340 -> 916972 | N50: =227649+764728 -> 992377 | O50: =255719+849113 -> 1104832 | P50: =261371+903806 -> 1165177 | Q50: =224231+980077 -> 1204308 | R50: =229576+1030327 -> 1259903 | AD50: =287996+748289 -> 1036285 | AE50: =227649+764728 -> 992377
B51: A/R | F51: 130479 | G51: 126079 | H51: 105815 | I51: 135614 | J51: 166731 | K51: 135195 | L51: 165001 | M51: 197555 | N51: 264565 | O51: 201408 | P51: 197775 | Q51: 221140 | R51: 304301 | AD51: 166731 | AE51: 264565
B52: Deferred acquisition costs | F52: =26505+15628 -> 42133 | G52: =25093+15014 -> 40107 | H52: =25069+14743 -> 39812 | I52: =27196+15104 -> 42300 | J52: =32300+4390 -> 36690 | K52: =31034+17738 -> 48772 | L52: =33841+15753 -> 49594 | M52: =34518+17248 -> 51766 | N52: =38964+4437 -> 43401 | O52: =35455+19830 -> 55285 | P52: =18961+35306 -> 54267 | Q52: =36522+20288 -> 56810 | R52: =42676+23705 -> 66381 | AD52: =32300+4390 -> 36690 | AE52: =38964+4437 -> 43401
B53: Prepaids | F53: 24327 | G53: 26409 | H53: 26053 | I53: 29892 | J53: 49143 | K53: 35319 | L53: 32410 | M53: 43120 | N53: 40411 | O53: 39066 | P53: 37912 | Q53: 44979 | R53: 48899 | AD53: 49143 | AE53: 40411
B54: P&E | F54: 5797 | G54: 4936 | H54: 4080 | I54: 3690 | J54: 2954 | K54: 2820 | L54: 2899 | M54: 3563 | N54: 4013 | O54: 4856 | P54: 7642 | Q54: 10193 | R54: 11815 | AD54: 2954 | AE54: 4013
B55: Lease ROU | F55: 998 | G55: 1300 | H55: 673 | I55: 533 | J55: 405 | K55: 543 | L55: 482 | M55: 444 | N55: 381 | O55: 329 | P55: 393 | Q55: 0 | R55: 0 | AD55: 405 | AE55: 381
B56: Goodwill | F56: 8145 | G56: 8145 | H56: 8145 | I56: 8145 | J56: 8145 | K56: 16070 | L56: 16017 | M56: 16131 | N56: 16139 | O56: 16029 | P56: 16634 | Q56: 16919 | R56: 17379 | AD56: 8145 | AE56: 16139
B57: Intangible assets | F57: 3901 | G57: 3321 | H57: 2774 | I57: 2254 | J57: 1733 | K57: 16637 | L57: 21867 | M57: 19536 | N57: 17834 | O57: 15819 | P57: 13804 | Q57: 11789 | R57: 9774 | AD57: 1733 | AE57: 17834
B58: ONCA | F58: 4087 | G58: 4437 | H58: 4860 | I58: 5200 | J58: 19317 | K58: 4776 | L58: 4888 | M58: 3552 | N58: 20142 | O58: 4366 | P58: 4583 | Q58: 4701 | R58: 4295 | AD58: 19317 | AE58: 20142
B59: Total Assets | F59: =SUM(F50:F58) -> 1169200 | G59: =SUM(G50:G58) -> 1164108 | H59: =SUM(H50:H58) -> 1189069 | I59: =SUM(I50:I58) -> 1226896 | J59: =SUM(J50:J58) -> 1321403 | K59: =SUM(K50:K58) -> 1321627 | L59: =SUM(L50:L58) -> 1376262 | M59: =SUM(M50:M58) -> 1252639 | ... T59: =SUM(T50:T58) -> 0 | AD59: =SUM(AD50:AD58) -> 1321403 | AE59: =SUM(AE50:AE58) -> 1399263
B60: A/P | F60: 5184 | G60: 3029 | H60: 4165 | I60: 5023 | J60: 1738 | K60: 3230 | L60: 3219 | M60: 2224 | N60: 7519 | O60: 11288 | P60: 11395 | Q60: 9187 | R60: 9205 | AD60: 1738 | AE60: 7519
B61: Accrued expenses and OCL | F61: 25954 | G61: 28885 | H61: 24643 | I61: 269980 | J61: 301262 | K61: 306734 | L61: 272164 | M61: 51821 | N61: 50788 | O61: 66308 | P61: 52339 | Q61: 58406 | R61: 58185 | AD61: 301262 | AE61: 54680
B62: Accrued compensation | F62: 20776 | G62: 15716 | H62: 23504 | I62: 23272 | J62: =35809+23794 -> 59603 | K62: 22743 | L62: 29117 | M62: 27274 | N62: 40233 | O62: 28119 | P62: 30164 | Q62: 33402 | R62: 39657 | AD62: =35809+23794 -> 59603 | AE62: 40233
B63: Deferred revenue | F63: =254382+28355 -> 282737 | G63: =263423+28043 -> 291466 | H63: =268883+25860 -> 294743 | I63: =287647+23016 -> 310663 | J63: 338348 | K63: =341830+15267 -> 357097 | L63: =362348+14732 -> 377080 | M63: =383183+14138 -> 397321 | N63: =442599+26369 -> 468968 | O63: =450668+25981 -> 476649 | P63: =459459+25749 -> 485208 | Q63: =464813+28977 -> 493790 | R63: =545096+26994 -> 572090 | AD63: 338348 | AE63: =442599+26369 -> 468968
B64: ONCL | F64: 9824 | G64: 9411 | H64: 10774 | I64: 24776 | J64: 14060 | K64: 17465 | L64: 6678 | M64: 3776 | N64: 6557 | O64: 7029 | P64: 7499 | Q64: 8057 | R64: 7362 | AD64: 14060 | AE64: 6557
B65: Total Liabilities | F65: =SUM(F60:F64) -> 344475 | G65: =SUM(G60:G64) -> 348507 | H65: =SUM(H60:H64) -> 357829 | I65: =SUM(I60:I64) -> 633714 | J65: =SUM(J60:J64) -> 715011 | K65: =SUM(K60:K64) -> 707269 | L65: =SUM(L60:L64) -> 688258 | M65: =SUM(M60:M64) -> 482416 | ... T65: =SUM(T60:T64) -> 0 | AD65: =SUM(AD60:AD64) -> 715011 | AE65: =SUM(AE60:AE64) -> 577957
B66: SE | F66: 824725 | G66: 815601 | H66: 831240 | I66: 593182 | J66: 606392 | K66: 614358 | L66: 688004 | M66: 770223 | N66: 825198 | O66: 852597 | P66: 911582 | Q66: 967997 | R66: 1036248 | AD66: 606392 | AE66: 821306
B67: L+SE | F67: =F65+F66 -> 1169200 | G67: =G65+G66 -> 1164108 | H67: =H65+H66 -> 1189069 | I67: =I65+I66 -> 1226896 | J67: =J65+J66 -> 1321403 | K67: =K65+K66 -> 1321627 | L67: =L65+L66 -> 1376262 | M67: =M65+M66 -> 1252639 | ... T67: =T65+T66 -> 0 | AD67: =AD65+AD66 -> 1321403 | AE67: =AE65+AE66 -> 1399263
B72: STATEMENT OF CASH FLOWS
B73: Model NI/L | C73: =C20 -> -26613 | D73: =D20 -> -61497 | E73: =E20 -> -50465 | F73: =F20 -> -42121 | G73: =G20 -> -52899 | H73: =H20 -> -51208 | I73: =I20 -> -286355 | J73: =J20 -> -37972 | ... T73: =T20 -> 277000 | AC73: =AC20 -> -181792 | AD73: =AD20 -> -429536 | AE73: =AE20 -> -9119
B74: GAAP NI/L | C74: -26613 | D74: =-88110-C74 -> -61497 | E74: =-138575-D74-C74 -> -50465 | F74: -42121 | G74: -52899 | H74: -51208 | I74: -286355 | J74: -37972 | K74: -54887 | L74: 12274 | M74: 28267 | N74: 10207 | O74: -36258 | P74: -9996 | Q74: -8797 | R74: -3513 | AC74: -181792 | AD74: -429536 | AE74: -9119
B75: Stock-based compensation expense | C75: 17471 | D75: =55218-C75 -> 37747 | E75: =88926-D75-C75 -> 33708 | F75: 33641 | G75: 32330 | H75: 46368 | I75: 41334 | J75: 43017 | K75: 42252 | L75: 48969 | M75: 48042 | N75: 46636 | O75: 55827 | P75: 54284 | Q75: 51682 | R75: 53158 | AC75: 122567 | AD75: 163049 | AE75: 185899
B76: Change in fair value of acquisition | C76: 0 | D76: 0 | E76: 0 | F76: -1722 | G76: 0 | H76: 0 | I76: 0 | J76: 0 | K76: 0 | L76: 3750 | M76: 0 | N76: 0 | O76: 0 | P76: 0 | Q76: 0 | R76: 0 | AC76: -1722 | AD76: 0 | AE76: 3750
B77: Charitable donation of common stock | C77: 0 | D77: 0 | E77: 0 | F77: 0 | G77: 2675 | H77: 2675 | I77: 2675 | J77: 2675 | K77: 2957 | L77: 2957 | M77: 2957 | N77: 2956 | O77: 1739 | P77: 1787 | Q77: 1970 | R77: 1597 | AC77: 0 | AD77: 10700 | AE77: 11827
B78: D&A | C78: =581+558+10813 -> 11952 | D78: =1176+1286+21618-1293-C78 -> 10835 | E78: =1767+2198+32693-3346-D78-C78 -> 10525 | F78: =595+1033+12265-2731 -> 11162 | G78: =579+1092+10549-3596 -> 8624 | H78: =546+1114+10070-4898 -> 6832 | I78: =521+1123+10447-5867 -> 6224 | J78: =521+1039+12397-5988 -> 7969 | K78: =1087+937+11109-4900 -> 8233 | L78: =2333+744+11837-4241 -> 10673 | M78: =2511+680+12704-3792 -> 12103 | N78: =2195+499+14064-3813 -> 12945 | O78: =2020+556+13899-2996 -> 13479 | P78: =2015+759+13370-2609 -> 13535 | Q78: =2015+869+13478-1741 -> 14621 | R78: =2015+1096+14139-861 -> 16389 | AC78: =2362+3231+44958-6077 -> 44474 | AD78: =2167+4368+43463-20349 -> 29649 | AE78: =8126+2860+49714-16746 -> 43954
B79: Gain from deconsolidation of Arch, formerly Meltano | C79: -17798 | D79: 0 | E79: 0 | F79: 0 | G79: 0 | H79: 0 | I79: 0 | J79: 0 | K79: 0 | L79: 0 | M79: 0 | N79: 0 | O79: 0 | P79: 0 | Q79: 0 | R79: 0 | AC79: -17798 | AD79: 0 | AE79: 0
B80: Loss from equity method investment | C80: 256 | D80: =1290-C80 -> 1034 | E80: =2247-D80-C80 -> 957 | F80: 942 | G80: 947 | H80: 1161 | I80: 940 | J80: 776 | K80: 0 | L80: 0 | M80: 0 | N80: 0 | O80: 0 | P80: 0 | Q80: 0 | R80: 0 | AC80: 3189 | AD80: 3824 | AE80: 0
B81: Impairments | C81: 0 | D81: 0 | E81: 0 | F81: 0 | G81: 0 | H81: 0 | I81: 0 | J81: 8858 | K81: 0 | L81: 0 | M81: 0 | N81: 0 | O81: 0 | P81: 0 | Q81: 0 | R81: 0 | AC81: 0 | AD81: 8858 | AE81: 0
B82: Unrealized FX | C82: -231 | D82: =-1572-C82 -> -1341 | E82: =-4081-D82-C82 -> -2509 | F82: 354 | G82: -262 | H82: 1087 | I82: -573 | J82: 4194 | K82: 545 | L82: -803 | M82: -5184 | N82: -4083 | O82: 9901 | P82: 1069 | Q82: 2416 | R82: 5425 | AC82: -3964 | AD82: 4833 | AE82: -9526
B83: Other non-cash expense | C83: -268 | D83: =469-C83 -> 737 | E83: =439-D83-C83 -> -30 | F83: 717 | G83: -59 | H83: -44 | I83: 420 | J83: 1013 | K83: 412 | L83: -111 | M83: 467 | N83: 162 | O83: 208 | P83: 192 | Q83: 231 | R83: 367 | AC83: 1156 | AD83: 1330 | AE83: 930
B84: A/R | C84: 8674 | D84: =-13568-C84 -> -22242 | E84: =-22163-D84-C84 -> -8595 | F84: -32006 | G84: 4840 | H84: 20441 | I84: -30572 | J84: -31050 | K84: 31072 | L84: -29847 | M84: -32883 | N84: -67991 | O84: 65928 | P84: 3859 | Q84: -23472 | R84: -82033 | AC84: -54169 | AD84: -36341 | AE84: -99649
B85: Prepaids | C85: -2158 | D85: =-5488-C85 -> -3330 | E85: =-5320-D85-C85 -> 168 | F85: -3589 | G85: -2087 | H85: -2161 | I85: -3935 | J85: -15722 | K85: 10354 | L85: 2917 | M85: -10773 | N85: 5927 | O85: 1527 | P85: 1219 | Q85: -7036 | R85: -3832 | AC85: -8679 | AD85: -23688 | AE85: 8424
B86: Deferred costs | C86: -10249 | D86: =-21210-C86 -> -10961 | E86: =-33145-D86-C86 -> -11935 | F86: -15410 | G86: -8497 | H86: -9640 | I86: -13623 | J86: -21340 | K86: -8540 | L86: -12415 | M86: -14751 | N86: -22421 | O86: -8126 | P86: -12304 | Q86: -15898 | R86: -22966 | AC86: -48555 | AD86: -53100 | AE86: -58127
B87: ONCA | C87: -61 | D87: =2700-C87 -> 2761 | E87: =2050-D87-C87 -> -650 | F87: 962 | G87: -302 | H87: -419 | I87: -453 | J87: 865 | K87: -419 | L87: -78 | M87: 1348 | N87: -1034 | O87: 379 | P87: -198 | Q87: 233 | R87: 395 | AC87: 3012 | AD87: -309 | AE87: -183
B88: A/P | C88: 800 | D88: =528-C88 -> -272 | E88: =1393-D88-C88 -> 865 | F88: -1106 | G88: -2158 | H88: 1135 | I88: 799 | J88: -3219 | K88: 1336 | L88: 14 | M88: -1317 | N88: 5472 | O88: 3586 | P88: -472 | Q88: -2302 | R88: 794 | AC88: 287 | AD88: -3443 | AE88: 5505
B89: Accrued expenses | C89: 1569 | D89: =90-C89 -> -1479 | E89: =3249-D89-C89 -> 3159 | F89: 1370 | G89: 2789 | H89: -1606 | I89: 244674 | J89: 13090 | K89: 19617 | L89: -41250 | M89: -220071 | N89: -16647 | O89: 9979 | P89: -14257 | Q89: 6140 | R89: -624 | AC89: 5722 | AD89: 259445 | AE89: -253369
B90: Accrued compensation | C90: -20606 | D90: =-16680-C90 -> 3926 | E90: =-15150-D90-C90 -> 1530 | F90: 3457 | G90: =-5121 -> -5121 | H90: 7732 | I90: 231 | J90: 12331 | K90: -13152 | L90: 6250 | M90: -1913 | N90: 13558 | O90: -13084 | P90: 2021 | Q90: 3168 | R90: 5765 | AC90: -11693 | AD90: 15173 | AE90: 4743
B91: Deferred revenue | C91: 6687 | D91: =17549-C91 -> 10862 | E91: =40200-D91-C91 -> 22651 | F91: 32803 | G91: 8383 | H91: 1964 | I91: 14270 | J91: 50189 | K91: -4448 | L91: 19286 | M91: 19665 | N91: 74240 | O91: 1205 | P91: 8284 | Q91: 8011 | R91: 75781 | AC91: 73003 | AD91: 79347 | AE91: 108743
B92: ONCL | C92: 2419 | D92: =-696-C92 -> -3115 | E92: =-1272-D92-C92 -> -576 | F92: -1174 | G92: -164 | H92: 2792 | I92: 17983 | J92: -10821 | K92: 2806 | L92: -10889 | M92: -2985 | N92: 3295 | O92: 12 | P92: 346 | Q92: 461 | R92: -946 | AC92: -2446 | AD92: 5249 | AE92: -7773
B93: CFFO | C93: =SUM(C74:C92) -> -28156 | D93: =SUM(D74:D92) -> -36335 | E93: =SUM(E74:E92) -> -1197 | F93: =SUM(F74:F92) -> -11720 | G93: =SUM(G74:G92) -> -10961 | H93: =SUM(H74:H92) -> 27109 | I93: =SUM(I74:I92) -> -5961 | J93: =SUM(J74:J92) -> 24853 | ... S93: =SUM(S74:S92) -> 0 | AC93: =SUM(AC74:AC92) -> -77408 | AD93: =SUM(AD74:AD92) -> 35040 | AE93: =SUM(AE74:AE92) -> -63971
B94: Purchases of short-term investment | C94: -47361 | D94: =-520664-C94 -> -473303 | E94: =-631951-D94-C94 -> -111287 | F94: -189671 | G94: -58864 | H94: -276132 | I94: -238680 | J94: -242021 | K94: -144392 | L94: -118866 | M94: -240136 | N94: -204304 | O94: -245952 | P94: -237946 | Q94: -314385 | R94: -213209 | AC94: -821622 | AD94: -815697 | AE94: -707698
B95: Proceeds from maturities of short-term investments | C95: 50031 | D95: 0 | E95: =122701-D95-C95 -> 72670 | F95: 108925 | G95: 83500 | H95: 189484 | I95: 253995 | J95: 207028 | K95: 254687 | L95: 121412 | M95: 148763 | N95: 183520 | O95: =163606+1367 -> 164973 | P95: 184280 | Q95: 241641 | R95: 164139 | AC95: 231626 | AD95: 734007 | AE95: 708382
B96: Capex | C96: -1874 | D96: =-3234-C96 -> -1360 | E96: =-5018-D96-C96 -> -1784 | F96: -1052 | G96: -256 | H96: -277 | I96: -736 | J96: -329 | K96: -700 | L96: -851 | M96: -1057 | N96: -1157 | O96: -912 | P96: -2904 | Q96: -3038 | R96: -3973 | AC96: -6070 | AD96: -1598 | AE96: -3765
B97: Deconsolidation of Arch, formerly Meltano | C97: -9620 | D97: 0 | E97: 0 | F97: 0 | G97: 0 | H97: 0 | I97: 0 | J97: 0 | K97: 0 | L97: 0 | M97: 0 | N97: 0 | O97: 0 | P97: 0 | Q97: 0 | R97: 0 | AC97: -9620 | AD97: 0 | AE97: 0
B98: Payments for business combination, net of cash acquired | C98: 0 | D98: 0 | E98: 0 | F98: 0 | G98: 0 | H98: 0 | I98: 0 | J98: 0 | K98: 0 | L98: 0 | M98: 0 | N98: 0 | O98: 0 | P98: 0 | Q98: 0 | R98: 0 | AC98: 0 | AD98: 0 | AE98: -20210
B99: Payments for asset acquisition | C99: 0 | D99: 0 | E99: 0 | F99: 0 | G99: 0 | H99: 0 | I99: 0 | J99: 0 | K99: -20210 | L99: -7314 | M99: -346 | N99: 0 | O99: 0 | P99: 0 | Q99: 0 | R99: 0 | AC99: 0 | AD99: 0 | AE99: -7660
B100: Escrow payment related to business combination, after acquisition date | C100: 0 | D100: 0 | E100: 0 | F100: 0 | G100: 0 | H100: -2500 | I100: 0 | J100: 0 | K100: 0 | L100: 0 | M100: 0 | N100: 0 | O100: 0 | P100: 0 | Q100: 0 | R100: 0 | AC100: 0 | AD100: -2500 | AE100: 0
B101: Other investing activities | C101: 0 | D101: 0 | E101: 0 | F101: 0 | G101: 0 | H101: 0 | I101: 0 | J101: -450 | K101: 0 | L101: 457 | M101: 0 | N101: 0 | O101: 0 | P101: 0 | Q101: 0 | R101: 0 | AC101: 0 | AD101: -450 | AE101: 457
B102: CFFI | C102: =SUM(C94:C101) -> -8824 | D102: =SUM(D94:D101) -> -474663 | E102: =SUM(E94:E101) -> -40401 | F102: =SUM(F94:F101) -> -81798 | G102: =SUM(G94:G101) -> 24380 | H102: =SUM(H94:H101) -> -89425 | I102: =SUM(I94:I101) -> 14579 | J102: =SUM(J94:J101) -> -35772 | ... S102: =SUM(S94:S101) -> 0 | AC102: =SUM(AC94:AC101) -> -605686 | AD102: =SUM(AD94:AD101) -> -86238 | AE102: =SUM(AE94:AE101) -> -30494
B103: Issuance of stock | C103: 5317 | D103: =11311-C103 -> 5994 | E103: =17454-D103-C103 -> 6143 | F103: 7061 | G103: 7513 | H103: 10264 | I103: 4715 | J103: 9810 | K103: 5093 | L103: 4980 | M103: 7822 | N103: 6069 | O103: 3328 | P103: 3947 | Q103: 8182 | R103: 6324 | AC103: 24515 | AD103: 32302 | AE103: 23964
B104: Issuance of common stock under employee stock purchase plan | C104: 0 | D104: =9554-C104 -> 9554 | E104: 0 | F104: 4824 | G104: 0 | H104: 7751 | I104: 0 | J104: 5182 | K104: 0 | L104: 7932 | M104: 0 | N104: 5624 | O104: 0 | P104: 8404 | Q104: 0 | R104: =5571-416 -> 5155 | AC104: 14378 | AD104: 12933 | AE104: 13556
B105: Contributions from noncontroling interest | C105: =35528+2878 -> 38406 | D105: =57673-C105 -> 19267 | E105: =61726-D105-C105 -> 4053 | F105: 0 | G105: 0 | H105: 0 | I105: 0 | J105: 0 | K105: 0 | L105: 0 | M105: 0 | N105: 0 | O105: 0 | P105: 0 | Q105: 0 | R105: 0 | AC105: 61726 | AD105: 0 | AE105: 0
B106: Settlement of acquisition | C106: 0 | D106: 0 | E106: -3137 | F106: 0 | G106: 0 | H106: 0 | I106: 0 | J106: 0 | K106: 0 | L106: 0 | M106: -4900 | N106: 0 | O106: 0 | P106: 0 | Q106: -529 | R106: 0 | AC106: -3137 | AD106: 0 | AE106: -4900
B107: CFFF | C107: =SUM(C103:C106) -> 43723 | D107: =SUM(D103:D106) -> 34815 | E107: =SUM(E103:E106) -> 7059 | F107: =SUM(F103:F106) -> 11885 | G107: =SUM(G103:G106) -> 7513 | H107: =SUM(H103:H106) -> 18015 | I107: =SUM(I103:I106) -> 4715 | J107: =SUM(J103:J106) -> 14992 | ... S107: =SUM(S103:S106) -> 0 | AC107: =SUM(AC103:AC106) -> 97482 | AD107: =SUM(AD103:AD106) -> 45235 | AE107: =SUM(AE103:AE106) -> 32620
B108: Currency adj | C108: -3926 | D108: =-4475-C108 -> -549 | E108: =-8524-D108-C108 -> -4049 | F108: 4866 | G108: -401 | H108: -907 | I108: -1249 | J108: -1386 | K108: -290 | L108: -1153 | M108: 4898 | N108: -1957 | O108: 331 | P108: 331 | Q108: -439 | R108: 1152 | AC108: -3658 | AD108: -3943 | AE108: 1498
B109: CF | C109: =C93+C102+C107+C108 -> 2817 | D109: =D93+D102+D107+D108 -> -476732 | E109: =E93+E102+E107+E108 -> -38588 | F109: =F93+F102+F107+F108 -> -76767 | G109: =G93+G102+G107+G108 -> 20531 | H109: =H93+H102+H107+H108 -> -45208 | I109: =I93+I102+I107+I108 -> 12084 | J109: =J93+J102+J107+J108 -> 2687 | ... S109: =S93+S102+S107+S108 -> 0 | AC109: =AC93+AC102+AC107+AC108 -> -589270 | AD109: =AD93+AD102+AD107+AD108 -> -9906 | AE109: =AE93+AE102+AE107+AE108 -> -60347
B111: FCF | C111: =C93+C96 -> -30030 | D111: =D93+D96 -> -37695 | E111: =E93+E96 -> -2981 | F111: =F93+F96 -> -12772 | G111: =G93+G96 -> -11217 | H111: =H93+H96 -> 26832 | I111: =I93+I96 -> -6697 | J111: =J93+J96 -> 24524 | ... S111: =S93+S96 -> 0 | AC111: =AC93+AC96 -> -83478 | AD111: =AD93+AD96 -> 33442 | AE111: =AE93+AE96 -> -67736
B112: Capex Margin | C112: =C96/C73 -> 0.070416714 | D112: =D96/D73 -> 0.0221149 | E112: =E96/E73 -> 0.035351234 | F112: =F96/F73 -> 0.024975665 | G112: =G96/G73 -> 0.004839411 | H112: =H96/H73 -> 0.005409311 | I112: =I96/I73 -> 0.0025702362 | J112: =J96/J73 -> 0.0086642789 | ... S112: =S96/S73 -> 0 | AC112: =AC96/AC73 -> 0.033389808 | AD112: =AD96/AD73 -> 0.0037202935 | AE112: =AE96/AE73 -> 0.41287422
...

Sheet FA
C2: 2021 | D2: 2022 | E2: 2023 | F2: 2024 | G2: 2025 | H2: 2026 | I2: 2027
B3: Employees | C3: 1350 | D3: 1630 | E3: 2170 | F3: 2130 | G3: 2375
B4: Revenue | C4: 152180 | D4: 252653 | E4: =FS!AC5 -> 424336 | F4: =FS!AD5 -> 579906 | G4: =FS!AE5 -> 759249
B5: Revenue/Employee | C5: =C4/C3 -> 112.72593 | D5: =D4/D3 -> 155.00184 | E5: =E4/E3 -> 195.54654 | F5: =F4/F3 -> 272.25634 | G5: =G4/G3 -> 319.68379
B7: Employee Growth Rate | D7: =D3/C3-1 -> 0.20740741 | E7: =E3/D3-1 -> 0.33128834 | F7: =F3/E3-1 -> -0.01843318 | G7: =G3/F3-1 -> 0.11502347
B8: R/E y/y | D8: =D5/C5-1 -> 0.37503276 | E8: =E5/D5-1 -> 0.26157562 | F8: =F5/E5-1 -> 0.39228407 | G8: =G5/F5-1 -> 0.17420146
B13: ARR - Annual Recurring Revenue (Monthly recurring revenue ("MRR") multiplied by 12.)
B14: Customer base
C15: Q423 | D15: Q124 | E15: Q224 | F15: Q324 | G15: Q424 | H15: Q125 | I15: Q225 | J15: Q325 | K15: Q425 | L15: Q126 | M15: Q226 | N15: Q326 | O15: Q426
B16: $5,000+ ARR | C16: 7002 | D16: 7406 | E16: 7815 | F16: 8175 | G16: 8602 | H16: 8976 | I16: 9314 | J16: 9519 | K16: 9893 | L16: 10104 | M16: 10338 | N16: 10475 | O16: 10682
B17: $100,000+ ARR | C17: 697 | D17: 760 | E17: 810 | F17: 874 | G17: 955 | H17: 1025 | I17: 1076 | J17: 1144 | K17: 1229 | L17: 1288 | M17: 1344 | N17: 1405 | O17: 1456
B18: $1,000,000+ ARR | C18: 63 | G18: 96 | K18: 123 | O18: 155
B20: $5,000+ ARR q/q | D20: =D16/C16-1 -> 0.057697801 | E20: =E16/D16-1 -> 0.055225493 | F20: =F16/E16-1 -> 0.046065259 | G20: =G16/F16-1 -> 0.052232416 | H20: =H16/G16-1 -> 0.043478261 | I20: =I16/H16-1 -> 0.037655971 | J20: =J16/I16-1 -> 0.022009878 | K20: =K16/J16-1 -> 0.039289841 | ... O20: =O16/N16-1 -> 0.019761337
B21: $100,000+ ARR q/q | D21: =D17/C17-1 -> 0.090387374 | E21: =E17/D17-1 -> 0.065789474 | F21: =F17/E17-1 -> 0.079012346 | G21: =G17/F17-1 -> 0.092677346 | H21: =H17/G17-1 -> 0.073298429 | I21: =I17/H17-1 -> 0.049756098 | J21: =J17/I17-1 -> 0.063197026 | K21: =K17/J17-1 -> 0.074300699 | ... O21: =O17/N17-1 -> 0.036298932
B22: $1m y/y | G22: =G18/C18-1 -> 0.52380952 | K22: =K18/G18-1 -> 0.28125 | O22: =O18/K18-1 -> 0.2601626
B23: $5,000+ ARR y/y | G23: =G16/C16-1 -> 0.22850614 | H23: =H16/D16-1 -> 0.21199028 | I23: =I16/E16-1 -> 0.19181062 | J23: =J16/F16-1 -> 0.16440367 | K23: =K16/G16-1 -> 0.15008138 | L23: =L16/H16-1 -> 0.12566845 | M23: =M16/I16-1 -> 0.10994202 | N23: =N16/J16-1 -> 0.10043072 | O23: =O16/K16-1 -> 0.079753361
B24: $100,000+ ARR y/y | G24: =G17/C17-1 -> 0.37015782 | H24: =H17/D17-1 -> 0.34868421 | I24: =I17/E17-1 -> 0.32839506 | J24: =J17/F17-1 -> 0.30892449 | K24: =K17/G17-1 -> 0.28691099 | L24: =L17/H17-1 -> 0.25658537 | M24: =M17/I17-1 -> 0.24907063 | N24: =N17/J17-1 -> 0.22814685 | O24: =O17/K17-1 -> 0.18470301
A26: Total value of all future revenue from existing contracts that a company is obligated to fulfill
B27: RPO - Remaining Performance Obligation | L27: 955.1 | M27: 988.2 | N27: 1000 | O27: 1100
B28: cRPO - Current Remaining Performance Obligation | L28: 584.8 | M28: 621.6 | N28: 659.1 | O28: 719.4
B29: RPO QoQ | M29: =M27/L27-1 -> 0.034656057 | N29: =N27/M27-1 -> 0.011940903 | O29: =O27/N27-1 -> 0.1
B30: cRP QoQ | M30: =M28/L28-1 -> 0.062927497 | N30: =N28/M28-1 -> 0.060328185 | O30: =O28/N28-1 -> 0.091488393
B32: $ retention rate | O32: 1.18

Sheet Segments
B2: Metric | C2: Value (Date)
B3: Registered users (free-tier) | C3: >50 million (Apr 30, 2025)
B6: Company | C6: Headquarters | D6: Market Cap / Valuation | E6: Employees
B7: Sigma Defense | C7: Perry, GA, USA | D7: Private (Valuation N/A) | E7: 900
B8: CACI International | C8: Reston, VA, USA | D8: ~$10.15B (May 2025) (NASDAQ: CACI) | E8: 24000
B9: Southwest Airlines | C9: Dallas, TX, USA | D9: ~$18.07B (May 2025) (NYSE: LUV) | E9: 72,450 (2024)
B10: Nasdaq, Inc. | C10: New York, NY, USA | D10: ~$47.65B (May 2025) (Nasdaq: NDAQ) | E10: 9162
B11: Deutsche Telekom | C11: Bonn, Germany | D11: ~€166.5B (May 2025) (FWB: DTE) | E11: 199652
B12: Siemens AG | C12: Munich, Germany | D12: ~$196.2B (May 2025) (Xetra: SIE) | E12: 327000
B13: UBS Group AG | C13: Zurich, Switzerland | D13: ~$101.8B (as reported) (NYSE: UBS) | E13: 108648
B14: Hilti AG | C14: Schaan, Liechtenstein | D14: Private (family-owned) | E14: 32000
B15: Fujitsu Ltd | C15: Kawasaki, Kanagawa, Japan | D15: ~$41.04B (May 2025) (OTCM: FJTSY) | E15: 113000
B16: Fanatics, Inc. | C16: New York, NY, USA (inc. Jacksonville, FL) | D16: ~$31B (Dec 2023) (private) | E16: 22000
B17: Crédit Agricole SA | C17: Paris, France | D17: ~$56.34B (as reported) (EPA: ACA) | E17: 80518
B18: Airbus SE | C18: Toulouse, France | D18: ~$140.56B (May 2025) (EPA: AIR) | E18: 147,893 (2023)
B23: Feature Area | C23: GitHub | D23: GitLab | E23: Bitbucket (Atlassian)
B24: Deployment Model | C24: SaaS-first, then self-hosted (Enterprise) | D24: Self-hosted-first, then SaaS | E24: Primarily Cloud-based
B25: Open Source Status | C25: Not open-source (contributes to OSS) | D25: Fully open-source | E25: Not open-source
B26: Tech Stack | C26: Ruby on Rails + MySQL | D26: Ruby on Rails + Go + PostgreSQL | E26: Integrated with Atlassian suite (Jira, Confluence)
B27: Repository Management | C27: Pioneered forks & pull requests | D27: Merge requests, fork functionality | E27: Collaborative code repos, strong Jira integration
B28: CI/CD Capabilities | C28: GitHub Actions (strong 3rd-party ecosystem, more runtime envs) | D28: Pioneered built-in CI/CD & Auto DevOps (multi-project pipelines, canary deployments) | E28: Bitbucket Pipelines, robust automation with Jira
B29: Security | C29: Advanced Security (CodeQL, code/secret scanning) | D29: Pioneered DevSecOps (SAST, DAST, Dependency/Secret/IaC Scanning, Fuzz Testing) | E29: Integrates with security tools (e.g., Snyk)
B30: Project Management | C30: Projects & Issues (many prefer Jira) | D30: Issues, Epics, Boards (developer-centric) | E30: Jira (leading specialized tool)
B31: AI Capabilities | C31: GitHub Copilot (code suggestions, faster task completion) | D31: GitLab Duo (code suggestions, chat, vulnerability explanations, CI/CD troubleshooting) | E31: Rovo (new AI for teamwork)

Sheet Comp.
AZ1: In millions
AZ2: Q2FY26 R Cons. | BA2: 227 | BC2: FY26 R Cons. | BD2: 942
AZ3: Actual | BA3: 236 | BC3: Actual | BD3: 942
AZ4: Beat | BA4: =BA3/BA2-1 -> 0.039647577 | BC4: Beat | BD4: =BD3/BD2-1 -> 0
AZ5: Q2FY26 EPS Cons. | BA5: 0.17 | BC5: FY26 EPS Cons. | BD5: 0.75
G6: TEAM | H6: Q122 | I6: Q222 | J6: Q322 | K6: Q422 | L6: Q123 | M6: Q223 | N6: Q323 | O6: Q423 | P6: Q124 | Q6: Q224 | R6: Q324 | S6: Q424 | T6: Q125 | U6: Q225 | V6: Q325 | W6: Q425 | AA6: Q324 | AB6: Q325 | AC6: % | AE6: Q424 | AF6: Q425 | AG6: % | AH6: Guidance | AI6: % | AJ6: Beat | AM6: R | AN6: EPS | AQ6: Q126 | AT6: FY22 | AU6: FY23 | AV6: FY24 | AW6: FY25 | AX6: FY26 | AZ6: Actual | BA6: 0.24 | BC6: Actual | BD6: 0.83
G7: Revenue | H7: 614 | I7: 688.5 | J7: 740.5 | K7: 759.8 | L7: 807.4 | M7: 872.7 | N7: 915.5 | O7: 939.1 | P7: 977.8 | Q7: 1060.1 | R7: 1189.1 | S7: 1131.6 | T7: 1187.8 | U7: 1286.5 | V7: 1356.7 | W7: 1384.344 | Z7: Cloud | AA7: 703036 | AB7: 880429 | AC7: =AB7/AA7-1 -> 0.25232421 | AE7: 738006 | AF7: 927730 | AG7: =AF7/AE7-1 -> 0.2570765 | AH7: =AE7*1.23 -> 907747.38 | AI7: =AH7/AE7-1 -> 0.23 | AJ7: =AF7/AH7-1 -> 0.022013415 | AL7: Proj. | AM7: 1359 | AN7: 0.83 | AP7: Guidance | AQ7: 1395-1403 | AT7: =SUM(H7:K7) -> 2802.8 | AU7: =SUM(L7:O7) -> 3534.7 | AV7: =SUM(P7:S7) -> 4358.6 | AW7: =SUM(T7:W7) -> 5215.344 | AX7: =AW7*1.18 -> 6154.1059 | AZ7: Beat | BA7: =BA6/BA5-1 -> 0.41176471 | BC7: Beat | BD7: =BD6/BD5-1 -> 0.10666667
G8: COGS | H8: 96.3 | I8: 110.2 | J8: 116.1 | K8: 130.4 | L8: 139.4 | M8: 155.9 | N8: 168.7 | O8: 169.8 | P8: 178 | Q8: 194.5 | R8: 213.4 | S8: 217.5 | T8: 217.6 | U8: 223.1 | V8: 219.7 | Z8: DataCenter | AA8: 364134 | AB8: 388516 | AC8: =AB8/AA8-1 -> 0.066958867 | AE8: 326663 | AF8: 380776 | AG8: =AF8/AE8-1 -> 0.1656539 | AH8: =+AE8*1.165 -> 380562.4 | AI8: =AH8/AE8-1 -> 0.165 | AJ8: =AF8/AH8-1 -> 0.00056128772 | AL8: Act. | AM8: 1384.344 | AP8: Prev. Guidance | AQ8: 1410 | AZ8: Q2FY26 OpInc Cons. | BA8: 24 | BC8: FY26 OpInc Cons. | BD8: 121
G9: Gross Profit | H9: 517.8 | I9: 578.3 | J9: 624.4 | K9: 629.4 | L9: 668 | M9: 716.8 | N9: 746.8 | O9: 769.3 | P9: 799.7 | Q9: 865.6 | R9: 975.7 | S9: 914.1 | T9: 970.2 | U9: 1063.3 | V9: 1137 | Z9: Server | AA9: 29720 | AC9: =AB9/AA9-1 -> -1 | AU9: =AU7/AT7-1 -> 0.26113173 | AV9: =AV7/AU7-1 -> 0.23308909 | AW9: =AW7/AV7-1 -> 0.19656403 | AX9: =AX7/AW7-1 -> 0.18 | AZ9: Actual | BA9: 39.6 | BC9: Actual | BD9: 136
G10: SG&A Expense | H10: 89.8 | I10: 115.7 | J10: 115 | K10: 131.7 | L10: 142.9 | M10: 156.1 | N10: 165.1 | O10: 142.2 | P10: 143.3 | Q10: 157.3 | R10: 157.6 | S10: 152.3 | T10: 146.6 | U10: 168.7 | V10: 168.3 | Z10: Marketplance | AA10: 92238 | AB10: 87771 | AC10: =AB10/AA10-1 -> -0.048429064 | AE10: 66921 | AF10: 75838 | AG10: =AF10/AE10-1 -> 0.13324666 | AH10: =+AE10*1 -> 66921 | AI10: =AH10/AE10-1 -> 0 | AJ10: =AF10/AH10-1 -> 0.13324666 | AL10: Beat | AM10: =AM8/AM7-1 -> 0.018649007 | AN10: =AN8/AN7-1 -> -1 | AZ10: Beat | BA10: =BA9/BA8-1 -> 0.65 | BC10: Beat | BD10: =BD9/BD8-1 -> 0.12396694
G11: Net Income | H11: -411.2 | I11: -22.3 | J11: 4.7 | K11: -90.6 | L11: -13.7 | M11: -205 | N11: -209 | O11: -59 | P11: -31.9 | Q11: -84.5 | R11: 12.8 | S11: -196.9 | T11: -123.8 | U11: -38.2 | V11: -70.8 | W11: -60.4 | Z11: Total | AA11: =SUM(AA7:AA10) -> 1189128 | AB11: =SUM(AB7:AB10) -> 1356716 | AC11: =AB11/AA11-1 -> 0.14093352 | AE11: =SUM(AE7:AE10) -> 1131590 | AF11: =SUM(AF7:AF10) -> 1384344 | AG11: =AF11/AE11-1 -> 0.22336182 | AH11: =AE11*1.19 -> 1346592.1 | AI11: =AH11/AE11-1 -> 0.19 | AJ11: =AF11/AH11-1 -> 0.028035141 | AZ11: Q3FY26 R Guid. Cons. | BA11: 241
G12: EPS | T12: -0.48 | U12: -0.15 | V12: -0.27 | AZ12: Actual | BA12: 239
AZ13: Beat | BA13: =BA12/BA11-1 -> -0.0082987552
G14: Revenue to SG&A | H14: =H7/H10 -> 6.8374165 | I14: =I7/I10 -> 5.9507347 | J14: =J7/J10 -> 6.4391304 | K14: =K7/K10 -> 5.7691724 | L14: =L7/L10 -> 5.650105 | M14: =M7/M10 -> 5.590647 | N14: =N7/N10 -> 5.5451242 | O14: =O7/O10 -> 6.6040788 | ... V14: =V7/V10 -> 8.0612002 | AZ14: Q3FY26 EPS Guid. Cons | BA14: 0.19
AZ15: Actual | BA15: 0.2
G16: R Y/Y | L16: =L7/H7-1 -> 0.31498371 | M16: =M7/I7-1 -> 0.26753813 | N16: =N7/J7-1 -> 0.23632681 | O16: =O7/K7-1 -> 0.23598315 | P16: =P7/L7-1 -> 0.21104781 | Q16: =Q7/M7-1 -> 0.21473588 | R16: =R7/N7-1 -> 0.29885309 | S16: =S7/O7-1 -> 0.20498349 | ... W16: =W7/S7-1 -> 0.22335101 | AZ16: Beat | BA16: =BA15/BA14-1 -> 0.052631579
G17: R Q/Q | I17: =I7/H7-1 -> 0.1213355 | J17: =J7/I7-1 -> 0.075526507 | K17: =K7/J7-1 -> 0.026063471 | L17: =L7/K7-1 -> 0.062648065 | M17: =M7/L7-1 -> 0.080876889 | N17: =N7/M7-1 -> 0.049043199 | O17: =O7/N7-1 -> 0.025778263 | P17: =P7/O7-1 -> 0.041209669 | ... W17: =W7/V7-1 -> 0.020375912 | AZ17: Q3FY26 OpInc Cons. | BA17: 30
G18: NI Y/Y | L18: =L11/H11-1 -> -0.96668288 | M18: =M11/I11-1 -> 8.1928251 | N18: =N11/J11-1 -> -45.468085 | O18: =O11/K11-1 -> -0.34878587 | P18: =P11/L11-1 -> 1.3284672 | Q18: =Q11/M11-1 -> -0.58780488 | R18: =R11/N11-1 -> -1.061244 | S18: =S11/O11-1 -> 2.3372881 | ... W18: =W11/S11-1 -> -0.6932453 | AZ18: Actual | BA18: 32
G19: NI Q/Q | I19: =I11/H11-1 -> -0.94576848 | J19: =J11/I11-1 -> -1.2107623 | K19: =K11/J11-1 -> -20.276596 | L19: =L11/K11-1 -> -0.84878587 | M19: =M11/L11-1 -> 13.963504 | N19: =N11/M11-1 -> 0.019512195 | O19: =O11/N11-1 -> -0.71770335 | P19: =P11/O11-1 -> -0.45932203 | ... W19: =W11/V11-1 -> -0.14689266 | AZ19: Beat | BA19: =BA18/BA17-1 -> 0.066666667
G22: PEGA | H22: Q210 | I22: Q310 | J22: Q111 | K22: Q211 | L22: Q311 | M22: Q411 | N22: Q112 | O22: Q212 | P22: Q312 | Q22: Q412 | R22: Q113 | S22: Q213 | T22: Q313 | U22: Q413 | V22: Q114 | W22: Q214 | X22: Q314 | Y22: Q414 | Z22: Q115 | AA22: Q215 | AB22: Q315 | AC22: Q415 | AD22: Q116 | AE22: Q216 | AF22: Q316 | AG22: Q416 | AH22: Q117 | AI22: Q217 | AJ22: Q317 | AK22: Q417 | AL22: Q118 | AM22: Q218 | AN22: Q318 | AO22: Q418 | AP22: Q119 | AQ22: Q219 | AR22: Q319 | AS22: Q419 | AT22: Q120 | AU22: Q220 | AV22: Q320 | AW22: Q420 | AX22: Q121 | AY22: Q221 | AZ22: Q321 | BA22: Q421 | BB22: Q122 | BC22: Q222 | BD22: Q322 | BE22: Q422 | BF22: Q123 | BG22: Q223 | BH22: Q323 | BI22: Q423 | BJ22: Q124 | BK22: Q224 | BL22: Q324 | BM22: Q424 | BN22: Q125 | BO22: Q225
G23: Revenue | H23: 82.2 | I23: 90 | J23: 102.4 | K23: 103.5 | L23: 95.5 | M23: 115.3 | N23: 111.2 | O23: 105.1 | P23: 101.7 | Q23: 143.8 | R23: 116.2 | S23: 117.3 | T23: 122 | U23: 153.4 | V23: 140.5 | W23: 143 | X23: 137.6 | Y23: 168.9 | Z23: 153.9 | AA23: 162 | AB23: 162.4 | AC23: 204.4 | AD23: 178.9 | AE23: 189 | AF23: 182.8 | AG23: 211.6 | AH23: 256.3 | AI23: 186.6 | AJ23: 191 | AK23: 254.6 | AL23: 235.2 | AM23: 196.8 | AN23: 203.3 | AO23: 256.4 | AP23: 212.5 | AQ23: 205.6 | AR23: 216.7 | AS23: 276.5 | AT23: 265.6 | AU23: 227.4 | AV23: 226 | AW23: 298.6 | AX23: 313.5 | AY23: 325.7 | AZ23: 256.3 | BA23: 316.2 | BB23: 376.3 | BC23: 274.3 | BD23: 270.7 | BE23: 396.5 | BF23: 325.5 | BG23: 298.3 | BH23: 334.6 | BI23: 474.2 | BJ23: 330.1 | BK23: 351.2 | BL23: 325 | BM23: 490.8 | BN23: 475.6 | BO23: 384.5
G24: COGS | H24: 31.3 | I24: 35 | J24: 40 | K24: 40.4 | L24: 41.8 | M24: 42.6 | N24: 41.5 | O24: 40 | P24: 37.7 | Q24: 38.2 | R24: 37.7 | S24: 37.9 | T24: 38.1 | U24: 43.8 | V24: 45.9 | W24: 46.7 | X24: 46.4 | Y24: 46.1 | Z24: 50.1 | AA24: 54.8 | AB24: 55.4 | AC24: 53.2 | AD24: 56.5 | AE24: 60.1 | AF24: 60.4 | AG24: 62.2 | AH24: 68.1 | AI24: 0 | AJ24: 0 | AK24: 211.6 | AL24: 75.6 | AM24: 73.8 | AN24: 74.4 | AO24: 77.9 | AP24: 74.4 | AQ24: 77.1 | AR24: 80.9 | AS24: 77.6 | AT24: 79.5 | AU24: 76.7 | AV24: 77.8 | AW24: 76.9 | AX24: 82.4 | AY24: 84.5 | AZ24: 84.2 | BA24: 85.2 | BB24: 88.2 | BC24: 95.1 | BD24: 93 | BE24: 92.3 | BF24: 97.9 | BG24: 96.1 | BH24: 93.8 | BI24: 90.6 | BJ24: 94.7 | BK24: 96.9 | BL24: 96.7 | BM24: 102.4 | BN24: 102.4 | BO24: 109.6
G25: Gross Profit | H25: 51 | I25: 55 | J25: 62.3 | K25: 63.1 | L25: 53.7 | M25: 72.7 | N25: 69.6 | O25: 65.1 | P25: 64 | Q25: 105.6 | R25: 78.6 | S25: 79.4 | T25: 83.9 | U25: 109.6 | V25: 94.6 | W25: 96.3 | X25: 91.2 | Y25: 122.8 | Z25: 103.9 | AA25: 107.2 | AB25: 107 | AC25: 151.2 | AD25: 122.3 | AE25: 128.9 | AF25: 122.4 | AG25: 149.4 | AH25: 188.2 | AI25: 186.6 | AJ25: 191 | AK25: 43 | AL25: 159.6 | AM25: 123 | AN25: 128.8 | AO25: 178.4 | AP25: 138.1 | AQ25: 128.5 | AR25: 135.8 | AS25: 198.9 | AT25: 186.1 | AU25: 150.7 | AV25: 148.2 | AW25: 221.7 | AX25: 231.1 | AY25: 241.2 | AZ25: 172 | BA25: 231 | BB25: 288.1 | BC25: 179.2 | BD25: 177.7 | BE25: 304.2 | BF25: 227.5 | BG25: 202.1 | BH25: 240.9 | BI25: 383.6 | BJ25: 235.5 | BK25: 254.2 | BL25: 228.3 | BM25: 388.5 | BN25: 373.2 | BO25: 274.9
G26: SG&A Expense | H26: 6.7 | I26: 6.4 | J26: 7.1 | K26: 6.8 | L26: 7.2 | M26: 7 | N26: 6.3 | O26: 7.7 | P26: 7.2 | Q26: 7.7 | R26: 6.8 | S26: 7.3 | T26: 7.1 | U26: 8.4 | V26: 9.3 | W26: 10.2 | X26: 8.8 | Y26: 9.1 | Z26: 6.3 | AA26: 10.2 | AB26: 9.6 | AC26: 10.6 | AD26: 11 | AE26: 11.3 | AF26: 11.7 | AG26: 11.9 | AH26: 12.3 | AI26: 12.7 | AJ26: 13.1 | AK26: 14 | AL26: 16.5 | AM26: 10.2 | AN26: 12.1 | AO26: 12.9 | AP26: 12.7 | AQ26: 14.2 | AR26: 14.8 | AS26: 14.9 | AT26: 15.6 | AU26: 15.7 | AV26: 17.9 | AW26: 18.3 | AX26: 18.3 | AY26: 19.2 | AZ26: 20.2 | BA26: 25.9 | BB26: 35.8 | BC26: 32.7 | BD26: 26 | BE26: 23.2 | BF26: 23.1 | BG26: 23.5 | BH26: 27.3 | BI26: 22.8 | BJ26: 23.5 | BK26: 25.4 | BL26: 35.7 | BM26: 28.2 | BN26: 33.8 | BO26: 31.8
G28: Revenue to SG&A | H28: =H23/H26 -> 12.268657 | I28: =I23/I26 -> 14.0625 | J28: =J23/J26 -> 14.422535 | K28: =K23/K26 -> 15.220588 | L28: =L23/L26 -> 13.263889 | M28: =M23/M26 -> 16.471429 | N28: =N23/N26 -> 17.650794 | O28: =O23/O26 -> 13.649351 | ... BO28: =BO23/BO26 -> 12.091195

Sheet Sentiment
F23: 01.01.2015-06.06.2025 | O23: 06.06.2025-07.28.2025
B24: Company | C24: Avg_Sentiment | D24: Std_Sentiment | E24: Min_Sentiment | F24: Max_Sentiment | G24: Latest_SMA7 | H24: Latest_SMA30 | I24: Latest_SMA100 | J24: Total_Posts | K24: Avg_Daily_Posts | L24: Days_Analyzed | O24: Company | P24: Avg_Sentiment | Q24: Std_Sentiment | R24: Min_Sentiment | S24: Max_Sentiment | T24: Latest_SMA7 | U24: Latest_SMA30 | V24: Latest_SMA100 | W24: Total_Posts | X24: Avg_Daily_Posts | Y24: Days_Analyzed
B25: GitLab | C25: 0.535 | D25: 0.5535 | E25: -0.9986 | F25: 1 | G25: 0.6645 | H25: 0.4223 | I25: 0.5124 | J25: 1739 | K25: 2.422 | L25: 718 | O25: GitLab | P25: 0.5958 | Q25: 0.3447 | R25: -0.3211 | S25: 0.9966 | T25: 0.6202 | U25: 0.6585 | V25: 0.5958 | W25: 212 | X25: 4.24 | Y25: 50
