Workbook

Sheet Main
I7: P | J7: 19.38 | K7: 46060
I8: S/O | J8: =219270.891+8377.623 -> 227648.51
I9: MC | J9: =J7*J8 -> 4411828.2 | K9: Q325
I10: D | J10: =+Model!Q61 -> 971023 | K10: Q325
I11: C | J11: =+Model!Q44+Model!Q49 -> 888980 | K11: Q325
I13: EV | J13: =J9-J11+J10 -> 4493871.2

Sheet Model
A1: Main
C2: Q122 | D2: Q222 | E2: Q322 | F2: Q422 | G2: Q123 | H2: Q223 | I2: Q323 | J2: Q423 | K2: Q124 | L2: Q224 | M2: Q324 | N2: Q424 | O2: Q125 | P2: Q225 | Q2: Q325 | R2: Q425 | S2: Q126 | T2: Q226 | U2: Q326 | V2: Q426 | W2: Q127 | X2: Q227 | Y2: Q327 | Z2: Q427 | AE2: 2022 | AF2: 2023 | AG2: 2024 | AH2: 2025 | AI2: 2026 | AJ2: 2027 | AK2: 2028
B3: Online | C3: 94102 | D3: 107462 | E3: 139781 | F3: 161162 | G3: 184175 | H3: 201178 | I3: 219665 | J3: 237363 | K3: 267761 | L3: 306843 | M3: 392573 | N3: 470760 | O3: 576361 | P3: 536880 | Q3: 589095 | AE3: 502507 | AF3: 842381 | AG3: =SUM(K3:N3) -> 1437937
B4: Wholesale | C4: 7212 | D4: 6101 | E4: 5055 | F4: 6041 | G4: 6595 | H4: 6734 | I4: 7034 | J4: 9256 | K4: 10410 | L4: 8805 | M4: 8983 | N4: 10379 | O4: 9649 | P4: 7953 | Q4: 9881 | AE4: 24409 | AF4: 29619 | AG4: =SUM(K4:N4) -> 38577
B5: Total revenue | C5: =SUM(C3:C4) -> 101314 | D5: =SUM(D3:D4) -> 113563 | E5: =SUM(E3:E4) -> 144836 | F5: =SUM(F3:F4) -> 167203 | G5: =SUM(G3:G4) -> 190770 | H5: =SUM(H3:H4) -> 207912 | I5: =SUM(I3:I4) -> 226699 | J5: =SUM(J3:J4) -> 246619 | ... Q5: =SUM(Q3:Q4) -> 598976 | R5: 619000 | S5: 651000 | T5: 663000 | U5: 707000 | V5: 751000 | W5: 736000 | X5: 763000 | Y5: 805000 | Z5: 836000 | AE5: =SUM(AE3:AE4) -> 526916 | AF5: =SUM(AF3:AF4) -> 872000 | AG5: =SUM(AG3:AG4) -> 1476514 | AH5: =SUM(AH3:AH4) -> 0
B6: COGS | C6: 26558 | D6: 26387 | E6: 30383 | F6: 34866 | G6: 37345 | H6: 37754 | I6: 39391 | J6: 42561 | K6: 49076 | L6: 59035 | M6: 83670 | N6: 111598 | O6: 155321 | P6: 128637 | Q6: 156918 | AE6: 118194 | AF6: 157051 | AG6: =SUM(K6:N6) -> 303379
B7: Gross Profit | C7: =C5-C6 -> 74756 | D7: =D5-D6 -> 87176 | E7: =E5-E6 -> 114453 | F7: =F5-F6 -> 132337 | G7: =G5-G6 -> 153425 | H7: =H5-H6 -> 170158 | I7: =I5-I6 -> 187308 | J7: =J5-J6 -> 204058 | ... T7: =T5-T6 -> 663000 | AE7: =AE5-AE6 -> 408722 | AF7: =AF5-AF6 -> 714949 | AG7: =AG5-AG6 -> 1173135 | AH7: =AH5-AH6 -> 0
B8: Marketing | C8: 48093 | D8: 60490 | E8: 78462 | F8: 85542 | G8: 97245 | H8: 107219 | I8: 116076 | J8: 125895 | K8: 130553 | L8: 144922 | M8: 182284 | N8: 221085 | O8: 231235 | P8: 217862 | Q8: 232150 | AE8: 272587 | AF8: 446435 | AG8: =SUM(K8:N8) -> 678844
B9: Operations | C9: 15683 | D9: 17448 | E9: 21751 | F9: 22521 | G9: 26182 | H9: 29227 | I9: 31609 | J9: 32839 | K9: 38747 | L9: 41453 | M9: 47519 | N9: 58083 | O9: 63033 | P9: 66490 | Q9: 76848 | AE9: 77403 | AF9: 119857 | AG9: =SUM(K9:N9) -> 185802
B10: R&D | C10: 6088 | D10: 6861 | E10: 7977 | F10: 8311 | G10: 10748 | H10: 11804 | I10: 12270 | J10: 13405 | K10: 15324 | L10: 18654 | M10: 21092 | N10: 23749 | O10: 29914 | P10: 37848 | Q10: 40577 | AE10: 29237 | AF10: 48227 | AG10: =SUM(K10:N10) -> 78819
B11: G&A | C11: 21811 | D11: 22567 | E11: 26246 | F11: 27568 | G11: 30513 | H11: 31144 | I11: 35907 | J11: 32319 | K11: 34568 | L11: 40554 | M11: 44617 | N11: 48028 | O11: 48610 | P11: 67273 | Q11: 80676 | AE11: 98192 | AF11: 129883 | AG11: =SUM(K11:N11) -> 167767
B12: OpEx | C12: =SUM(C8:C11) -> 91675 | D12: =SUM(D8:D11) -> 107366 | E12: =SUM(E8:E11) -> 134436 | F12: =SUM(F8:F11) -> 143942 | G12: =SUM(G8:G11) -> 164688 | H12: =SUM(H8:H11) -> 179394 | I12: =SUM(I8:I11) -> 195862 | J12: =SUM(J8:J11) -> 204458 | ... T12: =SUM(T8:T11) -> 0 | AE12: =SUM(AE8:AE11) -> 477419 | AF12: =SUM(AF8:AF11) -> 744402 | AG12: =SUM(AG8:AG11) -> 1111232 | AH12: =SUM(AH8:AH11) -> 0
B13: OpInc | C13: =+C7-C12 -> -16919 | D13: =+D7-D12 -> -20190 | E13: =+E7-E12 -> -19983 | F13: =+F7-F12 -> -11605 | G13: =+G7-G12 -> -11263 | H13: =+H7-H12 -> -9236 | I13: =+I7-I12 -> -8554 | J13: =+J7-J12 -> -400 | ... T13: =+T7-T12 -> 663000 | AE13: =+AE7-AE12 -> -68697 | AF13: =+AF7-AF12 -> -29453 | AG13: =+AG7-AG12 -> 61903 | AH13: =+AH7-AH12 -> 0
B14: Other income | C14: 761 | D14: =121+402 -> 523 | E14: =450+677 -> 1127 | F14: =-942+1519 -> 577 | G14: =-295+1877 -> 1582 | H14: =-173+2239 -> 2066 | I14: =-588+2226 -> 1638 | J14: =-19+2615 -> 2596 | K14: 2500 | L14: 2394 | M14: 1219 | N14: 3695 | O14: 2598 | P14: 6130 | Q14: =-7626+8042 -> 416 | AE14: =70+2918 -> 2988 | AF14: =-1075+8957 -> 7882 | AG14: =SUM(K14:N14) -> 9808
B15: Pretax Inc | C15: =C13+C14 -> -16158 | D15: =D13+D14 -> -19667 | E15: =E13+E14 -> -18856 | F15: =F13+F14 -> -11028 | G15: =G13+G14 -> -9681 | H15: =H13+H14 -> -7170 | I15: =I13+I14 -> -6916 | J15: =J13+J14 -> 2196 | ... T15: =T13+T14 -> 663000 | AE15: =AE13+AE14 -> -65709 | AF15: =AF13+AF14 -> -21571 | AG15: =AG13+AG14 -> 71711 | AH15: =AH13+AH14 -> 0
B16: Taxes | C16: -94 | D16: -12 | E16: 16 | F16: 121 | G16: -386 | H16: 13 | I16: -651 | J16: -951 | K16: -1275 | L16: -127 | M16: 51995 | N16: 3734 | O16: -11010 | P16: 9652 | Q16: 3551 | AE16: 31 | AF16: -1975 | AG16: =SUM(K16:N16) -> 54327
B17: Net Income | C17: =C15+C16 -> -16252 | D17: =D15+D16 -> -19679 | E17: =E15+E16 -> -18840 | F17: =F15+F16 -> -10907 | G17: =G15+G16 -> -10067 | H17: =H15+H16 -> -7157 | I17: =I15+I16 -> -7567 | J17: =J15+J16 -> 1245 | ... T17: =T15+T16 -> 663000 | AE17: =AE15+AE16 -> -65678 | AF17: =AF15+AF16 -> -23546 | AG17: =AG15+AG16 -> 126038 | AH17: =AH15+AH16 -> 0
B18: S/O | C18: 202695.97 | D18: 203949.54 | E18: 205232.97 | F18: 206140.28 | G18: 207140.3 | H18: 208422.83 | I18: 210134.68 | J18: 211584.92 | K18: 213452.09 | L18: 214618.04 | M18: 216617.14 | N18: 219027.48 | O18: 221989.33 | P18: 224373.38 | Q18: 226313.82 | AE18: =+F18 -> 206140.28 | AF18: =J18 -> 211584.92 | AG18: =N18 -> 219027.48
B19: EPS | C19: =C17/C18 -> -0.080179196 | D19: =D17/D18 -> -0.096489556 | E19: =E17/E18 -> -0.091798117 | F19: =F17/F18 -> -0.052910571 | G19: =G17/G18 -> -0.048599911 | H19: =H17/H18 -> -0.034338849 | I19: =I17/I18 -> -0.036010239 | J19: =J17/J18 -> 0.0058841624 | ... T19: =T17/T18 -> #DIV/0! | AE19: =AE17/AE18 -> -0.31860828 | AF19: =AF17/AF18 -> -0.11128393 | AG19: =AG17/AG18 -> 0.57544376 | AH19: =AH17/AH18 -> #DIV/0!
B21: Subscribers | C21: 646 | D21: 748 | E21: 916 | F21: 1040 | G21: 1209 | H21: 1300 | I21: 1426 | J21: 1537 | K21: 1709 | L21: 1864 | M21: 2047 | N21: 2229 | O21: 2366 | P21: 2439 | Q21: 2471
B22: QT-ly Revenue per Avg Subscriber | C22: =C5/C21 -> 156.83282 | D22: =D5/D21 -> 151.82219 | E22: =E5/E21 -> 158.1179 | F22: =F5/F21 -> 160.77212 | G22: =G5/G21 -> 157.79156 | H22: =H5/H21 -> 159.93231 | I22: =I5/I21 -> 158.97546 | J22: =J5/J21 -> 160.45478 | ... T22: =T5/T21 -> #DIV/0!
B23: Net Orders | C23: 1207 | D23: 1385 | E23: 1675 | F23: 1855 | G23: 2047 | H23: 2109 | I23: 2222 | J23: 2298 | K23: 2461 | L23: 2527 | M23: 2664 | N23: 2807
B24: AOV (Avg Order Value) | C24: 78 | D24: 78 | E24: 83 | F24: 87 | G24: 90 | H24: 95 | I24: 99 | J24: 103 | K24: 109 | L24: 121 | M24: 147 | N24: 168
B26: Subscriber seq | D26: =D21/C21-1 -> 0.15789474 | E26: =E21/D21-1 -> 0.22459893 | F26: =F21/E21-1 -> 0.13537118 | G26: =G21/F21-1 -> 0.1625 | H26: =H21/G21-1 -> 0.075268817 | I26: =I21/H21-1 -> 0.096923077 | J26: =J21/I21-1 -> 0.077840112 | K26: =K21/J21-1 -> 0.11190631 | ... T26: =T21/S21-1 -> #DIV/0!
B27: Subscriber Y/Y | G27: =G21/C21-1 -> 0.87151703 | H27: =H21/D21-1 -> 0.73796791 | I27: =I21/E21-1 -> 0.55676856 | J27: =J21/F21-1 -> 0.47788462 | K27: =K21/G21-1 -> 0.41356493 | L27: =L21/H21-1 -> 0.43384615 | M27: =M21/I21-1 -> 0.43548387 | N27: =N21/J21-1 -> 0.45022772 | ... T27: =T21/P21-1 -> -1
B28: Rev per Avg Subscriber Y/Y | G28: =G22/C22-1 -> 0.0061131717 | H28: =H22/D22-1 -> 0.053418509 | I28: =I22/E22-1 -> 0.0054234964 | J28: =J22/F22-1 -> -0.0019738083 | K28: =K22/G22-1 -> 0.03153985 | L28: =L22/H22-1 -> 0.05881706 | M28: =M22/I22-1 -> 0.23395181 | N28: =N22/J22-1 -> 0.34526495 | ... T28: =T22/P22-1 -> #DIV/0!
B30: Gross Margin | C30: =C7/C5 -> 0.73786446 | D30: =D7/D5 -> 0.76764439 | E30: =E7/E5 -> 0.79022481 | F30: =F7/F5 -> 0.79147503 | G30: =G7/G5 -> 0.80424071 | H30: =H7/H5 -> 0.81841356 | I30: =I7/I5 -> 0.82624096 | J30: =J7/J5 -> 0.82742206 | ... T30: =T7/T5 -> 1 | AE30: =AE7/AE5 -> 0.77568721 | AF30: =AF7/AF5 -> 0.81989564 | AG30: =AG7/AG5 -> 0.79453022 | AH30: =AH7/AH5 -> #DIV/0!
B31: Op Margin | C31: =C13/C5 -> -0.16699568 | D31: =D13/D5 -> -0.17778678 | E31: =E13/E5 -> -0.13796984 | F31: =F13/F5 -> -0.069406649 | G31: =G13/G5 -> -0.059039681 | H31: =H13/H5 -> -0.04442264 | I31: =I13/I5 -> -0.037732853 | J31: =J13/J5 -> -0.001621935 | ... T31: =T13/T5 -> 1 | AE31: =AE13/AE5 -> -0.13037562 | AF31: =AF13/AF5 -> -0.033776376 | AG31: =AG13/AG5 -> 0.041925102 | AH31: =AH13/AH5 -> #DIV/0!
B32: Net Margin | C32: =C17/C5 -> -0.16041218 | D32: =D17/D5 -> -0.17328707 | E32: =E17/E5 -> -0.13007816 | F32: =F17/F5 -> -0.065232083 | G32: =G17/G5 -> -0.052770352 | H32: =H17/H5 -> -0.034423218 | I32: =I17/I5 -> -0.033379062 | J32: =J17/J5 -> 0.0050482728 | ... T32: =T17/T5 -> 1 | AE32: =AE17/AE5 -> -0.12464605 | AF32: =AF17/AF5 -> -0.027002294 | AG32: =AG17/AG5 -> 0.085361873 | AH32: =AH17/AH5 -> #DIV/0!
B34: Revenue Y/Y | G34: =G5/C5-1 -> 0.88295793 | H34: =H5/D5-1 -> 0.83080757 | I34: =I5/E5-1 -> 0.56521169 | J34: =J5/F5-1 -> 0.47496755 | K34: =K5/G5-1 -> 0.45814856 | L34: =L5/H5-1 -> 0.51818077 | M34: =M5/I5-1 -> 0.77131791 | N34: =N5/J5-1 -> 0.95094052 | ... T34: =T5/P5-1 -> 0.21688664 | AF34: =AF5/AE5-1 -> 0.65491274 | AG34: =AG5/AF5-1 -> 0.69325 | AH34: =AH5/AG5-1 -> -1
B36: Marketing Margin | C36: =C8/C$7 -> 0.64333298 | D36: =D8/D$7 -> 0.69388364 | E36: =E8/E$7 -> 0.68553904 | F36: =F8/F$7 -> 0.64639519 | G36: =G8/G$7 -> 0.6338276 | H36: =H8/H$7 -> 0.63011436 | I36: =I8/I$7 -> 0.61970658 | J36: =J8/J$7 -> 0.61695694 | ... T36: =T8/T$7 -> 0 | AE36: =AE8/AE$7 -> 0.6669252 | AF36: =AF8/AF$7 -> 0.62442916 | AG36: =AG8/AG$7 -> 0.57865804 | AH36: =AH8/AH$7 -> #DIV/0!
B37: Operating Margin | C37: =C9/C$7 -> 0.20978918 | D37: =D9/D$7 -> 0.20014683 | E37: =E9/E$7 -> 0.19004307 | F37: =F9/F$7 -> 0.17017916 | G37: =G9/G$7 -> 0.17065015 | H37: =H9/H$7 -> 0.17176389 | I37: =I9/I$7 -> 0.16875414 | J37: =J9/J$7 -> 0.16092974 | ... T37: =T9/T$7 -> 0 | AE37: =AE9/AE$7 -> 0.18937811 | AF37: =AF9/AF$7 -> 0.16764413 | AG37: =AG9/AG$7 -> 0.15838075 | AH37: =AH9/AH$7 -> #DIV/0!
B38: R&D Margin | C38: =C10/C$7 -> 0.081438279 | D38: =D10/D$7 -> 0.078702854 | E38: =E10/E$7 -> 0.069696731 | F38: =F10/F$7 -> 0.062801786 | G38: =G10/G$7 -> 0.070053772 | H38: =H10/H$7 -> 0.06937082 | I38: =I10/I$7 -> 0.065507079 | J38: =J10/J$7 -> 0.065692107 | ... T38: =T10/T$7 -> 0 | AE38: =AE10/AE$7 -> 0.071532729 | AF38: =AF10/AF$7 -> 0.067455161 | AG38: =AG10/AG$7 -> 0.067186641 | AH38: =AH10/AH$7 -> #DIV/0!
B39: G&A Margin | C39: =C11/C$7 -> 0.29176253 | D39: =D11/D$7 -> 0.25886712 | E39: =E11/E$7 -> 0.22931684 | F39: =F11/F$7 -> 0.20831665 | G39: =G11/G$7 -> 0.19887893 | H39: =H11/H$7 -> 0.18302989 | I39: =I11/I$7 -> 0.1917003 | J39: =J11/J$7 -> 0.15838144 | ... T39: =T11/T$7 -> 0 | AE39: =AE11/AE$7 -> 0.24024153 | AF39: =AF11/AF$7 -> 0.1816675 | AG39: =AG11/AG$7 -> 0.14300741 | AH39: =AH11/AH$7 -> #DIV/0!
B43: Net Cash | C43: =+C44+C49-C61 -> 0 | D43: =+D44+D49-D61 -> 0 | E43: =+E44+E49-E61 -> 0 | F43: =+F44+F49-F61 -> 179625 | G43: =+G44+G49-G61 -> 184393 | H43: =+H44+H49-H61 -> 193142 | I43: =+I44+I49-I61 -> 212497 | J43: =+J44+J49-J61 -> 220981 | ... Q43: =+Q44+Q49-Q61 -> -82043 | AE43: =+AE44+AE49-AE61 -> 179625 | AF43: =+AF44+AF49-AF61 -> 331862 | AG43: =+AG44+AG49-AG61 -> 300251 | AH43: =+AH44+AH49-AH61 -> 0 | AI43: =+AI44+AI49-AI61 -> 0 | AJ43: =+AJ44+AJ49-AJ61 -> 0 | AK43: =+AK44+AK49-AK61 -> 0
B44: Cash | F44: =46772+132853 -> 179625 | G44: =48745+135648 -> 184393 | H44: =65417+127725 -> 193142 | I44: =57996+154501 -> 212497 | J44: =96663+124318 -> 220981 | K44: =105237+98355 -> 203592 | L44: =129295+97997 -> 227292 | M44: =165518+88553 -> 254071 | N44: =220584+79667 -> 300251 | O44: =273736+48935 -> 322671 | P44: =1124582+20033 -> 1144615 | Q44: =345778+283966 -> 629744 | AE44: =46772+132853 -> 179625 | AF44: =96663+124318 -> 220981 | AG44: =220584+79667 -> 300251
B45: Inventory | F45: 21562 | G45: 20697 | H45: 21417 | I45: 21992 | J45: 22464 | K45: 29826 | L45: 40588 | M45: 49110 | N45: 64427 | O45: 76096 | P45: 141800 | Q45: 105989 | AE45: 21562 | AF45: 22464 | AG45: 64427
B46: Prepaids | F46: 15408 | G46: 20435 | H46: 20089 | I46: 15730 | J46: 21608 | K46: 28316 | L46: 23038 | M46: 23194 | N46: 31153 | O46: 48197 | P46: 69151 | Q46: 109527 | AE46: 15408 | AF46: 21608 | AG46: 31153
B47: Restricted cash | F47: 856 | G47: 856 | H47: 856 | I47: 856 | J47: 856 | K47: 856 | L47: 856 | M47: 856 | N47: 856 | O47: 1223 | P47: 368 | Q47: 0 | AE47: 856 | AF47: 856 | AG47: 856
B48: Goodwill | F48: 110881 | G48: 110881 | H48: 110881 | I48: 110881 | J48: 110881 | K48: 110881 | L48: 110881 | M48: 112728 | N48: 112728 | O48: 117753 | P48: 117753 | Q48: 438340 | AE48: 110881 | AG48: 112728
B49: Investments, NC | F49: 0 | G49: 0 | H49: 0 | I49: 0 | J49: 0 | K49: 0 | L49: 0 | M49: 0 | N49: 0 | O49: 0 | P49: 0 | Q49: 259236 | AE49: 0 | AF49: 110881 | AG49: 0
B50: PP&A | F50: 11199 | G50: 13587 | H50: 18802 | I50: 28238 | J50: 36143 | K50: 45212 | L50: 49540 | M50: 52144 | N50: 82083 | O50: 155707 | P50: 205480 | Q50: 267438 | AE50: 11199 | AF50: 36143 | AG50: 82083
B51: Intangibles | F51: 21841 | G51: 20909 | H51: 19962 | I51: 19297 | J51: 18574 | K51: 17853 | L51: 17133 | M51: 44818 | N51: 43410 | O51: 43431 | P51: 40657 | Q51: 194931 | AE51: 21841 | AF51: 18574 | AG51: 43410
B52: Operating lease ROU | F52: 4936 | G52: 4548 | H52: 4735 | I52: 4302 | J52: 9588 | K52: 11422 | L52: 11034 | M52: 10884 | N52: 10881 | O52: 62198 | P52: 71661 | Q52: 139297 | AE52: 4936 | AF52: 9588 | AG52: 10881
B53: Deferred tax | F53: 0 | G53: 0 | H53: 0 | I53: 0 | J53: 0 | K53: 0 | L53: 0 | M53: 54317 | N53: 61603 | O53: 62493 | P53: 84229 | Q53: 84925 | AE53: 0 | AG53: 61603
B54: ONCA | F54: 33 | G54: 0 | H54: 0 | I54: 72 | J54: 91 | K54: 138 | L54: 138 | M54: 138 | N54: 147 | O54: 1942 | P54: 1868 | Q54: 3877 | AE54: 33 | AF54: 91 | AG54: 147
B55: Total assets | C55: =SUM(C44:C54) -> 0 | D55: =SUM(D44:D54) -> 0 | E55: =SUM(E44:E54) -> 0 | F55: =SUM(F44:F54) -> 366341 | G55: =SUM(G44:G54) -> 376306 | H55: =SUM(H44:H54) -> 389884 | I55: =SUM(I44:I54) -> 413865 | J55: =SUM(J44:J54) -> 441186 | ... Q55: =SUM(Q44:Q54) -> 2233304 | AE55: =SUM(AE44:AE54) -> 366341 | AF55: =SUM(AF44:AF54) -> 441186 | AG55: =SUM(AG44:AG54) -> 707539 | AH55: =SUM(AH44:AH54) -> 0 | AI55: =SUM(AI44:AI54) -> 0 | AJ55: =SUM(AJ44:AJ54) -> 0 | AK55: =SUM(AK44:AK54) -> 0
B56: A/P | F56: 32363 | G56: 37609 | H56: 32267 | I56: 42001 | J56: 43070 | K56: 43919 | L56: 57099 | M56: 75444 | N56: 91180 | O56: 108919 | P56: 105009 | Q56: 198413 | AE56: 32363 | AF56: 43070 | AG56: 91180
B57: Accrued | F57: 12448 | G57: 14121 | H57: 19607 | I57: 27360 | J57: 28972 | K57: 26714 | L57: 28948 | M57: 43224 | N57: 53013 | O57: 56942 | P57: 65671 | Q57: 80131 | AE57: 12448 | AF57: 28972 | AG57: 53013
B58: Deferred revenue | F58: 1472 | G58: 2866 | H58: 2058 | I58: 4392 | J58: 7733 | K58: 13735 | L58: 20990 | M58: 32184 | N58: 75285 | O58: 110765 | P58: 98417 | Q58: 118458 | AE58: 1472 | AF58: 7733 | AG58: 75285
B59: Earn-out | F59: 0 | G59: 0 | H59: 4776 | I59: 6862 | J59: 7412 | K59: 7412 | L59: 0 | M59: 0 | N59: 0 | O59: 0 | P59: 0 | Q59: 50361 | AE59: 0 | AF59: 7412 | AG59: 0
B60: Operating lease | F60: 1658 | G60: 1687 | H60: 1839 | I60: 1930 | J60: 1281 | K60: 1544 | L60: 1634 | M60: 1793 | N60: 1889 | O60: 3736 | P60: 3135 | Q60: 3422 | AE60: 1658 | AF60: 1281 | AG60: 1889
B61: Debt | F61: 0 | G61: 0 | H61: 0 | I61: 0 | J61: 0 | K61: 0 | L61: 0 | M61: 0 | N61: 0 | O61: 0 | P61: 969467 | Q61: 971023 | AE61: 0 | AF61: 0 | AG61: 0
B62: Operating lease, NC | F62: 3649 | G62: 3217 | H62: 3252 | I62: 2753 | J62: 8667 | K62: 10279 | L62: 9841 | M62: 9565 | N62: 9456 | O62: 56648 | P62: 71786 | Q62: 143578 | AE62: 3649 | AF62: 8667 | AG62: 9456
B63: Earn-out, NC | F63: 2975 | G63: 3977 | H63: 0 | I63: 0 | J63: 0 | K63: 0 | L63: 0 | M63: 0 | N63: 0 | O63: 0 | P63: 0 | Q63: 49623 | AE63: 2975 | AF63: 0 | AG63: 0
B64: Deferred tax | F64: 0 | G64: 0 | H64: 0 | I64: 0 | J64: 0 | K64: 0 | L64: 0 | M64: 0 | N64: 0 | O64: 0 | P64: 0 | Q64: 31208 | AE64: 0 | AF64: 0 | AG64: 0
B65: ONCL | F65: 35 | G65: 84 | H65: 14 | I65: 5 | J65: 22 | K65: 21 | L65: 22 | M65: 0 | N65: 0 | O65: 2440 | P65: 1401 | Q65: 6105 | AE65: 35 | AF65: 22 | AG65: 0
B66: Total liabilities | C66: =SUM(C56:C65) -> 0 | D66: =SUM(D56:D65) -> 0 | E66: =SUM(E56:E65) -> 0 | F66: =SUM(F56:F65) -> 54600 | G66: =SUM(G56:G65) -> 63561 | H66: =SUM(H56:H65) -> 63813 | I66: =SUM(I56:I65) -> 85303 | J66: =SUM(J56:J65) -> 97157 | ... Q66: =SUM(Q56:Q65) -> 1652322 | AE66: =SUM(AE56:AE65) -> 54600 | AF66: =SUM(AF56:AF65) -> 97157 | AG66: =SUM(AG56:AG65) -> 230823 | AH66: =SUM(AH56:AH65) -> 0 | AI66: =SUM(AI56:AI65) -> 0 | AJ66: =SUM(AJ56:AJ65) -> 0 | AK66: =SUM(AK56:AK65) -> 0
B67: SE | F67: 311741 | G67: 312745 | H67: 320071 | I67: 328562 | J67: 344029 | K67: 344482 | L67: 361966 | M67: 440051 | N67: 476716 | O67: 549261 | P67: 562696 | Q67: 580982 | AE67: 311741 | AF67: 344029 | AG67: 476716
B68: L+SE | C68: =C66+C67 -> 0 | D68: =D66+D67 -> 0 | E68: =E66+E67 -> 0 | F68: =F66+F67 -> 366341 | G68: =G66+G67 -> 376306 | H68: =H66+H67 -> 383884 | I68: =I66+I67 -> 413865 | J68: =J66+J67 -> 441186 | ... Q68: =Q66+Q67 -> 2233304 | AE68: =AE66+AE67 -> 366341 | AF68: =AF66+AF67 -> 441186 | AG68: =AG66+AG67 -> 707539 | AH68: =AH66+AH67 -> 0 | AI68: =AI66+AI67 -> 0 | AJ68: =AJ66+AJ67 -> 0 | AK68: =AK66+AK67 -> 0
B71: Current Ratio | F71: =(F44+F45+F46)/(F56+F57+F58+F59+F60) -> 4.5179491 | G71: =(G44+G45+G46)/(G56+G57+G58+G59+G60) -> 4.0069826 | H71: =(H44+H45+H46)/(H56+H57+H58+H59+H60) -> 3.8754686 | I71: =(I44+I45+I46)/(I56+I57+I58+I59+I60) -> 3.0313041 | J71: =(J44+J45+J46)/(J56+J57+J58+J59+J60) -> 2.9960325 | K71: =(K44+K45+K46)/(K56+K57+K58+K59+K60) -> 2.8045733 | L71: =(L44+L45+L46)/(L56+L57+L58+L59+L60) -> 2.6770528 | M71: =(M44+M45+M46)/(M56+M57+M58+M59+M60) -> 2.138131 | ... Q71: =(Q44+Q45+Q46)/(Q56+Q57+Q58+Q59+Q60) -> 1.8750846
B72: Debt-to-Equity | F72: =F66/F67 -> 0.17514539 | G72: =G66/G67 -> 0.20323586 | H72: =H66/H67 -> 0.19937139 | I72: =I66/I67 -> 0.25962528 | J72: =J66/J67 -> 0.28240933 | K72: =K66/K67 -> 0.30081107 | L72: =L66/L67 -> 0.32747275 | M72: =M66/M67 -> 0.36861636 | ... Q72: =Q66/Q67 -> 2.8440158
B75: Model NI | C75: =C17 -> -16252 | D75: =D17 -> -19679 | E75: =E17 -> -18840 | F75: =F17 -> -10907 | G75: =G17 -> -10067 | H75: =H17 -> -7157 | I75: =I17 -> -7567 | J75: =J17 -> 1245 | ... Q75: =Q17 -> 15774 | AE75: =AE17 -> -65678 | AF75: =AF17 -> -23546 | AG75: =AG17 -> 126038 | AH75: =AH17 -> 0 | AI75: =AI17 -> 0 | AJ75: =AJ17 -> 0 | AK75: =AK17 -> 0
B76: GAAP NI | C76: -16252 | D76: -19679 | E76: -18840 | F76: -10907 | G76: -10067 | H76: -7157 | I76: -7567 | J76: 1245 | K76: 11128 | L76: 13297 | M76: 75588 | N76: 26025 | O76: 49485 | P76: 42505 | Q76: 15774 | AE76: -65678 | AF76: -23546 | AG76: 126038
B77: D&A | C77: 1741 | D77: 1821 | E77: 1902 | F77: 2010 | G77: 2117 | H77: 2377 | I77: 2363 | J77: 2658 | K77: 3001 | L77: 3643 | M77: 4383 | N77: 6061 | O77: 8276 | P77: 10465 | Q77: 17669 | AE77: 7474 | AF77: 9515 | AG77: 17088
B78: SBC | C78: 8856 | D78: 10632 | E78: 10979 | F78: 12350 | G78: 14167 | H78: 16845 | I78: 17277 | J78: 17791 | K78: 19032 | L78: 24042 | M78: 24899 | N78: 24349 | O78: 24858 | P78: 35726 | Q78: 40172 | AE78: 42817 | AF78: 66080 | AG78: 92322
B79: Fair value of liabilities | C79: -441 | D79: -121 | E79: -450 | F79: 942 | G79: 295 | H79: 173 | I79: 588 | J79: 19 | K79: 0 | L79: 0 | M79: 0 | N79: 0 | O79: 0 | P79: 0 | Q79: 7626 | AE79: -70 | AF79: 1075 | AG79: 0
B80: Accretion of securities | C80: 971 | D80: -108 | E80: 123 | F80: -840 | G80: -1041 | H80: -1476 | I80: -1517 | J80: -1652 | K80: -1077 | L80: -1204 | M80: -1159 | N80: -915 | O80: -693 | P80: -367 | Q80: -253 | AE80: 146 | AF80: -5686 | AG80: -4355
B81: Deferreed taxes | C81: -112 | D81: -146 | E81: -122 | F81: -214 | G81: 49 | H81: -69 | I81: -10 | J81: 17 | K81: -1 | L81: 1 | M81: -54340 | N81: -7309 | O81: -890 | P81: -9456 | Q81: 862 | AE81: -594 | AF81: -13 | AG81: -61649
B82: Impairments | C82: 0 | D82: 0 | E82: 1127 | F82: 0 | G82: 429 | H82: 0 | I82: 0 | J82: 0 | K82: 0 | L82: 114 | M82: 0 | N82: 0 | O82: 0 | P82: 0 | Q82: 531 | AE82: 1127 | AF82: 429 | AG82: 114
B83: Amort. Of debt | C83: 0 | D83: 0 | E83: 0 | F83: 0 | G83: 0 | H83: 0 | I83: 0 | J83: 0 | K83: 0 | L83: 0 | M83: 0 | N83: 0 | O83: 0 | P83: 1047 | Q83: 1743 | AE83: 0 | AF83: 0 | AG83: 0
B84: Non-cash operating lease | C84: 377 | D84: 378 | E84: 401 | F84: 449 | G84: 448 | H84: 466 | I84: 498 | J84: 510 | K84: 574 | L84: 647 | M84: 654 | N84: 671 | O84: 1905 | P84: 2689 | Q84: 3311 | AE84: 1605 | AF84: 1922 | AG84: 2546
B85: Non-cash acquisitions | C85: 69 | D85: -11 | E85: -256 | F85: 1035 | G85: 566 | H85: 500 | I85: 1198 | J85: 427 | K85: 0 | L85: 0 | M85: 0 | N85: 0 | O85: 1030 | P85: 1955 | Q85: 1976 | AE85: 837 | AF85: 2691 | AG85: 0
B86: Non-cash other | C86: -163 | D86: 163 | E86: 0 | F86: 0 | G86: 75 | H86: 0 | I86: 12 | J86: 108 | K86: 484 | L86: -72 | M86: 23 | N86: -78 | O86: 832 | P86: -2147 | Q86: -814 | AE86: 0 | AF86: 195 | AG86: 357
B87: Inventory | C87: 1415 | D87: -7530 | E87: -2674 | F87: 785 | G87: 865 | H87: -720 | I87: -575 | J87: -472 | K87: -7362 | L87: -10762 | M87: -8171 | N87: -15317 | O87: -11669 | P87: -65704 | Q87: 37270 | AE87: -8004 | AF87: -902 | AG87: -41612
... B94: Earn-out payable | C94: -6848 | D94: 0 | E94: 0 | F94: -3336 | G94: 0 | H94: 0 | I94: 0 | J94: 0 | K94: 0 | L94: -2825 | M94: 0 | N94: 0 | O94: 0 | P94: 0 | Q94: 0 | AE94: -10184 | AF94: 0 | AG94: -2825
B95: CFFO | C95: =SUM(C76:C94) -> -19403 | D95: =SUM(D76:D94) -> -6394 | E95: =SUM(E76:E94) -> 5985 | F95: =SUM(F76:F94) -> -6719 | G95: =SUM(G76:G94) -> 9483 | H95: =SUM(H76:H94) -> 16826 | I95: =SUM(I76:I94) -> 25191 | J95: =SUM(J76:J94) -> 21983 | ... Q95: =SUM(Q76:Q94) -> 148721 | AE95: =SUM(AE76:AE94) -> -26531 | AF95: =SUM(AF76:AF94) -> 73483 | AG95: =SUM(AG76:AG94) -> 251084 | AH95: =SUM(AH76:AH94) -> 0 | AI95: =SUM(AI76:AI94) -> 0 | AJ95: =SUM(AJ76:AJ94) -> 0 | AK95: =SUM(AK76:AK94) -> 0
B96: Purch of Investments | C96: -84881 | D96: -4265 | E96: -47670 | F96: -50884 | G96: -40687 | H96: -24689 | I96: -71039 | J96: -20824 | K96: -70700 | L96: -26839 | M96: -53056 | N96: -9969 | O96: 0 | P96: 0 | Q96: -713556 | AE96: -187700 | AF96: -157239 | AG96: -160564
B97: Maturities | C97: 82340 | D97: 18919 | E97: 33500 | F97: 59500 | G97: 39084 | H97: 33250 | I97: 45000 | J97: 52717 | K97: 97700 | L97: 28395 | M97: 63197 | N97: 19648 | O97: 31342 | P97: 29227 | Q97: 12188 | AE97: 194259 | AF97: 170051 | AG97: 208940
B98: Sales of Investments | C98: 22291 | D98: 0 | E98: 13555 | F98: 0 | G98: 0 | H98: 676 | I98: 898 | J98: 0 | K98: 0 | L98: 0 | M98: 725 | N98: 0 | O98: 0 | P98: 0 | Q98: 0 | AE98: 35846 | AF98: 1574 | AG98: 725
B99: Software Ex | C99: -1197 | D99: -1200 | E99: -923 | F99: -1213 | G99: -1875 | H99: -2187 | I99: -2643 | J99: -2567 | K99: -3377 | L99: -2814 | M99: -2539 | N99: -2365 | O99: -3711 | P99: -4250 | Q99: -4092 | AE99: -4533 | AF99: -9272 | AG99: -11095
B100: CapEx | C100: -100 | D100: -176 | E100: -1038 | F100: -1400 | G100: -635 | H100: -4677 | I100: -3277 | J100: -8631 | K100: -10581 | L100: -3212 | M100: -3342 | N100: -24520 | O100: -55327 | P100: -46065 | Q100: -65265 | AE100: -2714 | AF100: -17220 | AG100: -41655
B101: Acquisitions | C101: 0 | D101: -459 | E101: 0 | F101: 0 | G101: 0 | H101: 0 | I101: 0 | J101: 0 | K101: 0 | L101: 0 | M101: -15399 | N101: 0 | O101: -5100 | P101: 0 | Q101: -116673 | AE101: -459 | AF101: 0 | AG101: -15399
B102: CFFI | C102: =SUM(C96:C101) -> 18453 | D102: =SUM(D96:D101) -> 12819 | E102: =SUM(E96:E101) -> -2576 | F102: =SUM(F96:F101) -> 6003 | G102: =SUM(G96:G101) -> -4113 | H102: =SUM(H96:H101) -> 2373 | I102: =SUM(I96:I101) -> -31061 | J102: =SUM(J96:J101) -> 20695 | ... Q102: =SUM(Q96:Q101) -> -887398 | AE102: =SUM(AE96:AE101) -> 34699 | AF102: =SUM(AF96:AF101) -> -12106 | AG102: =SUM(AG96:AG101) -> -19048 | AH102: =SUM(AH96:AH101) -> 0 | AI102: =SUM(AI96:AI101) -> 0 | AJ102: =SUM(AJ96:AJ101) -> 0 | AK102: =SUM(AK96:AK101) -> 0
B103: Proceeds from issuance of notes | C103: 0 | D103: 0 | E103: 0 | F103: 0 | G103: 0 | H103: 0 | I103: 0 | J103: 0 | K103: 0 | L103: 0 | M103: 0 | N103: 0 | O103: 0 | P103: 970000 | Q103: 0 | AE103: 0 | AF103: 0 | AG103: 0
B104: Purch of capped calls | C104: 0 | D104: 0 | E104: 0 | F104: 0 | G104: 0 | H104: 0 | I104: 0 | J104: 0 | K104: 0 | L104: 0 | M104: 0 | N104: 0 | O104: 0 | P104: -47800 | Q104: 0 | AE104: 0 | AF104: 0 | AG104: 0
B105: Proceeds from vested stock options | C105: 891 | D105: 579 | E105: 687 | F105: 89 | G105: 245 | H105: 315 | I105: 1131 | J105: 631 | K105: 5070 | L105: 11402 | M105: 2033 | N105: 8146 | O105: 3928 | P105: 2569 | Q105: 3299 | AE105: 2246 | AF105: 2322 | AG105: 26651
B106: Pmnt for taxes on equity awards | C106: -407 | D106: -776 | E106: -1181 | F106: -1537 | G106: -3657 | H106: -3754 | I106: -2690 | J106: -3995 | K106: -7314 | L106: -14967 | M106: -10815 | N106: -19405 | O106: -25711 | P106: -36764 | Q106: -32480 | AE106: -3901 | AF106: -14096 | AG106: -52501
B107: Proceeds from employee stock purch plan | C107: 0 | D107: 553 | E107: 0 | F107: 625 | G107: 0 | H107: 898 | I107: 0 | J107: 1400 | K107: 0 | L107: 1622 | M107: 0 | N107: 2279 | O107: 0 | P107: 2970 | Q107: 0 | AE107: 1178 | AF107: 2298 | AG107: 3901
B108: Debt issuance costs | C108: 0 | D108: 0 | E108: 0 | F108: 0 | G108: 0 | H108: 0 | I108: 0 | J108: 0 | K108: 0 | L108: 0 | M108: 0 | N108: 0 | O108: -1235 | P108: -1806 | Q108: -349 | AE108: 0 | AF108: 0 | AG108: 0
B109: Repurchase of stock | C109: 0 | D109: 0 | E109: 0 | F109: 0 | G109: 0 | H109: 0 | I109: 0 | J109: -1999 | K109: -28064 | L109: -19932 | M109: -30038 | N109: -5005 | O109: 0 | P109: 0 | Q109: -9479 | AE109: 0 | AF109: -1999 | AG109: -83039
B110: Acquisition related earn-outs | C110: -23014 | D110: 0 | E110: 0 | F110: -9636 | G110: 0 | H110: 0 | I110: 0 | J110: 0 | K110: 0 | L110: -3190 | M110: 0 | N110: 0 | O110: 0 | P110: 0 | Q110: 0 | AE110: -32650 | AF110: 0 | AG110: -3190
B111: CFFF | C111: =SUM(C103:C110) -> -22530 | D111: =SUM(D103:D110) -> 356 | E111: =SUM(E103:E110) -> -494 | F111: =SUM(F103:F110) -> -10459 | G111: =SUM(G103:G110) -> -3412 | H111: =SUM(H103:H110) -> -2541 | I111: =SUM(I103:I110) -> -1559 | J111: =SUM(J103:J110) -> -3963 | ... Q111: =SUM(Q103:Q110) -> -39009 | AE111: =SUM(AE103:AE110) -> -33127 | AF111: =SUM(AF103:AF110) -> -11475 | AG111: =SUM(AG103:AG110) -> -108178 | AH111: =SUM(AH103:AH110) -> 0 | AI111: =SUM(AI103:AI110) -> 0 | AJ111: =SUM(AJ103:AJ110) -> 0 | AK111: =SUM(AK103:AK110) -> 0
B112: FX adj. | C112: -23 | D112: -29 | E112: 16 | F112: -17 | G112: 15 | H112: 14 | I112: 8 | J112: -48 | K112: 2 | M112: 190 | O112: 243 | Q112: -1486 | AE112: -53 | AF112: -11 | AG112: -270
B113: CF | C113: =C95+C102+C111+C112 -> -23503 | D113: =D95+D102+D111+D112 -> 6752 | E113: =E95+E102+E111+E112 -> 2931 | F113: =F95+F102+F111+F112 -> -11192 | G113: =G95+G102+G111+G112 -> 1973 | H113: =H95+H102+H111+H112 -> 16672 | I113: =I95+I102+I111+I112 -> -7421 | J113: =J95+J102+J111+J112 -> 38667 | ... Q113: =Q95+Q102+Q111+Q112 -> -779172 | AE113: =AE95+AE102+AE111+AE112 -> -25012 | AF113: =AF95+AF102+AF111+AF112 -> 49891 | AG113: =AG95+AG102+AG111+AG112 -> 123588 | AH113: =AH95+AH102+AH111+AH112 -> 0 | AI113: =AI95+AI102+AI111+AI112 -> 0 | AJ113: =AJ95+AJ102+AJ111+AJ112 -> 0 | AK113: =AK95+AK102+AK111+AK112 -> 0
B116: FCF | C116: =C95+C100+C99 -> -20700 | D116: =D95+D100+D99 -> -7770 | E116: =E95+E100+E99 -> 4024 | F116: =F95+F100+F99 -> -9332 | G116: =G95+G100+G99 -> 6973 | H116: =H95+H100+H99 -> 9962 | I116: =I95+I100+I99 -> 19271 | J116: =J95+J100+J99 -> 10785 | ... Q116: =Q95+Q100+Q99 -> 79364 | AF116: =AF95+AF100+AF99 -> 46991 | AG116: =AG95+AG100+AG99 -> 198334
B117: CapEx Margin | C117: =-(C100+C99)/C76 -> -0.079805562 | D117: =-(D100+D99)/D76 -> -0.069922252 | E117: =-(E100+E99)/E76 -> -0.10408705 | F117: =-(F100+F99)/F76 -> -0.23957092 | G117: =-(G100+G99)/G76 -> -0.24932949 | H117: =-(H100+H99)/H76 -> -0.95906106 | I117: =-(I100+I99)/I76 -> -0.78234439 | J117: =-(J100+J99)/J76 -> 8.9943775 | ... Q117: =-(Q100+Q99)/Q76 -> 4.396919 | AF117: =-(AF100+AF99)/AF76 -> -1.1251168 | AG117: =-(AG100+AG99)/AG76 -> 0.41852457
B118: Share price | C118: 3.2 | D118: 6.67 | E118: 5.53 | F118: 11.27 | G118: 10.65 | H118: 7.44 | I118: 6.97 | J118: 13.43 | K118: 12.35 | L118: 16.88 | M118: 20.64 | N118: 39.86 | O118: 49.47 | P118: 55.52 | Q118: 19.38 | R118: .Feb-07
B119: Trl FCF per Share | F119: =SUM(C116:F116)/F18 -> -0.16385929 | G119: =SUM(D116:G116)/G18 -> -0.029472778 | H119: =SUM(E116:H116)/H18 -> 0.055785637 | I119: =SUM(F116:I116)/I18 -> 0.12788941 | J119: =SUM(G116:J116)/J18 -> 0.2220905 | K119: =SUM(H116:K116)/K18 -> 0.24313653 | L119: =SUM(I116:L116)/L18 -> 0.41703857 | M119: =SUM(J116:M116)/M18 -> 0.69070711 | ... Q119: =SUM(N116:Q116)/Q18 -> 0.52795716
B120: FCF Yield | I120: =(SUM(F116:I116)/I18)/I118 -> 0.018348552 | J120: =(SUM(G116:J116)/J18)/J118 -> 0.016536895 | K120: =(SUM(H116:K116)/K18)/K118 -> 0.019687168 | L120: =(SUM(I116:L116)/L18)/L118 -> 0.024706077 | M120: =(SUM(J116:M116)/M18)/M118 -> 0.033464492 | N120: =(SUM(K116:N116)/N18)/N118 -> 0.022717538 | O120: =(SUM(L116:O116)/O18)/O118 -> 0.021536154 | P120: =(SUM(M116:P116)/P18)/P118 -> 0.00959332 | Q120: =(SUM(N116:Q116)/Q18)/Q118 -> 0.027242372
...

Sheet Forecast
C1: 15 | D1: 16 | E1: 17 | F1: 18 | G1: 19 | H1: 20 | I1: 21 | J1: 22 | K1: 23 | L1: 24 | M1: 25 | N1: 26 | O1: 27 | P1: 28 | Q1: 29 | R1: 30 | S1: 31 | T1: 32 | U1: 33 | V1: 34 | W1: 35 | X1: 36 | Y1: 37 | Z1: 38
C2: Q325 | D2: Q425 | E2: Q126 | F2: Q226 | G2: Q326 | H2: Q426 | I2: Q127 | J2: Q227 | K2: Q327 | L2: Q427 | M2: Q128 | N2: Q228 | O2: Q328 | P2: Q428 | Q2: Q129 | R2: Q229 | S2: Q329 | T2: Q429 | U2: Q130 | V2: Q230 | W2: Q330 | X2: Q430 | AB2: 2022 | AC2: 2023 | AD2: 2024 | AE2: 2025 | AF2: 2026 | AG2: 2027 | AH2: 2028 | AI2: 2029 | AJ2: 2030 | AK2: 2031 | AL2: 2032 | AM2: 2033 | AN2: 2034 | AO2: 2035 | AP2: 2036 | AQ2: 2037 | AR2: 2038 | AS2: 2039 | AT2: 2040 | AU2: 2041 | AV2: 2042 | AW2: 2043 | AX2: 2044 | AY2: 2045 | AZ2: 2046 | BA2: 2047 | BB2: 2048 | BC2: 2049 | BD2: 2050
B3: Online | C3: 589095 | AB3: 502507 | AC3: 842381 | AD3: 1437937
B4: Wholesale | C4: 9881 | AB4: 24409 | AC4: 29619 | AD4: 38577
A5: Revenue trend estimate | B5: Revenue | C5: =SUM(C3:C4) -> 598976 | D5: =35000*D1 + 26510 -> 586510 | E5: =35000*E1 + 26510 -> 621510 | F5: =35000*F1 + 26510 -> 656510 | G5: =35000*G1 + 26510 -> 691510 | H5: =35000*H1 + 26510 -> 726510 | I5: =35000*I1 + 26510 -> 761510 | J5: =35000*J1 + 26510 -> 796510 | K5: =35000*K1 + 26510 -> 831510 | ... X5: =35000*X1 + 26510 -> 1286510 | AB5: 526916 | AC5: 872000 | AD5: 1476514 | AE5: =Model!O5+Model!P5+Model!Q5+Forecast!D5 -> 2316329 | AF5: =SUM(E5:H5) -> 2696040 | AG5: =SUM(I5:L5) -> 3256040 | AH5: =SUM(M5:P5) -> 3816040 | AI5: =SUM(Q5:T5) -> 4376040 | AJ5: =SUM(U5:X5) -> 4936040 | AK5: =+AJ5*1.12 -> 5528364.8 | AL5: =+AK5*1.12 -> 6191768.6 | AM5: =+AL5*1.12 -> 6934780.8 | AN5: =+AM5*1.12 -> 7766954.5 | AO5: =+AN5*1.12 -> 8698989 | AP5: =+AO5*1.12 -> 9742867.7 | AQ5: =+AP5*1.12 -> 10912012 | AR5: =+AQ5*1.12 -> 12221453 | ... AT5: =+AS5*1.12 -> 15330591 | AU5: =AT5*1.1 -> 16863650 | AV5: =AU5*1.1 -> 18550015 | AW5: =AV5*1.1 -> 20405017 | AX5: =AW5*1.1 -> 22445518 | AY5: =AX5*1.1 -> 24690070 | AZ5: =+AY5*1.07 -> 26418375 | BA5: =+AZ5*1.07 -> 28267661 | BB5: =+BA5*1.07 -> 30246398 | BC5: =+BB5*1.07 -> 32363645 | BD5: =+BC5*1.07 -> 34629101
B6: COGS | C6: 156918 | D6: =D5-D7 -> 132844.51 | E6: =E5-E7 -> 141766.43 | F6: =F5-F7 -> 150800.35 | G6: =G5-G7 -> 159946.26 | H6: =H5-H7 -> 169204.18 | I6: =I5-I7 -> 178574.09 | J6: =J5-J7 -> 188056.01 | K6: =K5-K7 -> 197649.93 | ... X6: =X5-X7 -> 332562.83 | AB6: 118194 | AC6: 157051 | AD6: 303379 | AE6: =Model!O6+Model!P6+Model!Q6+Forecast!D6 -> 573720.51 | AF6: =SUM(E6:H6) -> 621717.22 | AG6: =SUM(I6:L6) -> 771635.88 | AH6: =SUM(M6:P6) -> 928722.53 | AI6: =SUM(Q6:T6) -> 1092977.2 | AJ6: =SUM(U6:X6) -> 1264399.8
B7: Gross Profit | C7: =C5-C6 -> 442058 | D7: =+D5*D30 -> 453665.49 | E7: =+E5*E30 -> 479743.57 | F7: =+F5*F30 -> 505709.65 | G7: =+G5*G30 -> 531563.74 | H7: =+H5*H30 -> 557305.82 | I7: =+I5*I30 -> 582935.91 | J7: =+J5*J30 -> 608453.99 | K7: =+K5*K30 -> 633860.07 | ... X7: =+X5*X30 -> 953947.17 | AB7: 408722 | AC7: 714949 | AD7: 1173135 | AE7: =Model!O7+Model!P7+Model!Q7+Forecast!D7 -> 1742608.5 | AF7: =SUM(E7:H7) -> 2074322.8 | AG7: =SUM(I7:L7) -> 2484404.1 | AH7: =SUM(M7:P7) -> 2887317.5 | AI7: =SUM(Q7:T7) -> 3283062.8 | AJ7: =SUM(U7:X7) -> 3671640.2
B8: Marketing | C8: 232150 | D8: =D$7*D37 -> 233546.99 | E8: =E$7*E37 -> 241598.86 | F8: =F$7*F37 -> 249011.43 | G8: =G$7*G37 -> 255788.47 | H8: =H$7*H37 -> 261933.74 | I8: =I$7*I37 -> 267450.99 | J8: =J$7*J37 -> 272344.01 | K8: =K$7*K37 -> 276616.54 | ... X8: =X$7*X37 -> 277407.84 | AB8: 272587 | AC8: 446435 | AD8: 678844 | AE8: =Model!O8+Model!P8+Model!Q8+Forecast!D8 -> 914793.99 | AF8: =SUM(E8:H8) -> 1008332.5 | AG8: =SUM(I8:L8) -> 1096683.9 | AH8: =SUM(M8:P8) -> 1145444.8 | AI8: =SUM(Q8:T8) -> 1155578.8 | AJ8: =SUM(U8:X8) -> 1128049
B9: Operations | C9: 76848 | D9: =D$7*D38 -> 66643.46 | E9: =E$7*E38 -> 69035.1 | F9: =F$7*F38 -> 71254.49 | G9: =G$7*G38 -> 73302.639 | H9: =H$7*H38 -> 75180.555 | I9: =I$7*I38 -> 76889.246 | J9: =J$7*J38 -> 78429.719 | K9: =K$7*K38 -> 79802.983 | ... X9: =X$7*X38 -> 82898.009 | AB9: 77403 | AC9: 119857 | AD9: 185802 | AE9: =Model!O9+Model!P9+Model!Q9+Forecast!D9 -> 273014.46 | AF9: =SUM(E9:H9) -> 288772.78 | AG9: =SUM(I9:L9) -> 316131.99 | AH9: =SUM(M9:P9) -> 332822.06 | AI9: =SUM(Q9:T9) -> 339101.04 | AJ9: =SUM(U9:X9) -> 335226.98
B10: R&D | C10: 40577 | D10: =D$7*D39 -> 41869.297 | E10: =E$7*E39 -> 44515.944 | F10: =F$7*F39 -> 47178.221 | G10: =G$7*G39 -> 49855.96 | H10: =H$7*H39 -> 52548.991 | I10: =I$7*I39 -> 55257.149 | J10: =J$7*J39 -> 57980.264 | K10: =K$7*K39 -> 60718.168 | ... X10: =X$7*X39 -> 97580.326 | AB10: 29237 | AC10: 48227 | AD10: 78819 | AE10: =Model!O10+Model!P10+Model!Q10+Forecast!D10 -> 150208.3 | AF10: =SUM(E10:H10) -> 194099.12 | AG10: =SUM(I10:L10) -> 237426.27 | AH10: =SUM(M10:P10) -> 281694.58 | AI10: =SUM(Q10:T10) -> 326861.03 | AJ10: =SUM(U10:X10) -> 372882.62
B11: G&A | C11: 80676 | D11: =D$7*D40 -> 86876.94 | E11: =E$7*E40 -> 89951.919 | F11: =F$7*F40 -> 92797.721 | G11: =G$7*G40 -> 95415.691 | H11: =H$7*H40 -> 97807.172 | I11: =I$7*I40 -> 99973.508 | J11: =J$7*J40 -> 101916.04 | K11: =K$7*K40 -> 103636.12 | ... X11: =X$7*X40 -> 106365.11 | AB11: 98192 | AC11: 129883 | AD11: 167767 | AE11: =Model!O11+Model!P11+Model!Q11+Forecast!D11 -> 283435.94 | AF11: =SUM(E11:H11) -> 375972.5 | AG11: =SUM(I11:L11) -> 410660.76 | AH11: =SUM(M11:P11) -> 431154.8 | AI11: =SUM(Q11:T11) -> 437798.68 | AJ11: =SUM(U11:X11) -> 430936.48
B12: OpEx | C12: =SUM(C8:C11) -> 430251 | D12: =SUM(D8:D11) -> 428936.69 | E12: =SUM(E8:E11) -> 445101.82 | F12: =SUM(F8:F11) -> 460241.87 | G12: =SUM(G8:G11) -> 474362.76 | H12: =SUM(H8:H11) -> 487470.45 | I12: =SUM(I8:I11) -> 499570.9 | J12: =SUM(J8:J11) -> 510670.03 | ... X12: =SUM(X8:X11) -> 564251.28 | AB12: 477419 | AC12: 744402 | AD12: 1111232 | AE12: =Model!O12+Model!P12+Model!Q12+Forecast!D12 -> 1621452.7 | AF12: =SUM(E12:H12) -> 1867176.9 | AG12: =SUM(I12:L12) -> 2060902.9 | AH12: =SUM(M12:P12) -> 2191116.3 | AI12: =SUM(Q12:T12) -> 2259339.5 | AJ12: =SUM(U12:X12) -> 2267095.1
B13: OpInc | C13: =+C7-C12 -> 11807 | D13: =D7-D12 -> 24728.796 | E13: =E7-E12 -> 34641.745 | F13: =F7-F12 -> 45467.787 | G13: =G7-G12 -> 57200.977 | H13: =H7-H12 -> 69835.367 | I13: =I7-I12 -> 83365.009 | J13: =J7-J12 -> 97783.958 | K13: =K7-K12 -> 113086.26 | ... X13: =X7-X12 -> 389695.89 | AB13: -68697 | AC13: -29453 | AD13: 61903 | AE13: =Model!O13+Model!P13+Model!Q13+Forecast!D13 -> 121155.8 | AF13: =SUM(E13:H13) -> 207145.88 | AG13: =SUM(I13:L13) -> 423501.21 | AH13: =SUM(M13:P13) -> 696201.18 | AI13: =SUM(Q13:T13) -> 1023723.3 | AJ13: =SUM(U13:X13) -> 1404545
B14: Other income | C14: =-7626+8042 -> 416 | D14: =AVERAGE(Model!$F$44:$Q$44)*0.03755/4-1000000*0.0064/4 -> 1586.1754 | E14: =AVERAGE(Model!$F$44:$Q$44)*0.03755/4-1000000*0.0064/4 -> 1586.1754 | F14: =AVERAGE(Model!$F$44:$Q$44)*0.03755/4-1000000*0.0064/4 -> 1586.1754 | G14: =AVERAGE(Model!$F$44:$Q$44)*0.03755/4-1000000*0.0064/4 -> 1586.1754 | H14: =AVERAGE(Model!$F$44:$Q$44)*0.03755/4-1000000*0.0064/4 -> 1586.1754 | I14: =AVERAGE(Model!$F$44:$Q$44)*0.03755/4-1000000*0.0064/4 -> 1586.1754 | J14: =AVERAGE(Model!$F$44:$Q$44)*0.03755/4-1000000*0.0064/4 -> 1586.1754 | K14: =AVERAGE(Model!$F$44:$Q$44)*0.03755/4-1000000*0.0064/4 -> 1586.1754 | ... X14: =AVERAGE(Model!$F$44:$Q$44)*0.03755/4-1000000*0.0064/4 -> 1586.1754 | AB14: 2988 | AC14: 7882 | AD14: 9808 | AE14: =Model!O14+Model!P14+Model!Q14+Forecast!D14 -> 10730.175 | AF14: =SUM(E14:H14) -> 6344.7016 | AG14: =SUM(I14:L14) -> 6344.7016 | AH14: =SUM(M14:P14) -> 6344.7016 | AI14: =SUM(Q14:T14) -> 6344.7016 | AJ14: =SUM(U14:X14) -> 6344.7016
B15: Pretax Inc | C15: =C13+C14 -> 12223 | D15: =D13+D14 -> 26314.972 | E15: =E13+E14 -> 36227.92 | F15: =F13+F14 -> 47053.963 | G15: =G13+G14 -> 58787.152 | H15: =H13+H14 -> 71421.542 | I15: =I13+I14 -> 84951.185 | J15: =J13+J14 -> 99370.133 | ... X15: =X13+X14 -> 391282.06 | AB15: -65709 | AC15: -21571 | AD15: 71711 | AE15: =Model!O15+Model!P15+Model!Q15+Forecast!D15 -> 131885.97 | AF15: =SUM(E15:H15) -> 213490.58 | AG15: =SUM(I15:L15) -> 429845.91 | AH15: =SUM(M15:P15) -> 702545.88 | AI15: =SUM(Q15:T15) -> 1030068 | AJ15: =SUM(U15:X15) -> 1410889.7
B16: Taxes | C16: 3551 | D16: =-D15*0.2 -> -5262.9944 | E16: =-E15*0.2 -> -7245.584 | F16: =-F15*0.2 -> -9410.7925 | G16: =-G15*0.2 -> -11757.43 | H16: =-H15*0.2 -> -14284.308 | I16: =-I15*0.2 -> -16990.237 | J16: =-J15*0.2 -> -19874.027 | K16: =-K15*0.2 -> -22934.488 | ... X16: =-X15*0.2 -> -78256.412 | AB16: 31 | AC16: -1975 | AD16: 54327 | AE16: =Model!O16+Model!P16+Model!Q16+Forecast!D16 -> -3069.9944 | AF16: =SUM(E16:H16) -> -42698.115 | AG16: =SUM(I16:L16) -> -85969.183 | AH16: =SUM(M16:P16) -> -140509.18 | AI16: =SUM(Q16:T16) -> -206013.6 | AJ16: =SUM(U16:X16) -> -282177.95
B17: Net Income | C17: =C15+C16 -> 15774 | D17: =D15+D16 -> 21051.977 | E17: =E15+E16 -> 28982.336 | F17: =F15+F16 -> 37643.17 | G17: =G15+G16 -> 47029.722 | H17: =H15+H16 -> 57137.234 | I17: =I15+I16 -> 67960.948 | J17: =J15+J16 -> 79496.106 | ... X17: =X15+X16 -> 313025.65 | AB17: -65678 | AC17: -23546 | AD17: 126038 | AE17: =Model!O17+Model!P17+Model!Q17+Forecast!D17 -> 128815.98 | AF17: =SUM(E17:H17) -> 170792.46 | AG17: =SUM(I17:L17) -> 343876.73 | AH17: =SUM(M17:P17) -> 562036.7 | AI17: =SUM(Q17:T17) -> 824054.39 | AJ17: =SUM(U17:X17) -> 1128711.8 | AK17: =+AK5*0.24 -> 1326807.6 | AL17: =+AL5*0.24 -> 1486024.5 | AM17: =+AM5*0.24 -> 1664347.4 | AN17: =+AN5*0.24 -> 1864069.1 | AO17: =+AO5*0.24 -> 2087757.4 | AP17: =+AP5*0.25 -> 2435716.9 | AQ17: =+AQ5*0.25 -> 2728003 | AR17: =+AR5*0.25 -> 3055363.3 | AS17: =+AS5*0.25 -> 3422006.9 | AT17: =+AT5*0.25 -> 3832647.7 | AU17: =+AU5*0.275 -> 4637503.8 | AV17: =+AV5*0.275 -> 5101254.2 | AW17: =+AW5*0.275 -> 5611379.6 | AX17: =+AX5*0.275 -> 6172517.5 | AY17: =+AY5*0.275 -> 6789769.3 | AZ17: =+AZ5*0.3 -> 7925512.5 | BA17: =+BA5*0.3 -> 8480298.4 | BB17: =+BB5*0.3 -> 9073919.3 | BC17: =+BC5*0.3 -> 9709093.6 | BD17: =+BD5*0.3 -> 10388730 | BE17: =+BD17*0.98 -> 10180956 | BF17: =+BE17*0.98 -> 9977336.4 | BG17: =+BF17*0.98 -> 9777789.7 | BH17: =+BG17*0.98 -> 9582233.9 | BI17: =+BH17*0.98 -> 9390589.2 | BJ17: =+BI17*0.98 -> 9202777.5 | BK17: =+BJ17*0.98 -> 9018721.9 | BL17: =+BK17*0.98 -> 8838347.5 | ... BCI17: =+BCH17*0.98 -> 7.6247419e-06
B18: S/O | C18: 226313.82 | AB18: 206140.28 | AC18: 211584.92 | AD18: 219027.48 | AE18: =+C18 -> 226313.82 | AF18: =(1+$AF$20)*AE18 -> 233469.43 | AG18: =(1+$AF$20)*AF18 -> 240851.29 | AH18: =(1+$AF$20)*AG18 -> 248466.56 | AI18: =(1+$AF$20)*AH18 -> 256322.6 | AJ18: =(1+$AF$20)*AI18 -> 264427.04
B19: EPS | C19: =C17/C18 -> 0.069699678 | AB19: -0.31860828 | AC19: -0.11128393 | AD19: 0.57544376 | AE19: =AE17/AE18 -> 0.56919184 | AF19: =AF17/AF18 -> 0.731541 | AG19: =AG17/AG18 -> 1.4277554 | AH19: =AH17/AH18 -> 2.2620215 | AI19: =AI17/AI18 -> 3.2149112 | AJ19: =AJ17/AJ18 -> 4.2685189
AB20: S/O Y/Y | AC20: =AC18/AB18-1 -> 0.026412266 | AD20: =AD18/AC18-1 -> 0.035175334 | AE20: =AE18/AD18-1 -> 0.033266738 | AF20: =AVERAGE(AC20:AE20) -> 0.031618113 | AP20: Maturity | AQ20: -0.02
B21: Subscribers | C21: 2471 | D21: =(138.76*D1 + 486.41)*0.9945 -> 2691.6839 | E21: =(138.76*E1 + 486.41)*0.9945 -> 2829.6807 | F21: =(138.76*F1 + 486.41)*0.9945 -> 2967.6775 | G21: =(138.76*G1 + 486.41)*0.9945 -> 3105.6743 | H21: =(138.76*H1 + 486.41)*0.9945 -> 3243.6711 | I21: =(138.76*I1 + 486.41)*0.9945 -> 3381.668 | J21: =(138.76*J1 + 486.41)*0.9945 -> 3519.6648 | K21: =(138.76*K1 + 486.41)*0.9945 -> 3657.6616 | ... X21: =(138.76*X1 + 486.41)*0.9945 -> 5451.6203 | AP21: Discount | AQ21: 0.2
B22: QT-ly Revenue per Avg Subscriber | AP22: NPV | AQ22: =+NPV(AQ21,C17,AF17:BCI17)+Model!Q43 -> 5912315
B23: Net Orders | AP23: Share | AQ23: =AQ22/AE18 -> 26.124411
B24: AOV (Avg Order Value) | AP24: Current | AQ24: 19.38
AP25: Return | AQ25: =AQ23/AQ24-1 -> 0.34800881
B26: Subscriber seq
B27: Subscriber Y/Y
B28: Rev per Avg Subscriber Y/Y
B30: Gross Margin | C30: =C7/C5 -> 0.73802289 | D30: =-0.0016*D1 + 0.7991 -> 0.7735 | E30: =-0.0016*E1 + 0.7991 -> 0.7719 | F30: =-0.0016*F1 + 0.7991 -> 0.7703 | G30: =-0.0016*G1 + 0.7991 -> 0.7687 | H30: =-0.0016*H1 + 0.7991 -> 0.7671 | I30: =-0.0016*I1 + 0.7991 -> 0.7655 | J30: =-0.0016*J1 + 0.7991 -> 0.7639 | K30: =-0.0016*K1 + 0.7991 -> 0.7623 | ... X30: =-0.0016*X1 + 0.7991 -> 0.7415 | AB30: =AB7/AB5 -> 0.77568721 | AC30: =AC7/AC5 -> 0.81989564 | AD30: =AD7/AD5 -> 0.79453022 | AE30: =AE7/AE5 -> 0.75231476 | AF30: =AF7/AF5 -> 0.76939614 | AG30: =AG7/AG5 -> 0.76301401 | AH30: =AH7/AH5 -> 0.75662663 | AI30: =AI7/AI5 -> 0.75023602 | AJ30: =AJ7/AJ5 -> 0.74384327
B31: Op Margin | C31: =C13/C5 -> 0.019711975 | D31: =D13/D5 -> 0.042162617 | E31: =E13/E5 -> 0.055738033 | F31: =F13/F5 -> 0.069256808 | G31: =G13/G5 -> 0.082718944 | H31: =H13/H5 -> 0.09612444 | I31: =I13/I5 -> 0.1094733 | J31: =J13/J5 -> 0.12276551 | ... X31: =X13/X5 -> 0.30290933 | AB31: =AB13/AB5 -> -0.13037562 | AC31: =AC13/AC5 -> -0.033776376 | AD31: =AD13/AD5 -> 0.041925102 | AE31: =AE13/AE5 -> 0.05230509 | AF31: =AF13/AF5 -> 0.076833384 | AG31: =AG13/AG5 -> 0.13006634 | AH31: =AH13/AH5 -> 0.18244074 | AI31: =AI13/AI5 -> 0.23393828 | AJ31: =AJ13/AJ5 -> 0.28454896
B32: Net Margin | C32: =C17/C5 -> 0.026334945 | D32: =D17/D5 -> 0.035893638 | E32: =E17/E5 -> 0.046632131 | F32: =F17/F5 -> 0.057338304 | G32: =G17/G5 -> 0.068010183 | H32: =H17/H5 -> 0.078646177 | I32: =I17/I5 -> 0.089244984 | J32: =J17/J5 -> 0.099805535 | ... X32: =X17/X5 -> 0.24331381 | AB32: =AB17/AB5 -> -0.12464605 | AC32: =AC17/AC5 -> -0.027002294 | AD32: =AD17/AD5 -> 0.085361873 | AE32: =AE17/AE5 -> 0.055612125 | AF32: =AF17/AF5 -> 0.06334938 | AG32: =AG17/AG5 -> 0.10561195 | AH32: =AH17/AH5 -> 0.14728271 | AI32: =AI17/AI5 -> 0.18831052 | AJ32: =AJ17/AJ5 -> 0.22866747
B35: Revenue Y/Y | AC35: =AC5/AB5-1 -> 0.65491274 | AD35: =AD5/AC5-1 -> 0.69325 | AE35: =AE5/AD5-1 -> 0.56878228 | AF35: =AF5/AE5-1 -> 0.16392792 | AG35: =AG5/AF5-1 -> 0.20771205 | AH35: =AH5/AG5-1 -> 0.17198806 | AI35: =AI5/AH5-1 -> 0.14674899 | AJ35: =AJ5/AI5-1 -> 0.12796958
B37: Marketing Margin | C37: =C8/C$7 -> 0.52515733 | D37: =-0.0112*D1+0.694 -> 0.5148 | E37: =-0.0112*E1+0.694 -> 0.5036 | F37: =-0.0112*F1+0.694 -> 0.4924 | G37: =-0.0112*G1+0.694 -> 0.4812 | H37: =-0.0112*H1+0.694 -> 0.47 | I37: =-0.0112*I1+0.694 -> 0.4588 | J37: =-0.0112*J1+0.694 -> 0.4476 | K37: =-0.0112*K1+0.694 -> 0.4364 | ... X37: =-0.0112*X1+0.694 -> 0.2908 | AB37: =AB8/AB$7 -> 0.6669252 | AC37: =AC8/AC$7 -> 0.62442916 | AD37: =AD8/AD$7 -> 0.57865804 | AE37: =AE8/AE$7 -> 0.5249567 | AF37: =AF8/AF$7 -> 0.48610202 | AG37: =AG8/AG$7 -> 0.44142733 | AH37: =AH8/AH$7 -> 0.39671593 | AI37: =AI8/AI$7 -> 0.35198193 | AJ37: =AJ8/AJ$7 -> 0.307233
B38: Operating Margin | C38: =C9/C$7 -> 0.17384144 | D38: =-0.003*D1+0.1949 -> 0.1469 | E38: =-0.003*E1+0.1949 -> 0.1439 | F38: =-0.003*F1+0.1949 -> 0.1409 | G38: =-0.003*G1+0.1949 -> 0.1379 | H38: =-0.003*H1+0.1949 -> 0.1349 | I38: =-0.003*I1+0.1949 -> 0.1319 | J38: =-0.003*J1+0.1949 -> 0.1289 | K38: =-0.003*K1+0.1949 -> 0.1259 | ... X38: =-0.003*X1+0.1949 -> 0.0869 | AB38: =AB9/AB$7 -> 0.18937811 | AC38: =AC9/AC$7 -> 0.16764413 | AD38: =AD9/AD$7 -> 0.15838075 | AE38: =AE9/AE$7 -> 0.15666999 | AF38: =AF9/AF$7 -> 0.13921304 | AG38: =AG9/AG$7 -> 0.12724661 | AH38: =AH9/AH$7 -> 0.11527034 | AI38: =AI9/AI$7 -> 0.10328802 | AJ38: =AJ9/AJ$7 -> 0.091301698
B39: R&D Margin | C39: =C10/C$7 -> 0.091791122 | D39: =+C39+0.0005 -> 0.092291122 | E39: =+D39+0.0005 -> 0.092791122 | F39: =+E39+0.0005 -> 0.093291122 | G39: =+F39+0.0005 -> 0.093791122 | H39: =+G39+0.0005 -> 0.094291122 | I39: =+H39+0.0005 -> 0.094791122 | J39: =+I39+0.0005 -> 0.095291122 | K39: =+J39+0.0005 -> 0.095791122 | ... X39: =+W39+0.0005 -> 0.10229112 | AB39: =AB10/AB$7 -> 0.071532729 | AC39: =AC10/AC$7 -> 0.067455161 | AD39: =AD10/AD$7 -> 0.067186641 | AE39: =AE10/AE$7 -> 0.086197386 | AF39: =AF10/AF$7 -> 0.093572282 | AG39: =AG10/AG$7 -> 0.095566688 | AH39: =AH10/AH$7 -> 0.097562733 | AI39: =AI10/AI$7 -> 0.099559786 | AJ39: =AJ10/AJ$7 -> 0.10155751
B40: G&A Margin | C40: =C11/C$7 -> 0.18250094 | D40: =-0.004*D1+0.2555 -> 0.1915 | E40: =-0.004*E1+0.2555 -> 0.1875 | F40: =-0.004*F1+0.2555 -> 0.1835 | G40: =-0.004*G1+0.2555 -> 0.1795 | H40: =-0.004*H1+0.2555 -> 0.1755 | I40: =-0.004*I1+0.2555 -> 0.1715 | J40: =-0.004*J1+0.2555 -> 0.1675 | K40: =-0.004*K1+0.2555 -> 0.1635 | ... X40: =-0.004*X1+0.2555 -> 0.1115 | AB40: =AB11/AB$7 -> 0.24024153 | AC40: =AC11/AC$7 -> 0.1816675 | AD40: =AD11/AD$7 -> 0.14300741 | AE40: =AE11/AE$7 -> 0.16265038 | AF40: =AF11/AF$7 -> 0.18125072 | AG40: =AG11/AG$7 -> 0.16529548 | AH40: =AH11/AH$7 -> 0.14932712 | AI40: =AI11/AI$7 -> 0.13335069 | AJ40: =AJ11/AJ$7 -> 0.11736893
