Workbook

Sheet Main
A1: Model
I6: Price | J6: 183.95 | K6: 46080 | N6: Cons. | O6: 46050
I7: S/O | J7: =+Model!U19 -> 24327 | K7: Q426 | N7: Beat | O7: =Model!T8/O6-1 -> 0.01504886
I8: MC | J8: =+J7*J6 -> 4474951.6
I9: Cash | J9: =+Model!U39 -> 60608 | K9: Q426 | N9: EPS Cons. | O9: 1.01
I10: Debt | J10: =+Model!U52+Model!U53 -> 8467 | K10: Q426 | N10: Beat | O10: =Model!T20/O9-1 -> 0.069306931
I12: EV | J12: =J8-J9+J10 -> 4422810.6 | N12: Guidance cons. | O12: 53430
N13: Beat | O13: =Model!U8/O12-1 -> 0.066928692

Sheet Model
A1: Main | S1: 45774
C2: Q122 | D2: Q222 | E2: Q322 | F2: Q422 | G2: Q123 | H2: Q223 | I2: Q323 | J2: Q423 | K2: Q124 | L2: Q224 | M2: Q324 | N2: Q424 | O2: Q125 | P2: Q225 | Q2: Q325 | R2: Q425 | S2: Q126 | T2: Q226 | U2: Q326 | V2: Q426 | W2: Q127 | X2: Q227 | AA2: 2022 | AB2: 2023 | AC2: 2024 | AD2: 2025 | AE2: 2026 | AF2: 2027
B3: Data Center | C3: 2048 | D3: 2366 | E3: 2936 | F3: 3263 | G3: 3750 | H3: 3806 | I3: 3833 | J3: 3616 | K3: 4284 | L3: 10323 | M3: 14514 | N3: 18404 | O3: 22563 | P3: 26272 | Q3: 30771 | R3: 35580 | S3: 39112 | T3: 41096 | U3: 51215 | V3: 62314 | AA3: =C3+D3+E3+F3 -> 10613 | AB3: =+G3+H3+I3+J3 -> 15005 | AC3: =K3+L3+M3+N3 -> 47525 | AD3: =O3+P3+Q3+R3 -> 115186 | AE3: =SUM(S3:V3) -> 193737
B4: Gaming | C4: 2760 | D4: 3061 | E4: 3221 | F4: 3420 | G4: 3620 | H4: 2042 | I4: 1574 | J4: 1831 | K4: 2240 | L4: 2486 | M4: 2856 | N4: 2865 | O4: 2647 | P4: 2880 | Q4: 3279 | R4: 2544 | S4: 3763 | T4: 4287 | U4: 4265 | V4: 3727 | AA4: =C4+D4+E4+F4 -> 12462 | AB4: =+G4+H4+I4+J4 -> 9067 | AC4: =K4+L4+M4+N4 -> 10447 | AD4: =O4+P4+Q4+R4 -> 11350 | AE4: =SUM(S4:V4) -> 16042
B5: Visualization | C5: 372 | D5: 519 | E5: 577 | F5: 643 | G5: 622 | H5: 496 | I5: 200 | J5: 226 | K5: 295 | L5: 379 | M5: 416 | N5: 463 | O5: 427 | P5: 454 | Q5: 486 | R5: 511 | S5: 509 | T5: 601 | U5: 760 | V5: 1321 | AA5: =C5+D5+E5+F5 -> 2111 | AB5: =+G5+H5+I5+J5 -> 1544 | AC5: =K5+L5+M5+N5 -> 1553 | AD5: =O5+P5+Q5+R5 -> 1878 | AE5: =SUM(S5:V5) -> 3191
B6: Auto | C6: 154 | D6: 152 | E6: 135 | F6: 125 | G6: 138 | H6: 220 | I6: 251 | J6: 294 | K6: 296 | L6: 253 | M6: 261 | N6: 281 | O6: 329 | P6: 346 | Q6: 449 | R6: 570 | S6: 567 | T6: 586 | U6: 592 | V6: 604 | AA6: =C6+D6+E6+F6 -> 566 | AB6: =+G6+H6+I6+J6 -> 903 | AC6: =K6+L6+M6+N6 -> 1091 | AD6: =O6+P6+Q6+R6 -> 1694 | AE6: =SUM(S6:V6) -> 2349
B7: OEM & Other | C7: 327 | D7: 409 | E7: 234 | F7: 192 | G7: 158 | H7: 140 | I7: 73 | J7: 84 | K7: 77 | L7: 66 | M7: 73 | N7: 90 | O7: 78 | P7: 88 | Q7: 97 | R7: 126 | S7: 111 | T7: 173 | U7: 174 | V7: 161 | AA7: =C7+D7+E7+F7 -> 1162 | AB7: =+G7+H7+I7+J7 -> 455 | AC7: =K7+L7+M7+N7 -> 306 | AD7: =O7+P7+Q7+R7 -> 389 | AE7: =SUM(S7:V7) -> 619
B8: Revenue | C8: =SUM(C3:C7) -> 5661 | D8: =SUM(D3:D7) -> 6507 | E8: =SUM(E3:E7) -> 7103 | F8: =SUM(F3:F7) -> 7643 | G8: =SUM(G3:G7) -> 8288 | H8: =SUM(H3:H7) -> 6704 | I8: =SUM(I3:I7) -> 5931 | J8: =SUM(J3:J7) -> 6051 | ... X8: =SUM(X3:X7) -> 0 | AA8: =C8+D8+E8+F8 -> 26914 | AB8: =+G8+H8+I8+J8 -> 26974 | AC8: =K8+L8+M8+N8 -> 60922 | AD8: =O8+P8+Q8+R8 -> 130497 | AE8: =SUM(AE3:AE7) -> 215938 | AF8: 253590
B9: COGS | K9: 2544 | L9: 4045 | M9: 4720 | N9: 5312 | O9: 5638 | P9: 7466 | Q9: 8926 | R9: 10608 | S9: 17394 | T9: 12890 | U9: 15157 | V9: 17034 | AC9: =K9+L9+M9+N9 -> 16621 | AD9: =O9+P9+Q9+R9 -> 32638 | AE9: =SUM(S9:V9) -> 62475
B10: Gross Profit | C10: =C8-C9 -> 5661 | D10: =D8-D9 -> 6507 | E10: =E8-E9 -> 7103 | F10: =F8-F9 -> 7643 | G10: =G8-G9 -> 8288 | H10: =H8-H9 -> 6704 | I10: =I8-I9 -> 5931 | J10: =J8-J9 -> 6051 | ... X10: =X8-X9 -> 0 | AC10: =AC8-AC9 -> 44301 | AD10: =AD8-AD9 -> 97859 | AE10: =AE8-AE9 -> 153463 | AF10: =AF8-AF9 -> 253590
B11: R&D | K11: 1875 | L11: 2040 | M11: 2294 | N11: 2465 | O11: 2720 | P11: 3090 | Q11: 3390 | R11: 3714 | S11: 3989 | T11: 4291 | U11: 4705 | V11: 5512 | AC11: =K11+L11+M11+N11 -> 8674 | AD11: =O11+P11+Q11+R11 -> 12914 | AE11: =SUM(S11:V11) -> 18497
B12: SG&A | K12: 633 | L12: 622 | M12: 689 | N12: 711 | O12: 777 | P12: 842 | Q12: 897 | R12: 975 | S12: 1041 | T12: 1122 | U12: 1134 | V12: 1282 | AC12: =K12+L12+M12+N12 -> 2655 | AD12: =O12+P12+Q12+R12 -> 3491 | AE12: =SUM(S12:V12) -> 4579
B13: Operating expenses | C13: =+C12+C11 -> 0 | D13: =+D12+D11 -> 0 | E13: =+E12+E11 -> 0 | F13: =+F12+F11 -> 0 | G13: =+G12+G11 -> 0 | H13: =+H12+H11 -> 0 | I13: =+I12+I11 -> 0 | J13: =+J12+J11 -> 0 | ... X13: =+X12+X11 -> 0 | AC13: =+AC12+AC11 -> 11329 | AD13: =+AD12+AD11 -> 16405 | AE13: =+AE12+AE11 -> 23076 | AF13: =+AF12+AF11 -> 0
B14: Operating profit | C14: =C10-C13 -> 5661 | D14: =D10-D13 -> 6507 | E14: =E10-E13 -> 7103 | F14: =F10-F13 -> 7643 | G14: =G10-G13 -> 8288 | H14: =H10-H13 -> 6704 | I14: =I10-I13 -> 5931 | J14: =J10-J13 -> 6051 | ... S14: =S10-S13 -> 21638 | T14: 28440 | U14: =U10-U13 -> 36010 | V14: =V10-V13 -> 44299 | W14: =W10-W13 -> 0 | X14: =X10-X13 -> 0 | AC14: =AC10-AC13 -> 32972 | AD14: =AD10-AD13 -> 81454 | AE14: =AE10-AE13 -> 130387 | AF14: =AF10-AF13 -> 253590
B15: Interest income | K15: =150-66-15 -> 69 | L15: =187-65+59 -> 181 | M15: =234-63-66 -> 105 | N15: =294-63+260 -> 491 | O15: =359-64+75 -> 370 | P15: =444-61+189 -> 572 | Q15: =472-61+36 -> 447 | R15: =511-61+733 -> 1183 | S15: =515-63-180 -> 272 | T15: =592-62+2236 -> 2766 | U15: =624-61+1363 -> 1926 | V15: 6098 | AC15: =K15+L15+M15+N15 -> 846 | AD15: =O15+P15+Q15+R15 -> 2572 | AE15: =SUM(S15:V15) -> 11062
B16: Pretax income | C16: =C14+C15 -> 5661 | D16: =D14+D15 -> 6507 | E16: =E14+E15 -> 7103 | F16: =F14+F15 -> 7643 | G16: =G14+G15 -> 8288 | H16: =H14+H15 -> 6704 | I16: =I14+I15 -> 5931 | J16: =J14+J15 -> 6051 | ... X16: =X14+X15 -> 0 | AC16: =AC14+AC15 -> 33818 | AD16: =AD14+AD15 -> 84026 | AE16: =AE14+AE15 -> 141449 | AF16: =AF14+AF15 -> 253590
B17: Taxes | K17: 166 | L17: 793 | M17: 1279 | N17: 1821 | O17: 2398 | P17: 2615 | Q17: 3007 | R17: 3126 | S17: 3135 | T17: 4784 | U17: 6026 | V17: 7437 | AC17: =K17+L17+M17+N17 -> 4059 | AD17: =O17+P17+Q17+R17 -> 11146 | AE17: =SUM(S17:V17) -> 21382
B18: Net Income | C18: =C16-C17 -> 5661 | D18: =D16-D17 -> 6507 | E18: =E16-E17 -> 7103 | F18: =F16-F17 -> 7643 | G18: =G16-G17 -> 8288 | H18: =H16-H17 -> 6704 | I18: =I16-I17 -> 5931 | J18: =J16-J17 -> 6051 | ... X18: =X16-X17 -> 0 | AC18: =AC16-AC17 -> 29759 | AD18: =AD16-AD17 -> 72880 | AE18: =AE16-AE17 -> 120067 | AF18: =AF16-AF17 -> 253590
B19: S/O | K19: 24700 | L19: 24729 | M19: 24680 | N19: 24660 | O19: 24620 | P19: 24578 | Q19: 24533 | R19: 24489 | S19: 24441 | T19: 24366 | U19: 24327 | V19: 24304 | AC19: 24660 | AD19: 24489 | AE19: =V19 -> 24304 | AF19: =AF18/AF20 -> #DIV/0!
B20: EPS | C20: =C18/C19 -> #DIV/0! | D20: =D18/D19 -> #DIV/0! | E20: =E18/E19 -> #DIV/0! | F20: =F18/F19 -> #DIV/0! | G20: =G18/G19 -> #DIV/0! | H20: =H18/H19 -> #DIV/0! | I20: =I18/I19 -> #DIV/0! | J20: =J18/J19 -> #DIV/0! | ... S20: =S18/S19 -> 0.76817642 | T20: 1.08 | U20: =U18/U19 -> 1.3117113 | V20: =V18/V19 -> 1.7676103 | W20: =W18/W19 -> #DIV/0! | X20: =X18/X19 -> #DIV/0! | AC20: =AC18/AC19 -> 1.2067721 | AD20: =AD18/AD19 -> 2.9760301 | AE20: =AE18/AE19 -> 4.9402156
B23: Gross Margin | K23: =K10/K8 -> 0.64627364 | L23: =L10/L8 -> 0.70052565 | M23: =M10/M8 -> 0.73951435 | N23: =N10/N8 -> 0.75967063 | O23: =O10/O8 -> 0.7835202 | P23: =P10/P8 -> 0.75146471 | Q23: =Q10/Q8 -> 0.74556753 | R23: =R10/R8 -> 0.73028908 | ... X23: =X10/X8 -> #DIV/0! | AC23: =AC10/AC8 -> 0.72717573 | AD23: =AD10/AD8 -> 0.74989463 | AE23: =AE10/AE8 -> 0.71068084 | AF23: =AF10/AF8 -> 1
B24: Operating Margin | K24: =K14/K8 -> 0.29755284 | L24: =L14/L8 -> 0.50344266 | M24: =M14/M8 -> 0.57488962 | N24: =N14/N8 -> 0.61597973 | O24: =O14/O8 -> 0.64924743 | P24: =P14/P8 -> 0.62057257 | Q24: =Q14/Q8 -> 0.62336811 | R24: =R14/R8 -> 0.61107015 | ... X24: =X14/X8 -> #DIV/0! | AC24: =AC14/AC8 -> 0.54121664 | AD24: =AD14/AD8 -> 0.62418293 | AE24: =AE14/AE8 -> 0.60381684 | AF24: =AF14/AF8 -> 1
B25: Net Margin | K25: =K18/K8 -> 0.28406563 | L25: =L18/L8 -> 0.45813282 | M25: =M18/M8 -> 0.51009934 | N25: =N18/N8 -> 0.5558069 | O25: =O18/O8 -> 0.5713792 | P25: =P18/P8 -> 0.55256325 | Q25: =Q18/Q8 -> 0.55039621 | R25: =R18/R8 -> 0.56166891 | ... X25: =X18/X8 -> #DIV/0! | AC25: =AC18/AC8 -> 0.48847707 | AD25: =AD18/AD8 -> 0.55848027 | AE25: =AE18/AE8 -> 0.55602534 | AF25: =AF18/AF8 -> 1
B27: R&D Margin | K27: =K11/K10 -> 0.40339931 | L27: =L11/L10 -> 0.21559924 | M27: =M11/M10 -> 0.17119403 | N27: =N11/N10 -> 0.14680484 | O27: =O11/O10 -> 0.13329413 | P27: =P11/P10 -> 0.13688314 | Q27: =Q11/Q10 -> 0.12960697 | R27: =R11/R10 -> 0.12930404 | ... X27: =X11/X10 -> #DIV/0! | AC27: =AC11/AC10 -> 0.19579693 | AD27: =AD11/AD10 -> 0.13196538 | AE27: =AE11/AE10 -> 0.12053068 | AF27: =AF11/AF10 -> 0
B28: SG&A Margin | K28: =K12/K10 -> 0.13618761 | L28: =L12/L10 -> 0.065736631 | M28: =M12/M10 -> 0.05141791 | N28: =N12/N10 -> 0.042344113 | O28: =O12/O10 -> 0.038077036 | P28: =P12/P10 -> 0.037299548 | Q28: =Q12/Q10 -> 0.034294235 | R28: =R12/R10 -> 0.033944922 | ... X28: =X12/X10 -> #DIV/0! | AC28: =AC12/AC10 -> 0.059930927 | AD28: =AD12/AD10 -> 0.035673776 | AE28: =AE12/AE10 -> 0.029837811 | AF28: =AF12/AF10 -> 0
B29: Effective tax rate | K29: =K17/K16 -> 0.075147125 | L29: =L17/L16 -> 0.11359404 | M29: =M17/M16 -> 0.12155484 | N29: =N17/N16 -> 0.129094 | O29: =O17/O16 -> 0.13878118 | P29: =P17/P16 -> 0.13609868 | Q29: =Q17/Q16 -> 0.13474637 | R29: =R17/R16 -> 0.12396399 | ... X29: =X17/X16 -> #DIV/0! | AC29: =AC17/AC16 -> 0.12002484 | AD29: =AD17/AD16 -> 0.13264942 | AE29: =AE17/AE16 -> 0.15116402 | AF29: =AF17/AF16 -> 0
B30: Interest Margin | K30: =K15/K14 -> 0.032242991 | L30: =L15/L14 -> 0.026617647 | M30: =M15/M14 -> 0.010079677 | N30: =N15/N14 -> 0.036063166 | O30: =O15/O14 -> 0.021881838 | P30: =P15/P14 -> 0.030683403 | Q30: =Q15/Q14 -> 0.020439892 | R30: =R15/R14 -> 0.049221936 | ... X30: =X15/X14 -> #DIV/0! | AC30: =AC15/AC14 -> 0.025658134 | AD30: =AD15/AD14 -> 0.031576104 | AE30: =AE15/AE14 -> 0.084839746 | AF30: =AF15/AF14 -> 0
B32: Revenue Y/Y | G32: =G8/C8-1 -> 0.46405229 | H32: =H8/D8-1 -> 0.030275088 | I32: =I8/E8-1 -> -0.1650007 | J32: =J8/F8-1 -> -0.20829517 | K32: =K8/G8-1 -> -0.13223938 | L32: =L8/H8-1 -> 1.0147673 | M32: =M8/I8-1 -> 2.055134 | N32: =N8/J8-1 -> 2.6527847 | ... X32: =X8/T8-1 -> -1 | AB32: =AB8/AA8-1 -> 0.002229323 | AC32: =AC8/AB8-1 -> 1.2585453 | AD32: =AD8/AC8-1 -> 1.1420341 | AE32: =AE8/AD8-1 -> 0.65473536 | AF32: =AF8/AE8-1 -> 0.17436486
B33: Data Center Y/Y | G33: =G3/C3-1 -> 0.83105469 | H33: =H3/D3-1 -> 0.60862215 | I33: =I3/E3-1 -> 0.30551771 | J33: =J3/F3-1 -> 0.10818265 | K33: =K3/G3-1 -> 0.1424 | L33: =L3/H3-1 -> 1.7122964 | M33: =M3/I3-1 -> 2.7865901 | N33: =N3/J3-1 -> 4.0896018 | ... X33: =X3/T3-1 -> -1 | AB33: =AB3/AA3-1 -> 0.41383209 | AC33: =AC3/AB3-1 -> 2.1672776 | AD33: =AD3/AC3-1 -> 1.4236928 | AE33: =AE3/AD3-1 -> 0.6819492 | AF33: =AF3/AE3-1 -> -1
B34: Gaming Y/Y | G34: =G4/C4-1 -> 0.3115942 | H34: =H4/D4-1 -> -0.33289775 | I34: =I4/E4-1 -> -0.51133188 | J34: =J4/F4-1 -> -0.46461988 | K34: =K4/G4-1 -> -0.38121547 | L34: =L4/H4-1 -> 0.21743389 | M34: =M4/I4-1 -> 0.81448539 | N34: =N4/J4-1 -> 0.56471873 | ... X34: =X4/T4-1 -> -1 | AB34: =AB4/AA4-1 -> -0.27242818 | AC34: =AC4/AB4-1 -> 0.15220029 | AD34: =AD4/AC4-1 -> 0.086436298 | AE34: =AE4/AD4-1 -> 0.41339207 | AF34: =AF4/AE4-1 -> -1
B38: Net Cash | N38: =+N39-N52-N53 -> 16275 | O38: =+O39-O52-O53 -> 21728 | P38: =+P39-P52-P53 -> 26339 | Q38: =+Q39-Q52-Q53 -> 30025 | R38: =+R39-R52-R53 -> 34747 | S38: =+S39-S52-S53 -> 45227 | T38: =+T39-T52-T53 -> 48325 | U38: =+U39-U52-U53 -> 52141 | ... X38: =+X39-X52-X53 -> 0 | AC38: =+AC39-AC52-AC53 -> 16275 | AD38: =+AD39-AD52-AD53 -> 34747 | AE38: =+AE39-AE52-AE53 -> 54088
B39: Cash | N39: 25984 | O39: 31438 | P39: 34800 | Q39: 38487 | R39: 43210 | S39: 53691 | T39: 56791 | U39: =11486+49122 -> 60608 | V39: 62556 | AC39: 25984 | AD39: 43210 | AE39: 62556
B40: A/R | N40: 9999 | O40: 12365 | P40: 14132 | Q40: 17693 | R40: 23065 | S40: 22132 | T40: 27808 | U40: 33391 | V40: 38466 | AC40: 9999 | AD40: 23065 | AE40: 38466
B41: Inventories | N41: 5282 | O41: 5864 | P41: 6675 | Q41: 7654 | R41: 10080 | S41: 11333 | T41: 14962 | U41: 19754 | V41: 21403 | AC41: 5282 | AD41: 10080 | AE41: 21403
B42: Prepaids | N42: 3080 | O42: 4062 | P42: 4026 | Q42: 3806 | R42: 3771 | S42: 2779 | T42: 2658 | U42: 2709 | V42: 3180 | AC42: 3080 | AD42: 3771 | AE42: 3180
B43: PP&A | N43: 3914 | O43: 4006 | P43: 4885 | Q43: 5343 | R43: 6283 | S43: 7136 | T43: 9141 | U43: 9780 | V43: 10383 | AC43: 3914 | AD43: 6283 | AE43: 10383
B44: Leases | N44: 1346 | O44: 1532 | P44: 1556 | Q44: 1755 | R44: 1793 | S44: 1810 | T44: 2084 | U44: 2281 | V44: 2867 | AC44: 1346 | AD44: 1793 | AE44: 2867
B45: Goodwill | N45: 4430 | O45: 4453 | P45: 4622 | Q45: 4724 | R45: 5188 | S45: 5498 | T45: 5755 | U45: 6261 | V45: 20832 | AC45: 4430 | AD45: 5188 | AE45: 20832
B46: Intangibles | N46: 1112 | O46: 986 | P46: 952 | Q46: 838 | R46: 807 | S46: 769 | T46: 755 | U46: 936 | V46: 3306 | AC46: 1112 | AD46: 807 | AE46: 3306
B47: Deferred income tax | N47: 6081 | O47: 7798 | P47: 9578 | Q47: 10276 | R47: 10979 | S47: 13318 | T47: 13570 | U47: 13674 | V47: 13258 | AC47: 6081 | AD47: 10979 | AE47: 13258
B48: ONCA | N48: 4500 | O48: 4568 | P48: 4001 | Q48: 5437 | R48: 6425 | S48: 6788 | T48: 7216 | U48: 11724 | V48: =22251+8301 -> 30552 | AC48: 4500 | AD48: 6425 | AE48: =22251+8301 -> 30552
B49: Total Assets | N49: =SUM(N39:N48) -> 65728 | O49: =SUM(O39:O48) -> 77072 | P49: =SUM(P39:P48) -> 85227 | Q49: =SUM(Q39:Q48) -> 96013 | R49: =SUM(R39:R48) -> 111601 | S49: =SUM(S39:S48) -> 125254 | T49: =SUM(T39:T48) -> 140740 | U49: =SUM(U39:U48) -> 161118 | ... X49: =SUM(X39:X48) -> 0 | AC49: =SUM(AC39:AC48) -> 65728 | AD49: =SUM(AD39:AD48) -> 111601 | AE49: =SUM(AE39:AE48) -> 206803
B50: A/P | N50: 2699 | O50: 2715 | P50: 3680 | Q50: 5353 | R50: 6310 | S50: 7331 | T50: 9064 | U50: 8624 | V50: 9812 | AC50: 2699 | AD50: 6310 | AE50: 9812
B51: Accrued liabilities | N51: 6682 | O51: 11258 | P51: 10289 | Q51: 11126 | R51: 11737 | S51: 19211 | T51: 15193 | U51: 16452 | V51: 21352 | AC51: 6682 | AD51: 11737 | AE51: 21352
B52: Short-term debt | N52: 1250 | O52: 1250 | U52: 999 | V52: 999 | AC52: 1250 | AE52: 999
B53: Long-term debt | N53: 8459 | O53: 8460 | P53: 8461 | Q53: 8462 | R53: 8463 | S53: 8464 | T53: 8466 | U53: 7468 | V53: 7469 | AC53: 8459 | AD53: 8463 | AE53: 7469
B54: Long-term lease | N54: 1119 | O54: 1281 | P54: 1304 | Q54: 1490 | R54: 1519 | S54: 1521 | T54: 1831 | U54: 2014 | V54: 2572 | AC54: 1119 | AD54: 1519 | AE54: 2572
B55: ONCL | N55: 2541 | O55: 2966 | P55: 3336 | Q55: 3683 | R55: 4245 | S55: 4884 | T55: 6055 | U55: 6694 | V55: 7306 | AC55: 2541 | AD55: 4245 | AE55: 7306
B56: Total liabilities | N56: =SUM(N50:N55) -> 22750 | O56: =SUM(O50:O55) -> 27930 | P56: =SUM(P50:P55) -> 27070 | Q56: =SUM(Q50:Q55) -> 30114 | R56: =SUM(R50:R55) -> 32274 | S56: =SUM(S50:S55) -> 41411 | T56: =SUM(T50:T55) -> 40609 | U56: =SUM(U50:U55) -> 42251 | ... X56: =SUM(X50:X55) -> 0 | AC56: =SUM(AC50:AC55) -> 22750 | AD56: =SUM(AD50:AD55) -> 32274 | AE56: =SUM(AE50:AE55) -> 49510
B57: SE | N57: 42978 | O57: 49142 | P57: 58157 | Q57: 65899 | R57: 79327 | S57: 83843 | T57: 100131 | U57: 118897 | V57: 157293 | AC57: 42978 | AD57: 79327 | AE57: 157293
B58: L+SE | N58: =N57+N56 -> 65728 | O58: =O57+O56 -> 77072 | P58: =P57+P56 -> 85227 | Q58: =Q57+Q56 -> 96013 | R58: =R57+R56 -> 111601 | S58: =S57+S56 -> 125254 | T58: =T57+T56 -> 140740 | U58: =U57+U56 -> 161148 | ... X58: =X57+X56 -> 0 | AC58: =AC57+AC56 -> 65728 | AD58: =AD57+AD56 -> 111601 | AE58: =AE57+AE56 -> 206803
B60: Debt to equity | N60: =N56/N57 -> 0.52934059 | O60: =O56/O57 -> 0.56835294 | P60: =P56/P57 -> 0.46546417 | Q60: =Q56/Q57 -> 0.45697203 | R60: =R56/R57 -> 0.40684761 | S60: =S56/S57 -> 0.49391124 | T60: =T56/T57 -> 0.40555872 | U60: =U56/U57 -> 0.355358 | ... X60: =X56/X57 -> #DIV/0! | AC60: =AC56/AC57 -> 0.52934059 | AD60: =AD56/AD57 -> 0.40684761 | AE60: =AE56/AE57 -> 0.31476289
B63: Model NI | K63: =K18 -> 2043 | L63: =L18 -> 6188 | M63: =M18 -> 9243 | N63: =N18 -> 12285 | O63: =O18 -> 14881 | P63: =P18 -> 16599 | Q63: =Q18 -> 19309 | R63: =R18 -> 22091 | ... X63: =X18 -> 0 | AC63: =AC18 -> 29759 | AD63: =AD18 -> 72880 | AE63: =AE18 -> 120067 | AF63: =AF18 -> 253590
B64: GAAP NI | K64: 2043 | L64: 6188 | M64: 9243 | N64: 12285 | O64: 14881 | P64: 16599 | Q64: 19309 | R64: 22091 | S64: 18775 | T64: 26422 | U64: 31910 | V64: 42960 | AC64: =K64+L64+M64+N64 -> 29759 | AD64: =O64+P64+Q64+R64 -> 72880 | AE64: =SUM(S64:V64) -> 120067
B65: Stock-based compensation | K65: 735 | L65: 842 | M65: 979 | N65: 993 | O65: 1011 | P65: 1154 | Q65: 1252 | R65: 1321 | S65: 1474 | T65: 1624 | U65: 1655 | V65: 1633 | AC65: =K65+L65+M65+N65 -> 3549 | AD65: =O65+P65+Q65+R65 -> 4738 | AE65: =SUM(S65:V65) -> 6386
B66: D&A | K66: 384 | L66: 365 | M66: 372 | N66: 387 | O66: 410 | P66: 433 | Q66: 478 | R66: 543 | S66: 611 | T66: 668 | U66: 752 | V66: 811 | AC66: =K66+L66+M66+N66 -> 1508 | AD66: =O66+P66+Q66+R66 -> 1864 | AE66: =SUM(S66:V66) -> 2842
B67: Gains from non-affiliated entities | K67: 14 | L67: -60 | M67: 69 | N67: -78 | O67: -69 | P67: -193 | Q67: -37 | R67: -598 | S67: 175 | T67: 18 | U67: 124 | V67: -5491 | AC67: =K67+L67+M67+N67 -> -55 | AD67: =O67+P67+Q67+R67 -> -897 | AE67: =SUM(S67:V67) -> -5174
B68: Deferred income taxes | K68: -1135 | L68: -746 | M68: -529 | N68: -260 | O68: -1577 | P68: -1699 | Q68: -602 | R68: -727 | S68: -2177 | T68: -2247 | U68: -1354 | V68: 611 | AC68: =K68+L68+M68+N68 -> -2670 | AD68: =O68+P68+Q68+R68 -> -4605 | AE68: =SUM(S68:V68) -> -5167
B69: Other | K69: -34 | L69: -69 | M69: -66 | N69: -109 | O69: -145 | P69: -144 | Q69: -79 | R69: -138 | S69: -98 | T69: -100 | U69: -80 | V69: -9 | AC69: =K69+L69+M69+N69 -> -278 | AD69: =O69+P69+Q69+R69 -> -506 | AE69: =SUM(S69:V69) -> -287
B70: A/R | K70: -252 | L70: -2986 | M70: -1243 | N70: -1690 | O70: -2366 | P70: -1767 | Q70: -3561 | R70: -5370 | S70: 933 | T70: -5675 | U70: -5583 | V70: -5073 | AC70: =K70+L70+M70+N70 -> -6171 | AD70: =O70+P70+Q70+R70 -> -13064 | AE70: =SUM(S70:V70) -> -15398
B71: Inventories | K71: 566 | L71: 296 | M71: -457 | N71: -503 | O71: -577 | P71: -803 | Q71: -978 | R71: -2424 | S71: -1258 | T71: -3622 | U71: -4823 | V71: -1621 | AC71: =K71+L71+M71+N71 -> -98 | AD71: =O71+P71+Q71+R71 -> -4782 | AE71: =SUM(S71:V71) -> -11324
B72: Prepaids | K72: -215 | L72: -376 | M72: 254 | N72: -1184 | O72: -726 | P72: 714 | Q72: -714 | R72: 331 | S72: 560 | T72: 387 | U72: -89 | V72: -281 | AC72: =K72+L72+M72+N72 -> -1521 | AD72: =O72+P72+Q72+R72 -> -395 | AE72: =SUM(S72:V72) -> 577
B73: A/P | K73: 11 | L73: 777 | M73: 461 | N73: 281 | O73: -22 | P73: 823 | Q73: 1689 | R73: 867 | S73: 941 | T73: 1314 | U73: -223 | V73: 1064 | AC73: =K73+L73+M73+N73 -> 1530 | AD73: =O73+P73+Q73+R73 -> 3357 | AE73: =SUM(S73:V73) -> 3096
B74: Accrued liabilities | K74: 689 | L74: 1986 | M74: -1722 | N74: 1072 | O74: 4202 | P74: -888 | Q74: 606 | R74: 360 | S74: 7128 | T74: -4053 | U74: 1129 | V74: 1053 | AC74: =K74+L74+M74+N74 -> 2025 | AD74: =O74+P74+Q74+R74 -> 4280 | AE74: =SUM(S74:V74) -> 5257
B75: ONCL | K75: 105 | L75: 131 | M75: -28 | N75: 305 | O75: 323 | P75: 260 | Q75: 266 | R75: 372 | S75: 350 | T75: 629 | U75: 332 | V75: 533 | AC75: =K75+L75+M75+N75 -> 513 | AD75: =O75+P75+Q75+R75 -> 1221 | AE75: =SUM(S75:V75) -> 1844
B76: CFFO | K76: =SUM(K64:K75) -> 2911 | L76: =SUM(L64:L75) -> 6348 | M76: =SUM(M64:M75) -> 7333 | N76: =SUM(N64:N75) -> 11499 | O76: =SUM(O64:O75) -> 15345 | P76: =SUM(P64:P75) -> 14489 | Q76: =SUM(Q64:Q75) -> 17629 | R76: =SUM(R64:R75) -> 16628 | ... X76: =SUM(X64:X75) -> 0 | AC76: =SUM(AC64:AC75) -> 28091 | AD76: =SUM(AD64:AD75) -> 64091 | AE76: =SUM(AE64:AE75) -> 102719 | AF76: =SUM(AF64:AF75) -> 0
B77: Marketable maturities | K77: 2512 | L77: 2598 | M77: 2891 | N77: 1731 | O77: 4004 | P77: 4094 | Q77: 1386 | R77: 1710 | S77: 3122 | T77: 3130 | U77: =2728+2 -> 2730 | V77: 14670 | AC77: =K77+L77+M77+N77 -> 9732 | AD77: =O77+P77+Q77+R77 -> 11194 | AE77: =SUM(S77:V77) -> 23652
B78: Marketable sales | N78: =50-113 -> -63 | O78: 149 | P78: 15 | Q78: 154 | R78: =177-478 -> -301 | S78: 467 | T78: 20 | V78: 2258 | AC78: =K78+L78+M78+N78 -> -63 | AD78: =O78+P78+Q78+R78 -> 17 | AE78: =SUM(S78:V78) -> 2745
B79: Marketable purchases | K79: -2801 | L79: -2542 | M79: -5345 | N79: -7524 | O79: -9303 | P79: -5744 | Q79: -4518 | R79: -7010 | S79: =-6546-649 -> -7195 | T79: -7812 | U79: =-5718-3706 -> -9424 | V79: =-20540-12800 -> -33340 | AC79: =K79+L79+M79+N79 -> -18212 | AD79: =O79+P79+Q79+R79 -> -26575 | AE79: =SUM(S79:V79) -> -57771
B80: CapEx | K80: -248 | L80: -289 | M80: -278 | N80: -253 | O80: -369 | P80: -977 | Q80: -813 | R80: -1077 | S80: -1227 | T80: -1894 | U80: -1637 | V80: -1284 | AC80: =K80+L80+M80+N80 -> -1068 | AD80: =O80+P80+Q80+R80 -> -3236 | AE80: =SUM(S80:V80) -> -6042
B81: Acquisitions | K81: -83 | O81: -39 | P81: -279 | Q81: -147 | R81: =-542+22 -> -520 | S81: -383 | T81: -294 | U81: -694 | V81: -13000 | AC81: =K81+L81+M81+N81 -> -83 | AD81: =O81+P81+Q81+R81 -> -985 | AE81: =SUM(S81:V81) -> -14371
B82: Inv. In non-affiliated | K82: -221 | L82: =-235+21 -> -214 | M82: =-441+4 -> -437 | O82: -135 | P82: =-344+50 -> -294 | Q82: =-473+66 -> -407 | T82: =-346+70 -> -276 | V82: -165 | AC82: =K82+L82+M82+N82 -> -872 | AD82: =O82+P82+Q82+R82 -> -836 | AE82: =SUM(S82:V82) -> -441
B83: CFFI | K83: =SUM(K77:K82) -> -841 | L83: =SUM(L77:L82) -> -447 | M83: =SUM(M77:M82) -> -3169 | N83: =SUM(N77:N82) -> -6109 | O83: =SUM(O77:O82) -> -5693 | P83: =SUM(P77:P82) -> -3185 | Q83: =SUM(Q77:Q82) -> -4345 | R83: =SUM(R77:R82) -> -7198 | ... X83: =SUM(X77:X82) -> 0 | AC83: =SUM(AC77:AC82) -> -10566 | AD83: =SUM(AD77:AD82) -> -20421 | AE83: =SUM(AE77:AE82) -> -52228 | AF83: =SUM(AF77:AF82) -> 0
B84: Proceeds from emp. Stock plans | K84: 246 | L84: 1 | M84: 156 | O84: 285 | Q84: 204 | S84: 370 | U84: 274 | V84: 0 | AC84: =K84+L84+M84+N84 -> 403 | AD84: =O84+P84+Q84+R84 -> 489 | AE84: =SUM(S84:V84) -> 644
B85: Repurchases of stock | L85: -3067 | M85: -3806 | N85: -2660 | O85: -7740 | P85: -7158 | Q85: -10998 | R85: -7810 | S85: -14095 | T85: -9721 | U85: -12456 | V85: -3815 | AC85: =K85+L85+M85+N85 -> -9533 | AD85: =O85+P85+Q85+R85 -> -33706 | AE85: =SUM(S85:V85) -> -40087
B86: Repayment of debt | L86: -1250 | P86: -1250 | AC86: =K86+L86+M86+N86 -> -1250 | AD86: =O86+P86+Q86+R86 -> -1250 | AE86: =SUM(S86:V86) -> 0
B87: Tax on restricted stock | K87: -507 | L87: -672 | M87: -764 | N87: -841 | O87: -1752 | P87: -1637 | Q87: -1680 | R87: -1861 | S87: -1532 | T87: -1848 | U87: -2429 | V87: -2139 | AC87: =K87+L87+M87+N87 -> -2784 | AD87: =O87+P87+Q87+R87 -> -6930 | AE87: =SUM(S87:V87) -> -7948
B88: Dividends | K88: -99 | L88: -99 | M88: -99 | N88: -99 | O88: -98 | P88: -246 | Q88: -245 | R88: -245 | S88: -244 | T88: -244 | U88: -243 | V88: -243 | AC88: =K88+L88+M88+N88 -> -396 | AD88: =O88+P88+Q88+R88 -> -834 | AE88: =SUM(S88:V88) -> -974
B89: Principal on PP&A | K89: -20 | L89: -11 | M89: =-13-1 -> -14 | N89: -29 | O89: -40 | P89: -29 | Q89: -29 | R89: -32 | S89: -52 | T89: -21 | U89: -24 | V89: -13 | AC89: =K89+L89+M89+N89 -> -74 | AD89: =O89+P89+Q89+R89 -> -130 | AE89: =SUM(S89:V89) -> -110
B90: CFFF | K90: =SUM(K84:K89) -> -380 | L90: =SUM(L84:L89) -> -5098 | M90: =SUM(M84:M89) -> -4527 | N90: =SUM(N84:N89) -> -3629 | O90: =SUM(O84:O89) -> -9345 | P90: =SUM(P84:P89) -> -10320 | Q90: =SUM(Q84:Q89) -> -12748 | R90: =SUM(R84:R89) -> -9948 | ... X90: =SUM(X84:X89) -> 0 | AC90: =SUM(AC84:AC89) -> -13634 | AD90: =SUM(AD84:AD89) -> -42361 | AE90: =SUM(AE84:AE89) -> -48475 | AF90: =SUM(AF84:AF89) -> 0
B91: CF | K91: =K76+K83+K90 -> 1690 | L91: =L76+L83+L90 -> 803 | M91: =M76+M83+M90 -> -363 | N91: =N76+N83+N90 -> 1761 | O91: =O76+O83+O90 -> 307 | P91: =P76+P83+P90 -> 984 | Q91: =Q76+Q83+Q90 -> 536 | R91: =R76+R83+R90 -> -518 | ... X91: =X76+X83+X90 -> 0 | AC91: =AC76+AC83+AC90 -> 3891 | AD91: =AD76+AD83+AD90 -> 1309 | AE91: =AE76+AE83+AE90 -> 2016 | AF91: =AF76+AF83+AF90 -> 0
B92: BOP Cash | K92: 3389 | L92: =K93 -> 5079 | M92: =L93 -> 5882 | N92: =M93 -> 5519 | O92: 7280 | P92: =O93 -> 7587 | Q92: =P93 -> 8571 | R92: =Q93 -> 9107 | S92: =R93 -> 8589 | T92: =S93 -> 15234 | U92: =T93 -> 11639 | V92: =U93 -> 11486 | W92: =V93 -> 10605 | X92: =W93 -> 10605 | AC92: 3389 | AD92: =AC93 -> 7280 | AE92: =AD93 -> 8589 | AF92: =AE93 -> 10605
B93: EOP Cash | K93: =K92+K91 -> 5079 | L93: =L92+L91 -> 5882 | M93: =M92+M91 -> 5519 | N93: =N92+N91 -> 7280 | O93: =O92+O91 -> 7587 | P93: =P92+P91 -> 8571 | Q93: =Q92+Q91 -> 9107 | R93: =R92+R91 -> 8589 | ... X93: =X92+X91 -> 10605 | AC93: =AC92+AC91 -> 7280 | AD93: =AD92+AD91 -> 8589 | AE93: =AE92+AE91 -> 10605 | AF93: =AF92+AF91 -> 10605
B95: FCF | K95: =K76+K80+K89 -> 2643 | L95: =L76+L80+L89 -> 6048 | M95: =M76+M80+M89 -> 7041 | N95: =N76+N80+N89 -> 11217 | O95: =O76+O80+O89 -> 14936 | P95: =P76+P80+P89 -> 13483 | Q95: =Q76+Q80+Q89 -> 16787 | R95: =R76+R80+R89 -> 15519 | ... X95: =X76+X80+X89 -> 0 | AC95: =AC76+AC80+AC89 -> 26949 | AD95: =AD76+AD80+AD89 -> 60725 | AE95: =AE76+AE80+AE89 -> 96567 | AF95: =AF76+AF80+AF89 -> 0
B96: CapEx Margin | K96: =-K80/K64 -> 0.12139011 | L96: =-L80/L64 -> 0.046703297 | M96: =-M80/M64 -> 0.030076815 | N96: =-N80/N64 -> 0.020594221 | O96: =-O80/O64 -> 0.024796721 | P96: =-P80/P64 -> 0.058858967 | Q96: =-Q80/Q64 -> 0.042104718 | R96: =-R80/R64 -> 0.048752886 | ... X96: =-X80/X64 -> #DIV/0! | AC96: =-AC80/AC64 -> 0.035888303 | AD96: =-AD80/AD64 -> 0.044401756 | AE96: =-AE80/AE64 -> 0.050321904 | AF96: =-AF80/AF64 -> #DIV/0!
B97: FCF YoY
B98: FCF Margin
B101: Non-GAAP NI | K101: 2713 | L101: 6740 | M101: 10020 | N101: 12839 | O101: 15238 | P101: 16952 | Q101: 20010 | R101: 22066 | S101: 19894 | T101: 25783 | U101: 31767 | V101: 39552
B102: Non-GAAP EPS | K102: =K101/K19 -> 0.10983806 | L102: =L101/L19 -> 0.27255449 | M102: =M101/M19 -> 0.40599676 | N102: =N101/N19 -> 0.52064071 | O102: =O101/O19 -> 0.6189277 | P102: =P101/P19 -> 0.68972252 | Q102: =Q101/Q19 -> 0.81563608 | R102: =R101/R19 -> 0.90105762 | ... X102: =X101/X19 -> #DIV/0!
