Workbook

Sheet Main
J6: P | K6: 51.22
J7: S/O | K7: =Model!L30/1000 -> 170.776
J8: MC | K8: =K6*K7 -> 8747.1467
J9: Cash | K9: =(Model!L55+Model!L56)/1000 -> 411.567
J10: Debt | K10: =+Model!L68/1000 -> 0
J12: EV | K12: =+K8-K9+K10 -> 8335.5797

Sheet Model
A1: Main | C1: ($ thousands)
C2: Q123 | D2: Q223 | E2: Q323 | F2: Q423 | G2: Q124 | H2: Q224 | I2: Q324 | J2: Q424 | K2: Q125 | L2: Q225 | M2: Q325 | N2: Q425 | O2: Q126 | P2: Q226 | Q2: Q326 | R2: Q426 | S2: Q127 | T2: Q227 | U2: Q327 | V2: Q427 | Y2: 2022 | Z2: 2023 | AA2: 2024 | AB2: 2025 | AC2: 2026 | AD2: 2027 | AE2: 2028 | AF2: 2029 | AG2: 2030 | AH2: 2031 | AI2: 2032 | AJ2: 2033 | AK2: 2034 | AL2: 2035 | AM2: 2036 | AN2: 2037 | AO2: 2038 | AP2: 2039 | AQ2: 2040 | AR2: 2041 | AS2: 2042 | AT2: 2043 | AU2: 2044 | AV2: 2045 | AW2: 2046 | AX2: 2047 | AY2: 2048 | AZ2: 2049 | BA2: 2050 | BB2: 2051 | BC2: 2052 | BD2: 2053 | BE2: 2054 | BF2: 2055 | BG2: 2056 | BH2: 2057 | BI2: 2058 | BJ2: 2059 | BK2: 2060
B3: Pega Cloud | C3: 107879 | D3: 115063 | E3: 118040 | F3: 120346 | G3: 130902 | H3: 134086 | I3: 144108 | J3: 149638 | K3: 151123 | L3: 166743 | Y3: 384271 | Z3: 461328 | AA3: 558734 | AB3: =0.4*AB9 -> 682458
B4: Maintenance | C4: 79630 | D4: 82042 | E4: 83538 | F4: 86646 | G4: 81001 | H4: 80344 | I4: 80702 | J4: 81257 | K4: 76368 | L4: 79271 | Y4: 317564 | Z4: 331856 | AA4: 323304
B5: Subscription services | C5: =SUM(C3:C4) -> 187509 | D5: =SUM(D3:D4) -> 197105 | E5: =SUM(E3:E4) -> 201578 | F5: =SUM(F3:F4) -> 206992 | G5: =SUM(G3:G4) -> 211903 | H5: =SUM(H3:H4) -> 214430 | I5: =SUM(I3:I4) -> 224810 | J5: =SUM(J3:J4) -> 230895 | ... L5: =SUM(L3:L4) -> 246014 | Y5: =SUM(Y3:Y4) -> 701835 | Z5: =SUM(Z3:Z4) -> 793184 | AA5: =SUM(AA3:AA4) -> 882038 | AB5: =SUM(AB3:AB4) -> 682458
B6: Subscription license | C6: 84527 | D6: 41197 | E6: 74342 | F6: 207559 | G6: 63338 | H6: 84647 | I6: 45420 | J6: 204697 | K6: 186555 | L6: 79963 | Y6: 366063 | Z6: 407625 | AA6: 398102
B7: Consulting | C7: 53033 | D7: 58387 | E7: 55976 | F7: 54310 | G7: 54047 | H7: 52040 | I7: 54364 | J7: 52822 | K7: 60421 | L7: 57824 | Y7: 230654 | Z7: 221706 | AA7: 213273
B8: Perpetual license | C8: 403 | D8: 1579 | E8: 2747 | F8: 5372 | G8: 859 | H8: 36 | I8: 456 | J8: 2416 | K8: 1166 | L8: 711 | Y8: 19293 | Z8: 10101 | AA8: 3767
B9: Total revenue | C9: =SUM(C5:C8) -> 325472 | D9: =SUM(D5:D8) -> 298268 | E9: =SUM(E5:E8) -> 334643 | F9: =SUM(F5:F8) -> 474233 | G9: =SUM(G5:G8) -> 330147 | H9: =SUM(H5:H8) -> 351153 | I9: =SUM(I5:I8) -> 325050 | J9: =SUM(J5:J8) -> 490830 | ... L9: =SUM(L5:L8) -> 384512 | M9: 352000 | N9: 494000 | O9: 478000 | P9: 412000 | Q9: 392000 | R9: 533000 | S9: 505000 | T9: 452000 | U9: =Q9*(1+U43) -> 431200 | V9: =R9*(1+V43) -> 580970 | Y9: =SUM(Y5:Y8) -> 1317845 | Z9: =SUM(Z5:Z8) -> 1432616 | AA9: =SUM(AA5:AA8) -> 1497180 | AB9: =+K9+L9+M9+N9 -> 1706145 | AC9: =+O9+P9+Q9+R9 -> 1815000 | AD9: =S9+T9+U9+V9 -> 1969170 | AE9: =AD9*(1+AE43) -> 2107011.9 | AF9: =AE9*(1+AF43) -> 2254502.7 | AG9: =AF9*(1+AG43) -> 2412317.9 | AH9: =AG9*(1+AH43) -> 2581180.2 | AI9: =AH9*(1+AI43) -> 2761862.8 | AJ9: =AI9*(1+AJ43) -> 2955193.2 | AK9: =AJ9*(1+AK43) -> 3162056.7 | AL9: =AK9*(1+AL43) -> 3383400.7 | ... AV9: =AU9*(1+AV43) -> 5457358.8
B10: Subscription services | C10: 36864 | D10: 36783 | E10: 35906 | F10: 34697 | G10: 35824 | H10: 36238 | I10: 36868 | J10: 40988 | K10: 38128 | L10: 41510 | Y10: 138736 | Z10: 144250 | AA10: 149918
B11: Subscription license | C11: 719 | D11: 623 | E11: 629 | F11: 635 | G11: 643 | H11: 477 | I11: 384 | J11: 384 | K11: 386 | L11: 360 | Y11: 2642 | Z11: 2606 | AA11: 1888
B12: Consulting | C12: 60348 | D12: 58710 | E12: 57204 | F12: 55298 | G12: 58182 | H12: 60231 | I12: 59451 | J12: 60978 | K12: 63934 | L12: 67700 | Y12: 227082 | Z12: 231560 | AA12: 238842
B13: Perpetual license | C13: 3 | D13: 24 | E13: 24 | F13: 16 | G13: 9 | I13: 3 | J13: 5 | K13: 2 | L13: 4 | Y13: 175 | Z13: 67 | AA13: 17
B14: Total cost | C14: =SUM(C10:C13) -> 97934 | D14: =SUM(D10:D13) -> 96140 | E14: =SUM(E10:E13) -> 93763 | F14: =SUM(F10:F13) -> 90646 | G14: =SUM(G10:G13) -> 94658 | H14: =SUM(H10:H13) -> 96946 | I14: =SUM(I10:I13) -> 96706 | J14: =SUM(J10:J13) -> 102355 | ... L14: =SUM(L10:L13) -> 109574 | Y14: =SUM(Y10:Y13) -> 368635 | Z14: =SUM(Z10:Z13) -> 378483 | AA14: =SUM(AA10:AA13) -> 390665 | AB14: =SUM(AB10:AB13) -> 0
B15: Gross Profit | C15: =C9-C14 -> 227538 | D15: =D9-D14 -> 202128 | E15: =E9-E14 -> 240880 | F15: =F9-F14 -> 383587 | G15: =G9-G14 -> 235489 | H15: =H9-H14 -> 254207 | I15: =I9-I14 -> 228344 | J15: =J9-J14 -> 388475 | ... L15: =L9-L14 -> 274938 | Y15: =Y9-Y14 -> 949210 | Z15: =Z9-Z14 -> 1054133 | AA15: =AA9-AA14 -> 1106515 | AB15: =AB9-AB14 -> 1706145
B16: S&M | C16: 149797 | D16: 143858 | E16: 131598 | F16: 133924 | G16: 127695 | H16: 139761 | I16: 127669 | J16: 139655 | K16: 138069 | L16: 147131 | Y16: 624789 | Z16: 559177 | AA16: 534780
B17: R&D | C17: 75376 | D17: 73931 | E17: 74955 | F17: 71250 | G17: 72113 | H17: 75425 | I17: 74157 | J17: 76379 | K17: 74286 | L17: 78784 | Y17: 294349 | Z17: 295512 | AA17: 298074
B18: G&A | C18: 23110 | D18: 23462 | E18: 27321 | F18: 22850 | G18: 23527 | H18: 25420 | I18: 35694 | J18: 28207 | K18: 33828 | L18: 31788 | Y18: 117734 | Z18: 96743 | AA18: 112848
B19: Litigation | G19: 32403 | AA19: 32403
B20: Restructuring | C20: 1461 | D20: 2167 | E20: 17822 | F20: 297 | G20: 163 | H20: 635 | I20: 2485 | J20: 1245 | K20: 11 | L20: -44 | Y20: 21743 | Z20: 21747 | AA20: 4528
B21: Operating expenses | C21: =SUM(C16:C20) -> 249744 | D21: =SUM(D16:D20) -> 243418 | E21: =SUM(E16:E20) -> 251696 | F21: =SUM(F16:F20) -> 228321 | G21: =SUM(G16:G20) -> 255901 | H21: =SUM(H16:H20) -> 241241 | I21: =SUM(I16:I20) -> 240005 | J21: =SUM(J16:J20) -> 245486 | ... L21: =SUM(L16:L20) -> 257659 | Y21: =SUM(Y16:Y20) -> 1058615 | Z21: =SUM(Z16:Z20) -> 973179 | AA21: =SUM(AA16:AA20) -> 982633 | AB21: =SUM(AB16:AB20) -> 0
B22: Operating profit | C22: =C15-C21 -> -22206 | D22: =D15-D21 -> -41290 | E22: =E15-E21 -> -10816 | F22: =F15-F21 -> 155266 | G22: =G15-G21 -> -20412 | H22: =H15-H21 -> 12966 | I22: =I15-I21 -> -11661 | J22: =J15-J21 -> 142989 | ... L22: =L15-L21 -> 17279 | Y22: =Y15-Y21 -> -109405 | Z22: =Z15-Z21 -> 80954 | AA22: =AA15-AA21 -> 123882 | AB22: =AB15-AB21 -> 1706145
B23: FX | C23: -2675 | D23: -3290 | E23: 1994 | F23: -1271 | G23: -3262 | H23: 437 | I23: -4405 | J23: 6318 | K23: -5325 | L23: -14008 | Y23: 4560 | Z23: -5242 | AA23: -912
B24: Interest income | C24: 1485 | D24: 1814 | E24: 2532 | F24: 3428 | G24: 5281 | H24: 6785 | I24: 6769 | J24: 6944 | K24: 5335 | L24: 3248 | Y24: 1643 | Z24: 9259 | AA24: 25779
B25: Interest expense | C25: -1918 | D25: -1778 | E25: -1533 | F25: -1647 | G25: -1752 | H25: -1656 | I25: -1639 | J25: -1788 | K25: -1027 | L25: -1 | Y25: -7792 | Z25: -6876 | AA25: -6835
B26: Other income | C26: =3206+6583 -> 9789 | D26: =-1361+5702 -> 4341 | E26: =-2294+6383 -> 4089 | F26: =-899+25 -> -874 | G26: =3299+1684 -> 4983 | H26: -3277 | I26: -689 | J26: =4-299 -> -295 | K26: =-223+561 -> 338 | L26: 18729 | Y26: =-57382+6579 -> -50803 | Z26: =-1348+18693 -> 17345 | AA26: =-663+1385 -> 722
B27: Pretax income | C27: =C22+SUM(C23:C26) -> -15525 | D27: =D22+SUM(D23:D26) -> -40203 | E27: =E22+SUM(E23:E26) -> -3734 | F27: =F22+SUM(F23:F26) -> 154902 | G27: =G22+SUM(G23:G26) -> -15162 | H27: =H22+SUM(H23:H26) -> 15255 | I27: =I22+SUM(I23:I26) -> -11625 | J27: =J22+SUM(J23:J26) -> 154168 | ... L27: =L22+SUM(L23:L26) -> 25247 | Y27: =Y22+SUM(Y23:Y26) -> -161797 | Z27: =Z22+SUM(Z23:Z26) -> 95440 | AA27: =AA22+SUM(AA23:AA26) -> 142636 | AB27: =AB22+SUM(AB23:AB26) -> 1706145
B28: Taxes | C28: 5249 | D28: 6601 | E28: 3545 | F28: 12237 | G28: -3038 | H28: 8642 | I28: 2765 | J28: 35078 | K28: 40888 | L28: -4830 | Y28: 183785 | Z28: 27632 | AA28: 43447
B29: Net Income | C29: =C27-C28 -> -20774 | D29: =D27-D28 -> -46804 | E29: =E27-E28 -> -7279 | F29: =F27-F28 -> 142665 | G29: =G27-G28 -> -12124 | H29: =H27-H28 -> 6613 | I29: =I27-I28 -> -14390 | J29: =J27-J28 -> 119090 | ... L29: =L27-L28 -> 30077 | M29: -280 | N29: 106000 | O29: 84000 | P29: 30340 | Q29: 10210 | R29: 125000 | S29: 73120 | T29: 42000 | U29: 15180 | V29: 143000 | Y29: =Y27-Y28 -> -345582 | Z29: =Z27-Z28 -> 67808 | AA29: =AA27-AA28 -> 99189 | AB29: =+K29+L29+M29+N29 -> 221219 | AC29: =+O29+P29+Q29+R29 -> 249550 | AD29: =S29+T29+U29+V29 -> 273300 | AE29: =AE9*(AE40) -> 294981.67 | AF29: =AF9*(AF40) -> 320139.39 | AG29: =AG9*(AG40) -> 349786.1 | AH29: =AH9*(AH40) -> 379433.49 | AI29: =AI9*(AI40) -> 411517.56 | AJ29: =AJ9*(AJ40) -> 443278.98 | AK29: =AK9*(AK40) -> 474308.51 | AL29: =AL9*(AL40) -> 507510.1 | ... AV29: =AV9*(AV40) -> 818603.81 | AW29: =AV29*(1-$AZ$32) -> 794045.7 | AX29: =AW29*(1-$AZ$32) -> 770224.33 | AY29: =AX29*(1-$AZ$32) -> 747117.6 | AZ29: =AY29*(1-$AZ$32) -> 724704.07 | BA29: =AZ29*(1-$AZ$32) -> 702962.95 | BB29: =BA29*(1-$AZ$32) -> 681874.06 | BC29: =BB29*(1-$AZ$32) -> 661417.84 | BD29: =BC29*(1-$AZ$32) -> 641575.3 | ... OP29: =OO29*(1-$AZ$32) -> 15.043699
B30: S/O | C30: 82604 | D30: 83039 | E30: 83336 | F30: 83654 | G30: 84266 | H30: 170314 | I30: 85625 | J30: 86000 | K30: 85902 | L30: 170776 | Y30: 81947 | Z30: 83162 | AA30: 85265
B31: EPS | C31: =C29/C30 -> -0.25148903 | D31: =D29/D30 -> -0.56363877 | E31: =E29/E30 -> -0.087345205 | F31: =F29/F30 -> 1.7054176 | G31: =G29/G30 -> -0.14387772 | H31: =H29/H30 -> 0.038828282 | I31: =I29/I30 -> -0.16805839 | J31: =J29/J30 -> 1.3847674 | ... L31: =L29/L30 -> 0.1761196 | Y31: =Y29/Y30 -> -4.2171403 | Z31: =Z29/Z30 -> 0.81537241 | AA31: =AA29/AA30 -> 1.1633026 | AB31: =AB29/AB30 -> #DIV/0! | AY31: NI Model | BC31: FCF Model
AY32: Maturity | AZ32: 0.03 | BC32: Maturity | BD32: 0.03
AY33: Discount | AZ33: 0.115 | BC33: Discount | BD33: 0.115
AY34: NPV | AZ34: =NPV(AZ33,AC29:OP29)+AB29+L54 -> 4511495.4 | BC34: NPV | BD34: =NPV(BD33,AC107:OP107)+AB107+L54 -> 9084927.1
B35: Gross margin | C35: =C15/C9 -> 0.69910161 | D35: =D15/D9 -> 0.67767243 | E35: =E15/E9 -> 0.71981186 | F35: =F15/F9 -> 0.80885767 | G35: =G15/G9 -> 0.71328529 | H35: =H15/H9 -> 0.72392091 | I35: =I15/I9 -> 0.70248885 | J35: =J15/J9 -> 0.79146548 | ... L35: =L15/L9 -> 0.715031 | Y35: =Y15/Y9 -> 0.72027439 | Z35: =Z15/Z9 -> 0.73580988 | AA35: =AA15/AA9 -> 0.73906611 | AY35: Share | AZ35: =AZ34/L30 -> 26.41762 | BC35: Share | BD35: =BD34/L30 -> 53.197915
B36: S&M margin | C36: =C16/C15 -> 0.65833839 | D36: =D16/D15 -> 0.71171733 | E36: =E16/E15 -> 0.54632182 | F36: =F16/F15 -> 0.34913592 | G36: =G16/G15 -> 0.54225463 | H36: =H16/H15 -> 0.5497921 | I36: =I16/I15 -> 0.55910819 | J36: =J16/J15 -> 0.35949546 | ... L36: =L16/L15 -> 0.53514247 | Y36: =Y16/Y15 -> 0.65821999 | Z36: =Z16/Z15 -> 0.53046153 | AA36: =AA16/AA15 -> 0.48330118 | AY36: Current | AZ36: =Main!K6 -> 51.22 | BC36: Current | BD36: =Main!K6 -> 51.22
B37: R&D margin | C37: =C17/C15 -> 0.33126774 | D37: =D17/D15 -> 0.36576328 | E37: =E17/E15 -> 0.31117154 | F37: =F17/F15 -> 0.18574665 | G37: =G17/G15 -> 0.30622662 | H37: =H17/H15 -> 0.29670701 | I37: =I17/I15 -> 0.32476001 | J37: =J17/J15 -> 0.19661239 | ... L37: =L17/L15 -> 0.28655188 | Y37: =Y17/Y15 -> 0.31009892 | Z37: =Z17/Z15 -> 0.28033654 | AA37: =AA17/AA15 -> 0.26938089 | AY37: Return | AZ37: =AZ35/AZ36-1 -> -0.48423234 | BC37: Return | BD37: =BD35/BD36-1 -> 0.038616068
B38: Operating margin | C38: =C22/C9 -> -0.068227067 | D38: =D22/D9 -> -0.13843255 | E38: =E22/E9 -> -0.032321011 | F38: =F22/F9 -> 0.32740446 | G38: =G22/G9 -> -0.061827004 | H38: =H22/H9 -> 0.036924076 | I38: =I22/I9 -> -0.035874481 | J38: =J22/J9 -> 0.29132082 | ... L38: =L22/L9 -> 0.044937479 | Y38: =Y22/Y9 -> -0.083018109 | Z38: =Z22/Z9 -> 0.056507815 | AA38: =AA22/AA9 -> 0.082743558
B39: Interest margin | C39: =SUM(C23:C26)/C22 -> -0.30086463 | D39: =SUM(D23:D26)/D22 -> -0.026325987 | E39: =SUM(E23:E26)/E22 -> -0.65477071 | F39: =SUM(F23:F26)/F22 -> -0.0023443639 | G39: =SUM(G23:G26)/G22 -> -0.25720165 | H39: =SUM(H23:H26)/H22 -> 0.17653864 | I39: =SUM(I23:I26)/I22 -> -0.0030872138 | J39: =SUM(J23:J26)/J22 -> 0.078180839 | ... L39: =SUM(L23:L26)/L22 -> 0.4611378 | Y39: =SUM(Y23:Y26)/Y22 -> 0.47888122 | Z39: =SUM(Z23:Z26)/Z22 -> 0.17894113 | AA39: =SUM(AA23:AA26)/AA22 -> 0.151386
B40: Net margin | C40: =C29/C9 -> -0.063827303 | D40: =D29/D9 -> -0.15691928 | E40: =E29/E9 -> -0.021751538 | F40: =F29/F9 -> 0.30083313 | G40: =G29/G9 -> -0.036723035 | H40: =H29/H9 -> 0.018832247 | I40: =I29/I9 -> -0.044270112 | J40: =J29/J9 -> 0.24262983 | ... L40: =L29/L9 -> 0.078221226 | Y40: =Y29/Y9 -> -0.26223266 | Z40: =Z29/Z9 -> 0.047331595 | AA40: =AA29/AA9 -> 0.066250551 | AB40: =AB29/AB9 -> 0.12966014 | AC40: =AC29/AC9 -> 0.13749311 | AD40: =AD29/AD9 -> 0.13878944 | AE40: 0.14 | AF40: 0.142 | AG40: 0.145 | AH40: 0.147 | AI40: 0.149 | AJ40: 0.15 | AK40: 0.15 | AL40: 0.15 | AM40: 0.15 | AN40: 0.15 | AO40: 0.15 | AP40: 0.15 | AQ40: 0.15 | AR40: 0.15 | AS40: 0.15 | AT40: 0.15 | AU40: 0.15 | AV40: 0.15
B42: Cloud Y/Y | G42: =G3/C3-1 -> 0.21341503 | H42: =H3/D3-1 -> 0.16532682 | I42: =I3/E3-1 -> 0.22084039 | J42: =J3/F3-1 -> 0.2433982 | K42: =K3/G3-1 -> 0.15447434 | L42: =L3/H3-1 -> 0.24355265 | Z42: =Z3/Y3-1 -> 0.20052775 | AA42: =AA3/Z3-1 -> 0.21114261
B43: Revenue Y/Y | G43: =G9/C9-1 -> 0.014363755 | H43: =H9/D9-1 -> 0.17730699 | I43: =I9/E9-1 -> -0.02866637 | J43: =J9/F9-1 -> 0.034997564 | K43: =K9/G9-1 -> 0.44067037 | L43: =L9/H9-1 -> 0.094998476 | M43: =M9/I9-1 -> 0.082910321 | N43: =N9/J9-1 -> 0.0064584479 | ... T43: =T9/P9-1 -> 0.097087379 | U43: 0.1 | V43: 0.09 | Z43: =Z9/Y9-1 -> 0.087089908 | AA43: =AA9/Z9-1 -> 0.045067206 | AB43: =AB9/AA9-1 -> 0.1395724 | AC43: =AC9/AB9-1 -> 0.063801728 | AD43: =AD9/AC9-1 -> 0.084942149 | AE43: 0.07 | AF43: 0.07 | AG43: 0.07 | AH43: 0.07 | AI43: 0.07 | AJ43: 0.07 | AK43: 0.07 | AL43: 0.07 | AM43: 0.065 | AN43: 0.06 | AO43: 0.055 | AP43: 0.05 | AQ43: 0.045 | AR43: 0.045 | AS43: 0.045 | AT43: 0.045 | AU43: 0.04 | AV43: 0.04
B45: Cloud % | C45: =C3/C$9 -> 0.33145401 | D45: =D3/D$9 -> 0.38577052 | E45: =E3/E$9 -> 0.35273411 | F45: =F3/F$9 -> 0.25376977 | G45: =G3/G$9 -> 0.39649611 | H45: =H3/H$9 -> 0.38184495 | I45: =I3/I$9 -> 0.44334102 | J45: =J3/J$9 -> 0.30486727 | ... L45: =L3/L$9 -> 0.43364836 | Y45: =Y3/Y$9 -> 0.29159044 | Z45: =Z3/Z$9 -> 0.3220179 | AA45: =AA3/AA$9 -> 0.37319093
B46: Maintenece % | C46: =C4/C$9 -> 0.24466006 | D46: =D4/D$9 -> 0.27506135 | E46: =E4/E$9 -> 0.24963319 | F46: =F4/F$9 -> 0.18270766 | G46: =G4/G$9 -> 0.24534828 | H46: =H4/H$9 -> 0.22880055 | I46: =I4/I$9 -> 0.24827565 | J46: =J4/J$9 -> 0.16555019 | ... L46: =L4/L$9 -> 0.20616002 | Y46: =Y4/Y$9 -> 0.24097219 | Z46: =Z4/Z$9 -> 0.23164337 | AA46: =AA4/AA$9 -> 0.21594197
B47: Service % of revenue | C47: =C5/C$9 -> 0.57611407 | D47: =D5/D$9 -> 0.66083187 | E47: =E5/E$9 -> 0.6023673 | F47: =F5/F$9 -> 0.43647743 | G47: =G5/G$9 -> 0.64184439 | H47: =H5/H$9 -> 0.6106455 | I47: =I5/I$9 -> 0.69161667 | J47: =J5/J$9 -> 0.47041746 | ... L47: =L5/L$9 -> 0.63980838 | Y47: =Y5/Y$9 -> 0.53256263 | Z47: =Z5/Z$9 -> 0.55366127 | AA47: =AA5/AA$9 -> 0.5891329
B48: License % | C48: =C6/C$9 -> 0.2597059 | D48: =D6/D$9 -> 0.13812075 | E48: =E6/E$9 -> 0.22215316 | F48: =F6/F$9 -> 0.43767304 | G48: =G6/G$9 -> 0.19184787 | H48: =H6/H$9 -> 0.24105447 | I48: =I6/I$9 -> 0.13973235 | J48: =J6/J$9 -> 0.41704256 | ... L48: =L6/L$9 -> 0.2079597 | Y48: =Y6/Y$9 -> 0.27777394 | Z48: =Z6/Z$9 -> 0.28453193 | AA48: =AA6/AA$9 -> 0.26590123
B49: Consulting % | C49: =C7/C$9 -> 0.16294182 | D49: =D7/D$9 -> 0.19575348 | E49: =E7/E$9 -> 0.16727079 | F49: =F7/F$9 -> 0.11452176 | G49: =G7/G$9 -> 0.16370586 | H49: =H7/H$9 -> 0.14819751 | I49: =I7/I$9 -> 0.16724812 | J49: =J7/J$9 -> 0.10761771 | ... L49: =L7/L$9 -> 0.15038282 | Y49: =Y7/Y$9 -> 0.17502362 | Z49: =Z7/Z$9 -> 0.15475605 | AA49: =AA7/AA$9 -> 0.14244981
B50: Perp. License % | C50: =C8/C$9 -> 0.0012382018 | D50: =D8/D$9 -> 0.0052938968 | E50: =E8/E$9 -> 0.0082087478 | F50: =F8/F$9 -> 0.011327765 | G50: =G8/G$9 -> 0.0026018713 | H50: =H8/H$9 -> 0.00010251941 | I50: =I8/I$9 -> 0.0014028611 | J50: =J8/J$9 -> 0.0049222745 | ... L50: =L8/L$9 -> 0.001849097 | Y50: =Y8/Y$9 -> 0.01463981 | Z50: =Z8/Z$9 -> 0.007050738 | AA50: =AA8/AA$9 -> 0.0025160635
B54: Net cash | C54: =C55+C56-C68 -> 0 | D54: =D55+D56-D68 -> 0 | E54: =E55+E56-E68 -> 0 | F54: =F55+F56-F68 -> -76030 | G54: =G55+G56-G68 -> 118964 | H54: =H55+H56-H68 -> 164472 | I54: =I55+I56-I68 -> 201765 | J54: =J55+J56-J68 -> 272503 | ... L54: =L55+L56-L68 -> 411567 | Z54: =Z55+Z56-Z68 -> -76030 | AA54: =AA55+AA56-AA68 -> 272503
B55: Cash | F55: 229902 | G55: 291905 | H55: 258257 | I55: 287649 | J55: 337103 | K55: 231129 | L55: 201565 | Z55: 229902 | AA55: 337103
B56: Securities | F56: 193436 | G56: 327044 | H56: 406819 | I56: 415341 | J56: 402870 | K56: 140607 | L56: 210002 | Z56: 193436 | AA56: 402870
B57: A/R | F57: 300173 | G57: 191987 | H57: 165723 | I57: 173623 | J57: 305468 | K57: 202869 | L57: 156470 | Z57: 300173 | AA57: 305468
B58: Unbilled Receivables | F58: 237379 | G58: 170458 | H58: 164533 | I58: 157281 | J58: 173085 | K58: 179093 | L58: 184184 | Z58: 237379 | AA58: 173085
B59: OCA | F59: 68137 | G59: 78193 | H59: 76323 | I59: 85186 | J59: 115178 | K59: 92794 | L59: 93403 | Z59: 68137 | AA59: 115178
B60: Long-term unbilled receivables | F60: 85402 | G60: 72814 | H60: 81218 | I60: 77576 | J60: 61407 | K60: 98251 | L60: 104298 | Z60: 85402 | AA60: 61407
B61: Goodwill | F61: 81611 | G61: 81467 | H61: 81410 | I61: 81568 | J61: 81113 | K61: 81186 | L61: 81538 | Z61: 81611 | AA61: 81113
B62: ONCA | F62: 314696 | G62: 297860 | H62: 302249 | I62: 301008 | J62: 292049 | K62: 296021 | L62: 292957 | Z62: 314696 | AA62: 292049
B63: Total Assets | C63: =SUM(C55:C62) -> 0 | D63: =SUM(D55:D62) -> 0 | E63: =SUM(E55:E62) -> 0 | F63: =SUM(F55:F62) -> 1510736 | G63: =SUM(G55:G62) -> 1511728 | H63: =SUM(H55:H62) -> 1536532 | I63: =SUM(I55:I62) -> 1579232 | J63: =SUM(J55:J62) -> 1768273 | ... L63: =SUM(L55:L62) -> 1324417 | Z63: =SUM(Z55:Z62) -> 1510736 | AA63: =SUM(AA55:AA62) -> 1768273
B64: A/P | F64: 11290 | G64: 6353 | H64: 16682 | I64: 20103 | J64: 6226 | K64: 16649 | L64: 17101 | Z64: 11290 | AA64: 6226
B65: Accrued expenses | F65: 39941 | G65: 80642 | H65: 44875 | I65: 41236 | J65: 31544 | K65: 49875 | L65: 51430 | Z65: 39941 | AA65: 31544
B66: Accrued compensation | F66: 126640 | G66: 55438 | H66: 81110 | I66: 98033 | J66: 138042 | K66: 55919 | L66: 91769 | Z66: 126640 | AA66: 138042
B67: Deferred revenue | F67: 377845 | G67: 382765 | H67: 352618 | I67: 345574 | J67: 423910 | K67: 469298 | L67: 418931 | Z67: 377845 | AA67: 423910
B68: Convertible senior notes | F68: 499368 | G68: 499985 | H68: 500604 | I68: 501225 | J68: 467470 | Z68: 499368 | AA68: 467470
B69: OCL | F69: 21343 | G69: 19096 | H69: 20677 | I69: 18372 | J69: 18866 | K69: 17395 | L69: 20387 | Z69: 21343 | AA69: 18866
B70: Long-term operating lease liabilities | F70: 66901 | G70: 63645 | H70: 70202 | I70: 66750 | J70: 67647 | K70: 65117 | L70: 65191 | Z70: 66901 | AA70: 67647
B71: ONCL | F71: 13570 | G71: 13618 | H71: 14362 | I71: 14916 | J71: 29088 | K71: 36428 | L71: 35066 | Z71: 13570 | AA71: 29088
B72: Total liabilities | C72: =SUM(C64:C71) -> 0 | D72: =SUM(D64:D71) -> 0 | E72: =SUM(E64:E71) -> 0 | F72: =SUM(F64:F71) -> 1156898 | G72: =SUM(G64:G71) -> 1121542 | H72: =SUM(H64:H71) -> 1101130 | I72: =SUM(I64:I71) -> 1106209 | J72: =SUM(J64:J71) -> 1182793 | ... L72: =SUM(L64:L71) -> 699875 | Z72: =SUM(Z64:Z71) -> 1156898 | AA72: =SUM(AA64:AA71) -> 1182793
B73: SE | F73: 353838 | G73: 390186 | H73: 435402 | I73: 473023 | J73: 585480 | K73: 611269 | L73: 624542 | Z73: 353838 | AA73: 585480
B74: L+SE | C74: =C73+C72 -> 0 | D74: =D73+D72 -> 0 | E74: =E73+E72 -> 0 | F74: =F73+F72 -> 1510736 | G74: =G73+G72 -> 1511728 | H74: =H73+H72 -> 1536532 | I74: =I73+I72 -> 1579232 | J74: =J73+J72 -> 1768273 | ... L74: =L73+L72 -> 1324417 | Z74: =Z73+Z72 -> 1510736 | AA74: =AA73+AA72 -> 1768273
B78: Model NI | C78: =C29 -> -20774 | D78: =D29 -> -46804 | E78: =E29 -> -7279 | F78: =F29 -> 142665 | G78: =G29 -> -12124 | H78: =H29 -> 6613 | I78: =I29 -> -14390 | J78: =J29 -> 119090 | ... L78: =L29 -> 30077 | Y78: =Y29 -> -345582 | Z78: =Z29 -> 67808 | AA78: =AA29 -> 99189
B79: GAAP NI | C79: -20774 | D79: -46804 | E79: -7279 | F79: 142665 | G79: -12124 | H79: 6613 | I79: -14390 | J79: 119090 | K79: 85422 | L79: 30077 | Y79: -345582 | Z79: 67808 | AA79: 99189
B80: Stock-based comp. | C80: 42557 | D80: 36227 | E80: 31299 | F80: 33269 | G80: 34781 | H80: 36224 | I80: 37213 | J80: 34500 | K80: 41425 | L80: 36730 | Y80: 122210 | Z80: 143352 | AA80: 142718
B81: Amortization of deferred commissions | C81: 14277 | D81: 14750 | E81: 14947 | F81: 15487 | G81: 17282 | H81: 14994 | I81: 14867 | J81: 15126 | K81: 18504 | L81: 15074 | Y81: 53471 | Z81: 59461 | AA81: 62269
B82: D&A | C82: 4724 | D82: 4829 | E82: 4628 | F82: 4565 | G82: 4254 | H82: 4558 | I82: 4477 | J82: 4296 | K82: 3137 | L82: 3182 | Y82: 18780 | Z82: 18746 | AA82: 17585
B83: Amortization of ROU lease assets | C83: 4594 | D83: 3592 | E83: 3832 | F83: 3894 | G83: 3472 | H83: 4372 | I83: 5904 | J83: 4094 | K83: 2826 | L83: 2977 | Y83: 15940 | Z83: 15912 | AA83: 17842
B84: FX | C84: 2675 | D84: 3290 | E84: -1994 | F84: 1271 | G84: 3262 | H84: -437 | I84: 4405 | J84: -6318 | K84: 5325 | L84: 14008 | Y84: -4560 | Z84: 5242 | AA84: 912
B85: Capped call transactions | C85: -3206 | D85: 1361 | E85: 2294 | F85: 899 | G85: -3299 | H85: 3277 | I85: 689 | J85: -4 | K85: 223 | L85: 0 | Y85: 57382 | Z85: 1348 | AA85: 663
B86: Deferred income taxes | C86: -126 | D86: -10 | E86: -52 | F86: 551 | G86: -646 | H86: 878 | I86: -299 | J86: -1477 | K86: 179 | L86: 103 | Y86: 168890 | Z86: 363 | AA86: -1544
B87: Accretion of investments | C87: -3802 | D87: -628 | E87: 4430 | F87: -3302 | G87: -2612 | H87: -3923 | I87: 6535 | J87: -15263 | K87: -1526 | L87: -584 | Y87: 1972 | Z87: -3302 | AA87: -15263
B88: Gain on investments | C88: -2781 | D88: -5074 | E88: -2986 | F88: 0 | G88: -1628 | H88: 0 | I88: 0 | J88: 759 | K88: -751 | L88: -18729 | Y88: -6578 | Z88: -10841 | AA88: -869
B89: Other non-cash | C89: 854 | D89: 1268 | E89: -7768 | F89: 3348 | G89: 726 | H89: 753 | I89: -10043 | J89: 11833 | K89: 1067 | L89: 0 | Y89: 4763 | Z89: =-7855+5557 -> -2298 | AA89: =-459+3728 -> 3269
B90: Change in operating assets and liabilities | C90: 29115 | D90: 32844 | E90: -17183 | F90: -122782 | G90: 136678 | H90: -27212 | I90: -18904 | J90: -71407 | K90: 48397 | L90: 3430 | Y90: =-51157-9133+529+62578-53857-13312 -> -64352 | Z90: =-57602+11360-8777+45123-44529-23581 -> -78006 | AA90: =79034-50005-7115+48360-57628+6509 -> 19155
B91: CFFO | C91: =SUM(C79:C90) -> 68107 | D91: =SUM(D79:D90) -> 45645 | E91: =SUM(E79:E90) -> 24168 | F91: =SUM(F79:F90) -> 79865 | G91: =SUM(G79:G90) -> 180146 | H91: =SUM(H79:H90) -> 40097 | I91: =SUM(I79:I90) -> 30454 | J91: =SUM(J79:J90) -> 95229 | ... L91: =SUM(L79:L90) -> 86268 | M91: 42520 | N91: 137000 | O91: 235000 | P91: 97620 | Q91: 74190 | R91: 154000 | S91: 266000 | T91: 112000 | U91: =Q91*1.15 -> 85318.5 | V91: =R91*1.15 -> 177100 | Y91: =SUM(Y79:Y90) -> 22336 | Z91: =SUM(Z79:Z90) -> 217785 | AA91: =SUM(AA79:AA90) -> 345926
B92: Purchases of investmetns | C92: -39401 | D92: -30261 | E92: -120804 | F92: -96821 | G92: -161438 | H92: -130372 | I92: -125500 | J92: -142055 | K92: -69318 | L92: -89385 | Y92: -41015 | Z92: -287287 | AA92: -559365
B93: Proceeds from maturities | C93: 36475 | D93: 52374 | E93: 80987 | F93: 72757 | G93: 29643 | H93: 54324 | I93: 122265 | J93: 158269 | K93: 324596 | L93: 20570 | Y93: 66583 | Z93: 242593 | AA93: 364501
B94: Sales of investments | D94: 10725 | E94: 0 | F94: 0 | H94: 0 | I94: 0 | J94: 0 | K94: 8497 | L94: 22050 | Y94: =23808-922 -> 22886 | Z94: 10725
B95: CapEx | C95: -11487 | D95: -2446 | E95: -338 | F95: -2510 | G95: -604 | H95: -1253 | I95: -3064 | J95: -2791 | K95: -1880 | L95: -2135 | M95: -4000 | N95: -4000 | O95: -4000 | P95: -4000 | Q95: -4000 | R95: -4000 | S95: -4000 | T95: -4000 | U95: -4000 | V95: -4000 | Y95: -35379 | Z95: -16781 | AA95: -7712
B96: CFFI | C96: =SUM(C92:C95) -> -14413 | D96: =SUM(D92:D95) -> 30392 | E96: =SUM(E92:E95) -> -40155 | F96: =SUM(F92:F95) -> -26574 | G96: =SUM(G92:G95) -> -132399 | H96: =SUM(H92:H95) -> -77301 | I96: =SUM(I92:I95) -> -6299 | J96: =SUM(J92:J95) -> 13423 | ... L96: =SUM(L92:L95) -> -48900 | Y96: =SUM(Y92:Y95) -> 13075 | Z96: =SUM(Z92:Z95) -> -50750 | AA96: =SUM(AA92:AA95) -> -202576
B97: Repurchase of convertible senior notes | C97: -29901 | D97: -59088 | E97: 0 | F97: 0 | H97: 0 | I97: 0 | J97: -33890 | K97: -467864 | L97: 0 | Z97: -88989 | AA97: -33890
B98: Dividends | C98: -2474 | D98: -2488 | E98: -2496 | F98: -2506 | G98: -2515 | H98: -2550 | I98: -2561 | J98: -2573 | K98: -2583 | L98: -2567 | Y98: -9834 | Z98: -9964 | AA98: -10199
B99: Proceeds from employee stock plans | C99: 3922 | D99: 4122 | E99: 4685 | F99: -4985 | G99: 22419 | H99: 7509 | I99: 18883 | J99: -42102 | K99: 13969 | L99: 71018 | Y99: 9172 | Z99: 7744 | AA99: 6709
B100: Stock repurchases | C100: =-1107+188 -> -919 | D100: -162 | E100: -232 | F100: 10559 | G100: -2005 | H100: -355 | I100: -11876 | J100: 21402 | K100: =-2304-117204 -> -119508 | L100: -138781 | Y100: =-20620-25707 -> -46327 | Z100: =10821-1916+341 -> 9246 | AA100: =80651-5435-68057+7 -> 7166
B101: CFFF | C101: =SUM(C97:C100) -> -29372 | D101: =SUM(D97:D100) -> -57616 | E101: =SUM(E97:E100) -> 1957 | F101: =SUM(F97:F100) -> 3068 | G101: =SUM(G97:G100) -> 17899 | H101: =SUM(H97:H100) -> 4604 | I101: =SUM(I97:I100) -> 4446 | J101: =SUM(J97:J100) -> -57163 | ... L101: =SUM(L97:L100) -> -70330 | Y101: =SUM(Y97:Y100) -> -46989 | Z101: =SUM(Z97:Z100) -> -81963 | AA101: =SUM(AA97:AA100) -> -30214
B102: FX adj. | C102: 782 | D102: 228 | E102: -2631 | F102: 4322 | G102: -2803 | H102: -39 | I102: 7433 | J102: -9025 | K102: 3570 | L102: 3837 | Y102: -3333 | Z102: 2701 | AA102: -4434
B103: CF | C103: =C91+C96+C101+C102 -> 25104 | D103: =D91+D96+D101+D102 -> 18649 | E103: =E91+E96+E101+E102 -> -16661 | F103: =F91+F96+F101+F102 -> 60681 | G103: =G91+G96+G101+G102 -> 62843 | H103: =H91+H96+H101+H102 -> -32639 | I103: =I91+I96+I101+I102 -> 36034 | J103: =J91+J96+J101+J102 -> 42464 | ... L103: =L91+L96+L101+L102 -> -29125 | Y103: =Y91+Y96+Y101+Y102 -> -14911 | Z103: =Z91+Z96+Z101+Z102 -> 87773 | AA103: =AA91+AA96+AA101+AA102 -> 108702
B104: BOP Cash | C104: 145054 | D104: =C105 -> 170158 | E104: =D105 -> 188807 | F104: =E105 -> 172146 | G104: =F105 -> 232827 | H104: =G105 -> 295670 | I104: =H105 -> 263031 | J104: =I105 -> 299065 | K104: =J105 -> 341529 | L104: =K105 -> 235236 | Y104: 159965 | Z104: =Y105 -> 145054 | AA104: =Z105 -> 232827
B105: EOP Cash | C105: =C103+C104 -> 170158 | D105: =D103+D104 -> 188807 | E105: =E103+E104 -> 172146 | F105: =F103+F104 -> 232827 | G105: =G103+G104 -> 295670 | H105: =H103+H104 -> 263031 | I105: =I103+I104 -> 299065 | J105: =J103+J104 -> 341529 | ... L105: =L103+L104 -> 206111 | Y105: =Y103+Y104 -> 145054 | Z105: =Z103+Z104 -> 232827 | AA105: =AA103+AA104 -> 341529
B107: FCF | C107: =C91+C95 -> 56620 | D107: =D91+D95 -> 43199 | E107: =E91+E95 -> 23830 | F107: =F91+F95 -> 77355 | G107: =G91+G95 -> 179542 | H107: =H91+H95 -> 38844 | I107: =I91+I95 -> 27390 | J107: =J91+J95 -> 92438 | ... V107: =V91+V95 -> 173100 | Y107: =Y91+Y95 -> -13043 | Z107: =Z91+Z95 -> 201004 | AA107: =AA91+AA95 -> 338214 | AB107: =+K107+L107+M107+N107 -> 458001 | AC107: =+O107+P107+Q107+R107 -> 544810 | AD107: =S107+T107+U107+V107 -> 624418.5 | AE107: =AE9*AE110 -> 674243.81 | AF107: =AF9*AF110 -> 721440.87 | AG107: =AG9*AG110 -> 771941.74 | AH107: =AH9*AH110 -> 825977.66 | AI107: =AI9*AI110 -> 897605.41 | AJ107: =AJ9*AJ110 -> 960437.79 | AK107: =AK9*AK110 -> 1027668.4 | AL107: =AL9*AL110 -> 1099605.2 | ... AV107: =AV9*AV110 -> 1637207.6 | AW107: =AV107*(1-$BD$32) -> 1588091.4 | AX107: =AW107*(1-$BD$32) -> 1540448.7 | AY107: =AX107*(1-$BD$32) -> 1494235.2 | AZ107: =AY107*(1-$BD$32) -> 1449408.1 | BA107: =AZ107*(1-$BD$32) -> 1405925.9 | BB107: =BA107*(1-$BD$32) -> 1363748.1 | BC107: =BB107*(1-$BD$32) -> 1322835.7 | BD107: =BC107*(1-$BD$32) -> 1283150.6 | ... OP107: =OO107*(1-$BD$32) -> 30.087398
B108: CapEx margin | C108: =-C95/C79 -> -0.5529508 | D108: =-D95/D79 -> -0.052260491 | E108: =-E95/E79 -> -0.04643495 | F108: =-F95/F79 -> 0.017593663 | G108: =-G95/G79 -> -0.049818542 | H108: =-H95/H79 -> 0.18947528 | I108: =-I95/I79 -> -0.21292564 | J108: =-J95/J79 -> 0.023436057 | ... L108: =-L95/L79 -> 0.070984473 | Y108: =-Y95/Y79 -> -0.10237512 | Z108: =-Z95/Z79 -> 0.24747817 | AA108: =-AA95/AA79 -> 0.077750557
B109: FCF Y/Y | G109: =G107/C107-1 -> 2.1709996 | H109: =H107/D107-1 -> -0.10081252 | I109: =I107/E107-1 -> 0.14939152 | J109: =J107/F107-1 -> 0.19498416 | K109: =K107/G107-1 -> 0.1270232 | L109: =L107/H107-1 -> 1.1659201 | M109: =M107/I107-1 -> 0.40635268 | N109: =N107/J107-1 -> 0.43880222 | ... V109: =V107/R107-1 -> 0.154 | AA109: =AA107/Z107-1 -> 0.68262323
...
