Workbook

Sheet Main
A1: Tech
I6: P | J6: 137.65 | K6: 46061
I7: S/O | J7: =+Model!V18/1000 -> 2386.904 | K7: Q425
I8: MC | J8: =J6*J7 -> 328557.34
I9: Cash | J9: =+(Model!V36+Model!V37)/1000 -> 7177.143 | K9: Q425
I10: Debt | J10: 0 | K10: Q425
I12: EV | J12: =J8-J9+J10 -> 321380.19

Sheet Model
A1: Main | K1: ($ thousands)
C2: Q121 | D2: Q221 | E2: Q321 | F2: Q421 | G2: Q122 | H2: Q222 | I2: Q322 | J2: Q422 | K2: Q123 | L2: Q223 | M2: Q323 | N2: Q423 | O2: Q124 | P2: Q224 | Q2: Q324 | R2: Q424 | S2: Q125 | T2: Q225 | U2: Q325 | V2: Q425 | W2: Q126 | X2: Q226 | Y2: Q326 | Z2: Q426 | AC2: 2018 | AD2: 2019 | AE2: 2020 | AF2: 2021 | AG2: 2022 | AH2: 2023 | AI2: 2024 | AJ2: 2025 | AK2: 2026 | AL2: 2027 | AM2: 2028 | AN2: 2029 | AO2: 2030 | AP2: 2031 | AQ2: 2032 | AR2: 2033 | AS2: 2034 | AT2: 2035
B3: Revenue | C3: 341200 | D3: 375600 | E3: 392100 | F3: 432900 | G3: 446400 | H3: 473000 | I3: 477900 | J3: 508600 | K3: 525186 | L3: 533317 | M3: 558159 | N3: =AH3-SUM(K3:M3) -> 608350 | O3: 634338 | P3: 678134 | Q3: 725516 | R3: 827519 | S3: 883855 | T3: 1003697 | U3: 1181092 | V3: 1406802 | W3: 1536000 | AC3: 595409 | AD3: 742555 | AE3: 1092673 | AF3: 1541889 | AG3: 1905871 | AH3: 2225012 | AI3: 2865507 | AJ3: =SUM(S3:V3) -> 4475446 | AK3: 7198000
B4: COGS | C4: 74100 | D4: 90900 | E4: 86800 | F4: 87600 | G4: 94400 | H4: 102200 | I4: 107600 | J4: 104300 | K4: 107645 | L4: 106899 | M4: 107922 | N4: =AH4-SUM(K4:M4) -> 108639 | O4: 116256 | P4: 128562 | Q4: 146639 | R4: 174533 | S4: 172970 | T4: 192934 | U4: 207307 | V4: 215966 | AC4: 165401 | AD4: 242373 | AE4: 352547 | AF4: 339404 | AG4: 408549 | AH4: 431105 | AI4: 565990 | AJ4: =SUM(S4:V4) -> 789177
B5: Gross Profit | C5: =C3-C4 -> 267100 | D5: =D3-D4 -> 284700 | E5: =E3-E4 -> 305300 | F5: =F3-F4 -> 345300 | G5: =G3-G4 -> 352000 | H5: =H3-H4 -> 370800 | I5: =I3-I4 -> 370300 | J5: =J3-J4 -> 404300 | ... Z5: =Z3-Z4 -> 0 | AC5: =AC3-AC4 -> 430008 | AD5: =AD3-AD4 -> 500182 | AE5: =AE3-AE4 -> 740126 | AF5: =AF3-AF4 -> 1202485 | AG5: =AG3-AG4 -> 1497322 | AH5: =AH3-AH4 -> 1793907 | AI5: =AI3-AI4 -> 2299517 | AJ5: =AJ3-AJ4 -> 3686269
B6: S&M | K6: 187093 | L6: 184163 | M6: 176373 | N6: =AH6-SUM(K6:M6) -> 197363 | O6: 193177 | P6: 196809 | Q6: 209474 | R6: 288295 | S6: 236309 | T6: 243788 | U6: 274636 | V6: 302126 | AC6: 461762 | AD6: 450120 | AE6: 683701 | AF6: 614512 | AG6: 702511 | AH6: 744992 | AI6: 887755 | AJ6: =SUM(S6:V6) -> 1056859
B7: R&D | C7: 98500 | D7: 110500 | E7: 94300 | F7: 84200 | G7: 88600 | H7: 88200 | I7: 100900 | J7: 82000 | K7: 90100 | L7: 99533 | M7: 105708 | N7: =AH7-SUM(K7:M7) -> 109283 | O7: 110040 | P7: 108781 | Q7: 117555 | R7: 171502 | S7: 134889 | T7: 135043 | U7: 144191 | V7: 143554 | AC7: 285451 | AD7: 305563 | AE7: 560660 | AF7: 387487 | AG7: 359679 | AH7: 404624 | AI7: 507878 | AJ7: =SUM(S7:V7) -> 557677
B8: G&M | K8: 136233 | L8: 132648 | M8: 128173 | N8: =AH8-SUM(K8:M8) -> 127271 | O8: 133984 | P8: 138643 | Q8: 138708 | R8: 182146 | S8: 163639 | T8: 162615 | U8: 161702 | V8: 169762 | AC8: 306235 | AD8: 320943 | AE8: 669444 | AF8: 611532 | AG8: 596333 | AH8: 524325 | AI8: 593481 | AJ8: =SUM(S8:V8) -> 657718
B9: Operating expenses | C9: 381100 | D9: 430900 | E9: 397300 | F9: 404200 | G9: 391400 | H9: 412500 | I9: 432500 | J9: 422100 | K9: =SUM(K6:K8) -> 413426 | L9: =SUM(L6:L8) -> 416344 | M9: =SUM(M6:M8) -> 410254 | N9: =SUM(N6:N8) -> 433917 | O9: =SUM(O6:O8) -> 437201 | P9: =SUM(P6:P8) -> 444233 | Q9: =SUM(Q6:Q8) -> 465737 | R9: =SUM(R6:R8) -> 641943 | ... Z9: =SUM(Z6:Z8) -> 0 | AC9: =SUM(AC6:AC8) -> 1053448 | AD9: =SUM(AD6:AD8) -> 1076626 | AE9: =SUM(AE6:AE8) -> 1913805 | AF9: =SUM(AF6:AF8) -> 1613531 | AG9: =SUM(AG6:AG8) -> 1658523 | AH9: =SUM(AH6:AH8) -> 1673941 | AI9: =SUM(AI6:AI8) -> 1989114 | AJ9: =SUM(AJ6:AJ8) -> 2272254
B10: Operating income | C10: =C5-C9 -> -114000 | D10: =D5-D9 -> -146200 | E10: =E5-E9 -> -92000 | F10: =F5-F9 -> -58900 | G10: =G5-G9 -> -39400 | H10: =H5-H9 -> -41700 | I10: =I5-I9 -> -62200 | J10: =J5-J9 -> -17800 | ... Z10: =Z5-Z9 -> 0 | AC10: =AC5-AC9 -> -623440 | AD10: =AD5-AD9 -> -576444 | AE10: =AE5-AE9 -> -1173679 | AF10: =AF5-AF9 -> -411046 | AG10: =AG5-AG9 -> -161201 | AH10: =AH5-AH9 -> 119966 | AI10: =AI5-AI9 -> 310403 | AJ10: =AJ5-AJ9 -> 1414015
B11: Interest income | K11: 20853 | L11: 30310 | M11: 36864 | N11: =AH11-SUM(K11:M11) -> 44545 | O11: 43352 | P11: 46593 | Q11: 52120 | R11: 54727 | S11: 50441 | T11: 56255 | U11: 59762 | V11: 62723 | AC11: 10500 | AD11: 15090 | AE11: 4680 | AF11: 1607 | AG11: 20309 | AH11: 132572 | AI11: 196792 | AJ11: =SUM(S11:V11) -> 229181
B12: Interest expense | K12: -4136 | L12: -10341 | M12: 3122 | N12: =AH12-SUM(K12:M12) -> -4092 | O12: -13507 | P12: -11173 | Q12: -8110 | R12: 14768 | S12: -3173 | T12: 6596 | U12: 27483 | V12: -16734 | AC12: =-3440+48093-2638 -> 42015 | AD12: =-3061-3-2853 -> -5917 | AE12: =-14139+4111 -> -10028 | AF12: =-3640-75415 -> -79055 | AG12: -220135 | AH12: -15447 | AI12: -18022 | AJ12: =SUM(S12:V12) -> 14172
B13: Pretax income | C13: -120400 | D13: -144200 | E13: -100700 | F13: -123200 | G13: -99400 | H13: -176700 | I13: -122800 | J13: 37800 | K13: =K10+K11+K12 -> 20832 | L13: =L10+L11+L12 -> 30043 | M13: =M10+M11+M12 -> 79969 | N13: =N10+N11+N12 -> 106247 | O13: =O10+O11+O12 -> 110726 | P13: =P10+P11+P12 -> 140759 | Q13: =Q10+Q11+Q12 -> 157150 | R13: =R10+R11+R12 -> 80538 | ... Z13: =Z10+Z11+Z12 -> 0 | AC13: =AC10+AC11+AC12 -> -570925 | AD13: =AD10+AD11+AD12 -> -567271 | AE13: =AE10+AE11+AE12 -> -1179027 | AF13: =AF10+AF11+AF12 -> -488494 | AG13: =AG10+AG11+AG12 -> -361027 | AH13: =AH10+AH11+AH12 -> 237091 | AI13: =AI10+AI11+AI12 -> 489173 | AJ13: =AJ10+AJ11+AJ12 -> 1657368
B14: Taxes | C14: 3100 | D14: -5700 | E14: 1400 | F14: 3300 | G14: 200 | H14: 2600 | I14: 1100 | J14: 4400 | K14: 1681 | L14: 2171 | M14: 6530 | N14: =AH14-SUM(K14:M14) -> 9334 | O14: 4655 | P14: 5189 | Q14: 7809 | R14: 3602 | S14: 5599 | T14: 3596 | U14: 3753 | V14: 9776 | AC14: 9102 | AD14: 12375 | AE14: -12636 | AF14: 31885 | AG14: 10067 | AH14: 19716 | AI14: 21255 | AJ14: =SUM(S14:V14) -> 22724
B15: Net Income | C15: =C13-C14 -> -123500 | D15: =D13-D14 -> -138500 | E15: =E13-E14 -> -102100 | F15: =F13-F14 -> -126500 | G15: =G13-G14 -> -99600 | H15: =H13-H14 -> -179300 | I15: =I13-I14 -> -123900 | J15: =J13-J14 -> 33400 | ... Z15: =Z13-Z14 -> 0 | AC15: =AC13-AC14 -> -580027 | AD15: =AD13-AD14 -> -579646 | AE15: =AE13-AE14 -> -1166391 | AF15: =AF13-AF14 -> -520379 | AG15: =AG13-AG14 -> -371094 | AH15: =AH13-AH14 -> 217375 | AI15: =AI13-AI14 -> 467918 | AJ15: =AJ13-AJ14 -> 1634644
B16: Less: noncontrolling | K16: 2349 | L16: -255 | M16: 1934 | N16: =AH16-SUM(K16:M16) -> 3522 | O16: 541 | P16: 1444 | Q16: 5816 | R16: -2073 | S16: 3686 | T16: 1845 | U16: 1149 | V16: 2931 | AC16: 18098 | AD16: 8481 | AG16: 2611 | AH16: 7550 | AI16: 5728 | AJ16: =SUM(S16:V16) -> 9611
B17: Net income attributable to Palantir | C17: =C15-C16 -> -123500 | D17: =D15-D16 -> -138500 | E17: =E15-E16 -> -102100 | F17: =F15-F16 -> -126500 | G17: =G15-G16 -> -99600 | H17: =H15-H16 -> -179300 | I17: =I15-I16 -> -123900 | J17: =J15-J16 -> 33400 | ... Z17: =Z15-Z16 -> 0 | AC17: =AC15-AC16 -> -598125 | AD17: =AD15-AD16 -> -588127 | AE17: =AE15-AE16 -> -1166391 | AF17: =AF15-AF16 -> -520379 | AG17: =AG15-AG16 -> -373705 | AH17: =AH15-AH16 -> 209825 | AI17: =AI15-AI16 -> 462190 | AJ17: =AJ15-AJ16 -> 1625033 | AK17: 1460000 | AL17: =+AK17*1.33 -> 1941800
B18: S/O | C18: =C17/C19 -> 1764285.7 | D18: 1923617 | E18: 1923617 | F18: 1923617 | G18: =G17/G19 -> 1992000 | H18: =H17/H19 -> 1992222.2 | I18: 2063793 | J18: 2063793 | K18: 2107780 | L18: 2131224 | M18: 2162530 | N18: 2147446 | O18: 2213545 | P18: 2231592 | Q18: 2250032 | R18: 2250163 | S18: 2348679 | T18: 2365196 | U18: 2377167 | V18: 2386904 | AC18: 537280.39 | AD18: 576958.56 | AE18: 977722 | AF18: 1923617 | AG18: 2063793 | AH18: 2147446 | AI18: 2250163 | AJ18: 2386904
B19: EPS | C19: -0.07 | D19: =D17/D18 -> -0.07199978 | E19: =E17/E18 -> -0.053077094 | F19: =F17/F18 -> -0.065761532 | G19: -0.05 | H19: -0.09 | I19: -0.06 | J19: =J17/J18 -> 0.016183794 | K19: =K17/K18 -> 0.0079714202 | L19: =L17/L18 -> 0.01319758 | M19: =M17/M18 -> 0.033065437 | N19: =N17/N18 -> 0.043489336 | O19: =O17/O18 -> 0.047674658 | P19: =P17/P18 -> 0.060103281 | Q19: =Q17/Q18 -> 0.063787982 | ... Z19: =Z17/Z18 -> #DIV/0! | AC19: =AC17/AC18 -> -1.1132455 | AD19: =AD17/AD18 -> -1.0193574 | AE19: =AE17/AE18 -> -1.1929679 | AF19: =AF17/AF18 -> -0.27052111 | AG19: =AG17/AG18 -> -0.18107678 | AH19: =AH17/AH18 -> 0.097709093 | AI19: =AI17/AI18 -> 0.2054029 | AJ19: =AJ17/AJ18 -> 0.68081205 | AK19: 0.83
B22: Gross margin | C22: =C5/C3 -> 0.78282532 | D22: =D5/D3 -> 0.75798722 | E22: =E5/E3 -> 0.7786279 | F22: =F5/F3 -> 0.7976438 | G22: =G5/G3 -> 0.78853047 | H22: =H5/H3 -> 0.78393235 | I22: =I5/I3 -> 0.77484829 | J22: =J5/J3 -> 0.79492725 | ... Z22: =Z5/Z3 -> #DIV/0! | AC22: =AC5/AC3 -> 0.72220608 | AD22: =AD5/AD3 -> 0.6735959 | AE22: =AE5/AE3 -> 0.67735361 | AF22: =AF5/AF3 -> 0.7798778 | AG22: =AG5/AG3 -> 0.78563659 | AH22: =AH5/AH3 -> 0.80624599 | AI22: =AI5/AI3 -> 0.80248172 | AJ22: =AJ5/AJ3 -> 0.82366517 | ... AL22: =AL5/AL3 -> #DIV/0!
B23: S&M margin | C23: =C6/C$5 -> 0 | D23: =D6/D$5 -> 0 | E23: =E6/E$5 -> 0 | F23: =F6/F$5 -> 0 | G23: =G6/G$5 -> 0 | H23: =H6/H$5 -> 0 | I23: =I6/I$5 -> 0 | J23: =J6/J$5 -> 0 | ... Z23: =Z6/Z$5 -> #DIV/0! | AC23: =AC6/AC$5 -> 1.0738451 | AD23: =AD6/AD$5 -> 0.89991243 | AE23: =AE6/AE$5 -> 0.92376298 | AF23: =AF6/AF$5 -> 0.51103506 | AG23: =AG6/AG$5 -> 0.46917831 | AH23: =AH6/AH$5 -> 0.4152902 | AI23: =AI6/AI$5 -> 0.38606151 | AJ23: =AJ6/AJ$5 -> 0.28670154 | ... AL23: =AL6/AL$5 -> #DIV/0!
B24: R&D margin | C24: =C7/C$5 -> 0.36877574 | D24: =D7/D$5 -> 0.38812785 | E24: =E7/E$5 -> 0.30887651 | F24: =F7/F$5 -> 0.24384593 | G24: =G7/G$5 -> 0.25170455 | H24: =H7/H$5 -> 0.23786408 | I24: =I7/I$5 -> 0.27248177 | J24: =J7/J$5 -> 0.20281969 | ... Z24: =Z7/Z$5 -> #DIV/0! | AC24: =AC7/AC$5 -> 0.66382718 | AD24: =AD7/AD$5 -> 0.61090363 | AE24: =AE7/AE$5 -> 0.75751967 | AF24: =AF7/AF$5 -> 0.32223853 | AG24: =AG7/AG$5 -> 0.24021486 | AH24: =AH7/AH$5 -> 0.22555461 | AI24: =AI7/AI$5 -> 0.2208629 | AJ24: =AJ7/AJ$5 -> 0.15128494 | ... AL24: =AL7/AL$5 -> #DIV/0!
B25: G&M margin | C25: =C8/C$5 -> 0 | D25: =D8/D$5 -> 0 | E25: =E8/E$5 -> 0 | F25: =F8/F$5 -> 0 | G25: =G8/G$5 -> 0 | H25: =H8/H$5 -> 0 | I25: =I8/I$5 -> 0 | J25: =J8/J$5 -> 0 | ... Z25: =Z8/Z$5 -> #DIV/0! | AC25: =AC8/AC$5 -> 0.71216117 | AD25: =AD8/AD$5 -> 0.64165244 | AE25: =AE8/AE$5 -> 0.90450004 | AF25: =AF8/AF$5 -> 0.50855686 | AG25: =AG8/AG$5 -> 0.39826637 | AH25: =AH8/AH$5 -> 0.29228104 | AI25: =AI8/AI$5 -> 0.25808942 | AJ25: =AJ8/AJ$5 -> 0.17842377 | ... AL25: =AL8/AL$5 -> #DIV/0!
B26: Operating margin | C26: =C10/C3 -> -0.33411489 | D26: =D10/D3 -> -0.38924388 | E26: =E10/E3 -> -0.23463402 | F26: =F10/F3 -> -0.13605914 | G26: =G10/G3 -> -0.088261649 | H26: =H10/H3 -> -0.088160677 | I26: =I10/I3 -> -0.13015275 | J26: =J10/J3 -> -0.034998034 | ... Z26: =Z10/Z3 -> #DIV/0! | AC26: =AC10/AC3 -> -1.0470786 | AD26: =AD10/AD3 -> -0.77629805 | AE26: =AE10/AE3 -> -1.0741356 | AF26: =AF10/AF3 -> -0.26658599 | AG26: =AG10/AG3 -> -0.084581275 | AH26: =AH10/AH3 -> 0.053917013 | AI26: =AI10/AI3 -> 0.10832394 | AJ26: =AJ10/AJ3 -> 0.31594952 | ... AL26: =AL10/AL3 -> #DIV/0!
B27: Interest margin | C27: =(C11+C12)/C10 -> 0 | D27: =(D11+D12)/D10 -> 0 | E27: =(E11+E12)/E10 -> 0 | F27: =(F11+F12)/F10 -> 0 | G27: =(G11+G12)/G10 -> 0 | H27: =(H11+H12)/H10 -> 0 | I27: =(I11+I12)/I10 -> 0 | J27: =(J11+J12)/J10 -> 0 | ... Z27: =(Z11+Z12)/Z10 -> #DIV/0! | AC27: =(AC11+AC12)/AC10 -> -0.084234249 | AD27: =(AD11+AD12)/AD10 -> -0.015913081 | AE27: =(AE11+AE12)/AE10 -> 0.0045566122 | AF27: =(AF11+AF12)/AF10 -> 0.18841687 | AG27: =(AG11+AG12)/AG10 -> 1.2396077 | AH27: =(AH11+AH12)/AH10 -> 0.97631829 | AI27: =(AI11+AI12)/AI10 -> 0.57592871 | AJ27: =(AJ11+AJ12)/AJ10 -> 0.17210072 | ... AL27: =(AL11+AL12)/AL10 -> #DIV/0!
B28: Tax margin | C28: =C14/C13 -> -0.025747508 | D28: =D14/D13 -> 0.039528433 | E28: =E14/E13 -> -0.013902681 | F28: =F14/F13 -> -0.026785714 | G28: =G14/G13 -> -0.0020120724 | H28: =H14/H13 -> -0.014714205 | I28: =I14/I13 -> -0.0089576547 | J28: =J14/J13 -> 0.11640212 | ... Z28: =Z14/Z13 -> #DIV/0! | AC28: =AC14/AC13 -> -0.015942549 | AD28: =AD14/AD13 -> -0.02181497 | AE28: =AE14/AE13 -> 0.010717312 | AF28: =AF14/AF13 -> -0.06527204 | AG28: =AG14/AG13 -> -0.027884341 | AH28: =AH14/AH13 -> 0.083157944 | AI28: =AI14/AI13 -> 0.043450885 | AJ28: =AJ14/AJ13 -> 0.013710896 | ... AL28: =AL14/AL13 -> #DIV/0!
B29: Net margin | C29: =C17/C3 -> -0.3619578 | D29: =D17/D3 -> -0.36874334 | E29: =E17/E3 -> -0.26039276 | F29: =F17/F3 -> -0.29221529 | G29: =G17/G3 -> -0.22311828 | H29: =H17/H3 -> -0.37906977 | I29: =I17/I3 -> -0.25925926 | J29: =J17/J3 -> 0.065670468 | ... Z29: =Z17/Z3 -> #DIV/0! | AC29: =AC17/AC3 -> -1.0045616 | AD29: =AD17/AD3 -> -0.79203157 | AE29: =AE17/AE3 -> -1.0674657 | AF29: =AF17/AF3 -> -0.33749446 | AG29: =AG17/AG3 -> -0.19608095 | AH29: =AH17/AH3 -> 0.094302862 | AI29: =AI17/AI3 -> 0.16129432 | AJ29: =AJ17/AJ3 -> 0.36309968 | ... AL29: =AL17/AL3 -> #DIV/0!
B31: Revenue Y/Y | G31: =G3/C3-1 -> 0.30832356 | H31: =H3/D3-1 -> 0.25931842 | I31: =I3/E3-1 -> 0.21882173 | J31: =J3/F3-1 -> 0.17486717 | K31: =K3/G3-1 -> 0.17649194 | L31: =L3/H3-1 -> 0.12752008 | M31: =M3/I3-1 -> 0.16794099 | N31: =N3/J3-1 -> 0.19612662 | ... Z31: =Z3/V3-1 -> -1 | AD31: =AD3/AC3-1 -> 0.24713432 | AE31: =AE3/AD3-1 -> 0.47150447 | AF31: =AF3/AE3-1 -> 0.41111659 | AG31: =AG3/AF3-1 -> 0.23606239 | AH31: =AH3/AG3-1 -> 0.16745152 | AI31: =AI3/AH3-1 -> 0.28786137 | AJ31: =AJ3/AI3-1 -> 0.56183391 | AK31: =AK3/AJ3-1 -> 0.60833133 | AL31: =AL3/AK3-1 -> -1
B35: Net Cash | F35: =F36+F37 -> 2601067 | G35: =G36+G37 -> 0 | H35: =H36+H37 -> 0 | I35: =I36+I37 -> 0 | J35: =J36+J37 -> 2662470 | K35: =K36+K37 -> 0 | L35: =L36+L37 -> 0 | M35: =M36+M37 -> 0 | ... Z35: =Z36+Z37 -> 0 | AC35: =AC36+AC37 -> 1284335 | AD35: =AD36+AD37-AD52 -> 988522 | AE35: =AE36+AE37-AE52 -> 1925853 | AF35: =AF36+AF37 -> 2601067 | AG35: =AG36+AG37 -> 2662470 | AH35: =AH36+AH37 -> 3674179 | AI35: =AI36+AI37 -> 5229987 | AJ35: =AJ36+AJ37 -> 7177143 | AK35: =AK36+AK37 -> 0 | AL35: =AL36+AL37 -> 0
B36: Cash | F36: =2290674+36628+39612 -> 2366914 | J36: =2598540+16244+12551 -> 2627335 | N36: 831047 | O36: 520388 | P36: 512659 | Q36: 768710 | R36: 2098524 | S36: 993464 | T36: 929547 | U36: 1615967 | V36: 1423896 | AC36: =1116342+10484+140009+17500 -> 1284335 | AD36: =1079154+52099+270709+26145 -> 1428107 | AE36: =2011323+37285+79538 -> 2128146 | AF36: =2290674+36628+39612 -> 2366914 | AG36: =2598540+16244+12551 -> 2627335 | AH36: 831047 | AI36: 2098524 | AJ36: 1423896
B37: Securities | F37: 234153 | J37: 35135 | N37: 2843132 | O37: 3347512 | P37: 3485800 | Q37: 3795949 | R37: 3131463 | S37: 4437225 | T37: 5070875 | U37: 4821850 | V37: 5753247 | AF37: 234153 | AG37: 35135 | AH37: 2843132 | AI37: 3131463 | AJ37: 5753247
B38: A/R | F38: 190923 | J38: 258346 | N38: 364784 | O38: 486986 | P38: 659339 | Q38: 668110 | R38: 575048 | S38: 725205 | T38: 747484 | U38: 1005910 | V38: 1042065 | AC38: 19187 | AD38: 50315 | AE38: 156932 | AF38: 190923 | AG38: 258346 | AH38: 364784 | AI38: 575048 | AJ38: 1042065
B39: Prepaids | F39: 110872 | J39: 133312 | N39: 99655 | O39: 81178 | P39: 115712 | Q39: 119193 | R39: 129254 | S39: 126705 | T39: 142487 | U39: 142429 | V39: 139066 | AC39: 74063 | AD39: 32585 | AE39: 51889 | AF39: 110872 | AG39: 133312 | AH39: 99655 | AI39: 129254 | AJ39: 139066
B40: PP&A | F40: 31304 | J40: 69170 | N40: 47758 | O40: 46906 | P40: 43483 | Q40: 40345 | R40: 39638 | S40: 39669 | T40: 43523 | U40: 45706 | V40: 51960 | AC40: 30034 | AD40: 31589 | AE40: 29541 | AF40: 31304 | AG40: 69170 | AH40: 47758 | AI40: 39638 | AJ40: 51960
B41: Operating lease ROU | F41: 216898 | J41: 200240 | N41: 182863 | O41: 173707 | P41: 213453 | Q41: 211570 | R41: 200740 | S41: 209348 | T41: 203474 | U41: 204315 | V41: 200105 | AE41: 217075 | AF41: 216898 | AG41: 200240 | AH41: 182863 | AI41: 200740 | AJ41: 200105
B42: Other assets | F42: 96386 | J42: 137701 | N42: 153186 | O42: 150402 | P42: 161434 | Q42: 164220 | R42: 166217 | S42: 205301 | T42: 228298 | U42: 277783 | V42: 290153 | AC42: 23346 | AD42: 51429 | AE42: 106921 | AF42: 96386 | AG42: 137701 | AH42: 153186 | AI42: 166217 | AJ42: 290153
B43: Total assets | F43: =SUM(F36:F42) -> 3247450 | G43: =SUM(G36:G42) -> 0 | H43: =SUM(H36:H42) -> 0 | I43: =SUM(I36:I42) -> 0 | J43: =SUM(J36:J42) -> 3461239 | K43: =SUM(K36:K42) -> 0 | L43: =SUM(L36:L42) -> 0 | M43: =SUM(M36:M42) -> 0 | ... Z43: =SUM(Z36:Z42) -> 0 | AC43: =SUM(AC36:AC42) -> 1430965 | AD43: =SUM(AD36:AD42) -> 1594025 | AE43: =SUM(AE36:AE42) -> 2690504 | AF43: =SUM(AF36:AF42) -> 3247450 | AG43: =SUM(AG36:AG42) -> 3461239 | AH43: =SUM(AH36:AH42) -> 4522425 | AI43: =SUM(AI36:AI42) -> 6340884 | AJ43: =SUM(AJ36:AJ42) -> 8900492 | ... AL43: =SUM(AL36:AL42) -> 0
B44: A/P | F44: 74907 | J44: 44788 | N44: 12122 | O44: 35634 | P44: 67345 | Q44: 27021 | R44: 103 | S44: 2330 | T44: 10774 | U44: 67503 | V44: 8064 | AC44: 27399 | AD44: 51735 | AE44: 16358 | AF44: 74907 | AG44: 44788 | AH44: 12122 | AI44: 103 | AJ44: 8064
B45: Accrued liabilities | F45: 155806 | J45: 172715 | N45: 222991 | O45: 206034 | P45: 195489 | Q45: 265244 | R45: 427046 | S45: 371061 | T45: 393623 | U45: 381737 | V45: 355624 | AC45: 123745 | AD45: 126620 | AE45: 158546 | AF45: 155806 | AG45: 172715 | AH45: 222991 | AI45: 427046 | AJ45: 355624
B46: Deferred revenue | F46: 227816 | J46: 183350 | N46: 246901 | O46: 237195 | P46: 278441 | Q46: 236608 | R46: 259624 | S46: 318556 | T46: 376784 | U46: 316722 | V46: 408963 | AC46: 239116 | AD46: 186105 | AE46: 189520 | AF46: 227816 | AG46: 183350 | AH46: 246901 | AI46: 259624 | AJ46: 408963
B47: Customer deposits | F47: 161605 | J47: 141989 | N47: 209828 | O47: 217634 | P47: 221519 | Q47: 366946 | R47: 265252 | S47: 231077 | T47: 262994 | U47: 368170 | V47: 357066 | AC47: 141642 | AD47: 364138 | AE47: 210320 | AF47: 161605 | AG47: 141989 | AH47: 209828 | AI47: 265252 | AJ47: 357066
B48: Oprating lease liabilities | F48: 39927 | J48: 45099 | N48: 54176 | O48: 54056 | P48: 44125 | Q48: 47637 | R48: 43993 | S48: 44419 | T48: 45465 | U48: 46271 | V48: 45864 | AE48: 29079 | AF48: 39927 | AG48: 45099 | AH48: 54176 | AI48: 43993 | AJ48: 45864
B49: Defered revenue, noncurrent | F49: 40217 | J49: 9965 | N49: 28047 | O49: 20722 | P49: 15649 | Q49: 7825 | R49: 39885 | S49: 36372 | T49: 44638 | U49: 43901 | V49: 46216 | AC49: =169978+37868 -> 207846 | AD49: =77030+34685 -> 111715 | AE49: 50525 | AF49: 40217 | AG49: 9965 | AH49: 28047 | AI49: 39885 | AJ49: 46216
B50: Customer deposits, noncurrent | F50: 33699 | J50: 3936 | N50: 1477 | O50: 1651 | P50: 1527 | Q50: 3681 | R50: 1663 | S50: 1463 | T50: 1491 | U50: 1570 | V50: 18 | AC50: 106376 | AD50: 167538 | AE50: 81513 | AF50: 33699 | AG50: 3936 | AH50: 1477 | AI50: 1663 | AJ50: 18
B51: Operating lease liabilities, noncurrent | F51: 220146 | J51: 204305 | N51: 175216 | O51: 163013 | P51: 214334 | Q51: 207278 | R51: 195226 | S51: 200177 | T51: 192347 | U51: 189165 | V51: 183474 | AE51: 229800 | AF51: 220146 | AG51: 204305 | AH51: 175216 | AI51: 195226 | AJ51: 183474
B52: ONCL | F52: 2297 | J52: 12655 | N52: 10702 | O52: 9968 | P52: 15645 | Q52: 14495 | R52: 13685 | S52: 12489 | T52: 12008 | U52: 10652 | V52: 7092 | AC52: =76069+477 -> 76546 | AD52: =396065+42628+892 -> 439585 | AE52: =197977+4316 -> 202293 | AF52: 2297 | AG52: 12655 | AH52: 10702 | AI52: 13685 | AJ52: 7092
B53: Total liabilities | F53: =SUM(F44:F52) -> 956420 | G53: =SUM(G44:G52) -> 0 | H53: =SUM(H44:H52) -> 0 | I53: =SUM(I44:I52) -> 0 | J53: =SUM(J44:J52) -> 818802 | K53: =SUM(K44:K52) -> 0 | L53: =SUM(L44:L52) -> 0 | M53: =SUM(M44:M52) -> 0 | ... Z53: =SUM(Z44:Z52) -> 0 | AC53: =SUM(AC44:AC52) -> 922670 | AD53: =SUM(AD44:AD52) -> 1447436 | AE53: =SUM(AE44:AE52) -> 1167954 | AF53: =SUM(AF44:AF52) -> 956420 | AG53: =SUM(AG44:AG52) -> 818802 | AH53: =SUM(AH44:AH52) -> 961460 | AI53: =SUM(AI44:AI52) -> 1246477 | AJ53: =SUM(AJ44:AJ52) -> 1412381 | ... AL53: =SUM(AL44:AL52) -> 0
B54: Common stock | F54: 2027 | J54: 2099 | N54: 2200 | O54: 2227 | P54: 2238 | Q54: 2270 | R54: 2339 | S54: 2360 | T54: 2372 | U54: 2383 | V54: 2391 | AE54: 1792 | AF54: 2027 | AG54: 2099 | AH54: 2200 | AI54: 2339 | AJ54: 2391
B55: Additional paid-in capital | F55: 7777085 | J55: 8427998 | N55: 9122173 | O55: 9322803 | P55: 9463178 | Q55: 9757380 | R55: 10193970 | S55: 10398181 | T55: 10568473 | U55: 10747603 | V55: 10933325 | AC55: =-148621+1627737+570+2087560+172163 -> 3739409 | AD55: =-38895+1857331+588+2093662+33569 -> 3946255 | AE55: 6488857 | AF55: 7777085 | AG55: 8427998 | AH55: 9122173 | AI55: 10193970 | AJ55: 10933325
B56: Accumulated other income | F56: -2349 | J56: -5333 | N56: 801 | O56: -5720 | P56: -4935 | Q56: 4925 | R56: -5611 | S56: -2994 | T56: 4721 | U56: 11537 | V56: 13942 | AC56: 762 | AD56: -703 | AE56: -2745 | AF56: -2349 | AG56: -5333 | AH56: 801 | AI56: -5611 | AJ56: 13942
B57: Accumulated deficit | F57: -5485733 | J57: -5859438 | N57: -5649613 | O57: -5544083 | P57: -5409957 | Q57: -5266432 | R57: -5187423 | S57: -4973392 | T57: -4646665 | U57: -4171066 | V57: -3562390 | AC57: -3231876 | AD57: -3798963 | AE57: -4965354 | AF57: -5485733 | AG57: -5859438 | AH57: -5649613 | AI57: -5187423 | AJ57: -3562390
B58: Noncontrolling | J58: 77111 | N58: 85404 | O58: 85945 | P58: 87282 | Q58: 93219 | R58: 91132 | S58: 94818 | T58: 96663 | U58: 97812 | V58: 100743 | AG58: 77111 | AH58: 85404 | AI58: 91132 | AJ58: 100743
B59: SE | F59: =SUM(F54:F58) -> 2291030 | G59: =SUM(G54:G58) -> 0 | H59: =SUM(H54:H58) -> 0 | I59: =SUM(I54:I58) -> 0 | J59: =SUM(J54:J58) -> 2642437 | K59: =SUM(K54:K58) -> 0 | L59: =SUM(L54:L58) -> 0 | M59: =SUM(M54:M58) -> 0 | ... Z59: =SUM(Z54:Z58) -> 0 | AC59: =SUM(AC54:AC58) -> 508295 | AD59: =SUM(AD54:AD58) -> 146589 | AE59: =SUM(AE54:AE58) -> 1522550 | AF59: =SUM(AF54:AF58) -> 2291030 | AG59: =SUM(AG54:AG58) -> 2642437 | AH59: =SUM(AH54:AH58) -> 3560965 | AI59: =SUM(AI54:AI58) -> 5094407 | AJ59: =SUM(AJ54:AJ58) -> 7488011 | ... AL59: =SUM(AL54:AL58) -> 0
B60: L+SE | F60: =F53+F59 -> 3247450 | G60: =G53+G59 -> 0 | H60: =H53+H59 -> 0 | I60: =I53+I59 -> 0 | J60: =J53+J59 -> 3461239 | K60: =K53+K59 -> 0 | L60: =L53+L59 -> 0 | M60: =M53+M59 -> 0 | ... Z60: =Z53+Z59 -> 0 | AC60: =AC53+AC59 -> 1430965 | AD60: =AD53+AD59 -> 1594025 | AE60: =AE53+AE59 -> 2690504 | AF60: =AF53+AF59 -> 3247450 | AG60: =AG53+AG59 -> 3461239 | AH60: =AH53+AH59 -> 4522425 | AI60: =AI53+AI59 -> 6340884 | AJ60: =AJ53+AJ59 -> 8900392 | ... AL60: =AL53+AL59 -> 0
B64: Reported NI | C64: =C15 -> -123500 | D64: =D15 -> -138500 | E64: =E15 -> -102100 | F64: =F15 -> -126500 | G64: =G15 -> -99600 | H64: =H15 -> -179300 | I64: =I15 -> -123900 | J64: =J15 -> 33400 | ... Z64: =Z15 -> 0 | AC64: =AC15 -> -580027 | AD64: =AD15 -> -579646 | AE64: =AE15 -> -1166391 | AF64: =AF15 -> -520379 | AG64: =AG15 -> -371094 | AH64: =AH15 -> 217375 | AI64: =AI15 -> 467918 | AJ64: =AJ15 -> 1634644 | ... AL64: =AL15 -> 0
B65: GAAP NI | K65: 19151 | L65: 27872 | M65: 73439 | N65: 96913 | O65: 106071 | P65: 135570 | Q65: 149341 | R65: 76936 | S65: 217717 | T65: 328572 | U65: 476748 | V65: 611607 | AC65: -580027 | AD65: -579646 | AE65: -1166391 | AF65: -520379 | AG65: -371094 | AH65: 217375 | AI65: 467918 | AJ65: 1634644
B66: D&A | K66: 8320 | L66: 8174 | M66: 8888 | N66: 7972 | O66: 8438 | P66: 8056 | Q66: 8087 | R66: 7006 | S66: 6622 | T66: 6530 | U66: 5975 | V66: 7018 | AC66: 13910 | AD66: 12255 | AE66: 13871 | AF66: 14897 | AG66: 22522 | AH66: 33354 | AI66: 31587 | AJ66: 26145
B67: Stock-based compensation | K67: 114714 | L67: 152701 | M67: 75880 | N67: 132608 | O67: 125651 | P67: 141764 | Q67: 142425 | R67: 281798 | S67: 155339 | T67: 159971 | U67: 172318 | V67: 196405 | AC67: 248503 | AD67: 241970 | AE67: 1270702 | AF67: 778215 | AG67: 564798 | AH67: 475903 | AI67: 691638 | AJ67: 684033
B68: Noncash operating lease expense | K68: 10836 | L68: 11603 | M68: 12371 | N68: 12209 | P68: 0 | Q68: 32041 | R68: 9198 | T68: 0 | U68: 0 | V68: 0 | AE68: 35049 | AF68: 33821 | AG68: 40309 | AH68: 47019 | AI68: 41239 | AJ68: 0
B69: Gains from securities | K69: 8508 | L69: 11534 | M69: -8232 | N69: 1350 | O69: 12354 | P69: 7688 | Q69: 5979 | R69: -6715 | S69: 10688 | T69: -11140 | U69: 5457 | V69: 16223 | AC69: -48093 | AD69: =3+224 -> 227 | AF69: 73311 | AG69: 272108 | AH69: 13160 | AI69: 19306 | AJ69: 21228
B70: Noncash consideration | K70: -7596 | L70: -18888 | M70: -8368 | N70: -11757 | O70: -11907 | P70: -14577 | Q70: -8305 | R70: -17732 | S70: -17313 | T70: -7128 | U70: -7612 | V70: -5191 | AG70: -15537 | AH70: -46609 | AI70: -52521 | AJ70: -37244
B71: Other | K71: -6670 | L71: -4418 | M71: -2240 | N71: -20927 | O71: 5592 | P71: 5759 | Q71: 7764 | R71: 5680 | S71: 3531 | T71: 23002 | U71: -10700 | V71: -203 | AC71: =420+23700 -> 24120 | AD71: =2545+23407 -> 25952 | AE71: =-20385+4280 -> -16105 | AF71: =2722+43316 -> 46038 | AG71: -28152 | AH71: -34255 | AI71: 24795 | AJ71: 15630
B72: A/R | K72: 2709 | L72: -301020 | M72: 138559 | N72: 53593 | O72: -121884 | P72: -176427 | Q72: -13388 | R72: 100542 | S72: -134959 | T72: -28542 | U72: -259476 | V72: -27452 | AC72: -10483 | AD72: -23905 | AE72: -108476 | AF72: -35237 | AG72: -72819 | AH72: -106159 | AI72: -211157 | AJ72: -450429
B73: Prepaids | K73: 1252 | L73: -4026 | M73: 2699 | N73: -6122 | O73: 22924 | P73: -20127 | Q73: -22344 | R73: 26749 | S73: 40730 | T73: -48037 | U73: 57650 | V73: 1636 | AC73: -19361 | AD73: 18806 | AE73: -18565 | AF73: -10929 | AG73: -24811 | AH73: -6197 | AI73: 7202 | AJ73: 51979
B74: Other assets | K74: -4551 | L74: 10122 | M74: -3630 | N74: 1301 | P74: 0 | Q74: 4056 | R74: 625 | T74: 0 | U74: 0 | V74: 0 | AC74: -3424 | AD74: -29447 | AE74: -8605 | AF74: -3345 | AG74: 6033 | AH74: 3242 | AI74: 4681 | AJ74: 0
B75: A/P and accrued liabilities | K75: -39921 | L75: 93293 | M75: -85759 | N75: 53450 | O75: 4704 | P75: 18120 | Q75: -15114 | R75: 89083 | S75: 22395 | T75: 25807 | U75: 42380 | V75: -85923 | AC75: =10968+26424 -> 37392 | AD75: =23424+3733 -> 27157 | AE75: -34681 | AF75: 57767 | AG75: =-29859+5527 -> -24332 | AH75: =-31832+52895 -> 21063 | AI75: =-18841+115634 -> 96793 | AJ75: 4659
B76: Deferred revenue | K76: 4271 | L76: -34819 | M76: 33100 | N76: 76960 | P76: 0 | Q76: 42149 | R76: -19793 | T76: 0 | U76: 0 | V76: 0 | AC76: 173744 | AD76: -134396 | AE76: 38505 | AF76: 15245 | AG76: -61154 | AH76: 79512 | AI76: 22356 | AJ76: 0
B77: Customer deposits | K77: 43238 | L77: -21775 | M77: 43001 | N77: -117 | P77: 0 | Q77: -27117 | R77: 81557 | T77: 0 | U77: 0 | V77: 0 | AC77: 126028 | AD77: 279226 | AE77: -30905 | AF77: 24732 | AG77: -49471 | AH77: 64347 | AI77: 54440 | AJ77: 0
B78: Operating lease liabilities | K78: 43631 | L78: -31825 | M78: 72466 | N78: -133902 | P78: 0 | Q78: 159457 | R78: -208423 | T78: 0 | U78: 0 | V78: 0 | AE78: -230873 | AF78: -104944 | AG78: -34590 | AH78: -49630 | AI78: -48966 | AJ78: 0
B79: Contract liabilities | K79: -10536 | L79: -13242 | M79: -13989 | N79: 37767 | O79: -6849 | P79: 40118 | Q79: -68474 | R79: 35205 | S79: 18760 | T79: 101906 | U79: 39488 | V79: 78534 | AE79: -43639 | AF79: -32156 | AJ79: 238688
B80: Other liabilities | K80: 20 | L80: 6486 | M80: -6322 | N80: -126 | O80: -15515 | P80: -1757 | Q80: 23215 | R80: -1389 | S80: -13247 | T80: -11690 | U80: -14564 | V80: -15359 | AC80: -1321 | AD80: -3414 | AE80: 3505 | AF80: -3185 | AG80: -73 | AH80: 58 | AI80: 4554 | AJ80: -54860
B81: CFFO | C81: =SUM(C65:C80) -> 0 | D81: =SUM(D65:D80) -> 0 | E81: =SUM(E65:E80) -> 0 | F81: =SUM(F65:F80) -> 0 | G81: =SUM(G65:G80) -> 0 | H81: =SUM(H65:H80) -> 0 | I81: =SUM(I65:I80) -> 0 | J81: =SUM(J65:J80) -> 0 | ... Z81: =SUM(Z65:Z80) -> 0 | AC81: =SUM(AC65:AC80) -> -39012 | AD81: =SUM(AD65:AD80) -> -165215 | AE81: =SUM(AE65:AE80) -> -296608 | AF81: =SUM(AF65:AF80) -> 333851 | AG81: =SUM(AG65:AG80) -> 223737 | AH81: =SUM(AH65:AH80) -> 712183 | AI81: =SUM(AI65:AI80) -> 1153865 | AJ81: =SUM(AJ65:AJ80) -> 2134473 | ... AL81: =SUM(AL65:AL80) -> 0
B82: CapEx | K82: -4755 | L82: -3934 | M82: -1565 | N82: -4860 | O82: -2664 | P82: -2879 | Q82: -3985 | R82: -3106 | S82: -6184 | T82: -7634 | U82: -6792 | V82: -13272 | AC82: -13004 | AD82: -13096 | AE82: -12236 | AF82: -12627 | AG82: -40027 | AH82: -15114 | AI82: -12634 | AJ82: -33882
B83: Purchase of securities | K83: -2310367 | L83: -626572 | M83: -1854731 | N83: -844736 | O83: -1260327 | P83: -523788 | Q83: -1634584 | R83: -1977214 | S83: -1704720 | T83: -871511 | U83: -3515282 | V83: -1610547 | AC83: -2400 | AF83: -308315 | AG83: -124500 | AH83: -5636406 | AI83: -5395913 | AJ83: -7702060
B84: Proceeds from securities | K84: 709459 | L84: 239407 | M84: 1660032 | N84: 280370 | O84: 751746 | P84: 381789 | Q84: 1317843 | R84: 2622129 | S84: 350627 | T84: 302135 | U84: 3707565 | V84: 665988 | AC84: 8620 | AD84: -25868 | AF84: 851 | AG84: 52319 | AH84: 2889268 | AI84: 5073507 | AJ84: 5026315
B85: Other | K85: 51072 | L85: 0 | M85: 0 | N85: 0 | P85: -4000 | Q85: 0 | R85: -1615 | S85: -30000 | T85: -40000 | U85: -3924 | V85: 0 | AD85: 17000 | AE85: -2684 | AF85: =-50941-23009-3871 -> -77821 | AG85: 66781 | AH85: 51072 | AI85: -5615 | AJ85: =-72924-1000 -> -73924
B86: CFFI | C86: =SUM(C82:C85) -> 0 | D86: =SUM(D82:D85) -> 0 | E86: =SUM(E82:E85) -> 0 | F86: =SUM(F82:F85) -> 0 | G86: =SUM(G82:G85) -> 0 | H86: =SUM(H82:H85) -> 0 | I86: =SUM(I82:I85) -> 0 | J86: =SUM(J82:J85) -> 0 | ... Z86: =SUM(Z82:Z85) -> 0 | AC86: =SUM(AC82:AC85) -> -6784 | AD86: =SUM(AD82:AD85) -> -21964 | AE86: =SUM(AE82:AE85) -> -14920 | AF86: =SUM(AF82:AF85) -> -397912 | AG86: =SUM(AG82:AG85) -> -45427 | AH86: =SUM(AH82:AH85) -> -2711180 | AI86: =SUM(AI82:AI85) -> -340655 | AJ86: =SUM(AJ82:AJ85) -> -2783551 | ... AL86: =SUM(AL82:AL85) -> 0
B87: Exercise of common stock options | K87: 25924 | L87: 90349 | M87: 50556 | N87: 51409 | O87: 83840 | P87: 16030 | Q87: 170337 | R87: 475189 | S87: 66584 | T87: 28617 | U87: 25638 | V87: 8268 | AC87: 12671 | AD87: 16897 | AE87: 298829 | AF87: 507455 | AG87: 86089 | AH87: 218238 | AI87: 745396 | AJ87: 129107
B88: Repurchases of common stock | L88: 0 | M88: 0 | N88: 0 | O88: -9000 | P88: -17699 | Q88: -18899 | R88: -18598 | S88: -17998 | T88: -18596 | U88: -19195 | V88: -19196 | AC88: -7706 | AD88: -11202 | AI88: -64196 | AJ88: -74985
B89: Taxes paid related to net share settlement of equity awards | L89: 0 | M89: 0 | N89: 0 | P89: 0 | Q89: 0 | R89: -218280 | S89: -77573 | T89: -3544 | U89: 0 | V89: 0 | AI89: -218280 | AJ89: -81117
B90: Other | K90: 59 | L90: 335 | M90: 384 | N90: -177 | O90: 408 | P90: -306 | Q90: -11 | R90: 353 | S90: 90 | T90: -27 | U90: -8 | V90: 30 | AC90: =96480-56491+1200 -> 41189 | AD90: =100000+544413-150000+7500-168000-13873-1202 -> 318838 | AE90: =942529+199369-400000-4274 -> 737624 | AF90: =-200000-708 -> -200708 | AG90: -93 | AH90: 601 | AI90: 444 | AJ90: 85
B91: CFFF | C91: =SUM(C87:C90) -> 0 | D91: =SUM(D87:D90) -> 0 | E91: =SUM(E87:E90) -> 0 | F91: =SUM(F87:F90) -> 0 | G91: =SUM(G87:G90) -> 0 | H91: =SUM(H87:H90) -> 0 | I91: =SUM(I87:I90) -> 0 | J91: =SUM(J87:J90) -> 0 | ... Z91: =SUM(Z87:Z90) -> 0 | AC91: =SUM(AC87:AC90) -> 46154 | AD91: =SUM(AD87:AD90) -> 324533 | AE91: =SUM(AE87:AE90) -> 1036453 | AF91: =SUM(AF87:AF90) -> 306747 | AG91: =SUM(AG87:AG90) -> 85996 | AH91: =SUM(AH87:AH90) -> 218839 | AI91: =SUM(AI87:AI90) -> 463364 | AJ91: =SUM(AJ87:AJ90) -> -26910 | ... AL91: =SUM(AL87:AL90) -> 0
B92: FX adj | K92: 2676 | L92: -4531 | M92: -258 | N92: 5043 | O92: -4024 | P92: -924 | Q92: 5908 | R92: -7705 | S92: 3980 | T92: 7538 | U92: -2074 | V92: -1967 | AC92: -3703 | AD92: -2227 | AE92: 1259 | AF92: -3918 | AG92: -3885 | AH92: 2930 | AI92: -6745 | AJ92: 7477
B93: CF | C93: =C81+C86+C91+C92 -> 0 | D93: =D81+D86+D91+D92 -> 0 | E93: =E81+E86+E91+E92 -> 0 | F93: =F81+F86+F91+F92 -> 0 | G93: =G81+G86+G91+G92 -> 0 | H93: =H81+H86+H91+H92 -> 0 | I93: =I81+I86+I91+I92 -> 0 | J93: =J81+J86+J91+J92 -> 0 | ... Z93: =Z81+Z86+Z91+Z92 -> 0 | AC93: =AC81+AC86+AC91+AC92 -> -3345 | AD93: =AD81+AD86+AD91+AD92 -> 135127 | AE93: =AE81+AE86+AE91+AE92 -> 726184 | AF93: =AF81+AF86+AF91+AF92 -> 238768 | AG93: =AG81+AG86+AG91+AG92 -> 260421 | AH93: =AH81+AH86+AH91+AH92 -> -1777228 | AI93: =AI81+AI86+AI91+AI92 -> 1269829 | AJ93: =AJ81+AJ86+AJ91+AJ92 -> -668511 | ... AL93: =AL81+AL86+AL91+AL92 -> 0
B94: BOP Cash | D94: =C95 -> 0 | E94: =D95 -> 0 | F94: =E95 -> 0 | G94: =F95 -> 0 | H94: =G95 -> 0 | I94: =H95 -> 0 | J94: =I95 -> 0 | K94: 2627335 | L94: =K95 -> 1288779 | M94: =L95 -> 875605 | N94: =M95 -> 1061886 | O94: =N95 -> 850107 | P94: =O95 -> 539665 | Q94: =P95 -> 532075 | R94: =Q95 -> 788456 | S94: =R95 -> 2119936 | ... Z94: =Y95 -> 1451425 | AC94: 1270180 | AD94: =AC95 -> 1266835 | AE94: =AD95 -> 1401962 | AF94: =AE95 -> 2128146 | AG94: =AF95 -> 2366914 | AH94: =AG95 -> 2627335 | AI94: =AH95 -> 850107 | AJ94: =AI95 -> 2119936 | AK94: =AJ95 -> 1451425 | AL94: =AK95 -> 1451425
B95: EOP Cash | C95: =C94+C93 -> 0 | D95: =D94+D93 -> 0 | E95: =E94+E93 -> 0 | F95: =F94+F93 -> 0 | G95: =G94+G93 -> 0 | H95: =H94+H93 -> 0 | I95: =I94+I93 -> 0 | J95: =J94+J93 -> 0 | ... Z95: =Z94+Z93 -> 1451425 | AC95: =AC94+AC93 -> 1266835 | AD95: =AD94+AD93 -> 1401962 | AE95: =AE94+AE93 -> 2128146 | AF95: =AF94+AF93 -> 2366914 | AG95: =AG94+AG93 -> 2627335 | AH95: =AH94+AH93 -> 850107 | AI95: =AI94+AI93 -> 2119936 | AJ95: =AJ94+AJ93 -> 1451425 | ... AL95: =AL94+AL93 -> 1451425
B97: FCF | C97: =C81+C82 -> 0 | D97: =D81+D82 -> 0 | E97: =E81+E82 -> 0 | F97: =F81+F82 -> 0 | G97: =G81+G82 -> 0 | H97: =H81+H82 -> 0 | I97: =I81+I82 -> 0 | J97: =J81+J82 -> 0 | ... Z97: =Z81+Z82 -> 0 | AC97: =AC81+AC82 -> -52016 | AD97: =AD81+AD82 -> -178311 | AE97: =AE81+AE82 -> -308844 | AF97: =AF81+AF82 -> 321224 | AG97: =AG81+AG82 -> 183710 | AH97: =AH81+AH82 -> 697069 | AI97: =AI81+AI82 -> 1141231 | AJ97: =AJ81+AJ82 -> 2100591 | ... AL97: =AL81+AL82 -> 0
B98: CapEx margin | C98: =-C82/C65 -> #DIV/0! | D98: =-D82/D65 -> #DIV/0! | E98: =-E82/E65 -> #DIV/0! | F98: =-F82/F65 -> #DIV/0! | G98: =-G82/G65 -> #DIV/0! | H98: =-H82/H65 -> #DIV/0! | I98: =-I82/I65 -> #DIV/0! | J98: =-J82/J65 -> #DIV/0! | ... Z98: =-Z82/Z65 -> #DIV/0! | AC98: =-AC82/AC65 -> -0.022419646 | AD98: =-AD82/AD65 -> -0.0225931 | AE98: =-AE82/AE65 -> -0.010490479 | AF98: =-AF82/AF65 -> -0.024265007 | AG98: =-AG82/AG65 -> -0.10786216 | AH98: =-AH82/AH65 -> 0.069529615 | AI98: =-AI82/AI65 -> 0.027000457 | AJ98: =-AJ82/AJ65 -> 0.020727449 | ... AL98: =-AL82/AL65 -> #DIV/0!
B99: FCF per Share | AC99: =AC97/AC18 -> -0.096813509 | AD99: =AD97/AD18 -> -0.30905339 | AE99: =AE97/AE18 -> -0.3158812 | AF99: =AF97/AF18 -> 0.16698958 | AG99: =AG97/AG18 -> 0.08901571 | AH99: =AH97/AH18 -> 0.32460374 | AI99: =AI97/AI18 -> 0.50717704 | AJ99: =AJ97/AJ18 -> 0.88004838 | ... AL99: =AL97/AL18 -> #DIV/0!
B100: FCF Yield | AC100: =AC99/Main!$J$6 -> -0.00070333097 | AD100: =AD99/Main!$J$6 -> -0.0022452117 | AE100: =AE99/Main!$J$6 -> -0.0022948144 | AF100: =AF99/Main!$J$6 -> 0.0012131463 | AG100: =AG99/Main!$J$6 -> 0.00064668151 | AH100: =AH99/Main!$J$6 -> 0.0023581819 | AI100: =AI99/Main!$J$6 -> 0.0036845408 | AJ100: =AJ99/Main!$J$6 -> 0.0063933773 | ... AL100: =AL99/Main!$J$6 -> #DIV/0!
B102: Government revenue | K102: 289070 | L102: 301505 | M102: 307603 | N102: =AH102-SUM(K102:M102) -> 324037 | O102: 335373 | P102: 370767 | Q102: 408341 | R102: =AI102-SUM(O102:Q102) -> 455124 | S102: 486963 | T102: 552983 | U102: 632676 | AC102: 255131 | AD102: 345521 | AE102: 610198 | AF102: 897356 | AG102: 1071776 | AH102: 1222215 | AI102: 1569605
B103: Commercial revenue | K103: 236116 | L103: 231812 | M103: 250556 | N103: =AH103-SUM(K103:M103) -> 284313 | O103: 298965 | P103: 307367 | Q103: 317175 | R103: =AI103-SUM(O103:Q103) -> 372395 | S103: 396892 | T103: 450714 | U103: 548416 | AC103: 340278 | AD103: 397034 | AE103: 482475 | AF103: 644533 | AG103: 834095 | AH103: 1002797 | AI103: 1295902
B104: Total Revenue | C104: =SUM(C102:C103) -> 0 | D104: =SUM(D102:D103) -> 0 | E104: =SUM(E102:E103) -> 0 | F104: =SUM(F102:F103) -> 0 | G104: =SUM(G102:G103) -> 0 | H104: =SUM(H102:H103) -> 0 | I104: =SUM(I102:I103) -> 0 | J104: =SUM(J102:J103) -> 0 | ... Z104: =SUM(Z102:Z103) -> 0 | AC104: =SUM(AC102:AC103) -> 595409 | AD104: =SUM(AD102:AD103) -> 742555 | AE104: =SUM(AE102:AE103) -> 1092673 | AF104: =SUM(AF102:AF103) -> 1541889 | AG104: =SUM(AG102:AG103) -> 1905871 | AH104: =SUM(AH102:AH103) -> 2225012 | AI104: =SUM(AI102:AI103) -> 2865507 | AJ104: =SUM(AJ102:AJ103) -> 0 | ... AL104: =SUM(AL102:AL103) -> 0
B105: Government expenses | K105: =+K102-166233 -> 122837 | L105: =+L102-174230 -> 127275 | M105: =M102-185867 -> 121736 | N105: =AH105-SUM(K105:M105) -> 125397 | O105: 135985 | P105: 139373 | Q105: =+Q102-243227 -> 165114 | R105: =AI105-SUM(O105:Q105) -> 180693 | S105: 186003 | T105: 202571 | U105: 214967 | AC105: =+AC102-30963 -> 224168 | AD105: =+AD102-79606 -> 265915 | AE105: =+AE102-346937 -> 263261 | AF105: =+AF102-541883 -> 355473 | AG105: 451099 | AH105: 497245 | AI105: 621165
B106: Commercial expenses | K106: =+K103-112927 -> 123189 | L106: =+L103-114160 -> 117652 | M106: =M103-135101 -> 115455 | N106: =AH106-SUM(K106:M106) -> 125916 | O106: 120876 | P106: 125282 | Q106: =+Q103-189997 -> 127178 | R106: =AI106-SUM(O106:Q106) -> 151058 | S106: 155747 | T106: 163138 | U106: 188039 | AC106: =+AC103-50422 -> 289856 | AD106: =+AD103-77575 -> 319459 | AE106: =+AE103-247320 -> 235155 | AF106: =+AF103-357546 -> 286987 | AG106: 419599 | AH106: 482212 | AI106: 524394
B107: Total expenses | C107: =SUM(C105:C106) -> 0 | D107: =SUM(D105:D106) -> 0 | E107: =SUM(E105:E106) -> 0 | F107: =SUM(F105:F106) -> 0 | G107: =SUM(G105:G106) -> 0 | H107: =SUM(H105:H106) -> 0 | I107: =SUM(I105:I106) -> 0 | J107: =SUM(J105:J106) -> 0 | ... Z107: =SUM(Z105:Z106) -> 0 | AC107: =SUM(AC105:AC106) -> 514024 | AD107: =SUM(AD105:AD106) -> 585374 | AE107: =SUM(AE105:AE106) -> 498416 | AF107: =SUM(AF105:AF106) -> 642460 | AG107: =SUM(AG105:AG106) -> 870698 | AH107: =SUM(AH105:AH106) -> 979457 | AI107: =SUM(AI105:AI106) -> 1145559 | AJ107: =SUM(AJ105:AJ106) -> 0 | ... AL107: =SUM(AL105:AL106) -> 0
B109: Gov. Margin | C109: =(C102-C105)/C102 -> #DIV/0! | D109: =(D102-D105)/D102 -> #DIV/0! | E109: =(E102-E105)/E102 -> #DIV/0! | F109: =(F102-F105)/F102 -> #DIV/0! | G109: =(G102-G105)/G102 -> #DIV/0! | H109: =(H102-H105)/H102 -> #DIV/0! | I109: =(I102-I105)/I102 -> #DIV/0! | J109: =(J102-J105)/J102 -> #DIV/0! | ... Z109: =(Z102-Z105)/Z102 -> #DIV/0! | AC109: =(AC102-AC105)/AC102 -> 0.12136118 | AD109: =(AD102-AD105)/AD102 -> 0.2303941 | AE109: =(AE102-AE105)/AE102 -> 0.56856463 | AF109: =(AF102-AF105)/AF102 -> 0.60386625 | AG109: =(AG102-AG105)/AG102 -> 0.57911075 | AH109: =(AH102-AH105)/AH102 -> 0.59316078 | AI109: =(AI102-AI105)/AI102 -> 0.60425394 | AJ109: =(AJ102-AJ105)/AJ102 -> #DIV/0! | ... AL109: =(AL102-AL105)/AL102 -> #DIV/0!
B110: Comm. Margin | C110: =(C103-C106)/C103 -> #DIV/0! | D110: =(D103-D106)/D103 -> #DIV/0! | E110: =(E103-E106)/E103 -> #DIV/0! | F110: =(F103-F106)/F103 -> #DIV/0! | G110: =(G103-G106)/G103 -> #DIV/0! | H110: =(H103-H106)/H103 -> #DIV/0! | I110: =(I103-I106)/I103 -> #DIV/0! | J110: =(J103-J106)/J103 -> #DIV/0! | ... Z110: =(Z103-Z106)/Z103 -> #DIV/0! | AC110: =(AC103-AC106)/AC103 -> 0.14817884 | AD110: =(AD103-AD106)/AD103 -> 0.19538629 | AE110: =(AE103-AE106)/AE103 -> 0.51260687 | AF110: =(AF103-AF106)/AF103 -> 0.55473653 | AG110: =(AG103-AG106)/AG103 -> 0.496941 | AH110: =(AH103-AH106)/AH103 -> 0.51913299 | AI110: =(AI103-AI106)/AI103 -> 0.5953444 | AJ110: =(AJ103-AJ106)/AJ103 -> #DIV/0! | ... AL110: =(AL103-AL106)/AL103 -> #DIV/0!
B112: Gov. Revenue Y/Y | G112: =G102/C102-1 -> #DIV/0! | H112: =H102/D102-1 -> #DIV/0! | I112: =I102/E102-1 -> #DIV/0! | J112: =J102/F102-1 -> #DIV/0! | K112: =K102/G102-1 -> #DIV/0! | L112: =L102/H102-1 -> #DIV/0! | M112: =M102/I102-1 -> #DIV/0! | N112: =N102/J102-1 -> #DIV/0! | ... Z112: =Z102/V102-1 -> #DIV/0! | AD112: =AD102/AC102-1 -> 0.35428858 | AE112: =AE102/AD102-1 -> 0.7660229 | AF112: =AF102/AE102-1 -> 0.47059807 | AG112: =AG102/AF102-1 -> 0.19437102 | AH112: =AH102/AG102-1 -> 0.14036422 | AI112: =AI102/AH102-1 -> 0.28422986 | AJ112: =AJ102/AF102-1 -> -1 | AK112: =AK102/AG102-1 -> -1 | AL112: =AL102/AH102-1 -> -1
B113: Comm. Revenue Y/Y | G113: =G103/C103-1 -> #DIV/0! | H113: =H103/D103-1 -> #DIV/0! | I113: =I103/E103-1 -> #DIV/0! | J113: =J103/F103-1 -> #DIV/0! | K113: =K103/G103-1 -> #DIV/0! | L113: =L103/H103-1 -> #DIV/0! | M113: =M103/I103-1 -> #DIV/0! | N113: =N103/J103-1 -> #DIV/0! | ... Z113: =Z103/V103-1 -> #DIV/0! | AD113: =AD103/AC103-1 -> 0.16679303 | AE113: =AE103/AD103-1 -> 0.21519819 | AF113: =AF103/AE103-1 -> 0.33588891 | AG113: =AG103/AF103-1 -> 0.29410752 | AH113: =AH103/AG103-1 -> 0.20225754 | AI113: =AI103/AH103-1 -> 0.29228747 | AJ113: =AJ103/AF103-1 -> -1 | AK113: =AK103/AG103-1 -> -1 | AL113: =AL103/AH103-1 -> -1
...
