Workbook

Sheet Main
I7: Price | J7: 33.74
I8: S/O | J8: =+Model!N21/1000000 -> 417.566
I9: MC | J9: =J7*J8 -> 14088.677
I10: C | J10: =(Model!N39+Model!N40)/1000000 -> 1691.045
I11: D | J11: =Model!N52/1000000 -> 2233.255
I13: EV | J13: =+J9+J11-J10 -> 14630.887
H14: EV/Last 4Q Sales | J14: =J13/((Model!N5+Model!M5+Model!L5+Model!K5)/1000000) -> 8.2216317
H15: EV/Last 4Q Adj. EBITDA | J15: =J13/((Model!G130+Model!F130+Model!E130+Model!D130)/1000000) -> 51.717522
H16: EV/Last 4Q FCF | J16: =J13/((Model!N123+Model!M123+Model!L123+Model!K123)/1000000) -> 41.223636

Sheet Model
C2: Q322 | D2: Q422 | E2: Q123 | F2: Q223 | G2: Q323 | H2: Q423 | I2: Q124 | J2: Q224 | K2: Q324 | L2: Q424 | M2: Q125 | N2: Q225 | O2: Q325 | P2: Q425 | Q2: Q126 | R2: Q226 | S2: Q326 | T2: Q426 | Y2: 2023 | Z2: 2024 | AA2: 2025
B3: Create Solutions | C3: 189178000 | D3: 197762000 | E3: 187369000 | F3: 193110000 | G3: 188900000 | H3: 289795000 | I3: 163670000 | J3: 150777000 | K3: 147369000 | L3: 152150000 | M3: 150378000 | N3: 153782000 | Y3: 859174000 | Z3: 613966000
B4: Grow Solutions | C4: 133703000 | D4: 253212000 | E4: 312992000 | F4: 340368000 | G4: 355310000 | H4: 319473000 | I4: 296710000 | J4: 298482000 | K4: 299148000 | L4: 304949000 | M4: 284622000 | N4: 287162000 | Y4: 1328143000 | Z4: 1199289000
B5: Total Revenue | C5: =SUM(C3:C4) -> 322881000 | D5: =SUM(D3:D4) -> 450974000 | E5: =SUM(E3:E4) -> 500361000 | F5: =SUM(F3:F4) -> 533478000 | G5: =SUM(G3:G4) -> 544210000 | H5: =SUM(H3:H4) -> 609268000 | I5: =SUM(I3:I4) -> 460380000 | J5: =SUM(J3:J4) -> 449259000 | ... T5: =SUM(T3:T4) -> 0 | Y5: =SUM(Y3:Y4) -> 2187317000 | Z5: =SUM(Z3:Z4) -> 1813255000 | AA5: =SUM(AA3:AA4) -> 0
B6: COGS | C6: 111903000 | D6: 139928000 | E6: 161964000 | F6: 158827000 | G6: 151349000 | H6: 261582000 | I6: 144387000 | J6: 108875000 | K6: 112054000 | L6: 115537000 | M6: 113957000 | N6: 114211000 | Y6: 733722000 | Z6: 480853000
B7: Gross Profit | C7: =C5-C6 -> 210978000 | D7: =D5-D6 -> 311046000 | E7: =E5-E6 -> 338397000 | F7: =F5-F6 -> 374651000 | G7: =G5-G6 -> 392861000 | H7: =H5-H6 -> 347686000 | I7: =I5-I6 -> 315993000 | J7: =J5-J6 -> 340384000 | ... T7: =T5-T6 -> 0 | Y7: =Y5-Y6 -> 1453595000 | Z7: =Z5-Z6 -> 1332402000 | AA7: =AA5-AA6 -> 0
B8: R&D | C8: 248380000 | D8: 274111000 | E8: 280480000 | F8: 267955000 | G8: 240003000 | H8: 265150000 | I8: 282728000 | J8: 208935000 | K8: 215197000 | L8: 217970000 | M8: 220625000 | N8: 214807000 | Y8: 1053588000 | Z8: 924830000
B9: S&M | C9: 109639000 | D9: 183470000 | E9: 216127000 | F9: 209131000 | G9: 194000000 | H9: 215367000 | I9: 230625000 | J9: 169854000 | K9: 176423000 | L9: 175747000 | M9: 162013000 | N9: 161513000 | Y9: 834625000 | Z9: 752649000
B10: G&A | C10: 92585000 | D10: 127225000 | E10: 96774000 | F10: 89017000 | G10: 86256000 | H10: 126129000 | I10: 177569000 | J10: 91015000 | K10: 69989000 | L10: 71499000 | M10: 66340000 | N10: 69165000 | Y10: 398176000 | Z10: 410072000
B11: OpEx | C11: =SUM(C8:C10) -> 450604000 | D11: =SUM(D8:D10) -> 584806000 | E11: =SUM(E8:E10) -> 593381000 | F11: =SUM(F8:F10) -> 566103000 | G11: =SUM(G8:G10) -> 520259000 | H11: =SUM(H8:H10) -> 606646000 | I11: =SUM(I8:I10) -> 690922000 | J11: =SUM(J8:J10) -> 469804000 | ... T11: =SUM(T8:T10) -> 0 | Y11: =SUM(Y8:Y10) -> 2286389000 | Z11: =SUM(Z8:Z10) -> 2087551000 | AA11: =SUM(AA8:AA10) -> 0
B12: OpInc | C12: =C7-C11 -> -239626000 | D12: =D7-D11 -> -273760000 | E12: =E7-E11 -> -254984000 | F12: =F7-F11 -> -191452000 | G12: =G7-G11 -> -127398000 | H12: =H7-H11 -> -258960000 | I12: =I7-I11 -> -374929000 | J12: =J7-J11 -> -129420000 | ... T12: =T7-T11 -> 0 | Y12: =Y7-Y11 -> -832794000 | Z12: =Z7-Z11 -> -755149000 | AA12: =AA7-AA11 -> 0
B13: IntExp | C13: -1135000 | D13: -4035000 | E13: -6129000 | F13: -6142000 | G13: -6154000 | H13: -6155000 | I13: -6035000 | J13: -5829000 | K13: -5839000 | L13: -5839000 | M13: -5891000 | N13: -6030000 | Y13: -24580000 | Z13: -23542000
B14: IntInc & Other | C14: 2208000 | D14: 7101000 | E14: 13615000 | F14: 9061000 | G14: 16013000 | H14: 20840000 | I14: 76643000 | J14: 10457000 | K14: 15350000 | L14: 9108000 | M14: 58111000 | N14: 19837000 | Y14: 59529000 | Z14: 111558000
B15: Pretax Income | C15: =C12+C13+C14 -> -238553000 | D15: =D12+D13+D14 -> -270694000 | E15: =E12+E13+E14 -> -247498000 | F15: =F12+F13+F14 -> -188533000 | G15: =G12+G13+G14 -> -117539000 | H15: =H12+H13+H14 -> -244275000 | I15: =I12+I13+I14 -> -304321000 | J15: =J12+J13+J14 -> -124792000 | ... T15: =T12+T13+T14 -> 0 | Y15: =Y12+Y13+Y14 -> -797845000 | Z15: =Z12+Z13+Z14 -> -667133000 | AA15: =AA12+AA13+AA14 -> 0
B16: Taxes | C16: 11468000 | D16: 17060000 | E16: 6205000 | F16: 4791000 | G16: 7771000 | H16: 9710000 | I16: -12843000 | J16: 946000 | K16: 6913000 | L16: 2138000 | M16: 2192000 | N16: 2420000 | Y16: 28477000 | Z16: -2846000
B17: Net Income | C17: =C15-C16 -> -250021000 | D17: =D15-D16 -> -287754000 | E17: =E15-E16 -> -253703000 | F17: =F15-F16 -> -193324000 | G17: =G15-G16 -> -125310000 | H17: =H15-H16 -> -253985000 | I17: =I15-I16 -> -291478000 | J17: =J15-J16 -> -125738000 | ... T17: =T15-T16 -> 0 | Y17: =Y15-Y16 -> -826322000 | Z17: =Z15-Z16 -> -664287000 | AA17: =AA15-AA16 -> 0
B18: Noncontrolling | C18: 0 | D18: -1296000 | E18: -672000 | F18: -1164000 | G18: -1239000 | H18: -1236000 | I18: -404000 | J18: -164000 | K18: 191000 | L18: 204000 | M18: -265000 | N18: 1433000 | Y18: -4311000 | Z18: -173000
B19: Adj. | C19: 0 | D19: 2870000 | E19: 0 | F19: 0 | G19: 0 | H19: 0 | I19: 0 | J19: 0 | K19: 0 | L19: 0 | M19: 0 | N19: 0 | Y19: 0 | Z19: 0
B20: Net Income attributable to Unity | C20: =+C17-C18-C19 -> -250021000 | D20: =+D17-D18-D19 -> -289328000 | E20: =+E17-E18-E19 -> -253031000 | F20: =+F17-F18-F19 -> -192160000 | G20: =+G17-G18-G19 -> -124071000 | H20: =+H17-H18-H19 -> -252749000 | I20: =+I17-I18-I19 -> -291074000 | J20: =+J17-J18-J19 -> -125574000 | ... T20: =+T17-T18-T19 -> 0 | Y20: =+Y17-Y18-Y19 -> -822011000 | Z20: =+Z17-Z18-Z19 -> -664114000 | AA20: =+AA17-AA18-AA19 -> 0
B21: Basic | C21: 299062000 | D21: 351264000 | E21: 375909000 | F21: 380355000 | G21: 383674000 | H21: 381788000 | I21: 387151000 | J21: 392537000 | K21: 398810000 | L21: 405172000 | M21: 411852000 | N21: 417566000 | Y21: 380457000 | Z21: 395951000
B22: Diluted | C22: 299062000 | D22: 351264000 | E22: 375909000 | F22: 380355000 | G22: 383674000 | H22: 381788000 | I22: 387151000 | J22: 392537000 | K22: 398810000 | L22: 405172000 | M22: 411852000 | N22: 417566000 | Y22: 380457000 | Z22: 395951000
B23: EPS Basic | C23: =C20/C21 -> -0.83601728 | D23: =D20/D21 -> -0.82367678 | E23: =E20/E21 -> -0.6731177 | F23: =F20/F21 -> -0.50521224 | G23: =G20/G21 -> -0.3233761 | H23: =H20/H21 -> -0.662014 | I23: =I20/I21 -> -0.75183585 | J23: =J20/J21 -> -0.3199036 | ... T23: =T20/T21 -> #DIV/0! | Y23: =Y20/Y21 -> -2.1605885 | Z23: =Z20/Z21 -> -1.6772631 | AA23: =AA20/AA21 -> #DIV/0!
B24: EPS Diluted | C24: =C20/C22 -> -0.83601728 | D24: =D20/D22 -> -0.82367678 | E24: =E20/E22 -> -0.6731177 | F24: =F20/F22 -> -0.50521224 | G24: =G20/G22 -> -0.3233761 | H24: =H20/H22 -> -0.662014 | I24: =I20/I22 -> -0.75183585 | J24: =J20/J22 -> -0.3199036 | ... T24: =T20/T22 -> #DIV/0! | Y24: =Y20/Y22 -> -2.1605885 | Z24: =Z20/Z22 -> -1.6772631 | AA24: =AA20/AA22 -> #DIV/0!
B27: Gross Margin | C27: =C7/C5 -> 0.6534234 | D27: =D7/D5 -> 0.68972047 | E27: =E7/E5 -> 0.67630571 | F27: =F7/F5 -> 0.70228013 | G27: =G7/G5 -> 0.72189228 | H27: =H7/H5 -> 0.57066184 | I27: =I7/I5 -> 0.6863743 | J27: =J7/J5 -> 0.7576565 | ... T27: =T7/T5 -> #DIV/0! | Y27: =Y7/Y5 -> 0.66455617 | Z27: =Z7/Z5 -> 0.73481226 | AA27: =AA7/AA5 -> #DIV/0!
B28: Op Margin | C28: =C12/C5 -> -0.74214958 | D28: =D12/D5 -> -0.60704165 | E28: =E12/E5 -> -0.50960007 | F28: =F12/F5 -> -0.35887516 | G28: =G12/G5 -> -0.23409713 | H28: =H12/H5 -> -0.42503463 | I28: =I12/I5 -> -0.81439029 | J28: =J12/J5 -> -0.28807436 | ... T28: =T12/T5 -> #DIV/0! | Y28: =Y12/Y5 -> -0.38073768 | Z28: =Z12/Z5 -> -0.41646045 | AA28: =AA12/AA5 -> #DIV/0!
B29: Tax Margin | C29: =C16/C15 -> -0.048073175 | D29: =D16/D15 -> -0.063023192 | E29: =E16/E15 -> -0.02507091 | F29: =F16/F15 -> -0.025411997 | G29: =G16/G15 -> -0.066114226 | H29: =H16/H15 -> -0.039750281 | I29: =I16/I15 -> 0.042202148 | J29: =J16/J15 -> -0.0075806141 | ... T29: =T16/T15 -> #DIV/0! | Y29: =Y16/Y15 -> -0.035692396 | Z29: =Z16/Z15 -> 0.0042660159 | AA29: =AA16/AA15 -> #DIV/0!
B30: Net Margin | C30: =C17/C5 -> -0.77434411 | D30: =D17/D5 -> -0.63807226 | E30: =E17/E5 -> -0.50703992 | F30: =F17/F5 -> -0.3623842 | G30: =G17/G5 -> -0.23026038 | H30: =H17/H5 -> -0.4168691 | I30: =I17/I5 -> -0.63312481 | J30: =J17/J5 -> -0.27987864 | ... T30: =T17/T5 -> #DIV/0! | Y30: =Y17/Y5 -> -0.3777788 | Z30: =Z17/Z5 -> -0.36635057 | AA30: =AA17/AA5 -> #DIV/0!
B32: Create YoY | G32: =G3/D3-1 -> -0.04481144 | H32: =H3/E3-1 -> 0.54665393 | I32: =I3/F3-1 -> -0.15245197 | J32: =J3/G3-1 -> -0.20181578 | K32: =K3/H3-1 -> -0.49147156 | L32: =L3/I3-1 -> -0.070385532 | M32: =M3/J3-1 -> -0.0026462922 | N32: =N3/K3-1 -> 0.043516615 | ... T32: =T3/Q3-1 -> #DIV/0! | Z32: =Z3/Y3-1 -> -0.2853997 | AA32: =AA3/Z3-1 -> -1
B33: Grow YoY | G33: =G4/D4-1 -> 0.40321154 | H33: =H4/E4-1 -> 0.0207066 | I33: =I4/F4-1 -> -0.12826705 | J33: =J4/G4-1 -> -0.15993921 | K33: =K4/H4-1 -> -0.0636204 | L33: =L4/I4-1 -> 0.027767854 | M33: =M4/J4-1 -> -0.046434961 | N33: =N4/K4-1 -> -0.040067124 | ... T33: =T4/Q4-1 -> #DIV/0! | Z33: =Z4/Y4-1 -> -0.097018167 | AA33: =AA4/Z4-1 -> -1
B34: Revenue YoY | G34: =G5/D5-1 -> 0.20674363 | H34: =H5/E5-1 -> 0.21765685 | I34: =I5/F5-1 -> -0.13702158 | J34: =J5/G5-1 -> -0.17447493 | K34: =K5/H5-1 -> -0.26712547 | L34: =L5/I5-1 -> -0.0071267214 | M34: =M5/J5-1 -> -0.03173893 | N34: =N5/K5-1 -> -0.012481048 | ... T34: =T5/Q5-1 -> #DIV/0! | Z34: =Z5/Y5-1 -> -0.17101408 | AA34: =AA5/Z5-1 -> -1
B38: Net Cash | C38: =C39+C40-C52 -> -20300000 | D38: =D39+D40-D52 -> -1120376000 | E38: =E39+E40-E52 -> -1114354000 | F38: =F39+F40-F52 -> -1068516000 | G38: =G39+G40-G52 -> -1203432000 | H38: =H39+H40-H52 -> -1121425000 | I38: =I39+I40-I52 -> -1056453000 | J38: =J39+J40-J52 -> -969288000 | ... T38: =T39+T40-T52 -> 0 | Y38: =Y39+Y40-Y52 -> -1121425000 | Z38: =Z39+Z40-Z52 -> -721250000 | AA38: =AA39+AA40-AA52 -> 0
B39: Cash | C39: 1239337000 | D39: 1485084000 | E39: 1593946000 | F39: 1640926000 | G39: 1507164000 | H39: 1590325000 | I39: 1179962000 | J39: 1267957000 | K39: 1405276000 | L39: 1517672000 | M39: 1541170000 | N39: 1691045000 | Y39: 1590325000 | Z39: 1517672000
B40: Short-term investments | C40: 446766000 | D40: 101711000 | E40: 0 | F40: 0 | G40: 0 | H40: 0 | I40: 0 | J40: 0 | K40: 0 | L40: 0 | M40: 0 | N40: 0 | Y40: 0 | Z40: 0
B41: A/R | C41: 316337000 | D41: 633775000 | E41: 612763000 | F41: 632032000 | G41: 604743000 | H41: 611723000 | I41: 621184000 | J41: 573220000 | K41: 576436000 | L41: 573884000 | M41: 552958000 | N41: 596560000 | Y41: 611723000 | Z41: 573884000
B42: Prepaids & Other | C42: 81960000 | D42: 144070000 | E42: 136653000 | F42: 121406000 | G42: 120758000 | H42: 122843000 | I42: 140092000 | J42: 142889000 | K42: 134656000 | L42: 133795000 | M42: 144514000 | N42: 120171000 | Y42: 122843000 | Z42: 133795000
B43: PP&A | C43: 112458000 | D43: 121863000 | E43: 129050000 | F43: 135387000 | G43: 140807000 | H43: 140887000 | I43: 122783000 | J43: 112080000 | K43: 108085000 | L43: 98819000 | M43: 89972000 | N43: 82426000 | Y43: 140887000 | Z43: 98819000
B44: Goodwill | C44: 1657863000 | D44: 3200955000 | E44: 3200955000 | F44: 3200955000 | G44: 3202116000 | H44: 3166304000 | I44: 3166304000 | J44: 3166304000 | K44: 3166304000 | L44: 3166304000 | M44: 3166304000 | N44: 3166304000 | Y44: 3166304000 | Z44: 3166304000
B45: Intangible assets | C45: 724926000 | D45: 1922234000 | E45: 1824313000 | F45: 1725438000 | G45: 1626392000 | H45: 1406745000 | I45: 1318787000 | J45: 1230716000 | K45: 1154699000 | L45: 1066235000 | M45: 980584000 | N45: 894367000 | Y45: 1406745000 | Z45: 1066235000
B46: Other assets | C46: 147514000 | D46: 224293000 | E46: 237053000 | F46: 230702000 | G46: 223703000 | H46: 204614000 | I46: 204151000 | J46: 190568000 | K46: 180399000 | L46: 180698000 | M46: 170453000 | N46: 165551000 | Y46: 204614000 | Z46: 180698000
B47: Total Assets | C47: =SUM(C39:C46) -> 4727161000 | D47: =SUM(D39:D46) -> 7833985000 | E47: =SUM(E39:E46) -> 7734733000 | F47: =SUM(F39:F46) -> 7686846000 | G47: =SUM(G39:G46) -> 7425683000 | H47: =SUM(H39:H46) -> 7243441000 | I47: =SUM(I39:I46) -> 6753263000 | J47: =SUM(J39:J46) -> 6683734000 | ... T47: =SUM(T39:T46) -> 0 | Y47: =SUM(Y39:Y46) -> 7243441000 | Z47: =SUM(Z39:Z46) -> 6737407000 | AA47: =SUM(AA39:AA46) -> 0
B48: A/P | C48: 14182000 | D48: 20221000 | E48: 28222000 | F48: 18580000 | G48: 22166000 | H48: 14517000 | I48: 18862000 | J48: 12693000 | K48: 15195000 | L48: 13948000 | M48: 16538000 | N48: 12248000 | Y48: 14517000 | Z48: 13948000
B49: Accrued expenses & other | C49: 221931000 | D49: 326339000 | E49: 321234000 | F49: 295524000 | G49: 305137000 | H49: 307704000 | I49: 302207000 | J49: 264469000 | K49: 289340000 | L49: 294951000 | M49: 273444000 | N49: 278850000 | Y49: 307704000 | Z49: 294951000
B50: Publisher payables | C50: 172646000 | D50: 445622000 | E50: 417866000 | F50: 445950000 | G50: 408259000 | H50: 385113000 | I50: 410671000 | J50: 388253000 | K50: 382552000 | L50: 394284000 | M50: 339129000 | N50: 372719000 | Y50: 385113000 | Z50: 394284000
B51: Deferred revenue | C51: 202984000 | D51: 218102000 | E51: 212925000 | F51: 215012000 | G51: 214788000 | H51: 186769000 | I51: 170435000 | J51: 176127000 | K51: 189810000 | L51: 186304000 | M51: 188490000 | N51: 219448000 | Y51: 186769000 | Z51: 186304000
B52: Long-term debt | C52: 1706403000 | D52: 2707171000 | E52: 2708300000 | F52: 2709442000 | G52: 2710596000 | H52: 2711750000 | I52: 2236415000 | J52: 2237245000 | K52: 2238083000 | L52: 2238922000 | M52: 2232143000 | N52: 2233255000 | Y52: 2711750000 | Z52: 2238922000
B53: Long-term deferred revenue | C53: 118170000 | D53: 103442000 | E53: 90407000 | F53: 78859000 | G53: 65323000 | H53: 6015000 | I53: 9080000 | J53: 10173000 | K53: 17257000 | L53: 16846000 | M53: 14710000 | N53: 15480000 | Y53: 6015000 | Z53: 16846000
B54: ONCL | C54: 88159000 | D54: 258959000 | E54: 264107000 | F54: 255604000 | G54: 234044000 | H54: 217195000 | I54: 190869000 | J54: 178198000 | K54: 167058000 | L54: 165004000 | M54: 154863000 | N54: 150349000 | Y54: 217195000 | Z54: 165004000
B55: Total liabilities | C55: =SUM(C48:C54) -> 2524475000 | D55: =SUM(D48:D54) -> 4079856000 | E55: =SUM(E48:E54) -> 4043061000 | F55: =SUM(F48:F54) -> 4018971000 | G55: =SUM(G48:G54) -> 3960313000 | H55: =SUM(H48:H54) -> 3829063000 | I55: =SUM(I48:I54) -> 3338539000 | J55: =SUM(J48:J54) -> 3267158000 | ... T55: =SUM(T48:T54) -> 0 | Y55: =SUM(Y48:Y54) -> 3829063000 | Z55: =SUM(Z48:Z54) -> 3310259000 | AA55: =SUM(AA48:AA54) -> 0
B56: Redeemable noncontrolling interests | C56: 0 | D56: 219563000 | E56: 225376000 | F56: 215749000 | G56: 216945000 | H56: 225797000 | I56: 224736000 | J56: 226056000 | K56: 236914000 | L56: 230627000 | M56: 234740000 | N56: 240697000 | Y56: 225797000 | Z56: 230627000
B57: Common stock | C57: 2000 | D57: 2000 | E57: 2000 | F57: 2000 | G57: 2000 | H57: 2000 | I57: 2000 | J57: 2000 | K57: 2000 | L57: 2000 | M57: 2000 | N57: 2000 | Y57: 2000 | Z57: 2000
B58: Additional paid-in capital | C58: 4179621000 | D58: 5779776000 | E58: 5962358000 | F58: 6149631000 | G58: 6071209000 | H58: 6259479000 | I58: 6554787000 | J58: 6682060000 | K58: 6799899000 | L58: 6936038000 | M58: 7008134000 | N58: 7116124000 | Y58: 6259479000 | Z58: 6936038000
B59: Accumulated other comprehensive loss | C59: -13576000 | D59: -1691000 | E59: 490000 | F59: -8543000 | G59: -9646000 | H59: -5009000 | I59: -7760000 | J59: -8898000 | K59: -2987000 | L59: -9425000 | M59: -8501000 | N59: -6349000 | Y59: -5009000 | Z59: -9425000
B60: Accumulated deficit | C60: -1963361000 | D60: -2249819000 | E60: -2502850000 | F60: -2695010000 | G60: -2819081000 | H60: -3071830000 | I60: -3362904000 | J60: -3488478000 | K60: -3613217000 | L60: -3735944000 | M60: -3813586000 | N60: -3922384000 | Y60: -3071830000 | Z60: -3735944000
B61: Total Unity Software Inc. stockholders' equity | C61: =SUM(C56:C60) -> 2202686000 | D61: =SUM(D56:D60) -> 3747831000 | E61: =SUM(E56:E60) -> 3685376000 | F61: =SUM(F56:F60) -> 3661829000 | G61: =SUM(G56:G60) -> 3459429000 | H61: =SUM(H56:H60) -> 3408439000 | I61: =SUM(I56:I60) -> 3408861000 | J61: =SUM(J56:J60) -> 3410742000 | ... T61: =SUM(T56:T60) -> 0 | Y61: =SUM(Y56:Y60) -> 3408439000 | Z61: =SUM(Z56:Z60) -> 3421298000 | AA61: =SUM(AA56:AA60) -> 0
B62: Noncontrolling interest | C62: 0 | D62: 6298000 | E62: 6296000 | F62: 6046000 | G62: 5941000 | H62: 5939000 | I62: 5863000 | J62: 5834000 | K62: 5949000 | L62: 5850000 | M62: 5849000 | N62: 5985000 | Y62: 5939000 | Z62: 5850000
B63: Total stockholders’ equity | C63: =SUM(C61:C62) -> 2202686000 | D63: =SUM(D61:D62) -> 3754129000 | E63: =SUM(E61:E62) -> 3691672000 | F63: =SUM(F61:F62) -> 3667875000 | G63: =SUM(G61:G62) -> 3465370000 | H63: =SUM(H61:H62) -> 3414378000 | I63: =SUM(I61:I62) -> 3414724000 | J63: =SUM(J61:J62) -> 3416576000 | ... T63: =SUM(T61:T62) -> 0 | Y63: =SUM(Y61:Y62) -> 3414378000 | Z63: =SUM(Z61:Z62) -> 3427148000 | AA63: =SUM(AA61:AA62) -> 0
B64: Total liabilities and stockholders’ equity | C64: =SUM(C63+C55) -> 4727161000 | D64: =SUM(D63+D55) -> 7833985000 | E64: =SUM(E63+E55) -> 7734733000 | F64: =SUM(F63+F55) -> 7686846000 | G64: =SUM(G63+G55) -> 7425683000 | H64: =SUM(H63+H55) -> 7243441000 | I64: =SUM(I63+I55) -> 6753263000 | J64: =SUM(J63+J55) -> 6683734000 | ... T64: =SUM(T63+T55) -> 0 | Y64: =SUM(Y63+Y55) -> 7243441000 | Z64: =SUM(Z63+Z55) -> 6737407000 | AA64: =SUM(AA63+AA55) -> 0
B67: Current Ratio | C67: =(C39+C40+C41+C42)/(C48+C49+C50+C51) -> 3.4073132 | D67: =(D39+D40+D41+D42)/(D48+D49+D50+D51) -> 2.3405696 | E67: =(E39+E40+E41+E42)/(E48+E49+E50+E51) -> 2.3905832 | F67: =(F39+F40+F41+F42)/(F48+F49+F50+F51) -> 2.4555917 | G67: =(G39+G40+G41+G42)/(G48+G49+G50+G51) -> 2.3493081 | H67: =(H39+H40+H41+H42)/(H48+H49+H50+H51) -> 2.6002496 | I67: =(I39+I40+I41+I42)/(I48+I49+I50+I51) -> 2.1517311 | J67: =(J39+J40+J41+J42)/(J48+J49+J50+J51) -> 2.3576554 | ... T67: =(T39+T40+T41+T42)/(T48+T49+T50+T51) -> #DIV/0! | Y67: =(Y39+Y40+Y41+Y42)/(Y48+Y49+Y50+Y51) -> 2.6002496 | Z67: =(Z39+Z40+Z41+Z42)/(Z48+Z49+Z50+Z51) -> 2.5018365 | AA67: =(AA39+AA40+AA41+AA42)/(AA48+AA49+AA50+AA51) -> #DIV/0!
B68: Quick Ratio | C68: =+(C39+C40)/(C48+C49+C50+C51) -> 2.7562277 | D68: =+(D39+D40)/(D48+D49+D50+D51) -> 1.5706425 | E68: =+(E39+E40)/(E48+E49+E50+E51) -> 1.6260657 | F68: =+(F39+F40)/(F48+F49+F50+F51) -> 1.6828871 | G68: =+(G39+G40)/(G48+G49+G50+G51) -> 1.5859041 | H68: =+(H39+H40)/(H48+H49+H50+H51) -> 1.7786821 | I68: =+(I39+I40)/(I48+I49+I50+I51) -> 1.3079081 | J68: =+(J39+J40)/(J48+J49+J50+J51) -> 1.5067067 | ... T68: =+(T39+T40)/(T48+T49+T50+T51) -> #DIV/0! | Y68: =+(Y39+Y40)/(Y48+Y49+Y50+Y51) -> 1.7786821 | Z68: =+(Z39+Z40)/(Z48+Z49+Z50+Z51) -> 1.7062329 | AA68: =+(AA39+AA40)/(AA48+AA49+AA50+AA51) -> #DIV/0!
B69: Debt-To-Equity | C69: =C55/C63 -> 1.1460894 | D69: =D55/D63 -> 1.086765 | E69: =E55/E63 -> 1.0951842 | F69: =F55/F63 -> 1.0957219 | G69: =G55/G63 -> 1.1428254 | H69: =H55/H63 -> 1.1214526 | I69: =I55/I63 -> 0.97768927 | J69: =J55/J63 -> 0.95626674 | ... T69: =T55/T63 -> #DIV/0! | Y69: =Y55/Y63 -> 1.1214526 | Z69: =Z55/Z63 -> 0.96589321 | AA69: =AA55/AA63 -> #DIV/0!
B70: Hard Asset Ratio | C70: =(C43+C44+C45+C46)/C47 -> 0.55905881 | D70: =(D43+D44+D45+D46)/D47 -> 0.69815617 | E70: =(E43+E44+E45+E46)/E47 -> 0.69703389 | F70: =(F43+F44+F45+F46)/F47 -> 0.68851152 | G70: =(G43+G44+G45+G46)/G47 -> 0.69933203 | H70: =(H43+H44+H45+H46)/H47 -> 0.67903501 | I70: =(I43+I44+I45+I46)/I47 -> 0.71254814 | J70: =(J43+J44+J45+J46)/J47 -> 0.70315007 | ... T70: =(T43+T44+T45+T46)/T47 -> #DIV/0! | Y70: =(Y43+Y44+Y45+Y46)/Y47 -> 0.67903501 | Z70: =(Z43+Z44+Z45+Z46)/Z47 -> 0.66970216 | AA70: =(AA43+AA44+AA45+AA46)/AA47 -> #DIV/0!
B74: Model NI | C74: =C20 -> -250021000 | D74: =D20 -> -289328000 | E74: =E20 -> -253031000 | F74: =F20 -> -192160000 | G74: =G20 -> -124071000 | H74: =H20 -> -252749000 | I74: =I20 -> -291074000 | J74: =J20 -> -125574000 | ... T74: =T20 -> 0 | Y74: =Y20 -> -822011000 | Z74: =Z20 -> -664114000 | AA74: =AA20 -> 0
B75: GAAP NI | C75: -250021000 | D75: -287754000 | E75: -253703000 | F75: -193324000 | G75: -125310000 | H75: -253985000 | I75: -291478000 | J75: -125738000 | K75: -124548000 | L75: -122523000 | M75: -77907000 | N75: -107365000 | Y75: -826322000 | Z75: -664287000
B76: D&A | C76: 43490000 | D76: 83978000 | E76: 109560000 | F76: 111079000 | G76: 111023000 | H76: 232254000 | I76: 101810000 | J76: 101409000 | K76: 102600000 | L76: 103161000 | M76: 96217000 | N76: 96928000 | Y76: 563916000 | Z76: 408980000
B77: Stock-based compensation expense | C77: 154479000 | D77: 173917000 | E77: 163028000 | F77: 157534000 | G77: 147181000 | H77: 180953000 | I77: 265877000 | J77: 115399000 | K77: 104617000 | L77: 110356000 | M77: 98790000 | N77: 101604000 | Y77: 648696000 | Z77: 596249000
B78: Gain on repayment of convertible note | C78: 0 | D78: 0 | E78: 0 | F78: 0 | G78: 0 | H78: 0 | I78: -61371000 | J78: 0 | K78: 0 | L78: 0 | M78: -42744000 | N78: 0 | Y78: 0 | Z78: -61371000
B79: Impairment of property and equipment | C79: 0 | D79: 0 | E79: 0 | F79: 0 | G79: 0 | H79: 0 | I79: 13598000 | J79: 8320000 | K79: 956000 | L79: -83000 | M79: 3470000 | N79: 579000 | Y79: 0 | Z79: 22791000
B80: Other | C80: 3496000 | D80: 12032000 | E80: 379000 | F80: 1142000 | G80: 10036000 | H80: 13056000 | I80: 2918000 | J80: 12465000 | K80: -648000 | L80: 8574000 | M80: -218000 | N80: -7754000 | Y80: 24613000 | Z80: 23309000
B81: Accounts receivable, net | C81: 3385000 | D81: -30806000 | E81: 21013000 | F81: -19380000 | G81: 26713000 | H81: -6555000 | I81: -9740000 | J81: 47806000 | K81: -2603000 | L81: 1896000 | M81: 21022000 | N81: -43083000 | Y81: 21791000 | Z81: 37359000
B82: Prepaid expenses and other | C82: -474000 | D82: -13220000 | E82: 7589000 | F82: 15260000 | G82: -495000 | H82: -2040000 | I82: -16779000 | J82: -3036000 | K82: 7866000 | L82: 746000 | M82: -10602000 | N82: 24373000 | Y82: 20314000 | Z82: -11203000
B83: Other assets | C83: 8733000 | D83: 14198000 | E83: 11169000 | F83: 13142000 | G83: 9222000 | H83: 11514000 | I83: -2399000 | J83: 13000 | K83: 6753000 | L83: -7113000 | M83: 10023000 | N83: 1866000 | Y83: 45047000 | Z83: -2746000
B84: Accounts payable | C84: 1556000 | D84: -18548000 | E84: 7450000 | F84: -10519000 | G84: 3637000 | H84: -6881000 | I84: 5273000 | J84: -5733000 | K84: 550000 | L84: 652000 | M84: 2198000 | N84: -4297000 | Y84: -6313000 | Z84: 742000
B85: Accrued expenses and other | C85: 9825000 | D85: 5602000 | E85: -7305000 | F85: -26422000 | G85: 9706000 | H85: 2952000 | I85: -4269000 | J85: -36032000 | K85: 24934000 | L85: 8696000 | M85: -21029000 | N85: 7417000 | Y85: -21069000 | Z85: -6671000
B86: Publisher payables | C86: -24985000 | D86: 14749000 | E86: -27756000 | F86: 28084000 | G86: -37690000 | H86: -23147000 | I86: 25558000 | J86: -22418000 | K86: -5701000 | L86: 11731000 | M86: -55155000 | N86: 33590000 | Y86: -60509000 | Z86: 9170000
... B88: Deferred revenue | C88: -10273000 | D88: -925000 | E88: -18221000 | F88: -9453000 | G88: -12510000 | H88: -88035000 | I88: -12787000 | J88: 6973000 | K88: 19728000 | L88: -2720000 | M88: -120000 | N88: 31180000 | Y88: -128219000 | Z88: 11194000
B89: CFFO | C89: =SUM(C75:C88) -> -68800000 | D89: =SUM(D75:D88) -> -49061000 | E89: =SUM(E75:E88) -> -5099000 | F89: =SUM(F75:F88) -> 47643000 | G89: =SUM(G75:G88) -> 120053000 | H89: =SUM(H75:H88) -> 72103000 | I89: =SUM(I75:I88) -> -7373000 | J89: =SUM(J75:J88) -> 88376000 | ... T89: =SUM(T75:T88) -> 0 | Y89: =SUM(Y75:Y88) -> 234700000 | Z89: =SUM(Z75:Z88) -> 315553000 | AA89: =SUM(AA75:AA88) -> 0
B90: Purchases of short-term investments | C90: 0 | D90: 0 | E90: -212000 | F90: 0 | G90: 0 | H90: 0 | I90: 0 | J90: 0 | K90: 0 | L90: 0 | M90: 0 | N90: 0 | Y90: -212000 | Z90: 0
B91: Proceeds from sales of short-term investments | C91: 0 | D91: 436293000 | E91: 0 | F91: 0 | G91: 0 | H91: 0 | I91: 0 | J91: 0 | K91: 0 | L91: 0 | M91: 0 | N91: 0 | Y91: 0 | Z91: 0
B92: Proceeds from principal repayments and maturities of short-term investments | C92: 143310000 | D92: 12794000 | E92: 102673000 | F92: 0 | G92: 0 | H92: 0 | I92: 0 | J92: 0 | K92: 0 | L92: 0 | M92: 0 | N92: 0 | Y92: 102673000 | Z92: 0
B93: Purchases of short-term investments | C93: 0 | D93: 0 | E93: 0 | F93: -500000 | G93: -2000000 | H93: 0 | I93: 0 | J93: 0 | K93: 0 | L93: 0 | M93: 0 | N93: -2000000 | Y93: -2500000 | Z93: 0
B94: CapEx | C94: -11987000 | D94: -14794000 | E94: -14350000 | F94: -14118000 | G94: -16092000 | H94: -11361000 | I94: -7190000 | J94: -8766000 | K94: -7151000 | L94: -6442000 | M94: -5718000 | N94: -6446000 | Y94: -55921000 | Z94: -29549000
B95: Purchases of intangible assets | C95: 0 | D95: 0 | E95: 0 | F95: 0 | G95: 0 | H95: 0 | I95: 0 | J95: -360000 | K95: -12500000 | L95: 0 | M95: 0 | N95: 0 | Y95: 0 | Z95: -12860000
B96: Business acquisitions, net of cash acquired | C96: -193000 | D96: 147371000 | E96: 0 | F96: 0 | G96: 0 | H96: 0 | I96: 0 | J96: 0 | K96: 0 | L96: 0 | M96: 0 | N96: 0 | Y96: 0 | Z96: 0
B97: CFFI | C97: =SUM(C90:C96) -> 131130000 | D97: =SUM(D90:D96) -> 581664000 | E97: =SUM(E90:E96) -> 88111000 | F97: =SUM(F90:F96) -> -14618000 | G97: =SUM(G90:G96) -> -18092000 | H97: =SUM(H90:H96) -> -11361000 | I97: =SUM(I90:I96) -> -7190000 | J97: =SUM(J90:J96) -> -9126000 | ... T97: =SUM(T90:T96) -> 0 | Y97: =SUM(Y90:Y96) -> 44040000 | Z97: =SUM(Z90:Z96) -> -42409000 | AA97: =SUM(AA90:AA96) -> 0
B98: Proceeds from issuance of convertible notes | C98: 0 | D98: 1000000000 | E98: 0 | F98: 0 | G98: 0 | H98: 0 | I98: 0 | J98: 0 | K98: 0 | L98: 0 | M98: 690000000 | N98: 0 | Y98: 0 | Z98: 0
B99: Purchase of capped calls | C99: 0 | D99: 0 | E99: 0 | F99: 0 | G99: 0 | H99: 0 | I99: 0 | J99: 0 | K99: 0 | L99: 0 | M99: -44436000 | N99: 0 | Y99: 0 | Z99: 0
B100: Payment of debt issuance costs | C100: 0 | D100: -379000 | E100: 0 | F100: 0 | G100: 0 | H100: 0 | I100: 0 | J100: 0 | K100: 0 | L100: 0 | M100: -13236000 | N100: 0 | Y100: 0 | Z100: 0
B101: Capital contribution from noncontrolling interest holders | C101: 0 | D101: 210252000 | E101: 0 | F101: 0 | G101: 0 | H101: 0 | I101: 0 | J101: 0 | K101: 0 | L101: 0 | M101: 0 | N101: 0 | Y101: 0 | Z101: 0
B102: Repurchase and retirement of common stock | C102: 0 | D102: -1500000000 | E102: 0 | F102: 0 | G102: -250000000 | H102: 0 | I102: 0 | J102: 0 | K102: 0 | L102: 0 | M102: 0 | N102: 0 | Y102: -250000000 | Z102: 0
B103: Proceeds from issuance of common stock from employee equity plans | C103: 18766000 | D103: 7009000 | E103: 21971000 | F103: 19973000 | G103: 23050000 | H103: 10991000 | I103: 25998000 | J103: 11304000 | K103: 20000000 | L103: 19390000 | M103: 21611000 | N103: 9783000 | Y103: 75985000 | Z103: 76692000
B104: Repayments of convertible note | C104: 0 | D104: 0 | E104: 0 | F104: 0 | G104: 0 | H104: 0 | I104: -414999000 | J104: 0 | K104: 0 | L104: 0 | M104: -641691000 | N104: 0 | Y104: 0 | Z104: -414999000
B105: CFFF | C105: =SUM(C98:C104) -> 18766000 | D105: =SUM(D98:D104) -> -283118000 | E105: =SUM(E98:E104) -> 21971000 | F105: =SUM(F98:F104) -> 19973000 | G105: =SUM(G98:G104) -> -226950000 | H105: =SUM(H98:H104) -> 10991000 | I105: =SUM(I98:I104) -> -389001000 | J105: =SUM(J98:J104) -> 11304000 | ... T105: =SUM(T98:T104) -> 0 | Y105: =SUM(Y98:Y104) -> -174015000 | Z105: =SUM(Z98:Z104) -> -338307000 | AA105: =SUM(AA98:AA104) -> 0
B107: FX adj. | C107: -4144000 | D107: 6111000 | E107: 3151000 | F107: -11936000 | G107: -8871000 | H107: 11510000 | I107: -6202000 | J107: -3258000 | K107: 11464000 | L107: -13227000 | M107: 4197000 | N107: 15440000 | Y107: -6146000 | Z107: -11223000
B108: CF | C108: =C89+C97+C105+C107 -> 76952000 | D108: =D89+D97+D105+D107 -> 255596000 | E108: =E89+E97+E105+E107 -> 108134000 | F108: =F89+F97+F105+F107 -> 41062000 | G108: =G89+G97+G105+G107 -> -133860000 | H108: =H89+H97+H105+H107 -> 83243000 | I108: =I89+I97+I105+I107 -> -409766000 | J108: =J89+J97+J105+J107 -> 87296000 | ... T108: =T89+T97+T105+T107 -> 0 | Y108: =Y89+Y97+Y105+Y107 -> 98579000 | Z108: =Z89+Z97+Z105+Z107 -> -76386000 | AA108: =AA89+AA97+AA105+AA107 -> 0
B110: Cash BOP | C110: 1173140000 | D110: =+C111 -> 1250092000 | E110: =+D111 -> 1505688000 | F110: =+E111 -> 1613822000 | G110: =+F111 -> 1654884000 | H110: =+G111 -> 1521024000 | I110: =+H111 -> 1604267000 | J110: =+I111 -> 1194501000 | K110: =+J111 -> 1281797000 | ... T110: =+S111 -> 1701507000 | Y110: 1505688000 | Z110: =+Y111 -> 1604267000 | AA110: =+Z111 -> 1527881000
B111: Cash EOP | C111: =C108+C110 -> 1250092000 | D111: =D108+D110 -> 1505688000 | E111: =E108+E110 -> 1613822000 | F111: =F108+F110 -> 1654884000 | G111: =G108+G110 -> 1521024000 | H111: =H108+H110 -> 1604267000 | I111: =I108+I110 -> 1194501000 | J111: =J108+J110 -> 1281797000 | ... T111: =T108+T110 -> 1701507000 | Y111: =Y108+Y110 -> 1604267000 | Z111: =Z108+Z110 -> 1527881000 | AA111: =AA108+AA110 -> 1527881000
B113: Supplemental Disclosure of Cash Information:
B114: Cash paid for interest | C114: 0 | D114: 0 | E114: 0 | F114: 10389000 | G114: 0 | H114: 10000000 | I114: 0 | J114: 10000000 | K114: 0 | L114: 10000000 | M114: 0 | N114: 10000000 | Y114: 20389000 | Z114: 20000000
B115: Cash paid for income taxes, net of refunds | C115: 15927000 | D115: 3388000 | E115: 3751000 | F115: 1995000 | G115: 10123000 | H115: 6602000 | I115: 11041000 | J115: 5266000 | K115: 3034000 | L115: 7022000 | M115: -1736000 | N115: -1343000 | Y115: 22471000 | Z115: 26363000
B116: Cash paid for operating leases | C116: 6378000 | D116: 9432000 | E116: 10181000 | F116: 10025000 | G116: 11439000 | H116: 11260000 | I116: 13540000 | J116: 13118000 | K116: 12369000 | L116: 10947000 | M116: 10433000 | N116: 10482000 | Y116: 42905000 | Z116: 49974000
...
